Workbook

Sheet center-April
A1: Milk Chilling Centre(Ghado) - Monthly Camel Milk Procurement Report - 01-04-2024 TO 30-04-2024
A2: SR. NO. | B2: Farmer Code | C2: Farmer Name | D2: Total Quantity Supplied(Lits) | E2: Camel Milk Price/Lit(OMR) | F2: Total Value Milk (OMR) | G2: Paid | H2: balance | I2: ID No: | J2: Remarks
A3: 1 | B3: 1040 | C3: Ahmed Said Mahad Jamaan Dhishil al Kathiri | D3: 422.1 | E3: 0.4 | F3: =D3*E3 -> 168.84 | G3: =164.9+3.94 -> 168.84 | H3: =F3-G3 -> 0 | I3: 25082374 | J3: 11-08-2024-feeds
A4: 5 | B4: 1728 | C4: MUJEEB MUSALLAM SALIM ALKATINI ALRAWAS | D4: 500.9 | E4: 0.4 | F4: =D4*E4 -> 200.36 | G4: =198.85+1.51 -> 200.36 | H4: =F4-G4 -> 0 | I4: 8977778 | J4: 12-08-2024-feeds
D5: =SUM(D3:D4) -> 923 | F5: =SUM(F3:F4) -> 369.2 | G5: =SUM(G3:G4) -> 369.2 | H5: =SUM(H3:H4) -> 0
A11: Hassan Ghaly | F11: Sakku Mathew

Sheet 05-25
A1: Milk Chilling Centre(Ghado) - Monthly Camel Milk Procurement Report - 01-05-2024 TO 31-05-2024
A2: SR. NO. | B2: Farmer Code | C2: Farmer Name | D2: Total Quantity Supplied(Lits) | E2: Camel Milk Price/Lit(OMR) | F2: Total Value Milk (OMR) | G2: Paid | H2: Balance | I2: ID No: | J2: Account No | K2: Bank Name | L2: BANK SWIFT CODE | M2: Phone No: | N2: Remarks
A3: 1 | B3: 1106 | C3: Badar Said Masood Al Kathiri | D3: 1380 | E3: 0.4 | F3: =D3*E3 -> 552 | G3: =164.9+3.94+383.16 -> 552 | H3: =F3-G3 -> 0 | I3: 5502751 | J3: 10060192223001 | K3: NBO | L3: NBOMOMRX | M3: 99270001 | N3: 26-08-2024-feeds
A4: 4 | B4: 1333 | C4: Suhail Salim Ahmed Al Nubi Al Kathiri | D4: 839.1 | E4: 0.4 | F4: =D4*E4 -> 335.64 | G4: =334.65+0.99 -> 335.64 | H4: =F4-G4 -> 0 | I4: 1736679 | J4: 0401002496140031 | K4: Bank Muscat | L4: BMUSOMRX | M4: 99482212 | N4: 20-08-2024-feeds | O4: 45691
A5: 5 | B5: 1382 | C5: Suhail Mohammed Said Ghawas Al Kathiri | D5: 920 | E5: 0.4 | F5: =D5*E5 -> 368 | G5: =367.75+0.25 -> 368 | H5: =F5-G5 -> 0 | I5: 886492 | J5: 0397003786810019 | K5: Bank Muscat | L5: BMUSOMRX | M5: 99494166 | N5: 12-08-24-feeds | O5: 45600
A6: 6 | B6: 1384 | C6: Abdul Selam Musallam Mohammed Al Rawas | D6: 459 | E6: 0.4 | F6: =D6*E6 -> 183.6 | G6: =183.02+0.58 -> 183.6 | H6: =F6-G6 -> 0 | I6: 4426701 | J6: 0406003017570013 | K6: Bank Muscat | L6: BMUSOMRX | M6: 92634991 | N6: 11-08-2024-feeds | O6: 45658
A7: 7 | B7: 1386 | C7: Omar Salim Ahmed Al Hadi Ba Omar | D7: 924 | E7: 0.4 | F7: =D7*E7 -> 369.6 | G7: =368.6+1 -> 369.6 | H7: =F7-G7 -> 0 | I7: 711799 | J7: 0406003202280013 | K7: Bank Muscat | L7: BMUSOMRX | M7: 92394924 | N7: 26-08-2024- feeds | O7: 45601
A8: 13 | B8: 1417 | C8: Said Bakhit said Al mashikhi | D8: 689.5 | E8: 0.4 | F8: =D8*E8 -> 275.8 | G8: =274.6+1.2 -> 275.8 | H8: =F8-G8 -> 0 | I8: 1252579 | J8: 0397003628950016 | K8: Bank Muscat | L8: BMUSOMRX | M8: 98520912 | N8: 19-08-2024-fceeds | O8: 45635
A9: 14 | B9: 1435 | C9: Salim Said aoubad Ghawas | D9: 1376.5 | E9: 0.4 | F9: =D9*E9 -> 550.6 | G9: =548.8+1.8 -> 550.6 | H9: =F9-G9 -> 0 | I9: 1305522 | J9: 0397003064100017 | K9: Bank Muscat | L9: BMUSOMRX | M9: 93246263 | N9: 13-08-2024-feeds | O9: 45601
A10: 17 | B10: 1462 | C10: Mohammed Suhail Mohammed Ghawas | D10: 460 | E10: 0.4 | F10: =D10*E10 -> 184 | G10: =181.45+2.55 -> 184 | H10: =F10-G10 -> 0 | I10: 9664038 | J10: 132247650084010 | K10: Bank Muscat | L10: BMUSOMRX | M10: 92989674 | N10: 12-08-2024-feeds | O10: 45601
A11: 18 | B11: 1463 | C11: Said Salim Ali Aazad Al Kathiri | D11: 779.9 | E11: 0.4 | F11: =D11*E11 -> 311.96 | G11: =308.94+3.02 -> 311.96 | H11: =F11-G11 -> 0 | I11: 3798072 | J11: 01040280652001 | K11: Bank Dhofar | L11: BDOFOMRU | M11: 99480608 | N11: 19-08-2024-feeds | O11: 45623
A12: 20 | B12: 1711 | C12: MUSALLAM SALIM AHMED AL KATHIRI | D12: 714 | E12: 0.4 | F12: =D12*E12 -> 285.6 | G12: =281.3+4.3 -> 285.6 | H12: =F12-G12 -> 0 | I12: 638353 | J12: 0401059818360018 | K12: Bank Muscat | L12: BMUSOMRX | M12: 99292727 | N12: 20-08-2024-feeds | O12: 45691
A13: 21 | B13: 1712 | C13: SAID MAHAD JAMAAN DHISHLIL AL KATHIRI | D13: 434.6 | E13: 0.4 | F13: =D13*E13 -> 173.84 | G13: =72.75+97+4.09 -> 173.84 | H13: =F13-G13 -> 0 | I13: 788958 | J13: 0397003887980012 | K13: Bank Muscat | L13: BMUSOMRX | N13: 45635 | O13: 45609
A14: 22 | B14: 1714 | C14: Ghazi Omar Salim Al Hadi Ba Omar | D14: 458.9 | E14: 0.4 | F14: =D14*E14 -> 183.56 | G14: =179.45+4.11 -> 183.56 | H14: =F14-G14 -> 0 | I14: 6285703 | J14: 0406003231910018 | K14: Bank Muscat | L14: BMUSOMRX | N14: 27-08-2024-feeds | O14: 45573
A15: 23 | B15: 1715 | C15: AHMED AWADH MASOUD KIKAB AL SHIHRI | D15: 449.6 | E15: 0.4 | F15: =D15*E15 -> 179.84 | G15: =177.1+2.74 -> 179.84 | H15: =F15-G15 -> 0 | I15: 6511663 | J15: 0439014008250027 | K15: Bank Muscat | L15: BMUSOMRX | N15: 21-08-2024-feeds | O15: 45630
A16: 24 | B16: 1723 | C16: SALIM Azad Ali Bait Said | D16: 529 | E16: 0.4 | F16: =D16*E16 -> 211.6 | G16: =207.2+4.4 -> 211.6 | H16: =F16-G16 -> 0 | I16: 6631224 | J16: 0406003245850018 | K16: Bank Muscat | L16: BMUSOMRX | M16: 92666839 | N16: 13-08-2024-feeds | O16: 45602
A17: 25 | B17: 1724 | C17: SAID SALIM MOHAMMED GHAWAS BAIT KATHIR | D17: 460 | E17: 0.4 | F17: =D17*E17 -> 184 | G17: =181.45+2.55 -> 184 | H17: =F17-G17 -> 0 | I17: 10795143 | J17: 1083705599017 | K17: NBO | L17: NBOMOMRX | M17: 99494166 | N17: 12-08-2024-feeds | O17: 45601
A18: 29 | B18: 1755 | C18: ABDULLAH ABDUL SALLAM ABDULLAH AL RAWAS | D18: 908.4 | E18: 0.4 | F18: =D18*E18 -> 363.36 | G18: =362.5+0.86 -> 363.36 | H18: =F18-G18 -> 0 | I18: 10592143 | J18: 3109139871500 | K18: Oman Arab Bank | L18: OMABOMRU | N18: 16-09-2024 | O18: 45614
A19: 30 | B19: 1758 | C19: AHMED SUHAIL HARIZ ALDAKRI ALKATHIRI | D19: 842.8 | E19: 0.4 | F19: =D19*E19 -> 337.12 | G19: =169.75+164.9+2.47 -> 337.12 | H19: =F19-G19 -> 0 | I19: 2443662 | J19: 0396003234530018 | K19: Bank Muscat | L19: BMUSOMRX | M19: 99608818 | N19: 9/5/2024, 16-09
A20: 35 | B20: 1787 | C20: SALIM MAHAD FAEL BAIT SAID | D20: 460 | E20: 0.4 | F20: =D20*E20 -> 184 | G20: =181.55+2.45 -> 184 | H20: =F20-G20 -> 0 | I20: 22980157 | J20: 0401051479010017 | K20: Bank Muscat | L20: BMUSOMRX | M20: 91490491 | N20: 18-08-2024-feeds
A21: 36 | B21: 1791 | C21: KHALID SALIM AHMED JUMAA AL KATHIRI | D21: 460 | E21: 0.4 | F21: =D21*E21 -> 184 | G21: =177.32+6.68 -> 184 | H21: =F21-G21 -> 0 | I21: 5335073 | J21: 0406003449250017 | K21: Bank Muscat | L21: BMUSOMRX | M21: 99806280 | N21: 18-08-2024-feeds
A22: 37 | B22: 1794 | C22: Said Mohammed Ahmed Bait Said | D22: 498.2 | E22: 0.4 | F22: =D22*E22 -> 199.28 | G22: =199+0.28 -> 199.28 | H22: =F22-G22 -> 0 | I22: 6122928 | J22: 0397003656600012 | K22: Bank Muscat | L22: BMUSOMRX | N22: 19-08-2024-feeds | O22: 45602
A23: 38 | B23: 1798 | C23: BAKHIT SALIM ALI AZAD AL KATHIRI | D23: 474.8 | E23: 0.4 | F23: =D23*E23 -> 189.92 | G23: =189.15+0.77 -> 189.92 | H23: =F23-G23 -> 0 | I23: 5314229 | J23: 01010855197001 | K23: Bank Dhofar | L23: BDOFOMRU | N23: 16-09-2024 | O23: 45623
A24: 39 | B24: 1808 | C24: SALIM ALI NASIB KIKAB AL SHAHRI | D24: 421 | E24: 0.4 | F24: =D24*E24 -> 168.4 | G24: =168.15+0.25 -> 168.4 | H24: =F24-G24 -> 0 | I24: 611136 | J24: 1083545856017 | K24: NBO | L24: NBOMOMRX | N24: 11-08-2024-feeds | O24: 45651
A25: 43 | B25: 1826 | C25: SALIM ALI AHMED SHDAR ALKATHIRI | D25: 454.5 | E25: 0.4 | F25: =D25*E25 -> 181.8 | G25: =F25 -> 181.8 | H25: =F25-G25 -> 0 | I25: 381215 | J25: 0406003301170017 | K25: BANK MUSCAT | L25: BMUSOMRX | M25: 95110746 | O25: 2.5 BT
A26: 45 | B26: 3763 | C26: GHANEM AHMED SALIM BAIT SAID | D26: 447.6 | E26: 0.4 | F26: =D26*E26 -> 179.04 | G26: =178.26+0.78 -> 179.04 | H26: =F26-G26 -> 0 | I26: 19189247 | J26: 0396003245930018 | K26: Bank Muscat | L26: BMUSOMRX | M26: 99846685 | N26: 13-08-2024-feeds
D27: =SUM(D3:D26) -> 15841.4 | F27: =SUM(F3:F26) -> 6336.56 | G27: =SUM(G3:G26) -> 6336.56 | H27: =SUM(H3:H26) -> 0
H31: =H27-118.06 -> -118.06
G32: =G27/F27 -> 1

Sheet center-06-24
A1: Milk Chilling Centre(Ghado) - Monthly Camel Milk Procurement Report - 01-06-2024 TO 30-06-2024
A2: SR. NO. | B2: Farmer Code | C2: Farmer Name | D2: Total Quantity Supplied(Lits) | E2: Camel Milk Price/Lit(OMR) | F2: Total Value Milk (OMR) | I2: ID No: | J2: Account No | K2: Bank Name | L2: BANK SWIFT CODE | M2: Phone No: | N2: Remarks | P2: Farmer Code | R2: Farmer Name | T2: ID No: | V2: Account No | X2: BANK SWIFT CODE
A3: 1 | B3: 1001 | C3: Abdul Hakim Musallam Salim Al Katini Al Rawas | D3: 268.9 | E3: 0.4 | F3: =D3*E3 -> 107.56 | G3: =F3 -> 107.56 | H3: =F3-G3 -> 0 | I3: 2130934 | J3: 0397020829680019 | K3: Bank Muscat | L3: BMUSOMRX | M3: 92911133 | N3: 45544 | O3: 1.06-Bt-19-12-24 | P3: 1001 | Q3: =P3=B3 -> TRUE | R3: Abdul Hakim Musallam Salim Al Katini Al Rawas | S3: =R3=C3 -> TRUE | T3: 2130934 | U3: =T3=I3 -> TRUE | V3: 0397020829680019 | W3: =V3=J3 -> TRUE | X3: BMUSOMRX | Y3: =X3=L3 -> TRUE
A4: 14 | B4: 1122 | C4: Hamed Hilal Said Al Kathiri | D4: 263.8 | E4: 0.4 | F4: =D4*E4 -> 105.52 | G4: =105.1+0.42 -> 105.52 | H4: =F4-G4 -> 0 | I4: 5219876 | J4: 0406045268200015 | K4: Bank Muscat | L4: BMUSOMRX | M4: 99066779 | N4: 23-09-2024 | O4: 45621 | P4: 1122 | Q4: =P4=B4 -> TRUE | R4: Hamed Hilal Said Al Kathiri | S4: =R4=C4 -> TRUE | T4: 5219876 | U4: =T4=I4 -> TRUE | V4: 0406045268200015 | W4: =V4=J4 -> TRUE | X4: BMUSOMRX | Y4: =X4=L4 -> TRUE
A5: 15 | B5: 1135 | C5: Khalid Said Ali Al Kathiri | D5: 591.7 | E5: 0.4 | F5: =D5*E5 -> 236.68 | G5: =235.75+0.93 -> 236.68 | H5: =F5-G5 -> 0 | I5: 19202954 | J5: 01013808698001 | K5: Bank Dhofar | L5: BDOFOMRU | M5: 92771786 | N5: 23-09-2024 | O5: 45601 | P5: 1135 | Q5: =P5=B5 -> TRUE | R5: Khalid Said Ali Al Kathiri | S5: =R5=C5 -> TRUE | T5: 19202954 | U5: =T5=I5 -> TRUE | V5: 01013808698001 | W5: =V5=J5 -> TRUE | X5: BDOFOMRU | Y5: =X5=L5 -> TRUE
A6: 26 | B6: 1247 | C6: Said Salim Azad Bait Ali Badar | D6: 528 | E6: 0.4 | F6: =D6*E6 -> 211.2 | G6: =208.35+2.85 -> 211.2 | H6: =F6-G6 -> 0 | I6: 4748561 | J6: 01040280570002 | K6: Bank Dhofar | L6: BDOFOMRU | M6: 92345282 | N6: 23-09-2024 | O6: 45637 | P6: 1247 | Q6: =P6=B6 -> TRUE | R6: Said Salim Azad Bait Ali Badar | S6: =R6=C6 -> TRUE | T6: 4748561 | U6: =T6=I6 -> TRUE | V6: 01040280570002 | W6: =V6=J6 -> TRUE | X6: BDOFOMRU | Y6: =X6=L6 -> TRUE
A7: 28 | B7: 1258 | C7: Said Ali Musallam Al Noubi Al Kathiri | D7: 698.9 | E7: 0.4 | F7: =D7*E7 -> 279.56 | G7: =279.04+0.52 -> 279.56 | H7: =F7-G7 -> 0 | I7: 1924174 | J7: 01040280044001 | K7: Bank Dhofar | L7: BDOFOMRU | M7: 99297990 | N7: 23-09-2024 | O7: 45644 | P7: 1258 | Q7: =P7=B7 -> TRUE | R7: Said Ali Musallam Al Noubi Al Kathiri | S7: =R7=C7 -> TRUE | T7: 1924174 | U7: =T7=I7 -> TRUE | V7: 01040280044001 | W7: =V7=J7 -> TRUE | X7: BDOFOMRU | Y7: =X7=L7 -> TRUE
A8: 30 | B8: 1261 | C8: Said Ali Nasib Kikab Al shahri | D8: 347.9 | E8: 0.4 | F8: =D8*E8 -> 139.16 | G8: =138.09+1.07 -> 139.16 | H8: =F8-G8 -> 0 | I8: 14429332 | J8: 0439018203570018 | K8: Bank Muscat | L8: BMUSOMRX | M8: 92939445 | N8: 45588 | O8: 45607 | P8: 1261 | Q8: =P8=B8 -> TRUE | R8: Said Ali Nasib Kikab Al shahri | S8: =R8=C8 -> TRUE | T8: 14429332 | U8: =T8=I8 -> TRUE | V8: 0439018203570018 | W8: =V8=J8 -> TRUE | X8: BMUSOMRX | Y8: =X8=L8 -> TRUE
A9: 31 | B9: 1268 | C9: Said Musallam Ali Ghawas | D9: 440 | E9: 0.4 | F9: =D9*E9 -> 176 | G9: =174.58+1.42 -> 176 | H9: =F9-G9 -> 0 | I9: 722058 | J9: 0397003940070023 | K9: Bank Muscat | L9: BMUSOMRX | M9: 92848609 | N9: 45635 | O9: 45573 | P9: 1268 | Q9: =P9=B9 -> TRUE | R9: Said Musallam Ali Ghawas | S9: =R9=C9 -> TRUE | T9: 722058 | U9: =T9=I9 -> TRUE | V9: 0397003940070023 | W9: =V9=J9 -> TRUE | X9: BMUSOMRX | Y9: =X9=L9 -> TRUE
A10: 32 | B10: 1282 | C10: Salim Ali Musallam Al Noubi Al Kathiri | D10: 588.7 | E10: 0.4 | F10: =D10*E10 -> 235.48 | G10: =234.2+1.28 -> 235.48 | H10: =F10-G10 -> 0 | I10: 2997747 | J10: 3109601542500 | K10: Oman Arab Bank | L10: OMABOMRU | M10: 92660969 | N10: 16-09-24 | O10: BT | P10: 1282 | Q10: =P10=B10 -> TRUE | R10: Salim Ali Musallam Al Noubi Al Kathiri | S10: =R10=C10 -> TRUE | T10: 2997747 | U10: =T10=I10 -> TRUE | V10: 3109601542500 | W10: =V10=J10 -> TRUE | X10: OMABOMRU | Y10: =X10=L10 -> TRUE
A11: 33 | B11: 1284 | C11: Salim Ali Said Al Nubi Al Kathiri | D11: 572 | E11: 0.4 | F11: =D11*E11 -> 228.8 | G11: =227.95+0.85 -> 228.8 | H11: =F11-G11 -> 0 | I11: 1177598 | J11: 01040280595001 | K11: Bank Dhofar | L11: BDOFOMRU | M11: 92825228 | N11: 45635 | P11: 1284 | Q11: =P11=B11 -> TRUE | R11: Salim Ali Said Al Nubi Al Kathiri | S11: =R11=C11 -> TRUE | T11: 1177598 | U11: =T11=I11 -> TRUE | V11: 01040280595001 | W11: =V11=J11 -> TRUE | X11: BDOFOMRU | Y11: =X11=L11 -> TRUE
A12: 37 | B12: 1328 | C12: Suhail Saeed Suhail ghawas | D12: 390.9 | E12: 0.4 | F12: =D12*E12 -> 156.36 | G12: =152.75+3.61 -> 156.36 | H12: =F12-G12 -> 0 | I12: 782833 | J12: 01015382117001 | K12: Bank Dhofar | L12: BDOFOMRU | M12: 92475895 | N12: 45575 | O12: 45601 | P12: 1328 | Q12: =P12=B12 -> TRUE | R12: Suhail Saeed Suhail ghawas | S12: =R12=C12 -> TRUE | T12: 782833 | U12: =T12=I12 -> TRUE | V12: 01015382117001 | W12: =V12=J12 -> TRUE | X12: BDOFOMRU | Y12: =X12=L12 -> TRUE
A13: 38 | B13: 1330 | C13: Said Mahad Ali Al Kathiri | D13: 601.6 | E13: 0.4 | F13: =D13*E13 -> 240.64 | G13: =237.65+2.99 -> 240.64 | H13: =F13-G13 -> 0 | I13: 12194826 | J13: 00510129167001 | K13: Bank Nizwa | L13: BNZWOMRX | M13: 91299100 | N13: 45567 | O13: 45686 | P13: 1330 | Q13: =P13=B13 -> TRUE | R13: Said Mahad Ali Al Kathiri | S13: =R13=C13 -> TRUE | T13: 12194826 | U13: =T13=I13 -> TRUE | V13: 00510129167001 | W13: =V13=J13 -> TRUE | X13: BNZWOMRX | Y13: =X13=L13 -> TRUE
A14: 48 | B14: 1396 | C14: Mustahil Ali Azad Al Kathiri | D14: 386.6 | E14: 0.4 | F14: =D14*E14 -> 154.64 | G14: =152.54+2.1 -> 154.64 | H14: =F14-G14 -> 0 | I14: 905845 | J14: 0397003647340016 | K14: Bank Muscat | L14: BMUSOMRX | M14: 99696204 | N14: 45567 | O14: 45628 | P14: 1396 | Q14: =P14=B14 -> TRUE | R14: Mustahil Ali Azad Al Kathiri | S14: =R14=C14 -> TRUE | T14: 905845 | U14: =T14=I14 -> TRUE | V14: 0397003647340016 | W14: =V14=J14 -> TRUE | X14: BMUSOMRX | Y14: =X14=L14 -> TRUE
A15: 49 | B15: 1397 | C15: Ahmed Musallam Amer Al Kathiri | D15: 327.2 | E15: 0.4 | F15: =D15*E15 -> 130.88 | G15: =128.65+2.23 -> 130.88 | H15: =F15-G15 -> 0 | I15: 1292885 | J15: 254001118001 | K15: HSBC | L15: BBMEOMRX | M15: 92307552 | N15: 16-09-2024 | O15: 45656 | P15: 1397 | Q15: =P15=B15 -> TRUE | R15: Ahmed Musallam Amer Al Kathiri | S15: =R15=C15 -> TRUE | T15: 1292885 | U15: =T15=I15 -> TRUE | V15: 254001118001 | W15: =V15=J15 -> TRUE | X15: BBMEOMRX | Y15: =X15=L15 -> TRUE
A16: 66 | B16: 1421 | C16: Malik Musallam Salim Masoud Al Rawas | D16: 638 | E16: 0.4 | F16: =D16*E16 -> 255.2 | G16: =252.8+2.4 -> 255.2 | H16: =F16-G16 -> 0 | I16: 15314262 | J16: 0397019441080011 | K16: Bank Muscat | L16: BMUSOMRX | M16: 90333361 | N16: 16-09-2024 | P16: 1421 | Q16: =P16=B16 -> TRUE | R16: Malik Musallam Salim Masoud Al Rawas | S16: =R16=C16 -> TRUE | T16: 15314262 | U16: =T16=I16 -> TRUE | V16: 0397019441080011 | W16: =V16=J16 -> TRUE | X16: BMUSOMRX | Y16: =X16=L16 -> TRUE
A17: 67 | B17: 1423 | C17: Ahmed Said Ali Azad Al Kathiri | D17: 593.2 | E17: 0.4 | F17: =D17*E17 -> 237.28 | G17: =232.8+4.48 -> 237.28 | H17: =F17-G17 -> 0 | I17: 5044397 | J17: 0397003645500016 | K17: Bank Muscat | L17: BMUSOMRX | M17: 99580550 | N17: 30-09-2024 | O17: 45677 | P17: 1423 | Q17: =P17=B17 -> TRUE | R17: Ahmed Said Ali Azad Al Kathiri | S17: =R17=C17 -> TRUE | T17: 5044397 | U17: =T17=I17 -> TRUE | V17: 0397003645500016 | W17: =V17=J17 -> TRUE | X17: BMUSOMRX | Y17: =X17=L17 -> TRUE
A18: 70 | B18: 1427 | C18: Salim Said Mohammed Musallam Al Nubi Al kathiri | D18: 305.1 | E18: 0.4 | F18: =D18*E18 -> 122.04 | G18: =118.99+3.05 -> 122.04 | H18: =F18-G18 -> 0 | I18: 24171637 | J18: 0439025022760016 | K18: Bank Muscat | L18: BMUSOMRX | M18: 97030409 | N18: 45635 | O18: 45665 | P18: 1427 | Q18: =P18=B18 -> TRUE | R18: Salim Said Mohammed Musallam Al Nubi Al kathiri | S18: =R18=C18 -> TRUE | T18: 24171637 | U18: =T18=I18 -> TRUE | V18: 0439025022760016 | W18: =V18=J18 -> TRUE | X18: BMUSOMRX | Y18: =X18=L18 -> TRUE
A19: 72 | B19: 1430 | C19: Ahmed Said Mohammed Houmdi Al Siari | D19: 308 | E19: 0.4 | F19: =D19*E19 -> 123.2 | G19: =122.04+1.16 -> 123.2 | H19: =F19-G19 -> 0 | I19: 564698 | J19: 0406003186630017 | K19: Bank Muscat | L19: BMUSOMRX | M19: 99189793 | N19: 23-09-2024 | O19: 45600 | P19: 1430 | Q19: =P19=B19 -> TRUE | R19: Ahmed Said Mohammed Houmdi Al Siari | S19: =R19=C19 -> TRUE | T19: 564698 | U19: =T19=I19 -> TRUE | V19: 0406003186630017 | W19: =V19=J19 -> TRUE | X19: BMUSOMRX | Y19: =X19=L19 -> TRUE
A20: 75 | B20: 1434 | C20: Muhssin Said Mohammed Ghawas | D20: 336.1 | E20: 0.4 | F20: =D20*E20 -> 134.44 | G20: =131.06+3.38 -> 134.44 | H20: =F20-G20 -> 0 | I20: 19197503 | J20: 0403015046590039 | K20: Bank Muscat | L20: BMUSOMRX | M20: 92466605 | N20: 18-09-2024 | O20: 45614 | P20: 1434 | Q20: =P20=B20 -> TRUE | R20: Muhssin Said Mohammed Ghawas | S20: =R20=C20 -> TRUE | T20: 19197503 | U20: =T20=I20 -> TRUE | V20: 0403015046590039 | W20: =V20=J20 -> TRUE | X20: BMUSOMRX | Y20: =X20=L20 -> TRUE
A21: 76 | B21: 1435 | C21: Salim Said aoubad Ghawas | D21: 968 | E21: 0.4 | F21: =D21*E21 -> 387.2 | G21: =383.15+4.05 -> 387.2 | H21: =F21-G21 -> 0 | I21: 1305522 | J21: 0397003064100017 | K21: Bank Muscat | L21: BMUSOMRX | M21: 93246263 | N21: 25-09-2024 | O21: 05/11/241 | P21: 1435 | Q21: =P21=B21 -> TRUE | R21: Salim Said aoubad Ghawas | S21: =R21=C21 -> TRUE | T21: 1305522 | U21: =T21=I21 -> TRUE | V21: 0397003064100017 | W21: =V21=J21 -> TRUE | X21: BMUSOMRX | Y21: =X21=L21 -> TRUE
A22: 77 | B22: 1437 | C22: Ahmed Ali Ahmed Shadar Al Kathiri | D22: 638 | E22: 0.4 | F22: =D22*E22 -> 255.2 | G22: =254.5+0.7 -> 255.2 | H22: =F22-G22 -> 0 | I22: 9685144 | J22: 250056066001 | K22: HSBC | L22: BBMEOMRX | M22: 96907302 | N22: 45544 | O22: 45614 | P22: 1437 | Q22: =P22=B22 -> TRUE | R22: Ahmed Ali Ahmed Shadar Al Kathiri | S22: =R22=C22 -> TRUE | T22: 9685144 | U22: =T22=I22 -> TRUE | V22: 250056066001 | W22: =V22=J22 -> TRUE | X22: BBMEOMRX | Y22: =X22=L22 -> TRUE
A23: 78 | B23: 1438 | C23: Salim Aubad Al Maslamin Al Mashali | D23: 968 | E23: 0.4 | F23: =D23*E23 -> 387.2 | G23: =383.15+4.05 -> 387.2 | H23: =F23-G23 -> 0 | I23: 656621 | J23: 1023386437017 | K23: NBO | L23: NBOMOMRX | M23: 92509804 | N23: 45581 | O23: 45637 | P23: 1438 | Q23: =P23=B23 -> TRUE | R23: Salim Aubad Al Maslamin Al Mashali | S23: =R23=C23 -> TRUE | T23: 656621 | U23: =T23=I23 -> TRUE | V23: 1023386437017 | W23: =V23=J23 -> TRUE | X23: NBOMOMRX | Y23: =X23=L23 -> TRUE
A24: 82 | B24: 1448 | C24: Salim Said Masoud Said Al Kathiri | D24: 270.7 | E24: 0.4 | F24: =D24*E24 -> 108.28 | G24: =107.86+0.42 -> 108.28 | H24: =F24-G24 -> 0 | I24: 26433121 | J24: 0397060499480017 | K24: Bank Muscat | L24: BMUSOMRX | M24: 93229244 | N24: 45635 | O24: 45656 | P24: 1448 | Q24: =P24=B24 -> TRUE | R24: Salim Said Masoud Said Al Kathiri | S24: =R24=C24 -> TRUE | T24: 26433121 | U24: =T24=I24 -> TRUE | V24: 0397060499480017 | W24: =V24=J24 -> TRUE | X24: BMUSOMRX | Y24: =X24=L24 -> TRUE
A25: 90 | B25: 1468 | C25: Ahmed Salim Ahmed Al Kathiri | D25: 655.7 | E25: 0.4 | F25: =D25*E25 -> 262.28 | G25: =258.14+4.14 -> 262.28 | H25: =F25-G25 -> 0 | I25: 6996485 | J25: 0439016595760027 | K25: Bank Muscat | L25: BMUSOMRX | M25: 92947741 | N25: 30-09-2024 | O25: 45642 | P25: 1468 | Q25: =P25=B25 -> TRUE | R25: Ahmed Salim Ahmed Al Kathiri | S25: =R25=C25 -> TRUE | T25: 6996485 | U25: =T25=I25 -> TRUE | V25: 0439016595760027 | W25: =V25=J25 -> TRUE | X25: BMUSOMRX | Y25: =X25=L25 -> TRUE
A26: 93 | B26: 1475 | C26: Musallam Said Ahmed Al kathiri | D26: 330.1 | E26: 0.4 | F26: =D26*E26 -> 132.04 | G26: =130.82+1.22 -> 132.04 | H26: =F26-G26 -> 0 | I26: 4584011 | J26: 0439061793370011 | K26: Bank Muscat | L26: BMUSOMRX | M26: 98822862 | N26: 30-09-2024 | O26: 45684 | P26: 1475 | Q26: =P26=B26 -> TRUE | R26: Musallam Said Ahmed Al kathiri | S26: =R26=C26 -> TRUE | T26: 4584011 | U26: =T26=I26 -> TRUE | V26: 0439061793370011 | W26: =V26=J26 -> TRUE | X26: BMUSOMRX | Y26: =X26=L26 -> TRUE
A27: 103 | B27: 1706 | C27: AIL MUSALLAM AMER AL KATHIRI | D27: 302.6 | E27: 0.4 | F27: =D27*E27 -> 121.04 | G27: =118.25+2.79 -> 121.04 | H27: =F27-G27 -> 0 | I27: 2520947 | J27: 250010035731 | K27: Bank Sohar | L27: BSHROMRU | M27: 92246641 | N27: 16-09-2024 | O27: 45573 | P27: 1706 | Q27: =P27=B27 -> TRUE | R27: AIL MUSALLAM AMER AL KATHIRI | S27: =R27=C27 -> TRUE | T27: 2520947 | U27: =T27=I27 -> TRUE | V27: 250010035731 | W27: =V27=J27 -> TRUE | X27: BSHROMRU | Y27: =X27=L27 -> TRUE
A28: 108 | B28: 1713 | C28: MOHAMMED SALIM ALI AL NOBI AL KATHIRI | D28: 352 | E28: 0.4 | F28: =D28*E28 -> 140.8 | G28: =138.7+2.1 -> 140.8 | H28: =F28-G28 -> 0 | I28: 19890467 | J28: 01010856539002 | K28: Bank Dhofar | L28: BDOFOMRU | N28: 45635 | P28: 1713 | Q28: =P28=B28 -> TRUE | R28: MOHAMMED SALIM ALI AL NOBI AL KATHIRI | S28: =R28=C28 -> TRUE | T28: 19890467 | U28: =T28=I28 -> TRUE | V28: 01010856539002 | W28: =V28=J28 -> TRUE | X28: BDOFOMRU | Y28: =X28=L28 -> TRUE
A29: 113 | B29: 1718 | C29: ADNAN SALIM ALI ALNOOB AL KATHIRI | D29: 330 | E29: 0.4 | F29: =D29*E29 -> 132 | G29: =F29 -> 132 | H29: =F29-G29 -> 0 | I29: 18656137 | J29: 250010162782 | K29: Bank Sohar | L29: BSHROMRU | N29: 16-09-2024 | O29: 2.5 bt | P29: 1718 | Q29: =P29=B29 -> TRUE | R29: ADNAN SALIM ALI ALNOOB AL KATHIRI | S29: =R29=C29 -> TRUE | T29: 18656137 | U29: =T29=I29 -> TRUE | V29: 250010162782 | W29: =V29=J29 -> TRUE | X29: BSHROMRU | Y29: =X29=L29 -> TRUE
A30: 122 | B30: 1730 | C30: Salim Mohsin Salim Saluma Baawain | D30: 385.5 | E30: 0.4 | F30: =D30*E30 -> 154.2 | G30: =152.97+1.23 -> 154.2 | H30: =F30-G30 -> 0 | I30: 18458405 | J30: 0396059029400018 | K30: Bank Muscat | L30: BMUSOMRX | M30: 98566660 | N30: 45635 | P30: 1730 | Q30: =P30=B30 -> TRUE | R30: Salim Mohsin Salim Saluma Baawain | S30: =R30=C30 -> TRUE | T30: 18458405 | U30: =T30=I30 -> TRUE | V30: 0396059029400018 | W30: =V30=J30 -> TRUE | X30: BMUSOMRX | Y30: =X30=L30 -> TRUE
A31: 126 | B31: 1736 | C31: HILAL SAID AZAD AL KATHIRI | D31: 282.4 | E31: 0.4 | F31: =D31*E31 -> 112.96 | G31: =112.13+0.83 -> 112.96 | H31: =F31-G31 -> 0 | I31: 960639 | J31: 0406003189710011 | K31: Bank Muscat | L31: BMUSOMRX | N31: 23-09-2024 | O31: 45621 | P31: 1736 | Q31: =P31=B31 -> TRUE | R31: HILAL SAID AZAD AL KATHIRI | S31: =R31=C31 -> TRUE | T31: 960639 | U31: =T31=I31 -> TRUE | V31: 0406003189710011 | W31: =V31=J31 -> TRUE | X31: BMUSOMRX | Y31: =X31=L31 -> TRUE
A32: 128 | B32: 1738 | C32: SALIM SUHAIL MAHAD ALI BAIT SAID | D32: 329.7 | E32: 0.4 | F32: =D32*E32 -> 131.88 | G32: =115.5+16.38 -> 131.88 | H32: =F32-G32 -> 0 | I32: 23187863 | J32: 0406042709700017 | K32: Bank Muscat | L32: BMUSOMRX | M32: 99464736 | N32: 45567 | O32: dcf-27-01-25 | P32: 1738 | Q32: =P32=B32 -> TRUE | R32: SALIM SUHAIL MAHAD ALI BAIT SAID | S32: =R32=C32 -> TRUE | T32: 23187863 | U32: =T32=I32 -> TRUE | V32: 0406042709700017 | W32: =V32=J32 -> TRUE | X32: BMUSOMRX | Y32: =X32=L32 -> TRUE
A33: 135 | B33: 1748 | C33: BAKHIT HAREEZ AHMED AL KATHAIRI | D33: 307.9 | E33: 0.4 | F33: =D33*E33 -> 123.16 | G33: =119.85+3.31 -> 123.16 | H33: =F33-G33 -> 0 | I33: 1354182 | J33: 0396003221340015 | K33: Bank Muscat | L33: BMUSOMRX | M33: 98953022 | N33: 45544 | O33: 45600 | P33: 1748 | Q33: =P33=B33 -> TRUE | R33: BAKHIT HAREEZ AHMED AL KATHAIRI | S33: =R33=C33 -> TRUE | T33: 1354182 | U33: =T33=I33 -> TRUE | V33: 0396003221340015 | W33: =V33=J33 -> TRUE | X33: BMUSOMRX | Y33: =X33=L33 -> TRUE
A34: 138 | B34: 1752 | C34: MOHAMMED SAID MOHAMMED GHAWAS | D34: 346.4 | E34: 0.4 | F34: =D34*E34 -> 138.56 | G34: =136.86+1.7 -> 138.56 | H34: =F34-G34 -> 0 | I34: 2808921 | J34: 0403015046590039 | K34: Bank Muscat | L34: BMUSOMRX | M34: 92740803 | N34: 18-09-2024 | O34: 45614 | P34: 1752 | Q34: =P34=B34 -> TRUE | R34: MOHAMMED SAID MOHAMMED GHAWAS | S34: =R34=C34 -> TRUE | T34: 2808921 | U34: =T34=I34 -> TRUE | V34: 0403015046590039 | W34: =V34=J34 -> TRUE | X34: BMUSOMRX | Y34: =X34=L34 -> TRUE
A35: 149 | B35: 1768 | C35: SALIM MUSTAHIL ALI AL KATHIRI | D35: 324.7 | E35: 0.4 | F35: =D35*E35 -> 129.88 | G35: =126.1+3.78 -> 129.88 | H35: =F35-G35 -> 0 | I35: 13899464 | J35: 0397003573860012 | K35: Bank Muscat | L35: BMUSOMRX | M35: 99166449 | N35: 30-09-2024 | P35: 1768 | Q35: =P35=B35 -> TRUE | R35: SALIM MUSTAHIL ALI AL KATHIRI | S35: =R35=C35 -> TRUE | T35: 13899464 | U35: =T35=I35 -> TRUE | V35: 0397003573860012 | W35: =V35=J35 -> TRUE | X35: BMUSOMRX | Y35: =X35=L35 -> TRUE
A36: 152 | B36: 1771 | C36: Abdullah Said Ali Azad Al Kathiri | D36: 330 | E36: 0.4 | F36: =D36*E36 -> 132 | G36: =130.95+1.05 -> 132 | H36: =F36-G36 -> 0 | I36: 5044401 | J36: 0397003645500016 | K36: Bank Muscat | L36: BMUSOMRX | M36: 93556616 | N36: 30-09-2024 | O36: 45635 | P36: 1771 | Q36: =P36=B36 -> TRUE | R36: Abdullah Said Ali Azad Al Kathiri | S36: =R36=C36 -> TRUE | T36: 5044401 | U36: =T36=I36 -> TRUE | V36: 0397003645500016 | W36: =V36=J36 -> TRUE | X36: BMUSOMRX | Y36: =X36=L36 -> TRUE
A37: 155 | B37: 1774 | C37: ADNAN MOHAMMED MOHISEEN HOUMDI AL SIARI | D37: 329.7 | E37: 0.4 | F37: =D37*E37 -> 131.88 | G37: =131.25+0.63 -> 131.88 | H37: =F37-G37 -> 0 | I37: 20865047 | J37: 0406051045750013 | K37: Bank Muscat | L37: BMUSOMRX | M37: 98825083 | N37: 45567 | O37: 45663 | P37: 1774 | Q37: =P37=B37 -> TRUE | R37: ADNAN MOHAMMED MOHISEEN HOUMDI AL SIARI | S37: =R37=C37 -> TRUE | T37: 20865047 | U37: =T37=I37 -> TRUE | V37: 0406051045750013 | W37: =V37=J37 -> TRUE | X37: BMUSOMRX | Y37: =X37=L37 -> TRUE
A38: 163 | B38: 1783 | C38: MUSALLAM HAREEZ AHMED ALDAKRI ALKATHIRI | D38: 272.5 | E38: 0.4 | F38: =D38*E38 -> 109 | G38: =106.38+2.62 -> 109 | H38: =F38-G38 -> 0 | I38: 1500187 | J38: 0396003224620019 | K38: Bank Muscat | L38: BMUSOMRX | M38: 91159122 | N38: 45544 | O38: 45600 | P38: 1783 | Q38: =P38=B38 -> TRUE | R38: MUSALLAM HAREEZ AHMED ALDAKRI ALKATHIRI | S38: =R38=C38 -> TRUE | T38: 1500187 | U38: =T38=I38 -> TRUE | V38: 0396003224620019 | W38: =V38=J38 -> TRUE | X38: BMUSOMRX | Y38: =X38=L38 -> TRUE
A39: 165 | B39: 1785 | C39: SUHAIL ALI ABDULLAH GHAWAS | D39: 326.1 | E39: 0.4 | F39: =D39*E39 -> 130.44 | G39: =126.4+4.04 -> 130.44 | H39: =F39-G39 -> 0 | I39: 7374743 | J39: 0406012723080017 | K39: Bank Muscat | L39: BMUSOMRX | M39: 93875087 | N39: 23-09-2024 | P39: 1785 | Q39: =P39=B39 -> TRUE | R39: SUHAIL ALI ABDULLAH GHAWAS | S39: =R39=C39 -> TRUE | T39: 7374743 | U39: =T39=I39 -> TRUE | V39: 0406012723080017 | W39: =V39=J39 -> TRUE | X39: BMUSOMRX | Y39: =X39=L39 -> TRUE
A40: 166 | B40: 1786 | C40: SUHAIL MOHAMMED ALI AL NUBI AL KATHIRI | D40: 314 | E40: 0.4 | F40: =D40*E40 -> 125.6 | G40: =121.25+4.35 -> 125.6 | H40: =F40-G40 -> 0 | I40: 5614637 | J40: 0406012235220015 | K40: Bank Muscat | L40: BMUSOMRX | M40: 92924645 | N40: 45567 | O40: 45686 | P40: 1786 | Q40: =P40=B40 -> TRUE | R40: SUHAIL MOHAMMED ALI AL NUBI AL KATHIRI | S40: =R40=C40 -> TRUE | T40: 5614637 | U40: =T40=I40 -> TRUE | V40: 0406012235220015 | W40: =V40=J40 -> TRUE | X40: BMUSOMRX | Y40: =X40=L40 -> TRUE
A41: 178 | B41: 1799 | C41: ALI HILAL SAID ALKATHIRI | D41: 308.3 | E41: 0.4 | F41: =D41*E41 -> 123.32 | G41: =121.01+2.31 -> 123.32 | H41: =F41-G41 -> 0 | I41: 5219843 | J41: 0439012451390028 | K41: Bank Muscat | L41: BMUSOMRX | N41: 23-09-2024 | O41: 45621 | P41: 1799 | Q41: =P41=B41 -> TRUE | R41: ALI HILAL SAID ALKATHIRI | S41: =R41=C41 -> TRUE | T41: 5219843 | U41: =T41=I41 -> TRUE | V41: 0439012451390028 | W41: =V41=J41 -> TRUE | X41: BMUSOMRX | Y41: =X41=L41 -> TRUE
A42: 179 | B42: 1800 | C42: ALI OMAR FARAJ AGHRIB AL SHAHRI | D42: 333 | E42: 0.4 | F42: =D42*E42 -> 133.2 | G42: =131.65+1.55 -> 133.2 | H42: =F42-G42 -> 0 | I42: 7293505 | J42: 0397016002320031 | K42: Bank Muscat | L42: BMUSOMRX | M42: 99189910 | P42: 1800 | Q42: =P42=B42 -> TRUE | R42: ALI OMAR FARAJ AGHRIB AL SHAHRI | S42: =R42=C42 -> TRUE | T42: 7293505 | U42: =T42=I42 -> TRUE | V42: 0397016002320031 | W42: =V42=J42 -> TRUE | X42: BMUSOMRX | Y42: =X42=L42 -> TRUE
A43: 180 | B43: 1801 | C43: HAMID MOHAMMED ZIDI BAIT SAID | D43: 352 | E43: 0.4 | F43: =D43*E43 -> 140.8 | G43: =139.3+1.5 -> 140.8 | H43: =F43-G43 -> 0 | I43: 655141 | J43: 250020014471 | K43: Bank Sohar | L43: BSHROMRU | N43: 04-09-24-feeds | O43: 1.5 dcf FEED | P43: 1801 | Q43: =P43=B43 -> TRUE | R43: HAMID MOHAMMED ZIDI BAIT SAID | S43: =R43=C43 -> TRUE | T43: 655141 | U43: =T43=I43 -> TRUE | V43: 250020014471 | W43: =V43=J43 -> TRUE | X43: BSHROMRU | Y43: =X43=L43 -> TRUE
A44: 190 | B44: 1816 | C44: MUSALLAM BAKHIT MASOUD AL KATHIRI | D44: 351.9 | E44: 0.4 | F44: =D44*E44 -> 140.76 | G44: =137.56+3.2 -> 140.76 | H44: =F44-G44 -> 0 | I44: 15694259 | J44: 0396003291210011 | K44: Bank Muscat | L44: BMUSOMRX | N44: 45586 | O44: 45601 | P44: 1816 | Q44: =P44=B44 -> TRUE | R44: MUSALLAM BAKHIT MASOUD AL KATHIRI | S44: =R44=C44 -> TRUE | T44: 15694259 | U44: =T44=I44 -> TRUE | V44: 0396003291210011 | W44: =V44=J44 -> TRUE | X44: BMUSOMRX | Y44: =X44=L44 -> TRUE
A45: 196 | B45: 1822 | C45: MANA SAID AHMED AL KATHIRI | D45: 316.4 | E45: 0.4 | F45: =D45*E45 -> 126.56 | G45: =122.45+4.11 -> 126.56 | H45: =F45-G45 -> 0 | I45: 22005737 | J45: 0439061793370011 | K45: Bank Muscat | L45: BMUSOMRX | N45: 30-09-2024 | O45: 45684 | P45: 1822 | Q45: =P45=B45 -> TRUE | R45: Mana Said Ahmed Al kathiri | S45: =R45=C45 -> TRUE | T45: 22005737 | U45: =T45=I45 -> TRUE | W45: =V45=J45 -> FALSE | Y45: =X45=L45 -> FALSE
A46: 198 | B46: 1824 | C46: SALIM AHMED ALI AL KATHIRI | D46: 274.7 | E46: 0.4 | F46: =D46*E46 -> 109.88 | G46: =105.66+4.22 -> 109.88 | H46: =F46-G46 -> 0 | I46: 766709 | J46: 3109634074500 | K46: Oman Arab Bank | L46: OMABOMRU | N46: 30-09-2024 | O46: 45643 | P46: 1824 | Q46: =P46=B46 -> TRUE | R46: Salim Ahmed Ali Al Kathiri | S46: =R46=C46 -> TRUE | T46: 766709 | U46: =T46=I46 -> TRUE | W46: =V46=J46 -> FALSE | Y46: =X46=L46 -> FALSE
A47: 205 | B47: 3250 | C47: Ali Said Aubad Ghawas Alkthiri | D47: 603.4 | E47: 0.4 | F47: =D47*E47 -> 241.36 | G47: =240.77+0.59 -> 241.36 | H47: =F47-G47 -> 0 | I47: 1357047 | J47: 10830402563017 | K47: NBO | L47: NBOMOMRX | M47: 91177550 | N47: 45635 | O47: 45601 | P47: 3250 | Q47: =P47=B47 -> TRUE | R47: Ali Said Aubad Ghawas Alkthiri | S47: =R47=C47 -> TRUE | T47: 1357047 | U47: =T47=I47 -> TRUE | V47: 10830402563017 | W47: =V47=J47 -> TRUE | X47: NBOMOMRX | Y47: =X47=L47 -> TRUE
A48: 219 | B48: 3826 | C48: Abdul Sallam Ahmed Said Al Kathiri | D48: 350.8 | E48: 0.4 | F48: =D48*E48 -> 140.32 | G48: =135.8+4.52 -> 140.32 | H48: =F48-G48 -> 0 | I48: 4919671 | J48: 0406003298990024 | K48: Bank Muscat | L48: BMUSOMRX | M48: 92516644 | N48: 45575 | O48: account name has changed | P48: 3826 | Q48: =P48=B48 -> TRUE | R48: Fahad Ahmed Said Jumaa Al Kathiri | S48: =R48=C48 -> FALSE | T48: 4919699 | U48: =T48=I48 -> FALSE | V48: 0397012182200017 | W48: =V48=J48 -> FALSE | X48: BMUSOMRX | Y48: =X48=L48 -> TRUE
D49: =SUM(D3:D48) -> 19441.1 | F49: =SUM(F3:F48) -> 7776.44 | G49: =SUM(G3:G48) -> 7776.44 | H49: =SUM(H3:H48) -> 0
G51: =G49/F49 -> 1
A55: Note: | B55: The payment for the month of March is 70,600 and will pay 50% only (35,300) OMR
A58: Suresh Bose | E58: Hassan Ghaly | J58: Said Al Bahanata
A59: Operations | E59: Cost Accountant | J59: DGM

Sheet center-July
A1: Milk Chilling Centre(Ghado) - Monthly Camel Milk Procurement Report - 01-07-2024 TO 31-07-2024
A2: SR. NO. | B2: Farmer Code | C2: Farmer Name | D2: Total Quantity Supplied(Lits) | E2: Camel Milk Price/Lit(OMR) | F2: Total Value Milk (OMR) | G2: Paid | H2: Balance | I2: ID No: | J2: Account No | K2: Bank Name | L2: BANK SWIFT CODE | M2: Phone No: | N2: Remarks
A3: 1 | B3: 1001 | C3: Abdul Hakim Musallam Salim Al Katini Al Rawas | D3: 340.5 | E3: 0.4 | F3: =D3*E3 -> 136.2 | G3: =F3 -> 136.2 | H3: =F3-G3 -> 0 | I3: 2130934 | J3: 0397020829680019 | K3: Bank Muscat | L3: BMUSOMRX | M3: 92911133
A4: 2 | B4: 1007 | C4: Ahmed Abdullah Said Al Rawas | D4: 1844 | E4: 0.4 | F4: =D4*E4 -> 737.6 | G4: =736.13+1.47 -> 737.6 | H4: =F4-G4 -> 0 | I4: 1515504 | J4: 3109147237500 | K4: Oman Arab Bank | L4: OMABOMRU | M4: 91748840 | N4: 45595 | O4: 45614
A5: 3 | B5: 1028 | C5: Ahmed Saeed Maatouq Al kathiri | D5: 400.3 | E5: 0.4 | F5: =D5*E5 -> 160.12 | G5: =160.05+0.07 -> 160.12 | H5: =F5-G5 -> 0 | I5: 802875 | J5: 0397004247250014 | K5: Bank Muscat | L5: BMUSOMRX | M5: 99498677 | N5: 45593
A6: 4 | B6: 1033 | C6: Ahmed Said Ali Al Nobi Al Kathiri | D6: 810 | E6: 0.4 | F6: =D6*E6 -> 324 | G6: =319.28+4.72 -> 324 | H6: =F6-G6 -> 0 | I6: 10132435 | J6: 01011076521002 | K6: Bank Dhofar | L6: BDOFOMRU | M6: 92268168 | N6: CHANGE THE ACCOUNT | O6: 45567 | P6: 45601
A7: 5 | B7: 1040 | C7: Ahmed Said Mahad Jamaan Dhishil al Kathiri | D7: 331 | E7: 0.4 | F7: =D7*E7 -> 132.4 | G7: =F7 -> 132.4 | H7: =F7-G7 -> 0 | I7: 25082374 | J7: 0406041201480018 | K7: Bank Muscat | L7: BMUSOMRX | M7: 99816344
A8: 6 | B8: 1044 | C8: Ahmed Salim Ahmed Al Hadi Baomar | D8: 405 | E8: 0.4 | F8: =D8*E8 -> 162 | G8: =F8 -> 162 | H8: =F8-G8 -> 0 | I8: 81904 | J8: 0406003182770027 | K8: Bank Muscat | L8: BMUSOMRX | M8: 99494120
A9: 7 | B9: 1080 | C9: Ali Saeed Matoq Alkthiri | D9: 354.1 | E9: 0.4 | F9: =D9*E9 -> 141.64 | G9: =F9 -> 141.64 | H9: =F9-G9 -> 0 | I9: 78762 | J9: 0397004237620018 | K9: Bank Muscat | L9: BMUSOMRX | M9: 92440088
A10: 8 | B10: 1089 | C10: Ali Said Nasib | D10: 641 | E10: 0.4 | F10: =D10*E10 -> 256.4 | G10: =F10 -> 256.4 | H10: =F10-G10 -> 0 | I10: 892683 | J10: 1023281341086 | K10: NBO | L10: NBOMOMRX | M10: 99506162
A11: 9 | B11: 1096 | C11: Ali Salim Awadh Al Kathiri | D11: 607.9 | E11: 0.4 | F11: =D11*E11 -> 243.16 | G11: =242.43+0.73 -> 243.16 | H11: =F11-G11 -> 0 | I11: 1959918 | J11: 3109647718500 | K11: Oman Arab Bank | L11: OMABOMRU | M11: 92699781 | N11: 45593 | O11: 45609
A12: 10 | B12: 1106 | C12: Badar Said Masood Al Kathiri | D12: 1188 | E12: 0.4 | F12: =D12*E12 -> 475.2 | G12: =F12 -> 475.2 | H12: =F12-G12 -> 0 | I12: 5502751 | J12: 10060192223001 | K12: NBO | L12: NBOMOMRX | M12: 99270001
A13: 11 | B13: 1110 | C13: Bakhit Salim Azad Al Kathiri | D13: 621 | E13: 0.4 | F13: =D13*E13 -> 248.4 | G13: =F13 -> 248.4 | H13: =F13-G13 -> 0 | I13: 934298 | J13: 0406003101920011 | K13: Bank Muscat | L13: BMUSOMRX | M13: 92811415 | N13: 45607
A14: 12 | B14: 1111 | C14: Bakhit Salim Ali Shadar Al Kathiri | D14: 711 | E14: 0.4 | F14: =D14*E14 -> 284.4 | G14: =F14 -> 284.4 | H14: =F14-G14 -> 0 | I14: 15571992 | J14: 01011058653001 | K14: Bank Dhofar | L14: BDOFOMRU | M14: 92708951
A15: 13 | B15: 1119 | C15: Ghanim Abdul Aziz Masoud Abdul Aziz Alash Al Kathiri | D15: 510 | E15: 0.4 | F15: =D15*E15 -> 204 | G15: =F15 -> 204 | H15: =F15-G15 -> 0 | I15: 24000245 | J15: 0397020978260014 | K15: Bank Muscat | L15: BMUSOMRX | M15: 90911369
A16: 14 | B16: 1122 | C16: Hamed Hilal Said Al Kathiri | D16: 367.7 | E16: 0.4 | F16: =D16*E16 -> 147.08 | G16: =F16 -> 147.08 | H16: =F16-G16 -> 0 | I16: 5219876 | J16: 0406045268200015 | K16: Bank Muscat | L16: BMUSOMRX | M16: 99066779 | N16: 45621
A17: 15 | B17: 1135 | C17: Khalid Said Ali Al Kathiri | D17: 729 | E17: 0.4 | F17: =D17*E17 -> 291.6 | G17: =290.07+1.53 -> 291.6 | H17: =F17-G17 -> 0 | I17: 19202954 | J17: 01013808698001 | K17: Bank Dhofar | L17: BDOFOMRU | M17: 92771786 | N17: 45601 | O17: 45628
A18: 16 | B18: 1141 | C18: Malik Said Ahmed Habkook Hat Al Shahri | D18: 746.7 | E18: 0.4 | F18: =D18*E18 -> 298.68 | G18: =298.14+0.54 -> 298.68 | H18: =F18-G18 -> 0 | I18: 11753992 | J18: 0396051591490029 | K18: Bank Muscat | L18: BMUSOMRX | M18: 99205960 | N18: 45575 | O18: 45609
A19: 17 | B19: 1154 | C19: Mohammed Salim Abdullah Al kathiri | D19: 1058.1 | E19: 0.4 | F19: =D19*E19 -> 423.24 | G19: =F19 -> 423.24 | H19: =F19-G19 -> 0 | I19: 18654817 | J19: 0439053703720016 | K19: Bank Muscat | L19: BMUSOMRX | M19: 98887846
A20: 18 | B20: 1161 | C20: Mohammed Ali Musallam Al Nubi Al Kathiri | D20: 405 | E20: 0.4 | F20: =D20*E20 -> 162 | G20: =160.05+1.95 -> 162 | H20: =F20-G20 -> 0 | I20: 257926 | J20: 3109603718500 | K20: Oman Arab Bank | L20: OMABOMRU | M20: 99589267 | N20: 45601 | O20: 45718
A21: 19 | B21: 1168 | C21: Mohammed Salim Said Jumaa Al Kathiri | D21: 645 | E21: 0.4 | F21: =D21*E21 -> 258 | G21: =F21 -> 258 | H21: =F21-G21 -> 0 | I21: 15498714 | J21: 00510097414001 | K21: Bank Nizwa | L21: BNZWOMRX | M21: 99292524
A22: 20 | B22: 1177 | C22: Said Salim Said BaitSaid | D22: 430 | E22: 0.4 | F22: =D22*E22 -> 172 | G22: =F22 -> 172 | H22: =F22-G22 -> 0 | I22: 219353 | J22: 01010127872001 | K22: Bank Dhofar | L22: BDOFOMRU | M22: 99485534
A23: 21 | B23: 1178 | C23: Mohammed Said Mohammed Akdha Al Rawas | D23: 753.5 | E23: 0.4 | F23: =D23*E23 -> 301.4 | G23: =296.86+4.54 -> 301.4 | H23: =F23-G23 -> 0 | I23: 970872 | J23: 1006123229017 | K23: NBO | L23: NBOMOMRX | M23: 99485535 | N23: 45567 | O23: 45607
A24: 22 | B24: 1224 | C24: Naif Masoud Awadh Nasib Kikab Al Shihri | D24: 827.1 | E24: 0.4 | F24: =D24*E24 -> 330.84 | G24: =329.8+1.04 -> 330.84 | H24: =F24-G24 -> 0 | I24: 24911691 | J24: 0406060856030017 | K24: Bank Muscat | L24: BMUSOMRX | M24: 99192216 | N24: 45595 | O24: 45644
A25: 23 | B25: 1225 | C25: Naif Said Awadh Fadhl | D25: 586.9 | E25: 0.4 | F25: =D25*E25 -> 234.76 | G25: =F25 -> 234.76 | H25: =F25-G25 -> 0 | I25: 9642357 | J25: 1501079705330 | K25: Ahli bank | L25: AUBOOMRU | M25: 99777877
A26: 24 | B26: 1235 | C26: Saeed Abdul Aziz Abdullah Al kathiri | D26: 783 | E26: 0.4 | F26: =D26*E26 -> 313.2 | G26: =312.66+0.54 -> 313.2 | H26: =F26-G26 -> 0 | I26: 1992436 | J26: 0402003122620013 | K26: BANK MUSCAT | L26: BMUSOMRX | M26: 99484668 | N26: 45586
A27: 25 | B27: 1241 | C27: Said Mohammed Abdallah Al kathiri | D27: 652.2 | E27: 0.4 | F27: =D27*E27 -> 260.88 | G27: =258.07+2.81 -> 260.88 | H27: =F27-G27 -> 0 | I27: 5343254 | J27: 0406003410830019 | K27: Bank Muscat | L27: BMUSOMRX | M27: 98964664 | N27: 45567 | O27: 11/11/2024 - 13-11-2024
A28: 26 | B28: 1247 | C28: Said Salim Azad Bait Ali Badar | D28: 648 | E28: 0.4 | F28: =D28*E28 -> 259.2 | G28: =259.05+0.15 -> 259.2 | H28: =F28-G28 -> 0 | I28: 4748561 | J28: 01040280570002 | K28: Bank Dhofar | L28: BDOFOMRU | M28: 92345282 | N28: 45637 | O28: 45644
A29: 27 | B29: 1252 | C29: Said Ahmed Ali Bait Said | D29: 594 | E29: 0.4 | F29: =D29*E29 -> 237.6 | G29: =F29 -> 237.6 | H29: =F29-G29 -> 0 | I29: 2433959 | J29: 01010120819002 | K29: Bank Dhofar | L29: BDOFOMRU | M29: 93555999
A30: 28 | B30: 1258 | C30: Said Ali Musallam Al Noubi Al Kathiri | D30: 810 | E30: 0.4 | F30: =D30*E30 -> 324 | G30: =F30 -> 324 | H30: =F30-G30 -> 0 | I30: 1924174 | J30: 01040280044001 | K30: Bank Dhofar | L30: BDOFOMRU | M30: 99297990
A31: 29 | B31: 1260 | C31: Said Salim Ali Kibab Al Shahri | D31: 756 | E31: 0.4 | F31: =D31*E31 -> 302.4 | G31: =299.43+2.97 -> 302.4 | H31: =F31-G31 -> 0 | I31: 18363579 | J31: 01041057246001 | K31: Bank Dhofar | L31: BDOFOMRU | M31: 98217444 | N31: 45595 | O31: 45621
A32: 30 | B32: 1261 | C32: Said Ali Nasib Kikab Al shahri | D32: 423.5 | E32: 0.4 | F32: =D32*E32 -> 169.4 | G32: =168.68+0.72 -> 169.4 | H32: =F32-G32 -> 0 | I32: 14429332 | J32: 0439018203570018 | K32: Bank Muscat | L32: BMUSOMRX | M32: 92939445 | N32: 45607 | O32: 45623
A33: 31 | B33: 1268 | C33: Said Musallam Ali Ghawas | D33: 540 | E33: 0.4 | F33: =D33*E33 -> 216 | G33: =212.58+3.42 -> 216 | H33: =F33-G33 -> 0 | I33: 722058 | J33: 0397003940070023 | K33: Bank Muscat | L33: BMUSOMRX | M33: 92848609 | N33: 45573 | O33: 45600
A34: 32 | B34: 1282 | C34: Salim Ali Musallam Al Noubi Al Kathiri | D34: 702 | E34: 0.4 | F34: =D34*E34 -> 280.8 | G34: =F34 -> 280.8 | H34: =F34-G34 -> 0 | I34: 2997747 | J34: 3109601542500 | K34: Oman Arab Bank | L34: OMABOMRU | M34: 92660969 | N34: Bank transfer-04-11-2024
A35: 33 | B35: 1284 | C35: Salim Ali Said Al Nubi Al Kathiri | D35: 702 | E35: 0.4 | F35: =D35*E35 -> 280.8 | G35: =280.45+0.35 -> 280.8 | H35: =F35-G35 -> 0 | I35: 1177598 | J35: 01040280595001 | K35: Bank Dhofar | L35: BDOFOMRU | M35: 92825228 | N35: 45573 | O35: 45602
A36: 34 | B36: 1300 | C36: Salem Suhail Omer Bit Fhadel | D36: 862.2 | E36: 0.4 | F36: =D36*E36 -> 344.88 | G36: =F36 -> 344.88 | H36: =F36-G36 -> 0 | I36: 19534277 | J36: 0439016892350027 | K36: Bank Muscat | L36: BMUSOMRX | M36: 99710505
A37: 35 | B37: 1306 | C37: Salim Ali Nasib Al Kathiri | D37: 428.4 | E37: 0.4 | F37: =D37*E37 -> 171.36 | G37: =168.53+2.83 -> 171.36 | H37: =F37-G37 -> 0 | I37: 2006904 | J37: 0439051845390018 | K37: Bank Muscat | L37: BMUSOMRX | M37: 96137717 | N37: 45600
A38: 36 | B38: 1315 | C38: Salim Said Ali Ghawas | D38: 367.4 | E38: 0.4 | F38: =D38*E38 -> 146.96 | G38: =F38 -> 146.96 | H38: =F38-G38 -> 0 | I38: 19528845 | J38: 0439026234320047 | K38: Bank Muscat | L38: BMUSOMRX | M38: 92432606
A39: 37 | B39: 1328 | C39: Suhail Saeed Suhail ghawas | D39: 482.7 | E39: 0.4 | F39: =D39*E39 -> 193.08 | G39: =F39 -> 193.08 | H39: =F39-G39 -> 0 | I39: 782833 | J39: 01015382117001 | K39: Bank Dhofar | L39: BDOFOMRU | M39: 92475895 | N39: 45601
A40: 38 | B40: 1330 | C40: Said Mahad Ali Al Kathiri | D40: 738 | E40: 0.4 | F40: =D40*E40 -> 295.2 | G40: =F40 -> 295.2 | H40: =F40-G40 -> 0 | I40: 12194826 | J40: 00510129167001 | K40: Bank Nizwa | L40: BNZWOMRX | M40: 91299100
A41: 39 | B41: 1331 | C41: Mohammed Said Musallam Al Noob Al Kathiri | D41: 405 | E41: 0.4 | F41: =D41*E41 -> 162 | G41: =159.32+2.68 -> 162 | H41: =F41-G41 -> 0 | I41: 2107763 | J41: 3109043578500 | K41: Oman Arab Bank | L41: OMABOMRU | M41: 93536009 | N41: 45593 | O41: 45628
A42: 40 | B42: 1333 | C42: Suhail Salim Ahmed Al Nubi Al Kathiri | D42: 650 | E42: 0.4 | F42: =D42*E42 -> 260 | G42: =F42 -> 260 | H42: =F42-G42 -> 0 | I42: 1736679 | J42: 0401002496140031 | K42: Bank Muscat | L42: BMUSOMRX | M42: 99482212
A43: 41 | B43: 1382 | C43: Suhail Mohammed Said Ghawas Al Kathiri | D43: 783 | E43: 0.4 | F43: =D43*E43 -> 313.2 | G43: =F43 -> 313.2 | H43: =F43-G43 -> 0 | I43: 886492 | J43: 0397003786810019 | K43: Bank Muscat | L43: BMUSOMRX | M43: 99494166 | N43: 45601
A44: 42 | B44: 1384 | C44: Abdul Selam Musallam Mohammed Al Rawas | D44: 376.5 | E44: 0.4 | F44: =D44*E44 -> 150.6 | G44: =F44 -> 150.6 | H44: =F44-G44 -> 0 | I44: 4426701 | J44: 0406003017570013 | K44: Bank Muscat | L44: BMUSOMRX | M44: 92634991
A45: 43 | B45: 1386 | C45: Omar Salim Ahmed Al Hadi Ba Omar | D45: 864 | E45: 0.4 | F45: =D45*E45 -> 345.6 | G45: =343.35+2.25 -> 345.6 | H45: =F45-G45 -> 0 | I45: 711799 | J45: 0406003202280013 | K45: Bank Muscat | L45: BMUSOMRX | M45: 92394924 | N45: 45601 | O45: 45621
A46: 44 | B46: 1387 | C46: Ali Said Mahisan Kayakab Al Shihri | D46: 721 | E46: 0.4 | F46: =D46*E46 -> 288.4 | G46: =F46 -> 288.4 | H46: =F46-G46 -> 0 | I46: 6759716 | J46: 3109117911500 | K46: Oman Arab Bank | L46: OMABOMRU | M46: 91907675
A47: 45 | B47: 1388 | C47: Tarik Suhail Salim Al Kathiri | D47: 432 | E47: 0.4 | F47: =D47*E47 -> 172.8 | G47: =168.93+3.87 -> 172.8 | H47: =F47-G47 -> 0 | I47: 18610874 | J47: 01011035504001 | K47: Bank Dhofar | L47: BDOFOMRU | M47: 93955577 | N47: 45595 | O47: 45600
A48: 46 | B48: 1389 | C48: Ali Said Musallam Al Noubi Al Kathiri | D48: 1080 | E48: 0.4 | F48: =D48*E48 -> 432 | G48: =429.7+2.3 -> 432 | H48: =F48-G48 -> 0 | I48: 1036354 | J48: 01010281496001 | K48: Bank Dhofar | L48: BDOFOMRU | M48: 92413881 | N48: 45567 | O48: 45600
A49: 47 | B49: 1394 | C49: Ali Ahmed Salim Ahmed Al Kathiri | D49: 434.8 | E49: 0.4 | F49: =D49*E49 -> 173.92 | G49: =171.3+2.62 -> 173.92 | H49: =F49-G49 -> 0 | I49: 25656187 | J49: 0396016034040018 | K49: Bank Muscat | L49: BMUSOMRX | M49: 98987848 | N49: 45586 | O49: 45621
A50: 48 | B50: 1396 | C50: Mustahil Ali Azad Al Kathiri | D50: 476.3 | E50: 0.4 | F50: =D50*E50 -> 190.52 | G50: =187.05+3.47 -> 190.52 | H50: =F50-G50 -> 0 | I50: 905845 | J50: 0397003647340016 | K50: Bank Muscat | L50: BMUSOMRX | M50: 99696204 | N50: 45628 | O50: 45650
A51: 49 | B51: 1397 | C51: Ahmed Musallam Amer Al Kathiri | D51: 392.3 | E51: 0.4 | F51: =D51*E51 -> 156.92 | G51: =F51 -> 156.92 | H51: =F51-G51 -> 0 | I51: 1292885 | J51: 254001118001 | K51: HSBC | L51: BBMEOMRX | M51: 92307552
A52: 50 | B52: 1398 | C52: Salim Amer Azad Al Kathiri | D52: 311.3 | E52: 0.4 | F52: =D52*E52 -> 124.52 | G52: =121.62+2.9 -> 124.52 | H52: =F52-G52 -> 0 | I52: 1161437 | J52: 00510128357001 | K52: Bank Nizwa | L52: BNZWOMRX | M52: 91135580 | N52: 45567 | O52: 45607
A53: 51 | B53: 1400 | C53: Manei Said Ahmed Al Kathiri | D53: 732 | E53: 0.4 | F53: =D53*E53 -> 292.8 | G53: =141.25+150.05+1.5 -> 292.8 | H53: =F53-G53 -> 0 | I53: 7223707 | J53: 10060183858001 | K53: NBO | L53: NBOMOMRX | M53: 92616136 | N53: 45595 | O53: 45637 | P53: 45691
A54: 52 | B54: 1403 | C54: Ali Salim Ahmed Al Nubi Al Kathiri | D54: 606.6 | E54: 0.4 | F54: =D54*E54 -> 242.64 | G54: =F54 -> 242.64 | H54: =F54-G54 -> 0 | I54: 499044 | J54: 0406003202740014 | K54: Bank Muscat | L54: BMUSOMRX | M54: 92226988 | N54: 45607
A55: 53 | B55: 1406 | C55: Said Salim Musallam AlNoob Al Kathiri | D55: 539 | E55: 0.4 | F55: =D55*E55 -> 215.6 | G55: =215.6 -> 215.6 | H55: =F55-G55 -> 0 | I55: 880849 | J55: 3109015600500 | K55: Oman Arab Bank | L55: OMABOMRU | M55: 99365157 | N55: 45574
A56: 54 | B56: 1408 | C56: Abdullah Salim AhmedAl Hadi Ba Omar | D56: 1566 | E56: 0.4 | F56: =D56*E56 -> 626.4 | G56: =F56 -> 626.4 | H56: =F56-G56 -> 0 | I56: 997465 | J56: 0397003981360017 | K56: Bank Muscat | L56: BMUSOMRX | M56: 99490975
A57: 55 | B57: 1409 | C57: Mahisan Ali Mahisan Al Shihri | D57: 604.3 | E57: 0.4 | F57: =D57*E57 -> 241.72 | G57: =234.09+7.63 -> 241.72 | H57: =F57-G57 -> 0 | I57: 7279409 | J57: 0406016730440035 | K57: Bank Muscat | L57: BMUSOMRX | M57: 99626634 | N57: 30-10-2024# | O57: 45621
A58: 56 | B58: 1410 | C58: Masoud Ali suhail Bait Said | D58: 656.9 | E58: 0.4 | F58: =D58*E58 -> 262.76 | G58: =F58 -> 262.76 | H58: =F58-G58 -> 0 | I58: 757372 | J58: 0406003338100019 | K58: Bank Muscat | L58: BMUSOMRX | M58: 92018800 | N58: 45614
A59: 57 | B59: 1411 | C59: Said Ali Ahmed Amor Jid | D59: 729 | E59: 0.4 | F59: =D59*E59 -> 291.6 | G59: =288.4+3.2 -> 291.6 | H59: =F59-G59 -> 0 | I59: 1650389 | J59: 0406018263680011 | K59: Bank Muscat | L59: BMUSOMRX | M59: 92294150 | N59: 45567 | O59: 45601
A60: 58 | B60: 1412 | C60: Musallam Said Salim Bait Said | D60: 810 | E60: 0.4 | F60: =D60*E60 -> 324 | G60: =F60 -> 324 | H60: =F60-G60 -> 0 | I60: 312227 | J60: 0406003457720017 | K60: Bank Muscat | L60: BMUSOMRX | M60: 95414124
A61: 59 | B61: 1413 | C61: Awadh Salim Ali Ghawas | D61: 405 | E61: 0.4 | F61: =D61*E61 -> 162 | G61: =159.75+2.25 -> 162 | H61: =F61-G61 -> 0 | I61: 539906 | J61: 01010128406001 | K61: Bank Dhofar | L61: BDOFOMRU | N61: 45586 | O61: 45607
A62: 60 | B62: 1414 | C62: Salim Said Ali Bait Said | D62: 1195.4 | E62: 0.4 | F62: =D62*E62 -> 478.16 | G62: =477.45+0.71 -> 478.16 | H62: =F62-G62 -> 0 | I62: 9178238 | J62: 01010852881001 | K62: Bank Dhofar | L62: BDOFOMRU | M62: 91966140 | N62: 45593 | O62: 45610
A63: 61 | B63: 1415 | C63: Salim ahmed Masoud Jumaa Al kathiri | D63: 320.8 | E63: 0.4 | F63: =D63*E63 -> 128.32 | G63: =F63 -> 128.32 | H63: =F63-G63 -> 0 | I63: 818787 | J63: 01011455172002 | K63: Bank Dhofar | L63: BDOFOMRU | M63: 99806280
A64: 62 | B64: 1417 | C64: Said Bakhit said Al mashikhi | D64: 590.6 | E64: 0.4 | F64: =D64*E64 -> 236.24 | G64: =F64 -> 236.24 | H64: =F64-G64 -> 0 | I64: 1252579 | J64: 0397003628950016 | K64: Bank Muscat | L64: BMUSOMRX | M64: 98520912 | N64: 45635
A65: 63 | B65: 1418 | C65: SALIM ALI MUSALLAM GHAWAS | D65: 344.5 | E65: 0.4 | F65: =D65*E65 -> 137.8 | G65: =F65 -> 137.8 | H65: =F65-G65 -> 0 | I65: 9954378 | J65: 0500013032002001 | K65: Bank alizz islamic | L65: IZZBOMRU | M65: 99282423
A66: 64 | B66: 1419 | C66: Mahad Masoud Salim Baitsaid | D66: 972 | E66: 0.4 | F66: =D66*E66 -> 388.8 | G66: =F66 -> 388.8 | H66: =F66-G66 -> 0 | I66: 386821 | J66: 0406003414760015 | K66: Bank Muscat | L66: BMUSOMRX | M66: 99181419 | N66: Bank transfer-04-11-2024
A67: 65 | B67: 1420 | C67: Salim Said Salim Al Rawas | D67: 729 | E67: 0.4 | F67: =D67*E67 -> 291.6 | G67: =F67 -> 291.6 | H67: =F67-G67 -> 0 | I67: 5460297 | J67: 0402003168320014 | K67: Bank Muscat | L67: BMUSOMRX | M67: 95898899
A68: 66 | B68: 1421 | C68: Malik Musallam Salim Masoud Al Rawas | D68: 781 | E68: 0.4 | F68: =D68*E68 -> 312.4 | G68: =F68 -> 312.4 | H68: =F68-G68 -> 0 | I68: 15314262 | J68: 0397019441080011 | K68: Bank Muscat | L68: BMUSOMRX | M68: 90333361
A69: 67 | B69: 1423 | C69: Ahmed Said Ali Azad Al Kathiri | D69: 708 | E69: 0.4 | F69: =D69*E69 -> 283.2 | G69: =F69 -> 283.2 | H69: =F69-G69 -> 0 | I69: 5044397 | J69: 0397003645500016 | K69: Bank Muscat | L69: BMUSOMRX | M69: 99580550
A70: 68 | B70: 1425 | C70: Salim Mohammed Ali Al Kathiri | D70: 666.2 | E70: 0.4 | F70: =D70*E70 -> 266.48 | G70: =F70 -> 266.48 | H70: =F70-G70 -> 0 | I70: 5614623 | J70: 0406002564870025 | K70: Bank Muscat | L70: BMUSOMRX | M70: 99583112
A71: 69 | B71: 1426 | C71: Ahmed Salim Ahmed Said Al Nubi Al Kathiri | D71: 723 | E71: 0.4 | F71: =D71*E71 -> 289.2 | G71: =285.45+3.75 -> 289.2 | H71: =F71-G71 -> 0 | I71: 2160707 | J71: 3109076938500 | K71: Oman Arab Bank | L71: OMABOMRU | M71: 92280327 | N71: 45567 | O71: 45600
A72: 70 | B72: 1427 | C72: Salim Said Mohammed Musallam Al Nubi Al kathiri | D72: 375.3 | E72: 0.4 | F72: =D72*E72 -> 150.12 | G72: =F72 -> 150.12 | H72: =F72-G72 -> 0 | I72: 24171637 | J72: 0439025022760016 | K72: Bank Muscat | L72: BMUSOMRX | M72: 97030409
A73: 71 | B73: 1428 | C73: Abdullah Said Abdullah Alkthiri | D73: 371.7 | E73: 0.4 | F73: =D73*E73 -> 148.68 | G73: =147.17+1.51 -> 148.68 | H73: =F73-G73 -> 0 | I73: 921364 | J73: 0406003192550017 | K73: BANK MUSCAT | L73: BMUSOMRX | M73: 92599597 | N73: 45567 | O73: 45600
A74: 72 | B74: 1430 | C74: Ahmed Said Mohammed Houmdi Al Siari | D74: 378 | E74: 0.4 | F74: =D74*E74 -> 151.2 | G74: =F74 -> 151.2 | H74: =F74-G74 -> 0 | I74: 564698 | J74: 0406003186630017 | K74: Bank Muscat | L74: BMUSOMRX | M74: 99189793 | N74: 45600
A75: 73 | B75: 1432 | C75: Ali Ahmed Ali Sajlil Al shanfari | D75: 890.8 | E75: 0.4 | F75: =D75*E75 -> 356.32 | G75: =F75 -> 356.32 | H75: =F75-G75 -> 0 | I75: 5004855 | J75: 01013803818001 | K75: Bank Dhofar | L75: BDOFOMRU | M75: 99899962
A76: 74 | B76: 1433 | C76: Ali Said Ali Bait Said | D76: 891 | E76: 0.4 | F76: =D76*E76 -> 356.4 | G76: =355.84+0.56 -> 356.4 | H76: =F76-G76 -> 0 | I76: 285841 | J76: 0397003981260015 | K76: Bank Muscat | L76: BMUSOMRX | M76: 92958552 | N76: 45593 | O76: .56-dcf
A77: 75 | B77: 1434 | C77: Muhssin Said Mohammed Ghawas | D77: 430 | E77: 0.4 | F77: =D77*E77 -> 172 | G77: =171.22+0.78 -> 172 | H77: =F77-G77 -> 0 | I77: 19197503 | J77: 0403015046590039 | K77: Bank Muscat | L77: BMUSOMRX | M77: 92466605 | N77: 45614
A78: 76 | B78: 1435 | C78: Salim Said aoubad Ghawas | D78: 1188 | E78: 0.4 | F78: =D78*E78 -> 475.2 | G78: =474.3+0.9 -> 475.2 | H78: =F78-G78 -> 0 | I78: 1305522 | J78: 0397003064100017 | K78: Bank Muscat | L78: BMUSOMRX | M78: 93246263 | N78: 45601 | O78: 45623
A79: 77 | B79: 1437 | C79: Ahmed Ali Ahmed Shadar Al Kathiri | D79: 777 | E79: 0.4 | F79: =D79*E79 -> 310.8 | G79: =F79 -> 310.8 | H79: =F79-G79 -> 0 | I79: 9685144 | J79: 250056066001 | K79: HSBC | L79: BBMEOMRX | M79: 96907302
A80: 78 | B80: 1438 | C80: Salim Aubad Al Maslamin Al Mashali | D80: 1188 | E80: 0.4 | F80: =D80*E80 -> 475.2 | G80: =F80 -> 475.2 | H80: =F80-G80 -> 0 | I80: 656621 | J80: 1023386437017 | K80: NBO | L80: NBOMOMRX | M80: 92509804 | N80: 45637
A81: 79 | B81: 1439 | C81: Ahmed Musallam Salim Al Kathiri | D81: 568.7 | E81: 0.4 | F81: =D81*E81 -> 227.48 | G81: =227.14+0.34 -> 227.48 | H81: =F81-G81 -> 0 | I81: 18880548 | J81: 0406060805600016 | K81: Bank Muscat | L81: BMUSOMRX | M81: 98901515 | N81: 45593 | O81: 45621
A82: 80 | B82: 1441 | C82: Musallam Said Amer Azad Al kathiri | D82: 638.1 | E82: 0.4 | F82: =D82*E82 -> 255.24 | G82: =F82 -> 255.24 | H82: =F82-G82 -> 0 | I82: 7285624 | J82: 00510041624001 | K82: Bank Nizwa | L82: BMUSOMRX | M82: 93587666
A83: 81 | B83: 1444 | C83: Masoud Musallam Masoud Baitsaid | D83: 858 | E83: 0.4 | F83: =D83*E83 -> 343.2 | G83: =F83 -> 343.2 | H83: =F83-G83 -> 0 | I83: 13487202 | J83: 0406003229140019 | K83: Bank Muscat | L83: BMUSOMRX | M83: 92244429
A84: 82 | B84: 1448 | C84: Salim Said Masoud Said Al Kathiri | D84: 341.4 | E84: 0.4 | F84: =D84*E84 -> 136.56 | G84: =F84 -> 136.56 | H84: =F84-G84 -> 0 | I84: 26433121 | J84: 0397060499480017 | K84: Bank Muscat | L84: BMUSOMRX | M84: 93229244
A85: 83 | B85: 1451 | C85: Maneef Ali Abdullah Ghawas | D85: 429.6 | E85: 0.4 | F85: =D85*E85 -> 171.84 | G85: =170.24+1.6 -> 171.84 | H85: =F85-G85 -> 0 | I85: 20337612 | J85: 0406061272960011 | K85: Bank Muscat | L85: BMUSOMRX | M85: 98829667 | N85: 45586 | O85: 45609
A86: 84 | B86: 1453 | C86: Ahmed Said Salim Al Rawas | D86: 404 | E86: 0.4 | F86: =D86*E86 -> 161.6 | G86: =F86 -> 161.6 | H86: =F86-G86 -> 0 | I86: 5460259 | J86: 010010017675 | K86: Bank Sohar | L86: BSHROMRU | M86: 90199947 | N86: 45607
A87: 85 | B87: 1455 | C87: Thuwaini Ali Musallam Ghawas | D87: 820.4 | E87: 0.4 | F87: =D87*E87 -> 328.16 | G87: =97+230.05+1.11 -> 328.16 | H87: =F87-G87 -> 0 | I87: 9954383 | J87: 0403061364570014 | K87: Bank Muscat | L87: BMUSOMRX | M87: 93270751 | N87: 45601 | O87: 45635 | P87: 45637
A88: 86 | B88: 1462 | C88: Mohammed Suhail Mohammed Ghawas | D88: 404 | E88: 0.4 | F88: =D88*E88 -> 161.6 | G88: =F88 -> 161.6 | H88: =F88-G88 -> 0 | I88: 9664038 | J88: 132247650084010 | K88: Bank Muscat | L88: BMUSOMRX | M88: 92989674 | N88: 45601
A89: 87 | B89: 1463 | C89: Said Salim Ali Aazad Al Kathiri | D89: 648 | E89: 0.4 | F89: =D89*E89 -> 259.2 | G89: =254.03+5.17 -> 259.2 | H89: =F89-G89 -> 0 | I89: 3798072 | J89: 01040280652001 | K89: Bank Dhofar | L89: BDOFOMRU | M89: 99480608 | N89: 45623 | O89: 45643
A90: 88 | B90: 1464 | C90: Ahmed Hamid Mohammed Zidi Bait Said | D90: 756 | E90: 0.4 | F90: =D90*E90 -> 302.4 | G90: =F90 -> 302.4 | H90: =F90-G90 -> 0 | I90: 6352996 | J90: 01011028474002 | K90: Bank Dhofar | L90: BDOFOMRU | M90: 92463267
A91: 89 | B91: 1467 | C91: Salim Suhail Ali Al Kathiri | D91: 580.5 | E91: 0.4 | F91: =D91*E91 -> 232.2 | G91: =F91 -> 232.2 | H91: =F91-G91 -> 0 | I91: 4279933 | J91: 01013038536001 | K91: Bank Dhofar | L91: BDOFOMRU | M91: 98510166
A92: 90 | B92: 1468 | C92: Ahmed Salim Ahmed Al Kathiri | D92: 810 | E92: 0.4 | F92: =D92*E92 -> 324 | G92: =F92 -> 324 | H92: =F92-G92 -> 0 | I92: 6996485 | J92: 0439016595760027 | K92: Bank Muscat | L92: BMUSOMRX | M92: 92947741
A93: 91 | B93: 1472 | C93: Rams Musallam Said Ghawas | D93: 729 | E93: 0.4 | F93: =D93*E93 -> 291.6 | G93: =F93 -> 291.6 | H93: =F93-G93 -> 0 | I93: 962967 | J93: 3109046516500 | K93: Oman Arab Bank | L93: OMABOMRU | M93: 99365173
A94: 92 | B94: 1473 | C94: Salim Said Mahad Alshakal Al Kathiri | D94: 702 | E94: 0.4 | F94: =D94*E94 -> 280.8 | G94: =F94 -> 280.8 | H94: =F94-G94 -> 0 | I94: 18722784 | J94: 01010402046001 | K94: Bank Dhofar | L94: BDOFOMRU | M94: 98900644
A95: 93 | B95: 1475 | C95: Musallam Said Ahmed Al kathiri | D95: 424.9 | E95: 0.4 | F95: =D95*E95 -> 169.96 | G95: =F95 -> 169.96 | H95: =F95-G95 -> 0 | I95: 4584011 | J95: 0439061793370011 | K95: Bank Muscat | L95: BMUSOMRX | M95: 98822862
A96: 94 | B96: 1476 | C96: Ali Masoud Said Al Shahri | D96: 392.1 | E96: 0.4 | F96: =D96*E96 -> 156.84 | G96: =154.22+2.62 -> 156.84 | H96: =F96-G96 -> 0 | I96: 5486858 | J96: 10230186394017 | K96: NBO | L96: NBOMOMRX | M96: 99019634 | N96: 45586 | O96: 45607
A97: 95 | B97: 1477 | C97: Salim Mohammed Mahad Al Kathiri | D97: 405 | E97: 0.4 | F97: =D97*E97 -> 162 | G97: =F97 -> 162 | H97: =F97-G97 -> 0 | I97: 18656494 | J97: 0396055887490011 | K97: Bank Muscat | L97: BMUSOMRX | M97: 92610234
A98: 96 | B98: 1480 | C98: Mohsin Ali Mahisan Houmdi Al Siari | D98: 403.2 | E98: 0.4 | F98: =D98*E98 -> 161.28 | G98: =F98 -> 161.28 | H98: =F98-G98 -> 0 | I98: 19820777 | J98: 0439050442120017 | K98: Bank Muscat | L98: BMUSOMRX | M98: 92525031
A99: 97 | B99: 1482 | C99: Ahmed Abdullah Ahmed Qatmem Al marhoon | D99: 717.5 | E99: 0.4 | F99: =D99*E99 -> 287 | G99: =F99 -> 287 | H99: =F99-G99 -> 0 | I99: 4024306 | J99: 01011165430002 | K99: Bank Dhofar | L99: BDOFOMRU | M99: 94453330 | N99: DCF Feed
A100: 98 | B100: 1485 | C100: Salim Ali Mustahil Asat Al Shihri | D100: 457 | E100: 0.4 | F100: =D100*E100 -> 182.8 | G100: =181.44+1.36 -> 182.8 | H100: =F100-G100 -> 0 | I100: 18585573 | J100: 0406016500890015 | K100: Bank Muscat | L100: BMUSOMRX | M100: 92695802 | N100: 45593 | O100: 45593 | P100: 45607
...

Sheet center-Aug
A1: Milk Chilling Centre(Ghado) - Monthly Camel Milk Procurement Report - 01-08-2024 TO 31-08-2024
A2: SR. NO. | B2: Farmer Code | D2: Total Quantity Supplied(Lits) | E2: Camel Milk Price/Lit(OMR) | F2: Total Value Milk (OMR) | I2: ID No: | J2: Remarks
A3: 1 | B3: 1001 | C3: Abdul Hakim Musallam Salim Al Katini Al Rawas | D3: 295.6 | E3: 0.4 | F3: =D3*E3 -> 118.24 | G3: =F3 -> 118.24 | H3: =F3-G3 -> 0 | I3: 2130934 | J3: BT-19-12-24
A4: 2 | B4: 1007 | C4: Ahmed Abdullah Said Al Rawas | D4: 1775 | E4: 0.4 | F4: =D4*E4 -> 710 | G4: =704.78+5.22 -> 710 | H4: =F4-G4 -> 0 | I4: 1515504 | J4: 45614 | K4: 45630
A5: 3 | B5: 1028 | C5: Ahmed Saeed Maatouq Al kathiri | D5: 347.5 | E5: 0.4 | F5: =D5*E5 -> 139 | G5: =F5 -> 139 | H5: =F5-G5 -> 0 | I5: 802875
A6: 4 | B6: 1033 | C6: Ahmed Said Ali Al Nobi Al Kathiri | D6: 745.8 | E6: 0.4 | F6: =D6*E6 -> 298.32 | G6: =295.98+2.34 -> 298.32 | H6: =F6-G6 -> 0 | I6: 10132435 | J6: 45601 | K6: 45621
A7: 5 | B7: 1040 | C7: Ahmed Said Mahad Jamaan Dhishil al Kathiri | D7: 325 | E7: 0.4 | F7: =D7*E7 -> 130 | G7: =F7 -> 130 | H7: =F7-G7 -> 0 | I7: 25082374 | J7: 45684
A8: 6 | B8: 1044 | C8: Ahmed Salim Ahmed Al Hadi Baomar | D8: 365 | E8: 0.4 | F8: =D8*E8 -> 146 | G8: =145.5 -> 145.5 | H8: =F8-G8 -> 0.5 | I8: 81904 | J8: 45810
A9: 7 | B9: 1080 | C9: Ali Saeed Matoq Alkthiri | D9: 315.4 | E9: 0.4 | F9: =D9*E9 -> 126.16 | G9: =F9 -> 126.16 | H9: =F9-G9 -> 0 | I9: 78762
A10: 8 | B10: 1089 | C10: Ali Said Nasib | D10: 572.1 | E10: 0.4 | F10: =D10*E10 -> 228.84 | G10: =F10 -> 228.84 | H10: =F10-G10 -> 0 | I10: 892683 | J10: 45644
A11: 9 | B11: 1096 | C11: Ali Salim Awadh Al Kathiri | D11: 483.1 | E11: 0.4 | F11: =D11*E11 -> 193.24 | G11: =192.97+0.27 -> 193.24 | H11: =F11-G11 -> 0 | I11: 1959918 | J11: 45609 | K11: 45623
A12: 10 | B12: 1106 | C12: Badar Said Masood Al Kathiri | D12: 1100 | E12: 0.4 | F12: =D12*E12 -> 440 | G12: =F12 -> 440 | H12: =F12-G12 -> 0 | I12: 5502751
A13: 11 | B13: 1110 | C13: Bakhit Salim Azad Al Kathiri | D13: 575 | E13: 0.4 | F13: =D13*E13 -> 230 | G13: =226.9+3.1 -> 230 | H13: =F13-G13 -> 0 | I13: 934298 | J13: 45607 | K13: 45628
A14: 12 | B14: 1111 | C14: Bakhit Salim Ali Shadar Al Kathiri | D14: 662 | E14: 0.4 | F14: =D14*E14 -> 264.8 | G14: =F14 -> 264.8 | H14: =F14-G14 -> 0 | I14: 15571992
A15: 13 | B15: 1119 | C15: Ghanim Abdul Aziz Masoud Abdul Aziz Alash Al Kathiri | D15: 305.1 | E15: 0.4 | F15: =D15*E15 -> 122.04 | G15: =F15 -> 122.04 | H15: =F15-G15 -> 0 | I15: 24000245
A16: 14 | B16: 1122 | C16: Hamed Hilal Said Al Kathiri | D16: 348.3 | E16: 0.4 | F16: =D16*E16 -> 139.32 | G16: =138.65+0.67 -> 139.32 | H16: =F16-G16 -> 0 | I16: 5219876 | J16: 45621 | K16: 45643
A17: 15 | B17: 1135 | C17: Khalid Said Ali Al Kathiri | D17: 674.2 | E17: 0.4 | F17: =D17*E17 -> 269.68 | G17: =F17 -> 269.68 | H17: =F17-G17 -> 0 | I17: 19202954 | J17: 45628
A18: 16 | B18: 1141 | C18: Malik Said Ahmed Habkook Hat Al Shahri | D18: 593.1 | E18: 0.4 | F18: =D18*E18 -> 237.24 | G18: =237.11+0.13 -> 237.24 | H18: =F18-G18 -> 0 | I18: 11753992 | J18: 45609 | K18: 45644
A19: 17 | B19: 1154 | C19: Mohammed Salim Abdullah Al kathiri | D19: 938.2 | E19: 0.4 | F19: =D19*E19 -> 375.28 | G19: =F19 -> 375.28 | H19: =F19-G19 -> 0 | I19: 18654817
A20: 18 | B20: 1161 | C20: Mohammed Ali Musallam Al Nubi Al Kathiri | D20: 374.5 | E20: 0.4 | F20: =D20*E20 -> 149.8 | G20: =149.8 -> 149.8 | H20: =F20-G20 -> 0 | I20: 257926 | J20: 45691
A21: 19 | B21: 1168 | C21: Mohammed Salim Said Jumaa Al Kathiri | D21: 581.5 | E21: 0.4 | F21: =D21*E21 -> 232.6 | G21: =F21 -> 232.6 | H21: =F21-G21 -> 0 | I21: 15498714 | J21: 45691
A22: 20 | B22: 1177 | C22: Said Salim Said BaitSaid | D22: 399 | E22: 0.4 | F22: =D22*E22 -> 159.6 | G22: =F22 -> 159.6 | H22: =F22-G22 -> 0 | I22: 219353
A23: 21 | B23: 1178 | C23: Mohammed Said Mohammed Akdha Al Rawas | D23: 629.4 | E23: 0.4 | F23: =D23*E23 -> 251.76 | G23: =247.66+4.1 -> 251.76 | H23: =F23-G23 -> 0 | I23: 970872 | J23: 45607 | K23: 45656
A24: 22 | B24: 1224 | C24: Naif Masoud Awadh Nasib Kikab Al Shihri | D24: 743 | E24: 0.4 | F24: =D24*E24 -> 297.2 | G24: =294.81+2.39 -> 297.2 | H24: =F24-G24 -> 0 | I24: 24911691 | J24: 45644 | K24: 098-01-25
A25: 23 | B25: 1225 | C25: Naif Said Awadh Fadhl | D25: 610.5 | E25: 0.4 | F25: =D25*E25 -> 244.2 | G25: =F25 -> 244.2 | H25: =F25-G25 -> 0 | I25: 9642357
A26: 24 | B26: 1235 | C26: Saeed Abdul Aziz Abdullah Al kathiri | D26: 714 | E26: 0.4 | F26: =D26*E26 -> 285.6 | G26: =F26 -> 285.6 | H26: =F26-G26 -> 0 | I26: 1992436 | J26: 45609
A27: 25 | B27: 1241 | C27: Said Mohammed Abdallah Al kathiri | D27: 621.8 | E27: 0.4 | F27: =D27*E27 -> 248.72 | G27: =245.09+3.63 -> 248.72 | H27: =F27-G27 -> 0 | I27: 5343254 | J27: 45607 | K27: 45628
A28: 26 | B28: 1247 | C28: Said Salim Azad Bait Ali Badar | D28: 600 | E28: 0.4 | F28: =D28*E28 -> 240 | G28: =237.5+2.5 -> 240 | H28: =F28-G28 -> 0 | I28: 4748561 | J28: 45644 | K28: 45650
A29: 27 | B29: 1252 | C29: Said Ahmed Ali Bait Said | D29: 550 | E29: 0.4 | F29: =D29*E29 -> 220 | G29: =F29 -> 220 | H29: =F29-G29 -> 0 | I29: 2433959
A30: 28 | B30: 1258 | C30: Said Ali Musallam Al Noubi Al Kathiri | D30: 792 | E30: 0.4 | F30: =D30*E30 -> 316.8 | G30: =F30 -> 316.8 | H30: =F30-G30 -> 0 | I30: 1924174 | J30: 45644
A31: 29 | B31: 1260 | C31: Said Salim Ali Kibab Al Shahri | D31: 672 | E31: 0.4 | F31: =D31*E31 -> 268.8 | G31: =268.63+0.17 -> 268.8 | H31: =F31-G31 -> 0 | I31: 18363579 | J31: 45621 | K31: 45628
A32: 30 | B32: 1261 | C32: Said Ali Nasib Kikab Al shahri | D32: 380.7 | E32: 0.4 | F32: =D32*E32 -> 152.28 | G32: =149.63+2.65 -> 152.28 | H32: =F32-G32 -> 0 | I32: 14429332 | J32: 45623 | K32: 45637
A33: 31 | B33: 1268 | C33: Said Musallam Ali Ghawas | D33: 500 | E33: 0.4 | F33: =D33*E33 -> 200 | G33: =F33 -> 200 | H33: =F33-G33 -> 0 | I33: 722058 | J33: 45601
A34: 32 | B34: 1282 | C34: Salim Ali Musallam Al Noubi Al Kathiri | D34: 675 | E34: 0.4 | F34: =D34*E34 -> 270 | G34: =F34 -> 270 | H34: =F34-G34 -> 0 | I34: 2997747 | J34: 45621
A35: 33 | B35: 1284 | C35: Salim Ali Said Al Nubi Al Kathiri | D35: 648.5 | E35: 0.4 | F35: =D35*E35 -> 259.4 | G35: =256.7+2.7 -> 259.4 | H35: =F35-G35 -> 0 | I35: 1177598 | J35: 45602 | K35: 45635
A36: 34 | B36: 1300 | C36: Salem Suhail Omer Bit Fhadel | D36: 800 | E36: 0.4 | F36: =D36*E36 -> 320 | G36: =F36 -> 320 | H36: =F36-G36 -> 0 | I36: 19534277
A37: 35 | B37: 1306 | C37: Salim Ali Nasib Al Kathiri | D37: 393.8 | E37: 0.4 | F37: =D37*E37 -> 157.52 | G37: =157.22+0.3 -> 157.52 | H37: =F37-G37 -> 0 | I37: 2006904 | J37: 45600 | K37: 45630
A38: 36 | B38: 1315 | C38: Salim Said Ali Ghawas | D38: 336.2 | E38: 0.4 | F38: =D38*E38 -> 134.48 | G38: =F38 -> 134.48 | H38: =F38-G38 -> 0 | I38: 19528845
A39: 37 | B39: 1328 | C39: Suhail Saeed Suhail ghawas | D39: 438.2 | E39: 0.4 | F39: =D39*E39 -> 175.28 | G39: =172.56+2.72 -> 175.28 | H39: =F39-G39 -> 0 | I39: 782833 | J39: 45601 | K39: 45628
A40: 38 | B40: 1330 | C40: Said Mahad Ali Al Kathiri | D40: 646.2 | E40: 0.4 | F40: =D40*E40 -> 258.48 | G40: =F40 -> 258.48 | H40: =F40-G40 -> 0 | I40: 12194826 | J40: BT-29-01-25
A41: 39 | B41: 1331 | C41: Mohammed Said Musallam Al Noob Al Kathiri | D41: 375 | E41: 0.4 | F41: =D41*E41 -> 150 | G41: =F41 -> 150 | H41: =F41-G41 -> 0 | I41: 2107763 | J41: 45628
A42: 40 | B42: 1333 | C42: Suhail Salim Ahmed Al Nubi Al Kathiri | D42: 595 | E42: 0.4 | F42: =D42*E42 -> 238 | G42: =F42 -> 238 | H42: =F42-G42 -> 0 | I42: 1736679 | J42: 45691
A43: 41 | B43: 1382 | C43: Suhail Mohammed Said Ghawas Al Kathiri | D43: 725 | E43: 0.4 | F43: =D43*E43 -> 290 | G43: =287.95+2.05 -> 290 | H43: =F43-G43 -> 0 | I43: 886492 | J43: 45601 | K43: 45630
A44: 42 | B44: 1384 | C44: Abdul Selam Musallam Mohammed Al Rawas | D44: 242.8 | E44: 0.4 | F44: =D44*E44 -> 97.12 | G44: =F44 -> 97.12 | H44: =F44-G44 -> 0 | I44: 4426701 | J44: 45658
A45: 43 | B45: 1386 | C45: Omar Salim Ahmed Al Hadi Ba Omar | D45: 798.8 | E45: 0.4 | F45: =D45*E45 -> 319.52 | G45: =317.85+1.67 -> 319.52 | H45: =F45-G45 -> 0 | I45: 711799 | J45: 45621 | K45: 45650
A46: 44 | B46: 1387 | C46: Ali Said Mahisan Kayakab Al Shihri | D46: 675 | E46: 0.4 | F46: =D46*E46 -> 270 | G46: =F46 -> 270 | H46: =F46-G46 -> 0 | I46: 6759716 | J46: 45686
A47: 45 | B47: 1388 | C47: Tarik Suhail Salim Al Kathiri | D47: 399.3 | E47: 0.4 | F47: =D47*E47 -> 159.72 | G47: =156.63+3.09 -> 159.72 | H47: =F47-G47 -> 0 | I47: 18610874 | J47: 45600 | K47: 45621
A48: 46 | B48: 1389 | C48: Ali Said Musallam Al Noubi Al Kathiri | D48: 1000 | E48: 0.4 | F48: =D48*E48 -> 400 | G48: =395.4+4.6 -> 400 | H48: =F48-G48 -> 0 | I48: 1036354 | J48: 45600 | K48: 45628
A49: 47 | B49: 1394 | C49: Ali Ahmed Salim Ahmed Al Kathiri | D49: 420.2 | E49: 0.4 | F49: =D49*E49 -> 168.08 | G49: =167.13+0.95 -> 168.08 | H49: =F49-G49 -> 0 | I49: 25656187 | J49: 45621 | K49: 45643
A50: 48 | B50: 1396 | C50: Mustahil Ali Azad Al Kathiri | D50: 427.3 | E50: 0.4 | F50: =D50*E50 -> 170.92 | G50: =F50 -> 170.92 | H50: =F50-G50 -> 0 | I50: 905845 | J50: 45650
A51: 49 | B51: 1397 | C51: Ahmed Musallam Amer Al Kathiri | D51: 361.8 | E51: 0.4 | F51: =D51*E51 -> 144.72 | G51: =143.27+1.42 -> 144.69 | H51: =F51-G51 -> 0.03 | I51: 1292885 | J51: 45656 | K51: 45677
A52: 50 | B52: 1398 | C52: Salim Amer Azad Al Kathiri | D52: 252.7 | E52: 0.4 | F52: =D52*E52 -> 101.08 | G52: =98.95+2.13 -> 101.08 | H52: =F52-G52 -> 0 | I52: 1161437 | J52: 45607 | K52: 45635
A53: 51 | B53: 1400 | C53: Manei Said Ahmed Al Kathiri | D53: 653 | E53: 0.4 | F53: =D53*E53 -> 261.2 | G53: =F53 -> 261.2 | H53: =F53-G53 -> 0 | I53: 7223707 | J53: 45691
A54: 52 | B54: 1403 | C54: Ali Salim Ahmed Al Nubi Al Kathiri | D54: 565.9 | E54: 0.4 | F54: =D54*E54 -> 226.36 | G54: =222.96+3.4 -> 226.36 | H54: =F54-G54 -> 0 | I54: 499044 | J54: 45607 | K54: 45635
A55: 53 | B55: 1406 | C55: Said Salim Musallam AlNoob Al Kathiri | D55: 498.1 | E55: 0.4 | F55: =D55*E55 -> 199.24 | G55: =2+197.24 -> 199.24 | H55: =F55-G55 -> 0 | I55: 880849 | J55: 45573 | K55: 45602
A56: 54 | B56: 1408 | C56: Abdullah Salim AhmedAl Hadi Ba Omar | D56: 1448 | E56: 0.4 | F56: =D56*E56 -> 579.2 | G56: =577.15+2.05 -> 579.2 | H56: =F56-G56 -> 0 | I56: 997465 | J56: 45656 | K56: 45810
A57: 55 | B57: 1409 | C57: Mahisan Ali Mahisan Al Shihri | D57: 569.2 | E57: 0.4 | F57: =D57*E57 -> 227.68 | G57: =226.62+1.06 -> 227.68 | H57: =F57-G57 -> 0 | I57: 7279409 | J57: 45621 | K57: 45642
A58: 56 | B58: 1410 | C58: Masoud Ali suhail Bait Said | D58: 615.4 | E58: 0.4 | F58: =D58*E58 -> 246.16 | G58: =244.99+1.17 -> 246.16 | H58: =F58-G58 -> 0 | I58: 757372 | J58: 45614 | K58: 45635
A59: 57 | B59: 1411 | C59: Said Ali Ahmed Amor Jid | D59: 673 | E59: 0.4 | F59: =D59*E59 -> 269.2 | G59: =268.35+0.85 -> 269.2 | H59: =F59-G59 -> 0 | I59: 1650389 | J59: 45601 | K59: 45628
A60: 58 | B60: 1412 | C60: Musallam Said Salim Bait Said | D60: 749 | E60: 0.4 | F60: =D60*E60 -> 299.6 | G60: =F60 -> 299.6 | H60: =F60-G60 -> 0 | I60: 312227
A61: 59 | B61: 1413 | C61: Awadh Salim Ali Ghawas | D61: 375 | E61: 0.4 | F61: =D61*E61 -> 150 | G61: =147.8+2.2 -> 150 | H61: =F61-G61 -> 0 | I61: 539906 | J61: 45607 | K61: 45628
A62: 60 | B62: 1414 | C62: Salim Said Ali Bait Said | D62: 1043.1 | E62: 0.4 | F62: =D62*E62 -> 417.24 | G62: =416.39+0.85 -> 417.24 | H62: =F62-G62 -> 0 | I62: 9178238 | J62: 45621 | K62: 45663
A63: 61 | B63: 1415 | C63: Salim ahmed Masoud Jumaa Al kathiri | D63: 285.3 | E63: 0.4 | F63: =D63*E63 -> 114.12 | G63: =F63 -> 114.12 | H63: =F63-G63 -> 0 | I63: 818787 | J63: 45643
A64: 62 | B64: 1417 | C64: Said Bakhit said Al mashikhi | D64: 543.9 | E64: 0.4 | F64: =D64*E64 -> 217.56 | G64: =F64 -> 217.56 | H64: =F64-G64 -> 0 | I64: 1252579 | J64: 45635
A65: 63 | B65: 1418 | C65: SALIM ALI MUSALLAM GHAWAS | D65: 312.6 | E65: 0.4 | F65: =D65*E65 -> 125.04 | G65: =F65 -> 125.04 | H65: =F65-G65 -> 0 | I65: 9954378 | J65: 45630
A66: 64 | B66: 1419 | C66: Mahad Masoud Salim Baitsaid | D66: 900 | E66: 0.4 | F66: =D66*E66 -> 360 | G66: =97+97+97+69 -> 360 | H66: =F66-G66 -> 0 | I66: 386821 | J66: 45602 | K66: 45609 | L66: 45621 | M66: 45628
A67: 65 | B67: 1420 | C67: Salim Said Salim Al Rawas | D67: 646.2 | E67: 0.4 | F67: =D67*E67 -> 258.48 | G67: =F67 -> 258.48 | H67: =F67-G67 -> 0 | I67: 5460297
A68: 66 | B68: 1421 | C68: Malik Musallam Salim Masoud Al Rawas | D68: 725 | E68: 0.4 | F68: =D68*E68 -> 290 | G68: =F68 -> 290 | H68: =F68-G68 -> 0 | I68: 15314262
A69: 67 | B69: 1423 | C69: Ahmed Said Ali Azad Al Kathiri | D69: 618.9 | E69: 0.4 | F69: =D69*E69 -> 247.56 | G69: =242.87+4.69 -> 247.56 | H69: =F69-G69 -> 0 | I69: 5044397 | J69: 45677 | K69: 45963
A70: 68 | B70: 1425 | C70: Salim Mohammed Ali Al Kathiri | D70: 564.2 | E70: 0.4 | F70: =D70*E70 -> 225.68 | G70: =F70 -> 225.68 | H70: =F70-G70 -> 0 | I70: 5614623 | J70: BT-29-01-25
A71: 69 | B71: 1426 | C71: Ahmed Salim Ahmed Said Al Nubi Al Kathiri | D71: 675 | E71: 0.4 | F71: =D71*E71 -> 270 | G71: =267.85+2.15 -> 270 | H71: =F71-G71 -> 0 | I71: 2160707 | J71: 45600 | K71: 45628
A72: 70 | B72: 1427 | C72: Salim Said Mohammed Musallam Al Nubi Al kathiri | D72: 334.2 | E72: 0.4 | F72: =D72*E72 -> 133.68 | G72: =F72 -> 133.68 | H72: =F72-G72 -> 0 | I72: 24171637 | J72: 45665
A73: 71 | B73: 1428 | C73: Abdullah Said Abdullah Alkthiri | D73: 347.5 | E73: 0.4 | F73: =D73*E73 -> 139 | G73: =137.59+1.41 -> 139 | H73: =F73-G73 -> 0 | I73: 921364 | J73: 45600 | K73: 45623
A74: 72 | B74: 1430 | C74: Ahmed Said Mohammed Houmdi Al Siari | D74: 346.3 | E74: 0.4 | F74: =D74*E74 -> 138.52 | G74: =137.64+0.88 -> 138.52 | H74: =F74-G74 -> 0 | I74: 564698 | J74: 45600 | K74: 45621
A75: 73 | B75: 1432 | C75: Ali Ahmed Ali Sajlil Al shanfari | D75: 825 | E75: 0.4 | F75: =D75*E75 -> 330 | G75: =F75 -> 330 | H75: =F75-G75 -> 0 | I75: 5004855
A76: 74 | B76: 1433 | C76: Ali Said Ali Bait Said | D76: 825 | E76: 0.4 | F76: =D76*E76 -> 330 | G76: =270+60 -> 330 | H76: =F76-G76 -> 0 | I76: 285841 | J76: DCF FEED | K76: 45684
A77: 75 | B77: 1434 | C77: Muhssin Said Mohammed Ghawas | D77: 383.1 | E77: 0.4 | F77: =D77*E77 -> 153.24 | G77: =149.57+3.67 -> 153.24 | H77: =F77-G77 -> 0 | I77: 19197503 | J77: 45656 | K77: 45710
A78: 76 | B78: 1435 | C78: Salim Said aoubad Ghawas | D78: 1076.2 | E78: 0.4 | F78: =D78*E78 -> 430.48 | G78: =425.9+4.58 -> 430.48 | H78: =F78-G78 -> 0 | I78: 1305522 | J78: 45623 | K78: 45643
A79: 77 | B79: 1437 | C79: Ahmed Ali Ahmed Shadar Al Kathiri | D79: 725 | E79: 0.4 | F79: =D79*E79 -> 290 | G79: =285.49+4.51 -> 290 | H79: =F79-G79 -> 0 | I79: 9685144 | J79: 45614 | K79: 45658
A80: 78 | B80: 1438 | C80: Salim Aubad Al Maslamin Al Mashali | D80: 1098 | E80: 0.4 | F80: =D80*E80 -> 439.2 | G80: =432.55+6.65 -> 439.2 | H80: =F80-G80 -> 0 | I80: 656621 | J80: 11/12/2024 - 24-12-2024
A81: 79 | B81: 1439 | C81: Ahmed Musallam Salim Al Kathiri | D81: 469 | E81: 0.4 | F81: =D81*E81 -> 187.6 | G81: =F81 -> 187.6 | H81: =F81-G81 -> 0 | I81: 18880548 | J81: 45621
A82: 80 | B82: 1441 | C82: Ahmed Said Amer Al Kathiri | D82: 599 | E82: 0.4 | F82: =D82*E82 -> 239.6 | G82: =F82 -> 239.6 | H82: =F82-G82 -> 0 | I82: 7285573 | J82: 45650
A83: 81 | B83: 1444 | C83: Masoud Musallam Masoud Baitsaid | D83: 849 | E83: 0.4 | F83: =D83*E83 -> 339.6 | G83: =F83 -> 339.6 | H83: =F83-G83 -> 0 | I83: 13487202
A84: 82 | B84: 1448 | C84: Salim Said Masoud Said Al Kathiri | D84: 316.3 | E84: 0.4 | F84: =D84*E84 -> 126.52 | G84: =125.68+0.84 -> 126.52 | H84: =F84-G84 -> 0 | I84: 26433121 | J84: 45656
A85: 83 | B85: 1451 | C85: Maneef Ali Abdullah Ghawas | D85: 397 | E85: 0.4 | F85: =D85*E85 -> 158.8 | G85: =61.45+97+0.35 -> 158.8 | H85: =F85-G85 -> 0 | I85: 20337612 | J85: 45609 | K85: 45623 | L85: 45637
A86: 84 | B86: 1453 | C86: Ahmed Said Salim Al Rawas | D86: 351.9 | E86: 0.4 | F86: =D86*E86 -> 140.76 | G86: =139.1+1.66 -> 140.76 | H86: =F86-G86 -> 0 | I86: 5460259 | J86: 45607 | K86: 45637
A87: 85 | B87: 1455 | C87: Thuwaini Ali Musallam Ghawas | D87: 707.3 | E87: 0.4 | F87: =D87*E87 -> 282.92 | G87: =132.64+133.75+16.53 -> 282.92 | H87: =F87-G87 -> 0 | I87: 9954383 | J87: 45637 | K87: 45642 | L87: 45644
A88: 86 | B88: 1462 | C88: Mohammed Suhail Mohammed Ghawas | D88: 375 | E88: 0.4 | F88: =D88*E88 -> 150 | G88: =146.25+3.75 -> 150 | H88: =F88-G88 -> 0 | I88: 9664038 | J88: 45601 | K88: 45630
A89: 87 | B89: 1463 | C89: Said Salim Ali Aazad Al Kathiri | D89: 576.6 | E89: 0.4 | F89: =D89*E89 -> 230.64 | G89: =F89 -> 230.64 | H89: =F89-G89 -> 0 | I89: 3798072 | J89: 45643
A90: 88 | B90: 1464 | C90: Ahmed Hamid Mohammed Zidi Bait Said | D90: 700 | E90: 0.4 | F90: =D90*E90 -> 280 | G90: =F90 -> 280 | H90: =F90-G90 -> 0 | I90: 6352996
A91: 89 | B91: 1467 | C91: Salim Suhail Ali Al Kathiri | D91: 480.5 | E91: 0.4 | F91: =D91*E91 -> 192.2 | G91: =F91 -> 192.2 | H91: =F91-G91 -> 0 | I91: 4279933
A92: 90 | B92: 1468 | C92: Ahmed Salim Ahmed Al Kathiri | D92: 724 | E92: 0.4 | F92: =D92*E92 -> 289.6 | G92: =286.86+2.74 -> 289.6 | H92: =F92-G92 -> 0 | I92: 6996485 | J92: 45642 | K92: 45684
A93: 91 | B93: 1472 | C93: Rams Musallam Said Ghawas | D93: 655.6 | E93: 0.4 | F93: =D93*E93 -> 262.24 | G93: =F93 -> 262.24 | H93: =F93-G93 -> 0 | I93: 962967
A94: 92 | B94: 1473 | C94: Salim Said Mahad Alshakal Al Kathiri | D94: 648.7 | E94: 0.4 | F94: =D94*E94 -> 259.48 | G94: =F94 -> 259.48 | H94: =F94-G94 -> 0 | I94: 18722784
A95: 93 | B95: 1475 | C95: Musallam Said Ahmed Al kathiri | D95: 382.2 | E95: 0.4 | F95: =D95*E95 -> 152.88 | G95: =149.13+3.75 -> 152.88 | H95: =F95-G95 -> 0 | I95: 4584011 | J95: 45684 | K95: 45691
A96: 94 | B96: 1476 | C96: Ali Masoud Said Al Shahri | D96: 363.3 | E96: 0.4 | F96: =D96*E96 -> 145.32 | G96: =143.08+2.24 -> 145.32 | H96: =F96-G96 -> 0 | I96: 5486858 | J96: 45607 | K96: 45621
A97: 95 | B97: 1477 | C97: Salim Mohammed Mahad Al Kathiri | D97: 364.6 | E97: 0.4 | F97: =D97*E97 -> 145.84 | G97: =F97 -> 145.84 | H97: =F97-G97 -> 0 | I97: 18656494 | J97: 45691
A98: 96 | B98: 1480 | C98: Mohsin Ali Mahisan Houmdi Al Siari | D98: 373 | E98: 0.4 | F98: =D98*E98 -> 149.2 | G98: =F98 -> 149.2 | H98: =F98-G98 -> 0 | I98: 19820777 | J98: 45684
A99: 97 | B99: 1482 | C99: Ahmed Abdullah Ahmed Qatmem Al marhoon | D99: 596.5 | E99: 0.4 | F99: =D99*E99 -> 238.6 | G99: =F99 -> 238.6 | H99: =F99-G99 -> 0 | I99: 4024306 | J99: 45691
A100: 98 | B100: 1485 | C100: Salim Ali Mustahil Asat Al Shihri | D100: 425 | E100: 0.4 | F100: =D100*E100 -> 170 | G100: =168.39+1.61 -> 170 | H100: =F100-G100 -> 0 | I100: 18585573 | J100: 45607 | K100: 45621
...

Sheet center-Sept
A1: Milk Chilling Centre(Ghado) - Monthly Camel Milk Procurement Report - 01-09-2024 TO 30-09-2024
A2: SR. NO. | B2: Farmer Code | C2: Farmer Name | D2: Total Quantity Supplied(Lits) | E2: Camel Milk Price/Lit(OMR) | F2: Total Value Milk (OMR) | G2: Paid | H2: Balance | I2: ID No: | J2: Remarks
A3: 1 | B3: 1001 | C3: Abdul Hakim Musallam Salim Al Katini Al Rawas | D3: 263.5 | E3: 0.4 | F3: =D3*E3 -> 105.4 | G3: =F3 -> 105.4 | H3: =F3-G3 -> 0 | I3: 2130934 | J3: 45672
A4: 2 | B4: 1007 | C4: Ahmed Abdullah Said Al Rawas | D4: 1547.5 | E4: 0.4 | F4: =D4*E4 -> 619 | G4: =613.53+5.47 -> 619 | H4: =F4-G4 -> 0 | I4: 1515504 | J4: 45630 | K4: 45650
A5: 3 | B5: 1028 | C5: Ahmed Saeed Maatouq Al kathiri | D5: 284 | E5: 0.4 | F5: =D5*E5 -> 113.6 | H5: =F5-G5 -> 113.6 | I5: 802875
A6: 4 | B6: 1033 | C6: Ahmed Said Ali Al Nobi Al Kathiri | D6: 660 | E6: 0.4 | F6: =D6*E6 -> 264 | G6: =F6 -> 264 | H6: =F6-G6 -> 0 | I6: 10132435 | J6: 45622 | K6: .41 deduct from oct
A7: 5 | B7: 1040 | C7: Ahmed Said Mahad Jamaan Dhishil al Kathiri | D7: 283.5 | E7: 0.4 | F7: =D7*E7 -> 113.4 | G7: =0.95 -> 0.95 | H7: =F7-G7 -> 112.45 | I7: 25082374 | J7: 45684
A8: 6 | B8: 1044 | C8: Ahmed Salim Ahmed Al Hadi Baomar | D8: 328.8 | E8: 0.4 | F8: =D8*E8 -> 131.52 | H8: =F8-G8 -> 131.52 | I8: 81904
A9: 7 | B9: 1080 | C9: Ali Saeed Matoq Alkthiri | D9: 301.5 | E9: 0.4 | F9: =D9*E9 -> 120.6 | G9: =F9 -> 120.6 | H9: =F9-G9 -> 0 | I9: 78762 | J9: 45963
A10: 8 | B10: 1089 | C10: Ali Said Nasib | D10: 491.5 | E10: 0.4 | F10: =D10*E10 -> 196.6 | G10: =193.11+3.49 -> 196.6 | H10: =F10-G10 -> 0 | I10: 892683 | J10: 45644 | K10: 45686
A11: 9 | B11: 1096 | C11: Ali Salim Awadh Al Kathiri | D11: 393.4 | E11: 0.4 | F11: =D11*E11 -> 157.36 | G11: =154.63+2.73 -> 157.36 | H11: =F11-G11 -> 0 | I11: 1959918 | J11: 45623 | K11: 45658
A12: 10 | B12: 1106 | C12: Badar Said Masood Al Kathiri | D12: 968 | E12: 0.4 | F12: =D12*E12 -> 387.2 | H12: =F12-G12 -> 387.2 | I12: 5502751
A13: 11 | B13: 1110 | C13: Bakhit Salim Azad Al Kathiri | D13: 498 | E13: 0.4 | F13: =D13*E13 -> 199.2 | G13: =195.75+3.45 -> 199.2 | H13: =F13-G13 -> 0 | I13: 934298 | J13: 45628 | K13: 45658
A14: 12 | B14: 1111 | C14: Bakhit Salim Ali Shadar Al Kathiri | D14: 574.7 | E14: 0.4 | F14: =D14*E14 -> 229.88 | H14: =F14-G14 -> 229.88 | I14: 15571992
A15: 13 | B15: 1119 | C15: Ghanim Abdul Aziz Masoud Abdul Aziz Alash Al Kathiri | D15: 246.5 | E15: 0.4 | F15: =D15*E15 -> 98.6 | H15: =F15-G15 -> 98.6 | I15: 24000245
A16: 14 | B16: 1122 | C16: Hamed Hilal Said Al Kathiri | D16: 306.5 | E16: 0.4 | F16: =D16*E16 -> 122.6 | G16: =120.58+2.02 -> 122.6 | H16: =F16-G16 -> 0 | I16: 5219876 | J16: 45643 | K16: 45658
A17: 15 | B17: 1135 | C17: Khalid Said Ali Al Kathiri | D17: 591.6 | E17: 0.4 | F17: =D17*E17 -> 236.64 | G17: =0.39+232.8+3.45 -> 236.64 | H17: =F17-G17 -> 0 | I17: 19202954 | J17: 45628 | K17: 45643 | L17: 45665
A18: 16 | B18: 1141 | C18: Malik Said Ahmed Habkook Hat Al Shahri | D18: 523.8 | E18: 0.4 | F18: =D18*E18 -> 209.52 | G18: =208.42+1.1 -> 209.52 | H18: =F18-G18 -> 0 | I18: 11753992 | J18: 45644 | K18: 45658
A19: 17 | B19: 1154 | C19: Mohammed Salim Abdullah Al kathiri | D19: 800 | E19: 0.4 | F19: =D19*E19 -> 320 | H19: =F19-G19 -> 320 | I19: 18654817
A20: 18 | B20: 1161 | C20: Mohammed Ali Musallam Al Nubi Al Kathiri | D20: 330 | E20: 0.4 | F20: =D20*E20 -> 132 | G20: =129.55+2.45 -> 132 | H20: =F20-G20 -> 0 | I20: 257926 | J20: 45691 | K20: 45810
A21: 19 | B21: 1168 | C21: Mohammed Salim Said Jumaa Al Kathiri | D21: 525.2 | E21: 0.4 | F21: =D21*E21 -> 210.08 | G21: =F21 -> 210.08 | H21: =F21-G21 -> 0 | I21: 15498714 | J21: 45691
A22: 20 | B22: 1177 | C22: Said Salim Said BaitSaid | D22: 336 | E22: 0.4 | F22: =D22*E22 -> 134.4 | H22: =F22-G22 -> 134.4 | I22: 219353
A23: 21 | B23: 1178 | C23: Mohammed Said Mohammed Akdha Al Rawas | D23: 585.6 | E23: 0.4 | F23: =D23*E23 -> 234.24 | G23: =233.55+0.69 -> 234.24 | H23: =F23-G23 -> 0 | I23: 970872 | J23: 45656 | K23: 45664
A24: 22 | B24: 1224 | C24: Naif Masoud Awadh Nasib Kikab Al Shihri | D24: 678.5 | E24: 0.4 | F24: =D24*E24 -> 271.4 | G24: =269.21+2.19 -> 271.4 | H24: =F24-G24 -> 0 | I24: 24911691 | J24: 45665 | K24: 45686
A25: 23 | B25: 1225 | C25: Naif Said Awadh Fadhl | D25: 563.2 | E25: 0.4 | F25: =D25*E25 -> 225.28 | H25: =F25-G25 -> 225.28 | I25: 9642357
A26: 24 | B26: 1235 | C26: Saeed Abdul Aziz Abdullah Al kathiri | D26: 607.3 | E26: 0.4 | F26: =D26*E26 -> 242.92 | G26: =242.55 -> 242.55 | H26: =F26-G26 -> 0.37 | I26: 1992436 | J26: 45658
A27: 25 | B27: 1241 | C27: Said Mohammed Abdallah Al kathiri | D27: 548.6 | E27: 0.4 | F27: =D27*E27 -> 219.44 | G27: =218.87+0.57 -> 219.44 | H27: =F27-G27 -> 0 | I27: 5343254 | J27: 45628 | K27: 45645
A28: 26 | B28: 1247 | C28: Said Salim Azad Bait Ali Badar | D28: 528 | E28: 0.4 | F28: =D28*E28 -> 211.2 | G28: =210.9+0.3 -> 211.2 | H28: =F28-G28 -> 0 | I28: 4748561 | J28: 45650 | K28: 45665
A29: 27 | B29: 1252 | C29: Said Ahmed Ali Bait Said | D29: 478.5 | E29: 0.4 | F29: =D29*E29 -> 191.4 | H29: =F29-G29 -> 191.4 | I29: 2433959
A30: 28 | B30: 1258 | C30: Said Ali Musallam Al Noubi Al Kathiri | D30: 683.3 | E30: 0.4 | F30: =D30*E30 -> 273.32 | G30: =269.53+3.79 -> 273.32 | H30: =F30-G30 -> 0 | I30: 1924174 | J30: 45644 | K30: 45658
A31: 29 | B31: 1260 | C31: Said Salim Ali Kibab Al Shahri | D31: 616 | E31: 0.4 | F31: =D31*E31 -> 246.4 | G31: =F31 -> 246.4 | H31: =F31-G31 -> 0 | I31: 18363579 | J31: 45628 | L31: .030 deduct from oct 2024
A32: 30 | B32: 1261 | C32: Said Ali Nasib Kikab Al shahri | D32: 333.9 | E32: 0.4 | F32: =D32*E32 -> 133.56 | G32: =133.15+0.41 -> 133.56 | H32: =F32-G32 -> 0 | I32: 14429332 | J32: 45637 | K32: 45658
A33: 31 | B33: 1268 | C33: Said Musallam Ali Ghawas | D33: 440 | E33: 0.4 | F33: =D33*E33 -> 176 | G33: =F33 -> 176 | H33: =G33-F33 -> 0 | I33: 722058 | J33: 109-05-11-24
A34: 32 | B34: 1282 | C34: Salim Ali Musallam Al Noubi Al Kathiri | D34: 594 | E34: 0.4 | F34: =D34*E34 -> 237.6 | G34: =234.4+3.2 -> 237.6 | H34: =F34-G34 -> 0 | I34: 2997747 | J34: 45621 | K34: 45656
A35: 33 | B35: 1284 | C35: Salim Ali Said Al Nubi Al Kathiri | D35: 571.2 | E35: 0.4 | F35: =D35*E35 -> 228.48 | G35: =225.25+3.23 -> 228.48 | H35: =F35-G35 -> 0 | I35: 1177598 | J35: 45635 | K35: 45663
A36: 34 | B36: 1300 | C36: Salem Suhail Omer Bit Fhadel | D36: 666.1 | E36: 0.4 | F36: =D36*E36 -> 266.44 | H36: =F36-G36 -> 266.44 | I36: 19534277
A37: 35 | B37: 1306 | C37: Salim Ali Nasib Al Kathiri | D37: 344.7 | E37: 0.4 | F37: =D37*E37 -> 137.88 | G37: =135.5+2.38 -> 137.88 | H37: =F37-G37 -> 0 | I37: 2006904 | J37: 45630 | K37: 45663
A38: 36 | B38: 1315 | C38: Salim Said Ali Ghawas | D38: 285.5 | E38: 0.4 | F38: =D38*E38 -> 114.2 | H38: =F38-G38 -> 114.2 | I38: 19528845
A39: 37 | B39: 1328 | C39: Suhail Saeed Suhail ghawas | D39: 396.7 | E39: 0.4 | F39: =D39*E39 -> 158.68 | G39: =157.33+1.35 -> 158.68 | H39: =F39-G39 -> 0 | I39: 782833 | J39: 45628 | K39: 45658
A40: 38 | B40: 1330 | C40: Said Mahad Ali Al Kathiri | D40: 550.8 | E40: 0.4 | F40: =D40*E40 -> 220.32 | G40: =F40 -> 220.32 | H40: =F40-G40 -> 0 | I40: 12194826 | J40: 45810
A41: 39 | B41: 1331 | C41: Mohammed Said Musallam Al Noob Al Kathiri | D41: 328 | E41: 0.4 | F41: =D41*E41 -> 131.2 | G41: =128.62+2.58 -> 131.2 | H41: =F41-G41 -> 0 | I41: 2107763 | J41: 45628 | K41: 45679
A42: 40 | B42: 1333 | C42: Suhail Salim Ahmed Al Nubi Al Kathiri | D42: 510.6 | E42: 0.4 | F42: =D42*E42 -> 204.24 | G42: =202.36 -> 202.36 | H42: =F42-G42 -> 1.88 | I42: 1736679 | J42: 45691
A43: 41 | B43: 1382 | C43: Suhail Mohammed Said Ghawas Al Kathiri | D43: 630 | E43: 0.4 | F43: =D43*E43 -> 252 | G43: =250.15+1.85 -> 252 | H43: =F43-G43 -> 0 | I43: 886492 | J43: 45630 | K43: 45658
A44: 42 | B44: 1384 | C44: Abdul Selam Musallam Mohammed Al Rawas | D44: 293.6 | E44: 0.4 | F44: =D44*E44 -> 117.44 | G44: =9+106.7+1.74 -> 117.44 | H44: =F44-G44 -> 0 | I44: 4426701 | J44: 45658 | K44: 45663 | L44: 45679
A45: 43 | B45: 1386 | C45: Omar Salim Ahmed Al Hadi Ba Omar | D45: 669.4 | E45: 0.4 | F45: =D45*E45 -> 267.76 | G45: =265.08+2.68 -> 267.76 | H45: =F45-G45 -> 0 | I45: 711799 | J45: 45650 | K45: 45658
A46: 44 | B46: 1387 | C46: Ali Said Mahisan Kayakab Al Shihri | D46: 592 | E46: 0.4 | F46: =D46*E46 -> 236.8 | G46: =234.4 -> 234.4 | H46: =F46-G46 -> 2.4 | I46: 6759716 | J46: 45686
A47: 45 | B47: 1388 | C47: Tarik Suhail Salim Al Kathiri | D47: 352 | E47: 0.4 | F47: =D47*E47 -> 140.8 | G47: =137.56 -> 137.56 | H47: =F47-G47 -> 3.24 | I47: 18610874 | J47: 45621
A48: 46 | B48: 1389 | C48: Ali Said Musallam Al Noubi Al Kathiri | D48: 880 | E48: 0.4 | F48: =D48*E48 -> 352 | G48: =349.45+2.55 -> 352 | H48: =F48-G48 -> 0 | I48: 1036354 | J48: 45628 | K48: 45658
A49: 47 | B49: 1394 | C49: Ali Ahmed Salim Ahmed Al Kathiri | D49: 366.7 | E49: 0.4 | F49: =D49*E49 -> 146.68 | G49: =144.55+2.13 -> 146.68 | H49: =F49-G49 -> 0 | I49: 25656187 | J49: 45643 | K49: 45663
A50: 48 | B50: 1396 | C50: Mustahil Ali Azad Al Kathiri | D50: 384.2 | E50: 0.4 | F50: =D50*E50 -> 153.68 | G50: =0.21+150.35+3.12 -> 153.68 | H50: =F50-G50 -> 0 | I50: 905845 | J50: 45650 | K50: 45656 | L50: 45672
A51: 49 | B51: 1397 | C51: Ahmed Musallam Amer Al Kathiri | D51: 298.3 | E51: 0.4 | F51: =D51*E51 -> 119.32 | G51: =F51 -> 119.32 | H51: =F51-G51 -> 0 | I51: 1292885 | J51: 45677
A52: 50 | B52: 1398 | C52: Salim Amer Azad Al Kathiri | D52: 244.6 | E52: 0.4 | F52: =D52*E52 -> 97.84 | G52: =94.87+2.97 -> 97.84 | H52: =F52-G52 -> 0 | I52: 1161437 | J52: 45635 | K52: 45665
A53: 51 | B53: 1400 | C53: Manei Said Ahmed Al Kathiri | D53: 542.5 | E53: 0.4 | F53: =D53*E53 -> 217 | G53: =F53 -> 217 | H53: =F53-G53 -> 0 | I53: 7223707 | L53: 45691
A54: 52 | B54: 1403 | C54: Ali Salim Ahmed Al Nubi Al Kathiri | D54: 486.6 | E54: 0.4 | F54: =D54*E54 -> 194.64 | G54: =190.6+4.04 -> 194.64 | H54: =F54-G54 -> 0 | I54: 499044 | J54: 45635 | K54: 45663
A55: 53 | B55: 1406 | C55: Said Salim Musallam AlNoob Al Kathiri | D55: 440 | E55: 0.4 | F55: =D55*E55 -> 176 | G55: =1.61+169.75+4.64 -> 176 | H55: =F55-G55 -> 0 | I55: 880849 | J55: 45602 | K55: 45630 | L55: 45663
A56: 54 | B56: 1408 | C56: Abdullah Salim AhmedAl Hadi Ba Omar | D56: 1269.6 | E56: 0.4 | F56: =D56*E56 -> 507.84 | G56: =507.2 -> 507.2 | H56: =F56-G56 -> 0.64 | I56: 997465 | J56: 45810
A57: 55 | B57: 1409 | C57: Mahisan Ali Mahisan Al Shihri | D57: 499.4 | E57: 0.4 | F57: =D57*E57 -> 199.76 | G57: =197.89+1.87 -> 199.76 | H57: =F57-G57 -> 0 | I57: 7279409 | J57: 45642 | K57: 45658
A58: 56 | B58: 1410 | C58: Masoud Ali suhail Bait Said | D58: 534.1 | E58: 0.4 | F58: =D58*E58 -> 213.64 | G58: =212.23+1.41 -> 213.64 | H58: =F58-G58 -> 0 | I58: 757372 | J58: 45635 | K58: 45663
A59: 57 | B59: 1411 | C59: Said Ali Ahmed Amor Jid | D59: 592 | E59: 0.4 | F59: =D59*E59 -> 236.8 | G59: =234.05+2.75 -> 236.8 | H59: =F59-G59 -> 0 | I59: 1650389 | J59: 45628 | K59: 45663
A60: 58 | B60: 1412 | C60: Musallam Said Salim Bait Said | D60: 660 | E60: 0.4 | F60: =D60*E60 -> 264 | H60: =F60-G60 -> 264 | I60: 312227
A61: 59 | B61: 1413 | C61: Awadh Salim Ali Ghawas | D61: 327.5 | E61: 0.4 | F61: =D61*E61 -> 131 | G61: =128.45+2.55 -> 131 | H61: =F61-G61 -> 0 | I61: 539906 | J61: 45628 | K61: 45658
A62: 60 | B62: 1414 | C62: Salim Said Ali Bait Said | D62: 956.3 | E62: 0.4 | F62: =D62*E62 -> 382.52 | G62: =F62 -> 382.52 | H62: =F62-G62 -> 0 | I62: 9178238 | J62: 45663
A63: 61 | B63: 1415 | C63: Ali Salim Ahmed Ali Badar al Kathiri | D63: 298.1 | E63: 0.4 | F63: =D63*E63 -> 119.24 | G63: =118.68+0.56 -> 119.24 | H63: =F63-G63 -> 0 | I63: 5334952 | J63: 45643 | K63: 45658
A64: 62 | B64: 1417 | C64: Said Bakhit said Al mashikhi | D64: 482.5 | E64: 0.4 | F64: =D64*E64 -> 193 | G64: =190.05+2.95 -> 193 | H64: =F64-G64 -> 0 | I64: 1252579 | J64: 45635 | K64: 45686
A65: 63 | B65: 1418 | C65: SALIM ALI MUSALLAM GHAWAS | D65: 290.2 | E65: 0.4 | F65: =D65*E65 -> 116.08 | G65: =115.71+0.37 -> 116.08 | H65: =F65-G65 -> 0 | I65: 9954378 | J65: 45630 | K65: 45656
A66: 64 | B66: 1419 | C66: Mahad Masoud Salim Baitsaid | D66: 792 | E66: 0.4 | F66: =D66*E66 -> 316.8 | G66: =13.45+303.35 -> 316.8 | H66: =F66-G66 -> 0 | I66: 386821 | J66: 45628 | K66: BT 26-12-2024
A67: 65 | B67: 1420 | C67: Salim Said Salim Al Rawas | D67: 577 | E67: 0.4 | F67: =D67*E67 -> 230.8 | H67: =F67-G67 -> 230.8 | I67: 5460297
A68: 66 | B68: 1421 | C68: Malik Musallam Salim Masoud Al Rawas | D68: 638 | E68: 0.4 | F68: =D68*E68 -> 255.2 | H68: =F68-G68 -> 255.2 | I68: 15314262
A69: 67 | B69: 1423 | C69: Ahmed Said Ali Azad Al Kathiri | D69: 562.8 | E69: 0.4 | F69: =D69*E69 -> 225.12 | G69: =F69 -> 225.12 | H69: =F69-G69 -> 0 | I69: 5044397 | J69: 45963
A70: 68 | B70: 1425 | C70: Salim Mohammed Ali Al Kathiri | D70: 500.9 | E70: 0.4 | F70: =D70*E70 -> 200.36 | G70: =F70 -> 200.36 | H70: =F70-G70 -> 0 | I70: 5614623 | J70: 45810
A71: 69 | B71: 1426 | C71: Ahmed Salim Ahmed Said Al Nubi Al Kathiri | D71: 574.3 | E71: 0.4 | F71: =D71*E71 -> 229.72 | G71: =225.8+3.92 -> 229.72 | H71: =F71-G71 -> 0 | I71: 2160707 | J71: 45628 | K71: 45658
A72: 70 | B72: 1427 | C72: Salim Said Mohammed Musallam Al Nubi Al kathiri | D72: 283.2 | E72: 0.4 | F72: =D72*E72 -> 113.28 | G72: =110.62+2.66 -> 113.28 | H72: =F72-G72 -> 0 | I72: 24171637 | J72: 45665 | K72: 45684
A73: 71 | B73: 1428 | C73: Abdullah Said Abdullah Alkthiri | D73: 304.5 | E73: 0.4 | F73: =D73*E73 -> 121.8 | G73: =121.64+0.16 -> 121.8 | H73: =F73-G73 -> 0 | I73: 921364 | J73: 45623 | K73: 45658
A74: 72 | B74: 1430 | C74: Ahmed Said Mohammed Houmdi Al Siari | D74: 290 | E74: 0.4 | F74: =D74*E74 -> 116 | G74: =115.52+0.48 -> 116 | H74: =F74-G74 -> 0 | I74: 564698 | J74: 45621 | K74: 45658
A75: 73 | B75: 1432 | C75: Ali Ahmed Ali Sajlil Al shanfari | D75: 726 | E75: 0.4 | F75: =D75*E75 -> 290.4 | H75: =F75-G75 -> 290.4 | I75: 5004855
A76: 74 | B76: 1433 | C76: Ali Said Ali Bait Said | D76: 726 | E76: 0.4 | F76: =D76*E76 -> 290.4 | G76: =F76 -> 290.4 | H76: =F76-G76 -> 0 | I76: 285841 | J76: DCF-27-01-25
A77: 75 | B77: 1434 | C77: Muhssin Said Mohammed Ghawas | D77: 347.3 | E77: 0.4 | F77: =D77*E77 -> 138.92 | G77: =136.98 -> 136.98 | H77: =F77-G77 -> 1.94 | I77: 19197503 | J77: 45679
A78: 76 | B78: 1435 | C78: Salim Said aoubad Ghawas | D78: 968 | E78: 0.4 | F78: =D78*E78 -> 387.2 | G78: =383.42+3.78 -> 387.2 | H78: =F78-G78 -> 0 | I78: 1305522 | J78: 45643 | K78: 45658
A79: 77 | B79: 1437 | C79: Ahmed Ali Ahmed Shadar Al Kathiri | D79: 636 | E79: 0.4 | F79: =D79*E79 -> 254.4 | G79: =82.79+171.61 -> 254.4 | H79: =F79-G79 -> 0 | I79: 9685144 | J79: 45644 | K79: 45658
A80: 78 | B80: 1438 | C80: Salim Aubad Al Maslamin Al Mashali | D80: 968 | E80: 0.4 | F80: =D80*E80 -> 387.2 | G80: =386.2+1 -> 387.2 | H80: =F80-G80 -> 0 | I80: 656621 | J80: 45650 | K80: 45670
A81: 79 | B81: 1439 | C81: Ahmed Musallam Salim Al Kathiri | D81: 460 | E81: 0.4 | F81: =D81*E81 -> 184 | G81: =93.36+87.3+3.34 -> 184 | H81: =F81-G81 -> 0 | I81: 18880548 | J81: 45621 | K81: 09/12/2024 - 26-12-2024
A82: 80 | B82: 1441 | C82: Ahmed Said Amer Al Kathiri | D82: 526.4 | E82: 0.4 | F82: =D82*E82 -> 210.56 | G82: =2.9+203.7+3.96 -> 210.56 | H82: =F82-G82 -> 0 | I82: 7285573 | J82: 45650 | K82: 45677 | L82: 45684
A83: 81 | B83: 1444 | C83: Masoud Musallam Masoud Baitsaid | D83: 748 | E83: 0.4 | F83: =D83*E83 -> 299.2 | H83: =F83-G83 -> 299.2 | I83: 13487202
A84: 82 | B84: 1448 | C84: Salim Said Masoud Said Al Kathiri | D84: 304.2 | E84: 0.4 | F84: =D84*E84 -> 121.68 | G84: =120.41 -> 120.41 | H84: =F84-G84 -> 1.27 | I84: 26433121 | J84: 13-2-25
A85: 83 | B85: 1451 | C85: Maneef Ali Abdullah Ghawas | D85: 351.3 | E85: 0.4 | F85: =D85*E85 -> 140.52 | G85: =140.3+0.22 -> 140.52 | H85: =F85-G85 -> 0 | I85: 20337612 | J85: 45637 | K85: 45672
A86: 84 | B86: 1453 | C86: Ahmed Said Salim Al Rawas | D86: 328.7 | E86: 0.4 | F86: =D86*E86 -> 131.48 | G86: =129.29+2.19 -> 131.48 | H86: =F86-G86 -> 0 | I86: 5460259 | J86: 45637 | K86: 45658
A87: 85 | B87: 1455 | C87: Thuwaini Ali Musallam Ghawas | D87: 682.3 | E87: 0.4 | F87: =D87*E87 -> 272.92 | G87: =90.47+107+74.9+0.55 -> 272.92 | H87: =F87-G87 -> 0 | I87: 9954383 | J87: 45644 | K87: 45656 | L87: 45663
A88: 86 | B88: 1462 | C88: Mohammed Suhail Mohammed Ghawas | D88: 331 | E88: 0.4 | F88: =D88*E88 -> 132.4 | G88: =132.05+0.35 -> 132.4 | H88: =F88-G88 -> 0 | I88: 9664038 | J88: 04/12/2024 - 25-12-2024 | K88: 45658
A89: 87 | B89: 1463 | C89: Said Salim Ali Aazad Al Kathiri | D89: 524.3 | E89: 0.4 | F89: =D89*E89 -> 209.72 | G89: =205.54+4.18 -> 209.72 | H89: =F89-G89 -> 0 | I89: 3798072 | J89: 45643 | K89: 45691
A90: 88 | B90: 1464 | C90: Ahmed Hamid Mohammed Zidi Bait Said | D90: 616 | E90: 0.4 | F90: =D90*E90 -> 246.4 | H90: =F90-G90 -> 246.4 | I90: 6352996
A91: 89 | B91: 1467 | C91: Salim Suhail Ali Al Kathiri | D91: 480.8 | E91: 0.4 | F91: =D91*E91 -> 192.32 | H91: =F91-G91 -> 192.32 | I91: 4279933
A92: 90 | B92: 1468 | C92: Ahmed Salim Ahmed Al Kathiri | D92: 640.1 | E92: 0.4 | F92: =D92*E92 -> 256.04 | G92: =F92 -> 256.04 | H92: =F92-G92 -> 0 | I92: 6996485 | J92: 45684
A93: 91 | B93: 1472 | C93: Salim Ramas Musallam Ghawas | D93: 575 | E93: 0.4 | F93: =D93*E93 -> 230 | H93: =F93-G93 -> 230 | I93: 12987814
A94: 92 | B94: 1473 | C94: Salim Said Mahad Alshakal Al Kathiri | D94: 543.2 | E94: 0.4 | F94: =D94*E94 -> 217.28 | H94: =F94-G94 -> 217.28 | I94: 18722784
A95: 93 | B95: 1475 | C95: Musallam Said Ahmed Al kathiri | D95: 343.9 | E95: 0.4 | F95: =D95*E95 -> 137.56 | G95: =F95 -> 137.56 | H95: =F95-G95 -> 0 | I95: 4584011 | J95: 45691
A96: 94 | B96: 1476 | C96: Ali Masoud Said Al Shahri | D96: 316 | E96: 0.4 | F96: =D96*E96 -> 126.4 | G96: =124.41+1.99 -> 126.4 | H96: =F96-G96 -> 0 | I96: 5486858 | J96: 45621 | K96: 45663
A97: 95 | B97: 1477 | C97: Salim Mohammed Mahad Al Kathiri | D97: 313.3 | E97: 0.4 | F97: =D97*E97 -> 125.32 | G97: =F97 -> 125.32 | H97: =F97-G97 -> 0 | I97: 18656494 | J97: 45691
A98: 96 | B98: 1480 | C98: Mohsin Ali Mahisan Houmdi Al Siari | D98: 313.7 | E98: 0.4 | F98: =D98*E98 -> 125.48 | G98: =F98 -> 125.48 | H98: =F98-G98 -> 0 | I98: 19820777 | J98: 45684
A99: 97 | B99: 1482 | C99: Ahmed Abdullah Ahmed Qatmem Al marhoon | D99: 460.5 | E99: 0.4 | F99: =D99*E99 -> 184.2 | G99: =F99 -> 184.2 | H99: =F99-G99 -> 0 | I99: 4024306 | J99: 45691
A100: 98 | B100: 1485 | C100: Salim Ali Mustahil Asat Al Shihri | D100: 370.5 | E100: 0.4 | F100: =D100*E100 -> 148.2 | G100: =145.5+2.7 -> 148.2 | H100: =F100-G100 -> 0 | I100: 18585573 | J100: 45635 | K100: 45663
...

Sheet Center-oct
A1: Milk Chilling Centre(Ghado) - Monthly Camel Milk Procurement Report - 01-10-2024 TO 31-10-2024
A2: SR. NO. | B2: Farmer Code | C2: Farmer Name | D2: Total Quantity Supplied(Lits) | E2: Camel Milk Price/Lit(OMR) | F2: Total Value (OMR) | G2: Paid | H2: Balance | I2: ID No: | J2: Remarks | K2: Remarks
A3: 1 | B3: 1001 | C3: Abdul Hakim Musallam Salim Al Katini Al Rawas | D3: 293.7 | E3: 0.4 | F3: =D3*E3 -> 117.48 | G3: =112.85+4.63 -> 117.48 | H3: =F3-G3 -> 0 | I3: 2130934 | J3: 45672 | K3: 45963
A4: 2 | B4: 1007 | C4: Ahmed Abdullah Said Al Rawas | D4: 1627.9 | E4: 0.4 | F4: =D4*E4 -> 651.16 | G4: =650.78+0.38 -> 651.16 | H4: =F4-G4 -> 0 | I4: 1515504 | J4: 45650 | K4: 45665
A5: 3 | B5: 1028 | C5: Ahmed Saeed Maatouq Al kathiri | D5: 290.8 | E5: 0.4 | F5: =D5*E5 -> 116.32 | H5: =F5-G5 -> 116.32 | I5: 802875
A6: 4 | B6: 1033 | C6: Ahmed Said Ali Al Nobi Al Kathiri | D6: 690 | E6: 0.4 | F6: =D6*E6 -> 276 | G6: =271.6+4.4 -> 276 | H6: =F6-G6 -> 0 | I6: 10132435 | J6: 45644 | K6: 45670
A7: 5 | B7: 1040 | C7: Ahmed Said Mahad Jamaan Dhishil al Kathiri | D7: 297 | E7: 0.4 | F7: =D7*E7 -> 118.8 | H7: =F7-G7 -> 118.8 | I7: 25082374
A8: 6 | B8: 1044 | C8: Ahmed Salim Ahmed Al Hadi Baomar | D8: 345 | E8: 0.4 | F8: =D8*E8 -> 138 | H8: =F8-G8 -> 138 | I8: 81904
A9: 7 | B9: 1080 | C9: Ali Saeed Matoq Alkthiri | D9: 315.3 | E9: 0.4 | F9: =D9*E9 -> 126.12 | G9: =121.9 -> 121.9 | H9: =F9-G9 -> 4.22 | I9: 78762 | J9: 45963
A10: 8 | B10: 1089 | C10: Ali Said Nasib | D10: 544 | E10: 0.4 | F10: =D10*E10 -> 217.6 | G10: =F10 -> 217.6 | H10: =F10-G10 -> 0 | I10: 892683 | J10: 45686
A11: 9 | B11: 1096 | C11: Ali Salim Awadh Al Kathiri | D11: 451.5 | E11: 0.4 | F11: =D11*E11 -> 180.6 | G11: =176.72+3.88 -> 180.6 | H11: =F11-G11 -> 0 | I11: 1959918 | J11: 45658 | K11: 45686
A12: 10 | B12: 1106 | C12: Badar Said Masood Al Kathiri | D12: 1012 | E12: 0.4 | F12: =D12*E12 -> 404.8 | H12: =F12-G12 -> 404.8 | I12: 5502751
A13: 11 | B13: 1110 | C13: Bakhit Salim Azad Al Kathiri | D13: 529 | E13: 0.4 | F13: =D13*E13 -> 211.6 | G13: =209.95+1.65 -> 211.6 | H13: =F13-G13 -> 0 | I13: 934298 | J13: 45658 | K13: 45679
A14: 12 | B14: 1111 | C14: Bakhit Salim Ali Shadar Al Kathiri | D14: 596.3 | E14: 0.4 | F14: =D14*E14 -> 238.52 | H14: =F14-G14 -> 238.52 | I14: 15571992
A15: 13 | B15: 1119 | C15: Ghanim Abdul Aziz Masoud Abdul Aziz Alash Al Kathiri | D15: 339.9 | E15: 0.4 | F15: =D15*E15 -> 135.96 | H15: =F15-G15 -> 135.96 | I15: 24000245
A16: 14 | B16: 1122 | C16: Hamed Hilal Said Al Kathiri | D16: 319.6 | E16: 0.4 | F16: =D16*E16 -> 127.84 | G16: =124.08+3.76 -> 127.84 | H16: =F16-G16 -> 0 | I16: 5219876 | J16: 45658 | K16: 45684
A17: 15 | B17: 1135 | C17: Khalid Said Ali Al Kathiri | D17: 595.7 | E17: 0.4 | F17: =D17*E17 -> 238.28 | G17: =234.2+0.48 -> 234.68 | H17: =F17-G17 -> 3.6 | I17: 19202954 | J17: 45665 | K17: 45684
A18: 16 | B18: 1141 | C18: Malik Said Ahmed Habkook Hat Al Shahri | D18: 437.8 | E18: 0.4 | F18: =D18*E18 -> 175.12 | G18: =173.2+1.92 -> 175.12 | H18: =F18-G18 -> 0 | I18: 11753992 | J18: 45658 | K18: 45679
A19: 17 | B19: 1154 | C19: Mohammed Salim Abdullah Al kathiri | D19: 917.8 | E19: 0.4 | F19: =D19*E19 -> 367.12 | H19: =F19-G19 -> 367.12 | I19: 18654817
A20: 18 | B20: 1161 | C20: Mohammed Ali Musallam Al Nubi Al Kathiri | D20: 339.3 | E20: 0.4 | F20: =D20*E20 -> 135.72 | G20: =F20 -> 135.72 | H20: =F20-G20 -> 0 | I20: 257926 | J20: 45810
A21: 19 | B21: 1168 | C21: Mohammed Salim Said Jumaa Al Kathiri | D21: 533.7 | E21: 0.4 | F21: =D21*E21 -> 213.48 | G21: =212.1 -> 212.1 | H21: =F21-G21 -> 1.38 | I21: 15498714 | J21: 45691
A22: 20 | B22: 1177 | C22: Said Salim Said BaitSaid | D22: 338.3 | E22: 0.4 | F22: =D22*E22 -> 135.32 | H22: =F22-G22 -> 135.32 | I22: 219353
A23: 21 | B23: 1178 | C23: Mohammed Said Mohammed Akdha Al Rawas | D23: 580.4 | E23: 0.4 | F23: =D23*E23 -> 232.16 | G23: =232.11+0.05 -> 232.16 | H23: =F23-G23 -> 0 | I23: 970872 | J23: 45664 | K23: 45685
A24: 22 | B24: 1224 | C24: Naif Masoud Awadh Nasib Kikab Al Shihri | D24: 713 | E24: 0.4 | F24: =D24*E24 -> 285.2 | G24: =283.96 -> 283.96 | H24: =F24-G24 -> 1.24 | I24: 24911691 | J24: 45686
A25: 23 | B25: 1225 | C25: Naif Said Awadh Fadhl | D25: 592.8 | E25: 0.4 | F25: =D25*E25 -> 237.12 | H25: =F25-G25 -> 237.12 | I25: 9642357
A26: 24 | B26: 1235 | C26: Saeed Abdul Aziz Abdullah Al kathiri | D26: 662 | E26: 0.4 | F26: =D26*E26 -> 264.8 | H26: =F26-G26 -> 264.8 | I26: 1992436
A27: 25 | B27: 1241 | C27: Said Mohammed Abdallah Al kathiri | D27: 579.6 | E27: 0.4 | F27: =D27*E27 -> 231.84 | G27: =230.78+1.06 -> 231.84 | H27: =F27-G27 -> 0 | I27: 5343254 | J27: 45645 | K27: 45684
A28: 26 | B28: 1247 | C28: Said Salim Azad Bait Ali Badar | D28: 552 | E28: 0.4 | F28: =D28*E28 -> 220.8 | G28: =217.95+2.85 -> 220.8 | H28: =F28-G28 -> 0 | I28: 4748561 | J28: 45665 | K28: 45679
A29: 27 | B29: 1252 | C29: Said Ahmed Ali Bait Said | D29: 505.2 | E29: 0.4 | F29: =D29*E29 -> 202.08 | H29: =F29-G29 -> 202.08 | I29: 2433959
A30: 28 | B30: 1258 | C30: Said Ali Musallam Al Noubi Al Kathiri | D30: 733 | E30: 0.4 | F30: =D30*E30 -> 293.2 | G30: =292.06+1.14 -> 293.2 | H30: =F30-G30 -> 0 | I30: 1924174 | J30: 45658 | K30: 45677
A31: 29 | B31: 1260 | C31: Said Salim Ali Kibab Al Shahri | D31: 642 | E31: 0.4 | F31: =D31*E31 -> 256.8 | G31: =255.4+1.4 -> 256.8 | H31: =F31-G31 -> 0 | I31: 18363579 | J31: 45663 | K31: 45684
A32: 30 | B32: 1261 | C32: Said Ali Nasib Kikab Al shahri | D32: 331.9 | E32: 0.4 | F32: =D32*E32 -> 132.76 | G32: =130.54+2.22 -> 132.76 | H32: =F32-G32 -> 0 | I32: 14429332 | J32: 45658 | K32: 45679
A33: 31 | B33: 1268 | C33: Said Musallam Ali Ghawas | D33: 460 | E33: 0.4 | F33: =D33*E33 -> 184 | G33: =179.45+4.55 -> 184 | H33: =F33-G33 -> 0 | I33: 722058 | J33: 45670 | K33: 45684
A34: 32 | B34: 1282 | C34: Salim Ali Musallam Al Noubi Al Kathiri | D34: 621 | E34: 0.4 | F34: =D34*E34 -> 248.4 | G34: =247.35+1.05 -> 248.4 | H34: =F34-G34 -> 0 | I34: 2997747 | J34: 45656 | K34: 45684
A35: 33 | B35: 1284 | C35: Salim Ali Said Al Nubi Al Kathiri | D35: 598 | E35: 0.4 | F35: =D35*E35 -> 239.2 | G35: =234.42+4.78 -> 239.2 | H35: =F35-G35 -> 0 | I35: 1177598 | J35: 45663 | K35: 45679
A36: 34 | B36: 1300 | C36: Salem Suhail Omer Bit Fhadel | D36: 733.7 | E36: 0.4 | F36: =D36*E36 -> 293.48 | H36: =F36-G36 -> 293.48 | I36: 19534277
A37: 35 | B37: 1306 | C37: Salim Ali Nasib Al Kathiri | D37: 363.7 | E37: 0.4 | F37: =D37*E37 -> 145.48 | G37: =143.12+2.36 -> 145.48 | H37: =F37-G37 -> 0 | I37: 2006904 | J37: 45663 | K37: 45684
A38: 36 | B38: 1315 | C38: Salim Said Ali Ghawas | D38: 263 | E38: 0.4 | F38: =D38*E38 -> 105.2 | H38: =F38-G38 -> 105.2 | I38: 19528845
A39: 37 | B39: 1328 | C39: Suhail Saeed Suhail ghawas | D39: 400.2 | E39: 0.4 | F39: =D39*E39 -> 160.08 | G39: =158.7+1.38 -> 160.08 | H39: =F39-G39 -> 0 | I39: 782833 | J39: 45658 | K39: 45686
A40: 38 | B40: 1330 | C40: Said Mahad Ali Al Kathiri | D40: 631.5 | E40: 0.4 | F40: =D40*E40 -> 252.6 | G40: =36.73+213.4 -> 250.13 | H40: =F40-G40 -> 2.47 | I40: 12194826 | J40: 45810 | K40: 13-2-25
A41: 39 | B41: 1331 | C41: Mohammed Said Musallam Al Noob Al Kathiri | D41: 344.8 | E41: 0.4 | F41: =D41*E41 -> 137.92 | G41: =F41 -> 137.92 | H41: =F41-G41 -> 0 | I41: 2107763 | J41: 45679
A42: 40 | B42: 1333 | C42: Suhail Salim Ahmed Al Nubi Al Kathiri | D42: 554 | E42: 0.4 | F42: =D42*E42 -> 221.6 | H42: =F42-G42 -> 221.6 | I42: 1736679
A43: 41 | B43: 1382 | C43: Suhail Mohammed Said Ghawas Al Kathiri | D43: 667 | E43: 0.4 | F43: =D43*E43 -> 266.8 | G43: =264.9+1.9 -> 266.8 | H43: =F43-G43 -> 0 | I43: 886492 | J43: 45658 | K43: 29-0125
A44: 42 | B44: 1384 | C44: Abdul Selam Musallam Mohammed Al Rawas | D44: 301.1 | E44: 0.4 | F44: =D44*E44 -> 120.44 | G44: =119.51+0.93 -> 120.44 | H44: =F44-G44 -> 0 | I44: 4426701 | J44: 45679 | K44: 45684
A45: 43 | B45: 1386 | C45: Omar Salim Ahmed Al Hadi Ba Omar | D45: 734.4 | E45: 0.4 | F45: =D45*E45 -> 293.76 | G45: =293.17+0.59 -> 293.76 | H45: =F45-G45 -> 0 | I45: 711799 | J45: 45658 | K45: 45677
A46: 44 | B46: 1387 | C46: Ali Said Mahisan Kayakab Al Shihri | D46: 621 | E46: 0.4 | F46: =D46*E46 -> 248.4 | H46: =F46-G46 -> 248.4 | I46: 6759716
A47: 45 | B47: 1388 | C47: Tarik Suhail Salim Al Kathiri | D47: 368 | E47: 0.4 | F47: =D47*E47 -> 147.2 | H47: =F47-G47 -> 147.2 | I47: 18610874
A48: 46 | B48: 1389 | C48: Ali Said Musallam Al Noubi Al Kathiri | D48: 920 | E48: 0.4 | F48: =D48*E48 -> 368 | G48: =366.05+1.95 -> 368 | H48: =F48-G48 -> 0 | I48: 1036354 | J48: 45658 | K48: 45686
A49: 47 | B49: 1394 | C49: Ali Ahmed Salim Ahmed Al Kathiri | D49: 364.5 | E49: 0.4 | F49: =D49*E49 -> 145.8 | G49: =143.37+2.43 -> 145.8 | H49: =F49-G49 -> 0 | I49: 25656187 | J49: 45663 | K49: 45684
A50: 48 | B50: 1396 | C50: Mustahil Ali Azad Al Kathiri | D50: 401.9 | E50: 0.4 | F50: =D50*E50 -> 160.76 | G50: =156.93+3.83 -> 160.76 | H50: =F50-G50 -> 0 | I50: 905845 | J50: 45679
A51: 49 | B51: 1397 | C51: Ahmed Musallam Amer Al Kathiri | D51: 327 | E51: 0.4 | F51: =D51*E51 -> 130.8 | G51: =126.58+4.22 -> 130.8 | H51: =F51-G51 -> 0 | I51: 1292885 | J51: 45677 | K51: 45686
A52: 50 | B52: 1398 | C52: Salim Amer Azad Al Kathiri | D52: 263 | E52: 0.4 | F52: =D52*E52 -> 105.2 | G52: =103.73+1.47 -> 105.2 | H52: =F52-G52 -> 0 | I52: 1161437 | J52: 45665 | K52: 45684
A53: 51 | B53: 1400 | C53: Manei Said Ahmed Al Kathiri | D53: 532.5 | E53: 0.4 | F53: =D53*E53 -> 213 | G53: =F53 -> 213 | H53: =F53-G53 -> 0 | I53: 7223707 | K53: 45691
A54: 52 | B54: 1403 | C54: Ali Salim Ahmed Al Nubi Al Kathiri | D54: 525 | E54: 0.4 | F54: =D54*E54 -> 210 | G54: =209.36+0.64 -> 210 | H54: =F54-G54 -> 0 | I54: 499044 | J54: 45663 | K54: 45963
A55: 53 | B55: 1406 | C55: Said Salim Musallam AlNoob Al Kathiri | D55: 444.6 | E55: 0.4 | F55: =D55*E55 -> 177.84 | G55: =174.81+3.03 -> 177.84 | H55: =F55-G55 -> 0 | I55: 880849 | J55: 45663 | K55: 45691
A56: 54 | B56: 1408 | C56: Abdullah Salim AhmedAl Hadi Ba Omar | D56: 1334 | E56: 0.4 | F56: =D56*E56 -> 533.6 | H56: =F56-G56 -> 533.6 | I56: 997465
A57: 55 | B57: 1409 | C57: Mahisan Ali Mahisan Al Shihri | D57: 521 | E57: 0.4 | F57: =D57*E57 -> 208.4 | G57: =206.03+2.37 -> 208.4 | H57: =F57-G57 -> 0 | I57: 7279409 | J57: 45658 | K57: 45809
A58: 56 | B58: 1410 | C58: Masoud Ali suhail Bait Said | D58: 574.2 | E58: 0.4 | F58: =D58*E58 -> 229.68 | G58: =225.64+4.04 -> 229.68 | H58: =F58-G58 -> 0 | I58: 757372 | J58: 45663 | K58: 45686
A59: 57 | B59: 1411 | C59: Said Ali Ahmed Amor Jid | D59: 573.5 | E59: 0.4 | F59: =D59*E59 -> 229.4 | G59: =225.2+4.2 -> 229.4 | H59: =F59-G59 -> 0 | I59: 1650389 | J59: 45663 | K59: 45677
A60: 58 | B60: 1412 | C60: Musallam Said Salim Bait Said | D60: 690 | E60: 0.4 | F60: =D60*E60 -> 276 | H60: =F60-G60 -> 276 | I60: 312227
A61: 59 | B61: 1413 | C61: Awadh Salim Ali Ghawas | D61: 346 | E61: 0.4 | F61: =D61*E61 -> 138.4 | G61: =138.1+0.3 -> 138.4 | H61: =F61-G61 -> 0 | I61: 539906 | J61: 45658 | K61: 45686
A62: 60 | B62: 1414 | C62: Salim Said Ali Bait Said | D62: 1029.5 | E62: 0.4 | F62: =D62*E62 -> 411.8 | G62: =407.185+4.615 -> 411.8 | H62: =F62-G62 -> 0 | I62: 9178238 | J62: 45663 | K62: 45684
A63: 61 | B63: 1415 | C63: Salim ahmed Masoud Jumaa Al kathiri | D63: 314.8 | E63: 0.4 | F63: =D63*E63 -> 125.92 | G63: =125.54+0.38 -> 125.92 | H63: =F63-G63 -> 0 | I63: 818787 | J63: 45658 | K63: 45672
A64: 62 | B64: 1417 | C64: Said Bakhit said Al mashikhi | D64: 486 | E64: 0.4 | F64: =D64*E64 -> 194.4 | G64: =F64 -> 194.4 | H64: =F64-G64 -> 0 | I64: 1252579 | J64: 45686
A65: 63 | B65: 1418 | C65: SALIM ALI MUSALLAM GHAWAS | D65: 288.7 | E65: 0.4 | F65: =D65*E65 -> 115.48 | G65: =111.18+4.3 -> 115.48 | H65: =F65-G65 -> 0 | I65: 9954378 | J65: 45656 | K65: 45670
A66: 64 | B66: 1419 | C66: Mahad Masoud Salim Baitsaid | D66: 828 | E66: 0.4 | F66: =D66*E66 -> 331.2 | G66: =106.7+111.55+111.55+1.4 -> 331.2 | H66: =F66-G66 -> 0 | I66: 386821 | J66: 45658 | K66: 45663 | L66: 45677 | M66: 45684
A67: 65 | B67: 1420 | C67: Salim Said Salim Al Rawas | D67: 616.6 | E67: 0.4 | F67: =D67*E67 -> 246.64 | H67: =F67-G67 -> 246.64 | I67: 5460297
A68: 66 | B68: 1421 | C68: Malik Musallam Salim Masoud Al Rawas | D68: 667 | E68: 0.4 | F68: =D68*E68 -> 266.8 | H68: =F68-G68 -> 266.8 | I68: 15314262
A69: 67 | B69: 1423 | C69: Ahmed Said Ali Azad Al Kathiri | D69: 585.5 | E69: 0.4 | F69: =D69*E69 -> 234.2 | G69: =230.94 -> 230.94 | H69: =F69-G69 -> 3.26 | I69: 5044397 | J69: 45963
A70: 68 | B70: 1425 | C70: Salim Mohammed Ali Al Kathiri | D70: 565.3 | E70: 0.4 | F70: =D70*E70 -> 226.12 | G70: =22.74+198.85 -> 221.59 | H70: =F70-G70 -> 4.53 | I70: 5614623 | J70: 45810 | K70: 13-2-25
A71: 69 | B71: 1426 | C71: Ahmed Salim Ahmed Said Al Nubi Al Kathiri | D71: 603.7 | E71: 0.4 | F71: =D71*E71 -> 241.48 | G71: =238.58+2.9 -> 241.48 | H71: =F71-G71 -> 0 | I71: 2160707 | J71: 45658 | K71: 45686
A72: 70 | B72: 1427 | C72: Salim Said Mohammed Musallam Al Nubi Al kathiri | D72: 288.4 | E72: 0.4 | F72: =D72*E72 -> 115.36 | G72: =F72 -> 115.36 | H72: =F72-G72 -> 0 | I72: 24171637 | J72: 45684
A73: 71 | B73: 1428 | C73: Abdullah Said Abdullah Alkthiri | D73: 318.5 | E73: 0.4 | F73: =D73*E73 -> 127.4 | G73: =125.94+1.46 -> 127.4 | H73: =F73-G73 -> 0 | I73: 921364 | J73: 45658 | K73: 45679
A74: 72 | B74: 1430 | C74: Ahmed Said Mohammed Houmdi Al Siari | D74: 321.2 | E74: 0.4 | F74: =D74*E74 -> 128.48 | G74: =125.62+2.86 -> 128.48 | H74: =F74-G74 -> 0 | I74: 564698 | J74: 45658 | K74: 45684
A75: 73 | B75: 1432 | C75: Ali Ahmed Ali Sajlil Al shanfari | D75: 759 | E75: 0.4 | F75: =D75*E75 -> 303.6 | H75: =F75-G75 -> 303.6 | I75: 5004855
A76: 74 | B76: 1433 | C76: Ali Said Ali Bait Said | D76: 741 | E76: 0.4 | F76: =D76*E76 -> 296.4 | H76: =F76-G76 -> 296.4 | I76: 285841
A77: 75 | B77: 1434 | C77: Muhssin Said Mohammed Ghawas | D77: 368 | E77: 0.4 | F77: =D77*E77 -> 147.2 | H77: =F77-G77 -> 147.2 | I77: 19197503
A78: 76 | B78: 1435 | C78: Salim Said aoubad Ghawas | D78: 1012 | E78: 0.4 | F78: =D78*E78 -> 404.8 | G78: =403.62+1.18 -> 404.8 | H78: =F78-G78 -> 0 | I78: 1305522 | J78: 45658 | K78: 45679
A79: 77 | B79: 1437 | C79: Ahmed Ali Ahmed Shadar Al Kathiri | D79: 667 | E79: 0.4 | F79: =D79*E79 -> 266.8 | G79: =F79 -> 266.8 | H79: =F79-G79 -> 0 | I79: 9685144 | J79: 45658 | K79: 2.940 willd educt from 11-2024
A80: 78 | B80: 1438 | C80: Salim Aubad Al Maslamin Al Mashali | D80: 1012 | E80: 0.4 | F80: =D80*E80 -> 404.8 | G80: =401.55+3.25 -> 404.8 | H80: =F80-G80 -> 0 | I80: 656621 | J80: 45670 | K80: 45691
A81: 79 | B81: 1439 | C81: Ahmed Musallam Salim Al Kathiri | D81: 480.4 | E81: 0.4 | F81: =D81*E81 -> 192.16 | G81: =190.66+1.5 -> 192.16 | H81: =F81-G81 -> 0 | I81: 18880548 | J81: 45652 | K81: 45679
A82: 80 | B82: 1441 | C82: Musallam Said Amer Azad Al kathiri | D82: 552 | E82: 0.4 | F82: =D82*E82 -> 220.8 | G82: =219.14+1.66 -> 220.8 | H82: =F82-G82 -> 0 | I82: 7285624 | J82: 45684 | K82: 45686
A83: 81 | B83: 1444 | C83: Masoud Musallam Masoud Baitsaid | D83: 782 | E83: 0.4 | F83: =D83*E83 -> 312.8 | H83: =F83-G83 -> 312.8 | I83: 13487202
A84: 82 | B84: 1448 | C84: Salim Said Masoud Said Al Kathiri | D84: 423.6 | E84: 0.4 | F84: =D84*E84 -> 169.44 | H84: =F84-G84 -> 169.44 | I84: 26433121
A85: 83 | B85: 1451 | C85: Maneef Ali Abdullah Ghawas | D85: 335.6 | E85: 0.4 | F85: =D85*E85 -> 134.24 | G85: =130.73+3.51 -> 134.24 | H85: =F85-G85 -> 0 | I85: 20337612 | J85: 45672 | K85: 45684
A86: 84 | B86: 1453 | C86: Ahmed Said Salim Al Rawas | D86: 345 | E86: 0.4 | F86: =D86*E86 -> 138 | G86: =133.61+4.39 -> 138 | H86: =F86-G86 -> 0 | I86: 5460259 | J86: 45658 | K86: 45679
A87: 85 | B87: 1455 | C87: Thuwaini Ali Musallam Ghawas | D87: 644.1 | E87: 0.4 | F87: =D87*E87 -> 257.64 | G87: =133.2+123.05+1.39 -> 257.64 | H87: =F87-G87 -> 0 | I87: 9954383 | J87: 45663 | K87: 45665 | L87: 45677
A88: 86 | B88: 1462 | C88: Mohammed Suhail Mohammed Ghawas | D88: 344 | E88: 0.4 | F88: =D88*E88 -> 137.6 | G88: =135.45+2.15 -> 137.6 | H88: =F88-G88 -> 0 | I88: 9664038 | J88: 45658 | K88: 45686
A89: 87 | B89: 1463 | C89: Said Salim Ali Aazad Al Kathiri | D89: 550 | E89: 0.4 | F89: =D89*E89 -> 220 | G89: =F89 -> 220 | H89: =F89-G89 -> 0 | I89: 3798072 | J89: 45691
A90: 88 | B90: 1464 | C90: Ahmed Hamid Mohammed Zidi Bait Said | D90: 644 | E90: 0.4 | F90: =D90*E90 -> 257.6 | H90: =F90-G90 -> 257.6 | I90: 6352996
A91: 89 | B91: 1467 | C91: Salim Suhail Ali Al Kathiri | D91: 501.4 | E91: 0.4 | F91: =D91*E91 -> 200.56 | H91: =F91-G91 -> 200.56 | I91: 4279933
A92: 90 | B92: 1468 | C92: Ahmed Salim Ahmed Al Kathiri | D92: 685.6 | E92: 0.4 | F92: =D92*E92 -> 274.24 | G92: =269.87+4.37 -> 274.24 | H92: =F92-G92 -> 0 | I92: 6996485 | J92: 45684 | K92: 45810
A93: 91 | B93: 1472 | C93: Salim Ramas Musallam Ghawas | D93: 606.9 | E93: 0.4 | F93: =D93*E93 -> 242.76 | H93: =F93-G93 -> 242.76 | I93: 12987814 | K93: account name has changed
A94: 92 | B94: 1473 | C94: Salim Said Mahad Alshakal Al Kathiri | D94: 553.3 | E94: 0.4 | F94: =D94*E94 -> 221.32 | H94: =F94-G94 -> 221.32 | I94: 18722784
A95: 93 | B95: 1475 | C95: Musallam Said Ahmed Al kathiri | D95: 341 | E95: 0.4 | F95: =D95*E95 -> 136.4 | G95: =135.14 -> 135.14 | H95: =F95-G95 -> 1.26 | I95: 4584011 | J95: 45691
A96: 94 | B96: 1476 | C96: Ali Masoud Said Al Shahri | D96: 327.6 | E96: 0.4 | F96: =D96*E96 -> 131.04 | G96: =130.26+0.78 -> 131.04 | H96: =F96-G96 -> 0 | I96: 5486858 | J96: 45663 | K96: 45684
A97: 95 | B97: 1477 | C97: Salim Mohammed Mahad Al Kathiri | D97: 321.2 | E97: 0.4 | F97: =D97*E97 -> 128.48 | G97: =109.6 -> 109.6 | H97: =F97-G97 -> 18.88 | I97: 18656494 | J97: 45691
A98: 96 | B98: 1480 | C98: Mohsin Ali Mahisan Houmdi Al Siari | D98: 339.8 | E98: 0.4 | F98: =D98*E98 -> 135.92 | G98: =132.72 -> 132.72 | H98: =F98-G98 -> 3.2 | I98: 19820777 | J98: 45684
A99: 97 | B99: 1482 | C99: Ahmed Abdullah Ahmed Qatmem Al marhoon | D99: 523.3 | E99: 0.4 | F99: =D99*E99 -> 209.32 | G99: 0 | H99: =F99-G99 -> 209.32 | I99: 4024306
A100: 98 | B100: 1485 | C100: Salim Ali Mustahil Asat Al Shihri | D100: 388.5 | E100: 0.4 | F100: =D100*E100 -> 155.4 | G100: =152.5+2.9 -> 155.4 | H100: =F100-G100 -> 0 | I100: 18585573 | J100: 45663 | K100: 45679
...

Sheet Center-Nov
A1: Milk Chilling Centre(Ghado) - Monthly Camel Milk Procurement Report - 01-11-2024 TO 30-11-2024
A2: SR. NO. | B2: Farmer Code | C2: Farmer Name | D2: Total Quantity Supplied(Lits) | E2: Camel Milk Price/Lit(OMR) | F2: Total Value (OMR) | G2: Paid | H2: Balance | I2: ID No: | J2: Account No | K2: Bank Name | L2: BANK SWIFT CODE | M2: Phone No: | N2: Remarks
A3: 1 | B3: 1001 | C3: Abdul Hakim Musallam Salim Al Katini Al Rawas | D3: 247 | E3: 0.4 | F3: =D3*E3 -> 98.8 | G3: =97.22 -> 97.22 | H3: =F3-G3 -> 1.58 | I3: 2130934 | J3: 0397020829680019 | K3: Bank Muscat | L3: BMUSOMRX | M3: 92911133 | N3: 45963
A4: 2 | B4: 1007 | C4: Ahmed Abdullah Said Al Rawas | D4: 1349 | E4: 0.4 | F4: =D4*E4 -> 539.6 | G4: =537.12 -> 537.12 | H4: =F4-G4 -> 2.48 | I4: 1515504 | J4: 3109147237500 | K4: Oman Arab Bank | L4: OMABOMRU | M4: 91748840 | N4: 45665
A5: 3 | B5: 1028 | C5: Ahmed Saeed Maatouq Al kathiri | D5: 258.6 | E5: 0.4 | F5: =D5*E5 -> 103.44 | H5: =F5-G5 -> 103.44 | I5: 802875 | J5: 0397004247250014 | K5: Bank Muscat | L5: BMUSOMRX | M5: 99498677
A6: 4 | B6: 1033 | C6: Ahmed Said Ali Al Nobi Al Kathiri | D6: 560 | E6: 0.4 | F6: =D6*E6 -> 224 | G6: =220.3+3.7 -> 224 | H6: =F6-G6 -> 0 | I6: 10132435 | J6: 01011076521002 | K6: Bank Dhofar | L6: BDOFOMRU | M6: 92268168 | N6: 45670 | O6: 45701
A7: 5 | B7: 1040 | C7: Ahmed Said Mahad Jamaan Dhishil al Kathiri | D7: 247 | E7: 0.4 | F7: =D7*E7 -> 98.8 | H7: =F7-G7 -> 98.8 | I7: 25082374 | J7: 0406041201480018 | K7: Bank Muscat | L7: BMUSOMRX | M7: 99816344
A8: 6 | B8: 1044 | C8: Ahmed Salim Ahmed Al Hadi Baomar | D8: 285 | E8: 0.4 | F8: =D8*E8 -> 114 | H8: =F8-G8 -> 114 | I8: 81904 | J8: 0406003182770027 | K8: Bank Muscat | L8: BMUSOMRX | M8: 99494120
A9: 7 | B9: 1080 | C9: Ali Saeed Matoq Alkthiri | D9: 263.7 | E9: 0.4 | F9: =D9*E9 -> 105.48 | H9: =F9-G9 -> 105.48 | I9: 78762 | J9: 0397004237620018 | K9: Bank Muscat | L9: BMUSOMRX | M9: 92440088
A10: 8 | B10: 1089 | C10: Ali Said Nasib | D10: 436 | E10: 0.4 | F10: =D10*E10 -> 174.4 | G10: =171.76 -> 171.76 | H10: =F10-G10 -> 2.64 | I10: 892683 | J10: 1023281341086 | K10: NBO | L10: NBOMOMRX | M10: 99506162 | N10: 45686
A11: 9 | B11: 1096 | C11: Ali Salim Awadh Al Kathiri | D11: 299.8 | E11: 0.4 | F11: =D11*E11 -> 119.92 | G11: =117.37 -> 117.37 | H11: =F11-G11 -> 2.55 | I11: 1959918 | J11: 3109647718500 | K11: Oman Arab Bank | L11: OMABOMRU | M11: 92699781 | N11: 45686
A12: 10 | B12: 1106 | C12: Badar Said Masood Al Kathiri | D12: 836 | E12: 0.4 | F12: =D12*E12 -> 334.4 | H12: =F12-G12 -> 334.4 | I12: 5502751 | J12: 10060192223001 | K12: NBO | L12: NBOMOMRX | M12: 99270001
A13: 11 | B13: 1110 | C13: Bakhit Salim Azad Al Kathiri | D13: 437 | E13: 0.4 | F13: =D13*E13 -> 174.8 | G13: =172.95 -> 172.95 | H13: =F13-G13 -> 1.85 | I13: 934298 | J13: 0406003101920011 | K13: Bank Muscat | L13: BMUSOMRX | M13: 92811415 | N13: 45679
A14: 12 | B14: 1111 | C14: Bakhit Salim Ali Shadar Al Kathiri | D14: 513 | E14: 0.4 | F14: =D14*E14 -> 205.2 | H14: =F14-G14 -> 205.2 | I14: 15571992 | J14: 01011058653001 | K14: Bank Dhofar | L14: BDOFOMRU | M14: 92708951
A15: 13 | B15: 1119 | C15: Ghanim Abdul Aziz Masoud Abdul Aziz Alash Al Kathiri | D15: 374.5 | E15: 0.4 | F15: =D15*E15 -> 149.8 | H15: =F15-G15 -> 149.8 | I15: 24000245 | J15: 0397020978260014 | K15: Bank Muscat | L15: BMUSOMRX | M15: 90911369
A16: 14 | B16: 1122 | C16: Hamed Hilal Said Al Kathiri | D16: 264.2 | E16: 0.4 | F16: =D16*E16 -> 105.68 | G16: =102.94 -> 102.94 | H16: =F16-G16 -> 2.74 | I16: 5219876 | J16: 0406045268200015 | K16: Bank Muscat | L16: BMUSOMRX | M16: 99066779 | N16: 45684
A17: 15 | B17: 1135 | C17: Khalid Said Ali Al Kathiri | D17: 499.5 | E17: 0.4 | F17: =D17*E17 -> 199.8 | G17: =199.62 -> 199.62 | H17: =F17-G17 -> 0.18 | I17: 19202954 | J17: 01013808698001 | K17: Bank Dhofar | L17: BDOFOMRU | M17: 92771786 | N17: 45684
A18: 16 | B18: 1141 | C18: Malik Said Ahmed Habkook Hat Al Shahri | D18: 417.8 | E18: 0.4 | F18: =D18*E18 -> 167.12 | G18: =163.93 -> 163.93 | H18: =F18-G18 -> 3.19 | I18: 11753992 | J18: 0396051591490029 | K18: Bank Muscat | L18: BMUSOMRX | M18: 99205960 | N18: 45679
A19: 17 | B19: 1154 | C19: Mohammed Salim Abdullah Al kathiri | D19: 755.8 | E19: 0.4 | F19: =D19*E19 -> 302.32 | H19: =F19-G19 -> 302.32 | I19: 18654817 | J19: 0439053703720016 | K19: Bank Muscat | L19: BMUSOMRX | M19: 98887846
A20: 18 | B20: 1161 | C20: Mohammed Ali Musallam Al Nubi Al Kathiri | D20: 285 | E20: 0.4 | F20: =D20*E20 -> 114 | G20: =109.18 -> 109.18 | H20: =F20-G20 -> 4.82 | I20: 257926 | J20: 3109603718500 | K20: Oman Arab Bank | L20: OMABOMRU | M20: 99589267 | N20: 45810
A21: 19 | B21: 1168 | C21: Mohammed Salim Said Jumaa Al Kathiri | D21: 448.6 | E21: 0.4 | F21: =D21*E21 -> 179.44 | H21: =F21-G21 -> 179.44 | I21: 15498714 | J21: 0402012153960016 | K21: Bank Muscat | L21: BMUSOMRX | M21: 99292524
A22: 20 | B22: 1177 | C22: Said Salim Said BaitSaid | D22: 277.2 | E22: 0.4 | F22: =D22*E22 -> 110.88 | H22: =F22-G22 -> 110.88 | I22: 219353 | J22: 01010127872001 | K22: Bank Dhofar | L22: BDOFOMRU | M22: 99485534
A23: 21 | B23: 1178 | C23: Mohammed Said Mohammed Akdha Al Rawas | D23: 490.9 | E23: 0.4 | F23: =D23*E23 -> 196.36 | G23: =F23 -> 196.36 | H23: =F23-G23 -> 0 | I23: 970872 | J23: 1006123229017 | K23: NBO | L23: NBOMOMRX | M23: 99485535 | N23: 45685
A24: 22 | B24: 1224 | C24: Naif Masoud Awadh Nasib Kikab Al Shihri | D24: 527 | E24: 0.4 | F24: =D24*E24 -> 210.8 | H24: =F24-G24 -> 210.8 | I24: 24911691 | J24: 0406060856030017 | K24: Bank Muscat | L24: BMUSOMRX | M24: 99192216
A25: 23 | B25: 1225 | C25: Naif Said Awadh Fadhl | D25: 489.5 | E25: 0.4 | F25: =D25*E25 -> 195.8 | H25: =F25-G25 -> 195.8 | I25: 9642357 | J25: 1501079705330 | K25: Ahli bank | L25: AUBOOMRU | M25: 99777877
A26: 24 | B26: 1235 | C26: Saeed Abdul Aziz Abdullah Al kathiri | D26: 551 | E26: 0.4 | F26: =D26*E26 -> 220.4 | H26: =F26-G26 -> 220.4 | I26: 1992436 | J26: 0402003122620013 | K26: BANK MUSCAT | L26: BMUSOMRX | M26: 99484668
A27: 25 | B27: 1241 | C27: Said Mohammed Abdallah Al kathiri | D27: 474.7 | E27: 0.4 | F27: =D27*E27 -> 189.88 | G27: =188.09 -> 188.09 | H27: =F27-G27 -> 1.79 | I27: 5343254 | J27: 0406003410830019 | K27: Bank Muscat | L27: BMUSOMRX | M27: 98964664 | N27: 45684
A28: 26 | B28: 1247 | C28: Said Salim Azad Bait Ali Badar | D28: 456 | E28: 0.4 | F28: =D28*E28 -> 182.4 | G28: =181.45 -> 181.45 | H28: =F28-G28 -> 0.95 | I28: 4748561 | J28: 01040280570002 | K28: Bank Dhofar | L28: BDOFOMRU | M28: 92345282 | N28: 45679
A29: 27 | B29: 1252 | C29: Said Ahmed Ali Bait Said | D29: 407.3 | E29: 0.4 | F29: =D29*E29 -> 162.92 | H29: =F29-G29 -> 162.92 | I29: 2433959 | J29: 01010120819002 | K29: Bank Dhofar | L29: BDOFOMRU | M29: 93555999
A30: 28 | B30: 1258 | C30: Said Ali Musallam Al Noubi Al Kathiri | D30: 608 | E30: 0.4 | F30: =D30*E30 -> 243.2 | G30: =241.36 -> 241.36 | H30: =F30-G30 -> 1.84 | I30: 1924174 | J30: 01040280044001 | K30: Bank Dhofar | L30: BDOFOMRU | M30: 99297990 | N30: 45677
A31: 29 | B31: 1260 | C31: Said Salim Ali Kibab Al Shahri | D31: 525.6 | E31: 0.4 | F31: =D31*E31 -> 210.24 | G31: =207.25 -> 207.25 | H31: =F31-G31 -> 2.99 | I31: 18363579 | J31: 01041057246001 | K31: Bank Dhofar | L31: BDOFOMRU | M31: 98217444 | N31: 45684
A32: 30 | B32: 1261 | C32: Said Ali Nasib Kikab Al shahri | D32: 268.2 | E32: 0.4 | F32: =D32*E32 -> 107.28 | G32: =104.48 -> 104.48 | H32: =F32-G32 -> 2.8 | I32: 14429332 | J32: 0406018203570028 | K32: Bank Muscat | L32: BMUSOMRX | M32: 92939445 | N32: 45679
A33: 31 | B33: 1268 | C33: Said Musallam Ali Ghawas | D33: 380 | E33: 0.4 | F33: =D33*E33 -> 152 | G33: =150.6 -> 150.6 | H33: =F33-G33 -> 1.4 | I33: 722058 | J33: 0397003940070023 | K33: Bank Muscat | L33: BMUSOMRX | M33: 92848609 | N33: 45684
A34: 32 | B34: 1282 | C34: Salim Ali Musallam Al Noubi Al Kathiri | D34: 513 | E34: 0.4 | F34: =D34*E34 -> 205.2 | G34: =F34 -> 205.2 | H34: =F34-G34 -> 0 | I34: 2997747 | J34: 3109601542500 | K34: Oman Arab Bank | L34: OMABOMRU | M34: 92660969 | N34: 45684 | O34: 2.3 wiil deduct fro 12-24
A35: 33 | B35: 1284 | C35: Salim Ali Said Al Nubi Al Kathiri | D35: 494 | E35: 0.4 | F35: =D35*E35 -> 197.6 | G35: =194.07 -> 194.07 | H35: =F35-G35 -> 3.53 | I35: 1177598 | J35: 01040280595001 | K35: Bank Dhofar | L35: BDOFOMRU | M35: 92825228 | N35: 45679
A36: 34 | B36: 1300 | C36: Salem Suhail Omer Bit Fhadel | D36: 604.4 | E36: 0.4 | F36: =D36*E36 -> 241.76 | H36: =F36-G36 -> 241.76 | I36: 19534277 | J36: 0439016892350027 | K36: Bank Muscat | L36: BMUSOMRX | M36: 99710505
A37: 35 | B37: 1306 | C37: Salim Ali Nasib Al Kathiri | D37: 269.4 | E37: 0.4 | F37: =D37*E37 -> 107.76 | G37: =104.34 -> 104.34 | H37: =F37-G37 -> 3.42 | I37: 2006904 | J37: 0439051845390018 | K37: Bank Muscat | L37: BMUSOMRX | M37: 96137717 | N37: 45684
A38: 36 | B38: 1315 | C38: Salim Said Ali Ghawas | D38: 212.4 | E38: 0.4 | F38: =D38*E38 -> 84.96 | H38: =F38-G38 -> 84.96 | I38: 19528845 | J38: 0439026234320047 | K38: Bank Muscat | L38: BMUSOMRX | M38: 92432606
A39: 37 | B39: 1328 | C39: Suhail Saeed Suhail ghawas | D39: 332.1 | E39: 0.4 | F39: =D39*E39 -> 132.84 | G39: =129.57 -> 129.57 | H39: =F39-G39 -> 3.27 | I39: 782833 | J39: 01015382117001 | K39: Bank Dhofar | L39: BDOFOMRU | M39: 92475895 | N39: 45686
A40: 38 | B40: 1330 | C40: Said Mahad Ali Al Kathiri | D40: 520.7 | E40: 0.4 | F40: =D40*E40 -> 208.28 | H40: =F40-G40 -> 208.28 | I40: 12194826 | J40: 00510129167001 | K40: Bank Nizwa | L40: BNZWOMRX | M40: 91299100
A41: 39 | B41: 1331 | C41: Mohammed Said Musallam Al Noob Al Kathiri | D41: 285 | E41: 0.4 | F41: =D41*E41 -> 114 | G41: =111.7 -> 111.7 | H41: =F41-G41 -> 2.3 | I41: 2107763 | J41: 3109043578500 | K41: Oman Arab Bank | L41: OMABOMRU | M41: 93536009 | N41: 45679
A42: 40 | B42: 1333 | C42: Suhail Salim Ahmed Al Nubi Al Kathiri | D42: 462.2 | E42: 0.4 | F42: =D42*E42 -> 184.88 | H42: =F42-G42 -> 184.88 | I42: 1736679 | J42: 0401002496140031 | K42: Bank Muscat | L42: BMUSOMRX | M42: 99482212
A43: 41 | B43: 1382 | C43: Suhail Mohammed Said Ghawas Al Kathiri | D43: 528.2 | E43: 0.4 | F43: =D43*E43 -> 211.28 | G43: =206.65 -> 206.65 | H43: =F43-G43 -> 4.63 | I43: 886492 | J43: 0397003786810019 | K43: Bank Muscat | L43: BMUSOMRX | M43: 99494166 | N43: 45686
A44: 42 | B44: 1384 | C44: Abdul Selam Musallam Mohammed Al Rawas | D44: 211.9 | E44: 0.4 | F44: =D44*E44 -> 84.76 | G44: =81.52 -> 81.52 | H44: =F44-G44 -> 3.24 | I44: 4426701 | J44: 0406003017570013 | K44: Bank Muscat | L44: BMUSOMRX | M44: 92634991 | N44: 45684
A45: 43 | B45: 1386 | C45: Omar Salim Ahmed Al Hadi Ba Omar | D45: 573.2 | E45: 0.4 | F45: =D45*E45 -> 229.28 | G45: =227.36 -> 227.36 | H45: =F45-G45 -> 1.92 | I45: 711799 | J45: 0406003202280013 | K45: Bank Muscat | L45: BMUSOMRX | M45: 92394924 | N45: 45677
A46: 44 | B46: 1387 | C46: Ali Said Mahisan Kayakab Al Shihri | D46: 505.8 | E46: 0.4 | F46: =D46*E46 -> 202.32 | H46: =F46-G46 -> 202.32 | I46: 6759716 | J46: 3109117911500 | K46: Oman Arab Bank | L46: OMABOMRU | M46: 91907675
A47: 45 | B47: 1388 | C47: Tarik Suhail Salim Al Kathiri | D47: 304 | E47: 0.4 | F47: =D47*E47 -> 121.6 | H47: =F47-G47 -> 121.6 | I47: 18610874 | J47: 01011035504001 | K47: Bank Dhofar | L47: BDOFOMRU | M47: 93955577
A48: 46 | B48: 1389 | C48: Ali Said Musallam Al Noubi Al Kathiri | D48: 760 | E48: 0.4 | F48: =D48*E48 -> 304 | G48: =303.6 -> 303.6 | H48: =F48-G48 -> 0.4 | I48: 1036354 | J48: 01010281496001 | K48: Bank Dhofar | L48: BDOFOMRU | M48: 92413881 | N48: 45686
A49: 47 | B49: 1394 | C49: Ali Ahmed Salim Ahmed Al Kathiri | D49: 262.7 | E49: 0.4 | F49: =D49*E49 -> 105.08 | G49: =104.27 -> 104.27 | H49: =F49-G49 -> 0.81 | I49: 25656187 | J49: 0396016034040018 | K49: Bank Muscat | L49: BMUSOMRX | M49: 98987848 | N49: 45684
A50: 48 | B50: 1396 | C50: Mustahil Ali Azad Al Kathiri | D50: 332 | E50: 0.4 | F50: =D50*E50 -> 132.8 | G50: =131.97 -> 131.97 | H50: =F50-G50 -> 0.83 | I50: 905845 | J50: 0397003647340016 | K50: Bank Muscat | L50: BMUSOMRX | M50: 99696204 | N50: 45679
A51: 49 | B51: 1397 | C51: Ahmed Musallam Amer Al Kathiri | D51: 273.7 | E51: 0.4 | F51: =D51*E51 -> 109.48 | G51: =107.3 -> 107.3 | H51: =F51-G51 -> 2.18 | I51: 1292885 | J51: 254001118001 | K51: HSBC | L51: BBMEOMRX | M51: 92307552 | N51: 45686
A52: 50 | B52: 1398 | C52: Salim Amer Azad Al Kathiri | D52: 204.5 | E52: 0.4 | F52: =D52*E52 -> 81.8 | G52: =80.98 -> 80.98 | H52: =F52-G52 -> 0.82 | I52: 1161437 | J52: 00510128357001 | K52: Bank Nizwa | L52: BNZWOMRX | M52: 91135580 | N52: 45684
A53: 51 | B53: 1400 | C53: Manei Said Ahmed Al Kathiri | D53: 515 | E53: 0.4 | F53: =D53*E53 -> 206 | G53: =F53 -> 206 | H53: =F53-G53 -> 0 | I53: 7223707 | J53: 10060183858001 | K53: NBO | L53: NBOMOMRX | M53: 92616136 | N53: 45691
A54: 52 | B54: 1403 | C54: Ali Salim Ahmed Al Nubi Al Kathiri | D54: 427.6 | E54: 0.4 | F54: =D54*E54 -> 171.04 | G54: =169.11 -> 169.11 | H54: =F54-G54 -> 1.93 | I54: 499044 | J54: 0406003202740014 | K54: Bank Muscat | L54: BMUSOMRX | M54: 92226988 | N54: 45963
A55: 53 | B55: 1406 | C55: Said Salim Musallam AlNoob Al Kathiri | D55: 368.7 | E55: 0.4 | F55: =D55*E55 -> 147.48 | G55: =147.3 -> 147.3 | H55: =F55-G55 -> 0.18 | I55: 880849 | J55: 3109015600500 | K55: Oman Arab Bank | L55: OMABOMRU | M55: 99365157 | N55: 45691
A56: 54 | B56: 1408 | C56: Abdullah Salim AhmedAl Hadi Ba Omar | D56: 1102 | E56: 0.4 | F56: =D56*E56 -> 440.8 | H56: =F56-G56 -> 440.8 | I56: 997465 | J56: 0397003981360017 | K56: Bank Muscat | L56: BMUSOMRX | M56: 99490975
A57: 55 | B57: 1409 | C57: Mahisan Ali Mahisan Al Shihri | D57: 423.1 | E57: 0.4 | F57: =D57*E57 -> 169.24 | G57: =166.43 -> 166.43 | H57: =F57-G57 -> 2.81 | I57: 7279409 | J57: 0406016730440035 | K57: Bank Muscat | L57: BMUSOMRX | M57: 99626634 | N57: 45809
A58: 56 | B58: 1410 | C58: Masoud Ali suhail Bait Said | D58: 469.4 | E58: 0.4 | F58: =D58*E58 -> 187.76 | G58: =185.11 -> 185.11 | H58: =F58-G58 -> 2.65 | I58: 757372 | J58: 0406003338100019 | K58: Bank Muscat | L58: BMUSOMRX | M58: 92018800 | N58: 45686
A59: 57 | B59: 1411 | C59: Said Ali Ahmed Amor Jid | D59: 494.4 | E59: 0.4 | F59: =D59*E59 -> 197.76 | G59: =194.65 -> 194.65 | H59: =F59-G59 -> 3.11 | I59: 1650389 | J59: 0406018263680011 | K59: Bank Muscat | L59: BMUSOMRX | M59: 92294150 | N59: 45677
A60: 58 | B60: 1412 | C60: Musallam Said Salim Bait Said | D60: 569.4 | E60: 0.4 | F60: =D60*E60 -> 227.76 | H60: =F60-G60 -> 227.76 | I60: 312227 | J60: 0406003457720017 | K60: Bank Muscat | L60: BMUSOMRX | M60: 95414124
A61: 59 | B61: 1413 | C61: Awadh Salim Ali Ghawas | D61: 285 | E61: 0.4 | F61: =D61*E61 -> 114 | G61: =111.25 -> 111.25 | H61: =F61-G61 -> 2.75 | I61: 539906 | J61: 01010128406001 | K61: Bank Dhofar | L61: BDOFOMRU | N61: 45686
A62: 60 | B62: 1414 | C62: Salim Said Ali Bait Said | D62: 819.3 | E62: 0.4 | F62: =D62*E62 -> 327.72 | G62: =325.185 -> 325.185 | H62: =F62-G62 -> 2.535 | I62: 9178238 | J62: 01010852881001 | K62: Bank Dhofar | L62: BDOFOMRU | M62: 91966140 | N62: 45684
A63: 61 | B63: 1415 | C63: Salim ahmed Masoud Jumaa Al kathiri | D63: 249.2 | E63: 0.4 | F63: =D63*E63 -> 99.68 | G63: =96.62 -> 96.62 | H63: =F63-G63 -> 3.06 | I63: 818787 | J63: 0439003977040022 | K63: Bank Muscat | L63: BMUSOMRX | M63: 99806280 | N63: 45672
A64: 62 | B64: 1417 | C64: Said Bakhit said Al mashikhi | D64: 416.9 | E64: 0.4 | F64: =D64*E64 -> 166.76 | G64: =166.4 -> 166.4 | H64: =F64-G64 -> 0.36 | I64: 1252579 | J64: 0397003628950016 | K64: Bank Muscat | L64: BMUSOMRX | M64: 98520912 | N64: 45686
A65: 63 | B65: 1418 | C65: SALIM ALI MUSALLAM GHAWAS | D65: 324.6 | E65: 0.4 | F65: =D65*E65 -> 129.84 | G65: =129.45+0.39 -> 129.84 | H65: =F65-G65 -> 0 | I65: 9954378 | J65: 0397003855180014 | K65: Bank Muscat | L65: BMUSOMRX | M65: 99282423 | N65: 45670 | O65: 45810
A66: 64 | B66: 1419 | C66: Mahad Masoud Salim Baitsaid | D66: 699 | E66: 0.4 | F66: =D66*E66 -> 279.6 | G66: =110.15+111.55+53.35 -> 275.05 | H66: =F66-G66 -> 4.55 | I66: 386821 | J66: 0406003414760015 | K66: Bank Muscat | L66: BMUSOMRX | M66: 99181419 | N66: 45684 | O66: 45963 | P66: 13-2-25
A67: 65 | B67: 1420 | C67: Salim Said Salim Al Rawas | D67: 482.8 | E67: 0.4 | F67: =D67*E67 -> 193.12 | H67: =F67-G67 -> 193.12 | I67: 5460297 | J67: 0402003168320014 | K67: Bank Muscat | L67: BMUSOMRX | M67: 95898899
A68: 66 | B68: 1421 | C68: Malik Musallam Salim Masoud Al Rawas | D68: 551 | E68: 0.4 | F68: =D68*E68 -> 220.4 | H68: =F68-G68 -> 220.4 | I68: 15314262 | J68: 0397019441080011 | K68: Bank Muscat | L68: BMUSOMRX | M68: 90333361
A69: 67 | B69: 1423 | C69: Ahmed Said Ali Azad Al Kathiri | D69: 497.7 | E69: 0.4 | F69: =D69*E69 -> 199.08 | H69: =F69-G69 -> 199.08 | I69: 5044397 | J69: 0397003645500016 | K69: Bank Muscat | L69: BMUSOMRX | M69: 99580550
A70: 68 | B70: 1425 | C70: Salim Mohammed Ali Al Kathiri | D70: 485 | E70: 0.4 | F70: =D70*E70 -> 194 | H70: =F70-G70 -> 194 | I70: 5614623 | J70: 0406002564870025 | K70: Bank Muscat | L70: BMUSOMRX | M70: 99583112
A71: 69 | B71: 1426 | C71: Ahmed Salim Ahmed Said Al Nubi Al Kathiri | D71: 503.8 | E71: 0.4 | F71: =D71*E71 -> 201.52 | G71: =200.8 -> 200.8 | H71: =F71-G71 -> 0.72 | I71: 2160707 | J71: 3109076938500 | K71: Oman Arab Bank | L71: OMABOMRU | M71: 92280327 | N71: 45686
A72: 70 | B72: 1427 | C72: Salim Said Mohammed Musallam Al Nubi Al kathiri | D72: 227.9 | E72: 0.4 | F72: =D72*E72 -> 91.16 | G72: =90.53 -> 90.53 | H72: =F72-G72 -> 0.63 | I72: 24171637 | J72: 0439025022760016 | K72: Bank Muscat | L72: BMUSOMRX | M72: 97030409 | N72: 45684
A73: 71 | B73: 1428 | C73: Abdullah Said Abdullah Alkthiri | D73: 258.1 | E73: 0.4 | F73: =D73*E73 -> 103.24 | G73: =100.39 -> 100.39 | H73: =F73-G73 -> 2.85 | I73: 921364 | J73: 0406003192550017 | K73: BANK MUSCAT | L73: BMUSOMRX | M73: 92599597 | N73: 45679
A74: 72 | B74: 1430 | C74: Ahmed Said Mohammed Houmdi Al Siari | D74: 266 | E74: 0.4 | F74: =D74*E74 -> 106.4 | G74: =103.84 -> 103.84 | H74: =F74-G74 -> 2.56 | I74: 564698 | J74: 0406003186630017 | K74: Bank Muscat | L74: BMUSOMRX | M74: 99189793 | N74: 45684
A75: 73 | B75: 1432 | C75: Ali Ahmed Ali Sajlil Al shanfari | D75: 627 | E75: 0.4 | F75: =D75*E75 -> 250.8 | H75: =F75-G75 -> 250.8 | I75: 5004855 | J75: 01013803818001 | K75: Bank Dhofar | L75: BDOFOMRU | M75: 99899962
A76: 74 | B76: 1433 | C76: Ali Said Ali Bait Said | D76: 627 | E76: 0.4 | F76: =D76*E76 -> 250.8 | H76: =F76-G76 -> 250.8 | I76: 285841 | J76: 0397003981260015 | K76: Bank Muscat | L76: BMUSOMRX | M76: 92958552
A77: 75 | B77: 1434 | C77: Muhssin Said Mohammed Ghawas | D77: 297.7 | E77: 0.4 | F77: =D77*E77 -> 119.08 | H77: =F77-G77 -> 119.08 | I77: 19197503 | J77: 0403015046590039 | K77: Bank Muscat | L77: BMUSOMRX | M77: 92466605
A78: 76 | B78: 1435 | C78: Salim Said aoubad Ghawas | D78: 831.5 | E78: 0.4 | F78: =D78*E78 -> 332.6 | G78: =328.62 -> 328.62 | H78: =F78-G78 -> 3.98 | I78: 1305522 | J78: 0397003064100017 | K78: Bank Muscat | L78: BMUSOMRX | M78: 93246263 | N78: 45679
A79: 77 | B79: 1437 | C79: Ahmed Ali Ahmed Shadar Al Kathiri | D79: 522 | E79: 0.4 | F79: =D79*E79 -> 208.8 | G79: =2.94+203.7 -> 206.64 | H79: =F79-G79 -> 2.16 | I79: 9685144 | J79: 250056066001 | K79: HSBC | L79: BBMEOMRX | M79: 96907302 | N79: 2.940 willd educt from 11-2024 | O79: 45684
A80: 78 | B80: 1438 | C80: Salim Aubad Al Maslamin Al Mashali | D80: 836 | E80: 0.4 | F80: =D80*E80 -> 334.4 | G80: =331.4 -> 331.4 | H80: =F80-G80 -> 3 | I80: 656621 | J80: 1023386437017 | K80: NBO | L80: NBOMOMRX | M80: 92509804 | N80: 45691
A81: 79 | B81: 1439 | C81: Ahmed Musallam Salim Al Kathiri | D81: 405.6 | E81: 0.4 | F81: =D81*E81 -> 162.24 | G81: =158.55 -> 158.55 | H81: =F81-G81 -> 3.69 | I81: 18880548 | J81: 0406060805600016 | K81: Bank Muscat | L81: BMUSOMRX | M81: 98901515 | N81: 45679
A82: 80 | B82: 1441 | C82: Musallam Said Amer Azad Al kathiri | D82: 449.9 | E82: 0.4 | F82: =D82*E82 -> 179.96 | G82: =177.79 -> 177.79 | H82: =F82-G82 -> 2.17 | I82: 7285624 | J82: 00510041624001 | K82: Bank Nizwa | M82: 93587666 | N82: 45686
A83: 81 | B83: 1444 | C83: Masoud Musallam Masoud Baitsaid | D83: 646 | E83: 0.4 | F83: =D83*E83 -> 258.4 | H83: =F83-G83 -> 258.4 | I83: 13487202 | J83: 0406003229140019 | K83: Bank Muscat | L83: BMUSOMRX | M83: 92244429
A84: 82 | B84: 1448 | C84: Salim Said Masoud Said Al Kathiri | D84: 373 | E84: 0.4 | F84: =D84*E84 -> 149.2 | H84: =F84-G84 -> 149.2 | I84: 26433121 | J84: 0397060499480017 | K84: Bank Muscat | L84: BMUSOMRX | M84: 93229244
A85: 83 | B85: 1451 | C85: Maneef Ali Abdullah Ghawas | D85: 284.5 | E85: 0.4 | F85: =D85*E85 -> 113.8 | G85: =112.89 -> 112.89 | H85: =F85-G85 -> 0.91 | I85: 20337612 | J85: 0406061272960011 | K85: Bank Muscat | L85: BMUSOMRX | M85: 98829667 | N85: 45684
A86: 84 | B86: 1453 | C86: Ahmed Said Salim Al Rawas | D86: 285 | E86: 0.4 | F86: =D86*E86 -> 114 | G86: =112.01 -> 112.01 | H86: =F86-G86 -> 1.99 | I86: 5460259 | J86: 010010017675 | K86: Bank Sohar | L86: BSHROMRU | M86: 90199947 | N86: 45679
A87: 85 | B87: 1455 | C87: Thuwaini Ali Musallam Ghawas | D87: 563 | E87: 0.4 | F87: =D87*E87 -> 225.2 | G87: =132.36+90.95 -> 223.31 | H87: =F87-G87 -> 1.89 | I87: 9954383 | J87: 0403061364570014 | K87: Bank Muscat | L87: BMUSOMRX | M87: 93270751 | N87: 45677 | O87: 45684
A88: 86 | B88: 1462 | C88: Mohammed Suhail Mohammed Ghawas | D88: 270 | E88: 0.4 | F88: =D88*E88 -> 108 | G88: =104.55 -> 104.55 | H88: =F88-G88 -> 3.45 | I88: 9664038 | J88: 132247650084010 | K88: Bank Muscat | L88: BMUSOMRX | M88: 92989674 | N88: 45686
A89: 87 | B89: 1463 | C89: Said Salim Ali Aazad Al Kathiri | D89: 456 | E89: 0.4 | F89: =D89*E89 -> 182.4 | G89: =178.4 -> 178.4 | H89: =F89-G89 -> 4 | I89: 3798072 | J89: 01040280652001 | K89: Bank Dhofar | L89: BDOFOMRU | M89: 99480608 | N89: 45691
A90: 88 | B90: 1464 | C90: Ahmed Hamid Mohammed Zidi Bait Said | D90: 532 | E90: 0.4 | F90: =D90*E90 -> 212.8 | H90: =F90-G90 -> 212.8 | I90: 6352996 | J90: 01011028474002 | K90: Bank Dhofar | L90: BDOFOMRU | M90: 92463267
A91: 89 | B91: 1467 | C91: Salim Suhail Ali Al Kathiri | D91: 414.3 | E91: 0.4 | F91: =D91*E91 -> 165.72 | H91: =F91-G91 -> 165.72 | I91: 4279933 | J91: 01013038536001 | K91: Bank Dhofar | L91: BDOFOMRU | M91: 98510166
A92: 90 | B92: 1468 | C92: Ahmed Salim Ahmed Al Kathiri | D92: 566.4 | E92: 0.4 | F92: =D92*E92 -> 226.56 | G92: =223.58 -> 223.58 | H92: =F92-G92 -> 2.98 | I92: 6996485 | J92: 0439016595760027 | K92: Bank Muscat | L92: BMUSOMRX | M92: 92947741 | N92: 45810
A93: 91 | B93: 1472 | C93: Salim Ramas Musallam Ghawas | D93: 467.6 | E93: 0.4 | F93: =D93*E93 -> 187.04 | H93: =F93-G93 -> 187.04 | I93: 12987814 | J93: 1083702512017 | K93: NBO | L93: NBOMOMRX | M93: 99365173
A94: 92 | B94: 1473 | C94: Salim Said Mahad Alshakal Al Kathiri | D94: 407.1 | E94: 0.4 | F94: =D94*E94 -> 162.84 | H94: =F94-G94 -> 162.84 | I94: 18722784 | J94: 01010402046001 | K94: Bank Dhofar | L94: BDOFOMRU | M94: 98900644
A95: 93 | B95: 1475 | C95: Musallam Said Ahmed Al kathiri | D95: 285.8 | E95: 0.4 | F95: =D95*E95 -> 114.32 | H95: =F95-G95 -> 114.32 | I95: 4584011 | J95: 0439061793370011 | K95: Bank Muscat | L95: BMUSOMRX | M95: 98822862
A96: 94 | B96: 1476 | C96: Ali Masoud Said Al Shahri | D96: 271.4 | E96: 0.4 | F96: =D96*E96 -> 108.56 | G96: =106.22 -> 106.22 | H96: =F96-G96 -> 2.34 | I96: 5486858 | J96: 10230186394017 | K96: NBO | L96: NBOMOMRX | M96: 99019634 | N96: 45684
A97: 95 | B97: 1477 | C97: Salim Mohammed Mahad Al Kathiri | D97: 281.9 | E97: 0.4 | F97: =D97*E97 -> 112.76 | H97: =F97-G97 -> 112.76 | I97: 18656494 | J97: 0396055887490011 | K97: Bank Muscat | L97: BMUSOMRX | M97: 92610234
A98: 96 | B98: 1480 | C98: Mohsin Ali Mahisan Houmdi Al Siari | D98: 282.6 | E98: 0.4 | F98: =D98*E98 -> 113.04 | H98: =F98-G98 -> 113.04 | I98: 19820777 | J98: 0439050442120017 | K98: Bank Muscat | L98: BMUSOMRX | M98: 92525031
A99: 97 | B99: 1482 | C99: Ahmed Abdullah Ahmed Qatmem Al marhoon | D99: 503 | E99: 0.4 | F99: =D99*E99 -> 201.2 | H99: =F99-G99 -> 201.2 | I99: 4024306 | J99: 01011165430002 | K99: Bank Dhofar | L99: BDOFOMRU | M99: 94453330
A100: 98 | B100: 1485 | C100: Salim Ali Mustahil Asat Al Shihri | D100: 323 | E100: 0.4 | F100: =D100*E100 -> 129.2 | G100: =128.05 -> 128.05 | H100: =F100-G100 -> 1.15 | I100: 18585573 | J100: 0406016500890015 | K100: Bank Muscat | L100: BMUSOMRX | M100: 92695802 | N100: 45679
...

Sheet center-dec
A1: Milk Chilling Centre(Ghado) - Monthly Camel Milk Procurement Report - 01-12-2024 TO 31-12-2024
A2: SR. NO. | B2: Farmer Code | C2: Farmer Name | D2: Total Quantity Supplied(Lits) | E2: Camel Milk Price/Lit(OMR) | F2: Total Value (OMR) | G2: Paid | H2: Balance | I2: ID No: | J2: Account No | K2: Bank Name | L2: BANK SWIFT CODE | M2: Phone No: | N2: Remarks
A3: 1 | B3: 1001 | C3: Abdul Hakim Musallam Salim Al Katini Al Rawas | D3: 273 | E3: 0.4 | F3: =D3*E3 -> 109.2 | H3: =F3-G3 -> 109.2 | I3: 2130934 | J3: 0397020829680019 | K3: Bank Muscat | L3: BMUSOMRX | M3: 92911133
A4: 2 | B4: 1007 | C4: Ahmed Abdullah Said Al Rawas | D4: 1632.4 | E4: 0.4 | F4: =D4*E4 -> 652.96 | G4: =652.27 -> 652.27 | H4: =F4-G4 -> 0.69 | I4: 1515504 | J4: 3109147237500 | K4: Oman Arab Bank | L4: OMABOMRU | M4: 91748840 | N4: 16-2-25
A5: 3 | B5: 1028 | C5: Ahmed Saeed Maatouq Al kathiri | D5: 315.4 | E5: 0.4 | F5: =D5*E5 -> 126.16 | H5: =F5-G5 -> 126.16 | I5: 802875 | J5: 0397004247250014 | K5: Bank Muscat | L5: BMUSOMRX | M5: 99498677
A6: 4 | B6: 1033 | C6: Ahmed Said Ali Al Nobi Al Kathiri | D6: 637 | E6: 0.4 | F6: =D6*E6 -> 254.8 | G6: =253.1 -> 253.1 | H6: =F6-G6 -> 1.7 | I6: 10132435 | J6: 01011076521002 | K6: Bank Dhofar | L6: BDOFOMRU | M6: 92268168 | N6: 13-2-25
A7: 5 | B7: 1040 | C7: Ahmed Said Mahad Jamaan Dhishil al Kathiri | D7: 298.8 | E7: 0.4 | F7: =D7*E7 -> 119.52 | H7: =F7-G7 -> 119.52 | I7: 25082374 | J7: 0406041201480018 | K7: Bank Muscat | L7: BMUSOMRX | M7: 99816344
A8: 6 | B8: 1044 | C8: Ahmed Salim Ahmed Al Hadi Baomar | D8: 345 | E8: 0.4 | F8: =D8*E8 -> 138 | H8: =F8-G8 -> 138 | I8: 81904 | J8: 0406003182770027 | K8: Bank Muscat | L8: BMUSOMRX | M8: 99494120
A9: 7 | B9: 1080 | C9: Ali Saeed Matoq Alkthiri | D9: 315.4 | E9: 0.4 | F9: =D9*E9 -> 126.16 | H9: =F9-G9 -> 126.16 | I9: 78762 | J9: 0397004237620018 | K9: Bank Muscat | L9: BMUSOMRX | M9: 92440088
A10: 8 | B10: 1089 | C10: Ali Said Nasib | D10: 548.7 | E10: 0.4 | F10: =D10*E10 -> 219.48 | H10: =F10-G10 -> 219.48 | I10: 892683 | J10: 1023281341086 | K10: NBO | L10: NBOMOMRX | M10: 99506162
A11: 9 | B11: 1096 | C11: Ali Salim Awadh Al Kathiri | D11: 341.3 | E11: 0.4 | F11: =D11*E11 -> 136.52 | H11: =F11-G11 -> 136.52 | I11: 1959918 | J11: 3109647718500 | K11: Oman Arab Bank | L11: OMABOMRU | M11: 92699781
A12: 10 | B12: 1106 | C12: Badar Said Masood Al Kathiri | D12: 1012 | E12: 0.4 | F12: =D12*E12 -> 404.8 | H12: =F12-G12 -> 404.8 | I12: 5502751 | J12: 10060192223001 | K12: NBO | L12: NBOMOMRX | M12: 99270001
A13: 11 | B13: 1110 | C13: Bakhit Salim Azad Al Kathiri | D13: 528 | E13: 0.4 | F13: =D13*E13 -> 211.2 | G13: =F13 -> 211.2 | H13: =F13-G13 -> 0 | I13: 934298 | J13: 0406003101920011 | K13: Bank Muscat | L13: BMUSOMRX | M13: 92811415 | N13: 20-2-25 | O13: .350 -1/25
A14: 12 | B14: 1111 | C14: Bakhit Salim Ali Shadar Al Kathiri | D14: 525.8 | E14: 0.4 | F14: =D14*E14 -> 210.32 | H14: =F14-G14 -> 210.32 | I14: 15571992 | J14: 01011058653001 | K14: Bank Dhofar | L14: BDOFOMRU | M14: 92708951
A15: 13 | B15: 1119 | C15: Ghanim Abdul Aziz Masoud Abdul Aziz Alash Al Kathiri | D15: 386.3 | E15: 0.4 | F15: =D15*E15 -> 154.52 | H15: =F15-G15 -> 154.52 | I15: 24000245 | J15: 0397020978260014 | K15: Bank Muscat | L15: BMUSOMRX | M15: 90911369
A16: 14 | B16: 1122 | C16: Hamed Hilal Said Al Kathiri | D16: 311.9 | E16: 0.4 | F16: =D16*E16 -> 124.76 | H16: =F16-G16 -> 124.76 | I16: 5219876 | J16: 0406045268200015 | K16: Bank Muscat | L16: BMUSOMRX | M16: 99066779
A17: 15 | B17: 1135 | C17: Khalid Said Ali Al Kathiri | D17: 597.6 | E17: 0.4 | F17: =D17*E17 -> 239.04 | G17: =F17 -> 239.04 | H17: =F17-G17 -> 0 | I17: 19202954 | J17: 01013808698001 | K17: Bank Dhofar | L17: BDOFOMRU | M17: 92771786 | N17: 20-2-25 | O17: 3.28 -01/25
A18: 16 | B18: 1141 | C18: Malik Said Ahmed Habkook Hat Al Shahri | D18: 506 | E18: 0.4 | F18: =D18*E18 -> 202.4 | G18: =200.11 -> 200.11 | H18: =F18-G18 -> 2.29 | I18: 11753992 | J18: 0396051591490029 | K18: Bank Muscat | L18: BMUSOMRX | M18: 99205960 | N18: 17-2-25
A19: 17 | B19: 1154 | C19: Mohammed Salim Abdullah Al kathiri | D19: 918.5 | E19: 0.4 | F19: =D19*E19 -> 367.4 | H19: =F19-G19 -> 367.4 | I19: 18654817 | J19: 0439053703720016 | K19: Bank Muscat | L19: BMUSOMRX | M19: 98887846
A20: 18 | B20: 1161 | C20: Mohammed Ali Musallam Al Nubi Al Kathiri | D20: 345 | E20: 0.4 | F20: =D20*E20 -> 138 | H20: =F20-G20 -> 138 | I20: 257926 | J20: 3109603718500 | K20: Oman Arab Bank | L20: OMABOMRU | M20: 99589267
A21: 19 | B21: 1168 | C21: Mohammed Salim Said Jumaa Al Kathiri | D21: 541.5 | E21: 0.4 | F21: =D21*E21 -> 216.6 | H21: =F21-G21 -> 216.6 | I21: 15498714 | J21: 0402012153960016 | K21: Bank Muscat | L21: BMUSOMRX | M21: 99292524
A22: 20 | B22: 1177 | C22: Said Salim Said BaitSaid | D22: 354.8 | E22: 0.4 | F22: =D22*E22 -> 141.92 | H22: =F22-G22 -> 141.92 | I22: 219353 | J22: 01010127872001 | K22: Bank Dhofar | L22: BDOFOMRU | M22: 99485534
A23: 21 | B23: 1178 | C23: Mohammed Said Mohammed Akdha Al Rawas | D23: 615.7 | E23: 0.4 | F23: =D23*E23 -> 246.28 | G23: =244.94 -> 244.94 | H23: =F23-G23 -> 1.34 | I23: 970872 | J23: 1006123229017 | K23: NBO | L23: NBOMOMRX | M23: 99485535 | N23: 45685
A24: 22 | B24: 1224 | C24: Naif Masoud Awadh Nasib Kikab Al Shihri | D24: 694.4 | E24: 0.4 | F24: =D24*E24 -> 277.76 | H24: =F24-G24 -> 277.76 | I24: 24911691 | J24: 0406060856030017 | K24: Bank Muscat | L24: BMUSOMRX | M24: 99192216
A25: 23 | B25: 1225 | C25: Naif Said Awadh Fadhl | D25: 603 | E25: 0.4 | F25: =D25*E25 -> 241.2 | H25: =F25-G25 -> 241.2 | I25: 9642357 | J25: 1501079705330 | K25: Ahli bank | L25: AUBOOMRU | M25: 99777877
A26: 24 | B26: 1235 | C26: Saeed Abdul Aziz Abdullah Al kathiri | D26: 667 | E26: 0.4 | F26: =D26*E26 -> 266.8 | H26: =F26-G26 -> 266.8 | I26: 1992436 | J26: 0402003122620013 | K26: BANK MUSCAT | L26: BMUSOMRX | M26: 99484668
A27: 25 | B27: 1241 | C27: Said Mohammed Abdallah Al kathiri | D27: 572.6 | E27: 0.4 | F27: =D27*E27 -> 229.04 | H27: =F27-G27 -> 229.04 | I27: 5343254 | J27: 0406003410830019 | K27: Bank Muscat | L27: BMUSOMRX | M27: 98964664
A28: 26 | B28: 1247 | C28: Said Salim Azad Bait Ali Badar | D28: 552 | E28: 0.4 | F28: =D28*E28 -> 220.8 | G28: =217.3 -> 217.3 | H28: =F28-G28 -> 3.5 | I28: 4748561 | J28: 01040280570002 | K28: Bank Dhofar | L28: BDOFOMRU | M28: 92345282 | N28: 20-2-25
A29: 27 | B29: 1252 | C29: Said Ahmed Ali Bait Said | D29: 506 | E29: 0.4 | F29: =D29*E29 -> 202.4 | H29: =F29-G29 -> 202.4 | I29: 2433959 | J29: 01010120819002 | K29: Bank Dhofar | L29: BDOFOMRU | M29: 93555999
A30: 28 | B30: 1258 | C30: Said Ali Musallam Al Noubi Al Kathiri | D30: 736 | E30: 0.4 | F30: =D30*E30 -> 294.4 | G30: =294.01 -> 294.01 | H30: =F30-G30 -> 0.39 | I30: 1924174 | J30: 01040280044001 | K30: Bank Dhofar | L30: BDOFOMRU | M30: 99297990 | N30: 20-2-25
A31: 29 | B31: 1260 | C31: Said Salim Ali Kibab Al Shahri | D31: 644 | E31: 0.4 | F31: =D31*E31 -> 257.6 | G31: =F31 -> 257.6 | H31: =F31-G31 -> 0 | I31: 18363579 | J31: 01041057246001 | K31: Bank Dhofar | L31: BDOFOMRU | M31: 98217444 | N31: 17-2-25 | O31: 1.56 deduct from 01-25
A32: 30 | B32: 1261 | C32: Said Ali Nasib Kikab Al shahri | D32: 361.1 | E32: 0.4 | F32: =D32*E32 -> 144.44 | H32: =F32-G32 -> 144.44 | I32: 14429332 | J32: 0406018203570028 | K32: Bank Muscat | L32: BMUSOMRX | M32: 92939445
A33: 31 | B33: 1268 | C33: Said Musallam Ali Ghawas | D33: 451.1 | E33: 0.4 | F33: =D33*E33 -> 180.44 | H33: =F33-G33 -> 180.44 | I33: 722058 | J33: 0397003940070023 | K33: Bank Muscat | L33: BMUSOMRX | M33: 92848609
A34: 32 | B34: 1282 | C34: Salim Ali Musallam Al Noubi Al Kathiri | D34: 621 | E34: 0.4 | F34: =D34*E34 -> 248.4 | G34: =2.3 -> 2.3 | H34: =F34-G34 -> 246.1 | I34: 2997747 | J34: 3109601542500 | K34: Oman Arab Bank | L34: OMABOMRU | M34: 92660969
A35: 33 | B35: 1284 | C35: Salim Ali Said Al Nubi Al Kathiri | D35: 598 | E35: 0.4 | F35: =D35*E35 -> 239.2 | G35: =238.97 -> 238.97 | H35: =F35-G35 -> 0.23 | I35: 1177598 | J35: 01040280595001 | K35: Bank Dhofar | L35: BDOFOMRU | M35: 92825228 | N35: 17-2-25
A36: 34 | B36: 1300 | C36: Salem Suhail Omer Bit Fhadel | D36: 684.2 | E36: 0.4 | F36: =D36*E36 -> 273.68 | H36: =F36-G36 -> 273.68 | I36: 19534277 | J36: 0439016892350027 | K36: Bank Muscat | L36: BMUSOMRX | M36: 99710505
A37: 35 | B37: 1306 | C37: Salim Ali Nasib Al Kathiri | D37: 366 | E37: 0.4 | F37: =D37*E37 -> 146.4 | G37: =F37 -> 146.4 | H37: =F37-G37 -> 0 | I37: 2006904 | J37: 0439051845390018 | K37: Bank Muscat | L37: BMUSOMRX | M37: 96137717 | N37: 17-2-25 | O37: .53 deduct -01-25
A38: 36 | B38: 1315 | C38: Salim Said Ali Ghawas | D38: 265.8 | E38: 0.4 | F38: =D38*E38 -> 106.32 | H38: =F38-G38 -> 106.32 | I38: 19528845 | J38: 0439026234320047 | K38: Bank Muscat | L38: BMUSOMRX | M38: 92432606
A39: 37 | B39: 1328 | C39: Suhail Saeed Suhail ghawas | D39: 410.3 | E39: 0.4 | F39: =D39*E39 -> 164.12 | H39: =F39-G39 -> 164.12 | I39: 782833 | J39: 01015382117001 | K39: Bank Dhofar | L39: BDOFOMRU | M39: 92475895
A40: 38 | B40: 1330 | C40: Said Mahad Ali Al Kathiri | D40: 640.9 | E40: 0.4 | F40: =D40*E40 -> 256.36 | H40: =F40-G40 -> 256.36 | I40: 12194826 | J40: 00510129167001 | K40: Bank Nizwa | L40: BNZWOMRX | M40: 91299100
A41: 39 | B41: 1331 | C41: Mohammed Said Musallam Al Noob Al Kathiri | D41: 345 | E41: 0.4 | F41: =D41*E41 -> 138 | H41: =F41-G41 -> 138 | I41: 2107763 | J41: 3109043578500 | K41: Oman Arab Bank | L41: OMABOMRU | M41: 93536009
A42: 40 | B42: 1333 | C42: Suhail Salim Ahmed Al Nubi Al Kathiri | D42: 572.3 | E42: 0.4 | F42: =D42*E42 -> 228.92 | H42: =F42-G42 -> 228.92 | I42: 1736679 | J42: 0401002496140031 | K42: Bank Muscat | L42: BMUSOMRX | M42: 99482212
A43: 41 | B43: 1382 | C43: Suhail Mohammed Said Ghawas Al Kathiri | D43: 663 | E43: 0.4 | F43: =D43*E43 -> 265.2 | H43: =F43-G43 -> 265.2 | I43: 886492 | J43: 0397003786810019 | K43: Bank Muscat | L43: BMUSOMRX | M43: 99494166
A44: 42 | B44: 1384 | C44: Abdul Selam Musallam Mohammed Al Rawas | D44: 272.5 | E44: 0.4 | F44: =D44*E44 -> 109 | H44: =F44-G44 -> 109 | I44: 4426701 | J44: 0406003017570013 | K44: Bank Muscat | L44: BMUSOMRX | M44: 92634991
A45: 43 | B45: 1386 | C45: Omar Salim Ahmed Al Hadi Ba Omar | D45: 736 | E45: 0.4 | F45: =D45*E45 -> 294.4 | H45: =F45-G45 -> 294.4 | I45: 711799 | J45: 0406003202280013 | K45: Bank Muscat | L45: BMUSOMRX | M45: 92394924
A46: 44 | B46: 1387 | C46: Ali Said Mahisan Kayakab Al Shihri | D46: 568.1 | E46: 0.4 | F46: =D46*E46 -> 227.24 | H46: =F46-G46 -> 227.24 | I46: 6759716 | J46: 3109117911500 | K46: Oman Arab Bank | L46: OMABOMRU | M46: 91907675
A47: 45 | B47: 1388 | C47: Tarik Suhail Salim Al Kathiri | D47: 361.6 | E47: 0.4 | F47: =D47*E47 -> 144.64 | H47: =F47-G47 -> 144.64 | I47: 18610874 | J47: 01011035504001 | K47: Bank Dhofar | L47: BDOFOMRU | M47: 93955577
A48: 46 | B48: 1389 | C48: Ali Said Musallam Al Noubi Al Kathiri | D48: 920 | E48: 0.4 | F48: =D48*E48 -> 368 | G48: =F48 -> 368 | H48: =F48-G48 -> 0 | I48: 1036354 | J48: 01010281496001 | K48: Bank Dhofar | L48: BDOFOMRU | M48: 92413881 | N48: 20-2-25 | O48: .2-01/25
A49: 47 | B49: 1394 | C49: Ali Ahmed Salim Ahmed Al Kathiri | D49: 276.1 | E49: 0.4 | F49: =D49*E49 -> 110.44 | H49: =F49-G49 -> 110.44 | I49: 25656187 | J49: 0396016034040018 | K49: Bank Muscat | L49: BMUSOMRX | M49: 98987848
A50: 48 | B50: 1396 | C50: Mustahil Ali Azad Al Kathiri | D50: 408.9 | E50: 0.4 | F50: =D50*E50 -> 163.56 | G50: =159.22 -> 159.22 | H50: =F50-G50 -> 4.34 | I50: 905845 | J50: 0397003647340016 | K50: Bank Muscat | L50: BMUSOMRX | M50: 99696204 | N50: 20-2-25
A51: 49 | B51: 1397 | C51: Ahmed Musallam Amer Al Kathiri | D51: 336.4 | E51: 0.4 | F51: =D51*E51 -> 134.56 | H51: =F51-G51 -> 134.56 | I51: 1292885 | J51: 254001118001 | K51: HSBC | L51: BBMEOMRX | M51: 92307552
A52: 50 | B52: 1398 | C52: Salim Amer Azad Al Kathiri | D52: 247.6 | E52: 0.4 | F52: =D52*E52 -> 99.04 | H52: =F52-G52 -> 99.04 | I52: 1161437 | J52: 00510128357001 | K52: Bank Nizwa | L52: BNZWOMRX | M52: 91135580
A53: 51 | B53: 1400 | C53: Manei Said Ahmed Al Kathiri | D53: 418.9 | E53: 0.4 | F53: =D53*E53 -> 167.56 | H53: =F53-G53 -> 167.56 | I53: 7223707 | J53: 10060183858001 | K53: NBO | L53: NBOMOMRX | M53: 92616136
A54: 52 | B54: 1403 | C54: Ali Salim Ahmed Al Nubi Al Kathiri | D54: 529 | E54: 0.4 | F54: =D54*E54 -> 211.6 | H54: =F54-G54 -> 211.6 | I54: 499044 | J54: 0406003202740014 | K54: Bank Muscat | L54: BMUSOMRX | M54: 92226988
A55: 53 | B55: 1406 | C55: Said Salim Musallam AlNoob Al Kathiri | D55: 444.9 | E55: 0.4 | F55: =D55*E55 -> 177.96 | H55: =F55-G55 -> 177.96 | I55: 880849 | J55: 3109015600500 | K55: Oman Arab Bank | L55: OMABOMRU | M55: 99365157
A56: 54 | B56: 1408 | C56: Abdullah Salim AhmedAl Hadi Ba Omar | D56: 1334 | E56: 0.4 | F56: =D56*E56 -> 533.6 | H56: =F56-G56 -> 533.6 | I56: 997465 | J56: 0397003981360017 | K56: Bank Muscat | L56: BMUSOMRX | M56: 99490975
A57: 55 | B57: 1409 | C57: Mahisan Ali Mahisan Al Shihri | D57: 479.1 | E57: 0.4 | F57: =D57*E57 -> 191.64 | H57: =F57-G57 -> 191.64 | I57: 7279409 | J57: 0406016730440035 | K57: Bank Muscat | L57: BMUSOMRX | M57: 99626634
A58: 56 | B58: 1410 | C58: Masoud Ali suhail Bait Said | D58: 550 | E58: 0.4 | F58: =D58*E58 -> 220 | G58: =F58 -> 220 | H58: =F58-G58 -> 0 | I58: 757372 | J58: 0406003338100019 | K58: Bank Muscat | L58: BMUSOMRX | M58: 92018800 | N58: 17-2-25 | O58: .450 deduct from 01-25
A59: 57 | B59: 1411 | C59: Said Ali Ahmed Amor Jid | D59: 607.1 | E59: 0.4 | F59: =D59*E59 -> 242.84 | G59: 239.39 | H59: =F59-G59 -> 3.45 | I59: 1650389 | J59: 0406018263680011 | K59: Bank Muscat | L59: BMUSOMRX | M59: 92294150 | N59: 17-2-25
A60: 58 | B60: 1412 | C60: Musallam Said Salim Bait Said | D60: 674.3 | E60: 0.4 | F60: =D60*E60 -> 269.72 | H60: =F60-G60 -> 269.72 | I60: 312227 | J60: 0406003457720017 | K60: Bank Muscat | L60: BMUSOMRX | M60: 95414124
A61: 59 | B61: 1413 | C61: Awadh Salim Ali Ghawas | D61: 344.6 | E61: 0.4 | F61: =D61*E61 -> 137.84 | H61: =F61-G61 -> 137.84 | I61: 539906 | J61: 01010128406001 | K61: Bank Dhofar | L61: BDOFOMRU
A62: 60 | B62: 1414 | C62: Salim Said Ali Bait Said | D62: 963.2 | E62: 0.4 | F62: =D62*E62 -> 385.28 | H62: =F62-G62 -> 385.28 | I62: 9178238 | J62: 01010852881001 | K62: Bank Dhofar | L62: BDOFOMRU | M62: 91966140
A63: 61 | B63: 1415 | C63: Ali Salim Ahmed Ali Badar al Kathiri | D63: 315.8 | E63: 0.4 | F63: =D63*E63 -> 126.32 | G63: =125.34 -> 125.34 | H63: =F63-G63 -> 0.98 | I63: 5334952 | J63: 0439003977040022 | K63: Bank Muscat | L63: BMUSOMRX | M63: 99806280 | N63: 20-2-25
A64: 62 | B64: 1417 | C64: Said Bakhit said Al mashikhi | D64: 507.6 | E64: 0.4 | F64: =D64*E64 -> 203.04 | H64: =F64-G64 -> 203.04 | I64: 1252579 | J64: 0397003628950016 | K64: Bank Muscat | L64: BMUSOMRX | M64: 98520912
A65: 63 | B65: 1418 | C65: SALIM ALI MUSALLAM GHAWAS | D65: 346 | E65: 0.4 | F65: =D65*E65 -> 138.4 | G65: =135.41 -> 135.41 | H65: =F65-G65 -> 2.99 | I65: 9954378 | J65: 0397003855180014 | K65: Bank Muscat | L65: BMUSOMRX | M65: 99282423 | N65: 45810
A66: 64 | B66: 1419 | C66: Mahad Masoud Salim Baitsaid | D66: 843 | E66: 0.4 | F66: =D66*E66 -> 337.2 | G66: =140.95 -> 140.95 | H66: =F66-G66 -> 196.25 | I66: 386821 | J66: 0406003414760015 | K66: Bank Muscat | L66: BMUSOMRX | M66: 99181419 | N66: 17-2-25
A67: 65 | B67: 1420 | C67: Salim Said Salim Al Rawas | D67: 621 | E67: 0.4 | F67: =D67*E67 -> 248.4 | H67: =F67-G67 -> 248.4 | I67: 5460297 | J67: 0402003168320014 | K67: Bank Muscat | L67: BMUSOMRX | M67: 95898899
A68: 66 | B68: 1421 | C68: Malik Musallam Salim Masoud Al Rawas | D68: 667 | E68: 0.4 | F68: =D68*E68 -> 266.8 | H68: =F68-G68 -> 266.8 | I68: 15314262 | J68: 0397019441080011 | K68: Bank Muscat | L68: BMUSOMRX | M68: 90333361
A69: 67 | B69: 1423 | C69: Ahmed Said Ali Azad Al Kathiri | D69: 601.9 | E69: 0.4 | F69: =D69*E69 -> 240.76 | H69: =F69-G69 -> 240.76 | I69: 5044397 | J69: 0397003645500016 | K69: Bank Muscat | L69: BMUSOMRX | M69: 99580550
A70: 68 | B70: 1425 | C70: Salim Mohammed Ali Al Kathiri | D70: 589.2 | E70: 0.4 | F70: =D70*E70 -> 235.68 | H70: =F70-G70 -> 235.68 | I70: 5614623 | J70: 0406002564870025 | K70: Bank Muscat | L70: BMUSOMRX | M70: 99583112
A71: 69 | B71: 1426 | C71: Ahmed Salim Ahmed Said Al Nubi Al Kathiri | D71: 621 | E71: 0.4 | F71: =D71*E71 -> 248.4 | H71: =F71-G71 -> 248.4 | I71: 2160707 | J71: 3109076938500 | K71: Oman Arab Bank | L71: OMABOMRU | M71: 92280327
A72: 70 | B72: 1427 | C72: Salim Said Mohammed Musallam Al Nubi Al kathiri | D72: 288.3 | E72: 0.4 | F72: =D72*E72 -> 115.32 | H72: =F72-G72 -> 115.32 | I72: 24171637 | J72: 0439025022760016 | K72: Bank Muscat | L72: BMUSOMRX | M72: 97030409
A73: 71 | B73: 1428 | C73: Abdullah Said Abdullah Alkthiri | D73: 320.1 | E73: 0.4 | F73: =D73*E73 -> 128.04 | G73: =F73 -> 128.04 | H73: =F73-G73 -> 0 | I73: 921364 | J73: 0406003192550017 | K73: BANK MUSCAT | L73: BMUSOMRX | M73: 92599597 | N73: 17-2-25 | O73: .06 will deduct form jan 25
A74: 72 | B74: 1430 | C74: Ahmed Said Mohammed Houmdi Al Siari | D74: 322 | E74: 0.4 | F74: =D74*E74 -> 128.8 | H74: =F74-G74 -> 128.8 | I74: 564698 | J74: 0406003186630017 | K74: Bank Muscat | L74: BMUSOMRX | M74: 99189793
A75: 73 | B75: 1432 | C75: Ali Ahmed Ali Sajlil Al shanfari | D75: 759 | E75: 0.4 | F75: =D75*E75 -> 303.6 | H75: =F75-G75 -> 303.6 | I75: 5004855 | J75: 01013803818001 | K75: Bank Dhofar | L75: BDOFOMRU | M75: 99899962
A76: 74 | B76: 1433 | C76: Ali Said Ali Bait Said | D76: 759 | E76: 0.4 | F76: =D76*E76 -> 303.6 | H76: =F76-G76 -> 303.6 | I76: 285841 | J76: 0397003981260015 | K76: Bank Muscat | L76: BMUSOMRX | M76: 92958552
A77: 75 | B77: 1434 | C77: Muhssin Said Mohammed Ghawas | D77: 347.9 | E77: 0.4 | F77: =D77*E77 -> 139.16 | H77: =F77-G77 -> 139.16 | I77: 19197503 | J77: 0403015046590039 | K77: Bank Muscat | L77: BMUSOMRX | M77: 92466605
A78: 76 | B78: 1435 | C78: Salim Said aoubad Ghawas | D78: 1010 | E78: 0.4 | F78: =D78*E78 -> 404 | G78: =403.42 -> 403.42 | H78: =F78-G78 -> 0.58 | I78: 1305522 | J78: 0397003064100017 | K78: Bank Muscat | L78: BMUSOMRX | M78: 93246263 | N78: 17-2-25
A79: 77 | B79: 1437 | C79: Ahmed Ali Ahmed Shadar Al Kathiri | D79: 667 | E79: 0.4 | F79: =D79*E79 -> 266.8 | G79: =264.59 -> 264.59 | H79: =F79-G79 -> 2.21 | I79: 9685144 | J79: 250056066001 | K79: HSBC | L79: BBMEOMRX | M79: 96907302 | N79: 20-2-25
A80: 78 | B80: 1438 | C80: Salim Aubad Al Maslamin Al Mashali | D80: 1012 | E80: 0.4 | F80: =D80*E80 -> 404.8 | H80: =F80-G80 -> 404.8 | I80: 656621 | J80: 1023386437017 | K80: NBO | L80: NBOMOMRX | M80: 92509804
A81: 79 | B81: 1439 | C81: Ahmed Musallam Salim Al Kathiri | D81: 439.2 | E81: 0.4 | F81: =D81*E81 -> 175.68 | G81: =F81 -> 175.68 | H81: =F81-G81 -> 0 | I81: 18880548 | J81: 0406060805600016 | K81: Bank Muscat | L81: BMUSOMRX | M81: 98901515 | N81: 17-2-25 | O81: .80 will deduct form 01-25
A82: 80 | B82: 1441 | C82: Musallam Said Amer Azad Al kathiri | D82: 552 | E82: 0.4 | F82: =D82*E82 -> 220.8 | H82: =F82-G82 -> 220.8 | I82: 7285624 | J82: 00510041624001 | K82: Bank Nizwa | M82: 93587666
A83: 81 | B83: 1444 | C83: Masoud Musallam Masoud Baitsaid | D83: 781.7 | E83: 0.4 | F83: =D83*E83 -> 312.68 | H83: =F83-G83 -> 312.68 | I83: 13487202 | J83: 0406003229140019 | K83: Bank Muscat | L83: BMUSOMRX | M83: 92244429
A84: 82 | B84: 1448 | C84: Salim Said Masoud Said Al Kathiri | D84: 459 | E84: 0.4 | F84: =D84*E84 -> 183.6 | H84: =F84-G84 -> 183.6 | I84: 26433121 | J84: 0397060499480017 | K84: Bank Muscat | L84: BMUSOMRX | M84: 93229244
A85: 83 | B85: 1451 | C85: Maneef Ali Abdullah Ghawas | D85: 361.6 | E85: 0.4 | F85: =D85*E85 -> 144.64 | H85: =F85-G85 -> 144.64 | I85: 20337612 | J85: 0406061272960011 | K85: Bank Muscat | L85: BMUSOMRX | M85: 98829667
A86: 84 | B86: 1453 | C86: Ahmed Said Salim Al Rawas | D86: 343.4 | E86: 0.4 | F86: =D86*E86 -> 137.36 | G86: =F86 -> 137.36 | H86: =F86-G86 -> 0 | I86: 5460259 | J86: 010010017675 | K86: Bank Sohar | L86: BSHROMRU | M86: 90199947 | N86: 20-2-25 | O86: 1.3 deduct from 01-25
A87: 85 | B87: 1455 | C87: Thuwaini Ali Musallam Ghawas | D87: 726.5 | E87: 0.4 | F87: =D87*E87 -> 290.6 | G87: =F87 -> 290.6 | H87: =F87-G87 -> 0 | I87: 9954383 | J87: 0403061364570014 | K87: Bank Muscat | L87: BMUSOMRX | M87: 93270751 | N87: 17-2-25 | O87: 1.760 will deduct from jan 25
A88: 86 | B88: 1462 | C88: Mohammed Suhail Mohammed Ghawas | D88: 343.9 | E88: 0.4 | F88: =D88*E88 -> 137.56 | H88: =F88-G88 -> 137.56 | I88: 9664038 | J88: 132247650084010 | K88: Bank Muscat | L88: BMUSOMRX | M88: 92989674
A89: 87 | B89: 1463 | C89: Said Salim Ali Aazad Al Kathiri | D89: 550.1 | E89: 0.4 | F89: =D89*E89 -> 220.04 | H89: =F89-G89 -> 220.04 | I89: 3798072 | J89: 01040280652001 | K89: Bank Dhofar | L89: BDOFOMRU | M89: 99480608
A90: 88 | B90: 1464 | C90: Ahmed Hamid Mohammed Zidi Bait Said | D90: 644 | E90: 0.4 | F90: =D90*E90 -> 257.6 | H90: =F90-G90 -> 257.6 | I90: 6352996 | J90: 01011028474002 | K90: Bank Dhofar | L90: BDOFOMRU | M90: 92463267
A91: 89 | B91: 1467 | C91: Salim Suhail Ali Al Kathiri | D91: 484 | E91: 0.4 | F91: =D91*E91 -> 193.6 | H91: =F91-G91 -> 193.6 | I91: 4279933 | J91: 01013038536001 | K91: Bank Dhofar | L91: BDOFOMRU | M91: 98510166
A92: 90 | B92: 1468 | C92: Ahmed Salim Ahmed Al Kathiri | D92: 615.4 | E92: 0.4 | F92: =D92*E92 -> 246.16 | H92: =F92-G92 -> 246.16 | I92: 6996485 | J92: 0439016595760027 | K92: Bank Muscat | L92: BMUSOMRX | M92: 92947741
A93: 91 | B93: 1472 | C93: Salim Ramas Musallam Ghawas | D93: 518.5 | E93: 0.4 | F93: =D93*E93 -> 207.4 | H93: =F93-G93 -> 207.4 | I93: 12987814 | J93: 1083702512017 | K93: NBO | L93: NBOMOMRX | M93: 99365173
A94: 92 | B94: 1473 | C94: Salim Said Mahad Alshakal Al Kathiri | D94: 336.3 | E94: 0.4 | F94: =D94*E94 -> 134.52 | H94: =F94-G94 -> 134.52 | I94: 18722784 | J94: 01010402046001 | K94: Bank Dhofar | L94: BDOFOMRU | M94: 98900644
A95: 93 | B95: 1475 | C95: Musallam Said Ahmed Al kathiri | D95: 328.2 | E95: 0.4 | F95: =D95*E95 -> 131.28 | H95: =F95-G95 -> 131.28 | I95: 4584011 | J95: 0439061793370011 | K95: Bank Muscat | L95: BMUSOMRX | M95: 98822862
A96: 94 | B96: 1476 | C96: Ali Masoud Said Al Shahri | D96: 330.8 | E96: 0.4 | F96: =D96*E96 -> 132.32 | G96: =131.41 -> 131.41 | H96: =F96-G96 -> 0.91 | I96: 5486858 | J96: 10230186394017 | K96: NBO | L96: NBOMOMRX | M96: 99019634 | N96: 20-2-25
A97: 95 | B97: 1477 | C97: Salim Mohammed Mahad Al Kathiri | D97: 314.9 | E97: 0.4 | F97: =D97*E97 -> 125.96 | H97: =F97-G97 -> 125.96 | I97: 18656494 | J97: 0396055887490011 | K97: Bank Muscat | L97: BMUSOMRX | M97: 92610234
A98: 96 | B98: 1480 | C98: Mohsin Ali Mahisan Houmdi Al Siari | D98: 343.2 | E98: 0.4 | F98: =D98*E98 -> 137.28 | H98: =F98-G98 -> 137.28 | I98: 19820777 | J98: 0439050442120017 | K98: Bank Muscat | L98: BMUSOMRX | M98: 92525031
A99: 97 | B99: 1482 | C99: Ahmed Abdullah Ahmed Qatmem Al marhoon | D99: 366.1 | E99: 0.4 | F99: =D99*E99 -> 146.44 | H99: =F99-G99 -> 146.44 | I99: 4024306 | J99: 01011165430002 | K99: Bank Dhofar | L99: BDOFOMRU | M99: 94453330
A100: 98 | B100: 1485 | C100: Salim Ali Mustahil Asat Al Shihri | D100: 383.5 | E100: 0.4 | F100: =D100*E100 -> 153.4 | G100: =F100 -> 153.4 | H100: =F100-G100 -> 0 | I100: 18585573 | J100: 0406016500890015 | K100: Bank Muscat | L100: BMUSOMRX | M100: 92695802 | N100: 20-2-25 | O100: .65-01/25
...

Sheet Aug 25
A1: Milk Chilling Centre(Ghado) - Monthly Camel Milk Procurement Report - 01-08-2025 TO 31-08-2025
A2: Farmer Code | B2: Farmer Name | C2: Total Quantity Supplied(Lits) | D2: Camel Milk Price/Lit(OMR) | E2: Total Value (OMR) | F2: Paid | G2: Balance | H2: ID No: | I2: Account No | J2: Bank Name | K2: BANK SWIFT CODE | L2: Phone No: | M2: Remarks
A3: 1001 | B3: Abdul Hakim Musallam Salim Al Katini Al Rawas | C3: 129.3 | D3: 0.4 | E3: =C3*D3 -> 51.72 | G3: =E3-F3 -> 51.72 | H3: 2130934 | I3: 0397020829680019 | J3: Bank Muscat | K3: BMUSOMRX | L3: 92911133
A4: 1007 | B4: Ahmed Abdullah Said Al Rawas | C4: 1207 | D4: 0.4 | E4: =C4*D4 -> 482.8 | F4: =1+481.8 -> 482.8 | G4: =E4-F4 -> 0 | H4: 1515504 | I4: 3109147237500 | J4: Oman Arab Bank | K4: OMABOMRU | L4: 91748840 | M4: 23-10-2025 | N4: 45912
A5: 1028 | B5: Ahmed Saeed Maatouq Al kathiri | C5: 229 | D5: 0.4 | E5: =C5*D5 -> 91.6 | F5: =E5 -> 91.6 | G5: =E5-F5 -> 0 | H5: 802875 | I5: 0397004247250014 | J5: Bank Muscat | K5: BMUSOMRX | L5: 99498677 | M5: 30-10-2025
A6: 1033 | B6: Ahmed Said Ali Al Nobi Al Kathiri | C6: 512 | D6: 0.4 | E6: =C6*D6 -> 204.8 | F6: =E6 -> 204.8 | G6: =E6-F6 -> 0 | H6: 10132435 | I6: 01011076521002 | J6: Bank Dhofar | K6: BDOFOMRU | L6: 92268168 | M6: 14-10-2025
A7: 1040 | B7: Ahmed Said Mahad Jamaan Dhishil al Kathiri | C7: 224.3 | D7: 0.4 | E7: =C7*D7 -> 89.72 | G7: =E7-F7 -> 89.72 | H7: 25082374 | I7: 0406041201480018 | J7: Bank Muscat | K7: BMUSOMRX | L7: 99816344
A8: 1044 | B8: Ahmed Salim Ahmed Al Hadi Baomar | C8: 256 | D8: 0.4 | E8: =C8*D8 -> 102.4 | F8: =99 -> 99 | G8: =E8-F8 -> 3.4 | H8: 81904 | I8: 0406003182770027 | J8: Bank Muscat | K8: BMUSOMRX | L8: 99494120 | M8: 23-12-25
A9: 1080 | B9: Ali Saeed Matoq Alkthiri | C9: 218.4 | D9: 0.4 | E9: =C9*D9 -> 87.36 | F9: =87.07+0.29 -> 87.36 | G9: =E9-F9 -> 0 | H9: 78762 | I9: 0397004237620018 | J9: Bank Muscat | K9: BMUSOMRX | L9: 92440088 | M9: 46002 | N9: 20-11-25
A10: 1089 | B10: Ali Said Nasib | C10: 406 | D10: 0.4 | E10: =C10*D10 -> 162.4 | F10: =E10 -> 162.4 | G10: =E10-F10 -> 0 | H10: 892683 | I10: 1023281341086 | J10: NBO | K10: NBOMOMRX | L10: 99506162 | M10: 14-10-2025
A11: 1096 | B11: Ali Salim Awadh Al Kathiri | C11: 224.9 | D11: 0.4 | E11: =C11*D11 -> 89.96 | G11: =E11-F11 -> 89.96 | H11: 1959918 | I11: 3109647718500 | J11: Oman Arab Bank | K11: OMABOMRU | L11: 92699781
A12: 1106 | B12: Badar Said Masood Al Kathiri | C12: 748 | D12: 0.4 | E12: =C12*D12 -> 299.2 | G12: =E12-F12 -> 299.2 | H12: 5502751 | I12: 10060192223001 | J12: NBO | K12: NBOMOMRX | L12: 99270001
A13: 1110 | B13: Bakhit Salim Azad Al Kathiri | C13: 390 | D13: 0.4 | E13: =C13*D13 -> 156 | F13: =155.1+0.9 -> 156 | G13: =E13-F13 -> 0 | H13: 934298 | I13: 0406003101920011 | J13: Bank Muscat | K13: BMUSOMRX | L13: 92811415 | M13: 45945 | N13: 45758
A14: 1111 | B14: Bakhit Salim Ali Shadar Al Kathiri | C14: 391.7 | D14: 0.4 | E14: =C14*D14 -> 156.68 | F14: =E14 -> 156.68 | G14: =E14-F14 -> 0 | H14: 15571992 | I14: 01011058653001 | J14: Bank Dhofar | K14: BDOFOMRU | L14: 92708951 | M14: 30-10-2025
A15: 1119 | B15: Ghanim Abdul Aziz Masoud Abdul Aziz Alash Al Kathiri | C15: 372 | D15: 0.4 | E15: =C15*D15 -> 148.8 | G15: =E15-F15 -> 148.8 | H15: 24000245 | I15: 0397020978260014 | J15: Bank Muscat | K15: BMUSOMRX | L15: 90911369
A16: 1122 | B16: Hamed Hilal Said Al Kathiri | C16: 237.6 | D16: 0.4 | E16: =C16*D16 -> 95.04 | F16: =94.58+0.46 -> 95.04 | G16: =E16-F16 -> 0 | H16: 5219876 | I16: 0406045268200015 | J16: Bank Muscat | K16: BMUSOMRX | L16: 99066779 | M16: 15-10-2025 | N16: 17-11-25
A17: 1135 | B17: Khalid Said Ali Al Kathiri | C17: 457.3 | D17: 0.4 | E17: =C17*D17 -> 182.92 | F17: =E17 -> 182.92 | G17: =E17-F17 -> 0 | H17: 19202954 | I17: 01013808698001 | J17: Bank Dhofar | K17: BDOFOMRU | L17: 92771786 | M17: 14-10-2025
A18: 1141 | B18: Malik Said Ahmed Habkook Hat Al Shahri | C18: 369.1 | D18: 0.4 | E18: =C18*D18 -> 147.64 | F18: =145.93+1.71 -> 147.64 | G18: =E18-F18 -> 0 | H18: 11753992 | I18: 0396051591490029 | J18: Bank Muscat | K18: BMUSOMRX | L18: 99205960 | M18: 45945 | N18: 27-10-2025
A19: 1154 | B19: Mohammed Salim Abdullah Al kathiri | C19: 642 | D19: 0.4 | E19: =C19*D19 -> 256.8 | G19: =E19-F19 -> 256.8 | H19: 18654817 | I19: 0439053703720016 | J19: Bank Muscat | K19: BMUSOMRX | L19: 98887846
A20: 1161 | B20: Mohammed Ali Musallam Al Nubi Al Kathiri | C20: 258 | D20: 0.4 | E20: =C20*D20 -> 103.2 | F20: =E20 -> 103.2 | G20: =E20-F20 -> 0 | H20: 257926 | I20: 3109603718500 | J20: Oman Arab Bank | K20: OMABOMRU | L20: 99589267 | M20: 14-10-2025
A21: 1168 | B21: Mohammed Salim Said Jumaa Al Kathiri | C21: 392.8 | D21: 0.4 | E21: =C21*D21 -> 157.12 | F21: =E21 -> 157.12 | G21: =E21-F21 -> 0 | H21: 15498714 | I21: 0402012153960016 | J21: Bank Muscat | K21: BMUSOMRX | L21: 99292524 | M21: 14-10-2025
A22: 1177 | B22: Said Salim Said BaitSaid | C22: 263.7 | D22: 0.4 | E22: =C22*D22 -> 105.48 | G22: =E22-F22 -> 105.48 | H22: 219353 | I22: 01010127872001 | J22: Bank Dhofar | K22: BDOFOMRU | L22: 99485534
A23: 1178 | B23: Mohammed Said Mohammed Akdha Al Rawas | C23: 475.2 | D23: 0.4 | E23: =C23*D23 -> 190.08 | F23: =E23 -> 190.08 | G23: =E23-F23 -> 0 | H23: 970872 | I23: 1006123229017 | J23: NBO | K23: NBOMOMRX | L23: 99485535 | M23: 45758
A24: 1224 | B24: Naif Masoud Awadh Nasib Kikab Al Shihri | C24: 530 | D24: 0.4 | E24: =C24*D24 -> 212 | F24: =E24 -> 212 | G24: =E24-F24 -> 0 | H24: 24911691 | I24: 0406060856030017 | J24: Bank Muscat | K24: BMUSOMRX | L24: 99192216 | M24: 14-10-2025
A25: 1225 | B25: Naif Said Awadh Fadhl | C25: 437 | D25: 0.4 | E25: =C25*D25 -> 174.8 | G25: =E25-F25 -> 174.8 | H25: 9642357 | I25: 1501079705330 | J25: Ahli bank | K25: AUBOOMRU | L25: 99777877
A26: 1235 | B26: Saeed Abdul Aziz Abdullah Al kathiri | C26: 493 | D26: 0.4 | E26: =C26*D26 -> 197.2 | F26: =111.3+85.9 -> 197.2 | G26: =E26-F26 -> 0 | H26: 1992436 | I26: 0402003122620013 | J26: BANK MUSCAT | K26: BMUSOMRX | L26: 99484668 | M26: 27-10-2025 | N26: 46002
A27: 1241 | B27: Said Mohammed Abdallah Al kathiri | C27: 423.6 | D27: 0.4 | E27: =C27*D27 -> 169.44 | F27: =165.02+4.42 -> 169.44 | G27: =E27-F27 -> 0 | H27: 5343254 | I27: 0406003410830019 | J27: Bank Muscat | K27: BMUSOMRX | L27: 98964664 | M27: 45758 | N27: 20-11-25
A28: 1247 | B28: Said Salim Azad Bait Ali Badar | C28: 406 | D28: 0.4 | E28: =C28*D28 -> 162.4 | F28: =158.25+4.15 -> 162.4 | G28: =E28-F28 -> 0 | H28: 4748561 | I28: 01040280570002 | J28: Bank Dhofar | K28: BDOFOMRU | L28: 92345282 | M28: 45945 | N28: 45758
A29: 1252 | B29: Said Ahmed Ali Bait Said | C29: 355.6 | D29: 0.4 | E29: =C29*D29 -> 142.24 | G29: =E29-F29 -> 142.24 | H29: 2433959 | I29: 01010120819002 | J29: Bank Dhofar | K29: BDOFOMRU | L29: 93555999
A30: 1258 | B30: Said Ali Musallam Al Noubi Al Kathiri | C30: 544 | D30: 0.4 | E30: =C30*D30 -> 217.6 | F30: =215.15+2.45 -> 217.6 | G30: =E30-F30 -> 0 | H30: 1924174 | I30: 01040280044001 | J30: Bank Dhofar | K30: BDOFOMRU | L30: 99297990 | M30: 45945 | N30: 46002
A31: 1260 | B31: Said Salim Ali Kibab Al Shahri | C31: 476 | D31: 0.4 | E31: =C31*D31 -> 190.4 | F31: =E31 -> 190.4 | G31: =E31-F31 -> 0 | H31: 18363579 | I31: 01041057246001 | J31: Bank Dhofar | K31: BDOFOMRU | L31: 98217444 | M31: 45972
A32: 1261 | B32: Said Ali Nasib Kikab Al shahri | C32: 251.4 | D32: 0.4 | E32: =C32*D32 -> 100.56 | F32: =97.958+2.602 -> 100.56 | G32: =E32-F32 -> 0 | H32: 14429332 | I32: 0406018203570028 | J32: Bank Muscat | K32: BMUSOMRX | L32: 92939445 | M32: 20-10-2025 | N32: 20-11-25
A33: 1268 | B33: Said Musallam Ali Ghawas | C33: 160 | D33: 0.4 | E33: =C33*D33 -> 64 | F33: =61.04+2.96 -> 64 | G33: =E33-F33 -> 0 | H33: 722058 | I33: 0397003940070023 | J33: Bank Muscat | K33: BMUSOMRX | L33: 92848609 | M33: 45945 | N33: 45758
A34: 1282 | B34: Salim Ali Musallam Al Noubi Al Kathiri | C34: 474 | D34: 0.4 | E34: =C34*D34 -> 189.6 | F34: =E34 -> 189.6 | G34: =E34-F34 -> 0 | H34: 2997747 | I34: 3109601542500 | J34: Oman Arab Bank | K34: OMABOMRU | L34: 92660969 | M34: 14-10-2025
A35: 1284 | B35: Salim Ali Said Al Nubi Al Kathiri | C35: 448 | D35: 0.4 | E35: =C35*D35 -> 179.2 | F35: =177.9+1.3 -> 179.2 | G35: =E35-F35 -> 0 | H35: 1177598 | I35: 01040280595001 | J35: Bank Dhofar | K35: BDOFOMRU | L35: 92825228 | M35: 20-10-2025 | N35: 16-12-25
A36: 1300 | B36: Salem Suhail Omer Bit Fhadel | C36: 544 | D36: 0.4 | E36: =C36*D36 -> 217.6 | F36: 213.75 | G36: =E36-F36 -> 3.85 | H36: 19534277 | I36: 0439016892350027 | J36: Bank Muscat | K36: BMUSOMRX | L36: 99710505 | M36: 16-12-25
A37: 1306 | B37: Salim Ali Nasib Al Kathiri | C37: 260 | D37: 0.4 | E37: =C37*D37 -> 104 | F37: =E37 -> 104 | G37: =E37-F37 -> 0 | H37: 2006904 | I37: 0439051845390018 | J37: Bank Muscat | K37: BMUSOMRX | L37: 96137717 | M37: 14-10-2025
A38: 1315 | B38: Salim Said Ali Ghawas | C38: 226.8 | D38: 0.4 | E38: =C38*D38 -> 90.72 | G38: =E38-F38 -> 90.72 | H38: 19528845 | I38: 0439026234320047 | J38: Bank Muscat | K38: BMUSOMRX | L38: 92432606
A39: 1328 | B39: Suhail Saeed Suhail ghawas | C39: 300.2 | D39: 0.4 | E39: =C39*D39 -> 120.08 | F39: =115.91+4.17 -> 120.08 | G39: =E39-F39 -> 0 | H39: 782833 | I39: 01015382117001 | J39: Bank Dhofar | K39: BDOFOMRU | L39: 92475895 | M39: 20-10-25 | N39: 30-10-2025
A40: 1330 | B40: Said Mahad Ali Al Kathiri | C40: 473.5 | D40: 0.4 | E40: =C40*D40 -> 189.4 | F40: =189.25+0.15 -> 189.4 | G40: =E40-F40 -> 0 | H40: 12194826 | I40: 00510129167001 | J40: Bank Nizwa | K40: BNZWOMRX | L40: 91299100 | M40: 45945 | N40: 45758
A41: 1331 | B41: Mohammed Said Musallam Al Noob Al Kathiri | C41: 256 | D41: 0.4 | E41: =C41*D41 -> 102.4 | F41: =E41 -> 102.4 | G41: =E41-F41 -> 0 | H41: 2107763 | I41: 3109043578500 | J41: Oman Arab Bank | K41: OMABOMRU | L41: 93536009 | M41: 24-12-25
A42: 1333 | B42: Suhail Salim Ahmed Al Nubi Al Kathiri | C42: 420.7 | D42: 0.4 | E42: =C42*D42 -> 168.28 | F42: =164.93+3.35 -> 168.28 | G42: =E42-F42 -> 0 | H42: 1736679 | I42: 0401002496140031 | J42: Bank Muscat | K42: BMUSOMRX | L42: 99482212 | M42: 45945 | N42: 45972
A43: 1382 | B43: Suhail Mohammed Said Ghawas Al Kathiri | C43: 481 | D43: 0.4 | E43: =C43*D43 -> 192.4 | F43: =187.75+4.65 -> 192.4 | G43: =E43-F43 -> 0 | H43: 886492 | I43: 0397003786810019 | J43: Bank Muscat | K43: BMUSOMRX | L43: 99494166 | M43: 45945 | N43: 45788
A44: 1384 | B44: Abdul Selam Musallam Mohammed Al Rawas | C44: 178.5 | D44: 0.4 | E44: =C44*D44 -> 71.4 | G44: =E44-F44 -> 71.4 | H44: 4426701 | I44: 0406003017570013 | J44: Bank Muscat | K44: BMUSOMRX | L44: 92634991
A45: 1386 | B45: Omar Salim Ahmed Al Hadi Ba Omar | C45: 544 | D45: 0.4 | E45: =C45*D45 -> 217.6 | F45: =0.04+217.56 -> 217.6 | G45: =E45-F45 -> 0 | H45: 711799 | I45: 0406003202280013 | J45: Bank Muscat | K45: BMUSOMRX | L45: 92394924 | M45: 45931 | N45: 24-11-25
A46: 1387 | B46: Ali Said Mahisan Kayakab Al Shihri | C46: 445.7 | D46: 0.4 | E46: =C46*D46 -> 178.28 | G46: =E46-F46 -> 178.28 | H46: 6759716 | I46: 3109117911500 | J46: Oman Arab Bank | K46: OMABOMRU | L46: 91907675
A47: 1388 | B47: Tarik Suhail Salim Al Kathiri | C47: 269 | D47: 0.4 | E47: =C47*D47 -> 107.6 | G47: =E47-F47 -> 107.6 | H47: 18610874 | I47: 01011035504001 | J47: Bank Dhofar | K47: BDOFOMRU | L47: 93955577
A48: 1389 | B48: Ali Said Musallam Al Noubi Al Kathiri | C48: 680 | D48: 0.4 | E48: =C48*D48 -> 272 | F48: =E48 -> 272 | G48: =E48-F48 -> 0 | H48: 1036354 | I48: 01010281496001 | J48: Bank Dhofar | K48: BDOFOMRU | L48: 92413881 | M48: 27-10-2025
A49: 1394 | B49: Ali Ahmed Salim Ahmed Al Kathiri | C49: 295.5 | D49: 0.4 | E49: =C49*D49 -> 118.2 | F49: =117.21+0.99 -> 118.2 | G49: =E49-F49 -> 0 | H49: 25656187 | I49: 0396016034040018 | J49: Bank Muscat | K49: BMUSOMRX | L49: 98987848 | M49: 45945 | N49: 27-10-2025
A50: 1396 | B50: Mustahil Ali Azad Al Kathiri | C50: 306 | D50: 0.4 | E50: =C50*D50 -> 122.4 | F50: =119.14+3.26 -> 122.4 | G50: =E50-F50 -> 0 | H50: 905845 | I50: 0397003647340016 | J50: Bank Muscat | K50: BMUSOMRX | L50: 99696204 | M50: 20-10-2025 | N50: 30-10-2025
A51: 1397 | B51: Ahmed Musallam Amer Al Kathiri | C51: 243.3 | D51: 0.4 | E51: =C51*D51 -> 97.32 | F51: =E51 -> 97.32 | G51: =E51-F51 -> 0 | H51: 1292885 | I51: 254001118001 | J51: HSBC | K51: BBMEOMRX | L51: 92307552 | M51: 14-10-2025
A52: 1398 | B52: Salim Amer Azad Al Kathiri | C52: 203.4 | D52: 0.4 | E52: =C52*D52 -> 81.36 | F52: =E52 -> 81.36 | G52: =E52-F52 -> 0 | H52: 1161437 | I52: 00510128357001 | J52: Bank Nizwa | K52: BNZWOMRX | L52: 91135580 | M52: 45945
A53: 1400 | B53: Manei Said Ahmed Al Kathiri | C53: 450 | D53: 0.4 | E53: =C53*D53 -> 180 | F53: =E53 -> 180 | G53: =E53-F53 -> 0 | H53: 7223707 | I53: 10060183858001 | J53: NBO | K53: NBOMOMRX | L53: 92616136 | M53: 30-10-2025
A54: 1403 | B54: Ali Salim Ahmed Al Nubi Al Kathiri | C54: 386.6 | D54: 0.4 | E54: =C54*D54 -> 154.64 | F54: =151.77+2.87 -> 154.64 | G54: =E54-F54 -> 0 | H54: 499044 | I54: 0406003202740014 | J54: Bank Muscat | K54: BMUSOMRX | L54: 92226988 | M54: 45945 | N54: 45788
A55: 1406 | B55: Said Salim Musallam AlNoob Al Kathiri | C55: 340 | D55: 0.4 | E55: =C55*D55 -> 136 | F55: =132.4+3.6 -> 136 | G55: =E55-F55 -> 0 | H55: 880849 | I55: 3109015600500 | J55: Oman Arab Bank | K55: OMABOMRU | L55: 99365157 | M55: 45945 | N55: 45758
A56: 1408 | B56: Abdullah Salim AhmedAl Hadi Ba Omar | C56: 985 | D56: 0.4 | E56: =C56*D56 -> 394 | F56: =390.341+3.659 -> 394 | G56: =E56-F56 -> 0 | H56: 997465 | I56: 0397003981360017 | J56: Bank Muscat | K56: BMUSOMRX | L56: 99490975 | M56: 20-10-2025 | N56: 24-11-25
A57: 1409 | B57: Mahisan Ali Mahisan Al Shihri | C57: 359.8 | D57: 0.4 | E57: =C57*D57 -> 143.92 | F57: =E57 -> 143.92 | G57: =E57-F57 -> 0 | H57: 7279409 | I57: 0406016730440035 | J57: Bank Muscat | K57: BMUSOMRX | L57: 99626634 | M57: 14-10-2025
A58: 1410 | B58: Masoud Ali suhail Bait Said | C58: 417.5 | D58: 0.4 | E58: =C58*D58 -> 167 | F58: =E58 -> 167 | G58: =E58-F58 -> 0 | H58: 757372 | I58: 0406003338100019 | J58: Bank Muscat | K58: BMUSOMRX | L58: 92018800 | M58: 45972
A59: 1411 | B59: Said Ali Ahmed Amor Jid | C59: 443.1 | D59: 0.4 | E59: =C59*D59 -> 177.24 | F59: =173.89+3.35 -> 177.24 | G59: =E59-F59 -> 0 | H59: 1650389 | I59: 0406018263680011 | J59: Bank Muscat | K59: BMUSOMRX | L59: 92294150 | M59: 45945 | N59: 45758
A60: 1412 | B60: Musallam Said Salim Bait Said | C60: 510 | D60: 0.4 | E60: =C60*D60 -> 204 | G60: =E60-F60 -> 204 | H60: 312227 | I60: 0406003457720017 | J60: Bank Muscat | K60: BMUSOMRX | L60: 95414124
A61: 1413 | B61: Awadh Salim Ali Ghawas | C61: 261 | D61: 0.4 | E61: =C61*D61 -> 104.4 | F61: =E61 -> 104.4 | G61: =E61-F61 -> 0 | H61: 539906 | I61: 01010128406001 | J61: Bank Dhofar | K61: BDOFOMRU | M61: 14-10-2025
A62: 1414 | B62: Salim Said Ali Bait Said | C62: 730.8 | D62: 0.4 | E62: =C62*D62 -> 292.32 | G62: =E62-F62 -> 292.32 | H62: 9178238 | I62: 01010852881001 | J62: Bank Dhofar | K62: BDOFOMRU | L62: 91966140
A63: 1415 | B63: Ali Salim Ahmed Ali Badar al Kathiri | C63: 200.8 | D63: 0.4 | E63: =C63*D63 -> 80.32 | F63: =0.1+79.2+1.02 -> 80.32 | G63: =E63-F63 -> 0 | H63: 5334952 | I63: 0439003977040022 | J63: Bank Muscat | K63: BMUSOMRX | L63: 99806280 | M63: 29.9.2025 | N63: 45945 | O63: 45972
A64: 1417 | B64: Said Bakhit said Al mashikhi | C64: 374 | D64: 0.4 | E64: =C64*D64 -> 149.6 | F64: =E64 -> 149.6 | G64: =E64-F64 -> 0 | H64: 1252579 | I64: 0397003628950016 | J64: Bank Muscat | K64: BMUSOMRX | L64: 98520912 | M64: 27-10-2025
A65: 1418 | B65: SALIM ALI MUSALLAM GHAWAS | C65: 332 | D65: 0.4 | E65: =C65*D65 -> 132.8 | F65: =128.32+4.48 -> 132.8 | G65: =E65-F65 -> 0 | H65: 9954378 | I65: 0397003855180014 | J65: Bank Muscat | K65: BMUSOMRX | L65: 99282423 | M65: 29.9.2025 | N65: 20-10-2025
A66: 1419 | B66: Mahad Masoud Salim Baitsaid | C66: 606 | D66: 0.4 | E66: =C66*D66 -> 242.4 | F66: =E66 -> 242.4 | G66: =E66-F66 -> 0 | H66: 386821 | I66: 0406003414760015 | J66: Bank Muscat | K66: BMUSOMRX | L66: 99181419 | M66: BT 28-9-2025
A67: 1420 | B67: Salim Said Salim Al Rawas | C67: 459 | D67: 0.4 | E67: =C67*D67 -> 183.6 | G67: =E67-F67 -> 183.6 | H67: 5460297 | I67: 0402003168320014 | J67: Bank Muscat | K67: BMUSOMRX | L67: 95898899
A68: 1421 | B68: Malik Musallam Salim Masoud Al Rawas | C68: 493 | D68: 0.4 | E68: =C68*D68 -> 197.2 | F68: =E68 -> 197.2 | G68: =E68-F68 -> 0 | H68: 15314262 | I68: 0397019441080011 | J68: Bank Muscat | K68: BMUSOMRX | L68: 90333361 | M68: 14-10-2025
A69: 1423 | B69: Ahmed Said Ali Azad Al Kathiri | C69: 450 | D69: 0.4 | E69: =C69*D69 -> 180 | G69: =E69-F69 -> 180 | H69: 5044397 | I69: 0397003645500016 | J69: Bank Muscat | K69: BMUSOMRX | L69: 99580550
A70: 1425 | B70: Salim Mohammed Ali Al Kathiri | C70: 431.2 | D70: 0.4 | E70: =C70*D70 -> 172.48 | F70: =172.19+0.29 -> 172.48 | G70: =E70-F70 -> 0 | H70: 5614623 | I70: 0406002564870025 | J70: Bank Muscat | K70: BMUSOMRX | L70: 99583112 | M70: 45945 | N70: 45758
A71: 1426 | B71: Ahmed Salim Ahmed Said Al Nubi Al Kathiri | C71: 430.7 | D71: 0.4 | E71: =C71*D71 -> 172.28 | F71: =E71 -> 172.28 | G71: =E71-F71 -> 0 | H71: 2160707 | I71: 3109076938500 | J71: Oman Arab Bank | K71: OMABOMRU | L71: 92280327 | M71: 14-10-2025
A72: 1427 | B72: Salim Said Mohammed Musallam Al Nubi Al kathiri | C72: 234.8 | D72: 0.4 | E72: =C72*D72 -> 93.92 | F72: =E72 -> 93.92 | G72: =E72-F72 -> 0 | H72: 24171637 | I72: 0439025022760016 | J72: Bank Muscat | K72: BMUSOMRX | L72: 97030409 | M72: 14-10-2025
A73: 1428 | B73: Abdullah Said Abdullah Alkthiri | C73: 231.4 | D73: 0.4 | E73: =C73*D73 -> 92.56 | F73: =92.1+0.46 -> 92.56 | G73: =E73-F73 -> 0 | H73: 921364 | I73: 0406003192550017 | J73: BANK MUSCAT | K73: BMUSOMRX | L73: 92599597 | M73: 14-10-2025 | N73: 30-10-2025
A74: 1430 | B74: Ahmed Said Mohammed Houmdi Al Siari | C74: 238 | D74: 0.4 | E74: =C74*D74 -> 95.2 | F74: =94.98+0.22 -> 95.2 | G74: =E74-F74 -> 0 | H74: 564698 | I74: 0406003186630017 | J74: Bank Muscat | K74: BMUSOMRX | L74: 99189793 | M74: 45945 | N74: 45758
A75: 1432 | B75: Ali Ahmed Ali Sajlil Al shanfari | C75: 560.9 | D75: 0.4 | E75: =C75*D75 -> 224.36 | G75: =E75-F75 -> 224.36 | H75: 5004855 | I75: 01013803818001 | J75: Bank Dhofar | K75: BDOFOMRU | L75: 99899962
A76: 1433 | B76: Ali Said Ali Bait Said | C76: 562 | D76: 0.4 | E76: =C76*D76 -> 224.8 | F76: =222.05+2.75 -> 224.8 | G76: =E76-F76 -> 0 | H76: 285841 | I76: 0397003981260015 | J76: Bank Muscat | K76: BMUSOMRX | L76: 92958552 | M76: 45788 | N76: 17-11-25
A77: 1434 | B77: Muhssin Said Mohammed Ghawas | C77: 272.8 | D77: 0.4 | E77: =C77*D77 -> 109.12 | F77: =106.43+2.69 -> 109.12 | G77: =E77-F77 -> 0 | H77: 19197503 | I77: 0403015046590039 | J77: Bank Muscat | K77: BMUSOMRX | L77: 92466605 | M77: 20-11-25 | N77: 16-12-25
A78: 1435 | B78: Salim Said aoubad Ghawas | C78: 727 | D78: 0.4 | E78: =C78*D78 -> 290.8 | F78: =289.55+1.25 -> 290.8 | G78: =E78-F78 -> 0 | H78: 1305522 | I78: 0397003064100017 | J78: Bank Muscat | K78: BMUSOMRX | L78: 93246263 | M78: 45945 | N78: 45972
A79: 1437 | B79: Ahmed Ali Ahmed Shadar Al Kathiri | C79: 488 | D79: 0.4 | E79: =C79*D79 -> 195.2 | F79: =191.34+3.86 -> 195.2 | G79: =E79-F79 -> 0 | H79: 9685144 | I79: 250056066001 | J79: HSBC | K79: BBMEOMRX | L79: 96907302 | M79: 45945 | N79: 30-10-2025
A80: 1438 | B80: Salim Aubad Al Maslamin Al Mashali | C80: 750 | D80: 0.4 | E80: =C80*D80 -> 300 | F80: =E80 -> 300 | G80: =E80-F80 -> 0 | H80: 656621 | I80: 1023386437017 | J80: NBO | K80: NBOMOMRX | L80: 92509804 | M80: 14-10-2025
A81: 1439 | B81: Ahmed Musallam Salim Al Kathiri | C81: 368 | D81: 0.4 | E81: =C81*D81 -> 147.2 | F81: =E81 -> 147.2 | G81: =E81-F81 -> 0 | H81: 18880548 | I81: 0406060805600016 | J81: Bank Muscat | K81: BMUSOMRX | L81: 98901515 | M81: 45945
A82: 1441 | B82: Musallam Said Amer Azad Al kathiri | C82: 407.4 | D82: 0.4 | E82: =C82*D82 -> 162.96 | F82: =E82 -> 162.96 | G82: =E82-F82 -> 0 | H82: 7285624 | I82: 00510041624001 | J82: Bank Nizwa | L82: 93587666 | M82: 15-10-2025
A83: 1444 | B83: Masoud Musallam Masoud Baitsaid | C83: 580 | D83: 0.4 | E83: =C83*D83 -> 232 | G83: =E83-F83 -> 232 | H83: 13487202 | I83: 0406003229140019 | J83: Bank Muscat | K83: BMUSOMRX | L83: 92244429
A84: 1448 | B84: Salim Said Masoud Said Al Kathiri | C84: 315.9 | D84: 0.4 | E84: =C84*D84 -> 126.36 | F84: =121.81+4.55 -> 126.36 | G84: =E84-F84 -> 0 | H84: 26433121 | I84: 0397060499480017 | J84: Bank Muscat | K84: BMUSOMRX | L84: 93229244 | M84: 45945 | N84: 45758
A85: 1451 | B85: Maneef Ali Abdullah Ghawas | C85: 266 | D85: 0.4 | E85: =C85*D85 -> 106.4 | G85: =E85-F85 -> 106.4 | H85: 20337612 | I85: 0406061272960011 | J85: Bank Muscat | K85: BMUSOMRX | L85: 98829667
A86: 1453 | B86: Ahmed Said Salim Al Rawas | C86: 256 | D86: 0.4 | E86: =C86*D86 -> 102.4 | F86: =E86 -> 102.4 | G86: =E86-F86 -> 0 | H86: 5460259 | I86: 010010017675 | J86: Bank Sohar | K86: BSHROMRU | L86: 90199947 | M86: 14-10-2025
A87: 1455 | B87: Thuwaini Ali Musallam Ghawas | C87: 448 | D87: 0.4 | E87: =C87*D87 -> 179.2 | F87: =177.5+1.7 -> 179.2 | G87: =E87-F87 -> 0 | H87: 9954383 | I87: 0403061364570014 | J87: Bank Muscat | K87: BMUSOMRX | L87: 93270751 | M87: 45945 | N87: 45758
A88: 1462 | B88: Mohammed Suhail Mohammed Ghawas | C88: 259.1 | D88: 0.4 | E88: =C88*D88 -> 103.64 | F88: =99.86+3.78 -> 103.64 | G88: =E88-F88 -> 0 | H88: 9664038 | I88: 132247650084010 | J88: Bank Muscat | K88: BMUSOMRX | L88: 92989674 | M88: 45945 | N88: 45788
A89: 1463 | B89: Said Salim Ali Aazad Al Kathiri | C89: 405 | D89: 0.4 | E89: =C89*D89 -> 162 | F89: =E89 -> 162 | G89: =E89-F89 -> 0 | H89: 3798072 | I89: 01040280652001 | J89: Bank Dhofar | K89: BDOFOMRU | L89: 99480608 | M89: 45669
A90: 1464 | B90: Ahmed Hamid Mohammed Zidi Bait Said | C90: 476.8 | D90: 0.4 | E90: =C90*D90 -> 190.72 | F90: =E90 -> 190.72 | G90: =E90-F90 -> 0 | H90: 6352996 | I90: 01011028474002 | J90: Bank Dhofar | K90: BDOFOMRU | L90: 92463267 | M90: 45972
A91: 1467 | B91: Salim Suhail Ali Al Kathiri | C91: 360.6 | D91: 0.4 | E91: =C91*D91 -> 144.24 | G91: =E91-F91 -> 144.24 | H91: 4279933 | I91: 01013038536001 | J91: Bank Dhofar | K91: BDOFOMRU | L91: 98510166
A92: 1468 | B92: Ahmed Salim Ahmed Al Kathiri | C92: 495.5 | D92: 0.4 | E92: =C92*D92 -> 198.2 | F92: =E92 -> 198.2 | G92: =E92-F92 -> 0 | H92: 6996485 | I92: 0439016595760027 | J92: Bank Muscat | K92: BMUSOMRX | L92: 92947741 | M92: 22-10-25
A93: 1472 | B93: Salim Ramas Musallam Ghawas | C93: 379.4 | D93: 0.4 | E93: =C93*D93 -> 151.76 | F93: =149.83+1.93 -> 151.76 | G93: =E93-F93 -> 0 | H93: 12987814 | I93: 1083702512017 | J93: NBO | K93: NBOMOMRX | L93: 99365173 | M93: 45945 | N93: 30-10-2025
A94: 1473 | B94: Salim Said Mahad Alshakal Al Kathiri | C94: 441.5 | D94: 0.4 | E94: =C94*D94 -> 176.6 | G94: =E94-F94 -> 176.6 | H94: 18722784 | I94: 01010402046001 | J94: Bank Dhofar | K94: BDOFOMRU | L94: 98900644
A95: 1475 | B95: Musallam Said Ahmed Al kathiri | C95: 265 | D95: 0.4 | E95: =C95*D95 -> 106 | F95: =103.53+2.47 -> 106 | G95: =E95-F95 -> 0 | H95: 4584011 | I95: 0439061793370011 | J95: Bank Muscat | K95: BMUSOMRX | L95: 98822862 | M95: 45945 | N95: 24-11-25
A96: 1476 | B96: Ali Masoud Said Al Shahri | C96: 245.8 | D96: 0.4 | E96: =C96*D96 -> 98.32 | F96: =E96 -> 98.32 | G96: =E96-F96 -> 0 | H96: 5486858 | I96: 10230186394017 | J96: NBO | K96: NBOMOMRX | L96: 99019634 | M96: 14-10-2025
A97: 1477 | B97: Salim Mohammed Mahad Al Kathiri | C97: 225.1 | D97: 0.4 | E97: =C97*D97 -> 90.04 | G97: =E97-F97 -> 90.04 | H97: 18656494 | I97: 0396055887490011 | J97: Bank Muscat | K97: BMUSOMRX | L97: 92610234
A98: 1480 | B98: Mohsin Ali Mahisan Houmdi Al Siari | C98: 255 | D98: 0.4 | E98: =C98*D98 -> 102 | F98: =98.22+3.78 -> 102 | G98: =E98-F98 -> 0 | H98: 19820777 | I98: 0439050442120017 | J98: Bank Muscat | K98: BMUSOMRX | L98: 92525031 | M98: 45945 | N98: 45758
A99: 1482 | B99: Ahmed Abdullah Ahmed Qatmem Al marhoon | C99: 455 | D99: 0.4 | E99: =C99*D99 -> 182 | F99: =E99 -> 182 | G99: =E99-F99 -> 0 | H99: 4024306 | I99: 01011165430002 | J99: Bank Dhofar | K99: BDOFOMRU | L99: 94453330 | M99: 45912
A100: 1485 | B100: Salim Ali Mustahil Asat Al Shihri | C100: 244.6 | D100: 0.4 | E100: =C100*D100 -> 97.84 | F100: =E100 -> 97.84 | G100: =E100-F100 -> 0 | H100: 18585573 | I100: 0406016500890015 | J100: Bank Muscat | K100: BMUSOMRX | L100: 92695802 | M100: 20-10-2025
...

Sheet SEP-25
A1: Milk Chilling Centre(Ghado) - Monthly Camel Milk Procurement Report - 01-08-2025 TO 31-08-2025
A2: Farmer Code | B2: Farmer Name | C2: Total Quantity Supplied(Lits) | D2: Camel Milk Price/Lit(OMR) | E2: Total Value (OMR) | G2: Balance | H2: ID No: | I2: Account No | J2: Bank Name | K2: BANK SWIFT CODE | L2: Phone No: | M2: Remarks
A3: 1001 | B3: Abdul Hakim Musallam Salim Al Katini Al Rawas | C3: 212 | D3: 0.3 | E3: =C3*D3 -> 63.6 | G3: =E3-F3 -> 63.6 | H3: 2130934 | I3: 0397020829680019 | J3: Bank Muscat | K3: BMUSOMRX | L3: 92911133
A4: 1007 | B4: Ahmed Abdullah Said Al Rawas | C4: 1278 | D4: 0.3 | E4: =C4*D4 -> 383.4 | F4: =379.5+3.9 -> 383.4 | G4: =E4-F4 -> 0 | H4: 1515504 | I4: 3109147237500 | J4: Oman Arab Bank | K4: OMABOMRU | L4: 91748840 | M4: 45912 | N4: 31-12-2025
A5: 1028 | B5: Ahmed Saeed Maatouq Al kathiri | C5: 245 | D5: 0.3 | E5: =C5*D5 -> 73.5 | F5: =69.99+3.51 -> 73.5 | G5: =E5-F5 -> 0 | H5: 802875 | I5: 0397004247250014 | J5: Bank Muscat | K5: BMUSOMRX | L5: 99498677 | M5: 30-10-2025 | N5: 24-12-25
A6: 1033 | B6: Ahmed Said Ali Al Nobi Al Kathiri | C6: 750.3 | D6: 0.3 | E6: =C6*D6 -> 225.09 | F6: =2.45+222.64 -> 225.09 | G6: =E6-F6 -> 0 | H6: 10132435 | I6: 01011076521002 | J6: Bank Dhofar | K6: BDOFOMRU | L6: 92268168 | M6: 14-10-2025 | N6: 45758 | O6: .110-10-25
A7: 1040 | B7: Ahmed Said Mahad Jamaan Dhishil al Kathiri | C7: 234 | D7: 0.3 | E7: =C7*D7 -> 70.2 | G7: =E7-F7 -> 70.2 | H7: 25082374 | I7: 0406041201480018 | J7: Bank Muscat | K7: BMUSOMRX | L7: 99816344
A8: 1044 | B8: Ahmed Salim Ahmed Al Hadi Baomar | C8: 267.5 | D8: 0.3 | E8: =C8*D8 -> 80.25 | G8: =E8-F8 -> 80.25 | H8: 81904 | I8: 0406003182770027 | J8: Bank Muscat | K8: BMUSOMRX | L8: 99494120
A9: 1080 | B9: Ali Saeed Matoq Alkthiri | C9: 238.7 | D9: 0.3 | E9: =C9*D9 -> 71.61 | F9: =69.01+2.6 -> 71.61 | G9: =E9-F9 -> 0 | H9: 78762 | I9: 0397004237620018 | J9: Bank Muscat | K9: BMUSOMRX | L9: 92440088 | M9: 20-11-25 | N9: 16-12-25
A10: 1089 | B10: Ali Said Nasib | C10: 424.4 | D10: 0.3 | E10: =C10*D10 -> 127.32 | F10: =3.61999999999999+123.7 -> 127.32 | G10: =E10-F10 -> 0 | H10: 892683 | I10: 1023281341086 | J10: NBO | K10: NBOMOMRX | L10: 99506162 | M10: 14-10-2025 | N10: 45788
A11: 1096 | B11: Ali Salim Awadh Al Kathiri | C11: 253.7 | D11: 0.3 | E11: =C11*D11 -> 76.11 | G11: =E11-F11 -> 76.11 | H11: 1959918 | I11: 3109647718500 | J11: Oman Arab Bank | K11: OMABOMRU | L11: 92699781
A12: 1106 | B12: Badar Said Masood Al Kathiri | C12: 788 | D12: 0.3 | E12: =C12*D12 -> 236.4 | G12: =E12-F12 -> 236.4 | H12: 5502751 | I12: 10060192223001 | J12: NBO | K12: NBOMOMRX | L12: 99270001
A13: 1110 | B13: Bakhit Salim Azad Al Kathiri | C13: 414 | D13: 0.3 | E13: =C13*D13 -> 124.2 | F13: =122.85+1.35 -> 124.2 | G13: =E13-F13 -> 0 | H13: 934298 | I13: 0406003101920011 | J13: Bank Muscat | K13: BMUSOMRX | L13: 92811415 | M13: 45758 | N13: 16-12-25
A14: 1111 | B14: Bakhit Salim Ali Shadar Al Kathiri | C14: 432.5 | D14: 0.3 | E14: =C14*D14 -> 129.75 | F14: =127.33+2.42 -> 129.75 | G14: =E14-F14 -> 0 | H14: 15571992 | I14: 01011058653001 | J14: Bank Dhofar | K14: BDOFOMRU | L14: 92708951 | M14: 30-10-2025 | N14: 16-12-25
A15: 1119 | B15: Ghanim Abdul Aziz Masoud Abdul Aziz Alash Al Kathiri | C15: 373 | D15: 0.3 | E15: =C15*D15 -> 111.9 | G15: =E15-F15 -> 111.9 | H15: 24000245 | I15: 0397020978260014 | J15: Bank Muscat | K15: BMUSOMRX | L15: 90911369
A16: 1122 | B16: Hamed Hilal Said Al Kathiri | C16: 242.3 | D16: 0.3 | E16: =C16*D16 -> 72.69 | F16: =68.84+3.85 -> 72.69 | G16: =E16-F16 -> 0 | H16: 5219876 | I16: 0406045268200015 | J16: Bank Muscat | K16: BMUSOMRX | L16: 99066779 | M16: 17-11-25 | N16: 23-12-25
A17: 1135 | B17: Khalid Said Ali Al Kathiri | C17: 481.1 | D17: 0.3 | E17: =C17*D17 -> 144.33 | F17: =4.48000000000003+138.6+1.25 -> 144.33 | G17: =E17-F17 -> 0 | H17: 19202954 | I17: 01013808698001 | J17: Bank Dhofar | K17: BDOFOMRU | L17: 92771786 | M17: 14-10-2025 | N17: 45669 | O17: 16-12-25
A18: 1141 | B18: Malik Said Ahmed Habkook Hat Al Shahri | C18: 330 | D18: 0.3 | E18: =C18*D18 -> 99 | F18: =97.29+1.71 -> 99 | G18: =E18-F18 -> 0 | H18: 11753992 | I18: 0396051591490029 | J18: Bank Muscat | K18: BMUSOMRX | L18: 99205960 | M18: 27-10-2025 | N18: 17-11-25
A19: 1154 | B19: Mohammed Salim Abdullah Al kathiri | C19: 710.8 | D19: 0.3 | E19: =C19*D19 -> 213.24 | G19: =E19-F19 -> 213.24 | H19: 18654817 | I19: 0439053703720016 | J19: Bank Muscat | K19: BMUSOMRX | L19: 98887846
A20: 1161 | B20: Mohammed Ali Musallam Al Nubi Al Kathiri | C20: 270 | D20: 0.3 | E20: =C20*D20 -> 81 | F20: =4.46000000000001+76+0.54 -> 81 | G20: =E20-F20 -> 0 | H20: 257926 | I20: 3109603718500 | J20: Oman Arab Bank | K20: OMABOMRU | L20: 99589267 | M20: 14-10-2025 | N20: 45972 | O20: 23-12-25
A21: 1168 | B21: Mohammed Salim Said Jumaa Al Kathiri | C21: 432 | D21: 0.3 | E21: =C21*D21 -> 129.6 | F21: =0.940000000000013+128.66 -> 129.6 | G21: =E21-F21 -> 0 | H21: 15498714 | I21: 0402012153960016 | J21: Bank Muscat | K21: BMUSOMRX | L21: 99292524 | M21: 14-10-2025 | N21: 45758 | O21: .040-10-25
A22: 1177 | B22: Said Salim Said BaitSaid | C22: 252.5 | D22: 0.3 | E22: =C22*D22 -> 75.75 | G22: =E22-F22 -> 75.75 | H22: 219353 | I22: 01010127872001 | J22: Bank Dhofar | K22: BDOFOMRU | L22: 99485534
A23: 1178 | B23: Mohammed Said Mohammed Akdha Al Rawas | C23: 390 | D23: 0.3 | E23: =C23*D23 -> 117 | F23: 114.29 | G23: =E23-F23 -> 2.71 | H23: 970872 | I23: 1006123229017 | J23: NBO | K23: NBOMOMRX | L23: 99485535 | M23: 45758
A24: 1224 | B24: Naif Masoud Awadh Nasib Kikab Al Shihri | C24: 558 | D24: 0.3 | E24: =C24*D24 -> 167.4 | F24: =164.25+3.15 -> 167.4 | G24: =E24-F24 -> 0 | H24: 24911691 | I24: 0406060856030017 | J24: Bank Muscat | K24: BMUSOMRX | L24: 99192216 | M24: 14-10-2025 | N24: 45788 | O24: 16-12-25
A25: 1225 | B25: Naif Said Awadh Fadhl | C25: 442 | D25: 0.3 | E25: =C25*D25 -> 132.6 | G25: =E25-F25 -> 132.6 | H25: 9642357 | I25: 1501079705330 | J25: Ahli bank | K25: AUBOOMRU | L25: 99777877
A26: 1235 | B26: Saeed Abdul Aziz Abdullah Al kathiri | C26: 522 | D26: 0.3 | E26: =C26*D26 -> 156.6 | F26: =112.1+44.5 -> 156.6 | G26: =E26-F26 -> 0 | H26: 1992436 | I26: 0402003122620013 | J26: BANK MUSCAT | K26: BMUSOMRX | L26: 99484668 | M26: 46002 | N26: 16-12-25
A27: 1241 | B27: Said Mohammed Abdallah Al kathiri | C27: 437.8 | D27: 0.3 | E27: =C27*D27 -> 131.34 | F27: =129.23+2.11 -> 131.34 | G27: =E27-F27 -> 0 | H27: 5343254 | I27: 0406003410830019 | J27: Bank Muscat | K27: BMUSOMRX | L27: 98964664 | M27: 20-11-25 | N27: 16-12-25
A28: 1247 | B28: Said Salim Azad Bait Ali Badar | C28: 432 | D28: 0.3 | E28: =C28*D28 -> 129.6 | F28: =129.5+0.1 -> 129.6 | G28: =E28-F28 -> 0 | H28: 4748561 | I28: 01040280570002 | J28: Bank Dhofar | K28: BDOFOMRU | L28: 92345282 | M28: 45758 | N28: 16-12-25
A29: 1252 | B29: Said Ahmed Ali Bait Said | C29: 347 | D29: 0.3 | E29: =C29*D29 -> 104.1 | G29: =E29-F29 -> 104.1 | H29: 2433959 | I29: 01010120819002 | J29: Bank Dhofar | K29: BDOFOMRU | L29: 93555999
A30: 1258 | B30: Said Ali Musallam Al Noubi Al Kathiri | C30: 568.7 | D30: 0.3 | E30: =C30*D30 -> 170.61 | F30: =168.55+2.06 -> 170.61 | G30: =E30-F30 -> 0 | H30: 1924174 | I30: 01040280044001 | J30: Bank Dhofar | K30: BDOFOMRU | L30: 99297990 | M30: 46002 | N30: 16-12-25
A31: 1260 | B31: Said Salim Ali Kibab Al Shahri | C31: 504 | D31: 0.3 | E31: =C31*D31 -> 151.2 | F31: =151.11+0.09 -> 151.2 | G31: =E31-F31 -> 0 | H31: 18363579 | I31: 01041057246001 | J31: Bank Dhofar | K31: BDOFOMRU | L31: 98217444 | M31: 45972 | N31: 16-12-25
A32: 1261 | B32: Said Ali Nasib Kikab Al shahri | C32: 268.4 | D32: 0.3 | E32: =C32*D32 -> 80.52 | F32: =76.598+3.922 -> 80.52 | G32: =E32-F32 -> 0 | H32: 14429332 | I32: 0406018203570028 | J32: Bank Muscat | K32: BMUSOMRX | L32: 92939445 | M32: 20-11-25 | N32: 16-12-25
A33: 1268 | B33: Said Musallam Ali Ghawas | C33: 358 | D33: 0.3 | E33: =C33*D33 -> 107.4 | F33: =105.94+1.46 -> 107.4 | G33: =E33-F33 -> 0 | H33: 722058 | I33: 0397003940070023 | J33: Bank Muscat | K33: BMUSOMRX | L33: 92848609 | M33: 45758 | N33: 16-12-25
A34: 1282 | B34: Salim Ali Musallam Al Noubi Al Kathiri | C34: 486 | D34: 0.3 | E34: =C34*D34 -> 145.8 | F34: =0.0500000000000149+142.5+3.25 -> 145.8 | G34: =E34-F34 -> 0 | H34: 2997747 | I34: 3109601542500 | J34: Oman Arab Bank | K34: OMABOMRU | L34: 92660969 | M34: 14-10-2025 | N34: 45788 | O34: 16-12-25
A35: 1284 | B35: Salim Ali Said Al Nubi Al Kathiri | C35: 468 | D35: 0.3 | E35: =C35*D35 -> 140.4 | F35: =E35 -> 140.4 | G35: =E35-F35 -> 0 | H35: 1177598 | I35: 01040280595001 | J35: Bank Dhofar | K35: BDOFOMRU | L35: 92825228 | M35: 16-12-25
A36: 1300 | B36: Salem Suhail Omer Bit Fhadel | C36: 550.5 | D36: 0.3 | E36: =C36*D36 -> 165.15 | G36: =E36-F36 -> 165.15 | H36: 19534277 | I36: 0439016892350027 | J36: Bank Muscat | K36: BMUSOMRX | L36: 99710505
A37: 1306 | B37: Salim Ali Nasib Al Kathiri | C37: 283.9 | D37: 0.3 | E37: =C37*D37 -> 85.17 | F37: =2.61999999999999+79.2+3.35 -> 85.17 | G37: =E37-F37 -> 0 | H37: 2006904 | I37: 0439051845390018 | J37: Bank Muscat | K37: BMUSOMRX | L37: 96137717 | M37: 14-10-2025 | N37: 45788 | O37: 16-12-25
A38: 1315 | B38: Salim Said Ali Ghawas | C38: 246.3 | D38: 0.3 | E38: =C38*D38 -> 73.89 | G38: =E38-F38 -> 73.89 | H38: 19528845 | I38: 0439026234320047 | J38: Bank Muscat | K38: BMUSOMRX | L38: 92432606
A39: 1328 | B39: Suhail Saeed Suhail ghawas | C39: 322 | D39: 0.3 | E39: =C39*D39 -> 96.6 | F39: =95.58+1.02 -> 96.6 | G39: =E39-F39 -> 0 | H39: 782833 | I39: 01015382117001 | J39: Bank Dhofar | K39: BDOFOMRU | L39: 92475895 | M39: 30-10-2025 | N39: 16-12-25
A40: 1330 | B40: Said Mahad Ali Al Kathiri | C40: 464.9 | D40: 0.3 | E40: =C40*D40 -> 139.47 | F40: =137.6+1.87 -> 139.47 | G40: =E40-F40 -> 0 | H40: 12194826 | I40: 00510129167001 | J40: Bank Nizwa | K40: BNZWOMRX | L40: 91299100 | M40: 45758 | N40: 45788
A41: 1331 | B41: Mohammed Said Musallam Al Noob Al Kathiri | C41: 270 | D41: 0.3 | E41: =C41*D41 -> 81 | F41: =E41 -> 81 | G41: =E41-F41 -> 0 | H41: 2107763 | I41: 3109043578500 | J41: Oman Arab Bank | K41: OMABOMRU | L41: 93536009 | M41: 24-12-25
A42: 1333 | B42: Suhail Salim Ahmed Al Nubi Al Kathiri | C42: 430 | D42: 0.3 | E42: =C42*D42 -> 129 | F42: =125.35+3.65 -> 129 | G42: =E42-F42 -> 0 | H42: 1736679 | I42: 0401002496140031 | J42: Bank Muscat | K42: BMUSOMRX | L42: 99482212 | M42: 45972 | N42: 24-12-25
A43: 1382 | B43: Suhail Mohammed Said Ghawas Al Kathiri | C43: 490.7 | D43: 0.3 | E43: =C43*D43 -> 147.21 | F43: =143.85+3.36 -> 147.21 | G43: =E43-F43 -> 0 | H43: 886492 | I43: 0397003786810019 | J43: Bank Muscat | K43: BMUSOMRX | L43: 99494166 | M43: 45788 | N43: 16-12-25
A44: 1384 | B44: Abdul Selam Musallam Mohammed Al Rawas | C44: 150.8 | D44: 0.3 | E44: =C44*D44 -> 45.24 | G44: =E44-F44 -> 45.24 | H44: 4426701 | I44: 0406003017570013 | J44: Bank Muscat | K44: BMUSOMRX | L44: 92634991
A45: 1386 | B45: Omar Salim Ahmed Al Hadi Ba Omar | C45: 572.5 | D45: 0.3 | E45: =C45*D45 -> 171.75 | F45: =168.54+3.21 -> 171.75 | G45: =E45-F45 -> 0 | H45: 711799 | I45: 0406003202280013 | J45: Bank Muscat | K45: BMUSOMRX | L45: 92394924 | M45: 24-11-25 | N45: 16-12-25
A46: 1387 | B46: Ali Said Mahisan Kayakab Al Shihri | C46: 478.3 | D46: 0.3 | E46: =C46*D46 -> 143.49 | G46: =E46-F46 -> 143.49 | H46: 6759716 | I46: 3109117911500 | J46: Oman Arab Bank | K46: OMABOMRU | L46: 91907675
A47: 1388 | B47: Tarik Suhail Salim Al Kathiri | C47: 272.6 | D47: 0.3 | E47: =C47*D47 -> 81.78 | G47: =E47-F47 -> 81.78 | H47: 18610874 | I47: 01011035504001 | J47: Bank Dhofar | K47: BDOFOMRU | L47: 93955577
A48: 1389 | B48: Ali Said Musallam Al Noubi Al Kathiri | C48: 720 | D48: 0.3 | E48: =C48*D48 -> 216 | F48: =214.7+1.3 -> 216 | G48: =E48-F48 -> 0 | H48: 1036354 | I48: 01010281496001 | J48: Bank Dhofar | K48: BDOFOMRU | L48: 92413881 | M48: 27-10-2025 | N48: 23-12-25
A49: 1394 | B49: Ali Ahmed Salim Ahmed Al Kathiri | C49: 331 | D49: 0.3 | E49: =C49*D49 -> 99.3 | F49: =98.76+0.54 -> 99.3 | G49: =E49-F49 -> 0 | H49: 25656187 | I49: 0396016034040018 | J49: Bank Muscat | K49: BMUSOMRX | L49: 98987848 | M49: 27-10-2025 | N49: 45788
A50: 1396 | B50: Mustahil Ali Azad Al Kathiri | C50: 323.6 | D50: 0.3 | E50: =C50*D50 -> 97.08 | F50: =96.49+0.59 -> 97.08 | G50: =E50-F50 -> 0 | H50: 905845 | I50: 0397003647340016 | J50: Bank Muscat | K50: BMUSOMRX | L50: 99696204 | M50: 30-10-2025 | N50: 16-12-25
A51: 1397 | B51: Ahmed Musallam Amer Al Kathiri | C51: 251 | D51: 0.3 | E51: =C51*D51 -> 75.3 | F51: =1.39000000000001+69.3+4.61 -> 75.3 | G51: =E51-F51 -> 0 | H51: 1292885 | I51: 254001118001 | J51: HSBC | K51: BBMEOMRX | L51: 92307552 | M51: 14-10-2025 | N51: 45758 | O51: 16-12-25
A52: 1398 | B52: Salim Amer Azad Al Kathiri | C52: 212.6 | D52: 0.3 | E52: =C52*D52 -> 63.78 | F52: =0.1+61.75+1.93 -> 63.78 | G52: =E52-F52 -> 0 | H52: 1161437 | I52: 00510128357001 | J52: Bank Nizwa | K52: BNZWOMRX | L52: 91135580 | M52: 45945 | N52: 27-10-2025 | O52: 23-12-25
A53: 1400 | B53: Manei Said Ahmed Al Kathiri | C53: 436 | D53: 0.3 | E53: =C53*D53 -> 130.8 | F53: =97.38+30.24+3.18 -> 130.8 | G53: =E53-F53 -> 0 | H53: 7223707 | I53: 10060183858001 | J53: NBO | K53: NBOMOMRX | L53: 92616136 | M53: 30-10-2025 | N53: 16-12-25
A54: 1403 | B54: Ali Salim Ahmed Al Nubi Al Kathiri | C54: 410.4 | D54: 0.3 | E54: =C54*D54 -> 123.12 | F54: =120.88+2.24 -> 123.12 | G54: =E54-F54 -> 0 | H54: 499044 | I54: 0406003202740014 | J54: Bank Muscat | K54: BMUSOMRX | L54: 92226988 | M54: 45788 | N54: 16-12-25
A55: 1406 | B55: Said Salim Musallam AlNoob Al Kathiri | C55: 360 | D55: 0.3 | E55: =C55*D55 -> 108 | F55: =105.65+2.35 -> 108 | G55: =E55-F55 -> 0 | H55: 880849 | I55: 3109015600500 | J55: Oman Arab Bank | K55: OMABOMRU | L55: 99365157 | M55: 45758 | N55: 16-12-25
A56: 1408 | B56: Abdullah Salim AhmedAl Hadi Ba Omar | C56: 1044 | D56: 0.3 | E56: =C56*D56 -> 313.2 | F56: =309.841+3.359 -> 313.2 | G56: =E56-F56 -> 0 | H56: 997465 | I56: 0397003981360017 | J56: Bank Muscat | K56: BMUSOMRX | L56: 99490975 | M56: 24-11-25 | N56: 24-12-25
A57: 1409 | B57: Mahisan Ali Mahisan Al Shihri | C57: 397 | D57: 0.3 | E57: =C57*D57 -> 119.1 | F57: =0.700000000000006+118.4 -> 119.1 | G57: =E57-F57 -> 0 | H57: 7279409 | I57: 0406016730440035 | J57: Bank Muscat | K57: BMUSOMRX | L57: 99626634 | M57: 14-10-2025 | N57: 16-12-25
A58: 1410 | B58: Masoud Ali suhail Bait Said | C58: 447.7 | D58: 0.3 | E58: =C58*D58 -> 134.31 | F58: =0.4+133.65+0.26 -> 134.31 | G58: =E58-F58 -> 0 | H58: 757372 | I58: 0406003338100019 | J58: Bank Muscat | K58: BMUSOMRX | L58: 92018800 | M58: 45972 | N58: 45728 | O58: 16-12-25
A59: 1411 | B59: Said Ali Ahmed Amor Jid | C59: 433.9 | D59: 0.3 | E59: =C59*D59 -> 130.17 | F59: =129.65+0.52 -> 130.17 | G59: =E59-F59 -> 0 | H59: 1650389 | I59: 0406018263680011 | J59: Bank Muscat | K59: BMUSOMRX | L59: 92294150 | M59: 45758 | N59: 16-12-25
A60: 1412 | B60: Musallam Said Salim Bait Said | C60: 30 | D60: 0.3 | E60: =C60*D60 -> 9 | G60: =E60-F60 -> 9 | H60: 312227 | I60: 0406003457720017 | J60: Bank Muscat | K60: BMUSOMRX | L60: 95414124
A61: 1413 | B61: Awadh Salim Ali Ghawas | C61: 268 | D61: 0.3 | E61: =C61*D61 -> 80.4 | F61: =0.750000000000004+76+3.65 -> 80.4 | G61: =E61-F61 -> 0 | H61: 539906 | I61: 01010128406001 | J61: Bank Dhofar | K61: BDOFOMRU | M61: 14-10-2025 | N61: 45819 | O61: 16-12-25
A62: 1414 | B62: Salim Said Ali Bait Said | C62: 745.2 | D62: 0.3 | E62: =C62*D62 -> 223.56 | G62: =E62-F62 -> 223.56 | H62: 9178238 | I62: 01010852881001 | J62: Bank Dhofar | K62: BDOFOMRU | L62: 91966140
A63: 1415 | B63: Ali Salim Ahmed Ali Badar al Kathiri | C63: 213.3 | D63: 0.3 | E63: =C63*D63 -> 63.99 | F63: =63.33+0.66 -> 63.99 | G63: =E63-F63 -> 0 | H63: 5334952 | I63: 0439003977040022 | J63: Bank Muscat | K63: BMUSOMRX | L63: 99806280 | M63: 45972 | N63: 16-12-25
A64: 1417 | B64: Said Bakhit said Al mashikhi | C64: 396 | D64: 0.3 | E64: =C64*D64 -> 118.8 | F64: =118.08+0.72 -> 118.8 | G64: =E64-F64 -> 0 | H64: 1252579 | I64: 0397003628950016 | J64: Bank Muscat | K64: BMUSOMRX | L64: 98520912 | M64: 27-10-2025 | N64: 31-12-25
A65: 1418 | B65: SALIM ALI MUSALLAM GHAWAS | C65: 321.7 | D65: 0.3 | E65: =C65*D65 -> 96.51 | F65: =94.52+1.99 -> 96.51 | G65: =E65-F65 -> 0 | H65: 9954378 | I65: 0397003855180014 | J65: Bank Muscat | K65: BMUSOMRX | L65: 99282423 | M65: 20-10-2025 | N65: 45972
A66: 1419 | B66: Mahad Masoud Salim Baitsaid | C66: 648 | D66: 0.3 | E66: =C66*D66 -> 194.4 | G66: =E66-F66 -> 194.4 | H66: 386821 | I66: 0406003414760015 | J66: Bank Muscat | K66: BMUSOMRX | L66: 99181419
A67: 1420 | B67: Salim Said Salim Al Rawas | C67: 483.8 | D67: 0.3 | E67: =C67*D67 -> 145.14 | G67: =E67-F67 -> 145.14 | H67: 5460297 | I67: 0402003168320014 | J67: Bank Muscat | K67: BMUSOMRX | L67: 95898899
A68: 1421 | B68: Malik Musallam Salim Masoud Al Rawas | C68: 522 | D68: 0.3 | E68: =C68*D68 -> 156.6 | F68: =0.999999999999995+152+3.6 -> 156.6 | G68: =E68-F68 -> 0 | H68: 15314262 | I68: 0397019441080011 | J68: Bank Muscat | K68: BMUSOMRX | L68: 90333361 | M68: 14-10-2025 | N68: 30-10-2025 | O68: 16-12-25
A69: 1423 | B69: Ahmed Said Ali Azad Al Kathiri | C69: 486 | D69: 0.3 | E69: =C69*D69 -> 145.8 | G69: =E69-F69 -> 145.8 | H69: 5044397 | I69: 0397003645500016 | J69: Bank Muscat | K69: BMUSOMRX | L69: 99580550
