Workbook

Sheet center-April
A1: HAJEEF CAMEL MILK PROCUREMENT FROM 01-APR-2024 TO 30-APR-2024
A3: Sr. No. | B3: Farmer Code | C3: Farmer Name | D3: Total Milk Qty | E3: Avg. Rate (OMR/Ltr.) | F3: Amount (OMR) | G3: paid | H3: balance | I3: ID No. | J3: remark 2
A4: 1 | B4: 1474 | C4: Mohamed Salam Amer Al Yafee | D4: 1158.9 | E4: 0.4 | F4: =E4*D4 -> 463.56 | G4: =460.75+2.81 -> 463.56 | H4: =F4-G4 -> 0 | I4: 4603773 | J4: 19-08-2024-feeds
A5: 2 | B5: 3136 | C5: Ghazi Salim Ahmed Al Kathiri | D5: 930.6 | E5: 0.4 | F5: =E5*D5 -> 372.24 | G5: =370.15+2.09 -> 372.24 | H5: =F5-G5 -> 0 | I5: 183498 | J5: 13-08-2024-FEEDS
A6: 4 | B6: 3700 | C6: Said Ahmed Suhail Alkathiri | D6: 1352.4 | E6: 0.4 | F6: 498.96 | G6: 498.96 | H6: =F6-G6 -> 0 | I6: 19729836
A7: 6 | B7: 3765 | C7: Wafi Musallam Ahmed Almasahli | D7: 1216 | E7: 0.4 | F7: =E7*D7 -> 486.4 | G7: =485.75+0.65 -> 486.4 | H7: =F7-G7 -> 0 | I7: 19752023 | J7: 19-08-2024-feeds | K7: 45663
A8: 7 | B8: 3770 | C8: Ali Mohammed Suhail Ghawas | D8: 340.2 | E8: 0.4 | F8: =E8*D8 -> 136.08 | G8: 135.8 | H8: =F8-G8 -> 0.28 | I8: 7198036 | J8: 18-08-2024-feeds
A9: 9 | B9: 3871 | C9: Ahmed Mohammed Ahmed Jashuul | D9: 1231.3 | E9: 0.4 | F9: =E9*D9 -> 492.52 | G9: =488.9+3.62 -> 492.52 | H9: =F9-G9 -> 0 | I9: 6920684 | J9: 14-08-24-feed
A10: 10 | B10: 3877 | C10: Musallm hassan Abdullah Khdhran Al Kathiri | D10: 475.7 | E10: 0.4 | F10: =E10*D10 -> 190.28 | G10: =187.85+2.43 -> 190.28 | H10: =F10-G10 -> 0 | I10: 14897254 | J10: 18-08-2024-feeds | K10: 13-01-25-dcf
C11: TOTAL | D11: =SUM(D4:D10) -> 6705.1 | F11: =SUM(F4:F10) -> 2640.04 | G11: =SUM(G4:G10) -> 2639.76 | H11: =SUM(H4:H10) -> 0.28
G13: Apr | H13: =H11 -> 0.28
G14: May | H14: ='center-May'!H32 -> 0
A15: Hassan Ghaly | E15: Sakku Mathew | G15: June | H15: ='06'!H57 -> 4.15
G16: July | H16: ='center-July'!H312 -> 0
G17: Aug | H17: ='center-Aug'!H309 -> 14.05
G18: Sep | H18: ='Center-Sept'!H312 -> 14434.09
G19: Oct | H19: 58708.52
G20: Nov | H20: 49811.8

Sheet center-May
A1: HAJEEF CAMEL MILK PROCUREMENT FROM 01-May-2024 TO 31-May-2024
A3: Sr. No. | B3: Farmer Code | C3: Farmer Name | D3: Total Milk Qty | E3: Avg. Rate (OMR/Ltr.) | F3: Amount (OMR) | G3: paid | H3: balance | I3: ID No. | J3: remark 2
A4: 1 | B4: 1431 | C4: Bakhit Mohamed Salim Rawas | D4: 440 | E4: 0.4 | F4: =E4*D4 -> 176 | G4: =174.6+1.4 -> 176 | H4: =F4-G4 -> 0 | I4: 721445 | J4: 26-08-2024-feeds | K4: 45607
A5: 2 | B5: 1483 | C5: Saed Ali Ahmed Al Kathiri | D5: 1140 | E5: 0.4 | F5: =E5*D5 -> 456 | G5: =452.94+3.06 -> 456 | H5: =F5-G5 -> 0 | I5: 1567826 | J5: 20-08-2024-feeds | K5: 45602
A6: 3 | B6: 3009 | C6: Ahmed Salim Bakhit Qatan | D6: 465.6 | E6: 0.4 | F6: =E6*D6 -> 186.24 | G6: =183.02+3.22 -> 186.24 | H6: =F6-G6 -> 0 | I6: 1448391 | J6: 05-09-2024-feeds
A7: 4 | B7: 3077 | C7: Mohammed Ali Suhail Qatan | D7: 917.4 | E7: 0.4 | F7: =E7*D7 -> 366.96 | G7: =365.42+1.54 -> 366.96 | H7: =F7-G7 -> 0 | I7: 21978752 | J7: 14-08-2024-feeds | K7: 45635
A8: 5 | B8: 3136 | C8: Ghazi Salim Ahmed Al Kathiri | D8: 892 | E8: 0.4 | F8: =E8*D8 -> 356.8 | G8: =354.05+2.75 -> 356.8 | H8: =F8-G8 -> 0 | I8: 183498 | J8: 45547 | K8: 45615
A9: 6 | B9: 3215 | C9: Suhail Awadh Salim Hawas Al Aamri | D9: 1017.9 | E9: 0.4 | F9: =E9*D9 -> 407.16 | G9: =404.79+2.37 -> 407.16 | H9: =F9-G9 -> 0 | I9: 11684091 | J9: 18-08-2024-feeds | K9: 45607
A10: 7 | B10: 3273 | C10: Masoud Salim Faraj Al Kathiri | D10: 896 | E10: 0.4 | F10: =E10*D10 -> 358.4 | G10: =356+2.4 -> 358.4 | H10: =F10-G10 -> 0 | I10: 7047221 | J10: 18-08-2024-feeds | K10: 45609
A11: 8 | B11: 3287 | C11: Ahmed Bakhit Ahmed Qatan | D11: 800.2 | E11: 0.4 | F11: =E11*D11 -> 320.08 | G11: =319.19+0.89 -> 320.08 | H11: =F11-G11 -> 0 | I11: 6504554 | J11: 12-08-2024-feeds | K11: 45629
A12: 9 | B12: 3329 | C12: Said Ahmed Mustahil Alshahri | D12: 460 | E12: 0.4 | F12: =E12*D12 -> 184 | G12: =182.55+1.45 -> 184 | H12: =F12-G12 -> 0 | I12: 9086292 | J12: 19-08-2024-feeds | K12: 05-014-25
A13: 10 | B13: 3334 | C13: Mohammed Said Mohammed Baitsaid | D13: 687.5 | E13: 0.4 | F13: =E13*D13 -> 275 | G13: =273.5+1.5 -> 275 | H13: =F13-G13 -> 0 | I13: 1176211 | J13: 26-08-2024-feeds | K13: 45691
A14: 11 | B14: 3340 | C14: Mohsin Suhail Ghawas | D14: 456.6 | E14: 0.4 | F14: =E14*D14 -> 182.64 | G14: =179.45+3.19 -> 182.64 | H14: =F14-G14 -> 0 | I14: 906355 | J14: 04-09-24-feeds
A15: 12 | B15: 3709 | C15: Abdul Aziz Ali Said Ali Kashoob | D15: 823.6 | E15: 0.4 | F15: =E15*D15 -> 329.44 | G15: =329.09+0.35 -> 329.44 | H15: =F15-G15 -> 0 | I15: 23860076 | J15: 14-08-2024-feeds
A16: 13 | B16: 3717 | C16: Salim Ali Musallam ALMaashani | D16: 917.2 | E16: 0.4 | F16: =E16*D16 -> 366.88 | G16: =363.37+3.51 -> 366.88 | H16: =F16-G16 -> 0 | I16: 6349394 | J16: feeds -06-08-2024
A17: 14 | B17: 3719 | C17: Said Ahmed Ali Al Zawamri | D17: 433 | E17: 0.4 | F17: =E17*D17 -> 173.2 | G17: =169.75+3.45 -> 173.2 | H17: =F17-G17 -> 0 | I17: 6610475 | J17: 45544
A18: 15 | B18: 3723 | C18: Said Suhail Said Qatan | D18: 454.8 | E18: 0.4 | F18: =E18*D18 -> 181.92 | G18: =179.9+2.02 -> 181.92 | H18: =F18-G18 -> 0 | I18: 993752 | J18: 13-08-24-feeds
A19: 16 | B19: 3725 | C19: Ahmed Bakhit Ahmed Qatan | D19: 671.8 | E19: 0.4 | F19: =E19*D19 -> 268.72 | G19: =267.53+1.19 -> 268.72 | H19: =F19-G19 -> 0 | I19: 1648248 | J19: 16-09-2024 | K19: 45602
A20: 17 | B20: 3764 | C20: Ali Musallam Amer Amer Jid Almahri | D20: 1205.5 | E20: 0.4 | F20: =E20*D20 -> 482.2 | G20: =480.15+2.05 -> 482.2 | H20: =F20-G20 -> 0 | I20: 1996843 | J20: 16-09-2024 | K20: 16-01-25
A21: 18 | B21: 3787 | C21: Ahmed Musallam Suhail Almaashani | D21: 899.9 | E21: 0.4 | F21: =E21*D21 -> 359.96 | G21: =357.32+2.64 -> 359.96 | H21: =F21-G21 -> 0 | I21: 813786 | J21: feeds -06-08-2024 | K21: 45652
A22: 19 | B22: 3799 | C22: Hamid Awadh Salim Hawas AL Aamri | D22: 1111.7 | E22: 0.4 | F22: =E22*D22 -> 444.68 | G22: =444.55+0.13 -> 444.68 | H22: =F22-G22 -> 0 | I22: 12494672 | J22: 18-09-2024-feeds | K22: 45607
A23: 20 | B23: 3823 | C23: Said Amer Azad AL Kathiri | D23: 457 | E23: 0.4 | F23: =E23*D23 -> 182.8 | G23: =179.45+3.35 -> 182.8 | H23: =F23-G23 -> 0 | I23: 865789 | J23: 26-08-2024-feeds | K23: 45602
A24: 21 | B24: 3829 | C24: Ahmed Suhail Ahmed Qatan | D24: 422.7 | E24: 0.4 | F24: =E24*D24 -> 169.08 | G24: =164.9+4.18 -> 169.08 | H24: =F24-G24 -> 0 | I24: 897384 | J24: 28-08-2024-feeds | K24: 45670
A25: 22 | B25: 3834 | C25: Musallem Ahmed Suhail Jashuul | D25: 920 | E25: 0.4 | F25: =E25*D25 -> 368 | G25: =364.35+3.65 -> 368 | H25: =F25-G25 -> 0 | I25: 5544756 | J25: 19-08-2024 feeds | K25: 45607
A26: 23 | B26: 3836 | C26: Mohammed Said Ahmed Shamas | D26: 867 | E26: 0.4 | F26: =E26*D26 -> 346.8 | G26: =345.92+0.88 -> 346.8 | H26: =F26-G26 -> 0 | I26: 20264434 | J26: 19-08-2024-feeds | K26: 45602
A27: 24 | B27: 3850 | C27: Said Salim Ali Jaboob | D27: 1114.7 | E27: 0.4 | F27: =E27*D27 -> 445.88 | G27: =444.22+1.66 -> 445.88 | H27: =F27-G27 -> 0 | I27: 5742985 | J27: 19-08-2024-feed | K27: 45650
A28: 25 | B28: 3862 | C28: Ali Mohammed Ali al Aamri | D28: 876.5 | E28: 0.4 | F28: =E28*D28 -> 350.6 | G28: =349.2+1.4 -> 350.6 | H28: =F28-G28 -> 0 | I28: 5892019 | J28: 27-08-2024-feeds
A29: 26 | B29: 3876 | C29: Mohammed Salim Ali Al Jahf ali | D29: 682.1 | E29: 0.4 | F29: =E29*D29 -> 272.84 | G29: =270.24+2.6 -> 272.84 | H29: =F29-G29 -> 0 | I29: 4767948 | J29: 12-08-2024-feeds | K29: 45635
A30: 27 | B30: 3878 | C30: Ahmed Salim Mustahil Ali Sakroon | D30: 460 | E30: 0.4 | F30: =E30*D30 -> 184 | G30: =181.69+2.31 -> 184 | H30: =F30-G30 -> 0 | I30: 22687078 | J30: 18-08-2024-feeds
A31: 28 | B31: 3884 | C31: Issa Salim Mubarak Raboob Al Shahri | D31: 409.4 | E31: 0.4 | F31: =E31*D31 -> 163.76 | G31: =161.31+2.45 -> 163.76 | H31: =F31-G31 -> 0 | I31: 22716378 | J31: 15-08-2024-feed | K31: 45630
C32: TOTAL | D32: =SUM(D4:D31) -> 20900.1 | F32: =SUM(F4:F31) -> 8360.04 | G32: =SUM(G4:G31) -> 8360.04 | H32: =SUM(H4:H31) -> 0
G34: =SUBTOTAL(9,G9:G32) -> 10521.52
F35: =G32/F32% -> 100

Sheet Sheet1
A6: May | B6: 3243 | C6: Asad Ali Ahmed Suhail Aamir Jid | D6: 453.8 | E6: 0.4 | F6: =E6*D6 -> 181.52 | H6: =F6-G6 -> 181.52 | AD6: 3708 | AE6: Said Salim Nassir Al Aamri | AF6: 925.2 | AG6: 0.4 | AH6: =AG6*AF6 -> 370.08 | AI6: 194 | AJ6: =AH6-AI6 -> 176.08
A7: June | B7: 3243 | C7: Asad Ali Ahmed Suhail Aamir Jid | D7: 327.1 | E7: 0.4 | F7: =E7*D7 -> 130.84 | H7: =F7-G7 -> 130.84
H8: =SUM(H6:H7) -> 312.36

Sheet 06
A1: HAJEEF CAMEL MILK PROCUREMENT FROM 01-June-2024 TO 30-June-2024
A3: Sr. No. | B3: Farmer Code | C3: Farmer Name | D3: Total Milk Qty | E3: Avg. Rate (OMR/Ltr.) | F3: Amount (OMR) | G3: Paid | H3: Balance | I3: ID No. | J3: remark 2
A4: 1 | B4: 1443 | C4: Ahmed Musallam Ahmed Al Kathiri | D4: 1271.7 | E4: 0.4 | F4: =E4*D4 -> 508.68 | G4: =F4 -> 508.68 | H4: =F4-G4 -> 0 | I4: 6026992 | J4: 45567
A5: 2 | B5: 1452 | C5: Sulaim Said Mohammed Hawas Al Aamri | D5: 412.9 | E5: 0.4 | F5: =E5*D5 -> 165.16 | G5: =162.1+3.06 -> 165.16 | H5: =F5-G5 -> 0 | I5: 20917176 | J5: 45538 | K5: 45602
A6: 3 | B6: 1461 | C6: Suhail Said Ali Bait said | D6: 326.7 | E6: 0.4 | F6: =E6*D6 -> 130.68 | G6: =F6 -> 130.68 | H6: =F6-G6 -> 0 | I6: 6828806 | J6: 45580
A7: 4 | B7: 3022 | C7: Hussein Masoud Aubad Al Kathiri | D7: 1080.1 | E7: 0.4 | F7: =E7*D7 -> 432.04 | G7: =430.39+1.65 -> 432.04 | H7: =F7-G7 -> 0 | I7: 5360253 | J7: 09-01-2024-feeds | K7: 45609
A8: 5 | B8: 3025 | C8: Musallam Salim Mahad Qatan | D8: 588.6 | E8: 0.4 | F8: =E8*D8 -> 235.44 | G8: =F8 -> 235.44 | H8: =F8-G8 -> 0 | I8: 7542172 | J8: 18-09-2024
A9: 6 | B9: 3030 | C9: Salim Ahmed Salim Amer Jid | D9: 330 | E9: 0.4 | F9: =E9*D9 -> 132 | G9: =130.65+1.35 -> 132 | H9: =F9-G9 -> 0 | I9: 6021175 | J9: 45580 | K9: 45650
A10: 7 | B10: 3043 | C10: Said Aubad Ali Ghawas | D10: 285.6 | E10: 0.4 | F10: =E10*D10 -> 114.24 | G10: =113.9+0.34 -> 114.24 | H10: =F10-G10 -> 0 | I10: 396336 | J10: 23-09-2024 | K10: 45642
A11: 8 | B11: 3072 | C11: Mohammed Salim Said Al Barami | D11: 293 | E11: 0.4 | F11: =E11*D11 -> 117.2 | G11: =F11 -> 117.2 | H11: =F11-G11 -> 0 | I11: 993077 | J11: 16-09-2024 feeds | K11: 45665
A12: 9 | B12: 3199 | C12: Ali Musallam Ahmed Tabuk | D12: 308.6 | E12: 0.4 | F12: =E12*D12 -> 123.44 | G12: =122.96+0.48 -> 123.44 | H12: =F12-G12 -> 0 | I12: 5168327 | J12: 45547 | K12: 45630
A13: 10 | B13: 3200 | C13: Ahmed Said Ahmed Qutan | D13: 291.3 | E13: 0.4 | F13: =E13*D13 -> 116.52 | G13: =113.65+2.87 -> 116.52 | H13: =F13-G13 -> 0 | I13: 21947578 | J13: 30-09-2024 | K13: 45628
A14: 11 | B14: 3209 | C14: Said Suhail Ali Al Kathiri | D14: 328.5 | E14: 0.4 | F14: =E14*D14 -> 131.4 | G14: =130.08+1.32 -> 131.4 | H14: =F14-G14 -> 0 | I14: 5634328 | J14: 18-09-2024 | K14: 45607
A15: 12 | B15: 3215 | C15: Suhail Awadh Salim Hawas Al Aamri | D15: 726.2 | E15: 0.4 | F15: =E15*D15 -> 290.48 | G15: =286.15+4.33 -> 290.48 | H15: =F15-G15 -> 0 | I15: 11684091 | J15: 45580 | K15: 45607
A16: 13 | B16: 3221 | C16: Musallam Mohammed Salim Al Barami | D16: 294.1 | E16: 0.4 | F16: =E16*D16 -> 117.64 | G16: =117.18+0.46 -> 117.64 | H16: =F16-G16 -> 0 | I16: 13362673 | J16: 16-09-2024-feeds | K16: 45630
A17: 14 | B17: 3222 | C17: Mohammed Ahmed Bakhit Qatan | D17: 555.3 | E17: 0.4 | F17: =E17*D17 -> 222.12 | G17: =218.1+4.02 -> 222.12 | H17: =F17-G17 -> 0 | I17: 18091329 | J17: 45544 | K17: 45602
A18: 15 | B18: 3231 | C18: Tanaf Suhail Ali Hawas Al Aamri | D18: 610.3 | E18: 0.4 | F18: =E18*D18 -> 244.12 | G18: =56+72.75+111.55+3.82 -> 244.12 | H18: =F18-G18 -> 0 | I18: 6203903 | J18: 25-09-2024,13-10-24,21-10
A19: 16 | B19: 3239 | C19: Ali Salim Bakhit Qatan | D19: 584 | E19: 0.4 | F19: =E19*D19 -> 233.6 | G19: =229.88+3.72 -> 233.6 | H19: =F19-G19 -> 0 | I19: 14379226 | J19: 09-01-2024-feeds | K19: 45609
A20: 17 | B20: 3240 | C20: Ali Said Salim Al kathiri | D20: 601.9 | E20: 0.4 | F20: =E20*D20 -> 240.76 | G20: =239.49+1.27 -> 240.76 | H20: =F20-G20 -> 0 | I20: 5622856 | J20: 23-09-2024 | K20: 45642
A21: 18 | B21: 3243 | C21: Asad Ali Ahmed Suhail Aamir Jid | D21: 327.1 | E21: 0.4 | F21: =E21*D21 -> 130.84 | G21: =128.88+1.96 -> 130.84 | H21: =F21-G21 -> 0 | I21: 25887256 | J21: 18-09-2024 | K21: 45615
A22: 19 | B22: 3244 | C22: Mohammed Ali Bakhit Qatan | D22: 253.4 | E22: 0.4 | F22: =E22*D22 -> 101.36 | G22: =F22 -> 101.36 | H22: =F22-G22 -> 0 | I22: 19340943 | J22: 23-09-2024
A23: 20 | B23: 3252 | C23: Said Amer Salim Qatan | D23: 233.8 | E23: 0.4 | F23: =E23*D23 -> 93.52 | G23: =92.96+0.56 -> 93.52 | H23: =F23-G23 -> 0 | I23: 460074 | J23: 09-01-2024-feeds | K23: 45621
A24: 21 | B24: 3254 | C24: Said Mohammed Musallam Al Shihri | D24: 552 | E24: 0.4 | F24: =E24*D24 -> 220.8 | G24: =220.47+0.33 -> 220.8 | H24: =F24-G24 -> 0 | I24: 6668983 | J24: 45547 | K24: 45602
A25: 22 | B25: 3258 | C25: Ahmed Salim Amer Qatan | D25: 806.7 | E25: 0.4 | F25: =E25*D25 -> 322.68 | G25: =320.1+2.58 -> 322.68 | H25: =F25-G25 -> 0 | I25: 15335306 | J25: 45538
A26: 23 | B26: 3286 | C26: Ali Salim Amor Salim Qatan | D26: 392 | E26: 0.4 | F26: =E26*D26 -> 156.8 | G26: =153.47+3.33 -> 156.8 | H26: =F26-G26 -> 0 | I26: 23232841 | J26: 16-09-24 | K26: 45624
A27: 24 | B27: 3294 | C27: Ahmed Ali Said Qatan | D27: 582 | E27: 0.4 | F27: =E27*D27 -> 232.8 | G27: =F27 -> 232.8 | H27: =F27-G27 -> 0 | I27: 19263029 | J27: 23-09-24 | K27: 45658
A28: 25 | B28: 3295 | C28: Ahmed Salim Ahmed Tabook | D28: 303.3 | E28: 0.4 | F28: =E28*D28 -> 121.32 | G28: =F28 -> 121.32 | H28: =F28-G28 -> 0 | I28: 20378353 | J28: 45332
A29: 26 | B29: 3302 | C29: Mohamed Ahmed Salim Khalis Almasahli | D29: 553.4 | E29: 0.4 | F29: =E29*D29 -> 221.36 | G29: =218.25+3.11 -> 221.36 | H29: =F29-G29 -> 0 | I29: 71004483 | J29: 23-09-2024 | K29: 3.11 dcf
A30: 27 | B30: 3309 | C30: Ahmed Said Amer Qatan | D30: 243.1 | E30: 0.4 | F30: =E30*D30 -> 97.24 | G30: =92.58+4.66 -> 97.24 | H30: =F30-G30 -> 0 | I30: 21453611 | J30: 09-01-2024-feeds | K30: 45621
A31: 28 | B31: 3312 | C31: Ahmed Salim Said Amor Jid Al Mahri | D31: 612 | E31: 0.4 | F31: =E31*D31 -> 244.8 | G31: =242.99+1.81 -> 244.8 | H31: =F31-G31 -> 0 | I31: 881326 | J31: 45582 | K31: 45602
A32: 29 | B32: 3314 | C32: Said Aubad Jamaan Al Kathiri | D32: 582.4 | E32: 0.4 | F32: =E32*D32 -> 232.96 | G32: =230.9+2.06 -> 232.96 | H32: =F32-G32 -> 0 | I32: 766893 | J32: 23-09-2024 | K32: 45609
A33: 30 | B33: 3315 | C33: Musallam Said Amer Qatan | D33: 240.8 | E33: 0.4 | F33: =E33*D33 -> 96.32 | G33: =92.44+3.88 -> 96.32 | H33: =F33-G33 -> 0 | I33: 23957422 | J33: 09-01-2024-feeds | K33: 45621
A34: 31 | B34: 3316 | C34: Amer Said Amer Salim Qatan | D34: 234.1 | E34: 0.4 | F34: =E34*D34 -> 93.64 | G34: =91.93+1.71 -> 93.64 | H34: =F34-G34 -> 0 | I34: 26159748 | J34: 09-01-2024-feeds | K34: 45621
A35: 32 | B35: 3325 | C35: Ali Salim Said Qatan | D35: 142.6 | E35: 0.4 | F35: =E35*D35 -> 57.04 | G35: =54.8+2.24 -> 57.04 | H35: =F35-G35 -> 0 | I35: 21849398 | J35: 45544 | K35: 45637
A36: 33 | B36: 3328 | C36: Ahmed Said Mohammed Tabook | D36: 592.1 | E36: 0.4 | F36: =E36*D36 -> 236.84 | G36: =230.78+6.06 -> 236.84 | H36: =F36-G36 -> 0 | I36: 1934204 | J36: 45538 | K36: 45602
A37: 34 | B37: 3720 | C37: Mohammed Ahmed Masoud Dakari ALKathiri | D37: 402.7 | E37: 0.4 | F37: =E37*D37 -> 161.08 | G37: =158.93+2.15 -> 161.08 | H37: =F37-G37 -> 0 | I37: 2518469 | J37: 09-01-2024-feeds | K37: 2.150 dcf feed
A38: 35 | B38: 3733 | C38: Salim Said Amer Salim Qatan | D38: 159 | E38: 0.4 | F38: =E38*D38 -> 63.6 | G38: =62+1.6 -> 63.6 | H38: =F38-G38 -> 0 | I38: 23270163 | J38: 45544 | K38: 45607
A39: 36 | B39: 3742 | C39: Mohammed Said Suhail Qatan | D39: 22.3 | E39: 0.4 | F39: =E39*D39 -> 8.92 | G39: =F39 -> 8.92 | H39: =F39-G39 -> 0 | I39: 1930281 | J39: 28=-1-25
A40: 37 | B40: 3746 | C40: Nadir Said Ahmed Al kathiri | D40: 369.5 | E40: 0.4 | F40: =E40*D40 -> 147.8 | G40: =143.96+3.84 -> 147.8 | H40: =F40-G40 -> 0 | I40: 21973713 | J40: 45567 | K40: 45624
A41: 38 | B41: 3755 | C41: Said Amer Said Amar Jid Al mahri | D41: 608.3 | E41: 0.4 | F41: =E41*D41 -> 243.32 | G41: =242.5+0.82 -> 243.32 | H41: =F41-G41 -> 0 | I41: 15536654 | J41: 45582 | K41: 45624
A42: 39 | B42: 3759 | C42: Ahmed Ali Suhail Lahbet Alkathiri | D42: 330 | E42: 0.4 | F42: =E42*D42 -> 132 | G42: =131.53+0.47 -> 132 | H42: =F42-G42 -> 0 | I42: 5634282 | J42: 30-09-2024 | K42: 45630
A43: 40 | B43: 3760 | C43: Aubad Said Aubad Ghawas | D43: 307.1 | E43: 0.4 | F43: =E43*D43 -> 122.84 | G43: =119.63+3.21 -> 122.84 | H43: =F43-G43 -> 0 | I43: 19531566 | J43: 30-09-2024 | K43: 45607
A44: 41 | B44: 3764 | C44: Ali Musallam Amer Amer Jid Almahri | D44: 747.7 | E44: 0.4 | F44: =E44*D44 -> 299.08 | G44: =295.85+3.23 -> 299.08 | H44: =F44-G44 -> 0 | I44: 1996843 | J44: 45586 | K44: 16-01-25
A45: 42 | B45: 3770 | C45: Ali Mohammed Suhail Ghawas | D45: 216.5 | E45: 0.4 | F45: =E45*D45 -> 86.6 | G45: 82.45 | H45: =F45-G45 -> 4.15 | I45: 7198036 | J45: 45547
A46: 43 | B46: 3775 | C46: Suhail Mohamed Suhail Saad Ghawas | D46: 204.7 | E46: 0.4 | F46: =E46*D46 -> 81.88 | G46: =78.32+3.56 -> 81.88 | H46: =F46-G46 -> 0 | I46: 7198074 | J46: 45547 | K46: 45635
A47: 44 | B47: 3793 | C47: Musallam Taman Ahmed Almaashani | D47: 812.3 | E47: 0.4 | F47: =E47*D47 -> 324.92 | G47: =322.57+2.35 -> 324.92 | H47: =F47-G47 -> 0 | I47: 1283875 | J47: 16-09-2024 | K47: BT 02-02-2025
A48: 45 | B48: 3799 | C48: Hamid Awadh Salim Hawas AL Aamri | D48: 769.5 | E48: 0.4 | F48: =E48*D48 -> 307.8 | G48: =305.55+2.25 -> 307.8 | H48: =F48-G48 -> 0 | I48: 12494672 | J48: 45580 | K48: 45607
A49: 46 | B49: 3812 | C49: Ali Musallam Rabeea Hubais | D49: 338 | E49: 0.4 | F49: =E49*D49 -> 135.2 | G49: =130.95+4.25 -> 135.2 | H49: =F49-G49 -> 0 | I49: 2441718 | J49: 30-09-2024 | K49: 4.25 bt
A50: 47 | B50: 3813 | C50: Nassar Musallam Said Qatan | D50: 193.1 | E50: 0.4 | F50: =E50*D50 -> 77.24 | G50: =F50 -> 77.24 | H50: =F50-G50 -> 0 | I50: 18842378 | J50: 16-09-2024
A51: 48 | B51: 3817 | C51: Suhail Musallam Ahmed Jaboob | D51: 472.9 | E51: 0.4 | F51: =E51*D51 -> 189.16 | G51: =186.8+2.36 -> 189.16 | H51: =F51-G51 -> 0 | I51: 7851322 | J51: 05-09-24-feeds | K51: 45662
A52: 49 | B52: 3827 | C52: Talal ali ahmed Al Jahfali | D52: 792 | E52: 0.4 | F52: =E52*D52 -> 316.8 | G52: =312.22+4.58 -> 316.8 | H52: =F52-G52 -> 0 | I52: 19049113 | J52: 18-09-2024 | K52: 45609
A53: 50 | B53: 3851 | C53: Rajeh Ahmed Said Kirdas Al Shahri | D53: 242.2 | E53: 0.4 | F53: =E53*D53 -> 96.88 | G53: =94.71+2.17 -> 96.88 | H53: =F53-G53 -> 0 | I53: 22766611 | J53: 23-09-2024 | K53: 45635
A54: 51 | B54: 3857 | C54: Ahmed Ali Said Musallam Hubas | D54: 779.7 | E54: 0.4 | F54: =E54*D54 -> 311.88 | G54: =307.82+4.06 -> 311.88 | H54: =F54-G54 -> 0 | I54: 28903474 | J54: 45578 | K54: 45638 | L54: 4.06-DCF
A55: 52 | B55: 3876 | C55: Mohammed Salim Ali Al Jahf ali | D55: 366 | E55: 0.4 | F55: =E55*D55 -> 146.4 | G55: =145.5+0.9 -> 146.4 | H55: =F55-G55 -> 0 | I55: 4767948 | J55: 45587 | K55: 45635
A56: 53 | B56: 3888 | C56: Salim Ali Dablan Jaboob | D56: 417 | E56: 0.4 | F56: =E56*D56 -> 166.8 | G56: =164.19+2.61 -> 166.8 | H56: =F56-G56 -> 0 | I56: 1808869 | J56: 45602
C57: TOTAL | D57: =SUM(D4:D56) -> 24090.1 | F57: =SUM(F4:F56) -> 9636.04 | G57: =SUM(G4:G56) -> 9631.89 | H57: =SUM(H4:H56) -> 4.15
G58: =SUBTOTAL(9,G23:G57) -> 10967.78
G61: =G57/F57 -> 0.99956933 | H61: =H57-142.37 -> -138.22

Sheet center-July
A1: HAJEEF CAMEL MILK PROCUREMENT FROM 01-July-2024 TO 31-July-2024
A3: Sr. No. | B3: Farmer Code | C3: Farmer Name | D3: Total Milk Qty | E3: Avg. Rate (OMR/Ltr.) | F3: Amount (OMR) | G3: Paid | H3: Balance | I3: ID No. | J3: Bank Account | K3: Bank Name. | L3: SWIFT | M3: Phone No. | N3: remark 2 | Q3: Farmer Code | S3: Farmer Name | U3: ID No. | W3: Bank Account | Y3: SWIFT
A4: 1 | B4: 1108 | C4: Bakhit Ahmed Musallam Al kathiri | D4: 1162.1 | E4: 0.4 | F4: =E4*D4 -> 464.84 | G4: =F4 -> 464.84 | H4: =F4-G4 -> 0 | I4: 15218386 | J4: 0439012124150013 | K4: BANK MUSCAT | L4: BMUSOMRX | M4: 92776884 | Q4: 1108 | R4: =Q4=B4 -> TRUE | S4: Bakhit Ahmed Musallam Al kathiri | T4: =S4=C4 -> TRUE | U4: 15218386 | V4: =U4=I4 -> TRUE | W4: 0439012124150013 | X4: =W4=J4 -> TRUE | Y4: BMUSOMRX | Z4: =Y4=L4 -> TRUE
A5: 2 | B5: 1390 | C5: Bakhait Salim Ahmed Alash Al Kathiri | D5: 400 | E5: 0.4 | F5: =E5*D5 -> 160 | G5: =155.15+4.85 -> 160 | H5: =F5-G5 -> 0 | I5: 12181822 | J5: 0439014599800023 | K5: BANK MUSCAT | L5: BMUSOMRX | M5: 92442060 | N5: 45596 | O5: 45609 | Q5: 1390 | R5: =Q5=B5 -> TRUE | S5: Bakhait Salim Ahmed Alash Al Kathiri | T5: =S5=C5 -> TRUE | U5: 12181822 | V5: =U5=I5 -> TRUE | W5: 0439014599800023 | X5: =W5=J5 -> TRUE | Y5: BMUSOMRX | Z5: =Y5=L5 -> TRUE
A6: 3 | B6: 1399 | C6: Mohammed Suhail Ali Hawas Al Aamri | D6: 304.3 | E6: 0.4 | F6: =E6*D6 -> 121.72 | G6: =118.07+3.65 -> 121.72 | H6: =F6-G6 -> 0 | I6: 10065546 | J6: 3109720870700 | K6: OAB | L6: OMABOMRU | N6: 45596 | O6: 45615 | Q6: 1399 | R6: =Q6=B6 -> TRUE | S6: Mohammed Suhail Ali Hawas Al Aamri | T6: =S6=C6 -> TRUE | U6: 10065546 | V6: =U6=I6 -> TRUE | W6: 3109720870700 | X6: =W6=J6 -> TRUE | Y6: OMABOMRU | Z6: =Y6=L6 -> TRUE
A7: 4 | B7: 1422 | C7: Mahammed Musallam Ahmed Hwas | D7: 310.5 | E7: 0.4 | F7: =E7*D7 -> 124.2 | G7: =119+5.2 -> 124.2 | H7: =F7-G7 -> 0 | I7: 3280016 | J7: 0397003987550015 | K7: BANK MUSCAT | L7: BMUSOMRX | N7: 45567 | O7: 45602 | Q7: 1422 | R7: =Q7=B7 -> TRUE | S7: Mahammed Musallam Ahmed Hwas | T7: =S7=C7 -> TRUE | U7: 3280016 | V7: =U7=I7 -> TRUE | W7: 0397003987550015 | X7: =W7=J7 -> TRUE | Y7: BMUSOMRX | Z7: =Y7=L7 -> TRUE
A8: 5 | B8: 1424 | C8: Said Ahmed Sabah Ali Badar | D8: 457 | E8: 0.4 | F8: =E8*D8 -> 182.8 | G8: =128.35+54.45 -> 182.8 | H8: =F8-G8 -> 0 | I8: 748395 | J8: 01012574607001 | K8: BANK DHOFAR | L8: BDOFOMRU | M8: 93011211 | N8: 45567 | O8: 45609 | Q8: 1424 | R8: =Q8=B8 -> TRUE | S8: Said Ahmed Sabah Ali Badar | T8: =S8=C8 -> TRUE | U8: 748395 | V8: =U8=I8 -> TRUE | W8: 01012574607001 | X8: =W8=J8 -> TRUE | Y8: BDOFOMRU | Z8: =Y8=L8 -> TRUE
A9: 6 | B9: 1429 | C9: Said Mohammed Salem Akdha Al Rawas | D9: 540 | E9: 0.4 | F9: =E9*D9 -> 216 | G9: =F9 -> 216 | H9: =F9-G9 -> 0 | I9: 339725 | J9: 0397003785300017 | K9: BANK MUSCAT | L9: BMUSOMRX | Q9: 1429 | R9: =Q9=B9 -> TRUE | S9: Said Mohammed Salem Akdha Al Rawas | T9: =S9=C9 -> TRUE | U9: 339725 | V9: =U9=I9 -> TRUE | W9: 0397003785300017 | X9: =W9=J9 -> TRUE | Y9: BMUSOMRX | Z9: =Y9=L9 -> TRUE
A10: 7 | B10: 1431 | C10: Bakhit Mohamed Salim Rawas | D10: 400.9 | E10: 0.4 | F10: =E10*D10 -> 160.36 | G10: =158.65+1.71 -> 160.36 | H10: =F10-G10 -> 0 | I10: 721445 | J10: 01010850230001 | K10: BANK DHOFAR | L10: BDOFOMRU | M10: 99291700 | N10: 45607 | O10: 45628 | Q10: 1431 | R10: =Q10=B10 -> TRUE | S10: Bakhit Mohamed Salim Rawas | T10: =S10=C10 -> TRUE | U10: 721445 | V10: =U10=I10 -> TRUE | W10: 01010850230001 | X10: =W10=J10 -> TRUE | Y10: BDOFOMRU | Z10: =Y10=L10 -> TRUE
A11: 8 | B11: 1443 | C11: Ahmed Musallam Ahmed Al Kathiri | D11: 1528.9 | E11: 0.4 | F11: =E11*D11 -> 611.56 | G11: =F11 -> 611.56 | H11: =F11-G11 -> 0 | I11: 6026992 | J11: 0439017196260028 | K11: BANK MUSCAT | L11: BMUSOMRX | M11: 95863774 | Q11: 1443 | R11: =Q11=B11 -> TRUE | S11: Ahmed Musallam Ahmed Al Kathiri | T11: =S11=C11 -> TRUE | U11: 6026992 | V11: =U11=I11 -> TRUE | W11: 0439017196260028 | X11: =W11=J11 -> TRUE | Y11: BMUSOMRX | Z11: =Y11=L11 -> TRUE
A12: 9 | B12: 1452 | C12: Sulaim Said Mohammed Hawas Al Aamri | D12: 220.6 | E12: 0.4 | F12: =E12*D12 -> 88.24 | G12: =88.24 -> 88.24 | H12: =F12-G12 -> 0 | I12: 20917176 | J12: 0406012189810015 | K12: BANK MUSCAT | L12: BMUSOMRX | M12: 95863774 | N12: 45602 | Q12: 1452 | R12: =Q12=B12 -> TRUE | S12: Sulaim Said Mohammed Hawas Al Aamri | T12: =S12=C12 -> TRUE | U12: 20917176 | V12: =U12=I12 -> TRUE | W12: 0406012189810015 | X12: =W12=J12 -> TRUE | Y12: BMUSOMRX | Z12: =Y12=L12 -> TRUE
A13: 10 | B13: 1458 | C13: Salim Mustahil Jamaan Al Shakl Al kathiri | D13: 369.5 | E13: 0.4 | F13: =E13*D13 -> 147.8 | G13: =F13 -> 147.8 | H13: =F13-G13 -> 0 | I13: 77628 | J13: 01012583986001 | K13: BANK DHOFAR | L13: BDOFOMRU | M13: 99275608 | Q13: 1458 | R13: =Q13=B13 -> TRUE | S13: Salim Mustahil Jamaan Al Shakl Al kathiri | T13: =S13=C13 -> TRUE | U13: 77628 | V13: =U13=I13 -> TRUE | W13: 01012583986001 | X13: =W13=J13 -> TRUE | Y13: BDOFOMRU | Z13: =Y13=L13 -> TRUE
A14: 11 | B14: 1461 | C14: Suhail Said Ali Bait said | D14: 342.9 | E14: 0.4 | F14: =E14*D14 -> 137.16 | G14: =F14 -> 137.16 | H14: =F14-G14 -> 0 | I14: 6828806 | J14: 0396003267730012 | K14: BANK MUSCAT | L14: BMUSOMRX | M14: 92330321 | Q14: 1461 | R14: =Q14=B14 -> TRUE | S14: Suhail Said Ali Bait said | T14: =S14=C14 -> TRUE | U14: 6828806 | V14: =U14=I14 -> TRUE | W14: 0396003267730012 | X14: =W14=J14 -> TRUE | Y14: BMUSOMRX | Z14: =Y14=L14 -> TRUE
A15: 12 | B15: 1465 | C15: Mahad Salim Zaed Baitsaid | D15: 354.1 | E15: 0.4 | F15: =E15*D15 -> 141.64 | G15: =F15 -> 141.64 | H15: =F15-G15 -> 0 | I15: 757601 | J15: 1023113274001 | K15: NBO | L15: NBOMOMRX | M15: 99892131 | Q15: 1465 | R15: =Q15=B15 -> TRUE | S15: Mahad Salim Zaed Baitsaid | T15: =S15=C15 -> TRUE | U15: 757601 | V15: =U15=I15 -> TRUE | W15: 1023113274001 | X15: =W15=J15 -> TRUE | Y15: NBOMOMRX | Z15: =Y15=L15 -> TRUE
A16: 13 | B16: 1474 | C16: Mohamed Salam Amer Al Yafee | D16: 915.7 | E16: 0.4 | F16: =E16*D16 -> 366.28 | G16: =360.94+5.34 -> 366.28 | H16: =F16-G16 -> 0 | I16: 4603773 | J16: 01041185194001 | K16: BANK DHOFAR | L16: BDOFOMRU | M16: 98820843 | N16: 45637 | O16: 45658 | Q16: 1474 | R16: =Q16=B16 -> TRUE | S16: Mohamed Salam Amer Al Yafee | T16: =S16=C16 -> TRUE | U16: 4603773 | V16: =U16=I16 -> TRUE | W16: 01041185194001 | X16: =W16=J16 -> TRUE | Y16: BDOFOMRU | Z16: =Y16=L16 -> TRUE
A17: 14 | B17: 1479 | C17: Ahmed Amer Said Baitsaid | D17: 383.7 | E17: 0.4 | F17: =E17*D17 -> 153.48 | G17: =F17 -> 153.48 | H17: =F17-G17 -> 0 | I17: 5217726 | J17: 0396003219770029 | K17: BANK MUSCAT | L17: BMUSOMRX | M17: 92610234 | N17: 45602
A18: 15 | B18: 1483 | C18: Saed Ali Ahmed Al Kathiri | D18: 912 | E18: 0.4 | F18: =E18*D18 -> 364.8 | G18: =360.69+4.11 -> 364.8 | H18: =F18-G18 -> 0 | I18: 1567826 | J18: 1083724895017 | K18: NBO | L18: NBOMOMRX | M18: 98532884 | N18: 45602 | O18: 45607 | Q18: 1483 | R18: =Q18=B18 -> TRUE | S18: Saed Ali Ahmed Al Kathiri | T18: =S18=C18 -> TRUE | U18: 1567826 | V18: =U18=I18 -> TRUE | W18: 1083724895017 | X18: =W18=J18 -> TRUE | Y18: NBOMOMRX | Z18: =Y18=L18 -> TRUE
A19: 16 | B19: 1486 | C19: Mosoud Ali Salim Al Kathiri | D19: 428.9 | E19: 0.4 | F19: =E19*D19 -> 171.56 | G19: =F19 -> 171.56 | H19: =F19-G19 -> 0 | I19: 22792564 | J19: 0401064266530014 | K19: BANK MUSCAT | L19: BMUSOMRX
A20: 17 | B20: 1762 | C20: MUSALLAM HASAN ALI BAIT SAID | D20: 1345 | E20: 0.4 | F20: =E20*D20 -> 538 | G20: =F20 -> 538 | H20: =F20-G20 -> 0 | I20: 1409527 | J20: 0397003183710017 | K20: Bank Muscat | L20: BMUSOMRX | N20: dcf feed | Q20: 1762 | R20: =Q20=B20 -> TRUE | S20: MUSALLAM HASAN ALI BAIT SAID | T20: =S20=C20 -> TRUE | U20: 1409527 | V20: =U20=I20 -> TRUE | W20: 0397003183710017 | X20: =W20=J20 -> TRUE | Y20: BMUSOMRX | Z20: =Y20=L20 -> TRUE
A21: 18 | B21: 1792 | C21: Musallam Bakhit Salim Al Aamri | D21: 394.1 | E21: 0.4 | F21: =E21*D21 -> 157.64 | G21: =F21 -> 157.64 | H21: =F21-G21 -> 0 | I21: 9545556 | J21: 01011373210001 | K21: BANK DHOFAR | L21: BDOFOMRU | Q21: 1792 | R21: =Q21=B21 -> TRUE | S21: Musallam Bakhit Salim Al Aamri | T21: =S21=C21 -> TRUE | U21: 9545556 | V21: =U21=I21 -> TRUE | W21: 01011373210001 | X21: =W21=J21 -> TRUE | Y21: BDOFOMRU | Z21: =Y21=L21 -> TRUE
A22: 19 | B22: 3009 | C22: Ahmed Salim Bakhit Qatan | D22: 352 | E22: 0.4 | F22: =E22*D22 -> 140.8 | G22: =F22 -> 140.8 | H22: =F22-G22 -> 0 | I22: 1448391 | J22: 3109628132500 | K22: OAB | L22: OMABOMRU | M22: 99100144 | Q22: 3009 | R22: =Q22=B22 -> TRUE | S22: Ahmed Salim Bakhit Qatan | T22: =S22=C22 -> TRUE | U22: 1448391 | V22: =U22=I22 -> TRUE | W22: 3109628132500 | X22: =W22=J22 -> TRUE | Y22: OMABOMRU | Z22: =Y22=L22 -> TRUE
A23: 20 | B23: 3012 | C23: Salim Suhail Ali Al Kathiri | D23: 364 | E23: 0.4 | F23: =E23*D23 -> 145.6 | G23: =142.67+2.93 -> 145.6 | H23: =F23-G23 -> 0 | I23: 5634422 | J23: 0406059374210012 | K23: BANK MUSCAT | L23: BMUSOMRX | M23: 96922118 | N23: 45586 | O23: 45624 | Q23: 3012 | R23: =Q23=B23 -> TRUE | S23: Salim Suhail Ali Al Kathiri | T23: =S23=C23 -> TRUE | U23: 5634422 | V23: =U23=I23 -> TRUE | W23: 0406059374210012 | X23: =W23=J23 -> TRUE | Y23: BMUSOMRX | Z23: =Y23=L23 -> TRUE
A24: 21 | B24: 3014 | C24: Ahmed Mohammed Salim Al Barami | D24: 315.1 | E24: 0.4 | F24: =E24*D24 -> 126.04 | G24: =123.35+2.69 -> 126.04 | H24: =F24-G24 -> 0 | I24: 648421 | J24: 3129711924500 | K24: OAB | L24: OMABOMRU | M24: 98815665 | N24: 45567 | O24: 45602 | Q24: 3014 | R24: =Q24=B24 -> TRUE | S24: Ahmed Mohammed Salim Al Barami | T24: =S24=C24 -> TRUE | U24: 648421 | V24: =U24=I24 -> TRUE | W24: 3129711924500 | X24: =W24=J24 -> TRUE | Y24: OMABOMRU | Z24: =Y24=L24 -> TRUE
A25: 22 | B25: 3015 | C25: Ahmed Mohammed Faraj Al Kathiri | D25: 372.4 | E25: 0.4 | F25: =E25*D25 -> 148.96 | G25: =F25 -> 148.96 | H25: =F25-G25 -> 0 | I25: 5753033 | J25: 0439058732890011 | K25: BANK MUSCAT | L25: BMUSOMRX | M25: 92838405 | Q25: 3015 | R25: =Q25=B25 -> TRUE | S25: Ahmed Mohammed Faraj Al Kathiri | T25: =S25=C25 -> TRUE | U25: 5753033 | V25: =U25=I25 -> TRUE | W25: 0439058732890011 | X25: =W25=J25 -> TRUE | Y25: BMUSOMRX | Z25: =Y25=L25 -> TRUE
A26: 23 | B26: 3018 | C26: Bakhit Salim Bakhit Qatan | D26: 297.2 | E26: 0.4 | F26: =E26*D26 -> 118.88 | G26: =117.88+1 -> 118.88 | H26: =F26-G26 -> 0 | I26: 1528087 | J26: 0397004184300024 | K26: BANK MUSCAT | L26: BMUSOMRX | N26: 45588 | O26: 45602 | Q26: 3018 | R26: =Q26=B26 -> TRUE | S26: Bakhit Salim Bakhit Qatan | T26: =S26=C26 -> TRUE | U26: 1528087 | V26: =U26=I26 -> TRUE | W26: 0397004184300024 | X26: =W26=J26 -> TRUE | Y26: BMUSOMRX | Z26: =Y26=L26 -> TRUE
A27: 24 | B27: 3020 | C27: Bakhit Ali Salim Qatan | D27: 672.4 | E27: 0.4 | F27: =E27*D27 -> 268.96 | G27: =268.09+0.87 -> 268.96 | H27: =F27-G27 -> 0 | I27: 5418422 | J27: 0401002342630017 | K27: BANK MUSCAT | L27: BMUSOMRX | M27: 99495434 | N27: 45567 | O27: 45602 | Q27: 3020 | R27: =Q27=B27 -> TRUE | S27: Bakhit Ali Salim Qatan | T27: =S27=C27 -> TRUE | U27: 5418422 | V27: =U27=I27 -> TRUE | W27: 0401002342630017 | X27: =W27=J27 -> TRUE | Y27: BMUSOMRX | Z27: =Y27=L27 -> TRUE
A28: 25 | B28: 3022 | C28: Hussein Masoud Aubad Al Kathiri | D28: 1246.9 | E28: 0.4 | F28: =E28*D28 -> 498.76 | G28: =497.9+0.86 -> 498.76 | H28: =F28-G28 -> 0 | I28: 5360253 | J28: 1060656310017 | K28: NBO | L28: NBOMOMRX | M28: 99257989 | N28: 45609 | O28: 45637 | Q28: 3022 | R28: =Q28=B28 -> TRUE | S28: Hussein Masoud Aubad Al Kathiri | T28: =S28=C28 -> TRUE | U28: 5360253 | V28: =U28=I28 -> TRUE | W28: 1060656310017 | X28: =W28=J28 -> TRUE | Y28: NBOMOMRX | Z28: =Y28=L28 -> TRUE
A29: 26 | B29: 3025 | C29: Musallam Salim Mahad Qatan | D29: 711.8 | E29: 0.4 | F29: =E29*D29 -> 284.72 | G29: =F29 -> 284.72 | H29: =F29-G29 -> 0 | I29: 7542172 | J29: 0401002461080028 | K29: BANK MUSCAT | L29: BMUSOMRX | Q29: 3025 | R29: =Q29=B29 -> TRUE | S29: Musallam Salim Mahad Qatan | T29: =S29=C29 -> TRUE | U29: 7542172 | V29: =U29=I29 -> TRUE | W29: 0401002461080028 | X29: =W29=J29 -> TRUE | Y29: BMUSOMRX | Z29: =Y29=L29 -> TRUE
A30: 27 | B30: 3026 | C30: Amer Salem Ahmed Qatan | D30: 374.6 | E30: 0.4 | F30: =E30*D30 -> 149.84 | G30: =F30 -> 149.84 | H30: =F30-G30 -> 0 | I30: 7033819 | J30: 0401003532620025 | K30: BANK MUSCAT | L30: BMUSOMRX | M30: 92256918 | Q30: 3026 | R30: =Q30=B30 -> TRUE | S30: Amer Salem Ahmed Qatan | T30: =S30=C30 -> TRUE | U30: 7033819 | V30: =U30=I30 -> TRUE | W30: 0401003532620025 | X30: =W30=J30 -> TRUE | Y30: BMUSOMRX | Z30: =Y30=L30 -> TRUE
A31: 28 | B31: 3027 | C31: Salim Ahmed Mahad Aamir Jid | D31: 732.8 | E31: 0.4 | F31: =E31*D31 -> 293.12 | G31: =292.65+0.47 -> 293.12 | H31: =F31-G31 -> 0 | I31: 6420643 | J31: 01011362595002 | K31: BANK DHOFAR | L31: BDOFOMRU | M31: 92288434 | N31: 45576 | O31: 45685 | Q31: 3027 | R31: =Q31=B31 -> TRUE | S31: Salim Ahmed Mahad Aamir Jid | T31: =S31=C31 -> TRUE | U31: 6420643 | V31: =U31=I31 -> TRUE | W31: 01011362595002 | X31: =W31=J31 -> TRUE | Y31: BDOFOMRU | Z31: =Y31=L31 -> TRUE
A32: 29 | B32: 3030 | C32: Salim Ahmed Salim Amer Jid | D32: 405 | E32: 0.4 | F32: =E32*D32 -> 162 | G32: =F32 -> 162 | H32: =F32-G32 -> 0 | I32: 6021175 | J32: 0401050718800013 | K32: BANK MUSCAT | L32: BMUSOMRX | M32: 91716888 | Q32: 3030 | R32: =Q32=B32 -> TRUE | S32: Salim Ahmed Salim Amer Jid | T32: =S32=C32 -> TRUE | U32: 6021175 | V32: =U32=I32 -> TRUE | W32: 0401050718800013 | X32: =W32=J32 -> TRUE | Y32: BMUSOMRX | Z32: =Y32=L32 -> TRUE
A33: 30 | B33: 3038 | C33: Said Ahmed Mahad Qatan | D33: 783 | E33: 0.4 | F33: =E33*D33 -> 313.2 | G33: =308.25+4.95 -> 313.2 | H33: =F33-G33 -> 0 | I33: 7976 | J33: 3109016888700 | K33: OAB | L33: OMABOMRU | M33: 98920007 | N33: 45602 | O33: 45621 | Q33: 3038 | R33: =Q33=B33 -> TRUE | S33: Said Ahmed Mahad Qatan | T33: =S33=C33 -> TRUE | U33: 7976 | V33: =U33=I33 -> TRUE | W33: 3109016888700 | X33: =W33=J33 -> TRUE | Y33: OMABOMRU | Z33: =Y33=L33 -> TRUE
A34: 31 | B34: 3043 | C34: Said Aubad Ali Ghawas | D34: 338.5 | E34: 0.4 | F34: =E34*D34 -> 135.4 | G34: =F34 -> 135.4 | H34: =F34-G34 -> 0 | I34: 396336 | J34: 0397003933630013 | K34: BANK MUSCAT | L34: BMUSOMRX | M34: 99498844 | Q34: 3043 | R34: =Q34=B34 -> TRUE | S34: Said Aubad Ali Ghawas | T34: =S34=C34 -> TRUE | U34: 396336 | V34: =U34=I34 -> TRUE | W34: 0397003933630013 | X34: =W34=J34 -> TRUE | Y34: BMUSOMRX | Z34: =Y34=L34 -> TRUE
A35: 32 | B35: 3058 | C35: Ali Bakhit Ahmed Qatan | D35: 1298.6 | E35: 0.4 | F35: =E35*D35 -> 519.44 | G35: =F35 -> 519.44 | H35: =F35-G35 -> 0 | I35: 965148 | J35: 3129376165700 | K35: OAB | L35: OMABOMRU | M35: 90980121 | Q35: 3058 | R35: =Q35=B35 -> TRUE | S35: Ali Bakhit Ahmed Qatan | T35: =S35=C35 -> TRUE | U35: 965148 | V35: =U35=I35 -> TRUE | W35: 3129376165700 | X35: =W35=J35 -> TRUE | Y35: OMABOMRU | Z35: =Y35=L35 -> TRUE
A36: 33 | B36: 3070 | C36: Mohamed Ahmed Suhail Qatan | D36: 1168.7 | E36: 0.4 | F36: =E36*D36 -> 467.48 | G36: =F36 -> 467.48 | H36: =F36-G36 -> 0 | I36: 1918001 | J36: 0397004395550019 | K36: BANK MUSCAT | L36: BMUSOMRX | M36: 92863640 | N36: 45627 | Q36: 3070 | R36: =Q36=B36 -> TRUE | S36: Mohamed Ahmed Suhail Qatan | T36: =S36=C36 -> TRUE | U36: 1918001 | V36: =U36=I36 -> TRUE | W36: 0397004395550019 | X36: =W36=J36 -> TRUE | Y36: BMUSOMRX | Z36: =Y36=L36 -> TRUE
A37: 34 | B37: 3072 | C37: Mohammed Salim Said Al Barami | D37: 379 | E37: 0.4 | F37: =E37*D37 -> 151.6 | G37: =149.8+1.8 -> 151.6 | H37: =F37-G37 -> 0 | I37: 993077 | J37: 250094968001 | K37: HSBC | L37: BBMEOMRX | M37: 92252981 | N37: 45630 | O37: 45665 | Q37: 3072 | R37: =Q37=B37 -> TRUE | S37: Mohammed Salim Said Al Barami | T37: =S37=C37 -> TRUE | U37: 993077 | V37: =U37=I37 -> TRUE | W37: 250094968001 | X37: =W37=J37 -> TRUE | Y37: BBMEOMRX | Z37: =Y37=L37 -> TRUE
A38: 35 | B38: 3077 | C38: Mohammed Ali Suhail Qatan | D38: 759.2 | E38: 0.4 | F38: =E38*D38 -> 303.68 | G38: =F38 -> 303.68 | H38: =F38-G38 -> 0 | I38: 21978752 | J38: 0396041232890032 | K38: BANK MUSCAT | L38: BMUSOMRX | M38: 90833336 | N38: 45635 | Q38: 3077 | R38: =Q38=B38 -> TRUE | S38: Mohammed Ali Suhail Qatan | T38: =S38=C38 -> TRUE | U38: 21978752 | V38: =U38=I38 -> TRUE | W38: 0396041232890032 | X38: =W38=J38 -> TRUE | Y38: BMUSOMRX | Z38: =Y38=L38 -> TRUE
A39: 36 | B39: 3081 | C39: Musallam Bakhit Masoud Qatan | D39: 519 | E39: 0.4 | F39: =E39*D39 -> 207.6 | G39: =207.15+0.45 -> 207.6 | H39: =F39-G39 -> 0 | I39: 21219868 | J39: 010010201414 | K39: Bank Sohar | L39: BSHROMRU | M39: 93288777 | N39: 45580 | O39: 45635 | Q39: 3081 | R39: =Q39=B39 -> TRUE | S39: Musallam Bakhit Masoud Qatan | T39: =S39=C39 -> TRUE | U39: 21219868 | V39: =U39=I39 -> TRUE | W39: 010010201414 | X39: =W39=J39 -> TRUE | Y39: BSHROMRU | Z39: =Y39=L39 -> TRUE
A40: 37 | B40: 3089 | C40: Yhaya Musallam Said Qatan | D40: 380.7 | E40: 0.4 | F40: =E40*D40 -> 152.28 | G40: =F40 -> 152.28 | H40: =F40-G40 -> 0 | I40: 18790484 | J40: 0401016503450018 | K40: BANK MUSCAT | L40: BMUSOMRX | Q40: 3089 | R40: =Q40=B40 -> TRUE | S40: Yhaya Musallam Said Qatan | T40: =S40=C40 -> TRUE | U40: 18790484 | V40: =U40=I40 -> TRUE | W40: 0401016503450018 | X40: =W40=J40 -> TRUE | Y40: BMUSOMRX | Z40: =Y40=L40 -> TRUE
A41: 38 | B41: 3093 | C41: Bakhit Amer Salem Qatan | D41: 615.4 | E41: 0.4 | F41: =E41*D41 -> 246.16 | G41: =F41 -> 246.16 | H41: =F41-G41 -> 0 | I41: 6361035 | J41: 00510034969002 | K41: BANK NIZWA | L41: BNZWOMRX | M41: 99497919 | Q41: 3093 | R41: =Q41=B41 -> TRUE | S41: Bakhit Amer Salem Qatan | T41: =S41=C41 -> TRUE | U41: 6361035 | V41: =U41=I41 -> TRUE | W41: 00510034969002 | X41: =W41=J41 -> TRUE | Y41: BNZWOMRX | Z41: =Y41=L41 -> TRUE
A42: 39 | B42: 3094 | C42: Ali Ahmed Aubad Jamaan Al Kathiri | D42: 1156.7 | E42: 0.4 | F42: =E42*D42 -> 462.68 | G42: =F42 -> 462.68 | H42: =F42-G42 -> 0 | I42: 26343985 | J42: 0304024501570012 | K42: BANK MUSCAT | L42: BMUSOMRX | M42: 93327740 | Q42: 3094 | R42: =Q42=B42 -> TRUE | S42: Ali Ahmed Aubad Jamaan Al Kathiri | T42: =S42=C42 -> TRUE | U42: 26343985 | V42: =U42=I42 -> TRUE | W42: 0304024501570012 | X42: =W42=J42 -> TRUE | Y42: BMUSOMRX | Z42: =Y42=L42 -> TRUE
A43: 40 | B43: 3100 | C43: Salim Ahmed Said Tabuk | D43: 1620 | E43: 0.4 | F43: =E43*D43 -> 648 | G43: =F43 -> 648 | H43: =F43-G43 -> 0 | I43: 1278615 | J43: 0426003863310028 | K43: NBO | L43: BMUSOMRX | M43: 99806386 | Q43: 3100 | R43: =Q43=B43 -> TRUE | S43: Salim Ahmed Said Tabuk | T43: =S43=C43 -> TRUE | U43: 1278615 | V43: =U43=I43 -> TRUE | W43: 0426003863310028 | X43: =W43=J43 -> TRUE | Y43: BMUSOMRX | Z43: =Y43=L43 -> TRUE
A44: 41 | B44: 3101 | C44: Salim Said Suhail Qatan | D44: 339.9 | E44: 0.4 | F44: =E44*D44 -> 135.96 | G44: =F44 -> 135.96 | H44: =F44-G44 -> 0 | I44: 6767598 | J44: 0401002332700028 | K44: BANK MUSCAT | L44: BMUSOMRX | M44: 99100344 | Q44: 3101 | R44: =Q44=B44 -> TRUE | S44: Salim Said Suhail Qatan | T44: =S44=C44 -> TRUE | U44: 6767598 | V44: =U44=I44 -> TRUE | W44: 0401002332700028 | X44: =W44=J44 -> TRUE | Y44: BMUSOMRX | Z44: =Y44=L44 -> TRUE
A45: 42 | B45: 3102 | C45: Mohammed Salim Amer Qatan | D45: 700.9 | E45: 0.4 | F45: =E45*D45 -> 280.36 | G45: =276.19+4.17 -> 280.36 | H45: =F45-G45 -> 0 | I45: 5916838 | J45: 0317002509980029 | K45: BANK MUSCAT | L45: BMUSOMRX | M45: 91917520 | N45: 45580 | O45: 45602 | Q45: 3102 | R45: =Q45=B45 -> TRUE | S45: Mohammed Salim Amer Qatan | T45: =S45=C45 -> TRUE | U45: 5916838 | V45: =U45=I45 -> TRUE | W45: 0317002509980029 | X45: =W45=J45 -> TRUE | Y45: BMUSOMRX | Z45: =Y45=L45 -> TRUE
A46: 43 | B46: 3119 | C46: Mohammed Ahmed Suhail Mahad Qatan | D46: 1131.2 | E46: 0.4 | F46: =E46*D46 -> 452.48 | G46: =F46 -> 452.48 | H46: =F46-G46 -> 0 | I46: 5903061 | J46: 0401016956230027 | K46: BANK MUSCAT | L46: BMUSOMRX | M46: 91904279 | N46: 45602 | Q46: 3119 | R46: =Q46=B46 -> TRUE | S46: Mohammed Ahmed Suhail Mahad Qatan | T46: =S46=C46 -> TRUE | U46: 5903061 | V46: =U46=I46 -> TRUE | W46: 0401016956230027 | X46: =W46=J46 -> TRUE | Y46: BMUSOMRX | Z46: =Y46=L46 -> TRUE
A47: 44 | B47: 3122 | C47: Khalid Ahmed Salim Amer Jid Al Mahri | D47: 405 | E47: 0.4 | F47: =E47*D47 -> 162 | G47: =130.5+29.1+2.4 -> 162 | H47: =F47-G47 -> 0 | I47: 12415718 | J47: 0401050718800013 | K47: BANK MUSCAT | L47: BMUSOMRX | M47: 99481799 | N47: 45596 | O47: 45602 | P47: 45615 | Q47: 3122 | R47: =Q47=B47 -> TRUE | S47: Khalid Ahmed Salim Amer Jid Al Mahri | T47: =S47=C47 -> TRUE | U47: 12415718 | V47: =U47=I47 -> TRUE | W47: 0401050718800013 | X47: =W47=J47 -> TRUE | Y47: BMUSOMRX | Z47: =Y47=L47 -> TRUE
A48: 45 | B48: 3136 | C48: Ghazi Salim Ahmed Al Kathiri | D48: 718 | E48: 0.4 | F48: =E48*D48 -> 287.2 | G48: =284.06+3.14 -> 287.2 | H48: =F48-G48 -> 0 | I48: 183498 | J48: 01011238092002 | K48: BANK DHOFAR | L48: BDOFOMRU | M48: 99481314 | N48: 45615 | O48: 45624 | Q48: 3136 | R48: =Q48=B48 -> TRUE | S48: Ghazi Salim Ahmed Al Kathiri | T48: =S48=C48 -> TRUE | U48: 183498 | V48: =U48=I48 -> TRUE | W48: 01011238092002 | X48: =W48=J48 -> TRUE | Y48: BDOFOMRU | Z48: =Y48=L48 -> TRUE
A49: 46 | B49: 3178 | C49: Abdul Sallam Ahmed Abdullah Al Abbadi Al Rawas | D49: 2700 | E49: 0.4 | F49: =E49*D49 -> 1080 | G49: =F49 -> 1080 | H49: =F49-G49 -> 0 | I49: 1511754 | J49: 3109061950500 | K49: OAB | L49: OMABOMRU | M49: 99495933 | Q49: 3178 | R49: =Q49=B49 -> TRUE | S49: Abdul Sallam Ahmed Abdullah Al Abbadi Al Rawas | T49: =S49=C49 -> TRUE | U49: 1511754 | V49: =U49=I49 -> TRUE | W49: 3109061950500 | X49: =W49=J49 -> TRUE | Y49: OMABOMRU | Z49: =Y49=L49 -> TRUE
A50: 47 | B50: 3199 | C50: Ali Musallam Ahmed Tabuk | D50: 378 | E50: 0.4 | F50: =E50*D50 -> 151.2 | G50: =F50 -> 151.2 | H50: =F50-G50 -> 0 | I50: 5168327 | J50: 0397004227360018 | K50: BANK MUSCAT | L50: BMUSOMRX | M50: 98066833 | N50: 45637 | Q50: 3199 | R50: =Q50=B50 -> TRUE | S50: Ali Musallam Ahmed Tabuk | T50: =S50=C50 -> TRUE | U50: 5168327 | V50: =U50=I50 -> TRUE | W50: 0397004227360018 | X50: =W50=J50 -> TRUE | Y50: BMUSOMRX | Z50: =Y50=L50 -> TRUE
A51: 48 | B51: 3200 | C51: Ahmed Said Ahmed Qutan | D51: 368.2 | E51: 0.4 | F51: =E51*D51 -> 147.28 | G51: =142.63+4.65 -> 147.28 | H51: =F51-G51 -> 0 | I51: 21947578 | J51: 0401044694220018 | K51: BANK MUSCAT | L51: BMUSOMRX | N51: 45628 | O51: 45656 | Q51: 3200 | R51: =Q51=B51 -> TRUE | S51: Ahmed Said Ahmed Qutan | T51: =S51=C51 -> TRUE | U51: 21947578 | V51: =U51=I51 -> TRUE | W51: 0401044694220018 | X51: =W51=J51 -> TRUE | Y51: BMUSOMRX | Z51: =Y51=L51 -> TRUE
A52: 49 | B52: 3201 | C52: Ali Salim Said Qatan | D52: 303.6 | E52: 0.4 | F52: =E52*D52 -> 121.44 | G52: =F52 -> 121.44 | H52: =F52-G52 -> 0 | I52: 7048401 | J52: 01041090275001 | K52: BANK DHOFAR | L52: BDOFOMRU | Q52: 3201 | R52: =Q52=B52 -> TRUE | S52: Ali Salim Said Qatan | T52: =S52=C52 -> TRUE | U52: 7048401 | V52: =U52=I52 -> TRUE | W52: 01041090275001 | X52: =W52=J52 -> TRUE | Y52: BDOFOMRU | Z52: =Y52=L52 -> TRUE
A53: 50 | B53: 3202 | C53: Salim Ahmed Ali Qatan | D53: 389.8 | E53: 0.4 | F53: =E53*D53 -> 155.92 | G53: =F53 -> 155.92 | H53: =F53-G53 -> 0 | I53: 5197371 | J53: 0132906010084010 | K53: BANK MUSCAT | L53: BMUSOMRX | M53: 93889732 | Q53: 3202 | R53: =Q53=B53 -> TRUE | S53: Salim Ahmed Ali Qatan | T53: =S53=C53 -> TRUE | U53: 5197371 | V53: =U53=I53 -> TRUE | W53: 0132906010084010 | X53: =W53=J53 -> TRUE | Y53: BMUSOMRX | Z53: =Y53=L53 -> TRUE
A54: 51 | B54: 3203 | C54: Musallam Salim Amir Said Qatan | D54: 483.1 | E54: 0.4 | F54: =E54*D54 -> 193.24 | G54: =F54 -> 193.24 | H54: =F54-G54 -> 0 | I54: 23215097 | J54: 0401047625040018 | K54: BANK MUSCAT | L54: BMUSOMRX | N54: 45607 | Q54: 3203 | R54: =Q54=B54 -> TRUE | S54: Musallam Salim Amir Said Qatan | T54: =S54=C54 -> TRUE | U54: 23215097 | V54: =U54=I54 -> TRUE | W54: 0401047625040018 | X54: =W54=J54 -> TRUE | Y54: BMUSOMRX | Z54: =Y54=L54 -> TRUE
A55: 52 | B55: 3204 | C55: Hassan Suhail Ahmed Said Qatan | D55: 484.2 | E55: 0.4 | F55: =E55*D55 -> 193.68 | G55: =F55 -> 193.68 | H55: =F55-G55 -> 0 | I55: 24958926 | J55: 0426060858570018 | K55: BANK MUSCAT | L55: BMUSOMRX | M55: 99312225 | N55: DCF feed | Q55: 3204 | R55: =Q55=B55 -> TRUE | S55: Hassan Suhail Ahmed Said Qatan | T55: =S55=C55 -> TRUE | U55: 24958926 | V55: =U55=I55 -> TRUE | W55: 0426060858570018 | X55: =W55=J55 -> TRUE | Y55: BMUSOMRX | Z55: =Y55=L55 -> TRUE
A56: 53 | B56: 3207 | C56: Said Ali Ahmed Al Katheri | D56: 816.3 | E56: 0.4 | F56: =E56*D56 -> 326.52 | G56: =F56 -> 326.52 | H56: =F56-G56 -> 0 | I56: 11940175 | J56: 0406020751730014 | K56: BANK MUSCAT | L56: BMUSOMRX | M56: 98138748 | Q56: 3207 | R56: =Q56=B56 -> TRUE | S56: Said Ali Ahmed Al Katheri | T56: =S56=C56 -> TRUE | U56: 11940175 | V56: =U56=I56 -> TRUE | W56: 0406020751730014 | X56: =W56=J56 -> TRUE | Y56: BMUSOMRX | Z56: =Y56=L56 -> TRUE
A57: 54 | B57: 3208 | C57: Ali Mahad Said Qatan | D57: 733.6 | E57: 0.4 | F57: =E57*D57 -> 293.44 | G57: =289.88+3.56 -> 293.44 | H57: =F57-G57 -> 0 | I57: 1742664 | J57: 001010070151 | K57: BANK SOHAR | L57: BSHROMRU | M57: 99482598 | N57: 45596 | O57: 45629 | Q57: 3208 | R57: =Q57=B57 -> TRUE | S57: MOHAMMED ALI MAHAD QATAN | T57: =S57=C57 -> FALSE | U57: 20320848 | V57: =U57=I57 -> FALSE | W57: 01011386365003 | X57: =W57=J57 -> FALSE | Y57: BDOFOMRU | Z57: =Y57=L57 -> FALSE
A58: 55 | B58: 3209 | C58: Said Suhail Ali Al Kathiri | D58: 405 | E58: 0.4 | F58: =E58*D58 -> 162 | G58: =161.18+0.82 -> 162 | H58: =F58-G58 -> 0 | I58: 5634328 | J58: 0397016698910016 | K58: BANK MUSCAT | L58: BMUSOMRX | M58: 92283227 | O58: 45607 | P58: 45637 | Q58: 3209 | R58: =Q58=B58 -> TRUE | S58: Said Suhail Ali Al Kathiri | T58: =S58=C58 -> TRUE | U58: 5634328 | V58: =U58=I58 -> TRUE | W58: 0397016698910016 | X58: =W58=J58 -> TRUE | Y58: BMUSOMRX | Z58: =Y58=L58 -> TRUE
A59: 56 | B59: 3210 | C59: Ahmed Said Mubarak Al Zawamri | D59: 757 | E59: 0.4 | F59: =E59*D59 -> 302.8 | G59: =143.75+155.2+3.85 -> 302.8 | H59: =F59-G59 -> 0 | I59: 45419 | J59: 0401002467120013 | K59: BANK MUSCAT | L59: BMUSOMRX | M59: 90101070 | N59: 09/10/2024,15-10-24 | O59: 45602 | Q59: 3210 | R59: =Q59=B59 -> TRUE | S59: Ahmed Said Mubarak Al Zawamri | T59: =S59=C59 -> TRUE | U59: 45419 | V59: =U59=I59 -> TRUE | W59: 0401002467120013 | X59: =W59=J59 -> TRUE | Y59: BMUSOMRX | Z59: =Y59=L59 -> TRUE
A60: 57 | B60: 3211 | C60: Salim Mohammed Musallam Al Baraami | D60: 345 | E60: 0.4 | F60: =E60*D60 -> 138 | G60: =136.7+1.3 -> 138 | H60: =F60-G60 -> 0 | I60: 9927207 | J60: 01010941305001 | K60: BANK DHOFAR | L60: BDOFOMRU | N60: 45574 | O60: 45602 | Q60: 3211 | R60: =Q60=B60 -> TRUE | S60: Salim Mohammed Musallam Al Baraami | T60: =S60=C60 -> TRUE | U60: 9927207 | V60: =U60=I60 -> TRUE | W60: 01010941305001 | X60: =W60=J60 -> TRUE | Y60: BDOFOMRU | Z60: =Y60=L60 -> TRUE
A61: 58 | B61: 3212 | C61: Mohammed Said Mahad Qatan | D61: 1071.3 | E61: 0.4 | F61: =E61*D61 -> 428.52 | G61: =F61 -> 428.52 | H61: =F61-G61 -> 0 | I61: 804443 | J61: 050170299001 | K61: HSBC | L61: BBMEOMRX | M61: 99483202 | Q61: 3212 | R61: =Q61=B61 -> TRUE | S61: Mohammed Said Mahad Qatan | T61: =S61=C61 -> TRUE | U61: 804443 | V61: =U61=I61 -> TRUE | W61: 050170299001 | X61: =W61=J61 -> TRUE | Y61: BBMEOMRX | Z61: =Y61=L61 -> TRUE
A62: 59 | B62: 3213 | C62: Ali Ahmed Suhail Qatan | D62: 912.1 | E62: 0.4 | F62: =E62*D62 -> 364.84 | G62: =F62 -> 364.84 | H62: =F62-G62 -> 0 | I62: 2594336 | J62: 0397004383920015 | K62: BANK MUSCAT | L62: BMUSOMRX | M62: 71773005 | Q62: 3213 | R62: =Q62=B62 -> TRUE | S62: Ali Ahmed Suhail Qatan | T62: =S62=C62 -> TRUE | U62: 2594336 | V62: =U62=I62 -> TRUE | W62: 0397004383920015 | X62: =W62=J62 -> TRUE | Y62: BMUSOMRX | Z62: =Y62=L62 -> TRUE
A63: 60 | B63: 3214 | C63: Salim Musallam Ahmed Tabouk | D63: 1013.2 | E63: 0.4 | F63: =E63*D63 -> 405.28 | G63: =F63 -> 405.28 | H63: =F63-G63 -> 0 | I63: 5168262 | J63: 01041249912001 | K63: BANK DHOFAR | L63: BDOFOMRU | M63: 99895383 | Q63: 3214 | R63: =Q63=B63 -> TRUE | S63: Salim Musallam Ahmed Tabouk | T63: =S63=C63 -> TRUE | U63: 5168262 | V63: =U63=I63 -> TRUE | W63: 01041249912001 | X63: =W63=J63 -> TRUE | Y63: BDOFOMRU | Z63: =Y63=L63 -> TRUE
A64: 61 | B64: 3215 | C64: Suhail Awadh Salim Hawas Al Aamri | D64: 875.6 | E64: 0.4 | F64: =E64*D64 -> 350.24 | G64: =347.35+2.89 -> 350.24 | H64: =F64-G64 -> 0 | I64: 11684091 | J64: 01010853900001 | K64: BANK DHOFAR | L64: BDOFOMRU | N64: 45607 | Q64: 3215 | R64: =Q64=B64 -> TRUE | S64: Suhail Awadh Salim Hawas Al Aamri | T64: =S64=C64 -> TRUE | U64: 11684091 | V64: =U64=I64 -> TRUE | W64: 01010853900001 | X64: =W64=J64 -> TRUE | Y64: BDOFOMRU | Z64: =Y64=L64 -> TRUE
A65: 62 | B65: 3216 | C65: Salim Ali said Al Masahli | D65: 1036.7 | E65: 0.4 | F65: =E65*D65 -> 414.68 | G65: =413.99+0.69 -> 414.68 | H65: =F65-G65 -> 0 | I65: 18715567 | J65: 0406045085100027 | K65: BANK MUSCAT | L65: BMUSOMRX | M65: 77279900 | N65: 45582 | O65: 45602 | Q65: 3216 | R65: =Q65=B65 -> TRUE | S65: Salim Ali said Al Masahli | T65: =S65=C65 -> TRUE | U65: 18715567 | V65: =U65=I65 -> TRUE | W65: 0406045085100027 | X65: =W65=J65 -> TRUE | Y65: BMUSOMRX | Z65: =Y65=L65 -> TRUE
A66: 63 | B66: 3217 | C66: Hassan Musallam Ali Qatan | D66: 371.8 | E66: 0.4 | F66: =E66*D66 -> 148.72 | G66: =F66 -> 148.72 | H66: =F66-G66 -> 0 | I66: 1568196 | J66: 00510059623001 | K66: BANK NIZWA | L66: BNZWOMRX | M66: 99494635 | Q66: 3217 | R66: =Q66=B66 -> TRUE | S66: Hassan Musallam Ali Qatan | T66: =S66=C66 -> TRUE | U66: 1568196 | V66: =U66=I66 -> TRUE | W66: 00510059623001 | X66: =W66=J66 -> TRUE | Y66: BNZWOMRX | Z66: =Y66=L66 -> TRUE
A67: 64 | B67: 3219 | C67: Said Salim Ali Hawas Al Aamri | D67: 1206.2 | E67: 0.4 | F67: =E67*D67 -> 482.48 | G67: =146.17+145.5+189.6+1.21 -> 482.48 | H67: =F67-G67 -> 0 | I67: 12398617 | J67: 0406003141690019 | K67: BANK MUSCAT | L67: BMUSOMRX | N67: 17/10/2024,28-10-24 | O67: 45602 | P67: 45607 | Q67: 3219 | R67: =Q67=B67 -> TRUE | S67: Said Salim Ali Hawas Al Aamri | T67: =S67=C67 -> TRUE | U67: 12398617 | V67: =U67=I67 -> TRUE | W67: 0406003141690019 | X67: =W67=J67 -> TRUE | Y67: BMUSOMRX | Z67: =Y67=L67 -> TRUE
A68: 65 | B68: 3220 | C68: Adnan Mohammed Said Bait Said | D68: 783 | E68: 0.4 | F68: =E68*D68 -> 313.2 | G68: =F68 -> 313.2 | H68: =F68-G68 -> 0 | I68: 5348311 | J68: 01011445808001 | K68: BANK DHOFAR | L68: BDOFOMRU | M68: 96313636 | Q68: 3220 | R68: =Q68=B68 -> TRUE | S68: Adnan Mohammed Said Bait Said | T68: =S68=C68 -> TRUE | U68: 5348311 | V68: =U68=I68 -> TRUE | W68: 01011445808001 | X68: =W68=J68 -> TRUE | Y68: BDOFOMRU | Z68: =Y68=L68 -> TRUE
A69: 66 | B69: 3221 | C69: Musallam Mohammed Salim Al Barami | D69: 378 | E69: 0.4 | F69: =E69*D69 -> 151.2 | G69: =149.89+1.31 -> 151.2 | H69: =F69-G69 -> 0 | I69: 13362673 | J69: 0401003471060021 | K69: BANK MUSCAT | L69: BMUSOMRX | M69: 92665337 | N69: 45630 | O69: 45665 | Q69: 3221 | R69: =Q69=B69 -> TRUE | S69: Musallam Mohammed Salim Al Barami | T69: =S69=C69 -> TRUE | U69: 13362673 | V69: =U69=I69 -> TRUE | W69: 0401003471060021 | X69: =W69=J69 -> TRUE | Y69: BMUSOMRX | Z69: =Y69=L69 -> TRUE
A70: 67 | B70: 3222 | C70: Mohammed Ahmed Bakhit Qatan | D70: 577.5 | E70: 0.4 | F70: =E70*D70 -> 231 | G70: =F70 -> 231 | H70: =F70-G70 -> 0 | I70: 18091329 | J70: 01011448559002 | K70: BANK DHOFAR | L70: BDOFOMRU | M70: 92197820 | N70: 45602 | Q70: 3222 | R70: =Q70=B70 -> TRUE | S70: Mohammed Ahmed Bakhit Qatan | T70: =S70=C70 -> TRUE | U70: 18091329 | V70: =U70=I70 -> TRUE | W70: 01011448559002 | X70: =W70=J70 -> TRUE | Y70: BDOFOMRU | Z70: =Y70=L70 -> TRUE
A71: 68 | B71: 3223 | C71: Salim Said Mustahil Al Kathiri | D71: 367.3 | E71: 0.4 | F71: =E71*D71 -> 146.92 | G71: =F71 -> 146.92 | H71: =F71-G71 -> 0 | I71: 5334914 | J71: 00510087464001 | K71: BANK NIZWA | L71: BNZWOMRX | M71: 98800996 | Q71: 3223 | R71: =Q71=B71 -> TRUE | S71: Salim Said Mustahil Al Kathiri | T71: =S71=C71 -> TRUE | U71: 5334914 | V71: =U71=I71 -> TRUE | W71: 00510087464001 | X71: =W71=J71 -> TRUE | Y71: BNZWOMRX | Z71: =Y71=L71 -> TRUE
A72: 69 | B72: 3224 | C72: Salim Said Salim Qatan | D72: 322.4 | E72: 0.4 | F72: =E72*D72 -> 128.96 | G72: =127.44+1.52 -> 128.96 | H72: =F72-G72 -> 0 | I72: 2066756 | J72: 0439002422440029 | K72: BANK MUSCAT | L72: BMUSOMRX | M72: 95316025 | O72: 45615 | Q72: 3224 | R72: =Q72=B72 -> TRUE | S72: Salim Said Salim Qatan | T72: =S72=C72 -> TRUE | U72: 2066756 | V72: =U72=I72 -> TRUE | W72: 0439002422440029 | X72: =W72=J72 -> TRUE | Y72: BMUSOMRX | Z72: =Y72=L72 -> TRUE
A73: 70 | B73: 3225 | C73: Mohamed Ahmed Salam Alamri | D73: 379.9 | E73: 0.4 | F73: =E73*D73 -> 151.96 | G73: =150.35+1.61 -> 151.96 | H73: =F73-G73 -> 0 | I73: 798637 | J73: 0397004248490019 | K73: BANK MUSCAT | L73: BMUSOMRX | N73: 45615 | O73: 1.61-dcf | Q73: 3225 | R73: =Q73=B73 -> TRUE | S73: Mohamed Ahmed Salam Alamri | T73: =S73=C73 -> TRUE | U73: 798637 | V73: =U73=I73 -> TRUE | W73: 0397004248490019 | X73: =W73=J73 -> TRUE | Y73: BMUSOMRX | Z73: =Y73=L73 -> TRUE
A74: 71 | B74: 3227 | C74: Ahmed Ali Suhail Hawas Al Aamri | D74: 309.9 | E74: 0.4 | F74: =E74*D74 -> 123.96 | G74: =123.09+0.87 -> 123.96 | H74: =F74-G74 -> 0 | I74: 15214649 | J74: 0406003835930033 | K74: BANK MUSCAT | L74: BMUSOMRX | M74: 92171914 | N74: 45567 | O74: 45615
A75: 72 | B75: 3228 | C75: Ali Amer Salim Qatan | D75: 756 | E75: 0.4 | F75: =E75*D75 -> 302.4 | G75: =F75 -> 302.4 | H75: =F75-G75 -> 0 | I75: 1307775 | J75: 01011440583003 | K75: BANK DHOFAR | L75: BDOFOMRU | M75: 99484101 | Q75: 3228 | R75: =Q75=B75 -> TRUE | S75: Ali Amer Salim Qatan | T75: =S75=C75 -> TRUE | U75: 1307775 | V75: =U75=I75 -> TRUE | W75: 01011440583003 | X75: =W75=J75 -> TRUE | Y75: BDOFOMRU | Z75: =Y75=L75 -> TRUE
A76: 73 | B76: 3229 | C76: Musallam Amer Salim Qatan | D76: 578 | E76: 0.4 | F76: =E76*D76 -> 231.2 | G76: =F76 -> 231.2 | H76: =F76-G76 -> 0 | I76: 6370978 | J76: 0401002417310016 | K76: BANK MUSCAT | L76: BMUSOMRX | M76: 99485611 | Q76: 3229 | R76: =Q76=B76 -> TRUE | S76: Musallam Amer Salim Qatan | T76: =S76=C76 -> TRUE | U76: 6370978 | V76: =U76=I76 -> TRUE | W76: 0401002417310016 | X76: =W76=J76 -> TRUE | Y76: BMUSOMRX | Z76: =Y76=L76 -> TRUE
A77: 74 | B77: 3230 | C77: Mohammed Abdullah Ali Ghawas | D77: 517.7 | E77: 0.4 | F77: =E77*D77 -> 207.08 | G77: =F77 -> 207.08 | H77: =F77-G77 -> 0 | I77: 1968755 | J77: 0406003363090017 | K77: BANK MUSCAT | L77: BMUSOMRX | Q77: 3230 | R77: =Q77=B77 -> TRUE | S77: Mohammed Abdullah Ali Ghawas | T77: =S77=C77 -> TRUE | U77: 1968755 | V77: =U77=I77 -> TRUE | W77: 0406003363090017 | X77: =W77=J77 -> TRUE | Y77: BMUSOMRX | Z77: =Y77=L77 -> TRUE
A78: 75 | B78: 3231 | C78: Tanaf Suhail Ali Hawas Al Aamri | D78: 690.3 | E78: 0.4 | F78: =E78*D78 -> 276.12 | G78: =117.43+72.75+85.94 -> 276.12 | H78: =F78-G78 -> 0 | I78: 6203903 | J78: 01010120940001 | K78: BANK DHOFAR | L78: BDOFOMRU | M78: 92535588 | N78: 45602 | O78: 45628 | P78: 45636 | Q78: 3231 | R78: =Q78=B78 -> TRUE | S78: Tanaf Suhail Ali Hawas Al Aamri | T78: =S78=C78 -> TRUE | U78: 6203903 | V78: =U78=I78 -> TRUE | W78: 01010120940001 | X78: =W78=J78 -> TRUE | Y78: BDOFOMRU | Z78: =Y78=L78 -> TRUE
A79: 76 | B79: 3232 | C79: Salim Mohammed Ahmed Al Aamri | D79: 366.2 | E79: 0.4 | F79: =E79*D79 -> 146.48 | G79: =145.5+0.98 -> 146.48 | H79: =F79-G79 -> 0 | I79: 6387264 | J79: 0500012521101001 | K79: Alizz Islamic Bank | L79: IZZBOMRU | M79: 96661076 | N79: 45615 | O79: .98-dcf | Q79: 3232 | R79: =Q79=B79 -> TRUE | S79: Salim Mohammed Ahmed Al Aamri | T79: =S79=C79 -> TRUE | U79: 6387264 | V79: =U79=I79 -> TRUE | W79: 0500012521101001 | X79: =W79=J79 -> TRUE | Y79: IZZBOMRU | Z79: =Y79=L79 -> TRUE
A80: 77 | B80: 3234 | C80: Masoud Salim Ahmed Alash Al Kathiri | D80: 776.6 | E80: 0.4 | F80: =E80*D80 -> 310.64 | G80: =F80 -> 310.64 | H80: =F80-G80 -> 0 | I80: 21834239 | J80: 0406017202280014 | K80: BANK MUSCAT | L80: BMUSOMRX | M80: 98135444 | Q80: 3234 | R80: =Q80=B80 -> TRUE | S80: Masoud Salim Ahmed Alash Al Kathiri | T80: =S80=C80 -> TRUE | U80: 21834239 | V80: =U80=I80 -> TRUE | W80: 0406017202280014 | X80: =W80=J80 -> TRUE | Y80: BMUSOMRX | Z80: =Y80=L80 -> TRUE
A81: 78 | B81: 3235 | C81: Ahmed Mahad Musallam Amor Jid | D81: 766.2 | E81: 0.4 | F81: =E81*D81 -> 306.48 | G81: =306.28+0.2 -> 306.48 | H81: =F81-G81 -> 0 | I81: 1234245 | J81: 10600341164086 | K81: NBO | L81: NBOMOMRX | M81: 99487759 | N81: 45578 | Q81: 3235 | R81: =Q81=B81 -> TRUE | S81: Ahmed Mahad Musallam Amor Jid | T81: =S81=C81 -> TRUE | U81: 1234245 | V81: =U81=I81 -> TRUE | W81: 10600341164086 | X81: =W81=J81 -> TRUE | Y81: NBOMOMRX | Z81: =Y81=L81 -> TRUE
A82: 79 | B82: 3236 | C82: Salim Ali Mohammed Hawas Al Amari | D82: 350.3 | E82: 0.4 | F82: =E82*D82 -> 140.12 | G82: =137.14+2.98 -> 140.12 | H82: =F82-G82 -> 0 | I82: 6733333 | J82: 0397060863170013 | K82: BANK MUSCAT | L82: BMUSOMRX | N82: 45567 | O82: 45602 | Q82: 3236 | R82: =Q82=B82 -> TRUE | S82: Salim Ali Mohammed Hawas Al Amari | T82: =S82=C82 -> TRUE | U82: 6733333 | V82: =U82=I82 -> TRUE | W82: 0397060863170013 | X82: =W82=J82 -> TRUE | Y82: BMUSOMRX | Z82: =Y82=L82 -> TRUE
A83: 80 | B83: 3237 | C83: Suhail Salim Mohammed Al Daakari | D83: 949.1 | E83: 0.4 | F83: =E83*D83 -> 379.64 | G83: =378.98+0.66 -> 379.64 | H83: =F83-G83 -> 0 | I83: 873637 | J83: 3109633774500 | K83: OAB | L83: OMABOMRU | M83: 97659667 | N83: 45580 | O83: 45602 | Q83: 3237 | R83: =Q83=B83 -> TRUE | S83: Suhail Salim Mohammed Al Daakari | T83: =S83=C83 -> TRUE | U83: 873637 | V83: =U83=I83 -> TRUE | W83: 3109633774500 | X83: =W83=J83 -> TRUE | Y83: OMABOMRU | Z83: =Y83=L83 -> TRUE
A84: 81 | B84: 3238 | C84: Mohammed Ali Said Qatan | D84: 49.1 | E84: 0.4 | F84: =E84*D84 -> 19.64 | G84: =F84 -> 19.64 | H84: =F84-G84 -> 0 | I84: 5361082 | J84: 0401011715810012 | K84: BANK MUSCAT | L84: BMUSOMRX | N84: 44621 | Q84: 3238 | R84: =Q84=B84 -> TRUE | S84: Mohammed Ali Said Qatan | T84: =S84=C84 -> TRUE | U84: 5361082 | V84: =U84=I84 -> TRUE | W84: 0401011715810012 | X84: =W84=J84 -> TRUE | Y84: BMUSOMRX | Z84: =Y84=L84 -> TRUE
A85: 82 | B85: 3239 | C85: Ali Salim Bakhit Qatan | D85: 711.7 | E85: 0.4 | F85: =E85*D85 -> 284.68 | G85: =230.88+53.8 -> 284.68 | H85: =F85-G85 -> 0 | I85: 14379226 | J85: 0413009940010018 | K85: BANK MUSCAT | L85: BMUSOMRX | M85: 92385524 | N85: 13--11-24 | O85: 45628 | Q85: 3239 | R85: =Q85=B85 -> TRUE | S85: Ali Salim Bakhit Qatan | T85: =S85=C85 -> TRUE | U85: 14379226 | V85: =U85=I85 -> TRUE | W85: 0413009940010018 | X85: =W85=J85 -> TRUE | Y85: BMUSOMRX | Z85: =Y85=L85 -> TRUE
A86: 83 | B86: 3240 | C86: Ali Said Salim Al kathiri | D86: 751.1 | E86: 0.4 | F86: =E86*D86 -> 300.44 | G86: =F86 -> 300.44 | H86: =F86-G86 -> 0 | I86: 5622856 | J86: 00510029714001 | K86: BANK NIZWA | L86: BNZWOMRX | M86: 92400553 | Q86: 3240 | R86: =Q86=B86 -> TRUE | S86: Ali Said Salim Al kathiri | T86: =S86=C86 -> TRUE | U86: 5622856 | V86: =U86=I86 -> TRUE | W86: 00510029714001 | X86: =W86=J86 -> TRUE | Y86: BNZWOMRX | Z86: =Y86=L86 -> TRUE
A87: 84 | B87: 3241 | C87: Bashar Ahmed Ali Qatan | D87: 398.9 | E87: 0.4 | F87: =E87*D87 -> 159.56 | G87: =F87 -> 159.56 | H87: =F87-G87 -> 0 | I87: 21125518 | J87: 0401040842100016 | K87: BANK MUSCAT | L87: BMUSOMRX | M87: 99508853 | Q87: 3241 | R87: =Q87=B87 -> TRUE | S87: Bashar Ahmed Ali Qatan | T87: =S87=C87 -> TRUE | U87: 21125518 | V87: =U87=I87 -> TRUE | W87: 0401040842100016 | X87: =W87=J87 -> TRUE | Y87: BMUSOMRX | Z87: =Y87=L87 -> TRUE
A88: 85 | B88: 3243 | C88: Asad Ali Ahmed Suhail Aamir Jid | D88: 402.6 | E88: 0.4 | F88: =E88*D88 -> 161.04 | G88: =160.5+0.54 -> 161.04 | H88: =F88-G88 -> 0 | I88: 25887256 | J88: 0406056811780029 | K88: BANK MUSCAT | L88: BMUSOMRX | M88: 93271871 | N88: 45602 | O88: 45615 | Q88: 3243 | R88: =Q88=B88 -> TRUE | S88: Asad Ali Ahmed Suhail Aamir Jid | T88: =S88=C88 -> TRUE | U88: 25887256 | V88: =U88=I88 -> TRUE | W88: 0406056811780029 | X88: =W88=J88 -> TRUE | Y88: BMUSOMRX | Z88: =Y88=L88 -> TRUE
A89: 86 | B89: 3244 | C89: Mohammed Ali Bakhit Qatan | D89: 314.3 | E89: 0.4 | F89: =E89*D89 -> 125.72 | G89: =F89 -> 125.72 | H89: =F89-G89 -> 0 | I89: 19340943 | J89: 0397042697150019 | K89: BANK MUSCAT | L89: BMUSOMRX | M89: 92594446 | Q89: 3244 | R89: =Q89=B89 -> TRUE | S89: Mohammed Ali Bakhit Qatan | T89: =S89=C89 -> TRUE | U89: 19340943 | V89: =U89=I89 -> TRUE | W89: 0397042697150019 | X89: =W89=J89 -> TRUE | Y89: BMUSOMRX | Z89: =Y89=L89 -> TRUE
A90: 87 | B90: 3245 | C90: Musallam Ahmed Mohammed Aldakari Al Kathiri | D90: 321 | E90: 0.4 | F90: =E90*D90 -> 128.4 | G90: =125.57+2.83 -> 128.4 | H90: =F90-G90 -> 0 | I90: 996477 | J90: 3109331947500 | K90: OAB | L90: OMABOMRU | M90: 99699068 | N90: 45567 | O90: 45602 | Q90: 3245 | R90: =Q90=B90 -> TRUE | S90: Musallam Ahmed Mohammed Aldakari Al Kathiri | T90: =S90=C90 -> TRUE | U90: 996477 | V90: =U90=I90 -> TRUE | W90: 3109331947500 | X90: =W90=J90 -> TRUE | Y90: OMABOMRU | Z90: =Y90=L90 -> TRUE
A91: 88 | B91: 3246 | C91: Salim Suhail Said Ghawas | D91: 323 | E91: 0.4 | F91: =E91*D91 -> 129.2 | G91: =126.1+3.1 -> 129.2 | H91: =F91-G91 -> 0 | I91: 662648 | J91: 0397003998840015 | K91: BANK MUSCAT | L91: BMUSOMRX | M91: 99498382 | N91: 19/11/2024 - 24/12/2024 | Q91: 3246 | R91: =Q91=B91 -> TRUE | S91: Salim Suhail Said Ghawas | T91: =S91=C91 -> TRUE | U91: 662648 | V91: =U91=I91 -> TRUE | W91: 0397003998840015 | X91: =W91=J91 -> TRUE | Y91: BMUSOMRX | Z91: =Y91=L91 -> TRUE
A92: 89 | B92: 3247 | C92: Mohammed Suhail Said Ghawas | D92: 349.5 | E92: 0.4 | F92: =E92*D92 -> 139.8 | G92: =135.8 -> 135.8 | H92: =F92-G92-4 -> 0 | I92: 6457783 | J92: 0406003150110017 | K92: BANK MUSCAT | L92: BMUSOMRX | M92: 92594442 | N92: 19/11/2024 - 24-12-2024 | Q92: 3247 | R92: =Q92=B92 -> TRUE | S92: Mohammed Suhail Said Ghawas | T92: =S92=C92 -> TRUE | U92: 6457783 | V92: =U92=I92 -> TRUE | W92: 0406003150110017 | X92: =W92=J92 -> TRUE | Y92: BMUSOMRX | Z92: =Y92=L92 -> TRUE
A93: 90 | B93: 3248 | C93: Ahmed Suhail Said Ghawas | D93: 321.9 | E93: 0.4 | F93: =E93*D93 -> 128.76 | G93: =126.1+2.66 -> 128.76 | H93: =F93-G93 -> 0 | I93: 18811851 | J93: 0406040710420017 | K93: BANK MUSCAT | L93: BMUSOMRX | M93: 92597556 | N93: 45615 | Q93: 3248 | R93: =Q93=B93 -> TRUE | S93: Ahmed Suhail Said Ghawas | T93: =S93=C93 -> TRUE | U93: 18811851 | V93: =U93=I93 -> TRUE | W93: 0406040710420017 | X93: =W93=J93 -> TRUE | Y93: BMUSOMRX | Z93: =Y93=L93 -> TRUE
A94: 91 | B94: 3249 | C94: Amir Musallam Hadi Salim Al Aamri | D94: 700 | E94: 0.4 | F94: =E94*D94 -> 280 | G94: =F94 -> 280 | H94: =F94-G94 -> 0 | I94: 24540784 | J94: 0406025047690017 | K94: BANK MUSCAT | L94: BMUSOMRX | M94: 99693301 | N94: DCF feed | Q94: 3249 | R94: =Q94=B94 -> TRUE | S94: Amir Musallam Hadi Salim Al Aamri | T94: =S94=C94 -> TRUE | U94: 24540784 | V94: =U94=I94 -> TRUE | W94: 0406025047690017 | X94: =W94=J94 -> TRUE | Y94: BMUSOMRX | Z94: =Y94=L94 -> TRUE
A95: 92 | B95: 3251 | C95: Mahad Ahmed Mahad Aamir Jid | D95: 397.6 | E95: 0.4 | F95: =E95*D95 -> 159.04 | G95: =157.24+1.8 -> 159.04 | H95: =F95-G95 -> 0 | I95: 6420681 | J95: 0401002372390013 | K95: BANK MUSCAT | L95: BMUSOMRX | M95: 99588744 | N95: 45578 | O95: 45685 | Q95: 3251 | R95: =Q95=B95 -> TRUE | S95: Mahad Ahmed Mahad Aamir Jid | T95: =S95=C95 -> TRUE | U95: 6420681 | V95: =U95=I95 -> TRUE | W95: 0401002372390013 | X95: =W95=J95 -> TRUE | Y95: BMUSOMRX | Z95: =Y95=L95 -> TRUE
A96: 93 | B96: 3252 | C96: Said Amer Salim Qatan | D96: 239.8 | E96: 0.4 | F96: =E96*D96 -> 95.92 | G96: =92.15+3.77 -> 95.92 | H96: =F96-G96 -> 0 | I96: 460074 | J96: 0397003656070021 | K96: BANK MUSCAT | L96: BMUSOMRX | M96: 99292354 | N96: 45544 | O96: 45621 | Q96: 3252 | R96: =Q96=B96 -> TRUE | S96: Said Amer Salim Qatan | T96: =S96=C96 -> TRUE | U96: 460074 | V96: =U96=I96 -> TRUE | W96: 0397003656070021 | X96: =W96=J96 -> TRUE | Y96: BMUSOMRX | Z96: =Y96=L96 -> TRUE
A97: 94 | B97: 3253 | C97: Abdull Ali Ahmed Suhail Aamir Jid | D97: 747 | E97: 0.4 | F97: =E97*D97 -> 298.8 | G97: =296.54+2.26 -> 298.8 | H97: =F97-G97 -> 0 | I97: 25887589 | J97: 0406061192660017 | K97: BANK MUSCAT | L97: BMUSOMRX | M97: 93995997 | N97: 45567 | O97: 45621 | Q97: 3253 | R97: =Q97=B97 -> TRUE | S97: Abdull Ali Ahmed Suhail Aamir Jid | T97: =S97=C97 -> TRUE | U97: 25887589 | V97: =U97=I97 -> TRUE | W97: 0406061192660017 | X97: =W97=J97 -> TRUE | Y97: BMUSOMRX | Z97: =Y97=L97 -> TRUE
A98: 95 | B98: 3254 | C98: Said Mohammed Musallam Al Shihri | D98: 700.2 | E98: 0.4 | F98: =E98*D98 -> 280.08 | G98: =F98 -> 280.08 | H98: =F98-G98 -> 0 | I98: 6668983 | J98: 0401004242270027 | K98: BANK MUSCAT | L98: BMUSOMRX | M98: 92321002 | N98: 45602 | Q98: 3254 | R98: =Q98=B98 -> TRUE | S98: Said Mohammed Musallam Al Shihri | T98: =S98=C98 -> TRUE | U98: 6668983 | V98: =U98=I98 -> TRUE | W98: 0401004242270027 | X98: =W98=J98 -> TRUE | Y98: BMUSOMRX | Z98: =Y98=L98 -> TRUE
A99: 96 | B99: 3255 | C99: Bakhit Ahmed Musallam Khinan Al Shahri | D99: 555.6 | E99: 0.4 | F99: =E99*D99 -> 222.24 | G99: =222.23+0.01 -> 222.24 | H99: =F99-G99 -> 0 | I99: 5851949 | J99: 1060605003017 | K99: NBO | L99: NBOMOMRX | N99: 45578 | O99: 45602 | Q99: 3255 | R99: =Q99=B99 -> TRUE | S99: Bakhit Ahmed Musallam Khinan Al Shahri | T99: =S99=C99 -> TRUE | U99: 5851949 | V99: =U99=I99 -> TRUE | W99: 1060605003017 | X99: =W99=J99 -> TRUE | Y99: NBOMOMRX | Z99: =Y99=L99 -> TRUE
A100: 97 | B100: 3256 | C100: Salim Said Salim Al Mahri | D100: 2349.2 | E100: 0.4 | F100: =E100*D100 -> 939.68 | G100: =642+297.68 -> 939.68 | H100: =F100-G100 -> 0 | I100: 6147152 | J100: 70401001815001 | K100: SOHAR ISLAMIC BANK | L100: BSHROMRUISL | M100: 99889778 | N100: 45602 | O100: 45609 | Q100: 3256 | R100: =Q100=B100 -> TRUE | S100: Salim Said Salim Al Mahri | T100: =S100=C100 -> TRUE | U100: 6147152 | V100: =U100=I100 -> TRUE | W100: 70401001815001 | X100: =W100=J100 -> TRUE | Y100: BSHROMRUISL | Z100: =Y100=L100 -> TRUE
A101: 98 | B101: 3258 | C101: Ahmed Salim Amer Qatan | D101: 1011 | E101: 0.4 | F101: =E101*D101 -> 404.4 | G101: =F101 -> 404.4 | H101: =F101-G101 -> 0 | I101: 15335306 | J101: 1006708876017 | K101: NBO | L101: NBOMOMRX | M101: 99772646 | N101: DCF feed | Q101: 3258 | R101: =Q101=B101 -> TRUE | S101: Ahmed Salim Amer Qatan | T101: =S101=C101 -> TRUE | U101: 15335306 | V101: =U101=I101 -> TRUE | W101: 1006708876017 | X101: =W101=J101 -> TRUE | Y101: NBOMOMRX | Z101: =Y101=L101 -> TRUE
...

Sheet center-Aug
A1: HAJEEF CAMEL MILK PROCUREMENT FROM 01-Aug-2024 TO 31-Aug-2024
A3: Sr. No. | B3: Farmer Code | C3: Farmer Name | D3: Total Milk Qty | E3: Avg. Rate (OMR/Ltr.) | F3: Amount (OMR) | G3: Paid | H3: Balance | I3: ID No. | J3: remark 2
A4: 1 | B4: 1108 | C4: Bakhit Ahmed Musallam Al kathiri | D4: 1077 | E4: 0.4 | F4: =E4*D4 -> 430.8 | G4: =F4 -> 430.8 | H4: =F4-G4 -> 0 | I4: 15218386
A5: 2 | B5: 1390 | C5: Bakhait Salim Ahmed Alash Al Kathiri | D5: 373.5 | E5: 0.4 | F5: =E5*D5 -> 149.4 | G5: =145.5+3.9 -> 149.4 | H5: =F5-G5 -> 0 | I5: 12181822 | J5: 45609 | K5: 45635
A6: 3 | B6: 1399 | C6: Mohammed Suhail Ali Hawas Al Aamri | D6: 245.8 | E6: 0.4 | F6: =E6*D6 -> 98.32 | G6: =98.2+0.12 -> 98.32 | H6: =F6-G6 -> 0 | I6: 10065546 | J6: 45615 | K6: .120-dcf
A7: 4 | B7: 1422 | C7: Mahammed Musallam Ahmed Hwas | D7: 286.7 | E7: 0.4 | F7: =E7*D7 -> 114.68 | G7: =111.2+3.48 -> 114.68 | H7: =F7-G7 -> 0 | I7: 3280016 | J7: 45602 | K7: 45628
A8: 5 | B8: 1424 | C8: Said Ahmed Sabah Ali Badar | D8: 403.6 | E8: 0.4 | F8: =E8*D8 -> 161.44 | G8: =158.95+2.49 -> 161.44 | H8: =F8-G8 -> 0 | I8: 748395 | J8: 45609 | K8: 45624
A9: 6 | B9: 1429 | C9: Said Mohammed Salem Akdha Al Rawas | D9: 500 | E9: 0.4 | F9: =E9*D9 -> 200 | G9: =F9 -> 200 | H9: =F9-G9 -> 0 | I9: 339725
A10: 7 | B10: 1431 | C10: Bakhit Mohamed Salim Rawas | D10: 347 | E10: 0.4 | F10: =E10*D10 -> 138.8 | G10: =134.09+4.71 -> 138.8 | H10: =F10-G10 -> 0 | I10: 721445 | J10: 45628 | K10: 45642
A11: 8 | B11: 1443 | C11: Ahmed Musallam Ahmed Al Kathiri | D11: 1354.3 | E11: 0.4 | F11: =E11*D11 -> 541.72 | G11: =F11 -> 541.72 | H11: =F11-G11 -> 0 | I11: 6026992
A12: 9 | B12: 1452 | C12: Sulaim Said Mohammed Hawas Al Aamri | D12: 319.4 | E12: 0.4 | F12: =E12*D12 -> 127.76 | G12: =126.95+0.81 -> 127.76 | H12: =F12-G12 -> 0 | I12: 20917176 | J12: 45602 | K12: 45628
A13: 10 | B13: 1458 | C13: Salim Mustahil Jamaan Al Shakl Al kathiri | D13: 348.6 | E13: 0.4 | F13: =E13*D13 -> 139.44 | G13: =F13 -> 139.44 | H13: =F13-G13 -> 0 | I13: 77628
A14: 11 | B14: 1461 | C14: Suhail Said Ali Bait said | D14: 358.1 | E14: 0.4 | F14: =E14*D14 -> 143.24 | G14: =F14 -> 143.24 | H14: =F14-G14 -> 0 | I14: 6828806
A15: 12 | B15: 1465 | C15: Mahad Salim Zaed Baitsaid | D15: 360.8 | E15: 0.4 | F15: =E15*D15 -> 144.32 | G15: =F15 -> 144.32 | H15: =F15-G15 -> 0 | I15: 757601 | J15: DCF FEED
A16: 13 | B16: 1474 | C16: Mohamed Salam Amer Al Yafee | D16: 850.2 | E16: 0.4 | F16: =E16*D16 -> 340.08 | G16: =334.16+5.92 -> 340.08 | H16: =F16-G16 -> 0 | I16: 4603773 | J16: 45658 | K16: 45691
A17: 14 | B17: 1479 | C17: Ahmed Amer Said Baitsaid | D17: 389.5 | E17: 0.4 | F17: =E17*D17 -> 155.8 | G17: =152.07+3.73 -> 155.8 | H17: =F17-G17 -> 0 | I17: 5217726 | J17: 45602 | K17: 45637
A18: 15 | B18: 1483 | C18: Saed Ali Ahmed Al Kathiri | D18: 896.9 | E18: 0.4 | F18: =E18*D18 -> 358.76 | G18: =354.79+3.97 -> 358.76 | H18: =F18-G18 -> 0 | I18: 1567826 | J18: 45607 | K18: 45635
A19: 16 | B19: 1486 | C19: Mosoud Ali Salim Al Kathiri | D19: 387.8 | E19: 0.4 | F19: =E19*D19 -> 155.12 | G19: =F19 -> 155.12 | H19: =F19-G19 -> 0 | I19: 22792564 | J19: 45685
A20: 17 | B20: 1762 | C20: MUSALLAM HASAN ALI BAIT SAID | D20: 1237 | E20: 0.4 | F20: =E20*D20 -> 494.8 | G20: =F20 -> 494.8 | H20: =F20-G20 -> 0 | I20: 1409527 | J20: 22-08-2024 already payment has been transferred and paid again , hence deducted from Aug
A21: 18 | B21: 1792 | C21: Musallam Bakhit Salim Al Aamri | D21: 357.4 | E21: 0.4 | F21: =E21*D21 -> 142.96 | G21: =F21 -> 142.96 | H21: =F21-G21 -> 0 | I21: 9545556 | J21: 45658
A22: 19 | B22: 3009 | C22: Ahmed Salim Bakhit Qatan | D22: 311.8 | E22: 0.4 | F22: =E22*D22 -> 124.72 | G22: =F22 -> 124.72 | H22: =F22-G22 -> 0 | I22: 1448391
A23: 20 | B23: 3012 | C23: Salim Suhail Ali Al Kathiri | D23: 350 | E23: 0.4 | F23: =E23*D23 -> 140 | G23: =134.57+5.43 -> 140 | H23: =F23-G23 -> 0 | I23: 5634422 | J23: 45624 | K23: 45637
A24: 21 | B24: 3014 | C24: Ahmed Mohammed Salim Al Barami | D24: 307.3 | E24: 0.4 | F24: =E24*D24 -> 122.92 | G24: =118.81+4.11 -> 122.92 | H24: =F24-G24 -> 0 | I24: 648421 | J24: 45602 | K24: 45624
A25: 22 | B25: 3015 | C25: Ahmed Mohammed Faraj Al Kathiri | D25: 353.4 | E25: 0.4 | F25: =E25*D25 -> 141.36 | G25: =F25 -> 141.36 | H25: =F25-G25 -> 0 | I25: 5753033 | J25: 45779
A26: 23 | B26: 3018 | C26: Bakhit Salim Bakhit Qatan | D26: 256.9 | E26: 0.4 | F26: =E26*D26 -> 102.76 | G26: =100.85+1.91 -> 102.76 | H26: =F26-G26 -> 0 | I26: 1528087 | J26: 45602 | K26: 45629
A27: 24 | B27: 3020 | C27: Bakhit Ali Salim Qatan | D27: 298.1 | E27: 0.4 | F27: =E27*D27 -> 119.24 | G27: =115.53+3.71 -> 119.24 | H27: =F27-G27 -> 0 | I27: 5418422 | J27: 45602 | K27: 45624
A28: 25 | B28: 3022 | C28: Hussein Masoud Aubad Al Kathiri | D28: 907.2 | E28: 0.4 | F28: =E28*D28 -> 362.88 | G28: =358.04+4.84 -> 362.88 | H28: =F28-G28 -> 0 | I28: 5360253 | J28: 45637 | K28: 45656
A29: 26 | B29: 3025 | C29: Musallam Salim Mahad Qatan | D29: 661.1 | E29: 0.4 | F29: =E29*D29 -> 264.44 | G29: =F29 -> 264.44 | H29: =F29-G29 -> 0 | I29: 7542172
A30: 27 | B30: 3026 | C30: Amer Salem Ahmed Qatan | D30: 336 | E30: 0.4 | F30: =E30*D30 -> 134.4 | G30: =F30 -> 134.4 | H30: =F30-G30 -> 0 | I30: 7033819
A31: 28 | B31: 3027 | C31: Salim Ahmed Mahad Aamir Jid | D31: 703.4 | E31: 0.4 | F31: =E31*D31 -> 281.36 | G31: =F31 -> 281.36 | H31: =F31-G31 -> 0 | I31: 6420643 | J31: 45685
A32: 29 | B32: 3030 | C32: Salim Ahmed Salim Amer Jid | D32: 375 | E32: 0.4 | F32: =E32*D32 -> 150 | G32: =F32 -> 150 | H32: =F32-G32 -> 0 | I32: 6021175 | J32: 45650
A33: 30 | B33: 3038 | C33: Said Ahmed Mahad Qatan | D33: 714.2 | E33: 0.4 | F33: =E33*D33 -> 285.68 | G33: =282.6+3.08 -> 285.68 | H33: =F33-G33 -> 0 | I33: 7976 | J33: 45621 | K33: 45637
A34: 31 | B34: 3043 | C34: Said Aubad Ali Ghawas | D34: 321.8 | E34: 0.4 | F34: =E34*D34 -> 128.72 | G34: =125.76+2.96 -> 128.72 | H34: =F34-G34 -> 0 | I34: 396336 | J34: 45642 | K34: 45656
A35: 32 | B35: 3058 | C35: Ali Bakhit Ahmed Qatan | D35: 1071.7 | E35: 0.4 | F35: =E35*D35 -> 428.68 | G35: =F35 -> 428.68 | H35: =F35-G35 -> 0 | I35: 965148
A36: 33 | B36: 3070 | C36: Mohamed Ahmed Suhail Qatan | D36: 1116.5 | E36: 0.4 | F36: =E36*D36 -> 446.6 | G36: =F36 -> 446.6 | H36: =F36-G36 -> 0 | I36: 1918001 | J36: 45627
A37: 34 | B37: 3072 | C37: Mohammed Salim Said Al Barami | D37: 350 | E37: 0.4 | F37: =E37*D37 -> 140 | G37: =138.3+1.7 -> 140 | H37: =F37-G37 -> 0 | I37: 993077 | J37: 45665 | K37: 45779
A38: 35 | B38: 3077 | C38: Mohammed Ali Suhail Qatan | D38: 640 | E38: 0.4 | F38: =E38*D38 -> 256 | G38: =F38 -> 256 | H38: =F38-G38 -> 0 | I38: 21978752 | J38: 45635
A39: 36 | B39: 3081 | C39: Musallam Bakhit Masoud Qatan | D39: 478.2 | E39: 0.4 | F39: =E39*D39 -> 191.28 | G39: =96.55+94.73 -> 191.28 | H39: =F39-G39 -> 0 | I39: 21219868 | J39: 45635 | K39: 94.730-DFI
A40: 37 | B40: 3089 | C40: Yhaya Musallam Said Qatan | D40: 336.4 | E40: 0.4 | F40: =E40*D40 -> 134.56 | G40: =F40 -> 134.56 | H40: =F40-G40 -> 0 | I40: 18790484 | J40: 45656
A41: 38 | B41: 3093 | C41: Bakhit Amer Salem Qatan | D41: 518.1 | E41: 0.4 | F41: =E41*D41 -> 207.24 | G41: =F41 -> 207.24 | H41: =F41-G41 -> 0 | I41: 6361035
A42: 39 | B42: 3094 | C42: Ali Ahmed Aubad Jamaan Al Kathiri | D42: 1043.4 | E42: 0.4 | F42: =E42*D42 -> 417.36 | G42: =312+105.36 -> 417.36 | H42: =F42-G42 -> 0 | I42: 26343985 | J42: 45691
A43: 40 | B43: 3100 | C43: Salim Ahmed Said Tabuk | D43: 1460 | E43: 0.4 | F43: =E43*D43 -> 584 | G43: =F43 -> 584 | H43: =F43-G43 -> 0 | I43: 1278615
A44: 41 | B44: 3101 | C44: Salim Said Suhail Qatan | D44: 360.4 | E44: 0.4 | F44: =E44*D44 -> 144.16 | G44: =F44 -> 144.16 | H44: =F44-G44 -> 0 | I44: 6767598
A45: 42 | B45: 3102 | C45: Mohammed Salim Amer Qatan | D45: 685.7 | E45: 0.4 | F45: =E45*D45 -> 274.28 | G45: =272.28+2 -> 274.28 | H45: =F45-G45 -> 0 | I45: 5916838 | J45: 45602 | K45: 45629
A46: 43 | B46: 3119 | C46: Mohammed Ahmed Suhail Mahad Qatan | D46: 765.5 | E46: 0.4 | F46: =E46*D46 -> 306.2 | G46: =304.12+2.08 -> 306.2 | H46: =F46-G46 -> 0 | I46: 5903061 | J46: 45602 | K46: 45629
A47: 44 | B47: 3122 | C47: Khalid Ahmed Salim Amer Jid Al Mahri | D47: 375 | E47: 0.4 | F47: =E47*D47 -> 150 | G47: =147.75+2.25 -> 150 | H47: =F47-G47 -> 0 | I47: 12415718 | J47: 45615 | K47: 45644
A48: 45 | B48: 3136 | C48: Ghazi Salim Ahmed Al Kathiri | D48: 676.2 | E48: 0.4 | F48: =E48*D48 -> 270.48 | G48: =F48 -> 270.48 | H48: =F48-G48 -> 0 | I48: 183498 | J48: 45624
A49: 46 | B49: 3178 | C49: Abdul Sallam Ahmed Abdullah Al Abbadi Al Rawas | D49: 2264.9 | E49: 0.4 | F49: =E49*D49 -> 905.96 | G49: =F49 -> 905.96 | H49: =F49-G49 -> 0 | I49: 1511754
A50: 47 | B50: 3199 | C50: Ali Musallam Ahmed Tabuk | D50: 342.5 | E50: 0.4 | F50: =E50*D50 -> 137 | G50: =F50 -> 137 | H50: =F50-G50 -> 0 | I50: 5168327 | J50: 45637
A51: 48 | B51: 3200 | C51: Ahmed Said Ahmed Qutan | D51: 289.9 | E51: 0.4 | F51: =E51*D51 -> 115.96 | G51: =111.75+4.21 -> 115.96 | H51: =F51-G51 -> 0 | I51: 21947578 | J51: 45656 | K51: 45677
A52: 49 | B52: 3201 | C52: Ali Salim Said Qatan | D52: 290.6 | E52: 0.4 | F52: =E52*D52 -> 116.24 | G52: =F52 -> 116.24 | H52: =F52-G52 -> 0 | I52: 7048401
A53: 50 | B53: 3202 | C53: Salim Ahmed Ali Qatan | D53: 350.5 | E53: 0.4 | F53: =E53*D53 -> 140.2 | G53: =F53 -> 140.2 | H53: =F53-G53 -> 0 | I53: 5197371 | J53: 45691
A54: 51 | B54: 3203 | C54: Musallam Salim Amir Said Qatan | D54: 436.8 | E54: 0.4 | F54: =E54*D54 -> 174.72 | G54: =170.56+4.16 -> 174.72 | H54: =F54-G54 -> 0 | I54: 23215097 | J54: 45607 | K54: 45629
A55: 52 | B55: 3204 | C55: Hassan Suhail Ahmed Said Qatan | D55: 454.2 | E55: 0.4 | F55: =E55*D55 -> 181.68 | G55: =F55 -> 181.68 | H55: =F55-G55 -> 0 | I55: 24958926 | J55: DCF FEED
A56: 53 | B56: 3207 | C56: Said Ali Ahmed Al Katheri | D56: 787.3 | E56: 0.4 | F56: =E56*D56 -> 314.92 | G56: =F56 -> 314.92 | H56: =F56-G56 -> 0 | I56: 11940175
A57: 54 | B57: 3208 | C57: Ali Mahad Said Qatan | D57: 608.3 | E57: 0.4 | F57: =E57*D57 -> 243.32 | G57: =132.24+111.08 -> 243.32 | H57: =F57-G57 -> 0 | I57: 1742664 | J57: 45629 | K57: 45658
A58: 55 | B58: 3209 | C58: Said Suhail Ali Al Kathiri | D58: 375 | E58: 0.4 | F58: =E58*D58 -> 150 | G58: =F58 -> 150 | H58: =F58-G58 -> 0 | I58: 5634328 | J58: 45624
A59: 56 | B59: 3210 | C59: Ahmed Said Mubarak Al Zawamri | D59: 640.4 | E59: 0.4 | F59: =E59*D59 -> 256.16 | G59: =253.2+2.96 -> 256.16 | H59: =F59-G59 -> 0 | I59: 45419 | J59: 45602 | K59: 45629
A60: 57 | B60: 3211 | C60: Salim Mohammed Musallam Al Baraami | D60: 330 | E60: 0.4 | F60: =E60*D60 -> 132 | G60: =129.65+2.35 -> 132 | H60: =F60-G60 -> 0 | I60: 9927207 | J60: 45602 | K60: 45629
A61: 58 | B61: 3212 | C61: Mohammed Said Mahad Qatan | D61: 977.7 | E61: 0.4 | F61: =E61*D61 -> 391.08 | G61: =F61 -> 391.08 | H61: =F61-G61 -> 0 | I61: 804443 | J61: 45648
A62: 59 | B62: 3213 | C62: Ali Ahmed Suhail Qatan | D62: 853.3 | E62: 0.4 | F62: =E62*D62 -> 341.32 | G62: =F62 -> 341.32 | H62: =F62-G62 -> 0 | I62: 2594336
A63: 60 | B63: 3214 | C63: Salim Musallam Ahmed Tabouk | D63: 938.3 | E63: 0.4 | F63: =E63*D63 -> 375.32 | G63: =373.45+1.87 -> 375.32 | H63: =F63-G63 -> 0 | I63: 5168262 | J63: 45658 | K63: 45691
A64: 61 | B64: 3215 | C64: Suhail Awadh Salim Hawas Al Aamri | D64: 742 | E64: 0.4 | F64: =E64*D64 -> 296.8 | G64: =195.96+97+3.84 -> 296.8 | H64: =F64-G64 -> 0 | I64: 11684091 | J64: 45635 | K64: 45637 | L64: 45644
A65: 62 | B65: 3216 | C65: Salim Ali said Al Masahli | D65: 889.1 | E65: 0.4 | F65: =E65*D65 -> 355.64 | G65: =353.36+2.28 -> 355.64 | H65: =F65-G65 -> 0 | I65: 18715567 | J65: 45602 | K65: 45637
A66: 63 | B66: 3217 | C66: Hassan Musallam Ali Qatan | D66: 311.9 | E66: 0.4 | F66: =E66*D66 -> 124.76 | G66: =F66 -> 124.76 | H66: =F66-G66 -> 0 | I66: 1568196
A67: 64 | B67: 3219 | C67: Said Salim Ali Hawas Al Aamri | D67: 1078.2 | E67: 0.4 | F67: =E67*D67 -> 431.28 | G67: =144.29+286.15+0.84 -> 431.28 | H67: =F67-G67 -> 0 | I67: 12398617 | J67: 45607 | K67: 45615 | L67: 45624
A68: 65 | B68: 3220 | C68: Adnan Mohammed Said Bait Said | D68: 696 | E68: 0.4 | F68: =E68*D68 -> 278.4 | G68: =F68 -> 278.4 | H68: =F68-G68 -> 0 | I68: 5348311
A69: 66 | B69: 3221 | C69: Musallam Mohammed Salim Al Barami | D69: 336 | E69: 0.4 | F69: =E69*D69 -> 134.4 | G69: =F69 -> 134.4 | H69: =F69-G69 -> 0 | I69: 13362673 | J69: 058-01-25
A70: 67 | B70: 3222 | C70: Mohammed Ahmed Bakhit Qatan | D70: 531 | E70: 0.4 | F70: =E70*D70 -> 212.4 | G70: =211.18+1.22 -> 212.4 | H70: =F70-G70 -> 0 | I70: 18091329 | J70: 45602 | K70: 45630
A71: 68 | B71: 3223 | C71: Salim Said Mustahil Al Kathiri | D71: 336 | E71: 0.4 | F71: =E71*D71 -> 134.4 | G71: =F71 -> 134.4 | H71: =F71-G71 -> 0 | I71: 5334914 | N71: =732.95-F61 -> 341.87
A72: 69 | B72: 3224 | C72: Salim Said Salim Qatan | D72: 300 | E72: 0.4 | F72: =E72*D72 -> 120 | G72: =117.83+2.17 -> 120 | H72: =F72-G72 -> 0 | I72: 2066756 | J72: 45615 | K72: 45635
A73: 70 | B73: 3225 | C73: Mohamed Ahmed Salam Alamri | D73: 350.6 | E73: 0.4 | F73: =E73*D73 -> 140.24 | G73: =F73 -> 140.24 | H73: =F73-G73 -> 0 | I73: 798637 | J73: DCF FEED
A74: 71 | B74: 3227 | C74: Ahmed Ali Suhail Hawas Al Aamri | D74: 246 | E74: 0.4 | F74: =E74*D74 -> 98.4 | G74: =96.13+2.27 -> 98.4 | H74: =F74-G74 -> 0 | I74: 15214649 | J74: 45615 | K74: 45630
A75: 72 | B75: 3228 | C75: Ali Amer Salim Qatan | D75: 683 | E75: 0.4 | F75: =E75*D75 -> 273.2 | G75: =F75 -> 273.2 | H75: =F75-G75 -> 0 | I75: 1307775
A76: 73 | B76: 3229 | C76: Musallam Amer Salim Qatan | D76: 546 | E76: 0.4 | F76: =E76*D76 -> 218.4 | G76: =F76 -> 218.4 | H76: =F76-G76 -> 0 | I76: 6370978
A77: 74 | B77: 3230 | C77: Mohammed Abdullah Ali Ghawas | D77: 518.2 | E77: 0.4 | F77: =E77*D77 -> 207.28 | G77: =F77 -> 207.28 | H77: =F77-G77 -> 0 | I77: 1968755
A78: 75 | B78: 3231 | C78: Tanaf Suhail Ali Hawas Al Aamri | D78: 610 | E78: 0.4 | F78: =E78*D78 -> 244 | G78: =59.56+97+87.3+0.14 -> 244 | H78: =F78-G78 -> 0 | I78: 6203903 | J78: 45636 | K78: 45644 | L78: 45658 | M78: 45663
A79: 76 | B79: 3232 | C79: Salim Mohammed Ahmed Al Aamri | D79: 347.8 | E79: 0.4 | F79: =E79*D79 -> 139.12 | G79: =F79 -> 139.12 | H79: =F79-G79 -> 0 | I79: 6387264 | J79: DCF FEED
A80: 77 | B80: 3234 | C80: Masoud Salim Ahmed Alash Al Kathiri | D80: 630.3 | E80: 0.4 | F80: =E80*D80 -> 252.12 | G80: =F80 -> 252.12 | H80: =F80-G80 -> 0 | I80: 21834239
A81: 78 | B81: 3235 | C81: Ahmed Mahad Musallam Amor Jid | D81: 711.5 | E81: 0.4 | F81: =E81*D81 -> 284.6 | G81: =F81 -> 284.6 | H81: =F81-G81 -> 0 | I81: 1234245
A82: 79 | B82: 3236 | C82: Salim Ali Mohammed Hawas Al Amari | D82: 158.1 | E82: 0.4 | F82: =E82*D82 -> 63.24 | G82: =59.77+3.47 -> 63.24 | H82: =F82-G82 -> 0 | I82: 6733333 | J82: 45602 | K82: 45630
A83: 80 | B83: 3237 | C83: Suhail Salim Mohammed Al Daakari | D83: 823.8 | E83: 0.4 | F83: =E83*D83 -> 329.52 | G83: =329.14+0.38 -> 329.52 | H83: =F83-G83 -> 0 | I83: 873637 | J83: 45602 | K83: 45623
A84: 82 | B84: 3239 | C84: Ali Salim Bakhit Qatan | D84: 648.5 | E84: 0.4 | F84: =E84*D84 -> 259.4 | G84: =256.6+2.8 -> 259.4 | H84: =F84-G84 -> 0 | I84: 14379226 | J84: 45629 | K84: 45642
A85: 83 | B85: 3240 | C85: Ali Said Salim Al kathiri | D85: 661.7 | E85: 0.4 | F85: =E85*D85 -> 264.68 | G85: =F85 -> 264.68 | H85: =F85-G85 -> 0 | I85: 5622856 | J85: 45642
A86: 84 | B86: 3241 | C86: Bashar Ahmed Ali Qatan | D86: 369.7 | E86: 0.4 | F86: =E86*D86 -> 147.88 | G86: =F86 -> 147.88 | H86: =F86-G86 -> 0 | I86: 21125518 | J86: 45691
A87: 85 | B87: 3243 | C87: Asad Ali Ahmed Suhail Aamir Jid | D87: 344.5 | E87: 0.4 | F87: =E87*D87 -> 137.8 | G87: =136.1+1.7 -> 137.8 | H87: =F87-G87 -> 0 | I87: 25887256 | J87: 45615 | K87: 45629
A88: 86 | B88: 3244 | C88: Mohammed Ali Bakhit Qatan | D88: 89.7 | E88: 0.4 | F88: =E88*D88 -> 35.88 | G88: =F88 -> 35.88 | H88: =F88-G88 -> 0 | I88: 19340943
A89: 87 | B89: 3245 | C89: Musallam Ahmed Mohammed Aldakari Al Kathiri | D89: 287.8 | E89: 0.4 | F89: =E89*D89 -> 115.12 | G89: =113.57+1.55 -> 115.12 | H89: =F89-G89 -> 0 | I89: 996477 | J89: 45602 | K89: 45630
A90: 88 | B90: 3246 | C90: Salim Suhail Said Ghawas | D90: 299.2 | E90: 0.4 | F90: =E90*D90 -> 119.68 | G90: =119.68 -> 119.68 | H90: =F90-G90 -> 0 | I90: 662648 | J90: 45650
A91: 89 | B91: 3247 | C91: Mohammed Suhail Said Ghawas | D91: 322.2 | E91: 0.4 | F91: =E91*D91 -> 128.88 | G91: =F91 -> 128.88 | H91: =F91-G91 -> 0 | I91: 6457783 | J91: 45650
A92: 90 | B92: 3248 | C92: Ahmed Suhail Said Ghawas | D92: 299.5 | E92: 0.4 | F92: =E92*D92 -> 119.8 | G92: =F92 -> 119.8 | H92: =F92-G92 -> 0 | I92: 18811851
A93: 91 | B93: 3249 | C93: Amir Musallam Hadi Salim Al Aamri | D93: 644 | E93: 0.4 | F93: =E93*D93 -> 257.6 | G93: =F93 -> 257.6 | H93: =F93-G93 -> 0 | I93: 24540784 | J93: DCF FEED
A94: 92 | B94: 3251 | C94: Mahad Ahmed Mahad Aamir Jid | D94: 371.2 | E94: 0.4 | F94: =E94*D94 -> 148.48 | G94: =F94 -> 148.48 | H94: =F94-G94 -> 0 | I94: 6420681 | J94: 45685
A95: 93 | B95: 3252 | C95: Said Amer Salim Qatan | D95: 26.9 | E95: 0.4 | F95: =E95*D95 -> 10.76 | G95: =10.22+0.54 -> 10.76 | H95: =F95-G95 -> 0 | I95: 460074 | J95: 45621 | K95: BT 02-02-2025
A96: 94 | B96: 3253 | C96: Abdull Ali Ahmed Suhail Aamir Jid | D96: 660.4 | E96: 0.4 | F96: =E96*D96 -> 264.16 | G96: =259.89+4.27 -> 264.16 | H96: =F96-G96 -> 0 | I96: 25887589 | J96: 45621 | K96: 45629
A97: 95 | B97: 3254 | C97: Said Mohammed Musallam Al Shihri | D97: 644.5 | E97: 0.4 | F97: =E97*D97 -> 257.8 | G97: =253.09+4.71 -> 257.8 | H97: =F97-G97 -> 0 | I97: 6668983 | J97: 45602 | K97: 45623
A98: 96 | B98: 3255 | C98: Bakhit Ahmed Musallam Khinan Al Shahri | D98: 441.8 | E98: 0.4 | F98: =E98*D98 -> 176.72 | G98: =174.59+2.13 -> 176.72 | H98: =F98-G98 -> 0 | I98: 5851949 | J98: 45602 | K98: 45635
A99: 97 | B99: 3256 | C99: Salim Said Salim Al Mahri | D99: 2342.2 | E99: 0.4 | F99: =E99*D99 -> 936.88 | G99: =237.32+294.5+405.06 -> 936.88 | H99: =F99-G99 -> 0 | I99: 6147152 | J99: 45609 | K99: 45615 | L99: 405.060-dcf
A100: 98 | B100: 3258 | C100: Ahmed Salim Amer Qatan | D100: 878.5 | E100: 0.4 | F100: =E100*D100 -> 351.4 | G100: =F100 -> 351.4 | H100: =F100-G100 -> 0 | I100: 15335306 | J100: DCF FEED
A101: 99 | B101: 3260 | C101: Ali Musalam Said Salim Qatan | D101: 312.6 | E101: 0.4 | F101: =E101*D101 -> 125.04 | G101: =F101 -> 125.04 | H101: =F101-G101 -> 0 | I101: 19361936 | J101: 45685
...

Sheet Center-Sept
A1: HAJEEF CAMEL MILK PROCUREMENT FROM 01-Sept-2024 TO 30-Sept-2024
A3: Sr. No. | B3: Farmer Code | C3: Farmer Name | D3: Total Milk Qty | E3: Avg. Rate (OMR/Ltr.) | F3: Amount (OMR) | G3: Paid | H3: Balance | I3: ID No. | J3: remark 2
A4: 1 | B4: 1108 | C4: Bakhit Ahmed Musallam Al kathiri | D4: 912.4 | E4: 0.4 | F4: =E4*D4 -> 364.96 | H4: =F4-G4 -> 364.96 | I4: 15218386
A5: 2 | B5: 1390 | C5: Bakhait Salim Ahmed Alash Al Kathiri | D5: 328.2 | E5: 0.4 | F5: =E5*D5 -> 131.28 | G5: =129.85+1.43 -> 131.28 | H5: =F5-G5 -> 0 | I5: 12181822 | J5: 45635 | K5: 45658
A6: 3 | B6: 1399 | C6: Mohammed Suhail Ali Hawas Al Aamri | D6: 241.6 | E6: 0.4 | F6: =E6*D6 -> 96.64 | G6: =F6 -> 96.64 | H6: =F6-G6 -> 0 | I6: 10065546 | J6: dcf feed
A7: 4 | B7: 1422 | C7: Mahammed Musallam Ahmed Hwas | D7: 263.5 | E7: 0.4 | F7: =E7*D7 -> 105.4 | G7: =103.22+2.18 -> 105.4 | H7: =F7-G7 -> 0 | I7: 3280016 | J7: 45628 | K7: 45658
A8: 5 | B8: 1424 | C8: Said Ahmed Sabah Ali Badar | D8: 371.9 | E8: 0.4 | F8: =E8*D8 -> 148.76 | G8: =147.86+0.9 -> 148.76 | H8: =F8-G8 -> 0 | I8: 748395 | J8: 45624 | K8: 45644
A9: 6 | B9: 1429 | C9: Said Mohammed Salem Akdha Al Rawas | D9: 440 | E9: 0.4 | F9: =E9*D9 -> 176 | G9: =174.6+1.4 -> 176 | H9: =F9-G9 -> 0 | I9: 339725 | J9: 45932 | K9: 13-2-25
A10: 7 | B10: 1431 | C10: Bakhit Mohamed Salim Rawas | D10: 329.4 | E10: 0.4 | F10: =E10*D10 -> 131.76 | G10: =131.09+0.67 -> 131.76 | H10: =F10-G10 -> 0 | I10: 721445 | J10: 45642 | K10: 45658
A11: 8 | B11: 1443 | C11: Ahmed Musallam Ahmed Al Kathiri | D11: 1188.9 | E11: 0.4 | F11: =E11*D11 -> 475.56 | H11: =F11-G11 -> 475.56 | I11: 6026992
A12: 9 | B12: 1452 | C12: Sulaim Said Mohammed Hawas Al Aamri | D12: 309.4 | E12: 0.4 | F12: =E12*D12 -> 123.76 | G12: =120.44+3.32 -> 123.76 | H12: =F12-G12 -> 0 | I12: 20917176 | J12: 45628 | K12: 45658
A13: 10 | B13: 1458 | C13: Salim Mustahil Jamaan Al Shakl Al kathiri | D13: 308.8 | E13: 0.4 | F13: =E13*D13 -> 123.52 | H13: =F13-G13 -> 123.52 | I13: 77628
A14: 11 | B14: 1461 | C14: Suhail Said Ali Bait said | D14: 303.9 | E14: 0.4 | F14: =E14*D14 -> 121.56 | H14: =F14-G14 -> 121.56 | I14: 6828806
A15: 12 | B15: 1465 | C15: Mahad Salim Zaed Baitsaid | D15: 315.1 | E15: 0.4 | F15: =E15*D15 -> 126.04 | G15: =F15 -> 126.04 | H15: =F15-G15 -> 0 | I15: 757601 | J15: dcf feed
A16: 13 | B16: 1474 | C16: Mohamed Salam Amer Al Yafee | D16: 706.6 | E16: 0.4 | F16: =E16*D16 -> 282.64 | G16: =280.23 -> 280.23 | H16: =F16-G16 -> 2.41 | I16: 4603773 | J16: 45691
A17: 14 | B17: 1479 | C17: Ahmed Amer Said Baitsaid | D17: 335.4 | E17: 0.4 | F17: =E17*D17 -> 134.16 | G17: =F17 -> 134.16 | H17: =F17-G17 -> 0 | I17: 5217726 | J17: 45637
A18: 15 | B18: 1483 | C18: Saed Ali Ahmed Al Kathiri | D18: 733.6 | E18: 0.4 | F18: =E18*D18 -> 293.44 | G18: =290.98+2.46 -> 293.44 | H18: =F18-G18 -> 0 | I18: 1567826 | J18: 45635 | K18: 45658
A19: 16 | B19: 1486 | C19: Mosoud Ali Salim Al Kathiri | D19: 351.5 | E19: 0.4 | F19: =E19*D19 -> 140.6 | G19: =F19 -> 140.6 | H19: =F19-G19 -> 0 | I19: 22792564 | J19: 45685
A20: 17 | B20: 1762 | C20: MUSALLAM HASAN ALI BAIT SAID | D20: 1093 | E20: 0.4 | F20: =E20*D20 -> 437.2 | G20: =132.96+304.24 -> 437.2 | H20: =F20-G20 -> 0 | I20: 1409527 | J20: 45526 | K20: 22-08-2024 already payment has been transferred and paid again , hence deducted from Aug | L20: 304.24-dcf
A21: 18 | B21: 1792 | C21: Musallam Bakhit Salim Al Aamri | D21: 316.9 | E21: 0.4 | F21: =E21*D21 -> 126.76 | G21: =F21 -> 126.76 | H21: =F21-G21 -> 0 | I21: 9545556 | J21: 45658
A22: 19 | B22: 3009 | C22: Ahmed Salim Bakhit Qatan | D22: 286.6 | E22: 0.4 | F22: =E22*D22 -> 114.64 | H22: =F22-G22 -> 114.64 | I22: 1448391
A23: 20 | B23: 3012 | C23: Salim Suhail Ali Al Kathiri | D23: 308 | E23: 0.4 | F23: =E23*D23 -> 123.2 | G23: =119.57+3.63 -> 123.2 | H23: =F23-G23 -> 0 | I23: 5634422 | J23: 45637 | K23: 45658
A24: 21 | B24: 3014 | C24: Ahmed Mohammed Salim Al Barami | D24: 260.6 | E24: 0.4 | F24: =E24*D24 -> 104.24 | G24: =102.59+1.65 -> 104.24 | H24: =F24-G24 -> 0 | I24: 648421 | J24: 45624 | K24: 45658
A25: 22 | B25: 3015 | C25: Ahmed Mohammed Faraj Al Kathiri | D25: 296.3 | E25: 0.4 | F25: =E25*D25 -> 118.52 | G25: =F25 -> 118.52 | H25: =F25-G25 -> 0 | I25: 5753033 | J25: 45779
A26: 23 | B26: 3018 | C26: Bakhit Salim Bakhit Qatan | D26: 209.4 | E26: 0.4 | F26: =E26*D26 -> 83.76 | G26: =80.54+3.22 -> 83.76 | H26: =F26-G26 -> 0 | I26: 1528087 | J26: 45629 | K26: 45658
A27: 24 | B27: 3020 | C27: Bakhit Ali Salim Qatan | D27: 391.8 | E27: 0.4 | F27: =E27*D27 -> 156.72 | G27: =156.34+0.38 -> 156.72 | H27: =F27-G27 -> 0 | I27: 5418422 | J27: 45624 | K27: 45650
A28: 25 | B28: 3022 | C28: Hussein Masoud Aubad Al Kathiri | D28: 865.8 | E28: 0.4 | F28: =E28*D28 -> 346.32 | G28: =344.36+1.96 -> 346.32 | H28: =F28-G28 -> 0 | I28: 5360253 | J28: 45656 | K28: 45670
A29: 26 | B29: 3025 | C29: Musallam Salim Mahad Qatan | D29: 587.6 | E29: 0.4 | F29: =E29*D29 -> 235.04 | H29: =F29-G29 -> 235.04 | I29: 7542172
A30: 27 | B30: 3026 | C30: Amer Salem Ahmed Qatan | D30: 308 | E30: 0.4 | F30: =E30*D30 -> 123.2 | H30: =F30-G30 -> 123.2 | I30: 7033819
A31: 28 | B31: 3027 | C31: Salim Ahmed Mahad Aamir Jid | D31: 638 | E31: 0.4 | F31: =E31*D31 -> 255.2 | G31: =F31 -> 255.2 | H31: =F31-G31 -> 0 | I31: 6420643 | J31: 45685
A32: 29 | B32: 3030 | C32: Salim Ahmed Salim Amer Jid | D32: 327 | E32: 0.4 | F32: =E32*D32 -> 130.8 | G32: =129.95+0.85 -> 130.8 | H32: =F32-G32 -> 0 | I32: 6021175 | J32: 45650 | K32: 45663
A33: 30 | B33: 3038 | C33: Said Ahmed Mahad Qatan | D33: 638 | E33: 0.4 | F33: =E33*D33 -> 255.2 | G33: =252.75+2.45 -> 255.2 | H33: =F33-G33 -> 0 | I33: 7976 | J33: 45637 | K33: 45650
A34: 31 | B34: 3043 | C34: Said Aubad Ali Ghawas | D34: 279.5 | E34: 0.4 | F34: =E34*D34 -> 111.8 | G34: =108.59+3.21 -> 111.8 | H34: =F34-G34 -> 0 | I34: 396336 | J34: 30-12-241 | K34: 45679
A35: 32 | B35: 3058 | C35: Ali Bakhit Ahmed Qatan | D35: 910.9 | E35: 0.4 | F35: =E35*D35 -> 364.36 | H35: =F35-G35 -> 364.36 | I35: 965148
A36: 33 | B36: 3070 | C36: Mohamed Ahmed Suhail Qatan | D36: 985.7 | E36: 0.4 | F36: =E36*D36 -> 394.28 | G36: =194+198.85+1.43 -> 394.28 | H36: =F36-G36 -> 0 | I36: 1918001 | J36: 45641 | K36: 45648 | L36: 45655
A37: 34 | B37: 3072 | C37: Mohammed Salim Said Al Barami | D37: 308 | E37: 0.4 | F37: =E37*D37 -> 123.2 | G37: =119.55 -> 119.55 | H37: =F37-G37 -> 3.65 | I37: 993077 | J37: 45779
A38: 35 | B38: 3077 | C38: Mohammed Ali Suhail Qatan | D38: 481.9 | E38: 0.4 | F38: =E38*D38 -> 192.76 | G38: =190.53 -> 190.53 | H38: =F38-G38 -> 2.23 | I38: 21978752 | J38: 45635
A39: 36 | B39: 3081 | C39: Musallam Bakhit Masoud Qatan | D39: 436.4 | E39: 0.4 | F39: =E39*D39 -> 174.56 | G39: =F39 -> 174.56 | H39: =F39-G39 -> 0 | I39: 21219868 | J39: dcf feed
A40: 37 | B40: 3089 | C40: Yhaya Musallam Said Qatan | D40: 320.5 | E40: 0.4 | F40: =E40*D40 -> 128.2 | G40: =127.34+0.86 -> 128.2 | H40: =F40-G40 -> 0 | I40: 18790484 | J40: 30-121-24 | K40: 45677
A41: 38 | B41: 3093 | C41: Bakhit Amer Salem Qatan | D41: 511.4 | E41: 0.4 | F41: =E41*D41 -> 204.56 | H41: =F41-G41 -> 204.56 | I41: 6361035
A42: 39 | B42: 3094 | C42: Ali Ahmed Aubad Jamaan Al Kathiri | D42: 1006.2 | E42: 0.4 | F42: =E42*D42 -> 402.48 | G42: =371.25 -> 371.25 | H42: =F42-G42 -> 31.23 | I42: 26343985 | J42: 45932
A43: 40 | B43: 3100 | C43: Salim Ahmed Said Tabuk | D43: 1315 | E43: 0.4 | F43: =E43*D43 -> 526 | H43: =F43-G43 -> 526 | I43: 1278615
A44: 41 | B44: 3101 | C44: Salim Said Suhail Qatan | D44: 347.7 | E44: 0.4 | F44: =E44*D44 -> 139.08 | H44: =F44-G44 -> 139.08 | I44: 6767598
A45: 42 | B45: 3102 | C45: Mohammed Salim Amer Qatan | D45: 568.8 | E45: 0.4 | F45: =E45*D45 -> 227.52 | G45: =222.7+4.82 -> 227.52 | H45: =F45-G45 -> 0 | I45: 5916838 | J45: 45629 | K45: 45663
A46: 43 | B46: 3119 | C46: Mohammed Ahmed Suhail Mahad Qatan | D46: 777.6 | E46: 0.4 | F46: =E46*D46 -> 311.04 | G46: =308.32+2.72 -> 311.04 | H46: =F46-G46 -> 0 | I46: 5903061 | J46: 45629 | K46: 45662
A47: 44 | B47: 3122 | C47: Khalid Ahmed Salim Amer Jid Al Mahri | D47: 330 | E47: 0.4 | F47: =E47*D47 -> 132 | G47: =131.65 -> 131.65 | H47: =F47-G47 -> 0.35 | I47: 12415718 | J47: 45644
A48: 45 | B48: 3136 | C48: Ghazi Salim Ahmed Al Kathiri | D48: 500.2 | E48: 0.4 | F48: =E48*D48 -> 200.08 | G48: =197.88+2.2 -> 200.08 | H48: =F48-G48 -> 0 | I48: 183498 | J48: 45624 | K48: 45658
A49: 46 | B49: 3178 | C49: Abdul Sallam Ahmed Abdullah Al Abbadi Al Rawas | D49: 1894 | E49: 0.4 | F49: =E49*D49 -> 757.6 | H49: =F49-G49 -> 757.6 | I49: 1511754
A50: 47 | B50: 3199 | C50: Ali Musallam Ahmed Tabuk | D50: 300.7 | E50: 0.4 | F50: =E50*D50 -> 120.28 | G50: =118.3 -> 118.3 | H50: =F50-G50 -> 1.98 | I50: 5168327 | J50: 45637
A51: 48 | B51: 3200 | C51: Ahmed Said Ahmed Qutan | D51: 246.4 | E51: 0.4 | F51: =E51*D51 -> 98.56 | G51: =F51 -> 98.56 | H51: =F51-G51 -> 0 | I51: 21947578 | J51: 45677
A52: 49 | B52: 3201 | C52: Ali Salim Said Qatan | D52: 275.2 | E52: 0.4 | F52: =E52*D52 -> 110.08 | H52: =F52-G52 -> 110.08 | I52: 7048401
A53: 50 | B53: 3202 | C53: Salim Ahmed Ali Qatan | D53: 315.7 | E53: 0.4 | F53: =E53*D53 -> 126.28 | G53: =102.3 -> 102.3 | H53: =F53-G53 -> 23.98 | I53: 5197371 | J53: 45691
A54: 51 | B54: 3203 | C54: Musallam Salim Amir Said Qatan | D54: 396.5 | E54: 0.4 | F54: =E54*D54 -> 158.6 | G54: =155.89+2.71 -> 158.6 | H54: =F54-G54 -> 0 | I54: 23215097 | J54: 45629 | K54: 45658
A55: 52 | B55: 3204 | C55: Hassan Suhail Ahmed Said Qatan | D55: 352.9 | E55: 0.4 | F55: =E55*D55 -> 141.16 | G55: =140.65 -> 140.65 | H55: =F55-G55 -> 0.51 | I55: 24958926 | J55: 45679
A56: 53 | B56: 3207 | C56: Said Ali Ahmed Al Katheri | D56: 596 | E56: 0.4 | F56: =E56*D56 -> 238.4 | H56: =F56-G56 -> 238.4 | I56: 11940175
A57: 54 | B57: 3208 | C57: Ali Mahad Said Qatan | D57: 499.6 | E57: 0.4 | F57: =E57*D57 -> 199.84 | G57: =199.32+0.52 -> 199.84 | H57: =F57-G57 -> 0 | I57: 1742664 | J57: 45658 | K57: 45691
A58: 55 | B58: 3209 | C58: Said Suhail Ali Al Kathiri | D58: 330 | E58: 0.4 | F58: =E58*D58 -> 132 | G58: =130.43+1.57 -> 132 | H58: =F58-G58 -> 0 | I58: 5634328 | J58: 45637 | K58: 45658
A59: 56 | B59: 3210 | C59: Ahmed Said Mubarak Al Zawamri | D59: 635 | E59: 0.4 | F59: =E59*D59 -> 254 | G59: =249.24+4.76 -> 254 | H59: =F59-G59 -> 0 | I59: 45419 | J59: 45629 | K59: 45658
A60: 57 | B60: 3211 | C60: Salim Mohammed Musallam Al Baraami | D60: 305.7 | E60: 0.4 | F60: =E60*D60 -> 122.28 | G60: =118.9+3.38 -> 122.28 | H60: =F60-G60 -> 0 | I60: 9927207 | J60: 45629 | K60: 45662
A61: 58 | B61: 3212 | C61: Mohammed Said Mahad Qatan | D61: 856.9 | E61: 0.4 | F61: =E61*D61 -> 342.76 | G61: =341.87+0.89 -> 342.76 | H61: =F61-G61 -> 0 | I61: 804443 | J61: 45648 | K61: 45673
A62: 59 | B62: 3213 | C62: Ali Ahmed Suhail Qatan | D62: 598.6 | E62: 0.4 | F62: =E62*D62 -> 239.44 | H62: =F62-G62 -> 239.44 | I62: 2594336
A63: 60 | B63: 3214 | C63: Salim Musallam Ahmed Tabouk | D63: 804.9 | E63: 0.4 | F63: =E63*D63 -> 321.96 | G63: =F63 -> 321.96 | H63: =F63-G63 -> 0 | I63: 5168262 | J63: 45691
A64: 61 | B64: 3215 | C64: Suhail Awadh Salim Hawas Al Aamri | D64: 686.5 | E64: 0.4 | F64: =E64*D64 -> 274.6 | G64: =272.61+1.99 -> 274.6 | H64: =F64-G64 -> 0 | I64: 11684091 | J64: 45644 | K64: 45670
A65: 62 | B65: 3216 | C65: Salim Ali said Al Masahli | D65: 880.2 | E65: 0.4 | F65: =E65*D65 -> 352.08 | G65: =351.77+0.31 -> 352.08 | H65: =F65-G65 -> 0 | I65: 18715567 | J65: 45637 | K65: 45665
A66: 63 | B66: 3217 | C66: Hassan Musallam Ali Qatan | D66: 299.8 | E66: 0.4 | F66: =E66*D66 -> 119.92 | H66: =F66-G66 -> 119.92 | I66: 1568196
A67: 64 | B67: 3219 | C67: Said Salim Ali Hawas Al Aamri | D67: 996.6 | E67: 0.4 | F67: =E67*D67 -> 398.64 | G67: =180.91+145.5+67.9+4.33 -> 398.64 | H67: =F67-G67 -> 0 | I67: 12398617 | J67: 45624 | K67: 45629 | L67: 45635 | M67: 45656
A68: 65 | B68: 3220 | C68: Adnan Mohammed Said Bait Said | D68: 609 | E68: 0.4 | F68: =E68*D68 -> 243.6 | H68: =F68-G68 -> 243.6 | I68: 5348311
A69: 66 | B69: 3221 | C69: Musallam Mohammed Salim Al Barami | D69: 308 | E69: 0.4 | F69: =E69*D69 -> 123.2 | G69: =0.09+121.25 -> 121.34 | H69: =F69-G69 -> 1.86 | I69: 13362673 | J69: 45665 | K69: 45779
A70: 67 | B70: 3222 | C70: Mohammed Ahmed Bakhit Qatan | D70: 427.7 | E70: 0.4 | F70: =E70*D70 -> 171.08 | G70: =168.53+2.55 -> 171.08 | H70: =F70-G70 -> 0 | I70: 18091329 | J70: 45630 | K70: 45658
A71: 68 | B71: 3223 | C71: Salim Said Mustahil Al Kathiri | D71: 294 | E71: 0.4 | F71: =E71*D71 -> 117.6 | H71: =F71-G71 -> 117.6 | I71: 5334914
A72: 69 | B72: 3224 | C72: Salim Said Salim Qatan | D72: 263 | E72: 0.4 | F72: =E72*D72 -> 105.2 | G72: =101.78+3.42 -> 105.2 | H72: =F72-G72 -> 0 | I72: 2066756 | J72: 45635 | K72: 45662
A73: 70 | B73: 3225 | C73: Mohamed Ahmed Salam Alamri | D73: 302.8 | E73: 0.4 | F73: =E73*D73 -> 121.12 | G73: =F73 -> 121.12 | H73: =F73-G73 -> 0 | I73: 798637 | J73: dcf feed
A74: 71 | B74: 3227 | C74: Ahmed Ali Suhail ALAamri | D74: 273 | E74: 0.4 | F74: =E74*D74 -> 109.2 | G74: =104.43+4.77 -> 109.2 | H74: =F74-G74 -> 0 | I74: 15214649 | J74: 45630 | K74: 45658
A75: 72 | B75: 3228 | C75: Ali Amer Salim Qatan | D75: 602 | E75: 0.4 | F75: =E75*D75 -> 240.8 | H75: =F75-G75 -> 240.8 | I75: 1307775
A76: 73 | B76: 3229 | C76: Musallam Amer Salim Qatan | D76: 484 | E76: 0.4 | F76: =E76*D76 -> 193.6 | H76: =F76-G76 -> 193.6 | I76: 6370978
A77: 74 | B77: 3230 | C77: Mohammed Abdullah Ali Ghawas | D77: 461 | E77: 0.4 | F77: =E77*D77 -> 184.4 | H77: =F77-G77 -> 184.4 | I77: 1968755
A78: 75 | B78: 3231 | C78: Tanaf Suhail Ali Hawas Al Aamri | D78: 600.8 | E78: 0.4 | F78: =E78*D78 -> 240.32 | G78: =121.11+116.4+2.81 -> 240.32 | H78: =F78-G78 -> 0 | I78: 6203903 | J78: 45663 | K78: 45677 | L78: 45779
A79: 76 | B79: 3232 | C79: Salim Mohammed Ahmed Al Aamri | D79: 310.2 | E79: 0.4 | F79: =E79*D79 -> 124.08 | G79: =F79 -> 124.08 | H79: =F79-G79 -> 0 | I79: 6387264 | J79: dcf feed
A80: 77 | B80: 3234 | C80: Masoud Salim Ahmed Alash Al Kathiri | D80: 602.6 | E80: 0.4 | F80: =E80*D80 -> 241.04 | H80: =F80-G80 -> 241.04 | I80: 21834239
A81: 78 | B81: 3235 | C81: Ahmed Mahad Musallam Amor Jid | D81: 638 | E81: 0.4 | F81: =E81*D81 -> 255.2 | H81: =F81-G81 -> 255.2 | I81: 1234245
A82: 79 | B82: 3236 | C82: Salim Ali Mohammed Hawas Al Amari | D82: 226.9 | E82: 0.4 | F82: =E82*D82 -> 90.76 | G82: =88.38+2.38 -> 90.76 | H82: =F82-G82 -> 0 | I82: 6733333 | J82: 45630 | K82: 45662
A83: 80 | B83: 3237 | C83: Suhail Salim Mohammed Al Daakari | D83: 750.1 | E83: 0.4 | F83: =E83*D83 -> 300.04 | G83: =295.47+4.57 -> 300.04 | H83: =F83-G83 -> 0 | I83: 873637 | J83: 28/11/2024 - 24-12-2024
A84: 82 | B84: 3239 | C84: Ali Salim Bakhit Qatan | D84: 585.6 | E84: 0.4 | F84: =E84*D84 -> 234.24 | G84: =16.6+213.4+4.24 -> 234.24 | H84: =F84-G84 -> 0 | I84: 14379226 | J84: 45642 | K84: 45644 | L84: 45663
A85: 83 | B85: 3240 | C85: Ali Said Salim Al kathiri | D85: 607.4 | E85: 0.4 | F85: =E85*D85 -> 242.96 | G85: =238.45+4.51 -> 242.96 | H85: =F85-G85 -> 0 | I85: 5622856 | J85: 45642 | K85: 45670
A86: 84 | B86: 3241 | C86: Bashar Ahmed Ali Qatan | D86: 298.6 | E86: 0.4 | F86: =E86*D86 -> 119.44 | G86: =F86 -> 119.44 | H86: =F86-G86 -> 0 | I86: 21125518 | J86: 45691
A87: 85 | B87: 3243 | C87: Asad Ali Ahmed Suhail Aamir Jid | D87: 297 | E87: 0.4 | F87: =E87*D87 -> 118.8 | G87: =116+2.8 -> 118.8 | H87: =F87-G87 -> 0 | I87: 25887256 | J87: 45629 | K87: 45664
A88: 86 | B88: 3244 | C88: Mohammed Ali Bakhit Qatan | D88: 219.1 | E88: 0.4 | F88: =E88*D88 -> 87.64 | H88: =F88-G88 -> 87.64 | I88: 19340943
A89: 87 | B89: 3245 | C89: Musallam Ahmed Mohammed Aldakari Al Kathiri | D89: 199.4 | E89: 0.4 | F89: =E89*D89 -> 79.76 | G89: =76.05+3.71 -> 79.76 | H89: =F89-G89 -> 0 | I89: 996477 | J89: 45630 | K89: 45658
A90: 88 | B90: 3246 | C90: Salim Suhail Said Ghawas | D90: 264 | E90: 0.4 | F90: =E90*D90 -> 105.6 | G90: =105.17+0.43 -> 105.6 | H90: =F90-G90 -> 0 | I90: 662648 | J90: 45652 | K90: 45685
A91: 89 | B91: 3247 | C91: Mohammed Suhail Said Ghawas | D91: 287.2 | E91: 0.4 | F91: =E91*D91 -> 114.88 | G91: =114.47+0.41 -> 114.88 | H91: =F91-G91 -> 0 | I91: 6457783 | J91: 45650 | K91: 45685
A92: 90 | B92: 3248 | C92: Ahmed Suhail Said Ghawas | D92: 264 | E92: 0.4 | F92: =E92*D92 -> 105.6 | H92: =F92-G92 -> 105.6 | I92: 18811851
A93: 91 | B93: 3249 | C93: Amir Musallam Hadi Salim Al Aamri | D93: 572 | E93: 0.4 | F93: =E93*D93 -> 228.8 | G93: =F93 -> 228.8 | H93: =F93-G93 -> 0 | I93: 24540784 | J93: dcf feed
A94: 92 | B94: 3251 | C94: Mahad Ahmed Mahad Aamir Jid | D94: 330 | E94: 0.4 | F94: =E94*D94 -> 132 | G94: =F94 -> 132 | H94: =F94-G94 -> 0 | I94: 6420681 | J94: 45685
A95: 94 | B95: 3253 | C95: Abdull Ali Ahmed Suhail Aamir Jid | D95: 592 | E95: 0.4 | F95: =E95*D95 -> 236.8 | G95: =234.43+2.37 -> 236.8 | H95: =F95-G95 -> 0 | I95: 25887589 | J95: 45629 | K95: 45644
A96: 95 | B96: 3254 | C96: Said Mohammed Musallam Al Shihri | D96: 572 | E96: 0.4 | F96: =E96*D96 -> 228.8 | G96: =228.09+0.71 -> 228.8 | H96: =F96-G96 -> 0 | I96: 6668983 | J96: 45623 | K96: 45658
A97: 96 | B97: 3255 | C97: Bakhit Ahmed Musallam Khinan Al Shahri | D97: 425.8 | E97: 0.4 | F97: =E97*D97 -> 170.32 | G97: =167.27+3.05 -> 170.32 | H97: =F97-G97 -> 0 | I97: 5851949 | J97: 45635 | K97: 45663
A98: 97 | B98: 3256 | C98: Salim Said Salim Al Mahri | D98: 1933.3 | E98: 0.4 | F98: =E98*D98 -> 773.32 | G98: =470+303.32 -> 773.32 | H98: =F98-G98 -> 0 | I98: 6147152 | J98: dcf feed | K98: 45635 | L98: 45645
A99: 98 | B99: 3258 | C99: Ahmed Salim Amer Qatan | D99: 807.3 | E99: 0.4 | F99: =E99*D99 -> 322.92 | G99: =320.1+2.82 -> 322.92 | H99: =F99-G99 -> 0 | I99: 15335306 | J99: 45677 | K99: 13-2-25
A100: 99 | B100: 3260 | C100: Ali Musalam Said Salim Qatan | D100: 215.5 | E100: 0.4 | F100: =E100*D100 -> 86.2 | G100: =83.51+2.69 -> 86.2 | H100: =F100-G100 -> 0 | I100: 19361936 | J100: 45685 | K100: 45691
A101: 100 | B101: 3261 | C101: Salim Mohamed Salim Qatan | D101: 292.1 | E101: 0.4 | F101: =E101*D101 -> 116.84 | H101: =F101-G101 -> 116.84 | I101: 8124516
...

Sheet Center-Oct
A1: HAJEEF CAMEL MILK PROCUREMENT FROM 01-Oct-2024 TO 31-Oct-2024
A3: Sr. No. | B3: Farmer Code | C3: Farmer Name | D3: Total Milk Qty | E3: Avg. Rate (OMR/Ltr.) | F3: Amount (OMR) | G3: Amount (OMR) | H3: Amount (OMR) | I3: ID No. | J3: Bank Account | K3: Bank Name. | L3: SWIFT | M3: Phone No. | N3: remark 2 | O3: remark 3
A4: 1 | B4: 1108 | C4: Bakhit Ahmed Musallam Al kathiri | D4: 936.5 | E4: 0.4 | F4: =E4*D4 -> 374.6 | H4: =F4-G4 -> 374.6 | I4: 15218386 | J4: 0439012124150013 | K4: BANK MUSCAT | L4: BMUSOMRX | M4: 92776884
A5: 2 | B5: 1390 | C5: Bakhait Salim Ahmed Alash Al Kathiri | D5: 344.4 | E5: 0.4 | F5: =E5*D5 -> 137.76 | G5: =137.67+0.09 -> 137.76 | H5: =F5-G5 -> 0 | I5: 12181822 | J5: 0439014599800023 | K5: BANK MUSCAT | L5: BMUSOMRX | M5: 92442060 | N5: 45662 | O5: 45691
A6: 3 | B6: 1399 | C6: Mohammed Suhail Ali Hawas Al Aamri | D6: 260.4 | E6: 0.4 | F6: =E6*D6 -> 104.16 | G6: =101.85+2.31 -> 104.16 | H6: =F6-G6 -> 0 | I6: 10065546 | J6: 3109720870700 | K6: OAB | L6: OMABOMRU | N6: 45658 | O6: 45691
A7: 4 | B7: 1422 | C7: Mahammed Musallam Ahmed Hwas | D7: 261.6 | E7: 0.4 | F7: =E7*D7 -> 104.64 | G7: =104.52+0.12 -> 104.64 | H7: =F7-G7 -> 0 | I7: 3280016 | J7: 0397003987550015 | K7: BANK MUSCAT | L7: BMUSOMRX | N7: 45658 | O7: 45691
A8: 5 | B8: 1424 | C8: Said Ahmed Sabah Ali Badar | D8: 388.2 | E8: 0.4 | F8: =E8*D8 -> 155.28 | G8: =154.3+0.98 -> 155.28 | H8: =F8-G8 -> 0 | I8: 748395 | J8: 01012574607001 | K8: BANK DHOFAR | L8: BDOFOMRU | M8: 93011211 | N8: 45644 | O8: 45677
A9: 6 | B9: 1429 | C9: Said Mohammed Salem Akdha Al Rawas | D9: 420 | E9: 0.4 | F9: =E9*D9 -> 168 | G9: =163.5 -> 163.5 | H9: =F9-G9 -> 4.5 | I9: 339725 | J9: 0397003785300017 | K9: BANK MUSCAT | L9: BMUSOMRX | N9: 13-2-25
A10: 7 | B10: 1431 | C10: Bakhit Mohamed Salim Rawas | D10: 186.9 | E10: 0.4 | F10: =E10*D10 -> 74.76 | G10: =72.08+2.68 -> 74.76 | H10: =F10-G10 -> 0 | I10: 721445 | J10: 01010850230001 | K10: BANK DHOFAR | L10: BDOFOMRU | M10: 99291700 | N10: 45658 | O10: 45679
A11: 8 | B11: 1443 | C11: Ahmed Musallam Ahmed Al Kathiri | D11: 1189.4 | E11: 0.4 | F11: =E11*D11 -> 475.76 | H11: =F11-G11 -> 475.76 | I11: 6026992 | J11: 0439017196260028 | K11: BANK MUSCAT | L11: BMUSOMRX | M11: 95863774
A12: 9 | B12: 1452 | C12: Sulaim Said Mohammed Hawas Al Aamri | D12: 389 | E12: 0.4 | F12: =E12*D12 -> 155.6 | G12: =151.89+3.71 -> 155.6 | H12: =F12-G12 -> 0 | I12: 20917176 | J12: 0406012189810015 | K12: BANK MUSCAT | L12: BMUSOMRX | M12: 95863774 | N12: 45658 | O12: 45779
A13: 10 | B13: 1458 | C13: Salim Mustahil Jamaan Al Shakl Al kathiri | D13: 319 | E13: 0.4 | F13: =E13*D13 -> 127.6 | H13: =F13-G13 -> 127.6 | I13: 77628 | J13: 01012583986001 | K13: BANK DHOFAR | L13: BDOFOMRU | M13: 99275608
A14: 11 | B14: 1461 | C14: Suhail Said Ali Bait said | D14: 333.5 | E14: 0.4 | F14: =E14*D14 -> 133.4 | H14: =F14-G14 -> 133.4 | I14: 6828806 | J14: 0396003267730012 | K14: BANK MUSCAT | L14: BMUSOMRX | M14: 92330321
A15: 12 | B15: 1465 | C15: Mahad Salim Zaed Baitsaid | D15: 331.7 | E15: 0.4 | F15: =E15*D15 -> 132.68 | G15: =F15 -> 132.68 | H15: =F15-G15 -> 0 | I15: 757601 | J15: 1023113274001 | K15: NBO | L15: NBOMOMRX | M15: 99892131 | N15: dcf feed
A16: 13 | B16: 1474 | C16: Mohamed Salam Amer Al Yafee | D16: 613.5 | E16: 0.4 | F16: =E16*D16 -> 245.4 | H16: =F16-G16 -> 245.4 | I16: 4603773 | J16: 01041185194001 | K16: BANK DHOFAR | L16: BDOFOMRU | M16: 98820843
A17: 14 | B17: 1479 | C17: Ahmed Amer Said Baitsaid | D17: 303.2 | E17: 0.4 | F17: =E17*D17 -> 121.28 | G17: =119.16 -> 119.16 | H17: =F17-G17 -> 2.12 | I17: 5217726 | J17: 0396003219770029 | K17: BANK MUSCAT | L17: BMUSOMRX | M17: 92610234 | N17: 45637
A18: 15 | B18: 1483 | C18: Saed Ali Ahmed Al Kathiri | D18: 820.3 | E18: 0.4 | F18: =E18*D18 -> 328.12 | G18: =327.34+0.78 -> 328.12 | H18: =F18-G18 -> 0 | I18: 1567826 | J18: 1083724895017 | K18: NBO | L18: NBOMOMRX | M18: 98532884 | N18: 45658 | O18: 45691
A19: 16 | B19: 1486 | C19: Mosoud Ali Salim Al Kathiri | D19: 354.5 | E19: 0.4 | F19: =E19*D19 -> 141.8 | G19: =F19 -> 141.8 | H19: =F19-G19 -> 0 | I19: 22792564 | J19: 0401064266530014 | K19: BANK MUSCAT | L19: BMUSOMRX | N19: 45685
A20: 17 | B20: 1762 | C20: MUSALLAM HASAN ALI BAIT SAID | D20: 1119.5 | E20: 0.4 | F20: =E20*D20 -> 447.8 | G20: =444.45+3.35 -> 447.8 | H20: =F20-G20 -> 0 | I20: 1409527 | J20: 0397003183710017 | K20: Bank Muscat | L20: BMUSOMRX | N20: 45650 | O20: 45677
A21: 18 | B21: 1792 | C21: Musallam Bakhit Salim Al Aamri | D21: 300.2 | E21: 0.4 | F21: =E21*D21 -> 120.08 | G21: =118.28 -> 118.28 | H21: =F21-G21 -> 1.8 | I21: 9545556 | J21: 01011373210001 | K21: BANK DHOFAR | L21: BDOFOMRU | N21: 45658
A22: 19 | B22: 3009 | C22: Ahmed Salim Bakhit Qatan | D22: 219.2 | E22: 0.4 | F22: =E22*D22 -> 87.68 | H22: =F22-G22 -> 87.68 | I22: 1448391 | J22: 3109628132500 | K22: OAB | L22: OMABOMRU | M22: 99100144
A23: 20 | B23: 3012 | C23: Salim Suhail Ali Al Kathiri | D23: 319 | E23: 0.4 | F23: =E23*D23 -> 127.6 | G23: =122.47+5.13 -> 127.6 | H23: =F23-G23 -> 0 | I23: 5634422 | J23: 0406059374210012 | K23: BANK MUSCAT | L23: BMUSOMRX | M23: 96922118 | N23: 45658 | O23: 45677
A24: 21 | B24: 3014 | C24: Ahmed Mohammed Salim Al Barami | D24: 221.3 | E24: 0.4 | F24: =E24*D24 -> 88.52 | G24: =85.65+2.87 -> 88.52 | H24: =F24-G24 -> 0 | I24: 648421 | J24: 3129711924500 | K24: OAB | L24: OMABOMRU | M24: 98815665 | N24: 45658 | O24: 45685
A25: 22 | B25: 3015 | C25: Ahmed Mohammed Faraj Al Kathiri | D25: 223.8 | E25: 0.4 | F25: =E25*D25 -> 89.52 | G25: =84.47 -> 84.47 | H25: =F25-G25 -> 5.05 | I25: 5753033 | J25: 0439058732890011 | K25: BANK MUSCAT | L25: BMUSOMRX | M25: 92838405 | N25: 45779
A26: 23 | B26: 3018 | C26: Bakhit Salim Bakhit Qatan | D26: 128.6 | E26: 0.4 | F26: =E26*D26 -> 51.44 | G26: =50.13+1.31 -> 51.44 | H26: =F26-G26 -> 0 | I26: 1528087 | J26: 0397004184300024 | K26: BANK MUSCAT | L26: BMUSOMRX | N26: 45658 | O26: 45679
A27: 24 | B27: 3020 | C27: Bakhit Ali Salim Qatan | D27: 405.2 | E27: 0.4 | F27: =E27*D27 -> 162.08 | G27: =159.67+2.41 -> 162.08 | H27: =F27-G27 -> 0 | I27: 5418422 | J27: 0401002342630017 | K27: BANK MUSCAT | L27: BMUSOMRX | M27: 99495434 | N27: 45650 | O27: 45677
A28: 25 | B28: 3022 | C28: Hussein Masoud Aubad Al Kathiri | D28: 647.6 | E28: 0.4 | F28: =E28*D28 -> 259.04 | G28: =255.09+3.95 -> 259.04 | H28: =F28-G28 -> 0 | I28: 5360253 | J28: 1060656310017 | K28: NBO | L28: NBOMOMRX | M28: 99257989 | N28: 45670 | O28: 45685
A29: 26 | B29: 3025 | C29: Musallam Salim Mahad Qatan | D29: 596.5 | E29: 0.4 | F29: =E29*D29 -> 238.6 | H29: =F29-G29 -> 238.6 | I29: 7542172 | J29: 0401002461080028 | K29: BANK MUSCAT | L29: BMUSOMRX
A30: 27 | B30: 3026 | C30: Amer Salem Ahmed Qatan | D30: 323 | E30: 0.4 | F30: =E30*D30 -> 129.2 | H30: =F30-G30 -> 129.2 | I30: 7033819 | J30: 0401003532620025 | K30: BANK MUSCAT | L30: BMUSOMRX | M30: 92256918
A31: 28 | B31: 3027 | C31: Salim Ahmed Mahad Aamir Jid | D31: 667 | E31: 0.4 | F31: =E31*D31 -> 266.8 | G31: =F31 -> 266.8 | H31: =F31-G31 -> 0 | I31: 6420643 | J31: 01011362595002 | K31: BANK DHOFAR | L31: BDOFOMRU | M31: 92288434 | N31: 45685
A32: 29 | B32: 3030 | C32: Salim Ahmed Salim Amer Jid | D32: 326 | E32: 0.4 | F32: =E32*D32 -> 130.4 | G32: =130.1+0.3 -> 130.4 | H32: =F32-G32 -> 0 | I32: 6021175 | J32: 0401050718800013 | K32: BANK MUSCAT | L32: BMUSOMRX | M32: 91716888 | N32: 45663 | O32: 45691
A33: 30 | B33: 3038 | C33: Said Ahmed Mahad Qatan | D33: 638 | E33: 0.4 | F33: =E33*D33 -> 255.2 | G33: =253.15+2.05 -> 255.2 | H33: =F33-G33 -> 0 | I33: 7976 | J33: 3109016888700 | K33: OAB | L33: OMABOMRU | M33: 98920007 | N33: 45650 | O33: 45670
A34: 31 | B34: 3043 | C34: Said Aubad Ali Ghawas | D34: 287.7 | E34: 0.4 | F34: =E34*D34 -> 115.08 | G34: =108.34+6.74 -> 115.08 | H34: =F34-G34 -> 0 | I34: 396336 | J34: 0397003933630013 | K34: BANK MUSCAT | L34: BMUSOMRX | M34: 99498844 | N34: 45679
A35: 32 | B35: 3058 | C35: Ali Bakhit Ahmed Qatan | D35: 1025.6 | E35: 0.4 | F35: =E35*D35 -> 410.24 | H35: =F35-G35 -> 410.24 | I35: 965148 | J35: 3129376165700 | K35: OAB | L35: OMABOMRU | M35: 90980121
A36: 33 | B36: 3070 | C36: Mohamed Ahmed Suhail Qatan | D36: 1024 | E36: 0.4 | F36: =E36*D36 -> 409.6 | G36: =405.97+3.63 -> 409.6 | H36: =F36-G36 -> 0 | I36: 1918001 | J36: 0397004395550019 | K36: BANK MUSCAT | L36: BMUSOMRX | M36: 92863640 | N36: 45655 | O36: 45670
A37: 34 | B37: 3072 | C37: Mohammed Salim Said Al Barami | D37: 322 | E37: 0.4 | F37: =E37*D37 -> 128.8 | H37: =F37-G37 -> 128.8 | I37: 993077 | J37: 250094968001 | K37: HSBC | L37: BBMEOMRX | M37: 92252981
A38: 35 | B38: 3077 | C38: Mohammed Ali Suhail Qatan | D38: 604.3 | E38: 0.4 | F38: =E38*D38 -> 241.72 | H38: =F38-G38 -> 241.72 | I38: 21978752 | J38: 0396041232890032 | K38: BANK MUSCAT | L38: BMUSOMRX | M38: 90833336
A39: 36 | B39: 3081 | C39: Musallam Bakhit Masoud Qatan | D39: 434.9 | E39: 0.4 | F39: =E39*D39 -> 173.96 | G39: =F39 -> 173.96 | H39: =F39-G39 -> 0 | I39: 21219868 | J39: 010010201414 | K39: Bank Sohar | L39: BSHROMRU | M39: 93288777
A40: 37 | B40: 3089 | C40: Yhaya Musallam Said Qatan | D40: 288.2 | E40: 0.4 | F40: =E40*D40 -> 115.28 | G40: =F40 -> 115.28 | H40: =F40-G40 -> 0 | I40: 18790484 | J40: 0401016503450018 | K40: BANK MUSCAT | L40: BMUSOMRX | N40: 45677
A41: 38 | B41: 3093 | C41: Bakhit Amer Salem Qatan | D41: 428.2 | E41: 0.4 | F41: =E41*D41 -> 171.28 | H41: =F41-G41 -> 171.28 | I41: 6361035 | J41: 00510034969002 | K41: BANK NIZWA | L41: BNZWOMRX | M41: 99497919
A42: 39 | B42: 3094 | C42: Ali Ahmed Aubad Jamaan Al Kathiri | D42: 692.4 | E42: 0.4 | F42: =E42*D42 -> 276.96 | H42: =F42-G42 -> 276.96 | I42: 26343985 | J42: 0304024501570012 | K42: BANK MUSCAT | L42: BMUSOMRX | M42: 93327740
A43: 40 | B43: 3100 | C43: Salim Ahmed Said Tabuk | D43: 1380 | E43: 0.4 | F43: =E43*D43 -> 552 | H43: =F43-G43 -> 552 | I43: 1278615 | J43: 0426003863310028 | K43: NBO | L43: BMUSOMRX | M43: 99806386
A44: 41 | B44: 3101 | C44: Salim Said Suhail Qatan | D44: 359.4 | E44: 0.4 | F44: =E44*D44 -> 143.76 | H44: =F44-G44 -> 143.76 | I44: 6767598 | J44: 0401002332700028 | K44: BANK MUSCAT | L44: BMUSOMRX | M44: 99100344
A45: 42 | B45: 3102 | C45: Mohammed Salim Amer Qatan | D45: 603.3 | E45: 0.4 | F45: =E45*D45 -> 241.32 | G45: =237.68+3.64 -> 241.32 | H45: =F45-G45 -> 0 | I45: 5916838 | J45: 0317002509980029 | K45: BANK MUSCAT | L45: BMUSOMRX | M45: 91917520 | N45: 45663 | O45: 45685
A46: 43 | B46: 3119 | C46: Mohammed Ahmed Suhail Mahad Qatan | D46: 1008 | E46: 0.4 | F46: =E46*D46 -> 403.2 | G46: =399.83+3.37 -> 403.2 | H46: =F46-G46 -> 0 | I46: 5903061 | J46: 0401016956230027 | K46: BANK MUSCAT | L46: BMUSOMRX | M46: 91904279 | N46: 45662 | O46: 45685
A47: 44 | B47: 3122 | C47: Khalid Ahmed Salim Amer Jid Al Mahri | D47: 343 | E47: 0.4 | F47: =E47*D47 -> 137.2 | G47: =F47 -> 137.2 | H47: =F47-G47 -> 0 | I47: 12415718 | J47: 0401050718800013 | K47: BANK MUSCAT | L47: BMUSOMRX | M47: 99481799 | N47: dcf feed
A48: 45 | B48: 3136 | C48: Ghazi Salim Ahmed Al Kathiri | D48: 495.9 | E48: 0.4 | F48: =E48*D48 -> 198.36 | G48: =195.75+2.61 -> 198.36 | H48: =F48-G48 -> 0 | I48: 183498 | J48: 01011238092002 | K48: BANK DHOFAR | L48: BDOFOMRU | M48: 99481314 | N48: 45658 | O48: 45691
A49: 46 | B49: 3178 | C49: Abdul Sallam Ahmed Abdullah Al Abbadi Al Rawas | D49: 2273.5 | E49: 0.4 | F49: =E49*D49 -> 909.4 | H49: =F49-G49 -> 909.4 | I49: 1511754 | J49: 3109061950500 | K49: OAB | L49: OMABOMRU | M49: 99495933
A50: 47 | B50: 3199 | C50: Ali Musallam Ahmed Tabuk | D50: 296.2 | E50: 0.4 | F50: =E50*D50 -> 118.48 | H50: =F50-G50 -> 118.48 | I50: 5168327 | J50: 0397004227360018 | K50: BANK MUSCAT | L50: BMUSOMRX | M50: 98066833
A51: 48 | B51: 3200 | C51: Ahmed Said Ahmed Qutan | D51: 45.2 | E51: 0.4 | F51: =E51*D51 -> 18.08 | G51: =F51 -> 18.08 | H51: =F51-G51 -> 0 | I51: 21947578 | J51: 0401044694220018 | K51: BANK MUSCAT | L51: BMUSOMRX | N51: 45677
A52: 49 | B52: 3201 | C52: Ali Salim Said Qatan | D52: 290.5 | E52: 0.4 | F52: =E52*D52 -> 116.2 | H52: =F52-G52 -> 116.2 | I52: 7048401 | J52: 01041090275001 | K52: BANK DHOFAR | L52: BDOFOMRU
A53: 50 | B53: 3202 | C53: Salim Ahmed Ali Qatan | D53: 295.3 | E53: 0.4 | F53: =E53*D53 -> 118.12 | G53: 0 | H53: =F53-G53 -> 118.12 | I53: 5197371 | J53: 0132906010084010 | K53: BANK MUSCAT | L53: BMUSOMRX | M53: 93889732
A54: 51 | B54: 3203 | C54: Musallam Salim Amir Said Qatan | D54: 442.4 | E54: 0.4 | F54: =E54*D54 -> 176.96 | G54: =171.29+5.67 -> 176.96 | H54: =F54-G54 -> 0 | I54: 23215097 | J54: 0401047625040018 | K54: BANK MUSCAT | L54: BMUSOMRX | N54: 45658 | O54: 45685
A55: 52 | B55: 3204 | C55: Hassan Suhail Ahmed Said Qatan | D55: 422.5 | E55: 0.4 | F55: =E55*D55 -> 169 | H55: =F55-G55 -> 169 | I55: 24958926 | J55: 0426060858570018 | K55: BANK MUSCAT | L55: BMUSOMRX | M55: 99312225
A56: 53 | B56: 3207 | C56: Said Ali Ahmed Al Katheri | D56: 680.1 | E56: 0.4 | F56: =E56*D56 -> 272.04 | H56: =F56-G56 -> 272.04 | I56: 11940175 | J56: 0406020751730014 | K56: BANK MUSCAT | L56: BMUSOMRX | M56: 98138748
A57: 54 | B57: 3208 | C57: Ali Mahad Said Qatan | D57: 625.4 | E57: 0.4 | F57: =E57*D57 -> 250.16 | G57: =F57 -> 250.16 | H57: =F57-G57 -> 0 | I57: 1742664 | J57: 001010070151 | K57: BANK SOHAR | L57: BSHROMRU | M57: 99482598 | N57: 45691
A58: 55 | B58: 3209 | C58: Said Suhail Ali Al Kathiri | D58: 338.3 | E58: 0.4 | F58: =E58*D58 -> 135.32 | G58: =134.23+1.09 -> 135.32 | H58: =F58-G58 -> 0 | I58: 5634328 | J58: 0397016698910016 | K58: BANK MUSCAT | L58: BMUSOMRX | M58: 92283227 | N58: 45658 | O58: 45677
A59: 56 | B59: 3210 | C59: Ahmed Said Mubarak Al Zawamri | D59: 657.6 | E59: 0.4 | F59: =E59*D59 -> 263.04 | G59: =261.54+1.5 -> 263.04 | H59: =F59-G59 -> 0 | I59: 45419 | J59: 0401002467120013 | K59: BANK MUSCAT | L59: BMUSOMRX | M59: 90101070 | N59: 45658 | O59: 45664
A60: 57 | B60: 3211 | C60: Salim Mohammed Musallam Al Baraami | D60: 326.8 | E60: 0.4 | F60: =E60*D60 -> 130.72 | G60: =127.57 -> 127.57 | H60: =F60-G60 -> 3.15 | I60: 9927207 | J60: 01010941305001 | K60: BANK DHOFAR | L60: BDOFOMRU | N60: 45662
A61: 58 | B61: 3212 | C61: Mohammed Said Mahad Qatan | D61: 800.2 | E61: 0.4 | F61: =E61*D61 -> 320.08 | G61: =F61 -> 320.08 | H61: =F61-G61 -> 0 | I61: 804443 | J61: 050170299001 | K61: HSBC | L61: BBMEOMRX | M61: 99483202 | N61: 45673
A62: 59 | B62: 3213 | C62: Ali Ahmed Suhail Qatan | D62: 735.6 | E62: 0.4 | F62: =E62*D62 -> 294.24 | H62: =F62-G62 -> 294.24 | I62: 2594336 | J62: 0397004383920015 | K62: BANK MUSCAT | L62: BMUSOMRX | M62: 71773005
A63: 60 | B63: 3214 | C63: Salim Musallam Ahmed Tabouk | D63: 187.1 | E63: 0.4 | F63: =E63*D63 -> 74.84 | G63: =73.87 -> 73.87 | H63: =F63-G63 -> 0.97 | I63: 5168262 | J63: 01041249912001 | K63: BANK DHOFAR | L63: BDOFOMRU | M63: 99895383 | N63: 45691
A64: 61 | B64: 3215 | C64: Suhail Awadh Salim Hawas Al Aamri | D64: 634.5 | E64: 0.4 | F64: =E64*D64 -> 253.8 | G64: =250.21+3.59 -> 253.8 | H64: =F64-G64 -> 0 | I64: 11684091 | J64: 01010853900001 | K64: BANK DHOFAR | L64: BDOFOMRU | N64: 45670 | O64: 13-2-25
A65: 62 | B65: 3216 | C65: Salim Ali said Al Masahli | D65: 912.3 | E65: 0.4 | F65: =E65*D65 -> 364.92 | G65: =363.44+1.48 -> 364.92 | H65: =F65-G65 -> 0 | I65: 18715567 | J65: 0406045085100027 | K65: BANK MUSCAT | L65: BMUSOMRX | M65: 77279900 | N65: 45665 | O65: 45691
A66: 63 | B66: 3217 | C66: Hassan Musallam Ali Qatan | D66: 303.7 | E66: 0.4 | F66: =E66*D66 -> 121.48 | H66: =F66-G66 -> 121.48 | I66: 1568196 | J66: 00510059623001 | K66: BANK NIZWA | L66: BNZWOMRX | M66: 99494635
A67: 64 | B67: 3219 | C67: Said Salim Ali Hawas Al Aamri | D67: 974.1 | E67: 0.4 | F67: =E67*D67 -> 389.64 | G67: =170.27+181.75+33.95+3.67 -> 389.64 | H67: =F67-G67 -> 0 | I67: 12398617 | J67: 0406003141690019 | K67: BANK MUSCAT | L67: BMUSOMRX | N67: 45650 | O67: 45656 | P67: 45663 | Q67: 45677
A68: 65 | B68: 3220 | C68: Adnan Mohammed Said Bait Said | D68: 667 | E68: 0.4 | F68: =E68*D68 -> 266.8 | H68: =F68-G68 -> 266.8 | I68: 5348311 | J68: 01011445808001 | K68: BANK DHOFAR | L68: BDOFOMRU | M68: 96313636
A69: 66 | B69: 3221 | C69: Musallam Mohammed Salim Al Barami | D69: 322 | E69: 0.4 | F69: =E69*D69 -> 128.8 | H69: =F69-G69 -> 128.8 | I69: 13362673 | J69: 0401003471060021 | K69: BANK MUSCAT | L69: BMUSOMRX | M69: 92665337
A70: 67 | B70: 3222 | C70: Mohammed Ahmed Bakhit Qatan | D70: 402.1 | E70: 0.4 | F70: =E70*D70 -> 160.84 | G70: =157.5+3.34 -> 160.84 | H70: =F70-G70 -> 0 | I70: 18091329 | J70: 01011448559002 | K70: BANK DHOFAR | L70: BDOFOMRU | M70: 92197820 | N70: 45658 | O70: 45662
A71: 68 | B71: 3223 | C71: Salim Said Mustahil Al Kathiri | D71: 320.6 | E71: 0.4 | F71: =E71*D71 -> 128.24 | H71: =F71-G71 -> 128.24 | I71: 5334914 | J71: 00510087464001 | K71: BANK NIZWA | L71: BNZWOMRX | M71: 98800996
A72: 69 | B72: 3224 | C72: Salim Said Salim Qatan | D72: 276 | E72: 0.4 | F72: =E72*D72 -> 110.4 | G72: =108.13+2.27 -> 110.4 | H72: =F72-G72 -> 0 | I72: 2066756 | J72: 0439002422440029 | K72: BANK MUSCAT | L72: BMUSOMRX | M72: 95316025 | N72: 45662 | O72: 45691
A73: 70 | B73: 3225 | C73: Mohamed Ahmed Salam Alamri | D73: 308.9 | E73: 0.4 | F73: =E73*D73 -> 123.56 | G73: =F73 -> 123.56 | H73: =F73-G73 -> 0 | I73: 798637 | J73: 0397004248490019 | K73: BANK MUSCAT | L73: BMUSOMRX | N73: 19-0125
A74: 71 | B74: 3227 | C74: Ahmed Ali Suhail ALAamri | D74: 304.9 | E74: 0.4 | F74: =E74*D74 -> 121.96 | G74: =121.33+0.63 -> 121.96 | H74: =F74-G74 -> 0 | I74: 15214649 | J74: 0406003835930033 | K74: BANK MUSCAT | L74: BMUSOMRX | M74: 92171914 | N74: 45658 | O74: 45691
A75: 72 | B75: 3228 | C75: Ali Amer Salim Qatan | D75: 602.9 | E75: 0.4 | F75: =E75*D75 -> 241.16 | H75: =F75-G75 -> 241.16 | I75: 1307775 | J75: 01011440583003 | K75: BANK DHOFAR | L75: BDOFOMRU | M75: 99484101
A76: 73 | B76: 3229 | C76: Musallam Amer Salim Qatan | D76: 482 | E76: 0.4 | F76: =E76*D76 -> 192.8 | H76: =F76-G76 -> 192.8 | I76: 6370978 | J76: 0401002417310016 | K76: BANK MUSCAT | L76: BMUSOMRX | M76: 99485611
A77: 74 | B77: 3230 | C77: Mohammed Abdullah Ali Ghawas | D77: 442.2 | E77: 0.4 | F77: =E77*D77 -> 176.88 | H77: =F77-G77 -> 176.88 | I77: 1968755 | J77: 0406003363090017 | K77: BANK MUSCAT | L77: BMUSOMRX
A78: 75 | B78: 3231 | C78: Tanaf Suhail Ali Hawas Al Aamri | D78: 575.3 | E78: 0.4 | F78: =E78*D78 -> 230.12 | G78: =120.94+97 -> 217.94 | H78: =F78-G78 -> 12.18 | I78: 6203903 | J78: 01010120940001 | K78: BANK DHOFAR | L78: BDOFOMRU | M78: 92535588 | N78: 45779 | O78: 13-2-25
A79: 76 | B79: 3232 | C79: Salim Mohammed Ahmed Al Aamri | D79: 318.3 | E79: 0.4 | F79: =E79*D79 -> 127.32 | G79: =F79 -> 127.32 | H79: =F79-G79 -> 0 | I79: 6387264 | J79: 0500012521101001 | K79: Alizz Islamic Bank | L79: IZZBOMRU | M79: 96661076 | N79: 19-01-25
A80: 77 | B80: 3234 | C80: Masoud Salim Ahmed Alash Al Kathiri | D80: 657.2 | E80: 0.4 | F80: =E80*D80 -> 262.88 | H80: =F80-G80 -> 262.88 | I80: 21834239 | J80: 0406017202280014 | K80: BANK MUSCAT | L80: BMUSOMRX | M80: 98135444
A81: 78 | B81: 3235 | C81: Ahmed Mahad Musallam Amor Jid | D81: 667 | E81: 0.4 | F81: =E81*D81 -> 266.8 | H81: =F81-G81 -> 266.8 | I81: 1234245 | J81: 10600341164086 | K81: NBO | L81: NBOMOMRX | M81: 99487759
A82: 79 | B82: 3236 | C82: Salim Ali Mohammed Hawas Al Amari | D82: 274.2 | E82: 0.4 | F82: =E82*D82 -> 109.68 | G82: =109.17+0.51 -> 109.68 | H82: =F82-G82 -> 0 | I82: 6733333 | J82: 0397060863170013 | K82: BANK MUSCAT | L82: BMUSOMRX | N82: 45662 | O82: 45691
A83: 80 | B83: 3237 | C83: Suhail Salim Mohammed Al Daakari | D83: 717.3 | E83: 0.4 | F83: =E83*D83 -> 286.92 | G83: =286.43+0.49 -> 286.92 | H83: =F83-G83 -> 0 | I83: 873637 | J83: 3109633774500 | K83: OAB | L83: OMABOMRU | M83: 97659667 | N83: 45650 | O83: 45670
A84: 81 | B84: 3238 | C84: Mohammed Ali Said Qatan | D84: 222.2 | E84: 0.4 | F84: =E84*D84 -> 88.88 | H84: =F84-G84 -> 88.88 | I84: 5361082 | J84: 0401011715810012 | K84: BANK MUSCAT | L84: BMUSOMRX | N84: 44621
A85: 82 | B85: 3239 | C85: Ali Salim Bakhit Qatan | D85: 558.3 | E85: 0.4 | F85: =E85*D85 -> 223.32 | G85: =218.86+4.46 -> 223.32 | H85: =F85-G85 -> 0 | I85: 14379226 | J85: 0413009940010018 | K85: BANK MUSCAT | L85: BMUSOMRX | M85: 92385524 | N85: 45663 | O85: 45677
A86: 83 | B86: 3240 | C86: Ali Said Salim Al kathiri | D86: 612.6 | E86: 0.4 | F86: =E86*D86 -> 245.04 | G86: =242.84+2.2 -> 245.04 | H86: =F86-G86 -> 0 | I86: 5622856 | J86: 00510029714001 | K86: BANK NIZWA | L86: BNZWOMRX | M86: 92400553 | N86: 45670 | O86: 45691
A87: 84 | B87: 3241 | C87: Bashar Ahmed Ali Qatan | D87: 308.4 | E87: 0.4 | F87: =E87*D87 -> 123.36 | G87: =F87 -> 123.36 | H87: =F87-G87 -> 0 | I87: 21125518 | J87: 0401040842100016 | K87: BANK MUSCAT | L87: BMUSOMRX | M87: 99508853 | N87: 45691
A88: 85 | B88: 3243 | C88: Asad Ali Ahmed Suhail Aamir Jid | D88: 337 | E88: 0.4 | F88: =E88*D88 -> 134.8 | G88: =133+1.8 -> 134.8 | H88: =F88-G88 -> 0 | I88: 25887256 | J88: 0406056811780029 | K88: BANK MUSCAT | L88: BMUSOMRX | M88: 93271871 | N88: 45664 | O88: DCF-27-01-2025
A89: 86 | B89: 3244 | C89: Mohammed Ali Bakhit Qatan | D89: 270.6 | E89: 0.4 | F89: =E89*D89 -> 108.24 | H89: =F89-G89 -> 108.24 | I89: 19340943 | J89: 0397042697150019 | K89: BANK MUSCAT | L89: BMUSOMRX | M89: 92594446
A90: 87 | B90: 3245 | C90: Musallam Ahmed Mohammed Aldakari Al Kathiri | D90: 242.2 | E90: 0.4 | F90: =E90*D90 -> 96.88 | G90: =93.29+3.59 -> 96.88 | H90: =F90-G90 -> 0 | I90: 996477 | J90: 3109331947500 | K90: OAB | L90: OMABOMRU | M90: 99699068 | N90: 45658 | O90: 45691
A91: 88 | B91: 3246 | C91: Salim Suhail Said Ghawas | D91: 264 | E91: 0.4 | F91: =E91*D91 -> 105.6 | G91: =F91 -> 105.6 | H91: =F91-G91 -> 0 | I91: 662648 | J91: 0397003998840015 | K91: BANK MUSCAT | L91: BMUSOMRX | M91: 99498382 | N91: 45685
A92: 89 | B92: 3247 | C92: Mohammed Suhail Said Ghawas | D92: 299 | E92: 0.4 | F92: =E92*D92 -> 119.6 | G92: =F92 -> 119.6 | H92: =F92-G92 -> 0 | I92: 6457783 | J92: 0406003150110017 | K92: BANK MUSCAT | L92: BMUSOMRX | M92: 92594442 | N92: 45685
A93: 90 | B93: 3248 | C93: Ahmed Suhail Said Ghawas | D93: 264 | E93: 0.4 | F93: =E93*D93 -> 105.6 | H93: =F93-G93 -> 105.6 | I93: 18811851 | J93: 0406040710420017 | K93: BANK MUSCAT | L93: BMUSOMRX | M93: 92597556
A94: 91 | B94: 3249 | C94: Amir Musallam Hadi Salim Al Aamri | D94: 598 | E94: 0.4 | F94: =E94*D94 -> 239.2 | G94: =F94 -> 239.2 | H94: =F94-G94 -> 0 | I94: 24540784 | J94: 0406025047690017 | K94: BANK MUSCAT | L94: BMUSOMRX | M94: 99693301
A95: 92 | B95: 3251 | C95: Mahad Ahmed Mahad Aamir Jid | D95: 345 | E95: 0.4 | F95: =E95*D95 -> 138 | G95: =F95 -> 138 | H95: =F95-G95 -> 0 | I95: 6420681 | J95: 0401002372390013 | K95: BANK MUSCAT | L95: BMUSOMRX | M95: 99588744 | N95: 45685
A96: 93 | B96: 3252 | C96: Said Amer Salim Qatan | D96: 75.5 | E96: 0.4 | F96: =E96*D96 -> 30.2 | G96: =F96 -> 30.2 | H96: =F96-G96 -> 0 | I96: 460074 | J96: 0397003656070021 | K96: BANK MUSCAT | L96: BMUSOMRX | M96: 99292354 | N96: BT 02-02-2025
A97: 94 | B97: 3253 | C97: Abdull Ali Ahmed Suhail Aamir Jid | D97: 644 | E97: 0.4 | F97: =E97*D97 -> 257.6 | G97: =253.78+3.82 -> 257.6 | H97: =F97-G97 -> 0 | I97: 25887589 | J97: 0406061192660017 | K97: BANK MUSCAT | L97: BMUSOMRX | M97: 93995997 | N97: 45655 | O97: DCF-27-01-2025
A98: 95 | B98: 3254 | C98: Said Mohammed Musallam Al Shihri | D98: 563.6 | E98: 0.4 | F98: =E98*D98 -> 225.44 | G98: =222.39+3.05 -> 225.44 | H98: =F98-G98 -> 0 | I98: 6668983 | J98: 0401004242270027 | K98: BANK MUSCAT | L98: BMUSOMRX | M98: 92321002 | N98: 45658 | O98: 45691
A99: 96 | B99: 3255 | C99: Bakhit Ahmed Musallam Khinan Al Shahri | D99: 459 | E99: 0.4 | F99: =E99*D99 -> 183.6 | G99: =181.75+1.85 -> 183.6 | H99: =F99-G99 -> 0 | I99: 5851949 | J99: 1060605003017 | K99: NBO | L99: NBOMOMRX | N99: 45663 | O99: 45691
A100: 97 | B100: 3256 | C100: Salim Said Salim Al Mahri | D100: 2076.1 | E100: 0.4 | F100: =E100*D100 -> 830.44 | G100: =470+358.05+2.39 -> 830.44 | H100: =F100-G100 -> 0 | I100: 6147152 | J100: 70401001815001 | K100: SOHAR ISLAMIC BANK | L100: BSHROMRUISL | M100: 99889778 | N100: dcf feed | O100: 358.05-13-01-25 | P100: 28-01-25
A101: 98 | B101: 3258 | C101: Ahmed Salim Amer Qatan | D101: 885.6 | E101: 0.4 | F101: =E101*D101 -> 354.24 | G101: =351.38 -> 351.38 | H101: =F101-G101 -> 2.86 | I101: 15335306 | J101: 1006708876017 | K101: NBO | L101: NBOMOMRX | M101: 99772646 | N101: 13-02-25
...

Sheet Center-Nov
A1: HAJEEF CAMEL MILK PROCUREMENT FROM 01-Nov-2024 TO 30-Nov-2024
A3: Sr. No. | B3: Farmer Code | C3: Farmer Name | D3: Total Milk Qty | E3: Avg. Rate (OMR/Ltr.) | F3: Amount (OMR) | G3: Paid | H3: BALANCE | I3: ID No. | J3: Bank Account | K3: Bank Name. | L3: SWIFT | M3: Phone No. | N3: remark 2
A4: 1 | B4: 1108 | C4: Bakhit Ahmed Musallam Al kathiri | D4: 812.9 | E4: 0.4 | F4: =E4*D4 -> 325.16 | H4: =F4-G4 -> 325.16 | I4: 15218386 | J4: 0439012124150013 | K4: BANK MUSCAT | L4: BMUSOMRX | M4: 92776884
A5: 2 | B5: 1390 | C5: Bakhait Salim Ahmed Alash Al Kathiri | D5: 250.7 | E5: 0.4 | F5: =E5*D5 -> 100.28 | G5: =96.21 -> 96.21 | H5: =F5-G5 -> 4.07 | I5: 12181822 | J5: 0439014599800023 | K5: BANK MUSCAT | L5: BMUSOMRX | M5: 92442060 | N5: 45691
A6: 3 | B6: 1399 | C6: Mohammed Suhail Ali Hawas Al Aamri | D6: 187.7 | E6: 0.4 | F6: =E6*D6 -> 75.08 | G6: =70.44 -> 70.44 | H6: =F6-G6 -> 4.64 | I6: 10065546 | J6: 3109720870700 | K6: OAB | L6: OMABOMRU | N6: 45691
A7: 4 | B7: 1422 | C7: Mahammed Musallam Ahmed Hwas | D7: 185.2 | E7: 0.4 | F7: =E7*D7 -> 74.08 | G7: =72.63 -> 72.63 | H7: =F7-G7 -> 1.45 | I7: 3280016 | J7: 0397003987550015 | K7: BANK MUSCAT | L7: BMUSOMRX | N7: 45691
A8: 5 | B8: 1424 | C8: Said Ahmed Sabah Ali Badar | D8: 299.9 | E8: 0.4 | F8: =E8*D8 -> 119.96 | G8: =115.42+4.54 -> 119.96 | H8: =F8-G8 -> 0 | I8: 748395 | J8: 01012574607001 | K8: BANK DHOFAR | L8: BDOFOMRU | M8: 93011211 | N8: 45677 | O8: 45902
A9: 6 | B9: 1429 | C9: Said Mohammed Salem Akdha Al Rawas | D9: 349 | E9: 0.4 | F9: =E9*D9 -> 139.6 | H9: =F9-G9 -> 139.6 | I9: 339725 | J9: 0397003785300017 | K9: BANK MUSCAT | L9: BMUSOMRX
A10: 7 | B10: 1431 | C10: Bakhit Mohamed Salim Rawas | D10: 265.9 | E10: 0.4 | F10: =E10*D10 -> 106.36 | G10: =104.02 -> 104.02 | H10: =F10-G10 -> 2.34 | I10: 721445 | J10: 01010850230001 | K10: BANK DHOFAR | L10: BDOFOMRU | M10: 99291700 | N10: 45680
A11: 8 | B11: 1443 | C11: Ahmed Musallam Ahmed Al Kathiri | D11: 944.6 | E11: 0.4 | F11: =E11*D11 -> 377.84 | H11: =F11-G11 -> 377.84 | I11: 6026992 | J11: 0439017196260028 | K11: BANK MUSCAT | L11: BMUSOMRX | M11: 95863774
A12: 9 | B12: 1452 | C12: Sulaim Said Mohammed Hawas Al Aamri | D12: 327.7 | E12: 0.4 | F12: =E12*D12 -> 131.08 | G12: =127.24 -> 127.24 | H12: =F12-G12 -> 3.84 | I12: 20917176 | J12: 0406012189810015 | K12: BANK MUSCAT | L12: BMUSOMRX | M12: 95863774 | N12: 45779
A13: 10 | B13: 1458 | C13: Salim Mustahil Jamaan Al Shakl Al kathiri | D13: 260.3 | E13: 0.4 | F13: =E13*D13 -> 104.12 | H13: =F13-G13 -> 104.12 | I13: 77628 | J13: 01012583986001 | K13: BANK DHOFAR | L13: BDOFOMRU | M13: 99275608
A14: 11 | B14: 1461 | C14: Suhail Said Ali Bait said | D14: 259.8 | E14: 0.4 | F14: =E14*D14 -> 103.92 | H14: =F14-G14 -> 103.92 | I14: 6828806 | J14: 0396003267730012 | K14: BANK MUSCAT | L14: BMUSOMRX | M14: 92330321
A15: 12 | B15: 1465 | C15: Mahad Salim Zaed Baitsaid | D15: 266.7 | E15: 0.4 | F15: =E15*D15 -> 106.68 | G15: =F15 -> 106.68 | H15: =F15-G15 -> 0 | I15: 757601 | J15: 1023113274001 | K15: NBO | L15: NBOMOMRX | M15: 99892131 | N15: dcF-02-02-2025
A16: 13 | B16: 1474 | C16: Mohamed Salam Amer Al Yafee | D16: 614.7 | E16: 0.4 | F16: =E16*D16 -> 245.88 | H16: =F16-G16 -> 245.88 | I16: 4603773 | J16: 01041185194001 | K16: BANK DHOFAR | L16: BDOFOMRU | M16: 98820843
A17: 14 | B17: 1479 | C17: Ahmed Amer Said Baitsaid | D17: 263.2 | E17: 0.4 | F17: =E17*D17 -> 105.28 | H17: =F17-G17 -> 105.28 | I17: 5217726 | J17: 0396003219770029 | K17: BANK MUSCAT | L17: BMUSOMRX | M17: 92610234
A18: 15 | B18: 1483 | C18: Saed Ali Ahmed Al Kathiri | D18: 678.4 | E18: 0.4 | F18: =E18*D18 -> 271.36 | G18: =270.82 -> 270.82 | H18: =F18-G18 -> 0.54 | I18: 1567826 | J18: 1083724895017 | K18: NBO | L18: NBOMOMRX | M18: 98532884 | N18: 45691
A19: 16 | B19: 1486 | C19: Mosoud Ali Salim Al Kathiri | D19: 286.8 | E19: 0.4 | F19: =E19*D19 -> 114.72 | G19: =110.53 -> 110.53 | H19: =F19-G19 -> 4.19 | I19: 22792564 | J19: 0401064266530014 | K19: BANK MUSCAT | L19: BMUSOMRX | N19: 45685
A20: 17 | B20: 1762 | C20: MUSALLAM HASAN ALI BAIT SAID | D20: 900 | E20: 0.4 | F20: =E20*D20 -> 360 | G20: =358.65 -> 358.65 | H20: =F20-G20 -> 1.35 | I20: 1409527 | J20: 0397003183710017 | K20: Bank Muscat | L20: BMUSOMRX | N20: 45677
A21: 18 | B21: 1792 | C21: Musallam Bakhit Salim Al Aamri | D21: 240.8 | E21: 0.4 | F21: =E21*D21 -> 96.32 | H21: =F21-G21 -> 96.32 | I21: 9545556 | J21: 01011373210001 | K21: BANK DHOFAR | L21: BDOFOMRU
A22: 19 | B22: 3009 | C22: Ahmed Salim Bakhit Qatan | D22: 56.8 | E22: 0.4 | F22: =E22*D22 -> 22.72 | H22: =F22-G22 -> 22.72 | I22: 1448391 | J22: 3109628132500 | K22: OAB | L22: OMABOMRU | M22: 99100144
A23: 20 | B23: 3012 | C23: Salim Suhail Ali Al Kathiri | D23: 267.6 | E23: 0.4 | F23: =E23*D23 -> 107.04 | G23: =101.12+5.92 -> 107.04 | H23: =F23-G23 -> 0 | I23: 5634422 | J23: 0406059374210012 | K23: BANK MUSCAT | L23: BMUSOMRX | M23: 96922118 | N23: 45677 | O23: 45993
A24: 21 | B24: 3014 | C24: Ahmed Mohammed Salim Al Barami | D24: 214.3 | E24: 0.4 | F24: =E24*D24 -> 85.72 | G24: =84.43 -> 84.43 | H24: =F24-G24 -> 1.29 | I24: 648421 | J24: 3129711924500 | K24: OAB | L24: OMABOMRU | M24: 98815665 | N24: 45685
A25: 22 | B25: 3015 | C25: Ahmed Mohammed Faraj Al Kathiri | D25: 252.7 | E25: 0.4 | F25: =E25*D25 -> 101.08 | H25: =F25-G25 -> 101.08 | I25: 5753033 | J25: 0439058732890011 | K25: BANK MUSCAT | L25: BMUSOMRX | M25: 92838405
A26: 23 | B26: 3018 | C26: Bakhit Salim Bakhit Qatan | D26: 189.3 | E26: 0.4 | F26: =E26*D26 -> 75.72 | G26: =71.44 -> 71.44 | H26: =F26-G26 -> 4.28 | I26: 1528087 | J26: 0397004184300024 | K26: BANK MUSCAT | L26: BMUSOMRX | N26: 45679
A27: 24 | B27: 3020 | C27: Bakhit Ali Salim Qatan | D27: 370.8 | E27: 0.4 | F27: =E27*D27 -> 148.32 | G27: =F27 -> 148.32 | H27: =F27-G27 -> 0 | I27: 5418422 | J27: 0401002342630017 | K27: BANK MUSCAT | L27: BMUSOMRX | M27: 99495434 | N27: 45677
A28: 25 | B28: 3022 | C28: Hussein Masoud Aubad Al Kathiri | D28: 648.6 | E28: 0.4 | F28: =E28*D28 -> 259.44 | G28: =257.95 -> 257.95 | H28: =F28-G28 -> 1.49 | I28: 5360253 | J28: 1060656310017 | K28: NBO | L28: NBOMOMRX | M28: 99257989 | N28: 45685
A29: 26 | B29: 3025 | C29: Musallam Salim Mahad Qatan | D29: 512.4 | E29: 0.4 | F29: =E29*D29 -> 204.96 | H29: =F29-G29 -> 204.96 | I29: 7542172 | J29: 0401002461080028 | K29: BANK MUSCAT | L29: BMUSOMRX
A30: 27 | B30: 3026 | C30: Amer Salem Ahmed Qatan | D30: 264.1 | E30: 0.4 | F30: =E30*D30 -> 105.64 | H30: =F30-G30 -> 105.64 | I30: 7033819 | J30: 0401003532620025 | K30: BANK MUSCAT | L30: BMUSOMRX | M30: 92256918
A31: 28 | B31: 3027 | C31: Salim Ahmed Mahad Aamir Jid | D31: 551 | E31: 0.4 | F31: =E31*D31 -> 220.4 | G31: =216.17 -> 216.17 | H31: =F31-G31 -> 4.23 | I31: 6420643 | J31: 01011362595002 | K31: BANK DHOFAR | L31: BDOFOMRU | M31: 92288434 | N31: 45685
A32: 29 | B32: 3030 | C32: Salim Ahmed Salim Amer Jid | D32: 282 | E32: 0.4 | F32: =E32*D32 -> 112.8 | G32: =111.25 -> 111.25 | H32: =F32-G32 -> 1.55 | I32: 6021175 | J32: 0401050718800013 | K32: BANK MUSCAT | L32: BMUSOMRX | M32: 91716888 | N32: 45691
A33: 30 | B33: 3038 | C33: Said Ahmed Mahad Qatan | D33: 551 | E33: 0.4 | F33: =E33*D33 -> 220.4 | G33: =219.15+1.25 -> 220.4 | H33: =F33-G33 -> 0 | I33: 7976 | J33: 3109016888700 | K33: OAB | L33: OMABOMRU | M33: 98920007 | N33: 45670 | O33: 45932
A34: 31 | B34: 3043 | C34: Said Aubad Ali Ghawas | D34: 240.8 | E34: 0.4 | F34: =E34*D34 -> 96.32 | G34: =95.11 -> 95.11 | H34: =F34-G34 -> 1.21 | I34: 396336 | J34: 0397003933630013 | K34: BANK MUSCAT | L34: BMUSOMRX | M34: 99498844 | N34: 45932
A35: 32 | B35: 3058 | C35: Ali Bakhit Ahmed Qatan | D35: 908.5 | E35: 0.4 | F35: =E35*D35 -> 363.4 | H35: =F35-G35 -> 363.4 | I35: 965148 | J35: 3129376165700 | K35: OAB | L35: OMABOMRU | M35: 90980121
A36: 33 | B36: 3070 | C36: Mohamed Ahmed Suhail Qatan | D36: 840.6 | E36: 0.4 | F36: =E36*D36 -> 336.24 | G36: =F36 -> 336.24 | H36: =F36-G36 -> 0 | I36: 1918001 | J36: 0397004395550019 | K36: BANK MUSCAT | L36: BMUSOMRX | M36: 92863640 | N36: 45670
A37: 34 | B37: 3072 | C37: Mohammed Salim Said Al Barami | D37: 266 | E37: 0.4 | F37: =E37*D37 -> 106.4 | H37: =F37-G37 -> 106.4 | I37: 993077 | J37: 250094968001 | K37: HSBC | L37: BBMEOMRX | M37: 92252981
A38: 35 | B38: 3077 | C38: Mohammed Ali Suhail Qatan | D38: 506.9 | E38: 0.4 | F38: =E38*D38 -> 202.76 | H38: =F38-G38 -> 202.76 | I38: 21978752 | J38: 0396041232890032 | K38: BANK MUSCAT | L38: BMUSOMRX | M38: 90833336
A39: 36 | B39: 3081 | C39: Musallam Bakhit Masoud Qatan | D39: 360 | E39: 0.4 | F39: =E39*D39 -> 144 | G39: =F39 -> 144 | H39: =F39-G39 -> 0 | I39: 21219868 | J39: 010010201414 | K39: Bank Sohar | L39: BSHROMRU | M39: 93288777 | N39: DCF Feed
A40: 37 | B40: 3089 | C40: Yhaya Musallam Said Qatan | D40: 211.1 | E40: 0.4 | F40: =E40*D40 -> 84.44 | G40: =82.71 -> 82.71 | H40: =F40-G40 -> 1.73 | I40: 18790484 | J40: 0401016503450018 | K40: BANK MUSCAT | L40: BMUSOMRX | N40: 45677
A41: 38 | B41: 3093 | C41: Bakhit Amer Salem Qatan | D41: 358 | E41: 0.4 | F41: =E41*D41 -> 143.2 | H41: =F41-G41 -> 143.2 | I41: 6361035 | J41: 00510034969002 | K41: BANK NIZWA | L41: BNZWOMRX | M41: 99497919
A42: 39 | B42: 3094 | C42: Ali Ahmed Aubad Jamaan Al Kathiri | D42: 702.4 | E42: 0.4 | F42: =E42*D42 -> 280.96 | H42: =F42-G42 -> 280.96 | I42: 26343985 | J42: 0304024501570012 | K42: BANK MUSCAT | L42: BMUSOMRX | M42: 93327740
A43: 40 | B43: 3100 | C43: Salim Ahmed Said Tabuk | D43: 1140 | E43: 0.4 | F43: =E43*D43 -> 456 | H43: =F43-G43 -> 456 | I43: 1278615 | J43: 0426003863310028 | K43: NBO | L43: BMUSOMRX | M43: 99806386
A44: 41 | B44: 3101 | C44: Salim Said Suhail Qatan | D44: 300.5 | E44: 0.4 | F44: =E44*D44 -> 120.2 | H44: =F44-G44 -> 120.2 | I44: 6767598 | J44: 0401002332700028 | K44: BANK MUSCAT | L44: BMUSOMRX | M44: 99100344
A45: 42 | B45: 3102 | C45: Mohammed Salim Amer Qatan | D45: 515.1 | E45: 0.4 | F45: =E45*D45 -> 206.04 | G45: =200.06+5.98 -> 206.04 | H45: =F45-G45 -> 0 | I45: 5916838 | J45: 0317002509980029 | K45: BANK MUSCAT | L45: BMUSOMRX | M45: 91917520 | N45: 45685 | O45: 45932
A46: 43 | B46: 3119 | C46: Mohammed Ahmed Suhail Mahad Qatan | D46: 798 | E46: 0.4 | F46: =E46*D46 -> 319.2 | G46: =316.73 -> 316.73 | H46: =F46-G46 -> 2.47 | I46: 5903061 | J46: 0401016956230027 | K46: BANK MUSCAT | L46: BMUSOMRX | M46: 91904279 | N46: 45685
A47: 44 | B47: 3122 | C47: Khalid Ahmed Salim Amer Jid Al Mahri | D47: 285 | E47: 0.4 | F47: =E47*D47 -> 114 | H47: =F47-G47 -> 114 | I47: 12415718 | J47: 0401050718800013 | K47: BANK MUSCAT | L47: BMUSOMRX | M47: 99481799
A48: 45 | B48: 3136 | C48: Ghazi Salim Ahmed Al Kathiri | D48: 420.5 | E48: 0.4 | F48: =E48*D48 -> 168.2 | G48: =166.79 -> 166.79 | H48: =F48-G48 -> 1.41 | I48: 183498 | J48: 01011238092002 | K48: BANK DHOFAR | L48: BDOFOMRU | M48: 99481314 | N48: 45691
A49: 46 | B49: 3178 | C49: Abdul Sallam Ahmed Abdullah Al Abbadi Al Rawas | D49: 1914 | E49: 0.4 | F49: =E49*D49 -> 765.6 | H49: =F49-G49 -> 765.6 | I49: 1511754 | J49: 3109061950500 | K49: OAB | L49: OMABOMRU | M49: 99495933
A50: 47 | B50: 3199 | C50: Ali Musallam Ahmed Tabuk | D50: 262 | E50: 0.4 | F50: =E50*D50 -> 104.8 | H50: =F50-G50 -> 104.8 | I50: 5168327 | J50: 0397004227360018 | K50: BANK MUSCAT | L50: BMUSOMRX | M50: 98066833
A51: 48 | B51: 3200 | C51: Ahmed Said Ahmed Qutan | D51: 5.6 | E51: 0.4 | F51: =E51*D51 -> 2.24 | G51: =0.4 -> 0.4 | H51: =F51-G51 -> 1.84 | I51: 21947578 | J51: 0401044694220018 | K51: BANK MUSCAT | L51: BMUSOMRX | N51: 45677
A52: 49 | B52: 3201 | C52: Ali Salim Said Qatan | D52: 240.9 | E52: 0.4 | F52: =E52*D52 -> 96.36 | H52: =F52-G52 -> 96.36 | I52: 7048401 | J52: 01041090275001 | K52: BANK DHOFAR | L52: BDOFOMRU
A53: 50 | B53: 3202 | C53: Salim Ahmed Ali Qatan | D53: 259.5 | E53: 0.4 | F53: =E53*D53 -> 103.8 | H53: =F53-G53 -> 103.8 | I53: 5197371 | J53: 0132906010084010 | K53: BANK MUSCAT | L53: BMUSOMRX | M53: 93889732
A54: 51 | B54: 3203 | C54: Musallam Salim Amir Said Qatan | D54: 369.1 | E54: 0.4 | F54: =E54*D54 -> 147.64 | G54: =146.58+1.06 -> 147.64 | H54: =F54-G54 -> 0 | I54: 23215097 | J54: 0401047625040018 | K54: BANK MUSCAT | L54: BMUSOMRX | N54: 45685 | O54: 45932
A55: 52 | B55: 3204 | C55: Hassan Suhail Ahmed Said Qatan | D55: 260.2 | E55: 0.4 | F55: =E55*D55 -> 104.08 | H55: =F55-G55 -> 104.08 | I55: 24958926 | J55: 0426060858570018 | K55: BANK MUSCAT | L55: BMUSOMRX | M55: 99312225
A56: 53 | B56: 3207 | C56: Said Ali Ahmed Al Katheri | D56: 625.4 | E56: 0.4 | F56: =E56*D56 -> 250.16 | H56: =F56-G56 -> 250.16 | I56: 11940175 | J56: 0406020751730014 | K56: BANK MUSCAT | L56: BMUSOMRX | M56: 98138748
A57: 54 | B57: 3208 | C57: Ali Mahad Said Qatan | D57: 538.7 | E57: 0.4 | F57: =E57*D57 -> 215.48 | G57: =214.92 -> 214.92 | H57: =F57-G57 -> 0.56 | I57: 1742664 | J57: 001010070151 | K57: BANK SOHAR | L57: BSHROMRU | M57: 99482598 | N57: 45691
A58: 55 | B58: 3209 | C58: Said Suhail Ali Al Kathiri | D58: 284.2 | E58: 0.4 | F58: =E58*D58 -> 113.68 | G58: =111.41+2.27 -> 113.68 | H58: =F58-G58 -> 0 | I58: 5634328 | J58: 0397016698910016 | K58: BANK MUSCAT | L58: BMUSOMRX | M58: 92283227 | N58: 45677 | O58: 45993
A59: 56 | B59: 3210 | C59: Ahmed Said Mubarak Al Zawamri | D59: 551 | E59: 0.4 | F59: =E59*D59 -> 220.4 | G59: =216.75+3.65 -> 220.4 | H59: =F59-G59 -> 0 | I59: 45419 | J59: 0401002467120013 | K59: BANK MUSCAT | L59: BMUSOMRX | M59: 90101070 | N59: 45664 | O59: 45993
A60: 57 | B60: 3211 | C60: Salim Mohammed Musallam Al Baraami | D60: 253.1 | E60: 0.4 | F60: =E60*D60 -> 101.24 | H60: =F60-G60 -> 101.24 | I60: 9927207 | J60: 01010941305001 | K60: BANK DHOFAR | L60: BDOFOMRU | N60: 44986
A61: 58 | B61: 3212 | C61: Mohammed Said Mahad Qatan | D61: 751.9 | E61: 0.4 | F61: =E61*D61 -> 300.76 | G61: =299.63 -> 299.63 | H61: =F61-G61 -> 1.13 | I61: 804443 | J61: 050170299001 | K61: HSBC | L61: BBMEOMRX | M61: 99483202 | N61: 45673
A62: 59 | B62: 3213 | C62: Ali Ahmed Suhail Qatan | D62: 636.3 | E62: 0.4 | F62: =E62*D62 -> 254.52 | H62: =F62-G62 -> 254.52 | I62: 2594336 | J62: 0397004383920015 | K62: BANK MUSCAT | L62: BMUSOMRX | M62: 71773005
A63: 60 | B63: 3214 | C63: Salim Musallam Ahmed Tabouk | D63: 539.1 | E63: 0.4 | F63: =E63*D63 -> 215.64 | H63: =F63-G63 -> 215.64 | I63: 5168262 | J63: 01041249912001 | K63: BANK DHOFAR | L63: BDOFOMRU | M63: 99895383
A64: 61 | B64: 3215 | C64: Suhail Awadh Salim Hawas Al Aamri | D64: 563 | E64: 0.4 | F64: =E64*D64 -> 225.2 | G64: =224.36 -> 224.36 | H64: =F64-G64 -> 0.84 | I64: 11684091 | J64: 01010853900001 | K64: BANK DHOFAR | L64: BDOFOMRU | N64: 13-2-25
A65: 62 | B65: 3216 | C65: Salim Ali said Al Masahli | D65: 769.4 | E65: 0.4 | F65: =E65*D65 -> 307.76 | G65: =304.07 -> 304.07 | H65: =F65-G65 -> 3.69 | I65: 18715567 | J65: 0406045085100027 | K65: BANK MUSCAT | L65: BMUSOMRX | M65: 77279900 | N65: 45691
A66: 63 | B66: 3217 | C66: Hassan Musallam Ali Qatan | D66: 260.3 | E66: 0.4 | F66: =E66*D66 -> 104.12 | H66: =F66-G66 -> 104.12 | I66: 1568196 | J66: 00510059623001 | K66: BANK NIZWA | L66: BNZWOMRX | M66: 99494635
A67: 64 | B67: 3219 | C67: Said Salim Ali Hawas Al Aamri | D67: 828.8 | E67: 0.4 | F67: =E67*D67 -> 331.52 | G67: =180.6315035+145.5 -> 326.1315 | H67: =F67-G67 -> 5.3884965 | I67: 12398617 | J67: 0406003141690019 | K67: BANK MUSCAT | L67: BMUSOMRX | N67: 45677 | O67: 45685 | P67: 13-2-25
A68: 65 | B68: 3220 | C68: Adnan Mohammed Said Bait Said | D68: 551 | E68: 0.4 | F68: =E68*D68 -> 220.4 | H68: =F68-G68 -> 220.4 | I68: 5348311 | J68: 01011445808001 | K68: BANK DHOFAR | L68: BDOFOMRU | M68: 96313636
A69: 66 | B69: 3221 | C69: Musallam Mohammed Salim Al Barami | D69: 266 | E69: 0.4 | F69: =E69*D69 -> 106.4 | H69: =F69-G69 -> 106.4 | I69: 13362673 | J69: 0401003471060021 | K69: BANK MUSCAT | L69: BMUSOMRX | M69: 92665337
A70: 67 | B70: 3222 | C70: Mohammed Ahmed Bakhit Qatan | D70: 405.3 | E70: 0.4 | F70: =E70*D70 -> 162.12 | G70: =F70 -> 162.12 | H70: =F70-G70 -> 0 | I70: 18091329 | J70: 01011448559002 | K70: BANK DHOFAR | L70: BDOFOMRU | M70: 92197820 | N70: 45662
A71: 68 | B71: 3223 | C71: Salim Said Mustahil Al Kathiri | D71: 258.9 | E71: 0.4 | F71: =E71*D71 -> 103.56 | H71: =F71-G71 -> 103.56 | I71: 5334914 | J71: 00510087464001 | K71: BANK NIZWA | L71: BNZWOMRX | M71: 98800996
A72: 69 | B72: 3224 | C72: Salim Said Salim Qatan | D72: 228 | E72: 0.4 | F72: =E72*D72 -> 91.2 | G72: =89.88 -> 89.88 | H72: =F72-G72 -> 1.32 | I72: 2066756 | J72: 0439002422440029 | K72: BANK MUSCAT | L72: BMUSOMRX | M72: 95316025 | N72: 45691
A73: 70 | B73: 3225 | C73: Mohamed Ahmed Salam Alamri | D73: 264.4 | E73: 0.4 | F73: =E73*D73 -> 105.76 | G73: =F73 -> 105.76 | H73: =F73-G73 -> 0 | I73: 798637 | J73: 0397004248490019 | K73: BANK MUSCAT | L73: BMUSOMRX | N73: 45693
A74: 71 | B74: 3227 | C74: Ahmed Ali Suhail ALAamri | D74: 241.7 | E74: 0.4 | F74: =E74*D74 -> 96.68 | G74: =95.62 -> 95.62 | H74: =F74-G74 -> 1.06 | I74: 15214649 | J74: 0406003835930033 | K74: BANK MUSCAT | L74: BMUSOMRX | M74: 92171914 | N74: 45691
A75: 72 | B75: 3228 | C75: Ali Amer Salim Qatan | D75: 532 | E75: 0.4 | F75: =E75*D75 -> 212.8 | H75: =F75-G75 -> 212.8 | I75: 1307775 | J75: 01011440583003 | K75: BANK DHOFAR | L75: BDOFOMRU | M75: 99484101
A76: 73 | B76: 3229 | C76: Musallam Amer Salim Qatan | D76: 410 | E76: 0.4 | F76: =E76*D76 -> 164 | H76: =F76-G76 -> 164 | I76: 6370978 | J76: 0401002417310016 | K76: BANK MUSCAT | L76: BMUSOMRX | M76: 99485611
A77: 74 | B77: 3230 | C77: Mohammed Abdullah Ali Ghawas | D77: 364.7 | E77: 0.4 | F77: =E77*D77 -> 145.88 | H77: =F77-G77 -> 145.88 | I77: 1968755 | J77: 0406003363090017 | K77: BANK MUSCAT | L77: BMUSOMRX
A78: 75 | B78: 3231 | C78: Tanaf Suhail Ali Hawas Al Aamri | D78: 470.4 | E78: 0.4 | F78: =E78*D78 -> 188.16 | H78: =F78-G78 -> 188.16 | I78: 6203903 | J78: 01010120940001 | K78: BANK DHOFAR | L78: BDOFOMRU | M78: 92535588
A79: 76 | B79: 3232 | C79: Salim Mohammed Ahmed Al Aamri | D79: 243.6 | E79: 0.4 | F79: =E79*D79 -> 97.44 | G79: =F79 -> 97.44 | H79: =F79-G79 -> 0 | I79: 6387264 | J79: 0500012521101001 | K79: Alizz Islamic Bank | L79: IZZBOMRU | M79: 96661076 | N79: 45963
A80: 77 | B80: 3234 | C80: Masoud Salim Ahmed Alash Al Kathiri | D80: 542.5 | E80: 0.4 | F80: =E80*D80 -> 217 | H80: =F80-G80 -> 217 | I80: 21834239 | J80: 0406017202280014 | K80: BANK MUSCAT | L80: BMUSOMRX | M80: 98135444
A81: 78 | B81: 3235 | C81: Ahmed Mahad Musallam Amor Jid | D81: 551 | E81: 0.4 | F81: =E81*D81 -> 220.4 | H81: =F81-G81 -> 220.4 | I81: 1234245 | J81: 10600341164086 | K81: NBO | L81: NBOMOMRX | M81: 99487759
A82: 79 | B82: 3236 | C82: Salim Ali Mohammed Hawas Al Amari | D82: 209.4 | E82: 0.4 | F82: =E82*D82 -> 83.76 | G82: =81.94 -> 81.94 | H82: =F82-G82 -> 1.82 | I82: 6733333 | J82: 0397060863170013 | K82: BANK MUSCAT | L82: BMUSOMRX | N82: 45691
A83: 80 | B83: 3237 | C83: Suhail Salim Mohammed Al Daakari | D83: 581.3 | E83: 0.4 | F83: =E83*D83 -> 232.52 | G83: =232.31+0.21 -> 232.52 | H83: =F83-G83 -> 0 | I83: 873637 | J83: 3109633774500 | K83: OAB | L83: OMABOMRU | M83: 97659667 | N83: 45670 | O83: 45685
A84: 81 | B84: 3238 | C84: Mohammed Ali Said Qatan | D84: 247 | E84: 0.4 | F84: =E84*D84 -> 98.8 | H84: =F84-G84 -> 98.8 | I84: 5361082 | J84: 0401011715810012 | K84: BANK MUSCAT | L84: BMUSOMRX
A85: 82 | B85: 3239 | C85: Ali Salim Bakhit Qatan | D85: 469.7 | E85: 0.4 | F85: =E85*D85 -> 187.88 | G85: =F85 -> 187.88 | H85: =F85-G85 -> 0 | I85: 14379226 | J85: 0413009940010018 | K85: BANK MUSCAT | L85: BMUSOMRX | M85: 92385524 | N85: 45677 | O85: .260 will deduct from 12-2024
A86: 83 | B86: 3240 | C86: Ali Said Salim Al kathiri | D86: 481.7 | E86: 0.4 | F86: =E86*D86 -> 192.68 | G86: =191.8 -> 191.8 | H86: =F86-G86 -> 0.88 | I86: 5622856 | J86: 00510029714001 | K86: BANK NIZWA | L86: BNZWOMRX | M86: 92400553 | N86: 45691
A87: 84 | B87: 3241 | C87: Bashar Ahmed Ali Qatan | D87: 269.5 | E87: 0.4 | F87: =E87*D87 -> 107.8 | G87: =105.17 -> 105.17 | H87: =F87-G87 -> 2.63 | I87: 21125518 | J87: 0401040842100016 | K87: BANK MUSCAT | L87: BMUSOMRX | M87: 99508853 | N87: 45691
A88: 85 | B88: 3243 | C88: Asad Ali Ahmed Suhail Aamir Jid | D88: 261.1 | E88: 0.4 | F88: =E88*D88 -> 104.44 | G88: =F88 -> 104.44 | H88: =F88-G88 -> 0 | I88: 25887256 | J88: 0406056811780029 | K88: BANK MUSCAT | L88: BMUSOMRX | M88: 93271871 | N88: DCF-27-01-2025
A89: 86 | B89: 3244 | C89: Mohammed Ali Bakhit Qatan | D89: 261.6 | E89: 0.4 | F89: =E89*D89 -> 104.64 | H89: =F89-G89 -> 104.64 | I89: 19340943 | J89: 0397042697150019 | K89: BANK MUSCAT | L89: BMUSOMRX | M89: 92594446
A90: 87 | B90: 3245 | C90: Musallam Ahmed Mohammed Aldakari Al Kathiri | D90: 192.5 | E90: 0.4 | F90: =E90*D90 -> 77 | G90: =74.01 -> 74.01 | H90: =F90-G90 -> 2.99 | I90: 996477 | J90: 3109331947500 | K90: OAB | L90: OMABOMRU | M90: 99699068 | N90: 45691
A91: 88 | B91: 3246 | C91: Salim Suhail Said Ghawas | D91: 228 | E91: 0.4 | F91: =E91*D91 -> 91.2 | G91: =87.97 -> 87.97 | H91: =F91-G91 -> 3.23 | I91: 662648 | J91: 0397003998840015 | K91: BANK MUSCAT | L91: BMUSOMRX | M91: 99498382 | N91: 45685
A92: 89 | B92: 3247 | C92: Mohammed Suhail Said Ghawas | D92: 247 | E92: 0.4 | F92: =E92*D92 -> 98.8 | G92: =98.24 -> 98.24 | H92: =F92-G92 -> 0.56 | I92: 6457783 | J92: 0406003150110017 | K92: BANK MUSCAT | L92: BMUSOMRX | M92: 92594442 | N92: 45685
A93: 90 | B93: 3248 | C93: Ahmed Suhail Said Ghawas | D93: 216 | E93: 0.4 | F93: =E93*D93 -> 86.4 | H93: =F93-G93 -> 86.4 | I93: 18811851 | J93: 0406040710420017 | K93: BANK MUSCAT | L93: BMUSOMRX | M93: 92597556
A94: 91 | B94: 3249 | C94: Amir Musallam Hadi Salim Al Aamri | D94: 491.9 | E94: 0.4 | F94: =E94*D94 -> 196.76 | G94: =F94 -> 196.76 | H94: =F94-G94 -> 0 | I94: 24540784 | J94: 0406025047690017 | K94: BANK MUSCAT | L94: BMUSOMRX | M94: 99693301 | N94: DCF-27-01-2025
A95: 92 | B95: 3251 | C95: Mahad Ahmed Mahad Aamir Jid | D95: 285 | E95: 0.4 | F95: =E95*D95 -> 114 | G95: =109.37 -> 109.37 | H95: =F95-G95 -> 4.63 | I95: 6420681 | J95: 0401002372390013 | K95: BANK MUSCAT | L95: BMUSOMRX | M95: 99588744 | N95: 45685
A96: 93 | B96: 3252 | C96: Said Amer Salim Qatan | D96: 112.4 | E96: 0.4 | F96: =E96*D96 -> 44.96 | G96: =F96 -> 44.96 | H96: =F96-G96 -> 0 | I96: 460074 | J96: 0397003656070021 | K96: BANK MUSCAT | L96: BMUSOMRX | M96: 99292354 | N96: BT 02-02-2025
A97: 94 | B97: 3253 | C97: Abdull Ali Ahmed Suhail Aamir Jid | D97: 519 | E97: 0.4 | F97: =E97*D97 -> 207.6 | G97: =F97 -> 207.6 | H97: =F97-G97 -> 0 | I97: 25887589 | J97: 0406061192660017 | K97: BANK MUSCAT | L97: BMUSOMRX | M97: 93995997 | N97: DCF-27-01-2025
A98: 95 | B98: 3254 | C98: Said Mohammed Musallam Al Shihri | D98: 493.5 | E98: 0.4 | F98: =E98*D98 -> 197.4 | G98: =195.8 -> 195.8 | H98: =F98-G98 -> 1.6 | I98: 6668983 | J98: 0401004242270027 | K98: BANK MUSCAT | L98: BMUSOMRX | M98: 92321002 | N98: 45691
A99: 96 | B99: 3255 | C99: Bakhit Ahmed Musallam Khinan Al Shahri | D99: 372.8 | E99: 0.4 | F99: =E99*D99 -> 149.12 | G99: =148.3 -> 148.3 | H99: =F99-G99 -> 0.82 | I99: 5851949 | J99: 1060605003017 | K99: NBO | L99: NBOMOMRX | N99: 45691
A100: 97 | B100: 3256 | C100: Salim Said Salim Al Mahri | D100: 1740.7 | E100: 0.4 | F100: =E100*D100 -> 696.28 | G100: =467.61+228.67 -> 696.28 | H100: =F100-G100 -> 0 | I100: 6147152 | J100: 70401001815001 | K100: SOHAR ISLAMIC BANK | L100: BSHROMRUISL | M100: 99889778 | N100: 28-01-25 | O100: 45932
A101: 98 | B101: 3258 | C101: Ahmed Salim Amer Qatan | D101: 747.9 | E101: 0.4 | F101: =E101*D101 -> 299.16 | H101: =F101-G101 -> 299.16 | I101: 15335306 | J101: 1006708876017 | K101: NBO | L101: NBOMOMRX | M101: 99772646
...

Sheet center-dec
A1: HAJEEF CAMEL MILK PROCUREMENT FROM 01-Nov-2024 TO 30-Nov-2024
A3: Sr. No. | B3: Farmer Code | C3: Farmer Name | D3: Total Milk Qty | E3: Avg. Rate (OMR/Ltr.) | F3: Amount (OMR) | G3: Paid | H3: Balance | I3: ID | J3: Remark
A4: 1 | B4: 1108 | C4: Bakhit Ahmed Musallam Al kathiri | D4: 957.8 | E4: 0.4 | F4: =E4*D4 -> 383.12 | H4: =F4-G4 -> 383.12 | I4: 15218386
A5: 2 | B5: 1390 | C5: Bakhait Salim Ahmed Alash Al Kathiri | D5: 342.4 | E5: 0.4 | F5: =E5*D5 -> 136.96 | H5: =F5-G5 -> 136.96 | I5: 12181822
A6: 3 | B6: 1399 | C6: Mohammed Suhail Ali Hawas Al Aamri | D6: 262.8 | E6: 0.4 | F6: =E6*D6 -> 105.12 | H6: =F6-G6 -> 105.12 | I6: 10065546
A7: 4 | B7: 1422 | C7: Mahammed Musallam Ahmed Hwas | D7: 213.7 | E7: 0.4 | F7: =E7*D7 -> 85.48 | H7: =F7-G7 -> 85.48 | I7: 3280016
A8: 5 | B8: 1424 | C8: Said Ahmed Sabah Ali Badar | D8: 342.8 | E8: 0.4 | F8: =E8*D8 -> 137.12 | G8: =136.11+1.01 -> 137.12 | H8: =F8-G8 -> 0 | I8: 748395 | J8: 45902 | K8: 25-2-25
A9: 6 | B9: 1429 | C9: Said Mohammed Salem Akdha Al Rawas | D9: 363 | E9: 0.4 | F9: =E9*D9 -> 145.2 | H9: =F9-G9 -> 145.2 | I9: 339725
A10: 7 | B10: 1431 | C10: Bakhit Mohamed Salim Rawas | D10: 338.7 | E10: 0.4 | F10: =E10*D10 -> 135.48 | G10: =133.46 -> 133.46 | H10: =F10-G10 -> 2.02 | I10: 721445 | J10: 20-2-25
A11: 8 | B11: 1443 | C11: Ahmed Musallam Ahmed Al Kathiri | D11: 1204.1 | E11: 0.4 | F11: =E11*D11 -> 481.64 | H11: =F11-G11 -> 481.64 | I11: 6026992
A12: 9 | B12: 1452 | C12: Sulaim Said Mohammed Hawas Al Aamri | D12: 305.2 | E12: 0.4 | F12: =E12*D12 -> 122.08 | H12: =F12-G12 -> 122.08 | I12: 20917176
A13: 10 | B13: 1458 | C13: Salim Mustahil Jamaan Al Shakl Al kathiri | D13: 316.2 | E13: 0.4 | F13: =E13*D13 -> 126.48 | H13: =F13-G13 -> 126.48 | I13: 77628
A14: 11 | B14: 1461 | C14: Suhail Said Ali Bait said | D14: 326.5 | E14: 0.4 | F14: =E14*D14 -> 130.6 | H14: =F14-G14 -> 130.6 | I14: 6828806
A15: 12 | B15: 1465 | C15: Mahad Salim Zaed Baitsaid | D15: 308.5 | E15: 0.4 | F15: =E15*D15 -> 123.4 | G15: =F15 -> 123.4 | H15: =F15-G15 -> 0 | I15: 757601 | J15: 45932
A16: 13 | B16: 1474 | C16: Mohamed Salam Amer Al Yafee | D16: 764.3 | E16: 0.4 | F16: =E16*D16 -> 305.72 | H16: =F16-G16 -> 305.72 | I16: 4603773
A17: 14 | B17: 1479 | C17: Ahmed Amer Said Baitsaid | D17: 315.5 | E17: 0.4 | F17: =E17*D17 -> 126.2 | G17: =125.4 -> 125.4 | H17: =F17-G17 -> 0.8 | I17: 5217726 | J17: 17-2-25
A18: 15 | B18: 1483 | C18: Saed Ali Ahmed Al Kathiri | D18: 822.2 | E18: 0.4 | F18: =E18*D18 -> 328.88 | H18: =F18-G18 -> 328.88 | I18: 1567826
A19: 16 | B19: 1486 | C19: Mosoud Ali Salim Al Kathiri | D19: 367.7 | E19: 0.4 | F19: =E19*D19 -> 147.08 | H19: =F19-G19 -> 147.08 | I19: 22792564
A20: 17 | B20: 1762 | C20: MUSALLAM HASAN ALI BAIT SAID | D20: 1148.2 | E20: 0.4 | F20: =E20*D20 -> 459.28 | H20: =F20-G20 -> 459.28 | I20: 1409527
A21: 18 | B21: 1792 | C21: Musallam Bakhit Salim Al Aamri | D21: 324.3 | E21: 0.4 | F21: =E21*D21 -> 129.72 | H21: =F21-G21 -> 129.72 | I21: 9545556
A22: 19 | B22: 3009 | C22: Ahmed Salim Bakhit Qatan | D22: 346.6 | E22: 0.4 | F22: =E22*D22 -> 138.64 | H22: =F22-G22 -> 138.64 | I22: 1448391
A23: 20 | B23: 3012 | C23: Salim Suhail Ali Al Kathiri | D23: 322 | E23: 0.4 | F23: =E23*D23 -> 128.8 | G23: =125.03 -> 125.03 | H23: =F23-G23 -> 3.77 | I23: 5634422 | J23: 45993
A24: 21 | B24: 3014 | C24: Ahmed Mohammed Salim Al Barami | D24: 284.2 | E24: 0.4 | F24: =E24*D24 -> 113.68 | G24: =110.26 -> 110.26 | H24: =F24-G24 -> 3.42 | I24: 648421 | J24: 20-02-25
A25: 22 | B25: 3015 | C25: Ahmed Mohammed Faraj Al Kathiri | D25: 345 | E25: 0.4 | F25: =E25*D25 -> 138 | H25: =F25-G25 -> 138 | I25: 5753033
A26: 23 | B26: 3018 | C26: Bakhit Salim Bakhit Qatan | D26: 128.9 | E26: 0.4 | F26: =E26*D26 -> 51.56 | H26: =F26-G26 -> 51.56 | I26: 1528087
A27: 24 | B27: 3020 | C27: Bakhit Ali Salim Qatan | D27: 486.1 | E27: 0.4 | F27: =E27*D27 -> 194.44 | G27: =193.62+0.82 -> 194.44 | H27: =F27-G27 -> 0 | I27: 5418422 | J27: 45677 | K27: 13-2-25
A28: 25 | B28: 3022 | C28: Hussein Masoud Aubad Al Kathiri | D28: 960.1 | E28: 0.4 | F28: =E28*D28 -> 384.04 | H28: =F28-G28 -> 384.04 | I28: 5360253
A29: 26 | B29: 3025 | C29: Musallam Salim Mahad Qatan | D29: 547.8 | E29: 0.4 | F29: =E29*D29 -> 219.12 | H29: =F29-G29 -> 219.12 | I29: 7542172
A30: 27 | B30: 3026 | C30: Amer Salem Ahmed Qatan | D30: 302.2 | E30: 0.4 | F30: =E30*D30 -> 120.88 | H30: =F30-G30 -> 120.88 | I30: 7033819
A31: 28 | B31: 3027 | C31: Salim Ahmed Mahad Aamir Jid | D31: 666.3 | E31: 0.4 | F31: =E31*D31 -> 266.52 | H31: =F31-G31 -> 266.52 | I31: 6420643
A32: 29 | B32: 3030 | C32: Salim Ahmed Salim Amer Jid | D32: 345 | E32: 0.4 | F32: =E32*D32 -> 138 | G32: =F32 -> 138 | H32: =F32-G32 -> 0 | I32: 6021175 | J32: 18-2-25
A33: 30 | B33: 3038 | C33: Said Ahmed Mahad Qatan | D33: 664 | E33: 0.4 | F33: =E33*D33 -> 265.6 | G33: =265.05 -> 265.05 | H33: =F33-G33 -> 0.55 | I33: 7976 | J33: 45932
A34: 31 | B34: 3043 | C34: Said Aubad Ali Ghawas | D34: 286.5 | E34: 0.4 | F34: =E34*D34 -> 114.6 | G34: =110.34 -> 110.34 | H34: =F34-G34 -> 4.26 | I34: 396336 | J34: 20-2-25
A35: 32 | B35: 3058 | C35: Ali Bakhit Ahmed Qatan | D35: 1081.1 | E35: 0.4 | F35: =E35*D35 -> 432.44 | H35: =F35-G35 -> 432.44 | I35: 965148
A36: 33 | B36: 3070 | C36: Mohamed Ahmed Suhail Qatan | D36: 1028.7 | E36: 0.4 | F36: =E36*D36 -> 411.48 | G36: =407.03 -> 407.03 | H36: =F36-G36 -> 4.45 | I36: 1918001 | J36: 45670
A37: 34 | B37: 3072 | C37: Mohammed Salim Said Al Barami | D37: 303.5 | E37: 0.4 | F37: =E37*D37 -> 121.4 | H37: =F37-G37 -> 121.4 | I37: 993077
A38: 35 | B38: 3077 | C38: Mohammed Ali Suhail Qatan | D38: 657.3 | E38: 0.4 | F38: =E38*D38 -> 262.92 | H38: =F38-G38 -> 262.92 | I38: 21978752
A39: 36 | B39: 3081 | C39: Musallam Bakhit Masoud Qatan | D39: 184.3 | E39: 0.4 | F39: =E39*D39 -> 73.72 | G39: =F39 -> 73.72 | H39: =F39-G39 -> 0 | I39: 21219868 | J39: 45718
A40: 37 | B40: 3089 | C40: Yhaya Musallam Said Qatan | D40: 358 | E40: 0.4 | F40: =E40*D40 -> 143.2 | G40: =F40 -> 143.2 | H40: =F40-G40 -> 0 | I40: 18790484 | J40: 20-02-25
A41: 38 | B41: 3093 | C41: Bakhit Amer Salem Qatan | D41: 491.3 | E41: 0.4 | F41: =E41*D41 -> 196.52 | H41: =F41-G41 -> 196.52 | I41: 6361035
A42: 39 | B42: 3094 | C42: Ali Ahmed Aubad Jamaan Al Kathiri | D42: 1041.2 | E42: 0.4 | F42: =E42*D42 -> 416.48 | H42: =F42-G42 -> 416.48 | I42: 26343985
A43: 40 | B43: 3100 | C43: Salim Ahmed Said Tabuk | D43: 1373.5 | E43: 0.4 | F43: =E43*D43 -> 549.4 | H43: =F43-G43 -> 549.4 | I43: 1278615
A44: 41 | B44: 3101 | C44: Salim Said Suhail Qatan | D44: 352 | E44: 0.4 | F44: =E44*D44 -> 140.8 | H44: =F44-G44 -> 140.8 | I44: 6767598
A45: 42 | B45: 3102 | C45: Mohammed Salim Amer Qatan | D45: 631 | E45: 0.4 | F45: =E45*D45 -> 252.4 | G45: =236.52 -> 236.52 | H45: =F45-G45 -> 15.88 | I45: 5916838 | J45: 45932
A46: 43 | B46: 3119 | C46: Mohammed Ahmed Suhail Mahad Qatan | D46: 924 | E46: 0.4 | F46: =E46*D46 -> 369.6 | H46: =F46-G46 -> 369.6 | I46: 5903061
A47: 44 | B47: 3122 | C47: Khalid Ahmed Salim Amer Jid Al Mahri | D47: 344 | E47: 0.4 | F47: =E47*D47 -> 137.6 | G47: =F47 -> 137.6 | H47: =F47-G47 -> 0 | I47: 12415718 | J47: 18-2-25
A48: 45 | B48: 3136 | C48: Ghazi Salim Ahmed Al Kathiri | D48: 531.7 | E48: 0.4 | F48: =E48*D48 -> 212.68 | G48: =212.59 -> 212.59 | H48: =F48-G48 -> 0.09 | I48: 183498 | J48: 20-2-25
A49: 46 | B49: 3178 | C49: Abdul Sallam Ahmed Abdullah Al Abbadi Al Rawas | D49: 2300 | E49: 0.4 | F49: =E49*D49 -> 920 | H49: =F49-G49 -> 920 | I49: 1511754
A50: 47 | B50: 3199 | C50: Ali Musallam Ahmed Tabuk | D50: 310 | E50: 0.4 | F50: =E50*D50 -> 124 | H50: =F50-G50 -> 124 | I50: 5168327
A51: 48 | B51: 3200 | C51: Ahmed Said Ahmed Qutan | D51: 199.1 | E51: 0.4 | F51: =E51*D51 -> 79.64 | H51: =F51-G51 -> 79.64 | I51: 21947578
A52: 49 | B52: 3201 | C52: Ali Salim Said Qatan | D52: 286 | E52: 0.4 | F52: =E52*D52 -> 114.4 | H52: =F52-G52 -> 114.4 | I52: 7048401
A53: 50 | B53: 3202 | C53: Salim Ahmed Ali Qatan | D53: 327.7 | E53: 0.4 | F53: =E53*D53 -> 131.08 | H53: =F53-G53 -> 131.08 | I53: 5197371
A54: 51 | B54: 3203 | C54: Musallam Salim Amir Said Qatan | D54: 458 | E54: 0.4 | F54: =E54*D54 -> 183.2 | G54: =180.19 -> 180.19 | H54: =F54-G54 -> 3.01 | I54: 23215097 | J54: 45932
A55: 52 | B55: 3204 | C55: Hassan Suhail Ahmed Said Qatan | D55: 455.6 | E55: 0.4 | F55: =E55*D55 -> 182.24 | H55: =F55-G55 -> 182.24 | I55: 24958926
A56: 53 | B56: 3207 | C56: Said Ali Ahmed Al Katheri | D56: 759 | E56: 0.4 | F56: =E56*D56 -> 303.6 | H56: =F56-G56 -> 303.6 | I56: 11940175
A57: 54 | B57: 3208 | C57: Ali Mahad Said Qatan | D57: 648.7 | E57: 0.4 | F57: =E57*D57 -> 259.48 | H57: =F57-G57 -> 259.48 | I57: 1742664
A58: 55 | B58: 3209 | C58: Said Suhail Ali Al Kathiri | D58: 344.6 | E58: 0.4 | F58: =E58*D58 -> 137.84 | G58: =133.53 -> 133.53 | H58: =F58-G58 -> 4.31 | I58: 5634328 | J58: 45993
A59: 56 | B59: 3210 | C59: Ahmed Said Mubarak Al Zawamri | D59: 667 | E59: 0.4 | F59: =E59*D59 -> 266.8 | G59: =263.1+3.7 -> 266.8 | H59: =F59-G59 -> 0 | I59: 45419 | J59: 45993 | K59: 18-2-25
A60: 57 | B60: 3211 | C60: Salim Mohammed Musallam Al Baraami | D60: 338.6 | E60: 0.4 | F60: =E60*D60 -> 135.44 | H60: =F60-G60 -> 135.44 | I60: 9927207 | J60: 44986
A61: 58 | B61: 3212 | C61: Mohammed Said Mahad Qatan | D61: 885.7 | E61: 0.4 | F61: =E61*D61 -> 354.28 | H61: =F61-G61 -> 354.28 | I61: 804443
A62: 59 | B62: 3213 | C62: Ali Ahmed Suhail Qatan | D62: 736.4 | E62: 0.4 | F62: =E62*D62 -> 294.56 | H62: =F62-G62 -> 294.56 | I62: 2594336
A63: 60 | B63: 3214 | C63: Salim Musallam Ahmed Tabouk | D63: 850.9 | E63: 0.4 | F63: =E63*D63 -> 340.36 | H63: =F63-G63 -> 340.36 | I63: 5168262
A64: 61 | B64: 3215 | C64: Suhail Awadh Salim Hawas Al Aamri | D64: 583.1 | E64: 0.4 | F64: =E64*D64 -> 233.24 | H64: =F64-G64 -> 233.24 | I64: 11684091
A65: 62 | B65: 3216 | C65: Salim Ali said Al Masahli | D65: 907.9 | E65: 0.4 | F65: =E65*D65 -> 363.16 | H65: =F65-G65 -> 363.16 | I65: 18715567
A66: 63 | B66: 3217 | C66: Hassan Musallam Ali Qatan | D66: 264.9 | E66: 0.4 | F66: =E66*D66 -> 105.96 | H66: =F66-G66 -> 105.96 | I66: 1568196
A67: 64 | B67: 3219 | C67: Said Salim Ali Hawas Al Aamri | D67: 1074.5 | E67: 0.4 | F67: =E67*D67 -> 429.8 | G67: =140.112 -> 140.112 | H67: =F67-G67 -> 289.688 | I67: 12398617 | J67: 17-2-25
A68: 65 | B68: 3220 | C68: Adnan Mohammed Said Bait Said | D68: 667 | E68: 0.4 | F68: =E68*D68 -> 266.8 | H68: =F68-G68 -> 266.8 | I68: 5348311
A69: 66 | B69: 3221 | C69: Musallam Mohammed Salim Al Barami | D69: 304 | E69: 0.4 | F69: =E69*D69 -> 121.6 | H69: =F69-G69 -> 121.6 | I69: 13362673
A70: 67 | B70: 3222 | C70: Mohammed Ahmed Bakhit Qatan | D70: 441 | E70: 0.4 | F70: =E70*D70 -> 176.4 | H70: =F70-G70 -> 176.4 | I70: 18091329
A71: 68 | B71: 3223 | C71: Salim Said Mustahil Al Kathiri | D71: 314.3 | E71: 0.4 | F71: =E71*D71 -> 125.72 | H71: =F71-G71 -> 125.72 | I71: 5334914
A72: 69 | B72: 3224 | C72: Salim Said Salim Qatan | D72: 208.3 | E72: 0.4 | F72: =E72*D72 -> 83.32 | H72: =F72-G72 -> 83.32 | I72: 2066756
A73: 70 | B73: 3225 | C73: Mohamed Ahmed Salam Alamri | D73: 301.8 | E73: 0.4 | F73: =E73*D73 -> 120.72 | G73: =F73 -> 120.72 | H73: =F73-G73 -> 0 | I73: 798637 | J73: 20-2-25
A74: 71 | B74: 3227 | C74: Ahmed Ali Suhail ALAamri | D74: 252.7 | E74: 0.4 | F74: =E74*D74 -> 101.08 | G74: =100.79 -> 100.79 | H74: =F74-G74 -> 0.29 | I74: 15214649 | J74: 23-2-25
A75: 72 | B75: 3228 | C75: Ali Amer Salim Qatan | D75: 634.4 | E75: 0.4 | F75: =E75*D75 -> 253.76 | H75: =F75-G75 -> 253.76 | I75: 1307775
A76: 73 | B76: 3229 | C76: Musallam Amer Salim Qatan | D76: 488 | E76: 0.4 | F76: =E76*D76 -> 195.2 | H76: =F76-G76 -> 195.2 | I76: 6370978
A77: 74 | B77: 3230 | C77: Mohammed Abdullah Ali Ghawas | D77: 462 | E77: 0.4 | F77: =E77*D77 -> 184.8 | H77: =F77-G77 -> 184.8 | I77: 1968755
A78: 75 | B78: 3231 | C78: Tanaf Suhail Ali Hawas Al Aamri | D78: 616 | E78: 0.4 | F78: =E78*D78 -> 246.4 | H78: =F78-G78 -> 246.4 | I78: 6203903
A79: 76 | B79: 3232 | C79: Salim Mohammed Ahmed Al Aamri | D79: 333.7 | E79: 0.4 | F79: =E79*D79 -> 133.48 | G79: =F79 -> 133.48 | H79: =F79-G79 -> 0 | I79: 6387264 | J79: 20-2-25
A80: 77 | B80: 3234 | C80: Masoud Salim Ahmed Alash Al Kathiri | D80: 646.3 | E80: 0.4 | F80: =E80*D80 -> 258.52 | H80: =F80-G80 -> 258.52 | I80: 21834239
A81: 78 | B81: 3235 | C81: Ahmed Mahad Musallam Amor Jid | D81: 664 | E81: 0.4 | F81: =E81*D81 -> 265.6 | H81: =F81-G81 -> 265.6 | I81: 1234245
A82: 79 | B82: 3236 | C82: Salim Ali Mohammed Hawas Al Amari | D82: 229.7 | E82: 0.4 | F82: =E82*D82 -> 91.88 | G82: =90.33 -> 90.33 | H82: =F82-G82 -> 1.55 | I82: 6733333 | J82: 20-02-25
A83: 80 | B83: 3237 | C83: Suhail Salim Mohammed Al Daakari | D83: 697.1 | E83: 0.4 | F83: =E83*D83 -> 278.84 | G83: =276.45 -> 276.45 | H83: =F83-G83 -> 2.39 | I83: 873637 | J83: 13-2-25
A84: 81 | B84: 3238 | C84: Mohammed Ali Said Qatan | D84: 297.4 | E84: 0.4 | F84: =E84*D84 -> 118.96 | H84: =F84-G84 -> 118.96 | I84: 5361082 | J84: 44621
A85: 82 | B85: 3239 | C85: Ali Salim Bakhit Qatan | D85: 481.5 | E85: 0.4 | F85: =E85*D85 -> 192.6 | H85: =F85-G85 -> 192.6 | I85: 14379226
A86: 83 | B86: 3240 | C86: Ali Said Salim Al kathiri | D86: 619.6 | E86: 0.4 | F86: =E86*D86 -> 247.84 | H86: =F86-G86 -> 247.84 | I86: 5622856
A87: 84 | B87: 3241 | C87: Bashar Ahmed Ali Qatan | D87: 280.4 | E87: 0.4 | F87: =E87*D87 -> 112.16 | G87: =108.87 -> 108.87 | H87: =F87-G87 -> 3.29 | I87: 21125518 | J87: 20-02-25
A88: 85 | B88: 3243 | C88: Asad Ali Ahmed Suhail Aamir Jid | D88: 314.9 | E88: 0.4 | F88: =E88*D88 -> 125.96 | G88: =123.2 -> 123.2 | H88: =F88-G88 -> 2.76 | I88: 25887256 | J88: 45993
A89: 86 | B89: 3244 | C89: Mohammed Ali Bakhit Qatan | D89: 292.4 | E89: 0.4 | F89: =E89*D89 -> 116.96 | H89: =F89-G89 -> 116.96 | I89: 19340943
A90: 87 | B90: 3245 | C90: Musallam Ahmed Mohammed Aldakari Al Kathiri | D90: 88.1 | E90: 0.4 | F90: =E90*D90 -> 35.24 | H90: =F90-G90 -> 35.24 | I90: 996477
A91: 88 | B91: 3246 | C91: Salim Suhail Said Ghawas | D91: 276 | E91: 0.4 | F91: =E91*D91 -> 110.4 | H91: =F91-G91 -> 110.4 | I91: 662648
A92: 89 | B92: 3247 | C92: Mohammed Suhail Said Ghawas | D92: 299 | E92: 0.4 | F92: =E92*D92 -> 119.6 | H92: =F92-G92 -> 119.6 | I92: 6457783
A93: 90 | B93: 3248 | C93: Ahmed Suhail Said Ghawas | D93: 276 | E93: 0.4 | F93: =E93*D93 -> 110.4 | H93: =F93-G93 -> 110.4 | I93: 18811851
A94: 91 | B94: 3249 | C94: Amir Musallam Hadi Salim Al Aamri | D94: 595 | E94: 0.4 | F94: =E94*D94 -> 238 | G94: =F94 -> 238 | H94: =F94-G94 -> 0 | I94: 24540784 | J94: 45932
A95: 92 | B95: 3251 | C95: Mahad Ahmed Mahad Aamir Jid | D95: 341.3 | E95: 0.4 | F95: =E95*D95 -> 136.52 | H95: =F95-G95 -> 136.52 | I95: 6420681
A96: 94 | B96: 3253 | C96: Abdull Ali Ahmed Suhail Aamir Jid | D96: 630 | E96: 0.4 | F96: =E96*D96 -> 252 | G96: 250.25 | H96: =F96-G96 -> 1.75 | I96: 25887589 | J96: 45993
A97: 95 | B97: 3254 | C97: Said Mohammed Musallam Al Shihri | D97: 546 | E97: 0.4 | F97: =E97*D97 -> 218.4 | H97: =F97-G97 -> 218.4 | I97: 6668983
A98: 96 | B98: 3255 | C98: Bakhit Ahmed Musallam Khinan Al Shahri | D98: 472.3 | E98: 0.4 | F98: =E98*D98 -> 188.92 | H98: =F98-G98 -> 188.92 | I98: 5851949
A99: 97 | B99: 3256 | C99: Salim Said Salim Al Mahri | D99: 2098 | E99: 0.4 | F99: =E99*D99 -> 839.2 | G99: =470 -> 470 | H99: =F99-G99 -> 369.2 | I99: 6147152 | J99: 17-2-25
A100: 98 | B100: 3258 | C100: Ahmed Salim Amer Qatan | D100: 914.4 | E100: 0.4 | F100: =E100*D100 -> 365.76 | G100: =363.75 -> 363.75 | H100: =F100-G100 -> 2.01 | I100: 15335306 | J100: 20-2-25
A101: 99 | B101: 3260 | C101: Ali Musalam Said Salim Qatan | D101: 290.5 | E101: 0.4 | F101: =E101*D101 -> 116.2 | H101: =F101-G101 -> 116.2 | I101: 19361936
...

Sheet Aug 25
A1: HAJEEF CAMEL MILK PROCUREMENT FROM 01-Aug-2025 to 31-Aug-2025
A3: Farmer Code | B3: Farmer Name | C3: Total Milk Qty | D3: Avg. Rate (OMR/Ltr.) | E3: Amount (OMR) | F3: paid | G3: balance | H3: ID No. | I3: Bank Account | J3: Bank Name. | K3: SWIFT | L3: Phone No. | M3: remark 2
A4: 1108 | B4: Bakhit Ahmed Musallam Al kathiri | C4: 612.4 | D4: 0.4 | E4: =D4*C4 -> 244.96 | G4: =E4-F4 -> 244.96 | H4: 15218386 | I4: 0439012124150013 | J4: BANK MUSCAT | K4: BMUSOMRX | L4: 92776884
A5: 1390 | B5: Bakhait Salim Ahmed Alash Al Kathiri | C5: 251.4 | D5: 0.4 | E5: =D5*C5 -> 100.56 | F5: =96.73+3.83 -> 100.56 | G5: =E5-F5 -> 0 | H5: 12181822 | I5: 0439014599800023 | J5: BANK MUSCAT | K5: BMUSOMRX | L5: 92442060 | M5: 15-10-25 | N5: 24-11-25
A6: 1399 | B6: Mohammed Suhail Ali Hawas Al Aamri | C6: 201.4 | D6: 0.4 | E6: =D6*C6 -> 80.56 | F6: =77.52+3.04 -> 80.56 | G6: =E6-F6 -> 0 | H6: 10065546 | I6: 3109720870700 | J6: OAB | K6: OMABOMRU | M6: 14-10-25 | N6: 45727
A7: 1422 | B7: Mahammed Musallam Ahmed Hwas | C7: 126.3 | D7: 0.4 | E7: =D7*C7 -> 50.52 | F7: =E7 -> 50.52 | G7: =E7-F7 -> 0 | H7: 3280016 | I7: 0397003987550015 | J7: BANK MUSCAT | K7: BMUSOMRX | M7: 26-10-2025
A8: 1424 | B8: Said Ahmed Sabah Ali Badar | D8: 0.4 | E8: =D8*C8 -> 0 | G8: =E8-F8 -> 0 | H8: 748395 | I8: 01012574607001 | J8: BANK DHOFAR | K8: BDOFOMRU | L8: 93011211
A9: 1429 | B9: Said Mohammed Salem Akdha Al Rawas | C9: 340.7 | D9: 0.4 | E9: =D9*C9 -> 136.28 | G9: =E9-F9 -> 136.28 | H9: 339725 | I9: 0397003785300017 | J9: BANK MUSCAT | K9: BMUSOMRX
A10: 1431 | B10: Bakhit Mohamed Salim Rawas | C10: 235.8 | D10: 0.4 | E10: =D10*C10 -> 94.32 | G10: =E10-F10 -> 94.32 | H10: 721445 | I10: 01010850230001 | J10: BANK DHOFAR | K10: BDOFOMRU | L10: 99291700
A11: 1443 | B11: Ahmed Musallam Ahmed Al Kathiri | C11: 827.6 | D11: 0.4 | E11: =D11*C11 -> 331.04 | F11: =E11 -> 331.04 | G11: =E11-F11 -> 0 | H11: 6026992 | I11: 0439017196260028 | J11: BANK MUSCAT | K11: BMUSOMRX | L11: 95863774 | M11: 45728
A12: 1452 | B12: Sulaim Said Mohammed Hawas Al Aamri | C12: 186.5 | D12: 0.4 | E12: =D12*C12 -> 74.6 | F12: =E12 -> 74.6 | G12: =E12-F12 -> 0 | H12: 20917176 | I12: 0406012189810015 | J12: BANK MUSCAT | K12: BMUSOMRX | L12: 95863774 | M12: 20-10-25
A13: 1458 | B13: Salim Mustahil Jamaan Al Shakl Al kathiri | C13: 246.3 | D13: 0.4 | E13: =D13*C13 -> 98.52 | G13: =E13-F13 -> 98.52 | H13: 77628 | I13: 01012583986001 | J13: BANK DHOFAR | K13: BDOFOMRU | L13: 99275608
A14: 1461 | B14: Suhail Said Ali Bait said | C14: 241.3 | D14: 0.4 | E14: =D14*C14 -> 96.52 | F14: 92.79 | G14: =E14-F14 -> 3.73 | H14: 6828806 | I14: 0396003267730012 | J14: BANK MUSCAT | K14: BMUSOMRX | L14: 92330321 | M14: 14-10-25
A15: 1465 | B15: Mahad Salim Zaed Baitsaid | C15: 229.8 | D15: 0.4 | E15: =D15*C15 -> 91.92 | F15: =E15 -> 91.92 | G15: =E15-F15 -> 0 | H15: 757601 | I15: 1023113274001 | J15: NBO | K15: NBOMOMRX | L15: 99892131 | M15: 14-10-25
A16: 1474 | B16: Mohamed Salam Amer Al Yafee | C16: 428.4 | D16: 0.4 | E16: =D16*C16 -> 171.36 | F16: =0.14+171.22 -> 171.36 | G16: =E16-F16 -> 0 | H16: 4603773 | I16: 01041185194001 | J16: BANK DHOFAR | K16: BDOFOMRU | L16: 98820843 | M16: 45936 | N16: 20-10-25
A17: 1479 | B17: Ahmed Amer Said Baitsaid | C17: 208.3 | D17: 0.4 | E17: =D17*C17 -> 83.32 | F17: =81.41+1.91 -> 83.32 | G17: =E17-F17 -> 0 | H17: 5217726 | I17: 0396003219770029 | J17: BANK MUSCAT | K17: BMUSOMRX | L17: 92610234 | M17: 14-10-25 | N17: 17-12-25
A18: 1483 | B18: Saed Ali Ahmed Al Kathiri | C18: 608.7 | D18: 0.4 | E18: =D18*C18 -> 243.48 | F18: =239.25+4.23 -> 243.48 | G18: =E18-F18 -> 0 | H18: 1567826 | I18: 1083724895017 | J18: NBO | K18: NBOMOMRX | L18: 98532884 | M18: 15-10-2025 | N18: 15-12-25
A19: 1486 | B19: Mosoud Ali Salim Al Kathiri | D19: 0.4 | E19: =D19*C19 -> 0 | G19: =E19-F19 -> 0 | H19: 22792564 | I19: 0401064266530014 | J19: BANK MUSCAT | K19: BMUSOMRX
A20: 1762 | B20: MUSALLAM HASAN ALI BAIT SAID | C20: 634 | D20: 0.4 | E20: =D20*C20 -> 253.6 | F20: =E20 -> 253.6 | G20: =E20-F20 -> 0 | H20: 1409527 | I20: 0397003183710017 | J20: Bank Muscat | K20: BMUSOMRX | M20: 15-10-25
A21: 1792 | B21: Musallam Bakhit Salim Al Aamri | C21: 178.5 | D21: 0.4 | E21: =D21*C21 -> 71.4 | F21: =E21 -> 71.4 | G21: =E21-F21 -> 0 | H21: 9545556 | I21: 01011373210001 | J21: BANK DHOFAR | K21: BDOFOMRU | M21: 45727
A22: 3009 | B22: Ahmed Salim Bakhit Qatan | C22: 218 | D22: 0.4 | E22: =D22*C22 -> 87.2 | G22: =E22-F22 -> 87.2 | H22: 1448391 | I22: 3109628132500 | J22: OAB | K22: OMABOMRU | L22: 99100144
A23: 3012 | B23: Salim Suhail Ali Al Kathiri | C23: 241.5 | D23: 0.4 | E23: =D23*C23 -> 96.6 | F23: =95.55+1.05 -> 96.6 | G23: =E23-F23 -> 0 | H23: 5634422 | I23: 0406059374210012 | J23: BANK MUSCAT | K23: BMUSOMRX | L23: 96922118 | M23: 15-10-2025 | N23: 45881
A24: 3014 | B24: Ahmed Mohammed Salim Al Barami | C24: 193.6 | D24: 0.4 | E24: =D24*C24 -> 77.44 | F24: =E24 -> 77.44 | G24: =E24-F24 -> 0 | H24: 648421 | I24: 3129711924500 | J24: OAB | K24: OMABOMRU | L24: 98815665 | M24: 45848 | N24: .69-09-2025
A25: 3015 | B25: Ahmed Mohammed Faraj Al Kathiri | C25: 261.8 | D25: 0.4 | E25: =D25*C25 -> 104.72 | G25: =E25-F25 -> 104.72 | H25: 5753033 | I25: 0439058732890011 | J25: BANK MUSCAT | K25: BMUSOMRX | L25: 92838405
A26: 3018 | B26: Bakhit Salim Bakhit Qatan | C26: 155.5 | D26: 0.4 | E26: =D26*C26 -> 62.2 | F26: =E26 -> 62.2 | G26: =E26-F26 -> 0 | H26: 1528087 | I26: 0397004184300024 | J26: BANK MUSCAT | K26: BMUSOMRX | M26: 29-10-2025
A27: 3020 | B27: Bakhit Ali Salim Qatan | C27: 426.8 | D27: 0.4 | E27: =D27*C27 -> 170.72 | F27: =24.55+146.17 -> 170.72 | G27: =E27-F27 -> 0 | H27: 5418422 | I27: 0401002342630017 | J27: BANK MUSCAT | K27: BMUSOMRX | L27: 99495434 | M27: 20-10-2025 | N27: 27-10-2025
A28: 3022 | B28: Hussein Masoud Aubad Al Kathiri | C28: 560.5 | D28: 0.4 | E28: =D28*C28 -> 224.2 | F28: =E28 -> 224.2 | G28: =E28-F28 -> 0 | H28: 5360253 | I28: 1060656310017 | J28: NBO | K28: NBOMOMRX | L28: 99257989 | M28: 20-10-2025
A29: 3025 | B29: Musallam Salim Mahad Qatan | C29: 443 | D29: 0.4 | E29: =D29*C29 -> 177.2 | G29: =E29-F29 -> 177.2 | H29: 7542172 | I29: 0401002461080028 | J29: BANK MUSCAT | K29: BMUSOMRX
A30: 3026 | B30: Amer Salem Ahmed Qatan | C30: 235.2 | D30: 0.4 | E30: =D30*C30 -> 94.08 | G30: =E30-F30 -> 94.08 | H30: 7033819 | I30: 0401003532620025 | J30: BANK MUSCAT | K30: BMUSOMRX | L30: 92256918
A31: 3027 | B31: Salim Ahmed Mahad Aamir Jid | C31: 493 | D31: 0.4 | E31: =D31*C31 -> 197.2 | F31: =E31 -> 197.2 | G31: =E31-F31 -> 0 | H31: 6420643 | I31: 01011362595002 | J31: BANK DHOFAR | K31: BDOFOMRU | L31: 92288434 | M31: 22-10-2025
A32: 3030 | B32: Salim Ahmed Salim Amer Jid | C32: 243.8 | D32: 0.4 | E32: =D32*C32 -> 97.52 | F32: =94.23+3.29 -> 97.52 | G32: =E32-F32 -> 0 | H32: 6021175 | I32: 0401050718800013 | J32: BANK MUSCAT | K32: BMUSOMRX | L32: 91716888 | M32: 15-10-2025 | N32: 45727
A33: 3038 | B33: Said Ahmed Mahad Qatan | C33: 487.3 | D33: 0.4 | E33: =D33*C33 -> 194.92 | F33: =82.85+112.07 -> 194.92 | G33: =E33-F33 -> 0 | H33: 7976 | I33: 3109016888700 | J33: OAB | K33: OMABOMRU | L33: 98920007 | M33: 26-10-2025
A34: 3043 | B34: Said Aubad Ali Ghawas | C34: 219.5 | D34: 0.4 | E34: =D34*C34 -> 87.8 | F34: =E34 -> 87.8 | G34: =E34-F34 -> 0 | H34: 396336 | I34: 0397003933630013 | J34: BANK MUSCAT | K34: BMUSOMRX | L34: 99498844 | M34: 27-10-2025
A35: 3058 | B35: Ali Bakhit Ahmed Qatan | C35: 786.5 | D35: 0.4 | E35: =D35*C35 -> 314.6 | G35: =E35-F35 -> 314.6 | H35: 965148 | I35: 3129376165700 | J35: OAB | K35: OMABOMRU | L35: 90980121
A36: 3070 | B36: Mohamed Ahmed Suhail Qatan | C36: 734.1 | D36: 0.4 | E36: =D36*C36 -> 293.64 | F36: =E36 -> 293.64 | G36: =E36-F36 -> 0 | H36: 1918001 | I36: 0397004395550019 | J36: BANK MUSCAT | K36: BMUSOMRX | L36: 92863640 | M36: 45700
A37: 3072 | B37: Mohammed Salim Said Al Barami | C37: 245.4 | D37: 0.4 | E37: =D37*C37 -> 98.16 | F37: =E37 -> 98.16 | G37: =E37-F37 -> 0 | H37: 993077 | I37: 250094968001 | J37: HSBC | K37: BBMEOMRX | L37: 92252981 | M37: 26-10-25
A38: 3077 | B38: Mohammed Ali Suhail Qatan | C38: 485.7 | D38: 0.4 | E38: =D38*C38 -> 194.28 | F38: =E38 -> 194.28 | G38: =E38-F38 -> 0 | H38: 21978752 | I38: 0396041232890032 | J38: BANK MUSCAT | K38: BMUSOMRX | L38: 90833336 | M38: 17-12-25
A39: 3081 | B39: Musallam Bakhit Masoud Qatan | C39: 327 | D39: 0.4 | E39: =D39*C39 -> 130.8 | F39: =E39 -> 130.8 | G39: =E39-F39 -> 0 | H39: 21219868 | I39: 010010201414 | J39: Bank Sohar | K39: BSHROMRU | L39: 93288777 | M39: 20-10-25
A40: 3089 | B40: Yhaya Musallam Said Qatan | C40: 195.2 | D40: 0.4 | E40: =D40*C40 -> 78.08 | F40: =E40 -> 78.08 | G40: =E40-F40 -> 0 | H40: 18790484 | I40: 0401016503450018 | J40: BANK MUSCAT | K40: BMUSOMRX | M40: BT02-11-25
A41: 3093 | B41: Bakhit Amer Salem Qatan | C41: 366.7 | D41: 0.4 | E41: =D41*C41 -> 146.68 | G41: =E41-F41 -> 146.68 | H41: 6361035 | I41: 00510034969002 | J41: BANK NIZWA | K41: BNZWOMRX | L41: 99497919
A42: 3094 | B42: Ali Ahmed Aubad Jamaan Al Kathiri | C42: 644.5 | D42: 0.4 | E42: =D42*C42 -> 257.8 | G42: =E42-F42 -> 257.8 | H42: 26343985 | I42: 0304024501570012 | J42: BANK MUSCAT | K42: BMUSOMRX | L42: 93327740
A43: 3100 | B43: Salim Ahmed Said Tabuk | C43: 1020 | D43: 0.4 | E43: =D43*C43 -> 408 | F43: =3.33999999999996+403.75+0.91 -> 408 | G43: =E43-F43 -> 0 | H43: 1278615 | I43: 0426003863310028 | J43: NBO | K43: BMUSOMRX | L43: 99806386 | M43: 17-11-25 | N43: 45942 | O43: 24-12-25
A44: 3101 | B44: Salim Said Suhail Qatan | C44: 277.3 | D44: 0.4 | E44: =D44*C44 -> 110.92 | G44: =E44-F44 -> 110.92 | H44: 6767598 | I44: 0401002332700028 | J44: BANK MUSCAT | K44: BMUSOMRX | L44: 99100344
A45: 3102 | B45: Mohammed Salim Amer Qatan | C45: 435.6 | D45: 0.4 | E45: =D45*C45 -> 174.24 | F45: =4.12+170.12 -> 174.24 | G45: =E45-F45 -> 0 | H45: 5916838 | I45: 0317002509980029 | J45: BANK MUSCAT | K45: BMUSOMRX | L45: 91917520 | M45: 29-10-2025 | N45: 17-11-25
A46: 3119 | B46: Mohammed Ahmed Suhail Mahad Qatan | C46: 125.9 | D46: 0.4 | E46: =D46*C46 -> 50.36 | F46: =E46 -> 50.36 | G46: =E46-F46 -> 0 | H46: 5903061 | I46: 0401016956230027 | J46: BANK MUSCAT | K46: BMUSOMRX | L46: 91904279 | N46: BT11-12-25
A47: 3122 | B47: Khalid Ahmed Salim Amer Jid Al Mahri | C47: 249 | D47: 0.4 | E47: =D47*C47 -> 99.6 | F47: =96.45+3.15 -> 99.6 | G47: =E47-F47 -> 0 | H47: 12415718 | I47: 0401050718800013 | J47: BANK MUSCAT | K47: BMUSOMRX | L47: 99481799 | M47: 15-10-2025 | N47: 45727
A48: 3136 | B48: Ghazi Salim Ahmed Al Kathiri | C48: 452.6 | D48: 0.4 | E48: =D48*C48 -> 181.04 | F48: =E48 -> 181.04 | G48: =E48-F48 -> 0 | H48: 183498 | I48: 01011238092002 | J48: BANK DHOFAR | K48: BDOFOMRU | L48: 99481314 | M48: 20-10-25
A49: 3178 | B49: Abdul Sallam Ahmed Abdullah Al Abbadi Al Rawas | C49: 1592.4 | D49: 0.4 | E49: =D49*C49 -> 636.96 | F49: =E49 -> 636.96 | G49: =E49-F49 -> 0 | H49: 1511754 | I49: 3109061950500 | J49: OAB | K49: OMABOMRU | L49: 99495933 | M49: BT 04-12-2025
A50: 3199 | B50: Ali Musallam Ahmed Tabuk | C50: 223.4 | D50: 0.4 | E50: =D50*C50 -> 89.36 | F50: =E50 -> 89.36 | G50: =E50-F50 -> 0 | H50: 5168327 | I50: 0397004227360018 | J50: BANK MUSCAT | K50: BMUSOMRX | L50: 98066833 | M50: 27-10-2025
A51: 3200 | B51: Ahmed Said Ahmed Qutan | C51: 213.5 | D51: 0.4 | E51: =D51*C51 -> 85.4 | F51: =E51 -> 85.4 | G51: =E51-F51 -> 0 | H51: 21947578 | I51: 0401044694220018 | J51: BANK MUSCAT | K51: BMUSOMRX | M51: 20-10-25
A52: 3201 | B52: Ali Salim Said Qatan | C52: 223 | D52: 0.4 | E52: =D52*C52 -> 89.2 | G52: =E52-F52 -> 89.2 | H52: 7048401 | I52: 01041090275001 | J52: BANK DHOFAR | K52: BDOFOMRU
A53: 3202 | B53: Salim Ahmed Ali Qatan | C53: 246.6 | D53: 0.4 | E53: =D53*C53 -> 98.64 | F53: =96.17+2.47 -> 98.64 | G53: =E53-F53 -> 0 | H53: 5197371 | I53: 0132906010084010 | J53: BANK MUSCAT | K53: BMUSOMRX | L53: 93889732 | M53: 45727 | N53: 15-12-25
A54: 3203 | B54: Musallam Salim Amir Said Qatan | C54: 306.8 | D54: 0.4 | E54: =D54*C54 -> 122.72 | F54: =E54 -> 122.72 | G54: =E54-F54 -> 0 | H54: 23215097 | I54: 0401047625040018 | J54: BANK MUSCAT | K54: BMUSOMRX | M54: 45700
A55: 3204 | B55: Hassan Suhail Ahmed Said Qatan | C55: 374 | D55: 0.4 | E55: =D55*C55 -> 149.6 | F55: =146.66+2.94 -> 149.6 | G55: =E55-F55 -> 0 | H55: 24958926 | I55: 0426060858570018 | J55: BANK MUSCAT | K55: BMUSOMRX | L55: 99312225 | M55: 15-10-2025 | N55: 45727
A56: 3207 | B56: Said Ali Ahmed Al Katheri | C56: 563.7 | D56: 0.4 | E56: =D56*C56 -> 225.48 | G56: =E56-F56 -> 225.48 | H56: 11940175 | I56: 0406020751730014 | J56: BANK MUSCAT | K56: BMUSOMRX | L56: 98138748
A57: 3208 | B57: Ali Mahad Said Qatan | C57: 468.1 | D57: 0.4 | E57: =D57*C57 -> 187.24 | G57: =E57-F57 -> 187.24 | H57: 1742664 | I57: 001010070151 | J57: BANK SOHAR | K57: BSHROMRU | L57: 99482598
A58: 3209 | B58: Said Suhail Ali Al Kathiri | C58: 257.2 | D58: 0.4 | E58: =D58*C58 -> 102.88 | F58: =99.35+3.53 -> 102.88 | G58: =E58-F58 -> 0 | H58: 5634328 | I58: 0397016698910016 | J58: BANK MUSCAT | K58: BMUSOMRX | L58: 92283227 | M58: 15-10-2025 | N58: 45881
A59: 3210 | B59: Ahmed Said Mubarak Al Zawamri | C59: 456.9 | D59: 0.4 | E59: =D59*C59 -> 182.76 | F59: =181.98+0.78 -> 182.76 | G59: =E59-F59 -> 0 | H59: 45419 | I59: 0401002467120013 | J59: BANK MUSCAT | K59: BMUSOMRX | L59: 90101070 | M59: 45879 | N59: 22-10-2025
A60: 3211 | B60: Salim Mohammed Musallam Al Baraami | D60: 0.4 | E60: =D60*C60 -> 0 | G60: =E60-F60 -> 0 | H60: 9927207 | I60: 01010941305001 | J60: BANK DHOFAR | K60: BDOFOMRU
A61: 3212 | B61: Mohammed Said Mahad Qatan | C61: 658 | D61: 0.4 | E61: =D61*C61 -> 263.2 | G61: =E61-F61 -> 263.2 | H61: 804443 | I61: 050170299001 | J61: HSBC | K61: BBMEOMRX | L61: 99483202
A62: 3213 | B62: Ali Ahmed Suhail Qatan | C62: 289.3 | D62: 0.4 | E62: =D62*C62 -> 115.72 | F62: =E62 -> 115.72 | G62: =E62-F62 -> 0 | H62: 2594336 | I62: 0397004383920015 | J62: BANK MUSCAT | K62: BMUSOMRX | L62: 71773005 | M62: 45700
A63: 3214 | B63: Salim Musallam Ahmed Tabouk | C63: 641 | D63: 0.4 | E63: =D63*C63 -> 256.4 | F63: =E63 -> 256.4 | G63: =E63-F63 -> 0 | H63: 5168262 | I63: 01041249912001 | J63: BANK DHOFAR | K63: BDOFOMRU | L63: 99895383 | M63: 22-10-2025
A64: 3215 | B64: Suhail Awadh Salim Hawas Al Aamri | C64: 372.3 | D64: 0.4 | E64: =D64*C64 -> 148.92 | F64: =E64 -> 148.92 | G64: =E64-F64 -> 0 | H64: 11684091 | I64: 01010853900001 | J64: BANK DHOFAR | K64: BDOFOMRU | M64: 20-10-2025
A65: 3216 | B65: Salim Ali said Al Masahli | C65: 682.3 | D65: 0.4 | E65: =D65*C65 -> 272.92 | F65: =E65 -> 272.92 | G65: =E65-F65 -> 0 | H65: 18715567 | I65: 0406045085100027 | J65: BANK MUSCAT | K65: BMUSOMRX | L65: 77279900 | M65: 17-12-25
A66: 3217 | B66: Hassan Musallam Ali Qatan | C66: 125.8 | D66: 0.4 | E66: =D66*C66 -> 50.32 | G66: =E66-F66 -> 50.32 | H66: 1568196 | I66: 00510059623001 | J66: BANK NIZWA | K66: BNZWOMRX | L66: 99494635
A67: 3219 | B67: Said Salim Ali Hawas Al Aamri | C67: 729.2 | D67: 0.4 | E67: =D67*C67 -> 291.68 | F67: =288.25+3.43 -> 291.68 | G67: =E67-F67 -> 0 | H67: 12398617 | I67: 0406003141690019 | J67: BANK MUSCAT | K67: BMUSOMRX | M67: 15-10-2025 | N67: 45788
A68: 3220 | B68: Adnan Mohammed Said Bait Said | C68: 462 | D68: 0.4 | E68: =D68*C68 -> 184.8 | G68: =E68-F68 -> 184.8 | H68: 5348311 | I68: 01011445808001 | J68: BANK DHOFAR | K68: BDOFOMRU | L68: 96313636
A69: 3221 | B69: Musallam Mohammed Salim Al Barami | C69: 247.9 | D69: 0.4 | E69: =D69*C69 -> 99.16 | F69: =E69 -> 99.16 | G69: =E69-F69 -> 0 | H69: 13362673 | I69: 0401003471060021 | J69: BANK MUSCAT | K69: BMUSOMRX | L69: 92665337 | M69: 26-10-2025
A70: 3222 | B70: Mohammed Ahmed Bakhit Qatan | C70: 409.6 | D70: 0.4 | E70: =D70*C70 -> 163.84 | F70: =E70 -> 163.84 | G70: =E70-F70 -> 0 | H70: 18091329 | I70: 01011448559002 | J70: BANK DHOFAR | K70: BDOFOMRU | L70: 92197820 | M70: 23-10-2025
A71: 3223 | B71: Salim Said Mustahil Al Kathiri | C71: 249.1 | D71: 0.4 | E71: =D71*C71 -> 99.64 | G71: =E71-F71 -> 99.64 | H71: 5334914 | I71: 00510087464001 | J71: BANK NIZWA | K71: BNZWOMRX | L71: 98800996
A72: 3224 | B72: Salim Said Salim Qatan | C72: 191.8 | D72: 0.4 | E72: =D72*C72 -> 76.72 | F72: =E72 -> 76.72 | G72: =E72-F72 -> 0 | H72: 2066756 | I72: 0439002422440029 | J72: BANK MUSCAT | K72: BMUSOMRX | L72: 95316025 | M72: 15-10-2025
A73: 3225 | B73: Mohamed Ahmed Salam Alamri | C73: 216.7 | D73: 0.4 | E73: =D73*C73 -> 86.68 | F73: =E73 -> 86.68 | G73: =E73-F73 -> 0 | H73: 798637 | I73: 0397004248490019 | J73: BANK MUSCAT | K73: BMUSOMRX | M73: 45881
A74: 3227 | B74: Ahmed Ali Suhail ALAamri | C74: 97.4 | D74: 0.4 | E74: =D74*C74 -> 38.96 | F74: =37.86+1.1 -> 38.96 | G74: =E74-F74 -> 0 | H74: 15214649 | I74: 0406003835930033 | J74: BANK MUSCAT | K74: BMUSOMRX | L74: 92171914 | M74: 15-10-2025 | N74: 45941
A75: 3228 | B75: Ali Amer Salim Qatan | C75: 476 | D75: 0.4 | E75: =D75*C75 -> 190.4 | G75: =E75-F75 -> 190.4 | H75: 1307775 | I75: 01011440583003 | J75: BANK DHOFAR | K75: BDOFOMRU | L75: 99484101
A76: 3229 | B76: Musallam Amer Salim Qatan | C76: 374 | D76: 0.4 | E76: =D76*C76 -> 149.6 | G76: =E76-F76 -> 149.6 | H76: 6370978 | I76: 0401002417310016 | J76: BANK MUSCAT | K76: BMUSOMRX | L76: 99485611
A77: 3230 | B77: Mohammed Abdullah Ali Ghawas | C77: 294.5 | D77: 0.4 | E77: =D77*C77 -> 117.8 | G77: =E77-F77 -> 117.8 | H77: 1968755 | I77: 0406003363090017 | J77: BANK MUSCAT | K77: BMUSOMRX
A78: 3231 | B78: Tanaf Suhail Ali Hawas Al Aamri | C78: 429.2 | D78: 0.4 | E78: =D78*C78 -> 171.68 | F78: =171.08+0.6 -> 171.68 | G78: =E78-F78 -> 0 | H78: 6203903 | I78: 01010120940001 | J78: BANK DHOFAR | K78: BDOFOMRU | L78: 92535588 | M78: 15-10-2025 | N78: 45727
A79: 3232 | B79: Salim Mohammed Ahmed Al Aamri | C79: 249.1 | D79: 0.4 | E79: =D79*C79 -> 99.64 | F79: =0.59+99.05 -> 99.64 | G79: =E79-F79 -> 0 | H79: 6387264 | I79: 0500012521101001 | J79: Alizz Islamic Bank | K79: IZZBOMRU | L79: 96661076 | M79: 45879 | N79: 45881
A80: 3234 | B80: Masoud Salim Ahmed Alash Al Kathiri | C80: 481.4 | D80: 0.4 | E80: =D80*C80 -> 192.56 | G80: =E80-F80 -> 192.56 | H80: 21834239 | I80: 0406017202280014 | J80: BANK MUSCAT | K80: BMUSOMRX | L80: 98135444
A81: 3235 | B81: Ahmed Mahad Musallam Amor Jid | C81: 493 | D81: 0.4 | E81: =D81*C81 -> 197.2 | F81: =1.25+195.95 -> 197.2 | G81: =E81-F81 -> 0 | H81: 1234245 | I81: 10600341164086 | J81: NBO | K81: NBOMOMRX | L81: 99487759 | M81: 45879 | N81: 19-11-25
A82: 3236 | B82: Salim Ali Mohammed Hawas Al Amari | C82: 136.7 | D82: 0.4 | E82: =D82*C82 -> 54.68 | F82: =E82 -> 54.68 | G82: =E82-F82 -> 0 | H82: 6733333 | I82: 0397060863170013 | J82: BANK MUSCAT | K82: BMUSOMRX | M82: 20-10-25
A83: 3237 | B83: Suhail Salim Mohammed Al Daakari | C83: 492.6 | D83: 0.4 | E83: =D83*C83 -> 197.04 | F83: =195.42+1.62 -> 197.04 | G83: =E83-F83 -> 0 | H83: 873637 | I83: 3109633774500 | J83: OAB | K83: OMABOMRU | L83: 97659667 | M83: 15-10-2025 | N83: 19-11-25
A84: 3238 | B84: Mohammed Ali Said Qatan | C84: 217.2 | D84: 0.4 | E84: =D84*C84 -> 86.88 | G84: =E84-F84 -> 86.88 | H84: 5361082 | I84: 0401011715810012 | J84: BANK MUSCAT | K84: BMUSOMRX
A85: 3239 | B85: Ali Salim Bakhit Qatan | C85: 293.4 | D85: 0.4 | E85: =D85*C85 -> 117.36 | F85: =E85 -> 117.36 | G85: =E85-F85 -> 0 | H85: 14379226 | I85: 0413009940010018 | J85: BANK MUSCAT | K85: BMUSOMRX | L85: 92385524 | M85: 27-10-2025
A86: 3240 | B86: Ali Said Salim Al kathiri | C86: 373.4 | D86: 0.4 | E86: =D86*C86 -> 149.36 | F86: =E86 -> 149.36 | G86: =E86-F86 -> 0 | H86: 5622856 | I86: 00510029714001 | J86: BANK NIZWA | K86: BNZWOMRX | L86: 92400553 | M86: 27-10-2025
A87: 3241 | B87: Bashar Ahmed Ali Qatan | C87: 249.6 | D87: 0.4 | E87: =D87*C87 -> 99.84 | G87: =E87-F87 -> 99.84 | H87: 21125518 | I87: 0401040842100016 | J87: BANK MUSCAT | K87: BMUSOMRX | L87: 99508853
A88: 3243 | B88: Asad Ali Ahmed Suhail Aamir Jid | C88: 258.4 | D88: 0.4 | E88: =D88*C88 -> 103.36 | F88: =101.818+1.542 -> 103.36 | G88: =E88-F88 -> 0 | H88: 25887256 | I88: 0406056811780029 | J88: BANK MUSCAT | K88: BMUSOMRX | L88: 93271871 | M88: 15-10-2025 | N88: 29-10-2025
A89: 3244 | B89: Mohammed Ali Bakhit Qatan | C89: 205.9 | D89: 0.4 | E89: =D89*C89 -> 82.36 | G89: =E89-F89 -> 82.36 | H89: 19340943 | I89: 0397042697150019 | J89: BANK MUSCAT | K89: BMUSOMRX | L89: 92594446
A90: 3245 | B90: Musallam Ahmed Mohammed Aldakari Al Kathiri | C90: 205.9 | D90: 0.4 | E90: =D90*C90 -> 82.36 | F90: =79.69+2.67 -> 82.36 | G90: =E90-F90 -> 0 | H90: 996477 | I90: 3109331947500 | J90: OAB | K90: OMABOMRU | L90: 99699068 | M90: 15-10-2025 | N90: 19-11-25
A91: 3246 | B91: Salim Suhail Said Ghawas | C91: 201.8 | D91: 0.4 | E91: =D91*C91 -> 80.72 | F91: =3.26999999999999+77.45 -> 80.72 | G91: =E91-F91 -> 0 | H91: 662648 | I91: 0397003998840015 | J91: BANK MUSCAT | K91: BMUSOMRX | L91: 99498382 | M91: 20-10-25 | N91: 45788
A92: 3247 | B92: Mohammed Suhail Said Ghawas | C92: 215.1 | D92: 0.4 | E92: =D92*C92 -> 86.04 | F92: =0.0899999999999999+85.5+0.45 -> 86.04 | G92: =E92-F92 -> 0 | H92: 6457783 | I92: 0406003150110017 | J92: BANK MUSCAT | K92: BMUSOMRX | L92: 92594442 | M92: 20-10-25 | N92: 45788 | O92: 46008
A93: 3248 | B93: Ahmed Suhail Said Ghawas | C93: 202.6 | D93: 0.4 | E93: =D93*C93 -> 81.04 | F93: =1.79000000000001+79.25 -> 81.04 | G93: =E93-F93 -> 0 | H93: 18811851 | I93: 0406040710420017 | J93: BANK MUSCAT | K93: BMUSOMRX | L93: 92597556 | M93: 20-10-25 | N93: 45788
A94: 3249 | B94: Amir Musallam Hadi Salim Al Aamri | C94: 442 | D94: 0.4 | E94: =D94*C94 -> 176.8 | F94: =173.5+3.3 -> 176.8 | G94: =E94-F94 -> 0 | H94: 24540784 | I94: 0406025047690017 | J94: BANK MUSCAT | K94: BMUSOMRX | L94: 99693301 | M94: 15-10-25 | N94: 27-10-2025
A95: 3251 | B95: Mahad Ahmed Mahad Aamir Jid | C95: 264 | D95: 0.4 | E95: =D95*C95 -> 105.6 | F95: =E95 -> 105.6 | G95: =E95-F95 -> 0 | H95: 6420681 | I95: 0401002372390013 | J95: BANK MUSCAT | K95: BMUSOMRX | L95: 99588744 | M95: 46002
A96: 3252 | B96: Said Amer Salim Qatan | C96: 158.7 | D96: 0.4 | E96: =D96*C96 -> 63.48 | F96: =E96 -> 63.48 | G96: =E96-F96 -> 0 | H96: 460074 | I96: 0397003656070021 | J96: BANK MUSCAT | K96: BMUSOMRX | L96: 99292354 | M96: BT-16-11-25
A97: 3253 | B97: Abdull Ali Ahmed Suhail Aamir Jid | C97: 476 | D97: 0.4 | E97: =D97*C97 -> 190.4 | F97: =188.5+1.9 -> 190.4 | G97: =E97-F97 -> 0 | H97: 25887589 | I97: 0406061192660017 | J97: BANK MUSCAT | K97: BMUSOMRX | L97: 93995997 | M97: 15-10-2025 | N97: 29-10-2025
A98: 3254 | B98: Said Mohammed Musallam Al Shihri | C98: 409.5 | D98: 0.4 | E98: =D98*C98 -> 163.8 | F98: =163.35+0.45 -> 163.8 | G98: =E98-F98 -> 0 | H98: 6668983 | I98: 0401004242270027 | J98: BANK MUSCAT | K98: BMUSOMRX | L98: 92321002 | M98: 15-10-2025 | N98: 45788
A99: 3255 | B99: Bakhit Ahmed Musallam Khinan Al Shahri | C99: 273.3 | D99: 0.4 | E99: =D99*C99 -> 109.32 | F99: =0.7+108.62 -> 109.32 | G99: =E99-F99 -> 0 | H99: 5851949 | I99: 1060605003017 | J99: NBO | K99: NBOMOMRX | M99: 13-10-2025 | N99: 27-10-2025
A100: 3256 | B100: Salim Said Salim Al Mahri | C100: 1517 | D100: 0.4 | E100: =D100*C100 -> 606.8 | F100: =E100 -> 606.8 | G100: =E100-F100 -> 0 | H100: 6147152 | I100: 70401001815001 | J100: SOHAR ISLAMIC BANK | K100: BSHROMRUISL | L100: 99889778 | M100: 14-10-25
A101: 3258 | B101: Ahmed Salim Amer Qatan | C101: 671.5 | D101: 0.4 | E101: =D101*C101 -> 268.6 | F101: =E101 -> 268.6 | G101: =E101-F101 -> 0 | H101: 15335306 | I101: 1006708876017 | J101: NBO | K101: NBOMOMRX | L101: 99772646 | M101: 20-10-25
...

Sheet SEP-25
A1: HAJEEF CAMEL MILK PROCUREMENT FROM 01-Sep-2025 to 30-Sep-2025
A3: Farmer Code | B3: Farmer Name | C3: Total Milk Qty | D3: Avg. Rate (OMR/Ltr.) | E3: Amount (OMR) | F3: Amount (OMR) | G3: Balance | H3: ID No. | I3: Bank Account | J3: Bank Name. | K3: SWIFT | L3: Phone No. | M3: remark 2
A4: 1108 | B4: Bakhit Ahmed Musallam Al kathiri | C4: 677.1 | D4: 0.3 | E4: =D4*C4 -> 203.13 | G4: =E4-F4 -> 203.13 | H4: 15218386 | I4: 0439012124150013 | J4: BANK MUSCAT | K4: BMUSOMRX | L4: 92776884
A5: 1390 | B5: Bakhait Salim Ahmed Alash Al Kathiri | C5: 264.5 | D5: 0.3 | E5: =D5*C5 -> 79.35 | F5: =E5 -> 79.35 | G5: =E5-F5 -> 0 | H5: 12181822 | I5: 0439014599800023 | J5: BANK MUSCAT | K5: BMUSOMRX | L5: 92442060 | M5: 24-11-25
A6: 1399 | B6: Mohammed Suhail Ali Hawas Al Aamri | C6: 184.6 | D6: 0.3 | E6: =D6*C6 -> 55.38 | F6: =51.41+3.97 -> 55.38 | G6: =E6-F6 -> 0 | H6: 10065546 | I6: 3109720870700 | J6: OAB | K6: OMABOMRU | M6: 45727 | N6: 46008
A7: 1422 | B7: Mahammed Musallam Ahmed Hwas | C7: 150.6 | D7: 0.3 | E7: =D7*C7 -> 45.18 | F7: =41.98+3.2 -> 45.18 | G7: =E7-F7 -> 0 | H7: 3280016 | I7: 0397003987550015 | J7: BANK MUSCAT | K7: BMUSOMRX | M7: 26-10-2025 | N7: 17-12-25
A8: 1424 | B8: Said Ahmed Sabah Ali Badar | D8: 0.3 | E8: =D8*C8 -> 0 | G8: =E8-F8 -> 0 | H8: 748395 | I8: 01012574607001 | J8: BANK DHOFAR | K8: BDOFOMRU | L8: 93011211
A9: 1429 | B9: Said Mohammed Salem Akdha Al Rawas | C9: 357.1 | D9: 0.3 | E9: =D9*C9 -> 107.13 | G9: =E9-F9 -> 107.13 | H9: 339725 | I9: 0397003785300017 | J9: BANK MUSCAT | K9: BMUSOMRX
A10: 1431 | B10: Bakhit Mohamed Salim Rawas | C10: 234.6 | D10: 0.3 | E10: =D10*C10 -> 70.38 | G10: =E10-F10 -> 70.38 | H10: 721445 | I10: 01010850230001 | J10: BANK DHOFAR | K10: BDOFOMRU | L10: 99291700
A11: 1443 | B11: Ahmed Musallam Ahmed Al Kathiri | C11: 750.9 | D11: 0.3 | E11: =D11*C11 -> 225.27 | F11: =E11 -> 225.27 | G11: =E11-F11 -> 0 | H11: 6026992 | I11: 0439017196260028 | J11: BANK MUSCAT | K11: BMUSOMRX | L11: 95863774 | M11: 45728
A12: 1452 | B12: Sulaim Said Mohammed Hawas Al Aamri | C12: 209.1 | D12: 0.3 | E12: =D12*C12 -> 62.73 | F12: =3.82000000000003+57+1.91 -> 62.73 | G12: =E12-F12 -> 0 | H12: 20917176 | I12: 0406012189810015 | J12: BANK MUSCAT | K12: BMUSOMRX | L12: 95863774 | M12: 20-10-25 | N12: 29-10-2025 | O12: 15-12-25
A13: 1458 | B13: Salim Mustahil Jamaan Al Shakl Al kathiri | C13: 252 | D13: 0.3 | E13: =D13*C13 -> 75.6 | G13: =E13-F13 -> 75.6 | H13: 77628 | I13: 01012583986001 | J13: BANK DHOFAR | K13: BDOFOMRU | L13: 99275608
A14: 1461 | B14: Suhail Said Ali Bait said | C14: 245.7 | D14: 0.3 | E14: =D14*C14 -> 73.71 | G14: =E14-F14 -> 73.71 | H14: 6828806 | I14: 0396003267730012 | J14: BANK MUSCAT | K14: BMUSOMRX | L14: 92330321
A15: 1465 | B15: Mahad Salim Zaed Baitsaid | C15: 206 | D15: 0.3 | E15: =D15*C15 -> 61.8 | F15: =0.470000000000009+61.33 -> 61.8 | G15: =E15-F15 -> 0 | H15: 757601 | I15: 1023113274001 | J15: NBO | K15: NBOMOMRX | L15: 99892131 | M15: 14-10-25 | N15: 45941
A16: 1474 | B16: Mohamed Salam Amer Al Yafee | C16: 525.2 | D16: 0.3 | E16: =D16*C16 -> 157.56 | F16: =0.33+157.23 -> 157.56 | G16: =E16-F16 -> 0 | H16: 4603773 | I16: 01041185194001 | J16: BANK DHOFAR | K16: BDOFOMRU | L16: 98820843 | M16: 20-10-25 | N16: 45941
A17: 1479 | B17: Ahmed Amer Said Baitsaid | C17: 286.7 | D17: 0.3 | E17: =D17*C17 -> 86.01 | F17: =E17 -> 86.01 | G17: =E17-F17 -> 0 | H17: 5217726 | I17: 0396003219770029 | J17: BANK MUSCAT | K17: BMUSOMRX | L17: 92610234 | M17: 17-12-25
A18: 1483 | B18: Saed Ali Ahmed Al Kathiri | C18: 590.5 | D18: 0.3 | E18: =D18*C18 -> 177.15 | F18: =E18 -> 177.15 | G18: =E18-F18 -> 0 | H18: 1567826 | I18: 1083724895017 | J18: NBO | K18: NBOMOMRX | L18: 98532884 | M18: 15-12-25
A19: 1486 | B19: Mosoud Ali Salim Al Kathiri | C19: 236.2 | D19: 0.3 | E19: =D19*C19 -> 70.86 | F19: =E19 -> 70.86 | G19: =E19-F19 -> 0 | H19: 22792564 | I19: 0401064266530014 | J19: BANK MUSCAT | K19: BMUSOMRX | M19: 45700
A20: 1762 | B20: MUSALLAM HASAN ALI BAIT SAID | C20: 509.7 | D20: 0.3 | E20: =D20*C20 -> 152.91 | F20: =E20 -> 152.91 | G20: =E20-F20 -> 0 | H20: 1409527 | I20: 0397003183710017 | J20: Bank Muscat | K20: BMUSOMRX | M20: 15-10-25 | N20: 49.78 will deduct from 10-25
A21: 1792 | B21: Musallam Bakhit Salim Al Aamri | C21: 171.1 | D21: 0.3 | E21: =D21*C21 -> 51.33 | F21: 50.69 | G21: =E21-F21 -> 0.64 | H21: 9545556 | I21: 01011373210001 | J21: BANK DHOFAR | K21: BDOFOMRU | M21: 45727
A22: 3009 | B22: Ahmed Salim Bakhit Qatan | C22: 258 | D22: 0.3 | E22: =D22*C22 -> 77.4 | G22: =E22-F22 -> 77.4 | H22: 1448391 | I22: 3109628132500 | J22: OAB | K22: OMABOMRU | L22: 99100144
A23: 3012 | B23: Salim Suhail Ali Al Kathiri | C23: 246.5 | D23: 0.3 | E23: =D23*C23 -> 73.95 | F23: =E23 -> 73.95 | G23: =E23-F23 -> 0 | H23: 5634422 | I23: 0406059374210012 | J23: BANK MUSCAT | K23: BMUSOMRX | L23: 96922118 | M23: 45881
A24: 3014 | B24: Ahmed Mohammed Salim Al Barami | C24: 230 | D24: 0.3 | E24: =D24*C24 -> 69 | F24: =0.69+66.5+1.81 -> 69 | G24: =E24-F24 -> 0 | H24: 648421 | I24: 3129711924500 | J24: OAB | K24: OMABOMRU | L24: 98815665 | N24: 22-10-25 | O24: 45819
A25: 3015 | B25: Ahmed Mohammed Faraj Al Kathiri | C25: 268.7 | D25: 0.3 | E25: =D25*C25 -> 80.61 | G25: =E25-F25 -> 80.61 | H25: 5753033 | I25: 0439058732890011 | J25: BANK MUSCAT | K25: BMUSOMRX | L25: 92838405
A26: 3018 | B26: Bakhit Salim Bakhit Qatan | C26: 142.7 | D26: 0.3 | E26: =D26*C26 -> 42.81 | F26: 40.25 | G26: =E26-F26 -> 2.56 | H26: 1528087 | I26: 0397004184300024 | J26: BANK MUSCAT | K26: BMUSOMRX | M26: 29-10-2025
A27: 3020 | B27: Bakhit Ali Salim Qatan | C27: 357.9 | D27: 0.3 | E27: =D27*C27 -> 107.37 | F27: =105.68+1.69 -> 107.37 | G27: =E27-F27 -> 0 | H27: 5418422 | I27: 0401002342630017 | J27: BANK MUSCAT | K27: BMUSOMRX | L27: 99495434 | M27: 27-10-2025 | N27: 17-11-25
A28: 3022 | B28: Hussein Masoud Aubad Al Kathiri | C28: 557.5 | D28: 0.3 | E28: =D28*C28 -> 167.25 | F28: =4.06000000000002+163.19 -> 167.25 | G28: =E28-F28 -> 0 | H28: 5360253 | I28: 1060656310017 | J28: NBO | K28: NBOMOMRX | L28: 99257989 | M28: 20-10-25 | N28: 24-12-25
A29: 3025 | B29: Musallam Salim Mahad Qatan | C29: 462.2 | D29: 0.3 | E29: =D29*C29 -> 138.66 | G29: =E29-F29 -> 138.66 | H29: 7542172 | I29: 0401002461080028 | J29: BANK MUSCAT | K29: BMUSOMRX
A30: 3026 | B30: Amer Salem Ahmed Qatan | C30: 235.7 | D30: 0.3 | E30: =D30*C30 -> 70.71 | G30: =E30-F30 -> 70.71 | H30: 7033819 | I30: 0401003532620025 | J30: BANK MUSCAT | K30: BMUSOMRX | L30: 92256918
A31: 3027 | B31: Salim Ahmed Mahad Aamir Jid | C31: 493 | D31: 0.3 | E31: =D31*C31 -> 147.9 | F31: =0.0500000000000014+143.55+4.3 -> 147.9 | G31: =E31-F31 -> 0 | H31: 6420643 | I31: 01011362595002 | J31: BANK DHOFAR | K31: BDOFOMRU | L31: 92288434 | M31: 22-10-2025 | N31: 45788 | O31: 17-12-25
A32: 3030 | B32: Salim Ahmed Salim Amer Jid | C32: 242.3 | D32: 0.3 | E32: =D32*C32 -> 72.69 | F32: =69.71+2.98 -> 72.69 | G32: =E32-F32 -> 0 | H32: 6021175 | I32: 0401050718800013 | J32: BANK MUSCAT | K32: BMUSOMRX | L32: 91716888 | M32: 45727 | N32: 14-12-25
A33: 3038 | B33: Said Ahmed Mahad Qatan | C33: 494 | D33: 0.3 | E33: =D33*C33 -> 148.2 | F33: =1.93+146.27 -> 148.2 | G33: =E33-F33 -> 0 | H33: 7976 | I33: 3109016888700 | J33: OAB | K33: OMABOMRU | L33: 98920007 | M33: 26-10-2025 | N33: 19-11-25
A34: 3043 | B34: Said Aubad Ali Ghawas | C34: 226.3 | D34: 0.3 | E34: =D34*C34 -> 67.89 | F34: =67.74+0.15 -> 67.89 | G34: =E34-F34 -> 0 | H34: 396336 | I34: 0397003933630013 | J34: BANK MUSCAT | K34: BMUSOMRX | L34: 99498844 | M34: 27-10-2025 | N34: 22-12-25
A35: 3058 | B35: Ali Bakhit Ahmed Qatan | C35: 899.3 | D35: 0.3 | E35: =D35*C35 -> 269.79 | G35: =E35-F35 -> 269.79 | H35: 965148 | I35: 3129376165700 | J35: OAB | K35: OMABOMRU | L35: 90980121
A36: 3070 | B36: Mohamed Ahmed Suhail Qatan | C36: 789.4 | D36: 0.3 | E36: =D36*C36 -> 236.82 | F36: 234.94 | G36: =E36-F36 -> 1.88 | H36: 1918001 | I36: 0397004395550019 | J36: BANK MUSCAT | K36: BMUSOMRX | L36: 92863640 | M36: 45700
A37: 3072 | B37: Mohammed Salim Said Al Barami | C37: 238 | D37: 0.3 | E37: =D37*C37 -> 71.4 | F37: 70.83 | G37: =E37-F37 -> 0.57 | H37: 993077 | I37: 250094968001 | J37: HSBC | K37: BBMEOMRX | L37: 92252981 | M37: 26-10-25
A38: 3077 | B38: Mohammed Ali Suhail Qatan | C38: 503.5 | D38: 0.3 | E38: =D38*C38 -> 151.05 | F38: =123.97+27.08 -> 151.05 | G38: =E38-F38 -> 0 | H38: 21978752 | I38: 0396041232890032 | J38: BANK MUSCAT | K38: BMUSOMRX | L38: 90833336 | M38: 17-12-25 | N38: 22-12-25
A39: 3081 | B39: Musallam Bakhit Masoud Qatan | C39: 318 | D39: 0.3 | E39: =D39*C39 -> 95.4 | F39: =0.279999999999979+95.12 -> 95.4 | G39: =E39-F39 -> 0 | H39: 21219868 | I39: 010010201414 | J39: Bank Sohar | K39: BSHROMRU | L39: 93288777 | M39: 20-10-25 | N39: 46002
A40: 3089 | B40: Yhaya Musallam Said Qatan | C40: 221.8 | D40: 0.3 | E40: =D40*C40 -> 66.54 | F40: =E40 -> 66.54 | G40: =E40-F40 -> 0 | H40: 18790484 | I40: 0401016503450018 | J40: BANK MUSCAT | K40: BMUSOMRX | M40: BT02-11-25
A41: 3093 | B41: Bakhit Amer Salem Qatan | C41: 405.4 | D41: 0.3 | E41: =D41*C41 -> 121.62 | G41: =E41-F41 -> 121.62 | H41: 6361035 | I41: 00510034969002 | J41: BANK NIZWA | K41: BNZWOMRX | L41: 99497919
A42: 3094 | B42: Ali Ahmed Aubad Jamaan Al Kathiri | C42: 564.4 | D42: 0.3 | E42: =D42*C42 -> 169.32 | G42: =E42-F42 -> 169.32 | H42: 26343985 | I42: 0304024501570012 | J42: BANK MUSCAT | K42: BMUSOMRX | L42: 93327740
A43: 3100 | B43: Salim Ahmed Said Tabuk | C43: 1067 | D43: 0.3 | E43: =D43*C43 -> 320.1 | F43: =E43 -> 320.1 | G43: =E43-F43 -> 0 | H43: 1278615 | I43: 0426003863310028 | J43: NBO | K43: BMUSOMRX | L43: 99806386 | M43: 24-12-25
A44: 3101 | B44: Salim Said Suhail Qatan | C44: 270 | D44: 0.3 | E44: =D44*C44 -> 81 | G44: =E44-F44 -> 81 | H44: 6767598 | I44: 0401002332700028 | J44: BANK MUSCAT | K44: BMUSOMRX | L44: 99100344
A45: 3102 | B45: Mohammed Salim Amer Qatan | C45: 371.6 | D45: 0.3 | E45: =D45*C45 -> 111.48 | F45: =0.880000000000006+110.6 -> 111.48 | G45: =E45-F45 -> 0 | H45: 5916838 | I45: 0317002509980029 | J45: BANK MUSCAT | K45: BMUSOMRX | L45: 91917520 | M45: 17-11-25 | N45: 15-12-25
A46: 3119 | B46: Mohammed Ahmed Suhail Mahad Qatan | C46: 353.1 | D46: 0.3 | E46: =D46*C46 -> 105.93 | F46: =E46 -> 105.93 | G46: =E46-F46 -> 0 | H46: 5903061 | I46: 0401016956230027 | J46: BANK MUSCAT | K46: BMUSOMRX | L46: 91904279 | M46: BT11-12-25
A47: 3122 | B47: Khalid Ahmed Salim Amer Jid Al Mahri | C47: 264 | D47: 0.3 | E47: =D47*C47 -> 79.2 | F47: =72.45+6.75 -> 79.2 | G47: =E47-F47 -> 0 | H47: 12415718 | I47: 0401050718800013 | J47: BANK MUSCAT | K47: BMUSOMRX | L47: 99481799 | M47: 45727 | N47: 14-12-25
A48: 3136 | B48: Ghazi Salim Ahmed Al Kathiri | C48: 488.6 | D48: 0.3 | E48: =D48*C48 -> 146.58 | F48: 145.09 | G48: =E48-F48 -> 1.49 | H48: 183498 | I48: 01011238092002 | J48: BANK DHOFAR | K48: BDOFOMRU | L48: 99481314 | M48: 20-10-25
A49: 3178 | B49: Abdul Sallam Ahmed Abdullah Al Abbadi Al Rawas | C49: 1603.5 | D49: 0.3 | E49: =D49*C49 -> 481.05 | G49: =E49-F49 -> 481.05 | H49: 1511754 | I49: 3109061950500 | J49: OAB | K49: OMABOMRU | L49: 99495933
A50: 3199 | B50: Ali Musallam Ahmed Tabuk | C50: 189.4 | D50: 0.3 | E50: =D50*C50 -> 56.82 | F50: 54.82 | G50: =E50-F50 -> 2 | H50: 5168327 | I50: 0397004227360018 | J50: BANK MUSCAT | K50: BMUSOMRX | L50: 98066833 | M50: 27-10-2025
A51: 3200 | B51: Ahmed Said Ahmed Qutan | C51: 225 | D51: 0.3 | E51: =D51*C51 -> 67.5 | F51: =3.42999999999999+64.07 -> 67.5 | G51: =E51-F51 -> 0 | H51: 21947578 | I51: 0401044694220018 | J51: BANK MUSCAT | K51: BMUSOMRX | M51: 20-10-25 | N51: 46002
A52: 3201 | B52: Ali Salim Said Qatan | C52: 221 | D52: 0.3 | E52: =D52*C52 -> 66.3 | G52: =E52-F52 -> 66.3 | H52: 7048401 | I52: 01041090275001 | J52: BANK DHOFAR | K52: BDOFOMRU
A53: 3202 | B53: Salim Ahmed Ali Qatan | C53: 229.3 | D53: 0.3 | E53: =D53*C53 -> 68.79 | F53: =E53 -> 68.79 | G53: =E53-F53 -> 0 | H53: 5197371 | I53: 0132906010084010 | J53: BANK MUSCAT | K53: BMUSOMRX | L53: 93889732 | M53: 15-12-25
A54: 3203 | B54: Musallam Salim Amir Said Qatan | C54: 308.5 | D54: 0.3 | E54: =D54*C54 -> 92.55 | F54: =1.81+90.25+0.49 -> 92.55 | G54: =E54-F54 -> 0 | H54: 23215097 | I54: 0401047625040018 | J54: BANK MUSCAT | K54: BMUSOMRX | M54: 45700 | N54: 45881 | O54: 22-12-25
