Workbook

Sheet center-April
A1: HAJEEF COW MILK PROCUREMENT FROM 01-APR-2024 TO 30-APR-2024
A2: Sr No. | B2: Farmer Code | C2: Farmer Name | D2: Milk Qty. (Ltr.) | E2: Avg. Rate (OMR/Ltr.) | F2: Amount (OMR) | G2: paid | H2: balance | I2: ID No. | J2: Bank Account No. | K2: Bank Name | L2: IFSC Code | M2: Phone No. | N2: Remarks
A4: 31 | B4: 3153 | C4: ALI MAHAD SAID QATAN | D4: 1897.7 | E4: 0.250 | F4: =D4*E4 -> 474.425 | G4: =473.5+0.925 -> 474.425 | H4: =F4-G4 -> 0 | I4: 6989479 | J4: 0397003672070015 | K4: BANK MUSCAT | L4: BMUSOMRX | M4: 99699500 | N4: 12-08-2024-feeds | P4: 3153 | Q4: =P4=B4 -> TRUE | R4: ALI MAHAD SAID QATAN | S4: =R4=C4 -> TRUE | T4: 6989479 | U4: =T4=I4 -> TRUE | V4: 0397003672070015 | W4: =V4=J4 -> TRUE | X4: BMUSOMRX | Y4: =X4=L4 -> TRUE
A5: 76 | B5: 3511 | C5: Said Ali Said Qatan | D5: 1359.8 | E5: 0.250 | F5: =D5*E5 -> 339.95 | G5: =337.05+2.9 -> 339.95 | H5: =F5-G5 -> 0 | I5: 2640016 | J5: 0501036199001 | K5: Ahli Islamic | L5: AUBOOMRUALH | M5: 92953388 | N5: 05-08-2024-feeds | O5: 45630 | P5: 3511 | Q5: =P5=B5 -> TRUE | R5: Said Ali Said Qatan | S5: =R5=C5 -> TRUE | T5: 2640016 | U5: =T5=I5 -> TRUE | V5: 0501036199001 | W5: =V5=J5 -> TRUE | X5: AUBOOMRUALH | Y5: =X5=L5 -> TRUE
D6: =SUM(D4:D5) -> 3257.5 | F6: =SUM(F4:F5) -> 814.375 | G6: =SUM(G4:G5) -> 814.375 | H6: =SUM(H4:H5) -> 0
A9: Hassan Ghaly | C9: Suresh Bose
A10: Cost Accountant | C10: Sr.Operations Officer
V12: Said Al Bahanata
V13: DGM

Sheet center-May
A1: HAJEEF COW MILK PROCUREMENT FROM 01-May-2024 TO 31-May-2024
A2: Sr No. | B2: Farmer Code | C2: Farmer Name | D2: Milk Qty. (Ltr.) | E2: Avg. Rate (OMR/Ltr.) | F2: Amount (OMR) | G2: Amount (OMR) | H2: Amount (OMR) | I2: ID No. | J2: Bank Account No. | K2: Bank Name | L2: IFSC Code | M2: Phone No. | N2: Remarks
A4: 6 | B4: 3169 | C4: MOHAMMED ALI SAID AL ZAWAMRY | D4: 1284.1 | E4: 0.250 | F4: =D4*E4 -> 321.025 | G4: =320.1+0.925 -> 321.025 | H4: =F4-G4 -> 0 | I4: 3068756 | J4: 01012573317001 | K4: BANK DHOFAR | L4: BDOFOMRU | M4: 99691806 | N4: 45547 | O4: 45615 | P4: 3169 | Q4: =P4=B4 -> TRUE | R4: MOHAMMED ALI SAID AL ZAWAMRY | S4: =R4=C4 -> TRUE | T4: 3068756 | U4: =T4=I4 -> TRUE | V4: 01012573317001 | W4: =V4=J4 -> TRUE | X4: BDOFOMRU | Y4: =X4=L4 -> TRUE
A5: 7 | B5: 3192 | C5: GHAZI SALIM MASOUD TABOOK | D5: 1124.5 | E5: 0.250 | F5: =D5*E5 -> 281.125 | G5: =279.73+1.395 -> 281.125 | H5: =F5-G5 -> 0 | I5: 5271448 | J5: 0401002602010018 | K5: BANK MUSCAT | L5: BMUSOMRX | M5: 99489918 | N5: 01-08-2024-feeds | O5: 09-12-234 | P5: 3192 | Q5: =P5=B5 -> TRUE | R5: GHAZI SALIM MASOUD TABOOK | S5: =R5=C5 -> TRUE | T5: 5271448 | U5: =T5=I5 -> TRUE | V5: 0426012948850015 | W5: =V5=J5 -> FALSE | X5: BMUSOMRX | Y5: =X5=L5 -> TRUE
A6: 8 | B6: 3198 | C6: ADIL SAID AHMED AL ZAWAMRI | D6: 591.6 | E6: 0.250 | F6: =D6*E6 -> 147.9 | G6: =144.15+3.75 -> 147.9 | H6: =F6-G6 -> 0 | I6: 6360793 | J6: 00510047506001 | K6: Bank Nizwa | L6: BNZWOMRX | M6: 99336200 | N6: 11-08-2024-feeds | P6: 3198 | Q6: =P6=B6 -> TRUE | R6: ADIL SAID AHMED AL ZAWAMRI | S6: =R6=C6 -> TRUE | T6: 6360793 | U6: =T6=I6 -> TRUE | V6: 00510047506001 | W6: =V6=J6 -> TRUE | X6: BNZWOMRX | Y6: =X6=L6 -> TRUE
A7: 9 | B7: 3508 | C7: Said Ali Said Al Zawamri | D7: 610.9 | E7: 0.250 | F7: =D7*E7 -> 152.725 | G7: =150.35+2.375 -> 152.725 | H7: =F7-G7 -> 0 | I7: 2567166 | J7: 0439004225500028 | K7: BANK MUSCAT | L7: BMUSOMRX | M7: 92570156 | N7: 45547 | O7: 45615 | P7: 3508 | Q7: =P7=B7 -> TRUE | R7: Said Ali Said Al Zawamri | S7: =R7=C7 -> TRUE | T7: 2567166 | U7: =T7=I7 -> TRUE | V7: 0439004225500028 | W7: =V7=J7 -> TRUE | X7: BMUSOMRX | Y7: =X7=L7 -> TRUE
A8: 11 | B8: 3515 | C8: Ali Ajaham Ali Bait said | D8: 1267.5 | E8: 0.250 | F8: =D8*E8 -> 316.875 | G8: =315.625+1.25 -> 316.875 | H8: =F8-G8 -> 0 | I8: 6645198 | J8: 01011180247001 | K8: BANK DHOFAR | L8: BDOFOMRU | M8: 94411217 | N8: 14-08-24-feeds | O8: 45635 | P8: 3515 | Q8: =P8=B8 -> TRUE | R8: Ali Ajaham Ali Bait said | S8: =R8=C8 -> TRUE | T8: 6645198 | U8: =T8=I8 -> TRUE | V8: 01011180247001 | W8: =V8=J8 -> TRUE | X8: BDOFOMRU | Y8: =X8=L8 -> TRUE
A9: 12 | B9: 3518 | C9: Ali Ahmed Ali Bait Said | D9: 899.8 | E9: 0.250 | F9: =D9*E9 -> 224.95 | G9: =221.275+3.675 -> 224.95 | H9: =F9-G9 -> 0 | I9: 20386956 | J9: 0396064567750014 | K9: BANK MUSCAT | L9: BMUSOMRX | N9: 14-08-24-feeds | P9: 3518 | Q9: =P9=B9 -> TRUE | R9: Ali Ahmed Ali Bait Said | S9: =R9=C9 -> TRUE | T9: 20386956 | U9: =T9=I9 -> TRUE | V9: 0396064567750014 | W9: =V9=J9 -> TRUE | X9: BMUSOMRX | Y9: =X9=L9 -> TRUE
D10: =SUM(D4:D9) -> 5778.4 | F10: =SUM(F4:F9) -> 1444.6 | G10: =SUM(G4:G9) -> 1444.6 | H10: =SUM(H4:H9) -> 0
A13: Hassan Ghaly | C13: Suresh Bose | D13: Dr .Nasser Ali Baitsaid | F13: Aqeel Ali Ibrahim | K13: Shk. | W13: Said Al Bahanta
A14: Cost Accountant | C14: Sr.Operations Officer | D14: General Manager | F14: Vice Chairman | K14: Chairman | W14: DGM

Sheet center-June
A1: HAJEEF COW MILK PROCUREMENT FROM 01-June-2024 TO 30-June-2024
A2: Sr No. | B2: Farmer Code | C2: Farmer Name | D2: Milk Qty. (Ltr.) | E2: Avg. Rate (OMR/Ltr.) | F2: Amount (OMR) | G2: Paid | H2: Balance | I2: ID No. | J2: Remarks
A4: 6 | B4: 1344 | C4: SAID AMERAHMED BAITSAID | D4: 2447.8 | E4: 0.250 | F4: =D4*E4 -> 611.95 | G4: =608.65+3.3 -> 611.95 | H4: =F4-G4 -> 0 | I4: 4014519 | J4: 45567 | K4: 45680
A5: 15 | B5: 3057 | C5: ALI AHMED MOHAMMED AL KATHIRI | D5: 2434.4 | E5: 0.250 | F5: =D5*E5 -> 608.6 | G5: =607.025+1.575 -> 608.6 | H5: =F5-G5 -> 0 | I5: 626819 | J5: 18-09-2024 | K5: 45607
A6: 45 | B6: 3184 | C6: ALI MOHAMMED MUSALLAM AL BARAAMI | D6: 1682 | E6: 0.250 | F6: =D6*E6 -> 420.5 | G6: =419.575+0.925 -> 420.5 | H6: =F6-G6 -> 0 | I6: 6701602 | J6: 25-09-2024
A7: 74 | B7: 3515 | C7: Ali Ajaham Ali Bait said | D7: 1459.6 | E7: 0.250 | F7: =D7*E7 -> 364.9 | G7: =362.5+2.4 -> 364.9 | H7: =F7-G7 -> 0 | I7: 6645198 | J7: 16-09-2024 | K7: 09-12-241
D9: =SUM(D4:D8) -> 8023.8 | F9: =SUM(F4:F8) -> 2005.95 | G9: =SUM(G4:G8) -> 2005.95 | H9: =SUM(H4:H8) -> 0

Sheet center-Aug
A1: HAJEEF COW MILK PROCUREMENT FROM 01-Aug-2024 TO 31-Aug-2024
A2: Sr No. | B2: Farmer Code | C2: Farmer Name | D2: Milk Qty. (Ltr.) | E2: Avg. Rate (OMR/Ltr.) | F2: Amount (OMR) | G2: Paid | H2: Balance | I2: ID No. | J2: Remarks
A4: 1 | B4: 1007 | C4: AHMED ABDULLAH SAID AL RAWAS | D4: 6235.9 | E4: 0.250 | F4: =D4*E4 -> 1558.975 | G4: =F4 -> 1558.975 | H4: =F4-G4 -> 0 | I4: 1515504
A5: 2 | B5: 1041 | C5: AHMED SALIM ALI BAITSAID | D5: 3114.6 | E5: 0.250 | F5: =D5*E5 -> 778.65 | G5: =F5 -> 778.65 | H5: =F5-G5 -> 0 | I5: 6827729
A6: 3 | B6: 1125 | C6: MUSALLAM SAID ALI BAITSAID | D6: 6268.6 | E6: 0.250 | F6: =D6*E6 -> 1567.15 | G6: =1231.5+335.65 -> 1567.15 | H6: =F6-G6 -> 0 | I6: 6828774 | J6: 45607 | K6: 45630
A7: 4 | B7: 1222 | C7: Mahad Salim Abdulaziz Alkathiri | D7: 81 | E7: 0.250 | F7: =D7*E7 -> 20.25 | G7: =F7 -> 20.25 | H7: =F7-G7 -> 0 | I7: 31221
A8: 5 | B8: 1286 | C8: SALIM AMER AHMED AL YAFAEI | D8: 3072.9 | E8: 0.250 | F8: =D8*E8 -> 768.225 | G8: =F8 -> 768.225 | H8: =F8-G8 -> 0 | I8: 368056
A9: 6 | B9: 1344 | C9: SAID AMERAHMED BAITSAID | D9: 2377.9 | E9: 0.250 | F9: =D9*E9 -> 594.475 | G9: =F9 -> 594.475 | H9: =F9-G9 -> 0 | I9: 4014519 | J9: 45680
A10: 7 | B10: 1352 | C10: MOHAMMED MASOUD AJHAM ALSH AL KATHIRI | D10: 1265 | E10: 0.250 | F10: =D10*E10 -> 316.25 | G10: =F10 -> 316.25 | H10: =F10-G10 -> 0 | I10: 1627344
A11: 8 | B11: 1354 | C11: AHMED SAID HASSAN BAITSAID | D11: 2517.5 | E11: 0.250 | F11: =D11*E11 -> 629.375 | G11: =F11 -> 629.375 | H11: =F11-G11 -> 0 | I11: 925709
A12: 9 | B12: 1357 | C12: MUSALLAM SAID ALI BAIT SAID | D12: 5109.3 | E12: 0.250 | F12: =D12*E12 -> 1277.325 | G12: =F12 -> 1277.325 | H12: =F12-G12 -> 0 | I12: 1052276
A13: 10 | B13: 1359 | C13: MUSALLAM MUSTAHIL SAID BAIT SAID | D13: 3123.6 | E13: 0.250 | F13: =D13*E13 -> 780.9 | G13: =325.675+455.225 -> 780.9 | H13: =F13-G13 -> 0 | I13: 4812026 | J13: 45630 | K13: 2 times taken from jan feed
A14: 11 | B14: 1367 | C14: ALI MUSALLAM AHMED BAIT SAID | D14: 1000 | E14: 0.250 | F14: =D14*E14 -> 250 | G14: =F14 -> 250 | H14: =F14-G14 -> 0 | I14: 6663593
A15: 12 | B15: 1368 | C15: MOHAMMD SAID AHMED AL KATHIRI | D15: 4041.6 | E15: 0.250 | F15: =D15*E15 -> 1010.4 | G15: =1008.875+1.525 -> 1010.4 | H15: =F15-G15 -> 0 | I15: 561902 | J15: 45601 | K15: 26-11-214
A16: 13 | B16: 3002 | C16: KHALID MUBARAK ALI ATQOON AL SHAHRI | D16: 1666.8 | E16: 0.250 | F16: =D16*E16 -> 416.7 | G16: =416.55+0.15 -> 416.7 | H16: =F16-G16 -> 0 | I16: 21220177 | J16: 45607 | K16: 45629
A17: 14 | B17: 3035 | C17: TARIQ SALIM SUHAIL AL BARAMI | D17: 389.8 | E17: 0.250 | F17: =D17*E17 -> 97.45 | G17: =F17 -> 97.45 | H17: =F17-G17 -> 0 | I17: 6725058
A18: 15 | B18: 3057 | C18: ALI AHMED MOHAMMED AL KATHIRI | D18: 2746.6 | E18: 0.250 | F18: =D18*E18 -> 686.65 | G18: =685.575+1.075 -> 686.65 | H18: =F18-G18 -> 0 | I18: 626819 | J18: 45607 | K18: 45629
A19: 16 | B19: 3062 | C19: ALI MAHAD SILMOUN QATAN | D19: 2523.4 | E19: 0.250 | F19: =D19*E19 -> 630.85 | G19: =312.375+315.25+3.2252 -> 630.8502 | H19: =F19-G19 -> -0.0002 | I19: 300741 | J19: 45615 | K19: 45644 | L19: 45677
A20: 17 | B20: 3080 | C20: MUSALLAM BAKHIT AWADH L BARAAMI | D20: 1270.2 | E20: 0.250 | F20: =D20*E20 -> 317.55 | G20: =F20 -> 317.55 | H20: =F20-G20 -> 0 | I20: 14301608
A21: 18 | B21: 3086 | C21: MUSALLAM ALI MATOOQ TABOOK | D21: 892.4 | E21: 0.250 | F21: =D21*E21 -> 223.1 | G21: =222.7+0.4 -> 223.1 | H21: =F21-G21 -> 0 | I21: 300033 | J21: 45607 | K21: 38325
A22: 19 | B22: 3132 | C22: HASHIM SALIM ALI ATIF AL YAFAI | D22: 1301.6 | E22: 0.250 | F22: =D22*E22 -> 325.4 | G22: =211.825+113.575 -> 325.4 | H22: =F22-G22 -> 0 | I22: 14606296 | J22: 45637 | K22: 45663
A23: 20 | B23: 3134 | C23: HASSAN SUHAIL MAHAD QATAN | D23: 1332.2 | E23: 0.250 | F23: =D23*E23 -> 333.05 | G23: =F23 -> 333.05 | H23: =F23-G23 -> 0 | I23: 2154413 | J23: 45672
A24: 21 | B24: 3142 | C24: MOHAMMED AHMED SAAD MASHRAH AL SHAHRI | D24: 4325.4 | E24: 0.250 | F24: =D24*E24 -> 1081.35 | G24: =F24 -> 1081.35 | H24: =F24-G24 -> 0 | I24: 165497 | J24: 29-01-25
A25: 22 | B25: 3145 | C25: MOHAMMED BAKHIT MASOUD QATAN | D25: 3318.2 | E25: 0.250 | F25: =D25*E25 -> 829.55 | G25: =F25 -> 829.55 | H25: =F25-G25 -> 0 | I25: 1915745 | J25: DCF feed
A26: 23 | B26: 3147 | C26: KHALID SAID MAHAD KASHOUB | D26: 810 | E26: 0.250 | F26: =D26*E26 -> 202.5 | G26: =F26 -> 202.5 | H26: =F26-G26 -> 0 | I26: 1662414 | J26: DCF feed
A27: 24 | B27: 3148 | C27: MUSALLAM AHMED MAHTOUQ AL ZAWAMRI | D27: 1233 | E27: 0.250 | F27: =D27*E27 -> 308.25 | G27: =F27 -> 308.25 | H27: =F27-G27 -> 0 | I27: 19545736 | J27: DCF feed
A28: 25 | B28: 3149 | C28: ALI SAID ALI AL ZAWAMRI | D28: 1465.5 | E28: 0.250 | F28: =D28*E28 -> 366.375 | G28: =F28 -> 366.375 | H28: =F28-G28 -> 0 | I28: 4941095 | J28: 032-12-24
A29: 26 | B29: 3152 | C29: BAKHIT SALIM MAHAD QATAN | D29: 2129.7 | E29: 0.250 | F29: =D29*E29 -> 532.425 | G29: =356.6+174.6+1.225 -> 532.425 | H29: =F29-G29 -> 0 | I29: 941993 | J29: 10-10-2024,PR-063 | K29: 45600 | L29: 174 | M29: 45621
A30: 27 | B30: 3153 | C30: ALI MAHAD SAID QATAN | D30: 2394.9 | E30: 0.250 | F30: =D30*E30 -> 598.725 | G30: =176.925+417.1+4.7 -> 598.725 | H30: =F30-G30 -> 0 | I30: 6989479 | J30: 45637 | K30: 45658 | M30: 15-01-245
A31: 28 | B31: 3155 | C31: SAID BAKHIT MAHAD QATAN | D31: 631.4 | E31: 0.250 | F31: =D31*E31 -> 157.85 | G31: =F31 -> 157.85 | H31: =F31-G31 -> 0 | I31: 19188794
A32: 29 | B32: 3158 | C32: AHMED OBAIDAN AHMED AL KATHIRI | D32: 2447.4 | E32: 0.250 | F32: =D32*E32 -> 611.85 | G32: =F32 -> 611.85 | H32: =F32-G32 -> 0 | I32: 596869
A33: 30 | B33: 3159 | C33: AHMED BAKHIT SALEM AL BARAMI | D33: 720.3 | E33: 0.250 | F33: =D33*E33 -> 180.075 | G33: =F33 -> 180.075 | H33: =F33-G33 -> 0 | I33: 1297478 | J33: BT 22-01-2025
A34: 31 | B34: 3160 | C34: NAIF MUBARAK BAKHIT AL BARAAMI | D34: 1751.3 | E34: 0.250 | F34: =D34*E34 -> 437.825 | G34: =F34 -> 437.825 | H34: =F34-G34 -> 0 | I34: 2837163
A35: 32 | B35: 3162 | C35: MOHAMMED SAID FARAJ AL KATHIRI | D35: 4854.9 | E35: 0.250 | F35: =D35*E35 -> 1213.725 | G35: =F35 -> 1213.725 | H35: =F35-G35 -> 0 | I35: 7017227 | J35: BT 22-01-2025
A36: 33 | B36: 3164 | C36: ALI MUSALLLAM HASSAN BAITSAID | D36: 2451.8 | E36: 0.250 | F36: =D36*E36 -> 612.95 | G36: =611.1 -> 611.1 | H36: =F36-G36 -> 1.85 | I36: 7466062 | J36: 45673
A37: 34 | B37: 3165 | C37: KHALID MOHAMMED MASAAOD AGGHRIB AL SHAHRI | D37: 442.2 | E37: 0.250 | F37: =D37*E37 -> 110.55 | G37: =F37 -> 110.55 | H37: =F37-G37 -> 0 | I37: 19029628
A38: 35 | B38: 3169 | C38: MOHAMMED ALI SAID AL ZAWAMRY | D38: 1784.1 | E38: 0.250 | F38: =D38*E38 -> 446.025 | G38: =441.6 -> 441.6 | H38: =F38-G38 -> 4.425 | I38: 3068756 | J38: 45615
A39: 36 | B39: 3171 | C39: HATAM AWADH SAID QATAN | D39: 1076 | E39: 0.250 | F39: =D39*E39 -> 269 | G39: =268.425+0.575 -> 269 | H39: =F39-G39 -> 0 | I39: 7239057 | J39: 45601
A40: 37 | B40: 3172 | C40: Fatima Suleimon Salim ALBaramiyah | D40: 697.8 | E40: 0.250 | F40: =D40*E40 -> 174.45 | G40: =F40 -> 174.45 | H40: =F40-G40 -> 0 | I40: 5276984
A41: 38 | B41: 3173 | C41: MUSALLAM AHMED SAAD AL BARAAMI | D41: 1255 | E41: 0.250 | F41: =D41*E41 -> 313.75 | G41: =F41 -> 313.75 | H41: =F41-G41 -> 0 | I41: 6825655 | J41: DCF feed
A42: 39 | B42: 3174 | C42: AHMED MUSALLAM SAID QATAN | D42: 2034.9 | E42: 0.250 | F42: =D42*E42 -> 508.725 | G42: =F42 -> 508.725 | H42: =F42-G42 -> 0 | I42: 7547492 | J42: DCF feed
A43: 40 | B43: 3175 | C43: SAID AHMED NASIB AL BARAAMI | D43: 120.9 | E43: 0.250 | F43: =D43*E43 -> 30.225 | G43: =F43 -> 30.225 | H43: =F43-G43 -> 0 | I43: 7325076 | J43: 45691
A44: 41 | B44: 3176 | C44: KHAYAR ALI SAID AL BARAAMI | D44: 625.2 | E44: 0.250 | F44: =D44*E44 -> 156.3 | G44: =F44 -> 156.3 | H44: =F44-G44 -> 0 | I44: 12178145
A45: 42 | B45: 3179 | C45: SUHAIL MOHAMMED SUHAIL TABUK | D45: 1348.6 | E45: 0.250 | F45: =D45*E45 -> 337.15 | G45: =F45 -> 337.15 | H45: =F45-G45 -> 0 | I45: 1870852
A46: 43 | B46: 3181 | C46: TARIK MASOUD MAJADAH AL KATHIRI | D46: 1766.7 | E46: 0.250 | F46: =D46*E46 -> 441.675 | G46: =F46 -> 441.675 | H46: =F46-G46 -> 0 | I46: 6116067
A47: 44 | B47: 3183 | C47: Salim Musallam Ali Qatan | D47: 523.32 | E47: 0.250 | F47: =D47*E47 -> 130.83 | G47: =126.6+4.23 -> 130.83 | H47: =F47-G47 -> 0 | I47: 4955092 | J47: 45601 | K47: 45629
A48: 45 | B48: 3184 | C48: ALI MOHAMMED MUSALLAM AL BARAAMI | D48: 1841.3 | E48: 0.250 | F48: =D48*E48 -> 460.325 | G48: =F48 -> 460.325 | H48: =F48-G48 -> 0 | I48: 6701602
A49: 46 | B49: 3185 | C49: MOHAMMED ALI AHMED AMOOSH THOAR | D49: 1286.7 | E49: 0.250 | F49: =D49*E49 -> 321.675 | G49: =320.675+1 -> 321.675 | H49: =F49-G49 -> 0 | I49: 15179209 | J49: 45607 | K49: 45630
A50: 47 | B50: 3188 | C50: HASSAN BAKHIT AHMED QATAN | D50: 1081.8 | E50: 0.250 | F50: =D50*E50 -> 270.45 | G50: =268.075+2.375 -> 270.45 | H50: =F50-G50 -> 0 | I50: 19290729 | J50: 45601 | K50: 45629
A51: 48 | B51: 3189 | C51: SAID AHMED SAID AL ZAWAMRI | D51: 788.2 | E51: 0.250 | F51: =D51*E51 -> 197.05 | G51: =195.775+1.275 -> 197.05 | H51: =F51-G51 -> 0 | I51: 2802613 | J51: 45602 | K51: 45624
A52: 49 | B52: 3190 | C52: TAFOOL SILMOUN SALIM AL BARAMI | D52: 443.9 | E52: 0.250 | F52: =D52*E52 -> 110.975 | G52: =F52 -> 110.975 | H52: =F52-G52 -> 0 | I52: 3555896
A53: 50 | B53: 3192 | C53: GHAZI SALIM MASOUD TABOOK | D53: 610 | E53: 0.250 | F53: =D53*E53 -> 152.5 | G53: =F53 -> 152.5 | H53: =F53-G53 -> 0 | I53: 5271448 | J53: 45635
A54: 51 | B54: 3195 | C54: MUSTAHIL SAID MUSTAHIL AL BARAAMI | D54: 602.4 | E54: 0.250 | F54: =D54*E54 -> 150.6 | G54: =F54 -> 150.6 | H54: =F54-G54 -> 0 | I54: 675849
A55: 52 | B55: 3196 | C55: JASIM MOHAMMED SAID ALI AFIR AL ZAWAMARI | D55: 637.1 | E55: 0.250 | F55: =D55*E55 -> 159.275 | G55: =F55 -> 159.275 | H55: =F55-G55 -> 0 | I55: 21080217
A56: 53 | B56: 3197 | C56: MOHSIN SAID MOHAMED BA AWAIN | D56: 1840.8 | E56: 0.250 | F56: =D56*E56 -> 460.2 | G56: =F56 -> 460.2 | H56: =F56-G56 -> 0 | I56: 6479515
A57: 54 | B57: 3198 | C57: ADIL SAID AHMED AL ZAWAMRI | D57: 616.6 | E57: 0.250 | F57: =D57*E57 -> 154.15 | G57: =F57 -> 154.15 | H57: =F57-G57 -> 0 | I57: 6360793
A58: 55 | B58: 3310 | C58: AHMED SUHAIL SAID AL BARAMI | D58: 1288.6 | E58: 0.250 | F58: =D58*E58 -> 322.15 | G58: =F58 -> 322.15 | H58: =F58-G58 -> 0 | I58: 1007615 | J58: BT07-01-2025
A59: 56 | B59: 3324 | C59: BAKHIT AWADH BAKHIT AL BARAAMI | D59: 1283.8 | E59: 0.250 | F59: =D59*E59 -> 320.95 | G59: =F59 -> 320.95 | H59: =F59-G59 -> 0 | I59: 207402
A60: 57 | B60: 3330 | C60: Salim Ahmed Aubad Al kathiri | D60: 1464.3 | E60: 0.250 | F60: =D60*E60 -> 366.075 | G60: =F60 -> 366.075 | H60: =F60-G60 -> 0 | I60: 6375079
A61: 58 | B61: 3333 | C61: Mahad Salim Zaed Bait Said | D61: 1920 | E61: 0.250 | F61: =D61*E61 -> 480 | G61: =F61 -> 480 | H61: =F61-G61 -> 0 | I61: 757601
A62: 59 | B62: 3339 | C62: Khalid Ahmed Salim Amer Jid Almahri | D62: 329.5 | E62: 0.250 | F62: =D62*E62 -> 82.375 | G62: =79.8+2.575 -> 82.375 | H62: =F62-G62 -> 0 | I62: 12415718 | J62: 45601 | K62: 45628
A63: 60 | B63: 3500 | C63: Salim Mohammed Ahmed Al Kathiri | D63: 646.2 | E63: 0.250 | F63: =D63*E63 -> 161.55 | G63: =159.47+2.08 -> 161.55 | H63: =F63-G63 -> 0 | I63: 13525845 | J63: 45637 | K63: 45655
A64: 61 | B64: 3501 | C64: Said Masoud Ahmed Al kathiri | D64: 2365.9 | E64: 0.250 | F64: =D64*E64 -> 591.475 | G64: =F64 -> 591.475 | H64: =F64-G64 -> 0 | I64: 13525794 | J64: Bank Transfer-08-12-24
A65: 62 | B65: 3502 | C65: Ahmed Bakhit Ahmed Al Kathiri | D65: 1258.9 | E65: 0.250 | F65: =D65*E65 -> 314.725 | G65: =F65 -> 314.725 | H65: =F65-G65 -> 0 | I65: 22522336
A66: 63 | B66: 3503 | C66: Imad Bakhit Salim Bakhit Qatan | D66: 644.5 | E66: 0.250 | F66: =D66*E66 -> 161.125 | G66: =F66 -> 161.125 | H66: =F66-G66 -> 0 | I66: 9212492
A67: 64 | B67: 3504 | C67: Ali Salem Amer Al Kathiri | D67: 1206.3 | E67: 0.250 | F67: =D67*E67 -> 301.575 | G67: =F67 -> 301.575 | H67: =F67-G67 -> 0 | I67: 939641 | J67: BT 15-12-2024
A68: 65 | B68: 3506 | C68: Ahmed Masoud Salim Al Kathiri | D68: 260.9 | E68: 0.250 | F68: =D68*E68 -> 65.225 | G68: =F68 -> 65.225 | H68: =F68-G68 -> 0 | I68: 13307752
A69: 66 | B69: 3507 | C69: Bakhit Suhail Ahmed Qatan | D69: 1152.5 | E69: 0.250 | F69: =D69*E69 -> 288.125 | G69: =F69 -> 288.125 | H69: =F69-G69 -> 0 | I69: 1184669
A70: 67 | B70: 3508 | C70: Said Ali Said Al Zawamri | D70: 635.8 | E70: 0.250 | F70: =D70*E70 -> 158.95 | G70: =158.475 -> 158.475 | H70: =F70-G70 -> 0.475 | I70: 2567166 | J70: 45615
A71: 68 | B71: 3509 | C71: Asama Mohammed Ahmed Masharah Al Shahri | D71: 592 | E71: 0.250 | F71: =D71*E71 -> 148 | G71: =F71 -> 148 | H71: =F71-G71 -> 0 | I71: 22760088
A72: 69 | B72: 3510 | C72: Amer Ali Ahmed Al kathiri | D72: 601.9 | E72: 0.250 | F72: =D72*E72 -> 150.475 | G72: =F72 -> 150.475 | H72: =F72-G72 -> 0 | I72: 6920351
A73: 71 | B73: 3512 | C73: Ahmed Abdul Rahim Ali Al Kathiri | D73: 401 | E73: 0.250 | F73: =D73*E73 -> 100.25 | G73: =F73 -> 100.25 | H73: =F73-G73 -> 0 | I73: 5514631
A74: 72 | B74: 3513 | C74: Khair Salim Faraj Al Kathiri | D74: 1914.8 | E74: 0.250 | F74: =D74*E74 -> 478.7 | G74: =141.175+145.5+189.15+2.875 -> 478.7 | H74: =F74-G74 -> 0 | I74: 7047376 | J74: 45601 | K74: 45602 | L74: 45607 | M74: 45629
A75: 73 | B75: 3514 | C75: Said Salim Faraj Al Kathiri | D75: 921.5 | E75: 0.250 | F75: =D75*E75 -> 230.375 | G75: =F75 -> 230.375 | H75: =F75-G75 -> 0 | I75: 440083 | J75: DCF feed
A76: 74 | B76: 3515 | C76: Ali Ajaham Ali Bait said | D76: 1672.6 | E76: 0.250 | F76: =D76*E76 -> 418.15 | G76: =F76 -> 418.15 | H76: =F76-G76 -> 0 | I76: 6645198 | J76: 45635
A77: 75 | B77: 3516 | C77: Musallam Hassan Ali Bait Muhammed Bin Ahmed | D77: 1274.4 | E77: 0.250 | F77: =D77*E77 -> 318.6 | G77: =F77 -> 318.6 | H77: =F77-G77 -> 0 | I77: 1165877
A78: 76 | B78: 3517 | C78: Mohammed Salim Faraj Al Kathiri | D78: 1264.8 | E78: 0.250 | F78: =D78*E78 -> 316.2 | G78: =313.775+2.425 -> 316.2 | H78: =F78-G78 -> 0 | I78: 7047081 | J78: 45602 | K78: 45630
A79: 77 | B79: 3518 | C79: Ali Ahmed Ali Bait Said | D79: 845.6 | E79: 0.250 | F79: =D79*E79 -> 211.4 | G79: =F79 -> 211.4 | H79: =F79-G79 -> 0 | I79: 20386956
A80: 78 | B80: 3519 | C80: Masoud Salim Faraj Al Kathiri | D80: 618.4 | E80: 0.250 | F80: =D80*E80 -> 154.6 | G80: =149.875+4.725 -> 154.6 | H80: =F80-G80 -> 0 | I80: 7047221 | J80: 45602 | K80: 45630
A81: 79 | B81: 3520 | C81: Musallam Mahad Suhail Al Barami | D81: 949.7 | E81: 0.250 | F81: =D81*E81 -> 237.425 | G81: =F81 -> 237.425 | H81: =F81-G81 -> 0 | I81: 5665362
A82: 80 | B82: 3521 | C82: Omar Said Awadh Bait Said | D82: 3863.6 | E82: 0.250 | F82: =D82*E82 -> 965.9 | G82: =F82 -> 965.9 | H82: =F82-G82 -> 0 | I82: 7064553
A83: 81 | B83: 3522 | C83: Said Ahmed Ali Qatan | D83: 580.5 | E83: 0.250 | F83: =D83*E83 -> 145.125 | G83: =F83 -> 145.125 | H83: =F83-G83 -> 0 | I83: 11365191
D84: =SUM(D4:D83) -> 130246.22 | F84: =SUM(F4:F83) -> 32561.555 | G84: =SUM(G4:G83) -> 32554.805 | H84: =SUM(H4:H83) -> 6.7498
G86: =G67+G64+G58 -> 1215.2
G87: =G84-G86 -> 31339.605
G88: =G87/F84 -> 0.96247262

Sheet Center-Sept
A1: HAJEEF COW MILK PROCUREMENT FROM 01-Sept-2024 TO 30-Sept-2024
A2: Sr No. | B2: Farmer Code | C2: Farmer Name | D2: Milk Qty. (Ltr.) | E2: Avg. Rate (OMR/Ltr.) | F2: Amount (OMR) | G2: Paid | H2: Balance | I2: Remarks
A4: 1 | B4: 1007 | C4: AHMED ABDULLAH SAID AL RAWAS | D4: 6082.2 | E4: 0.250 | F4: =D4*E4 -> 1520.55 | H4: =F4-G4 -> 1520.55 | M4: 1007 | N4: =M4=B4 -> TRUE | O4: AHMED ABDULLAH SAID AL RAWAS | P4: =O4=C4 -> TRUE | Q4: 1515504 | R4: =Q4=#REF! -> #REF! | S4: 0615500670380001 | T4: =S4=#REF! -> #REF! | U4: BMUSOMRXISL | V4: =U4=#REF! -> #REF!
A5: 2 | B5: 1041 | C5: AHMED SALIM ALI BAITSAID | D5: 2583.1 | E5: 0.250 | F5: =D5*E5 -> 645.775 | H5: =F5-G5 -> 645.775 | M5: 1041 | N5: =M5=B5 -> TRUE | O5: AHMED SALIM ALI BAITSAID | P5: =O5=C5 -> TRUE | Q5: 6827729 | R5: =Q5=#REF! -> #REF! | S5: 0406003463970017 | T5: =S5=#REF! -> #REF! | U5: BMUSOMRX | V5: =U5=#REF! -> #REF!
A6: 3 | B6: 1125 | C6: MUSALLAM SAID ALI BAITSAID | D6: 6122.4 | E6: 0.250 | F6: =D6*E6 -> 1530.6 | G6: =1526.35+4.25 -> 1530.6 | H6: =F6-G6 -> 0 | I6: 45630 | J6: 45658 | M6: 1125 | N6: =M6=B6 -> TRUE | O6: MUSALLAM SAID ALI BAITSAID | P6: =O6=C6 -> TRUE | Q6: 6828774 | R6: =Q6=#REF! -> #REF! | S6: 01011456108001 | T6: =S6=#REF! -> #REF! | U6: BDOFOMRU | V6: =U6=#REF! -> #REF!
A7: 4 | B7: 1222 | C7: Mahad Salim Abdulaziz Alkathiri | D7: 965.7 | E7: 0.250 | F7: =D7*E7 -> 241.425 | H7: =F7-G7 -> 241.425
A8: 5 | B8: 1286 | C8: SALIM AMER AHMED AL YAFAEI | D8: 2975.1 | E8: 0.250 | F8: =D8*E8 -> 743.775 | H8: =F8-G8 -> 743.775 | M8: 1286 | N8: =M8=B8 -> TRUE | O8: SALIM AMER AHMED AL YAFAEI | P8: =O8=C8 -> TRUE | Q8: 368056 | R8: =Q8=#REF! -> #REF! | S8: 0406003218280013 | T8: =S8=#REF! -> #REF! | U8: BMUSOMRX | V8: =U8=#REF! -> #REF!
A9: 6 | B9: 1344 | C9: SAID AMERAHMED BAITSAID | D9: 2380 | E9: 0.250 | F9: =D9*E9 -> 595 | G9: =590.275+4.725 -> 595 | H9: =F9-G9 -> 0 | I9: 45680 | J9: DCF-27-01-25 | M9: 1344 | N9: =M9=B9 -> TRUE | O9: SAID AMERAHMED BAITSAID | P9: =O9=C9 -> TRUE | Q9: 4014519 | R9: =Q9=#REF! -> #REF! | S9: 3109370559500 | T9: =S9=#REF! -> #REF! | U9: OMABOMRU | V9: =U9=#REF! -> #REF!
A10: 7 | B10: 1352 | C10: MOHAMMED MASOUD AJHAM ALSH AL KATHIRI | D10: 1605.1 | E10: 0.250 | F10: =D10*E10 -> 401.275 | H10: =F10-G10 -> 401.275 | M10: 1352 | N10: =M10=B10 -> TRUE | O10: MOHAMMED MASOUD AJHAM ALSH AL KATHIRI | P10: =O10=C10 -> TRUE | Q10: 1627344 | R10: =Q10=#REF! -> #REF! | S10: 0397046773470015 | T10: =S10=#REF! -> #REF! | U10: BMUSOMRX | V10: =U10=#REF! -> #REF!
A11: 8 | B11: 1354 | C11: AHMED SAID HASSAN BAITSAID | D11: 2445.3 | E11: 0.250 | F11: =D11*E11 -> 611.325 | H11: =F11-G11 -> 611.325 | M11: 1354 | N11: =M11=B11 -> TRUE | O11: AHMED SAID HASSAN BAITSAID | P11: =O11=C11 -> TRUE | Q11: 925709 | R11: =Q11=#REF! -> #REF! | S11: 0406018690130014 | T11: =S11=#REF! -> #REF! | U11: BMUSOMRX | V11: =U11=#REF! -> #REF!
A12: 9 | B12: 1357 | C12: MUSALLAM SAID ALI BAIT SAID | D12: 4796.9 | E12: 0.250 | F12: =D12*E12 -> 1199.225 | H12: =F12-G12 -> 1199.225 | M12: 1357 | N12: =M12=B12 -> TRUE | O12: MUSALLAM SAID ALI BAIT SAID | P12: =O12=C12 -> TRUE | Q12: 1052276 | R12: =Q12=#REF! -> #REF! | S12: 01040280323001 | T12: =S12=#REF! -> #REF! | U12: BDOFOMRU | V12: =U12=#REF! -> #REF!
A13: 10 | B13: 1359 | C13: MUSALLAM MUSTAHIL SAID BAIT SAID | D13: 2673.6 | E13: 0.250 | F13: =D13*E13 -> 668.4 | G13: =665.125+3.275 -> 668.4 | H13: =F13-G13 -> 0 | I13: 45630 | J13: 45655 | M13: 1359 | N13: =M13=B13 -> TRUE | O13: MUSALLAM MUSTAHIL SAID BAIT SAID | P13: =O13=C13 -> TRUE | Q13: 4812026 | R13: =Q13=#REF! -> #REF! | S13: 1083517184017 | T13: =S13=#REF! -> #REF! | U13: NBOMOMRX | V13: =U13=#REF! -> #REF!
A14: 11 | B14: 1367 | C14: ALI MUSALLAM AHMED BAIT SAID | D14: 943.9 | E14: 0.250 | F14: =D14*E14 -> 235.975 | G14: =F14 -> 235.975 | H14: =F14-G14 -> 0 | I14: 45902 | M14: 1367 | N14: =M14=B14 -> TRUE | O14: ALI MUSALLAM AHMED BAIT SAID | P14: =O14=C14 -> TRUE | Q14: 6663593 | R14: =Q14=#REF! -> #REF! | S14: 0406003006560016 | T14: =S14=#REF! -> #REF! | U14: BMUSOMRX | V14: =U14=#REF! -> #REF!
A15: 12 | B15: 1368 | C15: MOHAMMD SAID AHMED AL KATHIRI | D15: 3718.3 | E15: 0.250 | F15: =D15*E15 -> 929.575 | G15: =F15 -> 929.575 | H15: =F15-G15 -> 0 | I15: 45622 | M15: 1368 | N15: =M15=B15 -> TRUE | O15: MOHAMMD SAID AHMED AL KATHIRI | P15: =O15=C15 -> TRUE | Q15: 561902 | R15: =Q15=#REF! -> #REF! | S15: 01040854387001 | T15: =S15=#REF! -> #REF! | U15: BDOFOMRU | V15: =U15=#REF! -> #REF!
A16: 13 | B16: 3002 | C16: KHALID MUBARAK ALI ATQOON AL SHAHRI | D16: 1600.5 | E16: 0.250 | F16: =D16*E16 -> 400.125 | G16: =399.45+0.675 -> 400.125 | H16: =F16-G16 -> 0 | I16: 45629 | J16: 45658 | M16: 3002 | N16: =M16=B16 -> TRUE | O16: KHALID MUBARAK ALI ATQOON AL SHAHRI | P16: =O16=C16 -> TRUE | Q16: 21220177 | R16: =Q16=#REF! -> #REF! | S16: 0401016727580038 | T16: =S16=#REF! -> #REF! | U16: BMUSOMRX | V16: =U16=#REF! -> #REF!
A17: 14 | B17: 3035 | C17: TARIQ SALIM SUHAIL AL BARAMI | E17: 0.250 | F17: =D17*E17 -> 0 | H17: =F17-G17 -> 0 | M17: 3035 | N17: =M17=B17 -> TRUE | O17: TARIQ SALIM SUHAIL AL BARAMI | P17: =O17=C17 -> TRUE | Q17: 6725058 | R17: =Q17=#REF! -> #REF! | S17: 01011059048001 | T17: =S17=#REF! -> #REF! | U17: BDOFOMRU | V17: =U17=#REF! -> #REF!
A18: 15 | B18: 3057 | C18: ALI AHMED MOHAMMED AL KATHIRI | D18: 2488.3 | E18: 0.250 | F18: =D18*E18 -> 622.075 | G18: =619.725+2.35 -> 622.075 | H18: =F18-G18 -> 0 | I18: 45629 | J18: 29-1224 | M18: 3057 | N18: =M18=B18 -> TRUE | O18: ALI AHMED MOHAMMED AL KATHIRI | P18: =O18=C18 -> TRUE | Q18: 626819 | R18: =Q18=#REF! -> #REF! | S18: 0397003510460014 | T18: =S18=#REF! -> #REF! | U18: BMUSOMRX | V18: =U18=#REF! -> #REF!
A19: 16 | B19: 3062 | C19: ALI MAHAD SILMOUN QATAN | D19: 3216.3 | E19: 0.250 | F19: =D19*E19 -> 804.075 | G19: =239.28+242.5 -> 481.78 | H19: =F19-G19 -> 322.295 | I19: 45677 | J19: 13-2-25 | M19: 3062 | N19: =M19=B19 -> TRUE | O19: ALI MAHAD SILMOUN QATAN | P19: =O19=C19 -> TRUE | Q19: 300741 | R19: =Q19=#REF! -> #REF! | S19: 0397004203200017 | T19: =S19=#REF! -> #REF! | U19: BMUSOMRX | V19: =U19=#REF! -> #REF!
A20: 17 | B20: 3080 | C20: MUSALLAM BAKHIT AWADH L BARAAMI | D20: 1219.6 | E20: 0.250 | F20: =D20*E20 -> 304.9 | H20: =F20-G20 -> 304.9 | M20: 3080 | N20: =M20=B20 -> TRUE | O20: MUSALLAM BAKHIT AWADH L BARAAMI | P20: =O20=C20 -> TRUE | Q20: 14301608 | R20: =Q20=#REF! -> #REF! | S20: 0397003041020024 | T20: =S20=#REF! -> #REF! | U20: BMUSOMRX | V20: =U20=#REF! -> #REF!
A21: 18 | B21: 3086 | C21: MUSALLAM ALI MATOOQ TABOOK | D21: 1179.1 | E21: 0.250 | F21: =D21*E21 -> 294.775 | G21: =290.6 -> 290.6 | H21: =F21-G21 -> 4.175 | I21: 45630 | M21: 3086 | N21: =M21=B21 -> TRUE | O21: MUSALLAM ALI MATOOQ TABOOK | P21: =O21=C21 -> TRUE | Q21: 300033 | R21: =Q21=#REF! -> #REF! | S21: 0397003905720015 | T21: =S21=#REF! -> #REF! | U21: BMUSOMRX | V21: =U21=#REF! -> #REF!
A22: 19 | B22: 3132 | C22: HASHIM SALIM ALI ATIF AL YAFAI | D22: 1254.1 | E22: 0.250 | F22: =D22*E22 -> 313.525 | G22: =F22 -> 313.525 | H22: =F22-G22 -> 0 | I22: 45663 | M22: 3132 | N22: =M22=B22 -> TRUE | O22: HASHIM SALIM ALI ATIF AL YAFAI | P22: =O22=C22 -> TRUE | Q22: 14606296 | R22: =Q22=#REF! -> #REF! | S22: 0401024314310011 | T22: =S22=#REF! -> #REF! | U22: BMUSOMRX | V22: =U22=#REF! -> #REF!
A23: 20 | B23: 3134 | C23: HASSAN SUHAIL MAHAD QATAN | D23: 981.4 | E23: 0.250 | F23: =D23*E23 -> 245.35 | G23: =F23 -> 245.35 | H23: =F23-G23 -> 0 | I23: 45672 | M23: 3134 | N23: =M23=B23 -> TRUE | O23: HASSAN SUHAIL MAHAD QATAN | P23: =O23=C23 -> TRUE | Q23: 2154413 | R23: =Q23=#REF! -> #REF! | S23: 01010850952003 | T23: =S23=#REF! -> #REF! | U23: BDOFOMRU | V23: =U23=#REF! -> #REF!
A24: 21 | B24: 3142 | C24: MOHAMMED AHMED SAAD MASHRAH AL SHAHRI | D24: 4550.2 | E24: 0.250 | F24: =D24*E24 -> 1137.55 | G24: =F24 -> 1137.55 | H24: =F24-G24 -> 0 | I24: 29-01-25 | M24: 3142 | N24: =M24=B24 -> TRUE | O24: MOHAMMED AHMED SAAD MASHRAH AL SHAHRI | P24: =O24=C24 -> TRUE | Q24: 165497 | R24: =Q24=#REF! -> #REF! | S24: 3129019324700 | T24: =S24=#REF! -> #REF! | U24: OMABOMRU | V24: =U24=#REF! -> #REF!
A25: 22 | B25: 3145 | C25: MOHAMMED BAKHIT MASOUD QATAN | D25: 2985.2 | E25: 0.250 | F25: =D25*E25 -> 746.3 | G25: =F25 -> 746.3 | H25: =F25-G25 -> 0 | I25: DCF FEED
A26: 23 | B26: 3147 | C26: KHALID SAID MAHAD KASHOUB | D26: 1415.1 | E26: 0.250 | F26: =D26*E26 -> 353.775 | G26: =F26 -> 353.775 | H26: =F26-G26 -> 0 | I26: DCF FEED | M26: 3147 | N26: =M26=B26 -> TRUE | O26: KHALID SAID MAHAD KASHOUB | P26: =O26=C26 -> TRUE | Q26: 1662414 | R26: =Q26=#REF! -> #REF! | S26: 3129770819700 | T26: =S26=#REF! -> #REF! | U26: OMABOMRU | V26: =U26=#REF! -> #REF!
A27: 24 | B27: 3148 | C27: MUSALLAM AHMED MAHTOUQ AL ZAWAMRI | D27: 1113.4 | E27: 0.250 | F27: =D27*E27 -> 278.35 | G27: =F27 -> 278.35 | H27: =F27-G27 -> 0 | I27: 15-01-25 | M27: 3148 | N27: =M27=B27 -> TRUE | O27: MUSALLAM AHMED MAHTOUQ AL ZAWAMRI | P27: =O27=C27 -> TRUE | Q27: 19545736 | R27: =Q27=#REF! -> #REF! | S27: 01011208343002 | T27: =S27=#REF! -> #REF! | U27: BDOFOMRU | V27: =U27=#REF! -> #REF!
A28: 25 | B28: 3149 | C28: ALI SAID ALI AL ZAWAMRI | D28: 1444.2 | E28: 0.250 | F28: =D28*E28 -> 361.05 | G28: =360.4+0.65 -> 361.05 | H28: =F28-G28 -> 0 | I28: 45629 | J28: 45663 | M28: 3149 | N28: =M28=B28 -> TRUE | O28: ALI SAID ALI AL ZAWAMRI | P28: =O28=C28 -> TRUE | Q28: 4941095 | R28: =Q28=#REF! -> #REF! | S28: 1104036354300 | T28: =S28=#REF! -> #REF! | U28: AUBOOMRU | V28: =U28=#REF! -> #REF!
A29: 26 | B29: 3152 | C29: BAKHIT SALIM MAHAD QATAN | D29: 2172.5 | E29: 0.250 | F29: =D29*E29 -> 543.125 | G29: =541.575+1.55 -> 543.125 | H29: =F29-G29 -> 0 | I29: 45621 | J29: 45662 | M29: 3152 | N29: =M29=B29 -> TRUE | O29: BAKHIT SALIM MAHAD QATAN | P29: =O29=C29 -> TRUE | Q29: 941993 | R29: =Q29=#REF! -> #REF! | S29: 01042574515001 | T29: =S29=#REF! -> #REF! | U29: BDOFOMRU | V29: =U29=#REF! -> #REF!
A30: 27 | B30: 3153 | C30: ALI MAHAD SAID QATAN | D30: 2780.2 | E30: 0.250 | F30: =D30*E30 -> 695.05 | G30: =149.3+541.7+4.05 -> 695.05 | H30: =F30-G30 -> 0 | I30: 45672 | J30: 45691 | K30: 13-2-25 | M30: 3153 | N30: =M30=B30 -> TRUE | O30: ALI MAHAD SAID QATAN | P30: =O30=C30 -> TRUE | Q30: 6989479 | R30: =Q30=#REF! -> #REF! | S30: 0397003672070015 | T30: =S30=#REF! -> #REF! | U30: BMUSOMRX | V30: =U30=#REF! -> #REF!
A31: 28 | B31: 3155 | C31: SAID BAKHIT MAHAD QATAN | D31: 615.7 | E31: 0.250 | F31: =D31*E31 -> 153.925 | H31: =F31-G31 -> 153.925 | M31: 3155 | N31: =M31=B31 -> TRUE | O31: SAID BAKHIT MAHAD QATAN | P31: =O31=C31 -> TRUE | Q31: 19188794 | R31: =Q31=#REF! -> #REF! | S31: 0402003042750013 | T31: =S31=#REF! -> #REF! | U31: BMUSOMRX | V31: =U31=#REF! -> #REF!
A32: 29 | B32: 3158 | C32: AHMED OBAIDAN AHMED AL KATHIRI | D32: 2320.7 | E32: 0.250 | F32: =D32*E32 -> 580.175 | H32: =F32-G32 -> 580.175 | M32: 3158 | N32: =M32=B32 -> TRUE | O32: AHMED OBAIDAN AHMED AL KATHIRI | P32: =O32=C32 -> TRUE | Q32: 596869 | R32: =Q32=#REF! -> #REF! | S32: 0401049081340015 | T32: =S32=#REF! -> #REF! | U32: BMUSOMRX | V32: =U32=#REF! -> #REF!
A33: 30 | B33: 3159 | C33: AHMED BAKHIT SALEM AL BARAMI | D33: 540.7 | E33: 0.250 | F33: =D33*E33 -> 135.175 | G33: =F33 -> 135.175 | H33: =F33-G33 -> 0 | I33: BT 22-01-2025 | M33: 3159 | N33: =M33=B33 -> TRUE | O33: AHMED BAKHIT SALEM AL BARAMI | P33: =O33=C33 -> TRUE | Q33: 1297478 | R33: =Q33=#REF! -> #REF! | S33: 0397003703480012 | T33: =S33=#REF! -> #REF! | U33: BMUSOMRX | V33: =U33=#REF! -> #REF!
A34: 31 | B34: 3160 | C34: NAIF MUBARAK BAKHIT AL BARAAMI | D34: 1794.3 | E34: 0.250 | F34: =D34*E34 -> 448.575 | H34: =F34-G34 -> 448.575 | M34: 3160 | N34: =M34=B34 -> TRUE | O34: NAIF MUBARAK BAKHIT AL BARAAMI | P34: =O34=C34 -> TRUE | Q34: 2837163 | R34: =Q34=#REF! -> #REF! | S34: 00510031862001 | T34: =S34=#REF! -> #REF! | U34: BNZWOMRX | V34: =U34=#REF! -> #REF!
A35: 32 | B35: 3162 | C35: MOHAMMED SAID FARAJ AL KATHIRI | D35: 4955.4 | E35: 0.250 | F35: =D35*E35 -> 1238.85 | H35: =F35-G35 -> 1238.85 | M35: 3162 | N35: =M35=B35 -> TRUE | O35: MOHAMMED SAID FARAJ AL KATHIRI | P35: =O35=C35 -> TRUE | Q35: 7017227 | R35: =Q35=#REF! -> #REF! | S35: 01010940071001 | T35: =S35=#REF! -> #REF! | U35: BDOFOMRU | V35: =U35=#REF! -> #REF!
A36: 33 | B36: 3164 | C36: ALI MUSALLLAM HASSAN BAITSAID | D36: 2373.1 | E36: 0.250 | F36: =D36*E36 -> 593.275 | H36: =F36-G36 -> 593.275 | M36: 3164 | N36: =M36=B36 -> TRUE | O36: ALI MUSALLLAM HASSAN BAITSAID | P36: =O36=C36 -> TRUE | Q36: 7466062 | R36: =Q36=#REF! -> #REF! | S36: 01646038607001 | T36: =S36=#REF! -> #REF! | U36: BDOFOMRUMIB | V36: =U36=#REF! -> #REF!
A37: 34 | B37: 3165 | C37: KHALID MOHAMMED MASAAOD AGGHRIB AL SHAHRI | D37: 494.4 | E37: 0.250 | F37: =D37*E37 -> 123.6 | H37: =F37-G37 -> 123.6 | M37: 3165 | N37: =M37=B37 -> TRUE | O37: KHALID MOHAMMED MASAAOD AGGHRIB AL SHAHRI | P37: =O37=C37 -> TRUE | Q37: 19029628 | R37: =Q37=#REF! -> #REF! | S37: 01011251497002 | T37: =S37=#REF! -> #REF! | U37: BDOFOMRU | V37: =U37=#REF! -> #REF!
A38: 35 | B38: 3169 | C38: MOHAMMED ALI SAID AL ZAWAMRY | D38: 1728.9 | E38: 0.250 | F38: =D38*E38 -> 432.225 | H38: =F38-G38 -> 432.225 | M38: 3169 | N38: =M38=B38 -> TRUE | O38: MOHAMMED ALI SAID AL ZAWAMRY | P38: =O38=C38 -> TRUE | Q38: 3068756 | R38: =Q38=#REF! -> #REF! | S38: 01012573317001 | T38: =S38=#REF! -> #REF! | U38: BDOFOMRU | V38: =U38=#REF! -> #REF!
A39: 36 | B39: 3171 | C39: HATAM AWADH SAID QATAN | D39: 1028.2 | E39: 0.250 | F39: =D39*E39 -> 257.05 | G39: =256.475+0.575 -> 257.05 | H39: =F39-G39 -> 0 | I39: 45629 | J39: 45663 | M39: 3171 | N39: =M39=B39 -> TRUE | O39: HATAM AWADH SAID QATAN | P39: =O39=C39 -> TRUE | Q39: 7239057 | R39: =Q39=#REF! -> #REF! | S39: 3109607126500 | T39: =S39=#REF! -> #REF! | U39: OMABOMRU | V39: =U39=#REF! -> #REF!
A40: 37 | B40: 3172 | C40: Fatima Suleimon Salim ALBaramiyah | D40: 592.8 | E40: 0.250 | F40: =D40*E40 -> 148.2 | H40: =F40-G40 -> 148.2
A41: 38 | B41: 3173 | C41: MUSALLAM AHMED SAAD AL BARAAMI | D41: 1535.8 | E41: 0.250 | F41: =D41*E41 -> 383.95 | G41: =F41 -> 383.95 | H41: =F41-G41 -> 0 | M41: 3173 | N41: =M41=B41 -> TRUE | O41: MUSALLAM AHMED SAAD AL BARAAMI | P41: =O41=C41 -> TRUE | Q41: 6825655 | R41: =Q41=#REF! -> #REF! | S41: 0397004380200011 | T41: =S41=#REF! -> #REF! | U41: BMUSOMRX | V41: =U41=#REF! -> #REF!
A42: 39 | B42: 3174 | C42: AHMED MUSALLAM SAID QATAN | D42: 1887.9 | E42: 0.250 | F42: =D42*E42 -> 471.975 | G42: =F42 -> 471.975 | H42: =F42-G42 -> 0 | M42: 3174 | N42: =M42=B42 -> TRUE | O42: AHMED MUSALLAM SAID QATAN | P42: =O42=C42 -> TRUE | Q42: 7547492 | R42: =Q42=#REF! -> #REF! | S42: 0401002379960017 | T42: =S42=#REF! -> #REF! | U42: BMUSOMRX | V42: =U42=#REF! -> #REF!
A43: 40 | B43: 3175 | C43: SAID AHMED NASIB AL BARAAMI | D43: 546.5 | E43: 0.250 | F43: =D43*E43 -> 136.625 | G43: =F43 -> 136.625 | H43: =F43-G43 -> 0 | I43: 45691 | M43: 3175 | N43: =M43=B43 -> TRUE | O43: SAID AHMED NASIB AL BARAAMI | P43: =O43=C43 -> TRUE | Q43: 7325076 | R43: =Q43=#REF! -> #REF! | S43: 1006794849001 | T43: =S43=#REF! -> #REF! | U43: NBOMOMRX | V43: =U43=#REF! -> #REF!
A44: 41 | B44: 3176 | C44: KHAYAR ALI SAID AL BARAAMI | D44: 611.6 | E44: 0.250 | F44: =D44*E44 -> 152.9 | H44: =F44-G44 -> 152.9
A45: 42 | B45: 3179 | C45: SUHAIL MOHAMMED SUHAIL TABUK | D45: 1787.1 | E45: 0.250 | F45: =D45*E45 -> 446.775 | H45: =F45-G45 -> 446.775 | M45: 3179 | N45: =M45=B45 -> TRUE | O45: SUHAIL MOHAMMED SUHAIL TABUK | P45: =O45=C45 -> TRUE | Q45: 1870852 | R45: =Q45=#REF! -> #REF! | S45: 3129685484720 | T45: =S45=#REF! -> #REF! | U45: OMABOMRU | V45: =U45=#REF! -> #REF!
A46: 43 | B46: 3181 | C46: TARIK MASOUD MAJADAH AL KATHIRI | D46: 1874.4 | E46: 0.250 | F46: =D46*E46 -> 468.6 | H46: =F46-G46 -> 468.6 | M46: 3181 | N46: =M46=B46 -> TRUE | O46: TARIK MASOUD MAJADAH AL KATHIRI | P46: =O46=C46 -> TRUE | Q46: 6116067 | R46: =Q46=#REF! -> #REF! | S46: 3109710314700 | T46: =S46=#REF! -> #REF! | U46: OMABOMRU | V46: =U46=#REF! -> #REF!
A47: 44 | B47: 3183 | C47: Salim Musallam Ali Qatan | D47: 333 | E47: 0.250 | F47: =D47*E47 -> 83.25 | G47: =81.37+1.88 -> 83.25 | H47: =F47-G47 -> 0 | I47: 45629 | J47: 45658 | M47: 3183 | N47: =M47=B47 -> TRUE | O47: Salim Musallam Ali Qatan | P47: =O47=C47 -> TRUE | Q47: 4955092 | R47: =Q47=#REF! -> #REF! | S47: 0401002697260019 | T47: =S47=#REF! -> #REF! | U47: BMUSOMRX | V47: =U47=#REF! -> #REF!
A48: 45 | B48: 3184 | C48: ALI MOHAMMED MUSALLAM AL BARAAMI | D48: 1876.6 | E48: 0.250 | F48: =D48*E48 -> 469.15 | H48: =F48-G48 -> 469.15 | M48: 3184 | N48: =M48=B48 -> TRUE | O48: ALI MOHAMMED MUSALLAM AL BARAAMI | P48: =O48=C48 -> TRUE | Q48: 6701602 | R48: =Q48=#REF! -> #REF! | S48: 01011004872002 | T48: =S48=#REF! -> #REF! | U48: BDOFOMRU | V48: =U48=#REF! -> #REF!
A49: 46 | B49: 3185 | C49: MOHAMMED ALI AHMED AMOOSH THOAR | D49: 1233.8 | E49: 0.250 | F49: =D49*E49 -> 308.45 | G49: =304.55+3.9 -> 308.45 | H49: =F49-G49 -> 0 | I49: 45630 | J49: 45663 | M49: 3185 | N49: =M49=B49 -> TRUE | O49: MOHAMMED ALI AHMED AMOOSH THOAR | P49: =O49=C49 -> TRUE | Q49: 15179209 | R49: =Q49=#REF! -> #REF! | S49: 0405020308900019 | T49: =S49=#REF! -> #REF! | U49: BMUSOMRX | V49: =U49=#REF! -> #REF!
A50: 47 | B50: 3188 | C50: HASSAN BAKHIT AHMED QATAN | D50: 1030.1 | E50: 0.250 | F50: =D50*E50 -> 257.525 | G50: =254.675+2.85 -> 257.525 | H50: =F50-G50 -> 0 | I50: 45629 | J50: 45663 | M50: 3188 | N50: =M50=B50 -> TRUE | O50: HASSAN BAKHIT AHMED QATAN | P50: =O50=C50 -> TRUE | Q50: 19290729 | R50: =Q50=#REF! -> #REF! | S50: 01041574026001 | T50: =S50=#REF! -> #REF! | U50: BDOFOMRU | V50: =U50=#REF! -> #REF!
A51: 48 | B51: 3189 | C51: SAID AHMED SAID AL ZAWAMRI | D51: 975 | E51: 0.250 | F51: =D51*E51 -> 243.75 | G51: =240.775+2.975 -> 243.75 | H51: =F51-G51 -> 0 | I51: 45624 | J51: 45658 | M51: 3189 | N51: =M51=B51 -> TRUE | O51: SAID AHMED SAID AL ZAWAMRI | P51: =O51=C51 -> TRUE | Q51: 2802613 | R51: =Q51=#REF! -> #REF! | S51: 0405002746200013 | T51: =S51=#REF! -> #REF! | U51: BMUSOMRX | V51: =U51=#REF! -> #REF!
A52: 49 | B52: 3190 | C52: TAFOOL SILMOUN SALIM AL BARAMI | E52: 0.250 | F52: =D52*E52 -> 0 | H52: =F52-G52 -> 0
A53: 50 | B53: 3192 | C53: GHAZI SALIM MASOUD TABOOK | D53: 1119.5 | E53: 0.250 | F53: =D53*E53 -> 279.875 | G53: =276.53 -> 276.53 | H53: =F53-G53 -> 3.345 | I53: 45635 | M53: 3192 | N53: =M53=B53 -> TRUE | O53: GHAZI SALIM MASOUD TABOOK | P53: =O53=C53 -> TRUE | Q53: 5271448 | R53: =Q53=#REF! -> #REF! | S53: 0426012948850015 | T53: =S53=#REF! -> #REF! | U53: BMUSOMRX | V53: =U53=#REF! -> #REF!
A54: 51 | B54: 3195 | C54: MUSTAHIL SAID MUSTAHIL AL BARAAMI | D54: 598.4 | E54: 0.250 | F54: =D54*E54 -> 149.6 | H54: =F54-G54 -> 149.6 | M54: 3195 | N54: =M54=B54 -> TRUE | O54: MUSTAHIL SAID MUSTAHIL AL BARAAMI | P54: =O54=C54 -> TRUE | Q54: 675849 | R54: =Q54=#REF! -> #REF! | S54: 01011097969001 | T54: =S54=#REF! -> #REF! | U54: BDOFOMRU | V54: =U54=#REF! -> #REF!
A55: 52 | B55: 3196 | C55: JASIM MOHAMMED SAID ALI AFIR AL ZAWAMARI | D55: 624.8 | E55: 0.250 | F55: =D55*E55 -> 156.2 | H55: =F55-G55 -> 156.2 | M55: 3196 | N55: =M55=B55 -> TRUE | O55: JASIM MOHAMMED SAID ALI AFIR AL ZAWAMARI | P55: =O55=C55 -> TRUE | Q55: 21080217 | R55: =Q55=#REF! -> #REF! | S55: 0401007927380037 | T55: =S55=#REF! -> #REF! | U55: BMUSOMRX | V55: =U55=#REF! -> #REF!
A56: 53 | B56: 3197 | C56: MOHSIN SAID MOHAMED BA AWAIN | D56: 1658.9 | E56: 0.250 | F56: =D56*E56 -> 414.725 | H56: =F56-G56 -> 414.725 | M56: 3197 | N56: =M56=B56 -> TRUE | O56: MOHSIN SAID MOHAMED BA AWAIN | P56: =O56=C56 -> TRUE | Q56: 6479515 | R56: =Q56=#REF! -> #REF! | S56: 0406003220920038 | T56: =S56=#REF! -> #REF! | U56: BMUSOMRX | V56: =U56=#REF! -> #REF!
A57: 54 | B57: 3198 | C57: ADIL SAID AHMED AL ZAWAMRI | D57: 578.5 | E57: 0.250 | F57: =D57*E57 -> 144.625 | H57: =F57-G57 -> 144.625 | M57: 3198 | N57: =M57=B57 -> TRUE | O57: ADIL SAID AHMED AL ZAWAMRI | P57: =O57=C57 -> TRUE | Q57: 6360793 | R57: =Q57=#REF! -> #REF! | S57: 00510047506001 | T57: =S57=#REF! -> #REF! | U57: BNZWOMRX | V57: =U57=#REF! -> #REF!
A58: 55 | B58: 3310 | C58: AHMED SUHAIL SAID AL BARAMI | D58: 1252.2 | E58: 0.250 | F58: =D58*E58 -> 313.05 | G58: =F58 -> 313.05 | H58: =F58-G58 -> 0 | I58: BT07-01-2025 | M58: 3310 | N58: =M58=B58 -> TRUE | O58: AHMED SUHAIL SAID AL BARAMI | P58: =O58=C58 -> TRUE | Q58: 1007615 | R58: =Q58=#REF! -> #REF! | S58: 0397003855850017 | T58: =S58=#REF! -> #REF! | U58: BMUSOMRX | V58: =U58=#REF! -> #REF!
A59: 56 | B59: 3324 | C59: BAKHIT AWADH BAKHIT AL BARAAMI | D59: 1253 | E59: 0.250 | F59: =D59*E59 -> 313.25 | H59: =F59-G59 -> 313.25 | M59: 3324 | N59: =M59=B59 -> TRUE | O59: BAKHIT AWADH BAKHIT AL BARAAMI | P59: =O59=C59 -> TRUE | Q59: 207402 | R59: =Q59=#REF! -> #REF! | S59: 0401057742590016 | T59: =S59=#REF! -> #REF! | U59: BMUSOMRX | V59: =U59=#REF! -> #REF!
A60: 57 | B60: 3330 | C60: Salim Ahmed Aubad Al kathiri | D60: 1887.9 | E60: 0.250 | F60: =D60*E60 -> 471.975 | H60: =F60-G60 -> 471.975 | M60: 3330 | N60: =M60=B60 -> TRUE | O60: Salim Ahmed Aubad Al kathiri | P60: =O60=C60 -> TRUE | Q60: 6375079 | R60: =Q60=#REF! -> #REF! | S60: 0397062111930011 | T60: =S60=#REF! -> #REF! | U60: BMUSOMRX | V60: =U60=#REF! -> #REF!
A61: 58 | B61: 3333 | C61: Mahad Salim Zaed Bait Said | D61: 1797.6 | E61: 0.250 | F61: =D61*E61 -> 449.4 | H61: =F61-G61 -> 449.4 | M61: 3333 | N61: =M61=B61 -> TRUE | O61: Mahad Salim Zaed Bait Said | P61: =O61=C61 -> TRUE | Q61: 757601 | R61: =Q61=#REF! -> #REF! | S61: 1023113274001 | T61: =S61=#REF! -> #REF! | U61: NBOMOMRX | V61: =U61=#REF! -> #REF!
A62: 59 | B62: 3339 | C62: Khalid Ahmed Salim Amer Jid Almahri | D62: 209.3 | E62: 0.250 | F62: =D62*E62 -> 52.325 | G62: =50.775+1.55 -> 52.325 | H62: =F62-G62 -> 0 | I62: 45629 | J62: 45686 | M62: 3339 | N62: =M62=B62 -> TRUE | O62: Khalid Ahmed Salim Amer Jid Almahri | P62: =O62=C62 -> TRUE | Q62: 12415718 | R62: =Q62=#REF! -> #REF! | S62: 0401050718800013 | T62: =S62=#REF! -> #REF! | U62: BMUSOMRX | V62: =U62=#REF! -> #REF!
A63: 60 | B63: 3500 | C63: Salim Mohammed Ahmed Al Kathiri | D63: 703.2 | E63: 0.250 | F63: =D63*E63 -> 175.8 | G63: =172.52+3.28 -> 175.8 | H63: =F63-G63 -> 0 | I63: 45655 | J63: 45658 | M63: 3500 | N63: =M63=B63 -> TRUE | O63: Salim Mohammed Ahmed Al Kathiri | P63: =O63=C63 -> TRUE | Q63: 13525845 | R63: =Q63=#REF! -> #REF! | S63: 10600259604017 | T63: =S63=#REF! -> #REF! | U63: NBOMOMRX | V63: =U63=#REF! -> #REF!
A64: 61 | B64: 3501 | C64: Said Masoud Ahmed Al kathiri | D64: 1837.7 | E64: 0.250 | F64: =D64*E64 -> 459.425 | G64: =F64 -> 459.425 | H64: =F64-G64 -> 0 | I64: 45932 | M64: 3501 | N64: =M64=B64 -> TRUE | O64: Said Masoud Ahmed Al kathiri | P64: =O64=C64 -> TRUE | Q64: 13525794 | R64: =Q64=#REF! -> #REF! | S64: 0402003356710024 | T64: =S64=#REF! -> #REF! | U64: BMUSOMRX | V64: =U64=#REF! -> #REF!
A65: 62 | B65: 3502 | C65: Ahmed Bakhit Ahmed Al Kathiri | D65: 1247.1 | E65: 0.250 | F65: =D65*E65 -> 311.775 | H65: =F65-G65 -> 311.775 | M65: 3502 | N65: =M65=B65 -> TRUE | O65: Ahmed Bakhit Ahmed Al Kathiri | P65: =O65=C65 -> TRUE | Q65: 22522336 | R65: =Q65=#REF! -> #REF! | S65: 01011021065002 | T65: =S65=#REF! -> #REF! | U65: BDOFOMRU | V65: =U65=#REF! -> #REF!
A66: 63 | B66: 3503 | C66: Imad Bakhit Salim Bakhit Qatan | D66: 625 | E66: 0.250 | F66: =D66*E66 -> 156.25 | H66: =F66-G66 -> 156.25 | M66: 3503 | N66: =M66=B66 -> TRUE | O66: Imad Bakhit Salim Bakhit Qatan | P66: =O66=C66 -> TRUE | Q66: 9212492 | R66: =Q66=#REF! -> #REF! | S66: 0401028325700011 | T66: =S66=#REF! -> #REF! | U66: BMUSOMRX | V66: =U66=#REF! -> #REF!
A67: 64 | B67: 3504 | C67: Ali Salem Amer Al Kathiri | D67: 1208.3 | E67: 0.250 | F67: =D67*E67 -> 302.075 | G67: =F67 -> 302.075 | H67: =F67-G67 -> 0 | I67: BT 15-12-2024 | M67: 3504 | N67: =M67=B67 -> TRUE | O67: Ali Salem Amer Al Kathiri | P67: =O67=C67 -> TRUE | Q67: 939641 | R67: =Q67=#REF! -> #REF! | S67: 0406003375130017 | T67: =S67=#REF! -> #REF! | U67: BMUSOMRX | V67: =U67=#REF! -> #REF!
A68: 65 | B68: 3506 | C68: Ahmed Masoud Salim Al Kathiri | D68: 325.7 | E68: 0.250 | F68: =D68*E68 -> 81.425 | H68: =F68-G68 -> 81.425 | M68: 3506 | N68: =M68=B68 -> TRUE | O68: Ahmed Masoud Salim Al Kathiri | P68: =O68=C68 -> TRUE | Q68: 13307752 | R68: =Q68=#REF! -> #REF! | S68: 0397048001530015 | T68: =S68=#REF! -> #REF! | U68: BMUSOMRX | V68: =U68=#REF! -> #REF!
A69: 66 | B69: 3507 | C69: Bakhit Suhail Ahmed Qatan | D69: 675.1 | E69: 0.250 | F69: =D69*E69 -> 168.775 | H69: =F69-G69 -> 168.775 | M69: 3507 | N69: =M69=B69 -> TRUE | O69: Bakhit Suhail Ahmed Qatan | P69: =O69=C69 -> TRUE | Q69: 1184669 | R69: =Q69=#REF! -> #REF! | S69: 01040281423001 | T69: =S69=#REF! -> #REF! | U69: BDOFOMRU | V69: =U69=#REF! -> #REF!
A70: 67 | B70: 3508 | C70: Said Ali Said Al Zawamri | D70: 619.5 | E70: 0.250 | F70: =D70*E70 -> 154.875 | H70: =F70-G70 -> 154.875 | M70: 3508 | N70: =M70=B70 -> TRUE | O70: Said Ali Said Al Zawamri | P70: =O70=C70 -> TRUE | Q70: 2567166 | R70: =Q70=#REF! -> #REF! | S70: 0439004225500028 | T70: =S70=#REF! -> #REF! | U70: BMUSOMRX | V70: =U70=#REF! -> #REF!
A71: 68 | B71: 3509 | C71: Asama Mohammed Ahmed Masharah Al Shahri | D71: 577.8 | E71: 0.250 | F71: =D71*E71 -> 144.45 | H71: =F71-G71 -> 144.45 | M71: 3509 | N71: =M71=B71 -> TRUE | O71: Asama Mohammed Ahmed Masharah Al Shahri | P71: =O71=C71 -> TRUE | Q71: 22760088 | R71: =Q71=#REF! -> #REF! | S71: 3129152535700 | T71: =S71=#REF! -> #REF! | U71: OMABOMRU | V71: =U71=#REF! -> #REF!
A72: 69 | B72: 3510 | C72: Amer Ali Ahmed Al kathiri | D72: 562.7 | E72: 0.250 | F72: =D72*E72 -> 140.675 | G72: =138.6 -> 138.6 | H72: =F72-G72 -> 2.075 | I72: 13-2-25 | M72: 3510 | N72: =M72=B72 -> TRUE | O72: Amer Ali Ahmed Al kathiri | P72: =O72=C72 -> TRUE | Q72: 6920351 | R72: =Q72=#REF! -> #REF! | S72: 0397003252950036 | T72: =S72=#REF! -> #REF! | U72: BMUSOMRX | V72: =U72=#REF! -> #REF!
A73: 70 | B73: 3511 | C73: Said Ali Said Qatan | D73: 523.5 | E73: 0.250 | F73: =D73*E73 -> 130.875 | G73: =126.5+4.375 -> 130.875 | H73: =F73-G73 -> 0 | I73: 45630 | J73: 45658 | M73: 3511 | N73: =M73=B73 -> TRUE | O73: Said Ali Said Qatan | P73: =O73=C73 -> TRUE | Q73: 2640016 | R73: =Q73=#REF! -> #REF! | S73: 0501036199001 | T73: =S73=#REF! -> #REF! | U73: AUBOOMRUALH | V73: =U73=#REF! -> #REF!
A74: 71 | B74: 3512 | C74: Ahmed Abdul Rahim Ali Al Kathiri | D74: 426.8 | E74: 0.250 | F74: =D74*E74 -> 106.7 | H74: =F74-G74 -> 106.7 | M74: 3512 | N74: =M74=B74 -> TRUE | O74: Ahmed Abdul Rahim Ali Al Kathiri | P74: =O74=C74 -> TRUE | Q74: 5514631 | R74: =Q74=#REF! -> #REF! | S74: 01041149485001 | T74: =S74=#REF! -> #REF! | U74: BDOFOMRU | V74: =U74=#REF! -> #REF!
A75: 72 | B75: 3513 | C75: Khair Salim Faraj Al Kathiri | D75: 2118.3 | E75: 0.250 | F75: =D75*E75 -> 529.575 | G75: =142.625+145.5+237.65+3.8 -> 529.575 | H75: =F75-G75 -> 0 | I75: 45629 | J75: 45630 | K75: 45635 | L75: 30-12-241 | M75: 3513 | N75: =M75=B75 -> TRUE | O75: Khair Salim Faraj Al Kathiri | P75: =O75=C75 -> TRUE | Q75: 7047376 | R75: =Q75=#REF! -> #REF! | S75: 01013042263001 | T75: =S75=#REF! -> #REF! | U75: BDOFOMRU | V75: =U75=#REF! -> #REF!
A76: 73 | B76: 3514 | C76: Said Salim Faraj Al Kathiri | D76: 1334.1 | E76: 0.250 | F76: =D76*E76 -> 333.525 | G76: =F76 -> 333.525 | H76: =F76-G76 -> 0 | I76: 45656
A77: 74 | B77: 3515 | C77: Ali Ajaham Ali Bait said | D77: 1091.6 | E77: 0.250 | F77: =D77*E77 -> 272.9 | G77: =266.375+6.525 -> 272.9 | H77: =F77-G77 -> 0 | I77: 45635 | J77: 45658 | M77: 3515 | N77: =M77=B77 -> TRUE | O77: Ali Ajaham Ali Bait said | P77: =O77=C77 -> TRUE | Q77: 6645198 | R77: =Q77=#REF! -> #REF! | S77: 01011180247001 | T77: =S77=#REF! -> #REF! | U77: BDOFOMRU | V77: =U77=#REF! -> #REF!
A78: 75 | B78: 3516 | C78: Musallam Hassan Ali Bait Muhammed Bin Ahmed | D78: 1240.8 | E78: 0.250 | F78: =D78*E78 -> 310.2 | H78: =F78-G78 -> 310.2 | M78: 3516 | N78: =M78=B78 -> TRUE | O78: Musallam Hassan Ali Bait Muhammed Bin Ahmed | P78: =O78=C78 -> TRUE | Q78: 1165877 | R78: =Q78=#REF! -> #REF! | S78: 01010127958001 | T78: =S78=#REF! -> #REF! | U78: BDOFOMRU | V78: =U78=#REF! -> #REF!
A79: 76 | B79: 3517 | C79: Mohammed Salim Faraj Al Kathiri | D79: 1224.4 | E79: 0.250 | F79: =D79*E79 -> 306.1 | G79: =303.125+2.975 -> 306.1 | H79: =F79-G79 -> 0 | I79: 45630 | J79: 2.975-dcf | M79: 3517 | N79: =M79=B79 -> TRUE | O79: Mohammed Salim Faraj Al Kathiri | P79: =O79=C79 -> TRUE | Q79: 7047081 | R79: =Q79=#REF! -> #REF! | S79: 01010401370002 | T79: =S79=#REF! -> #REF! | U79: BDOFOMRU | V79: =U79=#REF! -> #REF!
A80: 77 | B80: 3518 | C80: Ali Ahmed Ali Bait Said | D80: 949.5 | E80: 0.250 | F80: =D80*E80 -> 237.375 | G80: =F80 -> 237.375 | H80: =F80-G80 -> 0 | I80: 13-2-25 | M80: 3518 | N80: =M80=B80 -> TRUE | O80: Ali Ahmed Ali Bait Said | P80: =O80=C80 -> TRUE | Q80: 20386956 | R80: =Q80=#REF! -> #REF! | S80: 0396064567750014 | T80: =S80=#REF! -> #REF! | U80: BMUSOMRX | V80: =U80=#REF! -> #REF!
A81: 78 | B81: 3519 | C81: Masoud Salim Faraj Al Kathiri | D81: 619.5 | E81: 0.250 | F81: =D81*E81 -> 154.875 | G81: =150.474+4.401 -> 154.875 | H81: =F81-G81 -> 0 | I81: 45630 | J81: 4.401 dcf | M81: 3519 | N81: =M81=B81 -> TRUE | O81: Masoud Salim Faraj Al Kathiri | P81: =O81=C81 -> TRUE | Q81: 7047221 | R81: =Q81=#REF! -> #REF! | S81: 01011028414003 | T81: =S81=#REF! -> #REF! | U81: BDOFOMRU | V81: =U81=#REF! -> #REF!
A82: 79 | B82: 3520 | C82: Musallam Mahad Suhail Al Barami | D82: 705.5 | E82: 0.250 | F82: =D82*E82 -> 176.375 | H82: =F82-G82 -> 176.375 | M82: 3520 | N82: =M82=B82 -> TRUE | O82: Musallam Mahad Suhail Al Barami | P82: =O82=C82 -> TRUE | Q82: 5665362 | R82: =Q82=#REF! -> #REF! | S82: 01011072899001 | T82: =S82=#REF! -> #REF! | U82: BDOFOMRU | V82: =U82=#REF! -> #REF!
A83: 80 | B83: 3521 | C83: Omar Said Awadh Bait Said | D83: 3675.9 | E83: 0.250 | F83: =D83*E83 -> 918.975 | H83: =F83-G83 -> 918.975 | M83: 3521 | N83: =M83=B83 -> TRUE | O83: Omar Said Awadh Bait Said | P83: =O83=C83 -> TRUE | Q83: 7064553 | R83: =Q83=#REF! -> #REF! | S83: 0396019442490023 | T83: =S83=#REF! -> #REF! | U83: BMUSOMRX | V83: =U83=#REF! -> #REF!
A84: 81 | B84: 3522 | C84: Said Ahmed Ali Qatan | D84: 587.4 | E84: 0.250 | F84: =D84*E84 -> 146.85 | H84: =F84-G84 -> 146.85 | M84: 3522 | N84: =M84=B84 -> TRUE | O84: Said Ahmed Ali Qatan | P84: =O84=C84 -> TRUE | Q84: 11365191 | R84: =Q84=#REF! -> #REF! | S84: 01010121273002 | T84: =S84=#REF! -> #REF! | U84: BDOFOMRU | V84: =U84=#REF! -> #REF!
D86: =SUM(D4:D85) -> 129687.2 | F86: =SUM(F4:F85) -> 32421.8 | G86: =SUM(G4:G85) -> 16388.985 | H86: =SUM(H4:H85) -> 16032.815
G88: =G67+G58 -> 615.125
G89: =G86-G88 -> 15773.86
G90: =G89/F86 -> 0.48652018

Sheet Center-Oct
A1: HAJEEF COW MILK PROCUREMENT FROM 01-Oct-2024 TO 31-Oct-2024
A2: Sr No. | B2: Farmer Code | C2: Farmer Name | D2: Milk Qty. (Ltr.) | E2: Avg. Rate (OMR/Ltr.) | F2: Amount (OMR) | G2: Paid | H2: Balance | I2: ID No. | J2: Bank Account No. | K2: Bank Name | L2: IFSC Code | M2: Phone No. | N2: Remarks
A4: 1 | B4: 1007 | C4: AHMED ABDULLAH SAID AL RAWAS | D4: 6320.7 | E4: 0.250 | F4: =D4*E4 -> 1580.175 | H4: =F4-G4 -> 1580.175 | I4: 1515504 | J4: 0615500670380001 | K4: Bank Meethaq | L4: BMUSOMRXISL | M4: 91748840
A5: 2 | B5: 1041 | C5: AHMED SALIM ALI BAITSAID | D5: 2412.1 | E5: 0.250 | F5: =D5*E5 -> 603.025 | H5: =F5-G5 -> 603.025 | I5: 6827729 | J5: 0406003463970017 | K5: BANK MUSCAT | L5: BMUSOMRX | M5: 92272935
A6: 3 | B6: 1125 | C6: MUSALLAM SAID ALI BAITSAID | D6: 6201 | E6: 0.250 | F6: =D6*E6 -> 1550.25 | G6: =1547+3.25 -> 1550.25 | H6: =F6-G6 -> 0 | I6: 6828774 | J6: 01011456108001 | K6: BANK DHOFAR | L6: BDOFOMRU | M6: 91267555 | N6: 45691
A7: 4 | B7: 1222 | C7: Mahad Salim Abdulaziz Alkathiri | D7: 499.2 | E7: 0.250 | F7: =D7*E7 -> 124.8 | H7: =F7-G7 -> 124.8 | I7: 31221 | J7: 1006623107017 | K7: NBO | L7: NBOMOMRX
A8: 5 | B8: 1286 | C8: SALIM AMER AHMED AL YAFAEI | D8: 3046.3 | E8: 0.250 | F8: =D8*E8 -> 761.575 | H8: =F8-G8 -> 761.575 | I8: 368056 | J8: 0406003218280013 | K8: BANK MUSCAT | L8: BMUSOMRX | M8: 99494264
A9: 6 | B9: 1344 | C9: SAID AMERAHMED BAITSAID | D9: 2436.7 | E9: 0.250 | F9: =D9*E9 -> 609.175 | G9: =F9 -> 609.175 | H9: =F9-G9 -> 0 | I9: 4014519 | J9: 3109370559500 | K9: OAB | L9: OMABOMRU | N9: DCf-27-01-25
A10: 7 | B10: 1352 | C10: MOHAMMED MASOUD AJHAM ALSH AL KATHIRI | D10: 1906.2 | E10: 0.250 | F10: =D10*E10 -> 476.55 | H10: =F10-G10 -> 476.55 | I10: 1627344 | J10: 0397046773470015 | K10: BANK MUSCAT | L10: BMUSOMRX
A11: 8 | B11: 1354 | C11: AHMED SAID HASSAN BAITSAID | D11: 2397.8 | E11: 0.250 | F11: =D11*E11 -> 599.45 | H11: =F11-G11 -> 599.45 | I11: 925709 | J11: 0406018690130014 | K11: BANK MUSCAT | L11: BMUSOMRX | M11: 95187860
A12: 9 | B12: 1357 | C12: MUSALLAM SAID ALI BAIT SAID | D12: 4704.6 | E12: 0.250 | F12: =D12*E12 -> 1176.15 | H12: =F12-G12 -> 1176.15 | I12: 1052276 | J12: 01040280323001 | K12: BANK DHOFAR | L12: BDOFOMRU | M12: 95301260
A13: 10 | B13: 1359 | C13: MUSALLAM MUSTAHIL SAID BAIT SAID | D13: 2434.3 | E13: 0.250 | F13: =D13*E13 -> 608.575 | G13: =602+6.575 -> 608.575 | H13: =F13-G13 -> 0 | I13: 4812026 | J13: 1083517184017 | K13: NBO | L13: NBOMOMRX | M13: 96616558 | N13: 45655 | O13: 45680
A14: 11 | B14: 1367 | C14: ALI MUSALLAM AHMED BAIT SAID | D14: 935 | E14: 0.250 | F14: =D14*E14 -> 233.75 | G14: =F14 -> 233.75 | H14: =F14-G14 -> 0 | I14: 6663593 | J14: 0406003006560016 | K14: BANK MUSCAT | L14: BMUSOMRX | M14: 92817702 | N14: 45902
A15: 12 | B15: 1368 | C15: MOHAMMD SAID AHMED AL KATHIRI | D15: 4093.2 | E15: 0.250 | F15: =D15*E15 -> 1023.3 | G15: =0.1+1023.2 -> 1023.3 | H15: =F15-G15 -> 0 | I15: 561902 | J15: 01040854387001 | K15: BANK DHOFAR | L15: BDOFOMRU | M15: 99499622 | N15: 45622 | O15: .150 WILL DEDUCT FROM NOV 24
A16: 13 | B16: 3002 | C16: KHALID MUBARAK ALI ATQOON AL SHAHRI | D16: 1634.3 | E16: 0.250 | F16: =D16*E16 -> 408.575 | G16: =406.725+1.85 -> 408.575 | H16: =F16-G16 -> 0 | I16: 21220177 | J16: 0401016727580038 | K16: BANK MUSCAT | L16: BMUSOMRX | M16: 99280644 | N16: 45658 | O16: 45691
A17: 14 | B17: 3057 | C17: ALI AHMED MOHAMMED AL KATHIRI | D17: 2498.6 | E17: 0.250 | F17: =D17*E17 -> 624.65 | G17: =623.3+1.35 -> 624.65 | H17: =F17-G17 -> 0 | I17: 626819 | J17: 0397003510460014 | K17: BANK MUSCAT | L17: BMUSOMRX | M17: 99298522 | N17: 45655 | O17: 45666
A18: 15 | B18: 3062 | C18: ALI MAHAD SILMOUN QATAN | D18: 3129 | E18: 0.250 | F18: =D18*E18 -> 782.25 | H18: =F18-G18 -> 782.25 | I18: 300741 | J18: 0397004203200017 | K18: BANK MUSCAT | L18: BMUSOMRX | M18: 99008320
A19: 16 | B19: 3080 | C19: MUSALLAM BAKHIT AWADH L BARAAMI | D19: 1265.9 | E19: 0.250 | F19: =D19*E19 -> 316.475 | H19: =F19-G19 -> 316.475 | I19: 14301608 | J19: 0397003041020024 | K19: BANK MUSCAT | L19: BMUSOMRX | M19: 98122611
A20: 17 | B20: 3086 | C20: MUSALLAM ALI MATOOQ TABOOK | D20: 1201.9 | E20: 0.250 | F20: =D20*E20 -> 300.475 | H20: =F20-G20 -> 300.475 | I20: 300033 | J20: 0397003905720015 | K20: BANK MUSCAT | L20: BMUSOMRX
A21: 18 | B21: 3132 | C21: HASHIM SALIM ALI ATIF AL YAFAI | D21: 1296.7 | E21: 0.250 | F21: =D21*E21 -> 324.175 | G21: =323.1+1.075 -> 324.175 | H21: =F21-G21 -> 0 | I21: 14606296 | J21: 0401024314310011 | K21: BANK MUSCAT | L21: BMUSOMRX | M21: 91493522 | N21: 45663 | O21: 45779
A22: 19 | B22: 3134 | C22: HASSAN SUHAIL MAHAD QATAN | D22: 1125.5 | E22: 0.250 | F22: =D22*E22 -> 281.375 | G22: =280.05 -> 280.05 | H22: =F22-G22 -> 1.325 | I22: 2154413 | J22: 01010850952003 | K22: BANK DHOFAR | L22: BDOFOMRU | M22: 99493731 | N22: 45672
A23: 20 | B23: 3142 | C23: MOHAMMED AHMED SAAD MASHRAH AL SHAHRI | D23: 4795.9 | E23: 0.250 | F23: =D23*E23 -> 1198.975 | H23: =F23-G23 -> 1198.975 | I23: 165497 | J23: 3129019324700 | K23: OAB | L23: OMABOMRU | M23: 99499872
A24: 21 | B24: 3145 | C24: MOHAMMED BAKHIT MASOUD QATAN | D24: 2436.3 | E24: 0.250 | F24: =D24*E24 -> 609.075 | G24: =F24 -> 609.075 | H24: =F24-G24 -> 0 | I24: 1915745 | J24: 0404002595460014 | K24: BANK MUSCAT | L24: BMUSOMRX | M24: 99489050 | N24: dcf feed
A25: 22 | B25: 3147 | C25: KHALID SAID MAHAD KASHOUB | D25: 1951.8 | E25: 0.250 | F25: =D25*E25 -> 487.95 | G25: =F25 -> 487.95 | H25: =F25-G25 -> 0 | I25: 1662414 | J25: 3129770819700 | K25: OAB | L25: OMABOMRU | M25: 99282006 | N25: 45778
A26: 23 | B26: 3148 | C26: MUSALLAM AHMED MAHTOUQ AL ZAWAMRI | D26: 1240.9 | E26: 0.250 | F26: =D26*E26 -> 310.225 | G26: =F26 -> 310.225 | H26: =F26-G26 -> 0 | I26: 19545736 | J26: 01011208343002 | K26: BANK DHOFAR | L26: BDOFOMRU | N26: 15-01-25
A27: 24 | B27: 3149 | C27: ALI SAID ALI AL ZAWAMRI | D27: 1078.8 | E27: 0.250 | F27: =D27*E27 -> 269.7 | G27: =266.1+3.6 -> 269.7 | H27: =F27-G27 -> 0 | I27: 4941095 | J27: 1104036354300 | K27: Ahli Bank | L27: AUBOOMRU | M27: 93500864 | N27: 45663 | O27: 45691
A28: 25 | B28: 3152 | C28: BAKHIT SALIM MAHAD QATAN | D28: 2035 | E28: 0.250 | F28: =D28*E28 -> 508.75 | G28: =252.2+255.5 -> 507.7 | H28: =F28-G28 -> 1.05 | I28: 941993 | J28: 01042574515001 | K28: BANK DHOFAR | L28: BDOFOMRU | M28: 99086500 | N28: Feeds ONLD 25-12-2024 | O28: 45662
A29: 26 | B29: 3153 | C29: ALI MAHAD SAID QATAN | D29: 2980.6 | E29: 0.250 | F29: =D29*E29 -> 745.15 | G29: =188.45 -> 188.45 | H29: =F29-G29 -> 556.7 | I29: 6989479 | J29: 0397003672070015 | K29: BANK MUSCAT | L29: BMUSOMRX | M29: 99699500 | N29: 13-2-25
A30: 27 | B30: 3155 | C30: SAID BAKHIT MAHAD QATAN | D30: 630.5 | E30: 0.250 | F30: =D30*E30 -> 157.625 | H30: =F30-G30 -> 157.625 | I30: 19188794 | J30: 0402003042750013 | K30: BANK MUSCAT | L30: BMUSOMRX | M30: 93215515
A31: 28 | B31: 3158 | C31: AHMED OBAIDAN AHMED AL KATHIRI | D31: 2372.7 | E31: 0.250 | F31: =D31*E31 -> 593.175 | H31: =F31-G31 -> 593.175 | I31: 596869 | J31: 0401049081340015 | K31: BANK MUSCAT | L31: BMUSOMRX | M31: 99694218
A32: 29 | B32: 3159 | C32: AHMED BAKHIT SALEM AL BARAMI | D32: 617.6 | E32: 0.250 | F32: =D32*E32 -> 154.4 | H32: =F32-G32 -> 154.4 | I32: 1297478 | J32: 0397003703480012 | K32: BANK MUSCAT | L32: BMUSOMRX | M32: 99497177
A33: 30 | B33: 3160 | C33: NAIF MUBARAK BAKHIT AL BARAAMI | D33: 1838.6 | E33: 0.250 | F33: =D33*E33 -> 459.65 | H33: =F33-G33 -> 459.65 | I33: 2837163 | J33: 00510031862001 | K33: Bank Nizwa | L33: BNZWOMRX | M33: 99497455
A34: 31 | B34: 3162 | C34: MOHAMMED SAID FARAJ AL KATHIRI | D34: 5248.6 | E34: 0.250 | F34: =D34*E34 -> 1312.15 | H34: =F34-G34 -> 1312.15 | I34: 7017227 | J34: 01010940071001 | K34: BANK DHOFAR | L34: BDOFOMRU | M34: 99523400
A35: 32 | B35: 3164 | C35: ALI MUSALLLAM HASSAN BAITSAID | D35: 2434 | E35: 0.250 | F35: =D35*E35 -> 608.5 | H35: =F35-G35 -> 608.5 | I35: 7466062 | J35: 01646038607001 | K35: Maisarah | L35: BDOFOMRUMIB | M35: 91135005
A36: 33 | B36: 3165 | C36: KHALID MOHAMMED MASAAOD AGGHRIB AL SHAHRI | D36: 516.6 | E36: 0.250 | F36: =D36*E36 -> 129.15 | H36: =F36-G36 -> 129.15 | I36: 19029628 | J36: 01011251497002 | K36: BANK DHOFAR | L36: BDOFOMRU | M36: 96055446
A37: 34 | B37: 3169 | C37: MOHAMMED ALI SAID AL ZAWAMRY | D37: 634.5 | E37: 0.250 | F37: =D37*E37 -> 158.625 | H37: =F37-G37 -> 158.625 | I37: 3068756 | J37: 01012573317001 | K37: BANK DHOFAR | L37: BDOFOMRU | M37: 99691806
A38: 35 | B38: 3171 | C38: HATAM AWADH SAID QATAN | D38: 985.4 | E38: 0.250 | F38: =D38*E38 -> 246.35 | G38: =241.925+4.425 -> 246.35 | H38: =F38-G38 -> 0 | I38: 7239057 | J38: 3109607126500 | K38: OAB | L38: OMABOMRU | M38: 95880860 | N38: 45663 | O38: 45692
A39: 36 | B39: 3172 | C39: Fatima Suleimon Salim ALBaramiyah | D39: 630.6 | E39: 0.250 | F39: =D39*E39 -> 157.65 | H39: =F39-G39 -> 157.65 | I39: 5276984 | J39: 0439046831000027 | K39: BANK MUSCAT | L39: BMUSOMRX | M39: 99188860
A40: 37 | B40: 3173 | C40: MUSALLAM AHMED SAAD AL BARAAMI | D40: 1865.1 | E40: 0.250 | F40: =D40*E40 -> 466.275 | G40: =F40 -> 466.275 | H40: =F40-G40 -> 0 | I40: 6825655 | J40: 0397004380200011 | K40: BANK MUSCAT | L40: BMUSOMRX | M40: 98957747 | N40: dcf feed
A41: 38 | B41: 3174 | C41: AHMED MUSALLAM SAID QATAN | D41: 1397.7 | E41: 0.250 | F41: =D41*E41 -> 349.425 | G41: =2.25+347.175 -> 349.425 | H41: =F41-G41 -> 0 | I41: 7547492 | J41: 0401002379960017 | K41: BANK MUSCAT | L41: BMUSOMRX | M41: 91790502 | N41: dcf feed
A42: 39 | B42: 3175 | C42: SAID AHMED NASIB AL BARAAMI | D42: 556.52 | E42: 0.250 | F42: =D42*E42 -> 139.13 | G42: =135.9 -> 135.9 | H42: =F42-G42 -> 3.23 | I42: 7325076 | J42: 1006794849001 | K42: NBO | L42: NBOMOMRX | M42: 92890700 | N42: 45718
A43: 40 | B43: 3176 | C43: KHAYAR ALI SAID AL BARAAMI | D43: 621.7 | E43: 0.250 | F43: =D43*E43 -> 155.425 | H43: =F43-G43 -> 155.425 | I43: 12178145 | J43: 0406015163810016 | K43: BANK MUSCAT | L43: BMUSOMRX | M43: 93348565
A44: 41 | B44: 3179 | C44: SUHAIL MOHAMMED SUHAIL TABUK | D44: 2367.7 | E44: 0.250 | F44: =D44*E44 -> 591.925 | H44: =F44-G44 -> 591.925 | I44: 1870852 | J44: 3129685484720 | K44: OAB | L44: OMABOMRU | M44: 99050691
A45: 42 | B45: 3181 | C45: TARIK MASOUD MAJADAH AL KATHIRI | D45: 1919.2 | E45: 0.250 | F45: =D45*E45 -> 479.8 | H45: =F45-G45 -> 479.8 | I45: 6116067 | J45: 3109710314700 | K45: OAB | L45: OMABOMRU | M45: 99191102
A46: 43 | B46: 3183 | C46: Salim Musallam Ali Qatan | D46: 457.7 | E46: 0.250 | F46: =D46*E46 -> 114.425 | G46: =110.47+3.955 -> 114.425 | H46: =F46-G46 -> 0 | I46: 4955092 | J46: 0401002697260019 | K46: BANK MUSCAT | L46: BMUSOMRX | M46: 98152775 | N46: 45658 | O46: 45677
A47: 44 | B47: 3184 | C47: ALI MOHAMMED MUSALLAM AL BARAAMI | D47: 1888.6 | E47: 0.250 | F47: =D47*E47 -> 472.15 | H47: =F47-G47 -> 472.15 | I47: 6701602 | J47: 01011004872002 | K47: BANK DHOFAR | L47: BDOFOMRU | M47: 99496161
A48: 45 | B48: 3185 | C48: MOHAMMED ALI AHMED AMOOSH THOAR | D48: 1272.6 | E48: 0.250 | F48: =D48*E48 -> 318.15 | G48: =316.2+1.95 -> 318.15 | H48: =F48-G48 -> 0 | I48: 15179209 | J48: 0405020308900019 | K48: BANK MUSCAT | L48: BMUSOMRX | M48: 94919974 | N48: 45663 | O48: 45718
A49: 46 | B49: 3188 | C49: HASSAN BAKHIT AHMED QATAN | D49: 1116.4 | E49: 0.250 | F49: =D49*E49 -> 279.1 | G49: =278.45+0.65 -> 279.1 | H49: =F49-G49 -> 0 | I49: 19290729 | J49: 01041574026001 | K49: BANK DHOFAR | L49: BDOFOMRU | M49: 95606029 | N49: 45663 | O49: 45680
A50: 47 | B50: 3189 | C50: SAID AHMED SAID AL ZAWAMRI | D50: 1236 | E50: 0.250 | F50: =D50*E50 -> 309 | G50: =302.575+6.425 -> 309 | H50: =F50-G50 -> 0 | I50: 2802613 | J50: 0405002746200013 | K50: BANK MUSCAT | L50: BMUSOMRX | M50: 99480848 | N50: 45658 | O50: 45693
A51: 48 | B51: 3190 | C51: TAFOOL SILMOUN SALIM AL BARAMI | D51: 20.9 | E51: 0.250 | F51: =D51*E51 -> 5.225 | H51: =F51-G51 -> 5.225 | I51: 3555896 | J51: 0402014490950017 | K51: BANK MUSCAT | L51: BMUSOMRX | M51: 92881155
A52: 49 | B52: 3192 | C52: GHAZI SALIM MASOUD TABOOK | D52: 1011.2 | E52: 0.250 | F52: =D52*E52 -> 252.8 | H52: =F52-G52 -> 252.8 | I52: 5271448 | J52: 0401002602010018 | K52: BANK MUSCAT | L52: BMUSOMRX | M52: 99489918
A53: 50 | B53: 3195 | C53: MUSTAHIL SAID MUSTAHIL AL BARAAMI | D53: 632.7 | E53: 0.250 | F53: =D53*E53 -> 158.175 | H53: =F53-G53 -> 158.175 | I53: 675849 | J53: 01011097969001 | K53: BANK DHOFAR | L53: BDOFOMRU | M53: 99483811
A54: 51 | B54: 3196 | C54: JASIM MOHAMMED SAID ALI AFIR AL ZAWAMARI | D54: 630.2 | E54: 0.250 | F54: =D54*E54 -> 157.55 | H54: =F54-G54 -> 157.55 | I54: 21080217 | J54: 0401007927380037 | K54: BANK MUSCAT | L54: BMUSOMRX | M54: 95490778
A55: 52 | B55: 3197 | C55: MOHSIN SAID MOHAMED BA AWAIN | D55: 1612.7 | E55: 0.250 | F55: =D55*E55 -> 403.175 | H55: =F55-G55 -> 403.175 | I55: 6479515 | J55: 0406003220920038 | K55: BANK MUSCAT | L55: BMUSOMRX | M55: 92349032
A56: 53 | B56: 3198 | C56: ADIL SAID AHMED AL ZAWAMRI | D56: 627.6 | E56: 0.250 | F56: =D56*E56 -> 156.9 | H56: =F56-G56 -> 156.9 | I56: 6360793 | J56: 00510047506001 | K56: Bank Nizwa | L56: BNZWOMRX | M56: 99336200
A57: 54 | B57: 3310 | C57: AHMED SUHAIL SAID AL BARAMI | D57: 1274.8 | E57: 0.250 | F57: =D57*E57 -> 318.7 | G57: =F57 -> 318.7 | H57: =F57-G57 -> 0 | I57: 1007615 | J57: 0397003855850017 | K57: BANK MUSCAT | L57: BMUSOMRX | M57: 99056614 | N57: BT07-01-2025
A58: 55 | B58: 3324 | C58: BAKHIT AWADH BAKHIT AL BARAAMI | D58: 1247.5 | E58: 0.250 | F58: =D58*E58 -> 311.875 | H58: =F58-G58 -> 311.875 | I58: 207402 | J58: 0401057742590016 | K58: BANK MUSCAT | L58: BMUSOMRX | M58: 99487533
A59: 56 | B59: 3330 | C59: Salim Ahmed Aubad Al kathiri | D59: 1932 | E59: 0.250 | F59: =D59*E59 -> 483 | H59: =F59-G59 -> 483 | I59: 6375079 | J59: 0397062111930011 | K59: Bank Muscat | L59: BMUSOMRX
A60: 57 | B60: 3333 | C60: Mahad Salim Zaed Bait Said | D60: 1803.9 | E60: 0.250 | F60: =D60*E60 -> 450.975 | H60: =F60-G60 -> 450.975 | I60: 757601 | J60: 1023113274001 | K60: NBO | L60: NBOMOMRX
A61: 58 | B61: 3339 | C61: Khalid Ahmed Salim Amer Jid Almahri | D61: 545.2 | E61: 0.250 | F61: =D61*E61 -> 136.3 | G61: =F61 -> 136.3 | H61: =F61-G61 -> 0 | I61: 12415718 | J61: 0401050718800013 | K61: BANK MUSCAT | L61: BMUSOMRX | N61: dcf feed
A62: 59 | B62: 3500 | C62: Salim Mohammed Ahmed Al Kathiri | D62: 590.5 | E62: 0.250 | F62: =D62*E62 -> 147.625 | G62: =147.07+0.555 -> 147.625 | H62: =F62-G62 -> 0 | I62: 13525845 | J62: 10600259604017 | K62: NBO | L62: NBOMOMRX | M62: 93985671 | N62: 45658 | O62: .555-dcf
A63: 60 | B63: 3501 | C63: Said Masoud Ahmed Al kathiri | D63: 1888.9 | E63: 0.250 | F63: =D63*E63 -> 472.225 | G63: =471.775 -> 471.775 | H63: =F63-G63 -> 0.45 | I63: 13525794 | J63: 0402003356710024 | K63: BANK MUSCAT | L63: BMUSOMRX | M63: 92868004 | N63: 45932
A64: 61 | B64: 3502 | C64: Ahmed Bakhit Ahmed Al Kathiri | D64: 1231.2 | E64: 0.250 | F64: =D64*E64 -> 307.8 | H64: =F64-G64 -> 307.8 | I64: 22522336 | J64: 01011021065002 | K64: BANK DHOFAR | L64: BDOFOMRU
A65: 62 | B65: 3503 | C65: Imad Bakhit Salim Bakhit Qatan | D65: 642.6 | E65: 0.250 | F65: =D65*E65 -> 160.65 | H65: =F65-G65 -> 160.65 | I65: 9212492 | J65: 0401028325700011 | K65: BANK MUSCAT | L65: BMUSOMRX | M65: 98080144
A66: 63 | B66: 3504 | C66: Ali Salem Amer Al Kathiri | D66: 1228 | E66: 0.250 | F66: =D66*E66 -> 307 | G66: =F66 -> 307 | H66: =F66-G66 -> 0 | I66: 939641 | J66: 0406003375130017 | K66: BANK MUSCAT | L66: BMUSOMRX | M66: 99588609 | N66: 45902
A67: 64 | B67: 3506 | C67: Ahmed Masoud Salim Al Kathiri | D67: 557.5 | E67: 0.250 | F67: =D67*E67 -> 139.375 | H67: =F67-G67 -> 139.375 | I67: 13307752 | J67: 0397048001530015 | K67: BANK MUSCAT | L67: BMUSOMRX | M67: 99294425
A68: 65 | B68: 3507 | C68: Bakhit Suhail Ahmed Qatan | D68: 445.7 | E68: 0.250 | F68: =D68*E68 -> 111.425 | H68: =F68-G68 -> 111.425 | I68: 1184669 | J68: 01040281423001 | K68: BANK DHOFAR | L68: BDOFOMRU | M68: 99291928
A69: 66 | B69: 3508 | C69: Said Ali Said Al Zawamri | D69: 634.1 | E69: 0.250 | F69: =D69*E69 -> 158.525 | H69: =F69-G69 -> 158.525 | I69: 2567166 | J69: 0439004225500028 | K69: BANK MUSCAT | L69: BMUSOMRX | M69: 92570156
A70: 67 | B70: 3509 | C70: Asama Mohammed Ahmed Masharah Al Shahri | D70: 589.9 | E70: 0.250 | F70: =D70*E70 -> 147.475 | H70: =F70-G70 -> 147.475 | I70: 22760088 | J70: 3129152535700 | K70: OAB | L70: OMABOMRU | M70: 91476443
A71: 68 | B71: 3510 | C71: Amer Ali Ahmed Al kathiri | D71: 620.5 | E71: 0.250 | F71: =D71*E71 -> 155.125 | H71: =F71-G71 -> 155.125 | I71: 6920351 | J71: 0397003252950036 | K71: BANK MUSCAT | L71: BMUSOMRX | M71: 98933077
A72: 69 | B72: 3511 | C72: Said Ali Said Qatan | D72: 1050 | E72: 0.250 | F72: =D72*E72 -> 262.5 | G72: =257.525+4.975 -> 262.5 | H72: =F72-G72 -> 0 | I72: 2640016 | J72: 0501036199001 | K72: Ahli Islamic | L72: AUBOOMRUALH | M72: 92953388 | N72: 45658 | O72: 45685
A73: 70 | B73: 3512 | C73: Ahmed Abdul Rahim Ali Al Kathiri | D73: 459.6 | E73: 0.250 | F73: =D73*E73 -> 114.9 | H73: =F73-G73 -> 114.9 | I73: 5514631 | J73: 01041149485001 | K73: BANK DHOFAR | L73: BDOFOMRU
A74: 71 | B74: 3513 | C74: Khair Salim Faraj Al Kathiri | D74: 2566.6 | E74: 0.250 | F74: =D74*E74 -> 641.65 | G74: =641.25+0.4 -> 641.65 | H74: =F74-G74 -> 0 | I74: 7047376 | J74: 01013042263001 | K74: BANK DHOFAR | L74: BDOFOMRU | M74: 90106022 | N74: 45656 | O74: 45691
A75: 72 | B75: 3514 | C75: Said Salim Faraj Al Kathiri | D75: 1396.9 | E75: 0.250 | F75: =D75*E75 -> 349.225 | G75: =345.4752 -> 345.4752 | H75: =F75-G75 -> 3.7498 | I75: 440083 | J75: 0397003539170015 | K75: Bank Muscat | L75: BMUSOMRX | M75: 92363355 | N75: 45656
A76: 73 | B76: 3515 | C76: Ali Ajaham Ali Bait said | D76: 1205.3 | E76: 0.250 | F76: =D76*E76 -> 301.325 | G76: =294.175+7.15 -> 301.325 | H76: =F76-G76 -> 0 | I76: 6645198 | J76: 01011180247001 | K76: BANK DHOFAR | L76: BDOFOMRU | M76: 94411217 | N76: 45658 | O76: 45693
A77: 74 | B77: 3516 | C77: Musallam Hassan Ali Bait Muhammed Bin Ahmed | D77: 1360.8 | E77: 0.250 | F77: =D77*E77 -> 340.2 | H77: =F77-G77 -> 340.2 | I77: 1165877 | J77: 01010127958001 | K77: BANK DHOFAR | L77: BDOFOMRU
A78: 75 | B78: 3517 | C78: Mohammed Salim Faraj Al Kathiri | D78: 1253.9 | E78: 0.250 | F78: =D78*E78 -> 313.475 | G78: =F78 -> 313.475 | H78: =F78-G78 -> 0 | I78: 7047081 | J78: 01010401370002 | K78: BANK DHOFAR | L78: BDOFOMRU
A79: 76 | B79: 3518 | C79: Ali Ahmed Ali Bait Said | D79: 473.4 | E79: 0.250 | F79: =D79*E79 -> 118.35 | G79: =F79 -> 118.35 | H79: =F79-G79 -> 0 | I79: 20386956 | J79: 0396064567750014 | K79: BANK MUSCAT | L79: BMUSOMRX | N79: 13-2-25
A80: 77 | B80: 3519 | C80: Masoud Salim Faraj Al Kathiri | D80: 636.8 | E80: 0.250 | F80: =D80*E80 -> 159.2 | G80: =F80 -> 159.2 | H80: =F80-G80 -> 0 | I80: 7047221 | J80: 01011028414003 | K80: BANK DHOFAR | L80: BDOFOMRU
A81: 78 | B81: 3520 | C81: Musallam Mahad Suhail Al Barami | D81: 879 | E81: 0.250 | F81: =D81*E81 -> 219.75 | H81: =F81-G81 -> 219.75 | I81: 5665362 | J81: 01011072899001 | K81: BANK DHOFAR | L81: BDOFOMRU
A82: 79 | B82: 3521 | C82: Omar Said Awadh Bait Said | D82: 3692.4 | E82: 0.250 | F82: =D82*E82 -> 923.1 | H82: =F82-G82 -> 923.1 | I82: 7064553 | J82: 0396019442490023 | K82: BANK MUSCAT | L82: BMUSOMRX
A83: 80 | B83: 3522 | C83: Said Ahmed Ali Qatan | D83: 719 | E83: 0.250 | F83: =D83*E83 -> 179.75 | H83: =F83-G83 -> 179.75 | I83: 11365191 | J83: 01010121273002 | K83: BANK DHOFAR | L83: BDOFOMRU
D84: =SUM(D4:D83) -> 132127.92 | F84: =SUM(F4:F83) -> 33031.98 | G84: =SUM(G4:G83) -> 13777.6 | H84: =SUM(H4:H83) -> 19254.38
G85: =G57 -> 318.7
G86: =G84-G85 -> 13458.9
G87: =G86/F84 -> 0.4074506

Sheet Center-Nov
A1: HAJEEF COW MILK PROCUREMENT FROM 01-Nov-2024 TO 30-Nov-2024
A2: Sr No. | B2: Farmer Code | C2: Farmer Name | D2: Milk Qty. (Ltr.) | E2: Avg. Rate (OMR/Ltr.) | F2: Amount (OMR) | G2: Paid | H2: Balance | I2: ID No. | J2: Remarks
A4: 1 | B4: 1007 | C4: AHMED ABDULLAH SAID AL RAWAS | D4: 5918.3 | E4: 0.250 | F4: =D4*E4 -> 1479.575 | H4: =F4-G4 -> 1479.575 | I4: 1515504
A5: 2 | B5: 1041 | C5: AHMED SALIM ALI BAITSAID | D5: 2883.4 | E5: 0.250 | F5: =D5*E5 -> 720.85 | H5: =F5-G5 -> 720.85 | I5: 6827729
A6: 3 | B6: 1125 | C6: MUSALLAM SAID ALI BAITSAID | D6: 5823.6 | E6: 0.250 | F6: =D6*E6 -> 1455.9 | G6: =1455.6 -> 1455.6 | H6: =F6-G6 -> 0.3 | I6: 6828774 | J6: 45691
A7: 4 | B7: 1222 | C7: Mahad Salim Abdulaziz Alkathiri | D7: 106.4 | E7: 0.250 | F7: =D7*E7 -> 26.6 | H7: =F7-G7 -> 26.6 | I7: 31221
A8: 5 | B8: 1286 | C8: SALIM AMER AHMED AL YAFAEI | D8: 3086.9 | E8: 0.250 | F8: =D8*E8 -> 771.725 | H8: =F8-G8 -> 771.725 | I8: 368056
A9: 6 | B9: 1344 | C9: SAID AMERAHMED BAITSAID | D9: 3155 | E9: 0.250 | F9: =D9*E9 -> 788.75 | G9: =F9 -> 788.75 | H9: =F9-G9 -> 0 | I9: 4014519 | J9: 45718
A10: 7 | B10: 1352 | C10: MOHAMMED MASOUD AJHAM ALSH AL KATHIRI | D10: 1804.3 | E10: 0.250 | F10: =D10*E10 -> 451.075 | H10: =F10-G10 -> 451.075 | I10: 1627344
A11: 8 | B11: 1354 | C11: AHMED SAID HASSAN BAITSAID | D11: 2119.4 | E11: 0.250 | F11: =D11*E11 -> 529.85 | H11: =F11-G11 -> 529.85 | I11: 925709
A12: 9 | B12: 1357 | C12: MUSALLAM SAID ALI BAIT SAID | D12: 4575.3 | E12: 0.250 | F12: =D12*E12 -> 1143.825 | H12: =F12-G12 -> 1143.825 | I12: 1052276
A13: 10 | B13: 1359 | C13: MUSALLAM MUSTAHIL SAID BAIT SAID | D13: 3449 | E13: 0.250 | F13: =D13*E13 -> 862.25 | G13: =856.725 -> 856.725 | H13: =F13-G13 -> 5.525 | I13: 4812026 | J13: 45680
A14: 11 | B14: 1367 | C14: ALI MUSALLAM AHMED BAIT SAID | D14: 1121 | E14: 0.250 | F14: =D14*E14 -> 280.25 | G14: =F14 -> 280.25 | H14: =F14-G14 -> 0 | I14: 6663593 | J14: 45902
A15: 12 | B15: 1368 | C15: MOHAMMD SAID AHMED AL KATHIRI | D15: 3909.6 | E15: 0.250 | F15: =D15*E15 -> 977.4 | G15: =F15 -> 977.4 | H15: =F15-G15 -> 0 | I15: 561902 | J15: DCF Feed-16-01-25
A16: 13 | B16: 3002 | C16: KHALID MUBARAK ALI ATQOON AL SHAHRI | D16: 1384.4 | E16: 0.250 | F16: =D16*E16 -> 346.1 | G16: =342.8 -> 342.8 | H16: =F16-G16 -> 3.3 | I16: 21220177 | J16: 45691
A17: 14 | B17: 3035 | C17: TARIQ SALIM SUHAIL AL BARAMI | D17: 618.6 | E17: 0.250 | F17: =D17*E17 -> 154.65 | H17: =F17-G17 -> 154.65 | I17: 6725058
A18: 15 | B18: 3057 | C18: ALI AHMED MOHAMMED AL KATHIRI | D18: 2358 | E18: 0.250 | F18: =D18*E18 -> 589.5 | G18: =585.5+4 -> 589.5 | H18: =F18-G18 -> 0 | I18: 626819 | J18: 45666 | K18: 45673
A19: 16 | B19: 3062 | C19: ALI MAHAD SILMOUN QATAN | D19: 2673.5 | E19: 0.250 | F19: =D19*E19 -> 668.375 | H19: =F19-G19 -> 668.375 | I19: 300741
A20: 17 | B20: 3080 | C20: MUSALLAM BAKHIT AWADH L BARAAMI | D20: 1190.9 | E20: 0.250 | F20: =D20*E20 -> 297.725 | H20: =F20-G20 -> 297.725 | I20: 14301608
A21: 18 | B21: 3086 | C21: MUSALLAM ALI MATOOQ TABOOK | D21: 1288.1 | E21: 0.250 | F21: =D21*E21 -> 322.025 | H21: =F21-G21 -> 322.025 | I21: 300033
A22: 19 | B22: 3132 | C22: HASHIM SALIM ALI ATIF AL YAFAI | D22: 1200.3 | E22: 0.250 | F22: =D22*E22 -> 300.075 | G22: =299.03 -> 299.03 | H22: =F22-G22 -> 1.045 | I22: 14606296 | J22: 45779
A23: 20 | B23: 3134 | C23: HASSAN SUHAIL MAHAD QATAN | D23: 942.6 | E23: 0.250 | F23: =D23*E23 -> 235.65 | H23: =F23-G23 -> 235.65 | I23: 2154413
A24: 21 | B24: 3142 | C24: MOHAMMED AHMED SAAD MASHRAH AL SHAHRI | D24: 4434.8 | E24: 0.250 | F24: =D24*E24 -> 1108.7 | H24: =F24-G24 -> 1108.7 | I24: 165497
A25: 22 | B25: 3145 | C25: MOHAMMED BAKHIT MASOUD QATAN | D25: 1948.9 | E25: 0.250 | F25: =D25*E25 -> 487.225 | G25: =F25 -> 487.225 | H25: =F25-G25 -> 0 | I25: 1915745 | J25: DCF Feed-29-01-25
A26: 23 | B26: 3147 | C26: KHALID SAID MAHAD KASHOUB | D26: 1884.9 | E26: 0.250 | F26: =D26*E26 -> 471.225 | G26: =F26 -> 471.225 | H26: =F26-G26 -> 0 | I26: 1662414 | J26: 45932
A27: 24 | B27: 3148 | C27: MUSALLAM AHMED MAHTOUQ AL ZAWAMRI | D27: 1017.5 | E27: 0.250 | F27: =D27*E27 -> 254.375 | G27: =F27 -> 254.375 | H27: =F27-G27 -> 0 | I27: 19545736 | J27: DCF Feed-15-01-25
A28: 25 | B28: 3149 | C28: ALI SAID ALI AL ZAWAMRI | D28: 980.5 | E28: 0.250 | F28: =D28*E28 -> 245.125 | G28: =244.85 -> 244.85 | H28: =F28-G28 -> 0.275 | I28: 4941095 | J28: 45691
A29: 26 | B29: 3152 | C29: BAKHIT SALIM MAHAD QATAN | D29: 1581.8 | E29: 0.250 | F29: =D29*E29 -> 395.45 | H29: =F29-G29 -> 395.45 | I29: 941993
A30: 27 | B30: 3153 | C30: ALI MAHAD SAID QATAN | D30: 2701.9 | E30: 0.250 | F30: =D30*E30 -> 675.475 | H30: =F30-G30 -> 675.475 | I30: 6989479
A31: 28 | B31: 3155 | C31: SAID BAKHIT MAHAD QATAN | D31: 560.7 | E31: 0.250 | F31: =D31*E31 -> 140.175 | H31: =F31-G31 -> 140.175 | I31: 19188794
A32: 29 | B32: 3158 | C32: AHMED OBAIDAN AHMED AL KATHIRI | D32: 2292.9 | E32: 0.250 | F32: =D32*E32 -> 573.225 | H32: =F32-G32 -> 573.225 | I32: 596869
A33: 30 | B33: 3159 | C33: AHMED BAKHIT SALEM AL BARAMI | D33: 590.8 | E33: 0.250 | F33: =D33*E33 -> 147.7 | H33: =F33-G33 -> 147.7 | I33: 1297478
A34: 31 | B34: 3160 | C34: NAIF MUBARAK BAKHIT AL BARAAMI | D34: 1701.8 | E34: 0.250 | F34: =D34*E34 -> 425.45 | H34: =F34-G34 -> 425.45 | I34: 2837163
A35: 32 | B35: 3162 | C35: MOHAMMED SAID FARAJ AL KATHIRI | D35: 4589.5 | E35: 0.250 | F35: =D35*E35 -> 1147.375 | H35: =F35-G35 -> 1147.375 | I35: 7017227
A36: 33 | B36: 3164 | C36: ALI MUSALLLAM HASSAN BAITSAID | D36: 2258.9 | E36: 0.250 | F36: =D36*E36 -> 564.725 | H36: =F36-G36 -> 564.725 | I36: 7466062
A37: 34 | B37: 3165 | C37: KHALID MOHAMMED MASAAOD AGGHRIB AL SHAHRI | D37: 463.2 | E37: 0.250 | F37: =D37*E37 -> 115.8 | H37: =F37-G37 -> 115.8 | I37: 19029628
A38: 35 | B38: 3169 | C38: MOHAMMED ALI SAID AL ZAWAMRY | D38: 751.4 | E38: 0.250 | F38: =D38*E38 -> 187.85 | H38: =F38-G38 -> 187.85 | I38: 3068756
A39: 36 | B39: 3171 | C39: HATAM AWADH SAID QATAN | D39: 952.6 | E39: 0.250 | F39: =D39*E39 -> 238.15 | G39: =238.08 -> 238.08 | H39: =F39-G39 -> 0.07 | I39: 7239057 | J39: 45692
A40: 37 | B40: 3172 | C40: Fatima Suleimon Salim ALBaramiyah | D40: 591.7 | E40: 0.250 | F40: =D40*E40 -> 147.925 | H40: =F40-G40 -> 147.925 | I40: 5276984
A41: 38 | B41: 3173 | C41: MUSALLAM AHMED SAAD AL BARAAMI | D41: 1917.9 | E41: 0.250 | F41: =D41*E41 -> 479.475 | G41: =F41 -> 479.475 | H41: =F41-G41 -> 0 | I41: 6825655 | J41: 45693
A42: 39 | B42: 3174 | C42: AHMED MUSALLAM SAID QATAN | D42: 1430.5 | E42: 0.250 | F42: =D42*E42 -> 357.625 | G42: =356.65+0.975 -> 357.625 | H42: =F42-G42 -> 0 | I42: 7547492 | J42: 45666 | K42: .975 dcf feed
A43: 40 | B43: 3175 | C43: SAID AHMED NASIB AL BARAAMI | D43: 578.6 | E43: 0.250 | F43: =D43*E43 -> 144.65 | H43: =F43-G43 -> 144.65 | I43: 7325076
A44: 41 | B44: 3176 | C44: KHAYAR ALI SAID AL BARAAMI | D44: 585.4 | E44: 0.250 | F44: =D44*E44 -> 146.35 | H44: =F44-G44 -> 146.35 | I44: 12178145
A45: 42 | B45: 3179 | C45: SUHAIL MOHAMMED SUHAIL TABUK | D45: 2204.7 | E45: 0.250 | F45: =D45*E45 -> 551.175 | H45: =F45-G45 -> 551.175 | I45: 1870852
A46: 43 | B46: 3181 | C46: TARIK MASOUD MAJADAH AL KATHIRI | D46: 1710.8 | E46: 0.250 | F46: =D46*E46 -> 427.7 | H46: =F46-G46 -> 427.7 | I46: 6116067
A47: 44 | B47: 3183 | C47: Salim Musallam Ali Qatan | D47: 626.1 | E47: 0.250 | F47: =D47*E47 -> 156.525 | G47: =151.2+5.325 -> 156.525 | H47: =F47-G47 -> 0 | I47: 4955092 | J47: 45677 | K47: 13-2-25
A48: 45 | B48: 3184 | C48: ALI MOHAMMED MUSALLAM AL BARAAMI | D48: 2012 | E48: 0.250 | F48: =D48*E48 -> 503 | H48: =F48-G48 -> 503 | I48: 6701602
A49: 46 | B49: 3185 | C49: MOHAMMED ALI AHMED AMOOSH THOAR | D49: 1149.4 | E49: 0.250 | F49: =D49*E49 -> 287.35 | G49: =284.2 -> 284.2 | H49: =F49-G49 -> 3.15 | I49: 15179209 | J49: 45691
A50: 47 | B50: 3188 | C50: HASSAN BAKHIT AHMED QATAN | D50: 1086.2 | E50: 0.250 | F50: =D50*E50 -> 271.55 | G50: =159.4 -> 159.4 | H50: =F50-G50 -> 112.15 | I50: 19290729 | J50: 45679
A51: 48 | B51: 3189 | C51: SAID AHMED SAID AL ZAWAMRI | D51: 1496.6 | E51: 0.250 | F51: =D51*E51 -> 374.15 | G51: =371.88 -> 371.88 | H51: =F51-G51 -> 2.27 | I51: 2802613 | J51: 45693
A52: 49 | B52: 3190 | C52: TAFOOL SILMOUN SALIM AL BARAMI | D52: 746.6 | E52: 0.250 | F52: =D52*E52 -> 186.65 | H52: =F52-G52 -> 186.65 | I52: 3555896
A53: 50 | B53: 3192 | C53: GHAZI SALIM MASOUD TABOOK | D53: 1015.5 | E53: 0.250 | F53: =D53*E53 -> 253.875 | H53: =F53-G53 -> 253.875 | I53: 5271448
A54: 51 | B54: 3195 | C54: MUSTAHIL SAID MUSTAHIL AL BARAAMI | D54: 568.6 | E54: 0.250 | F54: =D54*E54 -> 142.15 | H54: =F54-G54 -> 142.15 | I54: 675849
A55: 52 | B55: 3196 | C55: JASIM MOHAMMED SAID ALI AFIR AL ZAWAMARI | D55: 564.2 | E55: 0.250 | F55: =D55*E55 -> 141.05 | H55: =F55-G55 -> 141.05 | I55: 21080217
A56: 53 | B56: 3197 | C56: MOHSIN SAID MOHAMED BA AWAIN | D56: 1444.1 | E56: 0.250 | F56: =D56*E56 -> 361.025 | H56: =F56-G56 -> 361.025 | I56: 6479515
A57: 54 | B57: 3198 | C57: ADIL SAID AHMED AL ZAWAMRI | D57: 570.5 | E57: 0.250 | F57: =D57*E57 -> 142.625 | H57: =F57-G57 -> 142.625 | I57: 6360793
A58: 55 | B58: 3310 | C58: AHMED SUHAIL SAID AL BARAMI | D58: 1198.1 | E58: 0.250 | F58: =D58*E58 -> 299.525 | H58: =F58-G58 -> 299.525 | I58: 1007615
A59: 56 | B59: 3324 | C59: BAKHIT AWADH BAKHIT AL BARAAMI | D59: 1193.5 | E59: 0.250 | F59: =D59*E59 -> 298.375 | H59: =F59-G59 -> 298.375 | I59: 207402
A60: 57 | B60: 3330 | C60: Salim Ahmed Aubad Al kathiri | D60: 1637.4 | E60: 0.250 | F60: =D60*E60 -> 409.35 | H60: =F60-G60 -> 409.35 | I60: 6375079
A61: 58 | B61: 3333 | C61: Mahad Salim Zaed Bait Said | D61: 1790.1 | E61: 0.250 | F61: =D61*E61 -> 447.525 | H61: =F61-G61 -> 447.525 | I61: 757601
A62: 59 | B62: 3339 | C62: Khalid Ahmed Salim Amer Jid Almahri | D62: 567.9 | E62: 0.250 | F62: =D62*E62 -> 141.975 | G62: =F62 -> 141.975 | H62: =F62-G62 -> 0 | I62: 12415718 | J62: 29-01-2025-dcf
A63: 60 | B63: 3500 | C63: Salim Mohammed Ahmed Al Kathiri | D63: 519.1 | E63: 0.250 | F63: =D63*E63 -> 129.775 | G63: =F63 -> 129.775 | H63: =F63-G63 -> 0 | I63: 13525845 | J63: 20-01-25-dcf
A64: 61 | B64: 3501 | C64: Said Masoud Ahmed Al kathiri | D64: 1573.4 | E64: 0.250 | F64: =D64*E64 -> 393.35 | H64: =F64-G64 -> 393.35 | I64: 13525794
A65: 62 | B65: 3502 | C65: Ahmed Bakhit Ahmed Al Kathiri | D65: 1188.6 | E65: 0.250 | F65: =D65*E65 -> 297.15 | H65: =F65-G65 -> 297.15 | I65: 22522336
A66: 63 | B66: 3503 | C66: Imad Bakhit Salim Bakhit Qatan | D66: 574 | E66: 0.250 | F66: =D66*E66 -> 143.5 | H66: =F66-G66 -> 143.5 | I66: 9212492
A67: 64 | B67: 3504 | C67: Ali Salem Amer Al Kathiri | D67: 1181.4 | E67: 0.250 | F67: =D67*E67 -> 295.35 | G67: =F67 -> 295.35 | H67: =F67-G67 -> 0 | I67: 939641 | J67: 45902
A68: 65 | B68: 3506 | C68: Ahmed Masoud Salim Al Kathiri | D68: 547.8 | E68: 0.250 | F68: =D68*E68 -> 136.95 | H68: =F68-G68 -> 136.95 | I68: 13307752
A69: 66 | B69: 3507 | C69: Bakhit Suhail Ahmed Qatan | D69: 322.6 | E69: 0.250 | F69: =D69*E69 -> 80.65 | H69: =F69-G69 -> 80.65 | I69: 1184669
A70: 67 | B70: 3508 | C70: Said Ali Said Al Zawamri | D70: 580.2 | E70: 0.250 | F70: =D70*E70 -> 145.05 | H70: =F70-G70 -> 145.05 | I70: 2567166
A71: 68 | B71: 3509 | C71: Asama Mohammed Ahmed Masharah Al Shahri | D71: 555.5 | E71: 0.250 | F71: =D71*E71 -> 138.875 | H71: =F71-G71 -> 138.875 | I71: 22760088
A72: 69 | B72: 3510 | C72: Amer Ali Ahmed Al kathiri | D72: 871.3 | E72: 0.250 | F72: =D72*E72 -> 217.825 | H72: =F72-G72 -> 217.825 | I72: 6920351
A73: 70 | B73: 3511 | C73: Said Ali Said Qatan | D73: 1250.6 | E73: 0.250 | F73: =D73*E73 -> 312.65 | G73: =310.675+1.975 -> 312.65 | H73: =F73-G73 -> 0 | I73: 2640016 | J73: 45685 | K73: 45932
A74: 71 | B74: 3512 | C74: Ahmed Abdul Rahim Ali Al Kathiri | D74: 39.2 | E74: 0.250 | F74: =D74*E74 -> 9.8 | H74: =F74-G74 -> 9.8 | I74: 5514631
A75: 72 | B75: 3513 | C75: Khair Salim Faraj Al Kathiri | D75: 2399.8 | E75: 0.250 | F75: =D75*E75 -> 599.95 | G75: =596.15 -> 596.15 | H75: =F75-G75 -> 3.8 | I75: 7047376 | J75: 45691
A76: 73 | B76: 3514 | C76: Said Salim Faraj Al Kathiri | D76: 1293.8 | E76: 0.250 | F76: =D76*E76 -> 323.45 | H76: =F76-G76 -> 323.45 | I76: 440083
A77: 74 | B77: 3515 | C77: Ali Ajaham Ali Bait said | D77: 1562.8 | E77: 0.250 | F77: =D77*E77 -> 390.7 | G77: =390.55 -> 390.55 | H77: =F77-G77 -> 0.15 | I77: 6645198 | J77: 45693
A78: 75 | B78: 3516 | C78: Musallam Hassan Ali Bait Muhammed Bin Ahmed | D78: 1696.7 | E78: 0.250 | F78: =D78*E78 -> 424.175 | H78: =F78-G78 -> 424.175 | I78: 1165877
A79: 76 | B79: 3517 | C79: Mohammed Salim Faraj Al Kathiri | D79: 1182 | E79: 0.250 | F79: =D79*E79 -> 295.5 | G79: =F79 -> 295.5 | H79: =F79-G79 -> 0 | I79: 7047081 | J79: 29-01-2025-dcf
A80: 77 | B80: 3518 | C80: Ali Ahmed Ali Bait Said | D80: 572.6 | E80: 0.250 | F80: =D80*E80 -> 143.15 | G80: =F80 -> 143.15 | H80: =F80-G80 -> 0 | I80: 20386956 | J80: 13-2-25
A81: 78 | B81: 3519 | C81: Masoud Salim Faraj Al Kathiri | D81: 584.8 | E81: 0.250 | F81: =D81*E81 -> 146.2 | G81: =F81 -> 146.2 | H81: =F81-G81 -> 0 | I81: 7047221 | J81: 29-01-2025-dcf
A82: 79 | B82: 3520 | C82: Musallam Mahad Suhail Al Barami | D82: 746.9 | E82: 0.250 | F82: =D82*E82 -> 186.725 | H82: =F82-G82 -> 186.725 | I82: 5665362
A83: 80 | B83: 3521 | C83: Omar Said Awadh Bait Said | D83: 3489.9 | E83: 0.250 | F83: =D83*E83 -> 872.475 | H83: =F83-G83 -> 872.475 | I83: 7064553
A84: 81 | B84: 3522 | C84: Said Ahmed Ali Qatan | D84: 831.4 | E84: 0.250 | F84: =D84*E84 -> 207.85 | H84: =F84-G84 -> 207.85 | I84: 11365191
D85: =SUM(D4:D84) -> 128571.5 | F85: =SUM(F4:F84) -> 32142.875 | G85: =SUM(G4:G84) -> 11546.215 | H85: =SUM(H4:H84) -> 20596.66

Sheet Center-dec
A1: HAJEEF COW MILK PROCUREMENT FROM 01-Dec-2024 TO 31-Dec-2024
A2: Sr No. | B2: Farmer Code | C2: Farmer Name | D2: Milk Qty. (Ltr.) | E2: Avg. Rate (OMR/Ltr.) | F2: Amount (OMR) | G2: Paid | H2: Balance | I2: ID No. | J2: Remarks
A4: 1 | B4: 1007 | C4: AHMED ABDULLAH SAID AL RAWAS | D4: 6267.6 | E4: 0.250 | F4: =D4*E4 -> 1566.9 | H4: =F4-G4 -> 1566.9 | I4: 1515504
A5: 2 | B5: 1041 | C5: AHMED SALIM ALI BAITSAID | D5: 3741.7 | E5: 0.250 | F5: =D5*E5 -> 935.425 | H5: =F5-G5 -> 935.425 | I5: 6827729
A6: 3 | B6: 1125 | C6: MUSALLAM SAID ALI BAITSAID | D6: 6440.3 | E6: 0.250 | F6: =D6*E6 -> 1610.075 | H6: =F6-G6 -> 1610.075 | I6: 6828774
A7: 4 | B7: 1222 | C7: Mahad Salim Abdulaziz Alkathiri | D7: 483.1 | E7: 0.250 | F7: =D7*E7 -> 120.775 | H7: =F7-G7 -> 120.775 | I7: 31221
A8: 5 | B8: 1286 | C8: SALIM AMER AHMED AL YAFAEI | D8: 3071.5 | E8: 0.250 | F8: =D8*E8 -> 767.875 | H8: =F8-G8 -> 767.875 | I8: 368056
A9: 6 | B9: 1344 | C9: SAID AMERAHMED BAITSAID | D9: 2569.5 | E9: 0.250 | F9: =D9*E9 -> 642.375 | H9: =F9-G9 -> 642.375 | I9: 4014519
A10: 7 | B10: 1352 | C10: MOHAMMED MASOUD AJHAM ALSH AL KATHIRI | D10: 1843 | E10: 0.250 | F10: =D10*E10 -> 460.75 | H10: =F10-G10 -> 460.75 | I10: 1627344
A11: 8 | B11: 1354 | C11: AHMED SAID HASSAN BAITSAID | D11: 2487.1 | E11: 0.250 | F11: =D11*E11 -> 621.775 | H11: =F11-G11 -> 621.775 | I11: 925709
A12: 9 | B12: 1357 | C12: MUSALLAM SAID ALI BAIT SAID | D12: 5185.2 | E12: 0.250 | F12: =D12*E12 -> 1296.3 | H12: =F12-G12 -> 1296.3 | I12: 1052276
A13: 10 | B13: 1359 | C13: MUSALLAM MUSTAHIL SAID BAIT SAID | D13: 4102.2 | E13: 0.250 | F13: =D13*E13 -> 1025.55 | H13: =F13-G13 -> 1025.55 | I13: 4812026
A14: 11 | B14: 1367 | C14: ALI MUSALLAM AHMED BAIT SAID | D14: 1284.6 | E14: 0.250 | F14: =D14*E14 -> 321.15 | G14: =F14 -> 321.15 | H14: =F14-G14 -> 0 | I14: 6663593 | J14: 45902
A15: 12 | B15: 1368 | C15: MOHAMMD SAID AHMED AL KATHIRI | D15: 4172 | E15: 0.250 | F15: =D15*E15 -> 1043 | G15: =F15 -> 1043 | H15: =F15-G15 -> 0 | I15: 561902 | J15: 16-2-25
A16: 13 | B16: 3002 | C16: KHALID MUBARAK ALI ATQOON AL SHAHRI | D16: 1778.3 | E16: 0.250 | F16: =D16*E16 -> 444.575 | H16: =F16-G16 -> 444.575 | I16: 21220177
A17: 14 | B17: 3035 | C17: TARIQ SALIM SUHAIL AL BARAMI | D17: 677 | E17: 0.250 | F17: =D17*E17 -> 169.25 | H17: =F17-G17 -> 169.25 | I17: 6725058
A18: 15 | B18: 3057 | C18: ALI AHMED MOHAMMED AL KATHIRI | D18: 2694.3 | E18: 0.250 | F18: =D18*E18 -> 673.575 | G18: =670.15+3.425 -> 673.575 | H18: =F18-G18 -> 0 | I18: 626819 | J18: 45673 | K18: 45691
A19: 16 | B19: 3062 | C19: ALI MAHAD SILMOUN QATAN | D19: 2834.9 | E19: 0.250 | F19: =D19*E19 -> 708.725 | H19: =F19-G19 -> 708.725 | I19: 300741
A20: 17 | B20: 3080 | C20: MUSALLAM BAKHIT AWADH L BARAAMI | D20: 1277.8 | E20: 0.250 | F20: =D20*E20 -> 319.45 | H20: =F20-G20 -> 319.45 | I20: 14301608
A21: 18 | B21: 3086 | C21: MUSALLAM ALI MATOOQ TABOOK | D21: 1292.8 | E21: 0.250 | F21: =D21*E21 -> 323.2 | H21: =F21-G21 -> 323.2 | I21: 300033
A22: 19 | B22: 3132 | C22: HASHIM SALIM ALI ATIF AL YAFAI | D22: 1300.8 | E22: 0.250 | F22: =D22*E22 -> 325.2 | H22: =F22-G22 -> 325.2 | I22: 14606296
A23: 20 | B23: 3134 | C23: HASSAN SUHAIL MAHAD QATAN | D23: 941.1 | E23: 0.250 | F23: =D23*E23 -> 235.275 | H23: =F23-G23 -> 235.275 | I23: 2154413
A24: 21 | B24: 3142 | C24: MOHAMMED AHMED SAAD MASHRAH AL SHAHRI | D24: 4729.1 | E24: 0.250 | F24: =D24*E24 -> 1182.275 | H24: =F24-G24 -> 1182.275 | I24: 165497
A25: 22 | B25: 3145 | C25: MOHAMMED BAKHIT MASOUD QATAN | D25: 1752.5 | E25: 0.250 | F25: =D25*E25 -> 438.125 | G25: =F25 -> 438.125 | H25: =F25-G25 -> 0 | I25: 1915745 | J25: 23-2-2025
A26: 23 | B26: 3147 | C26: KHALID SAID MAHAD KASHOUB | D26: 2251.05 | E26: 0.250 | F26: =D26*E26 -> 562.7625 | H26: =F26-G26 -> 562.7625 | I26: 1662414
A27: 24 | B27: 3148 | C27: MUSALLAM AHMED MAHTOUQ AL ZAWAMRI | D27: 902.5 | E27: 0.250 | F27: =D27*E27 -> 225.625 | G27: =F27 -> 225.625 | H27: =F27-G27 -> 0 | I27: 19545736 | J27: DCF Feed-15-01-25
A28: 25 | B28: 3149 | C28: ALI SAID ALI AL ZAWAMRI | D28: 935.6 | E28: 0.250 | F28: =D28*E28 -> 233.9 | H28: =F28-G28 -> 233.9 | I28: 4941095
A29: 26 | B29: 3152 | C29: BAKHIT SALIM MAHAD QATAN | D29: 2348.8 | E29: 0.250 | F29: =D29*E29 -> 587.2 | G29: =584.65+2.55 -> 587.2 | H29: =F29-G29 -> 0 | I29: 941993 | J29: 27-01-25 | K29: 23-1-25
A30: 27 | B30: 3153 | C30: ALI MAHAD SAID QATAN | D30: 2880.7 | E30: 0.250 | F30: =D30*E30 -> 720.175 | H30: =F30-G30 -> 720.175 | I30: 6989479
A31: 28 | B31: 3155 | C31: SAID BAKHIT MAHAD QATAN | D31: 632.1 | E31: 0.250 | F31: =D31*E31 -> 158.025 | H31: =F31-G31 -> 158.025 | I31: 19188794
A32: 29 | B32: 3158 | C32: AHMED OBAIDAN AHMED AL KATHIRI | D32: 2466.6 | E32: 0.250 | F32: =D32*E32 -> 616.65 | H32: =F32-G32 -> 616.65 | I32: 596869
A33: 30 | B33: 3159 | C33: AHMED BAKHIT SALEM AL BARAMI | D33: 924.6 | E33: 0.250 | F33: =D33*E33 -> 231.15 | H33: =F33-G33 -> 231.15 | I33: 1297478
A34: 31 | B34: 3160 | C34: NAIF MUBARAK BAKHIT AL BARAAMI | D34: 1853.6 | E34: 0.250 | F34: =D34*E34 -> 463.4 | H34: =F34-G34 -> 463.4 | I34: 2837163
A35: 32 | B35: 3162 | C35: MOHAMMED SAID FARAJ AL KATHIRI | D35: 4567.5 | E35: 0.250 | F35: =D35*E35 -> 1141.875 | H35: =F35-G35 -> 1141.875 | I35: 7017227
A36: 33 | B36: 3164 | C36: ALI MUSALLLAM HASSAN BAITSAID | D36: 2398.8 | E36: 0.250 | F36: =D36*E36 -> 599.7 | H36: =F36-G36 -> 599.7 | I36: 7466062
A37: 34 | B37: 3165 | C37: KHALID MOHAMMED MASAAOD AGGHRIB AL SHAHRI | D37: 523 | E37: 0.250 | F37: =D37*E37 -> 130.75 | H37: =F37-G37 -> 130.75 | I37: 19029628
A38: 35 | B38: 3169 | C38: MOHAMMED ALI SAID AL ZAWAMRY | D38: 1042.5 | E38: 0.250 | F38: =D38*E38 -> 260.625 | H38: =F38-G38 -> 260.625 | I38: 3068756
A39: 36 | B39: 3171 | C39: HATAM AWADH SAID QATAN | D39: 1009 | E39: 0.250 | F39: =D39*E39 -> 252.25 | H39: =F39-G39 -> 252.25 | I39: 7239057
A40: 37 | B40: 3172 | C40: Fatima Suleimon Salim ALBaramiyah | D40: 1178.5 | E40: 0.250 | F40: =D40*E40 -> 294.625 | H40: =F40-G40 -> 294.625 | I40: 5276984
A41: 38 | B41: 3173 | C41: MUSALLAM AHMED SAAD AL BARAAMI | D41: 2336.7 | E41: 0.250 | F41: =D41*E41 -> 584.175 | H41: =F41-G41 -> 584.175 | I41: 6825655
A42: 39 | B42: 3174 | C42: AHMED MUSALLAM SAID QATAN | D42: 1746.9 | E42: 0.250 | F42: =D42*E42 -> 436.725 | G42: =F42 -> 436.725 | H42: =F42-G42 -> 0 | I42: 7547492 | J42: DCF Feed-26-01-25
A43: 40 | B43: 3175 | C43: SAID AHMED NASIB AL BARAAMI | D43: 547.2 | E43: 0.250 | F43: =D43*E43 -> 136.8 | H43: =F43-G43 -> 136.8 | I43: 7325076
A44: 41 | B44: 3176 | C44: KHAYAR ALI SAID AL BARAAMI | D44: 611.1 | E44: 0.250 | F44: =D44*E44 -> 152.775 | H44: =F44-G44 -> 152.775 | I44: 12178145
A45: 42 | B45: 3179 | C45: SUHAIL MOHAMMED SUHAIL TABUK | D45: 2435.8 | E45: 0.250 | F45: =D45*E45 -> 608.95 | H45: =F45-G45 -> 608.95 | I45: 1870852
A46: 43 | B46: 3181 | C46: TARIK MASOUD MAJADAH AL KATHIRI | D46: 1883.4 | E46: 0.250 | F46: =D46*E46 -> 470.85 | H46: =F46-G46 -> 470.85 | I46: 6116067
A47: 44 | B47: 3183 | C47: Salim Musallam Ali Qatan | D47: 930.2 | E47: 0.250 | F47: =D47*E47 -> 232.55 | G47: =230.075 -> 230.075 | H47: =F47-G47 -> 2.475 | I47: 4955092 | J47: 13-2-25
A48: 45 | B48: 3184 | C48: ALI MOHAMMED MUSALLAM AL BARAAMI | D48: 2560.4 | E48: 0.250 | F48: =D48*E48 -> 640.1 | H48: =F48-G48 -> 640.1 | I48: 6701602
A49: 46 | B49: 3185 | C49: MOHAMMED ALI AHMED AMOOSH THOAR | D49: 1107.5 | E49: 0.250 | F49: =D49*E49 -> 276.875 | H49: =F49-G49 -> 276.875 | I49: 15179209
A50: 47 | B50: 3188 | C50: HASSAN BAKHIT AHMED QATAN | D50: 1143.4 | E50: 0.250 | F50: =D50*E50 -> 285.85 | H50: =F50-G50 -> 285.85 | I50: 19290729
A51: 48 | B51: 3189 | C51: SAID AHMED SAID AL ZAWAMRI | D51: 1628.9 | E51: 0.250 | F51: =D51*E51 -> 407.225 | H51: =F51-G51 -> 407.225 | I51: 2802613
A52: 49 | B52: 3190 | C52: TAFOOL SILMOUN SALIM AL BARAMI | D52: 1425.1 | E52: 0.250 | F52: =D52*E52 -> 356.275 | H52: =F52-G52 -> 356.275 | I52: 3555896
A53: 50 | B53: 3192 | C53: GHAZI SALIM MASOUD TABOOK | D53: 1163.4 | E53: 0.250 | F53: =D53*E53 -> 290.85 | G53: =286.13 -> 286.13 | H53: =F53-G53 -> 4.72 | I53: 5271448 | J53: 17-2-25
A54: 51 | B54: 3195 | C54: MUSTAHIL SAID MUSTAHIL AL BARAAMI | D54: 648.5 | E54: 0.250 | F54: =D54*E54 -> 162.125 | H54: =F54-G54 -> 162.125 | I54: 675849
A55: 52 | B55: 3196 | C55: JASIM MOHAMMED SAID ALI AFIR AL ZAWAMARI | D55: 629.9 | E55: 0.250 | F55: =D55*E55 -> 157.475 | H55: =F55-G55 -> 157.475 | I55: 21080217
A56: 53 | B56: 3197 | C56: MOHSIN SAID MOHAMED BA AWAIN | D56: 1350 | E56: 0.250 | F56: =D56*E56 -> 337.5 | H56: =F56-G56 -> 337.5 | I56: 6479515
A57: 54 | B57: 3198 | C57: ADIL SAID AHMED AL ZAWAMRI | D57: 622.5 | E57: 0.250 | F57: =D57*E57 -> 155.625 | H57: =F57-G57 -> 155.625 | I57: 6360793
A58: 55 | B58: 3310 | C58: AHMED SUHAIL SAID AL BARAMI | D58: 1293.6 | E58: 0.250 | F58: =D58*E58 -> 323.4 | H58: =F58-G58 -> 323.4 | I58: 1007615
A59: 56 | B59: 3324 | C59: BAKHIT AWADH BAKHIT AL BARAAMI | D59: 1288.8 | E59: 0.250 | F59: =D59*E59 -> 322.2 | H59: =F59-G59 -> 322.2 | I59: 207402
A60: 57 | B60: 3330 | C60: Salim Ahmed Aubad Al kathiri | D60: 1328.5 | E60: 0.250 | F60: =D60*E60 -> 332.125 | H60: =F60-G60 -> 332.125 | I60: 6375079
A61: 58 | B61: 3333 | C61: Mahad Salim Zaed Bait Said | D61: 1917.4 | E61: 0.250 | F61: =D61*E61 -> 479.35 | H61: =F61-G61 -> 479.35 | I61: 757601
A62: 59 | B62: 3339 | C62: Khalid Ahmed Salim Amer Jid Almahri | D62: 624.3 | E62: 0.250 | F62: =D62*E62 -> 156.075 | G62: =F62 -> 156.075 | H62: =F62-G62 -> 0 | I62: 12415718 | J62: DCF-29-01-25
A63: 60 | B63: 3500 | C63: Salim Mohammed Ahmed Al Kathiri | D63: 697.1 | E63: 0.250 | F63: =D63*E63 -> 174.275 | G63: =F63 -> 174.275 | H63: =F63-G63 -> 0 | I63: 13525845 | J63: 20-2-25
A64: 61 | B64: 3501 | C64: Said Masoud Ahmed Al kathiri | D64: 1605.3 | E64: 0.250 | F64: =D64*E64 -> 401.325 | H64: =F64-G64 -> 401.325 | I64: 13525794
A65: 62 | B65: 3502 | C65: Ahmed Bakhit Ahmed Al Kathiri | D65: 1297.6 | E65: 0.250 | F65: =D65*E65 -> 324.4 | H65: =F65-G65 -> 324.4 | I65: 22522336
A66: 63 | B66: 3503 | C66: Imad Bakhit Salim Bakhit Qatan | D66: 675.7 | E66: 0.250 | F66: =D66*E66 -> 168.925 | H66: =F66-G66 -> 168.925 | I66: 9212492
A67: 64 | B67: 3504 | C67: Ali Salem Amer Al Kathiri | D67: 1268.8 | E67: 0.250 | F67: =D67*E67 -> 317.2 | H67: =F67-G67 -> 317.2 | I67: 939641
A68: 65 | B68: 3506 | C68: Ahmed Masoud Salim Al Kathiri | D68: 644.6 | E68: 0.250 | F68: =D68*E68 -> 161.15 | H68: =F68-G68 -> 161.15 | I68: 13307752
A69: 66 | B69: 3507 | C69: Bakhit Suhail Ahmed Qatan | D69: 403.6 | E69: 0.250 | F69: =D69*E69 -> 100.9 | H69: =F69-G69 -> 100.9 | I69: 1184669
A70: 67 | B70: 3508 | C70: Said Ali Said Al Zawamri | D70: 629.6 | E70: 0.250 | F70: =D70*E70 -> 157.4 | H70: =F70-G70 -> 157.4 | I70: 2567166
A71: 68 | B71: 3509 | C71: Asama Mohammed Ahmed Masharah Al Shahri | D71: 574.6 | E71: 0.250 | F71: =D71*E71 -> 143.65 | H71: =F71-G71 -> 143.65 | I71: 22760088
A72: 69 | B72: 3510 | C72: Amer Ali Ahmed Al kathiri | D72: 1276.7 | E72: 0.250 | F72: =D72*E72 -> 319.175 | G72: =318.525 -> 318.525 | H72: =F72-G72 -> 0.65 | I72: 6920351 | J72: 20-02-25
A73: 70 | B73: 3511 | C73: Said Ali Said Qatan | D73: 1814.7 | E73: 0.250 | F73: =D73*E73 -> 453.675 | G73: =452.775 -> 452.775 | H73: =F73-G73 -> 0.9 | I73: 2640016 | J73: 45932
A74: 71 | B74: 3512 | C74: Ahmed Abdul Rahim Ali Al Kathiri | E74: 0.250 | F74: =D74*E74 -> 0 | H74: =F74-G74 -> 0 | I74: 5514631
A75: 72 | B75: 3513 | C75: Khair Salim Faraj Al Kathiri | D75: 2520.5 | E75: 0.250 | F75: =D75*E75 -> 630.125 | H75: =F75-G75 -> 630.125 | I75: 7047376
A76: 73 | B76: 3514 | C76: Said Salim Faraj Al Kathiri | D76: 1303.4 | E76: 0.250 | F76: =D76*E76 -> 325.85 | H76: =F76-G76 -> 325.85 | I76: 440083
A77: 74 | B77: 3515 | C77: Ali Ajaham Ali Bait said | D77: 1879.2 | E77: 0.250 | F77: =D77*E77 -> 469.8 | H77: =F77-G77 -> 469.8 | I77: 6645198
A78: 75 | B78: 3516 | C78: Musallam Hassan Ali Bait Muhammed Bin Ahmed | D78: 1860.7 | E78: 0.250 | F78: =D78*E78 -> 465.175 | H78: =F78-G78 -> 465.175 | I78: 1165877
A79: 76 | B79: 3517 | C79: Mohammed Salim Faraj Al Kathiri | D79: 1283.9 | E79: 0.250 | F79: =D79*E79 -> 320.975 | H79: =F79-G79 -> 320.975 | I79: 7047081
A80: 77 | B80: 3518 | C80: Ali Ahmed Ali Bait Said | D80: 729.9 | E80: 0.250 | F80: =D80*E80 -> 182.475 | G80: =63.725 -> 63.725 | H80: =F80-G80 -> 118.75 | I80: 20386956 | J80: 13-2-25
A81: 78 | B81: 3519 | C81: Masoud Salim Faraj Al Kathiri | D81: 633.7 | E81: 0.250 | F81: =D81*E81 -> 158.425 | H81: =F81-G81 -> 158.425 | I81: 7047221
A82: 79 | B82: 3520 | C82: Musallam Mahad Suhail Al Barami | D82: 634.3 | E82: 0.250 | F82: =D82*E82 -> 158.575 | H82: =F82-G82 -> 158.575 | I82: 5665362
A83: 80 | B83: 3521 | C83: Omar Said Awadh Bait Said | D83: 3776.2 | E83: 0.250 | F83: =D83*E83 -> 944.05 | H83: =F83-G83 -> 944.05 | I83: 7064553
A84: 81 | B84: 3522 | C84: Said Ahmed Ali Qatan | D84: 861.5 | E84: 0.250 | F84: =D84*E84 -> 215.375 | H84: =F84-G84 -> 215.375 | I84: 11365191
D85: =SUM(D4:D84) -> 142436.35 | F85: =SUM(F4:F84) -> 35609.088 | G85: =SUM(G4:G84) -> 5406.98 | H85: =SUM(H4:H84) -> 30202.108

Sheet July 25
A1: HAJEEF COW MILK PROCUREMENT FROM 01-Jul-2025 to 31-Jul-2025
A2: Sr No. | B2: Farmer Code | C2: Farmer Name | D2: Milk Qty. (Ltr.) | E2: Avg. Rate (OMR/Ltr.) | F2: Amount (OMR) | G2: paid | H2: balance | I2: ID No. | J2: Bank Account No. | K2: Bank Name | L2: IFSC Code | M2: Phone No. | N2: Remarks
A4: 1 | B4: 1007 | C4: AHMED ABDULLAH SAID AL RAWAS | D4: 6375 | E4: 0.250 | F4: =D4*E4 -> 1593.75 | G4: =F4 -> 1593.75 | H4: =F4-G4 -> 0 | I4: 1515504 | J4: 0615500670380001 | K4: Bank Meethaq | L4: BMUSOMRXISL | M4: 91748840
A5: 2 | B5: 1041 | C5: AHMED SALIM ALI BAITSAID | D5: 3382.3 | E5: 0.250 | F5: =D5*E5 -> 845.575 | G5: =F5 -> 845.575 | H5: =F5-G5 -> 0 | I5: 6827729 | J5: 0406003463970017 | K5: BANK MUSCAT | L5: BMUSOMRX | M5: 92272935
A6: 3 | B6: 1125 | C6: MUSALLAM SAID ALI BAITSAID | D6: 5794.4 | E6: 0.250 | F6: =D6*E6 -> 1448.6 | G6: =F6 -> 1448.6 | H6: =F6-G6 -> 0 | I6: 6828774 | J6: 01011456108001 | K6: BANK DHOFAR | L6: BDOFOMRU | M6: 91267555 | N6: 20-10-2025
A7: 4 | B7: 1222 | C7: Mahad Salim Abdulaziz Alkathiri | E7: 0.250 | F7: =D7*E7 -> 0 | H7: =F7-G7 -> 0 | I7: 31221 | J7: 1006623107017 | K7: NBO | L7: NBOMOMRX
A8: 5 | B8: 1286 | C8: SALIM AMER AHMED AL YAFAEI | D8: 3002.7 | E8: 0.250 | F8: =D8*E8 -> 750.675 | G8: =F8 -> 750.675 | H8: =F8-G8 -> 0 | I8: 368056 | J8: 0406003218280013 | K8: BANK MUSCAT | L8: BMUSOMRX | M8: 99494264
A9: 6 | B9: 1344 | C9: SAID AMERAHMED BAITSAID | D9: 3180.4 | E9: 0.250 | F9: =D9*E9 -> 795.1 | G9: =793.925+1.175 -> 795.1 | H9: =F9-G9 -> 0 | I9: 4014519 | J9: 3109370559500 | K9: OAB | L9: OMABOMRU | N9: 45879 | O9: 15-10-25
A10: 7 | B10: 1352 | C10: MOHAMMED MASOUD AJHAM ALSH AL KATHIRI | D10: 1179.3 | E10: 0.250 | F10: =D10*E10 -> 294.825 | G10: =291.55+3.275 -> 294.825 | H10: =F10-G10 -> 0 | I10: 1627344 | J10: 0397046773470015 | K10: BANK MUSCAT | L10: BMUSOMRX | N10: 22.9.2025 | O10: 15-10-25
A11: 8 | B11: 1354 | C11: AHMED SAID HASSAN BAITSAID | D11: 2377.5 | E11: 0.250 | F11: =D11*E11 -> 594.375 | G11: =F11 -> 594.375 | H11: =F11-G11 -> 0 | I11: 925709 | J11: 0406018690130014 | K11: BANK MUSCAT | L11: BMUSOMRX | M11: 95187860
A12: 9 | B12: 1357 | C12: MUSALLAM SAID ALI BAIT SAID | D12: 5065.8 | E12: 0.250 | F12: =D12*E12 -> 1266.45 | G12: =F12 -> 1266.45 | H12: =F12-G12 -> 0 | I12: 1052276 | J12: 01040280323001 | K12: BANK DHOFAR | L12: BDOFOMRU | M12: 95301260
A13: 10 | B13: 1359 | C13: MUSALLAM MUSTAHIL SAID BAIT SAID | D13: 3841 | E13: 0.250 | F13: =D13*E13 -> 960.25 | G13: =959.05+1.2 -> 960.25 | H13: =F13-G13 -> 0 | I13: 4812026 | J13: 1083517184017 | K13: NBO | L13: NBOMOMRX | M13: 96616558 | N13: 18-9-2025 | O13: 15-10-25
A14: 11 | B14: 1367 | C14: ALI MUSALLAM AHMED BAIT SAID | D14: 1290.4 | E14: 0.250 | F14: =D14*E14 -> 322.6 | G14: =F14 -> 322.6 | H14: =F14-G14 -> 0 | I14: 6663593 | J14: 0406003006560016 | K14: BANK MUSCAT | L14: BMUSOMRX | M14: 92817702 | N14: 14-10-2025
A15: 12 | B15: 1368 | C15: MOHAMMD SAID AHMED AL KATHIRI | D15: 2271.9 | E15: 0.250 | F15: =D15*E15 -> 567.975 | G15: =F15 -> 567.975 | H15: =F15-G15 -> 0 | I15: 561902 | J15: 01040854387001 | K15: BANK DHOFAR | L15: BDOFOMRU | M15: 99499622
A16: 13 | B16: 2098 | C16: Bakhit Musallam Ali Kashoob | D16: 785.1 | E16: 0.250 | F16: =D16*E16 -> 196.275 | G16: =F16 -> 196.275 | H16: =F16-G16 -> 0 | I16: 1065899 | J16: 132857700081018 | K16: BANK MUSCAT | L16: BMUSOMRX | N16: 15-10-25
A17: 14 | B17: 3002 | C17: KHALID MUBARAK ALI ATQOON AL SHAHRI | D17: 1094.5 | E17: 0.250 | F17: =D17*E17 -> 273.625 | G17: =0.2+271.8+1.625 -> 273.625 | H17: =F17-G17 -> 0 | I17: 21220177 | J17: 0401016727580038 | K17: BANK MUSCAT | L17: BMUSOMRX | M17: 99280644 | N17: 45666 | O17: 18-9-2025 | P17: 15-10-25
A18: 15 | B18: 3035 | C18: TARIQ SALIM SUHAIL AL BARAMI | E18: 0.250 | F18: =D18*E18 -> 0 | H18: =F18-G18 -> 0 | I18: 6725058 | J18: 01011059048001 | K18: BANK DHOFAR | L18: BDOFOMRU | M18: 99198121
A19: 16 | B19: 3057 | C19: ALI AHMED MOHAMMED AL KATHIRI | D19: 2905.8 | E19: 0.250 | F19: =D19*E19 -> 726.45 | G19: =F19 -> 726.45 | H19: =F19-G19 -> 0 | I19: 626819 | J19: 0397003510460014 | K19: BANK MUSCAT | L19: BMUSOMRX | M19: 99298522 | N19: BT 04-12-2025
A20: 17 | B20: 3062 | C20: ALI MAHAD SILMOUN QATAN | D20: 2176.1 | E20: 0.250 | F20: =D20*E20 -> 544.025 | G20: =F20 -> 544.025 | H20: =F20-G20 -> 0 | I20: 300741 | J20: 0397004203200017 | K20: BANK MUSCAT | L20: BMUSOMRX | M20: 99008320
A21: 18 | B21: 3080 | C21: MUSALLAM BAKHIT AWADH L BARAAMI | D21: 1290.7 | E21: 0.250 | F21: =D21*E21 -> 322.675 | G21: =F21 -> 322.675 | H21: =F21-G21 -> 0 | I21: 14301608 | J21: 0397003041020024 | K21: BANK MUSCAT | L21: BMUSOMRX | M21: 98122611 | N21: BT 04-12-2025
A22: 19 | B22: 3086 | C22: MUSALLAM ALI MATOOQ TABOOK | D22: 39.5 | E22: 0.250 | F22: =D22*E22 -> 9.875 | G22: =6.3+3.575 -> 9.875 | H22: =F22-G22 -> 0 | I22: 300033 | J22: 0397003905720015 | K22: BANK MUSCAT | L22: BMUSOMRX | N22: 24.9.2025 | O22: 27-10-2025
A23: 20 | B23: 3132 | C23: HASHIM SALIM ALI ATIF AL YAFAI | D23: 1266.8 | E23: 0.250 | F23: =D23*E23 -> 316.7 | G23: =F23 -> 316.7 | H23: =F23-G23 -> 0 | I23: 14606296 | J23: 01013095125001 | K23: BANK DHOFAR | L23: BDOFOMRU | M23: 91493522 | O23: Update Bank account on 23-9-2025
A24: 21 | B24: 3134 | C24: HASSAN SUHAIL MAHAD QATAN | D24: 1344.5 | E24: 0.250 | F24: =D24*E24 -> 336.125 | G24: =F24 -> 336.125 | H24: =F24-G24 -> 0 | I24: 2154413 | J24: 01010850952003 | K24: BANK DHOFAR | L24: BDOFOMRU | M24: 99493731 | N24: BT 24-9-2025
A25: 22 | B25: 3142 | C25: MOHAMMED AHMED SAAD MASHRAH AL SHAHRI | D25: 4692.5 | E25: 0.250 | F25: =D25*E25 -> 1173.125 | G25: =0.3+584.25+584.25+4.325 -> 1173.125 | H25: =F25-G25 -> 0 | I25: 165497 | J25: 3129019324700 | K25: OAB | L25: OMABOMRU | M25: 99499872 | N25: 45666 | O25: 15-10-25
A26: 23 | B26: 3145 | C26: MOHAMMED BAKHIT MASOUD QATAN | D26: 2718.3 | E26: 0.250 | F26: =D26*E26 -> 679.575 | G26: =677.525+2.05 -> 679.575 | H26: =F26-G26 -> 0 | I26: 1915745 | J26: 0404002595460014 | K26: BANK MUSCAT | L26: BMUSOMRX | M26: 99489050 | N26: 29.9.2025 | O26: 20-10-2025
A27: 24 | B27: 3147 | C27: KHALID SAID MAHAD KASHOUB | D27: 1124.8 | E27: 0.250 | F27: =D27*E27 -> 281.2 | G27: =0.6+280.25+0.35 -> 281.2 | H27: =F27-G27 -> 0 | I27: 1662414 | J27: 3129770819700 | K27: OAB | L27: OMABOMRU | M27: 99282006 | N27: 17-9-2025 | O27: 45818 | P27: 27-10-2025
A28: 25 | B28: 3148 | C28: MUSALLAM AHMED MAHTOUQ AL ZAWAMRI | D28: 1299.3 | E28: 0.250 | F28: =D28*E28 -> 324.825 | G28: =324.725+0.1 -> 324.825 | H28: =F28-G28 -> 0 | I28: 19545736 | J28: 01011208343002 | K28: BANK DHOFAR | L28: BDOFOMRU | N28: 45667 | O28: 22-10-2025
A29: 26 | B29: 3149 | C29: ALI SAID ALI AL ZAWAMRI | D29: 1576.7 | E29: 0.250 | F29: =D29*E29 -> 394.175 | G29: =391.625+2.55 -> 394.175 | H29: =F29-G29 -> 0 | I29: 4941095 | J29: 1104036354300 | K29: Ahli Bank | L29: AUBOOMRU | M29: 93500864 | N29: 20-10-2025
A30: 27 | B30: 3152 | C30: BAKHIT SALIM MAHAD QATAN | D30: 3099.8 | E30: 0.250 | F30: =D30*E30 -> 774.95 | G30: =772.2+2.75 -> 774.95 | H30: =F30-G30 -> 0 | I30: 941993 | J30: 01042574515001 | K30: BANK DHOFAR | L30: BDOFOMRU | M30: 99086500 | N30: 45878
A31: 28 | B31: 3153 | C31: ALI MAHAD SAID QATAN | D31: 2859.2 | E31: 0.250 | F31: =D31*E31 -> 714.8 | G31: =F31 -> 714.8 | H31: =F31-G31 -> 0 | I31: 6989479 | J31: 0397003672070015 | K31: BANK MUSCAT | L31: BMUSOMRX | M31: 99699500
A32: 29 | B32: 3155 | C32: SAID BAKHIT MAHAD QATAN | D32: 631.9 | E32: 0.250 | F32: =D32*E32 -> 157.975 | G32: =F32 -> 157.975 | H32: =F32-G32 -> 0 | I32: 19188794 | J32: 0402003042750013 | K32: BANK MUSCAT | L32: BMUSOMRX | M32: 93215515
A33: 30 | B33: 3158 | C33: AHMED OBAIDAN AHMED AL KATHIRI | D33: 2875.5 | E33: 0.250 | F33: =D33*E33 -> 718.875 | G33: =F33 -> 718.875 | H33: =F33-G33 -> 0 | I33: 596869 | J33: 0401049081340015 | K33: BANK MUSCAT | L33: BMUSOMRX | M33: 99694218
A34: 31 | B34: 3159 | C34: AHMED BAKHIT SALEM AL BARAMI | D34: 1022.6 | E34: 0.250 | F34: =D34*E34 -> 255.65 | G34: =F34 -> 255.65 | H34: =F34-G34 -> 0 | I34: 1297478 | J34: 0397003703480012 | K34: BANK MUSCAT | L34: BMUSOMRX | M34: 99497177
A35: 32 | B35: 3160 | C35: NAIF MUBARAK BAKHIT AL BARAAMI | D35: 1834.9 | E35: 0.250 | F35: =D35*E35 -> 458.725 | G35: =F35 -> 458.725 | H35: =F35-G35 -> 0 | I35: 2837163 | J35: 00510031862001 | K35: Bank Nizwa | L35: BNZWOMRX | M35: 99497455
A36: 33 | B36: 3162 | C36: MOHAMMED SAID FARAJ AL KATHIRI | D36: 5679.5 | E36: 0.250 | F36: =D36*E36 -> 1419.875 | G36: =F36 -> 1419.875 | H36: =F36-G36 -> 0 | I36: 7017227 | J36: 0439003443420024 | K36: Bank Muscat | L36: BMUSOMRX | M36: 99523400 | N36: BT 28-10-2025 | O36: Update Bank Account
A37: 34 | B37: 3164 | C37: ALI MUSALLLAM HASSAN BAITSAID | D37: 2366.3 | E37: 0.250 | F37: =D37*E37 -> 591.575 | G37: =589.55+2.025 -> 591.575 | H37: =F37-G37 -> 0 | I37: 7466062 | J37: 01646038607001 | K37: Maisarah | L37: BDOFOMRUMIB | M37: 91135005 | N37: 29.9.2025 | O37: 29-10-2025
A38: 35 | B38: 3165 | C38: KHALID MOHAMMED MASAAOD AGGHRIB AL SHAHRI | D38: 345.2 | E38: 0.250 | F38: =D38*E38 -> 86.3 | G38: =F38 -> 86.3 | H38: =F38-G38 -> 0 | I38: 19029628 | J38: 01011251497002 | K38: BANK DHOFAR | L38: BDOFOMRU | M38: 96055446
A39: 36 | B39: 3169 | C39: MOHAMMED ALI SAID AL ZAWAMRY | D39: 1835.3 | E39: 0.250 | F39: =D39*E39 -> 458.825 | G39: =3.15+455.675 -> 458.825 | H39: =F39-G39 -> 0 | I39: 3068756 | J39: 01012573317001 | K39: BANK DHOFAR | L39: BDOFOMRU | M39: 99691806 | N39: 29-10-2025 | O39: 45727
A40: 37 | B40: 3171 | C40: HATAM AWADH SAID QATAN | D40: 1077.6 | E40: 0.250 | F40: =D40*E40 -> 269.4 | G40: =266.425+2.975 -> 269.4 | H40: =F40-G40 -> 0 | I40: 7239057 | J40: 3109607126500 | K40: OAB | L40: OMABOMRU | M40: 95880860 | N40: 18-9-2025 | O40: 15-10-25
A41: 38 | B41: 3172 | C41: Fatima Suleimon Salim ALBaramiyah | D41: 1274.3 | E41: 0.250 | F41: =D41*E41 -> 318.575 | G41: =F41 -> 318.575 | H41: =F41-G41 -> 0 | I41: 5276984 | J41: 0439046831000027 | K41: BANK MUSCAT | L41: BMUSOMRX | M41: 99188860
A42: 39 | B42: 3173 | C42: MUSALLAM AHMED SAAD AL BARAAMI | D42: 506.6 | E42: 0.250 | F42: =D42*E42 -> 126.65 | G42: =123.75+2.9 -> 126.65 | H42: =F42-G42 -> 0 | I42: 6825655 | J42: 0397004380200011 | K42: BANK MUSCAT | L42: BMUSOMRX | M42: 98957747 | N42: 24.9.2025 | O42: 15-10-25
A43: 40 | B43: 3174 | C43: AHMED MUSALLAM SAID QATAN | D43: 649.8 | E43: 0.250 | F43: =D43*E43 -> 162.45 | G43: =2.975+159.4752 -> 162.4502 | H43: =F43-G43 -> -0.0002 | I43: 7547492 | J43: 0401002379960017 | K43: BANK MUSCAT | L43: BMUSOMRX | M43: 91790502 | N43: 45728
A44: 41 | B44: 3175 | C44: SAID AHMED NASIB AL BARAAMI | D44: 653.3 | E44: 0.250 | F44: =D44*E44 -> 163.325 | G44: =161.875+1.45 -> 163.325 | H44: =F44-G44 -> 0 | I44: 7325076 | J44: 1006794849001 | K44: NBO | L44: NBOMOMRX | M44: 92890700 | N44: 18-9-2025 | O44: 27-10-2025
A45: 42 | B45: 3176 | C45: KHAYAR ALI SAID AL BARAAMI | D45: 593.7 | E45: 0.250 | F45: =D45*E45 -> 148.425 | G45: =1.67500000000001+146.75 -> 148.425 | H45: =F45-G45 -> 0 | I45: 12178145 | J45: 0406015163810016 | K45: BANK MUSCAT | L45: BMUSOMRX | M45: 93348565
A46: 43 | B46: 3179 | C46: SUHAIL MOHAMMED SUHAIL TABUK | D46: 4019.3 | E46: 0.250 | F46: =D46*E46 -> 1004.825 | G46: =F46 -> 1004.825 | H46: =F46-G46 -> 0 | I46: 1870852 | J46: 3129685484720 | K46: OAB | L46: OMABOMRU | M46: 99050691
A47: 44 | B47: 3181 | C47: TARIK MASOUD MAJADAH AL KATHIRI | D47: 1726.1 | E47: 0.250 | F47: =D47*E47 -> 431.525 | G47: =F47 -> 431.525 | H47: =F47-G47 -> 0 | I47: 6116067 | J47: 3109710314700 | K47: OAB | L47: OMABOMRU | M47: 99191102
A48: 45 | B48: 3183 | C48: Salim Musallam Ali Qatan | D48: 1256.2 | E48: 0.250 | F48: =D48*E48 -> 314.05 | G48: =311+3.05 -> 314.05 | H48: =F48-G48 -> 0 | I48: 4955092 | J48: 0401002697260019 | K48: BANK MUSCAT | L48: BMUSOMRX | M48: 98152775 | N48: 18-9-2025 | O48: 15-10-25
A49: 46 | B49: 3184 | C49: ALI MOHAMMED MUSALLAM AL BARAAMI | D49: 2500.2 | E49: 0.250 | F49: =D49*E49 -> 625.05 | G49: =F49 -> 625.05 | H49: =F49-G49 -> 0 | I49: 6701602 | J49: 01011004872002 | K49: BANK DHOFAR | L49: BDOFOMRU | M49: 99496161
A50: 47 | B50: 3185 | C50: MOHAMMED ALI AHMED AMOOSH THOAR | D50: 1125.6 | E50: 0.250 | F50: =D50*E50 -> 281.4 | G50: =177.35+104.05 -> 281.4 | H50: =F50-G50 -> 0 | I50: 15179209 | J50: 0405020308900019 | K50: BANK MUSCAT | L50: BMUSOMRX | M50: 94919974 | N50: 24.9.2025 | O50: 14-10-2025
A51: 48 | B51: 3188 | C51: HASSAN BAKHIT AHMED QATAN | D51: 888.8 | E51: 0.250 | F51: =D51*E51 -> 222.2 | G51: =221.525+0.675 -> 222.2 | H51: =F51-G51 -> 0 | I51: 19290729 | J51: 01041574026001 | K51: BANK DHOFAR | L51: BDOFOMRU | M51: 95606029 | N51: 29.9.2025 | O51: 27-10-2025
A52: 49 | B52: 3189 | C52: SAID AHMED SAID AL ZAWAMRI | D52: 1394.6 | E52: 0.250 | F52: =D52*E52 -> 348.65 | G52: =346.875+1.775 -> 348.65 | H52: =F52-G52 -> 0 | I52: 2802613 | J52: 0405002746200013 | K52: BANK MUSCAT | L52: BMUSOMRX | M52: 99480848 | N52: 18-9-2025 | O52: BT 30-10-2025
A53: 50 | B53: 3190 | C53: TAFOOL SILMOUN SALIM AL BARAMI | D53: 594.1 | E53: 0.250 | F53: =D53*E53 -> 148.525 | G53: =F53 -> 148.525 | H53: =F53-G53 -> 0 | I53: 3555896 | J53: 0402014490950017 | K53: BANK MUSCAT | L53: BMUSOMRX | M53: 92881155
A54: 51 | B54: 3192 | C54: GHAZI SALIM MASOUD TABOOK | D54: 1299.2 | E54: 0.250 | F54: =D54*E54 -> 324.8 | G54: =323.35+1.45 -> 324.8 | H54: =F54-G54 -> 0 | I54: 5271448 | J54: 0401002602010018 | K54: BANK MUSCAT | L54: BMUSOMRX | M54: 99489918 | N54: 22.9.2025 | O54: 27-10-2025
A55: 52 | B55: 3195 | C55: MUSTAHIL SAID MUSTAHIL AL BARAAMI | D55: 609.3 | E55: 0.250 | F55: =D55*E55 -> 152.325 | G55: =F55 -> 152.325 | H55: =F55-G55 -> 0 | I55: 675849 | J55: 01011097969001 | K55: BANK DHOFAR | L55: BDOFOMRU | M55: 99483811
A56: 53 | B56: 3196 | C56: JASIM MOHAMMED SAID ALI AFIR AL ZAWAMARI | D56: 638.5 | E56: 0.250 | F56: =D56*E56 -> 159.625 | G56: =F56 -> 159.625 | H56: =F56-G56 -> 0 | I56: 21080217 | J56: 0401007927380037 | K56: BANK MUSCAT | L56: BMUSOMRX | M56: 95490778
A57: 54 | B57: 3197 | C57: MOHSIN SAID MOHAMED BA AWAIN | D57: 1862.8 | E57: 0.250 | F57: =D57*E57 -> 465.7 | G57: =F57 -> 465.7 | H57: =F57-G57 -> 0 | I57: 6479515 | J57: 0406003220920038 | K57: BANK MUSCAT | L57: BMUSOMRX | M57: 92349032
A58: 55 | B58: 3198 | C58: ADIL SAID AHMED AL ZAWAMRI | D58: 629.6 | E58: 0.250 | F58: =D58*E58 -> 157.4 | G58: =F58 -> 157.4 | H58: =F58-G58 -> 0 | I58: 6360793 | J58: 00510047506001 | K58: Bank Nizwa | L58: BNZWOMRX | M58: 99336200
A59: 56 | B59: 3310 | C59: AHMED SUHAIL SAID AL BARAMI | D59: 1263 | E59: 0.250 | F59: =D59*E59 -> 315.75 | G59: =F59 -> 315.75 | H59: =F59-G59 -> 0 | I59: 1007615 | J59: 0397003855850017 | K59: BANK MUSCAT | L59: BMUSOMRX | M59: 99056614
A60: 57 | B60: 3324 | C60: BAKHIT AWADH BAKHIT AL BARAAMI | D60: 1294.4 | E60: 0.250 | F60: =D60*E60 -> 323.6 | G60: =F60 -> 323.6 | H60: =F60-G60 -> 0 | I60: 207402 | J60: 0401057742590016 | K60: BANK MUSCAT | L60: BMUSOMRX | M60: 99487533 | N60: BT 04-12-2025
A61: 58 | B61: 3330 | C61: Salim Ahmed Aubad Al kathiri | D61: 1818.7 | E61: 0.250 | F61: =D61*E61 -> 454.675 | G61: =F61 -> 454.675 | H61: =F61-G61 -> 0 | I61: 6375079 | J61: 0397062111930011 | K61: Bank Muscat | L61: BMUSOMRX
A62: 59 | B62: 3333 | C62: Mahad Salim Zaed Bait Said | D62: 1246.8 | E62: 0.250 | F62: =D62*E62 -> 311.7 | G62: =F62 -> 311.7 | H62: =F62-G62 -> 0 | I62: 757601 | J62: 1023113274001 | K62: NBO | L62: NBOMOMRX
A63: 60 | B63: 3339 | C63: Khalid Ahmed Salim Amer Jid Almahri | D63: 476.8 | E63: 0.250 | F63: =D63*E63 -> 119.2 | G63: =116.85+2.35 -> 119.2 | H63: =F63-G63 -> 0 | I63: 12415718 | J63: 0401050718800013 | K63: BANK MUSCAT | L63: BMUSOMRX | N63: 22.9.2025 | O63: 15-10-25
A64: 61 | B64: 3500 | C64: Salim Mohammed Ahmed Al Kathiri | D64: 312.2 | E64: 0.250 | F64: =D64*E64 -> 78.05 | G64: =F64 -> 78.05 | H64: =F64-G64 -> 0 | I64: 13525845 | J64: 10600259604017 | K64: NBO | L64: NBOMOMRX | M64: 93985671
A65: 62 | B65: 3501 | C65: Said Masoud Ahmed Al kathiri | D65: 2126.9 | E65: 0.250 | F65: =D65*E65 -> 531.725 | G65: =F65 -> 531.725 | H65: =F65-G65 -> 0 | I65: 13525794 | J65: 0402003356710024 | K65: BANK MUSCAT | L65: BMUSOMRX | M65: 92868004
A66: 63 | B66: 3502 | C66: Ahmed Bakhit Ahmed Al Kathiri | D66: 1261.1 | E66: 0.250 | F66: =D66*E66 -> 315.275 | G66: =F66 -> 315.275 | H66: =F66-G66 -> 0 | I66: 22522336 | J66: 01011021065002 | K66: BANK DHOFAR | L66: BDOFOMRU
A67: 64 | B67: 3503 | C67: Imad Bakhit Salim Bakhit Qatan | D67: 574 | E67: 0.250 | F67: =D67*E67 -> 143.5 | G67: =F67 -> 143.5 | H67: =F67-G67 -> 0 | I67: 9212492 | J67: 0401028325700011 | K67: BANK MUSCAT | L67: BMUSOMRX | M67: 98080144
A68: 65 | B68: 3504 | C68: Ali Salem Amer Al Kathiri | E68: 0.250 | F68: =D68*E68 -> 0 | H68: =F68-G68 -> 0 | I68: 939641 | J68: 0406003375130017 | K68: BANK MUSCAT | L68: BMUSOMRX | M68: 99588609
A69: 66 | B69: 3506 | C69: Ahmed Masoud Salim Al Kathiri | D69: 615.6 | E69: 0.250 | F69: =D69*E69 -> 153.9 | G69: =F69 -> 153.9 | H69: =F69-G69 -> 0 | I69: 13307752 | J69: 0397048001530015 | K69: BANK MUSCAT | L69: BMUSOMRX | M69: 99294425 | N69: 45941
A70: 67 | B70: 3507 | C70: Bakhit Suhail Ahmed Qatan | D70: 689.5 | E70: 0.250 | F70: =D70*E70 -> 172.375 | G70: =F70 -> 172.375 | H70: =F70-G70 -> 0 | I70: 1184669 | J70: 01040281423001 | K70: BANK DHOFAR | L70: BDOFOMRU | M70: 99291928 | N70: BT-27-10-2025
A71: 68 | B71: 3508 | C71: Said Ali Said Al Zawamri | D71: 668.6 | E71: 0.250 | F71: =D71*E71 -> 167.15 | G71: =F71 -> 167.15 | H71: =F71-G71 -> 0 | I71: 2567166 | J71: 0439004225500028 | K71: BANK MUSCAT | L71: BMUSOMRX | M71: 92570156
A72: 69 | B72: 3509 | C72: Asama Mohammed Ahmed Masharah Al Shahri | D72: 566.2 | E72: 0.250 | F72: =D72*E72 -> 141.55 | G72: =F72 -> 141.55 | H72: =F72-G72 -> 0 | I72: 22760088 | J72: 3129152535700 | K72: OAB | L72: OMABOMRU | M72: 91476443
A73: 70 | B73: 3510 | C73: Amer Ali Ahmed Al kathiri | D73: 1205.4 | E73: 0.250 | F73: =D73*E73 -> 301.35 | G73: =F73 -> 301.35 | H73: =F73-G73 -> 0 | I73: 6920351 | J73: 0397003252950036 | K73: BANK MUSCAT | L73: BMUSOMRX | M73: 98933077
A74: 71 | B74: 3511 | C74: Said Ali Said Qatan | D74: 181.6 | E74: 0.250 | F74: =D74*E74 -> 45.4 | G74: =F74 -> 45.4 | H74: =F74-G74 -> 0 | I74: 2640016 | J74: 0501036199001 | K74: Ahli Islamic | L74: AUBOOMRUALH | M74: 92953388 | N74: 15-10-25
A75: 72 | B75: 3512 | C75: Ahmed Abdul Rahim Ali Al Kathiri | E75: 0.250 | F75: =D75*E75 -> 0 | H75: =F75-G75 -> 0 | I75: 5514631 | J75: 01041149485001 | K75: BANK DHOFAR | L75: BDOFOMRU
A76: 73 | B76: 3513 | C76: Khair Salim Faraj Al Kathiri | D76: 2585.1 | E76: 0.250 | F76: =D76*E76 -> 646.275 | G76: =F76 -> 646.275 | H76: =F76-G76 -> 0 | I76: 7047376 | J76: 01013042263001 | K76: BANK DHOFAR | L76: BDOFOMRU | M76: 90106022 | N76: BT 29-10-2025
A77: 74 | B77: 3514 | C77: Said Salim Faraj Al Kathiri | D77: 1278.9 | E77: 0.250 | F77: =D77*E77 -> 319.725 | G77: =4.12500000000002+315.6 -> 319.725 | H77: =F77-G77 -> 0 | I77: 440083 | J77: 0397003539170015 | K77: Bank Muscat | L77: BMUSOMRX | M77: 92363355 | N77: 27-10-25 | O77: 19-11-25
A78: 75 | B78: 3515 | C78: Ali Ajaham Ali Bait said | D78: 1808.9 | E78: 0.250 | F78: =D78*E78 -> 452.225 | G78: =448.675+3.55 -> 452.225 | H78: =F78-G78 -> 0 | I78: 6645198 | J78: 01011180247001 | K78: BANK DHOFAR | L78: BDOFOMRU | M78: 94411217 | N78: 22.9.2025 | O78: 15-10-25
A79: 76 | B79: 3516 | C79: Musallam Hassan Ali Bait Muhammed Bin Ahmed | D79: 1899.4 | E79: 0.250 | F79: =D79*E79 -> 474.85 | G79: =3.325+471.525 -> 474.85 | H79: =F79-G79 -> 0 | I79: 1165877 | J79: 01010127958001 | K79: BANK DHOFAR | L79: BDOFOMRU | N79: 17-9-25 | O79: BT-16-11-25
A80: 77 | B80: 3517 | C80: Mohammed Salim Faraj Al Kathiri | D80: 1221 | E80: 0.250 | F80: =D80*E80 -> 305.25 | G80: =0.775+304.475 -> 305.25 | H80: =F80-G80 -> 0 | I80: 7047081 | J80: 01010401370002 | K80: BANK DHOFAR | L80: BDOFOMRU | N80: 18-9-2025 | O80: 14-10-2025
A81: 78 | B81: 3518 | C81: Ali Ahmed Ali Bait Said | D81: 1232.9 | E81: 0.250 | F81: =D81*E81 -> 308.225 | G81: =304.075+4.15 -> 308.225 | H81: =F81-G81 -> 0 | I81: 20386956 | J81: 0396064567750014 | K81: BANK MUSCAT | L81: BMUSOMRX | N81: 45667 | O81: 20-10-2025
A82: 79 | B82: 3519 | C82: Masoud Salim Faraj Al Kathiri | D82: 611.8 | E82: 0.250 | F82: =D82*E82 -> 152.95 | G82: =0.7+152.25 -> 152.95 | H82: =F82-G82 -> 0 | I82: 7047221 | J82: 01011028414003 | K82: BANK DHOFAR | L82: BDOFOMRU | N82: 18-9-2025 | O82: 14-10-2025
A83: 80 | B83: 3520 | C83: Musallam Mahad Suhail Al Barami | D83: 923.1 | E83: 0.250 | F83: =D83*E83 -> 230.775 | G83: =F83 -> 230.775 | H83: =F83-G83 -> 0 | I83: 5665362 | J83: 01011072899001 | K83: BANK DHOFAR | L83: BDOFOMRU
A84: 81 | B84: 3521 | C84: Omar Said Awadh Bait Said | D84: 3466.8 | E84: 0.250 | F84: =D84*E84 -> 866.7 | G84: =F84 -> 866.7 | H84: =F84-G84 -> 0 | I84: 7064553 | J84: 0396019442490023 | K84: BANK MUSCAT | L84: BMUSOMRX
A85: 82 | B85: 3522 | C85: Said Ahmed Ali Qatan | D85: 346.09 | E85: 0.250 | F85: =D85*E85 -> 86.5225 | G85: =F85 -> 86.5225 | H85: =F85-G85 -> 0 | I85: 11365191 | J85: 01010121273002 | K85: BANK DHOFAR | L85: BDOFOMRU
D86: =SUM(D4:D85) -> 135599.89 | F86: =SUM(F4:F85) -> 33899.973 | G86: =SUM(G4:G85) -> 33899.973 | H86: =SUM(H4:H85) -> -0.0002
A87: =A85-128 -> -46 | F87: =F86-46046.28 -> -12146.307
D88: =D79/30 -> 63.313333

Sheet Aug 25
A1: HAJEEF COW MILK PROCUREMENT FROM 01-Aug-2025 to 31-Aug-2025
A2: Farmer Code | B2: Farmer Name | C2: Milk Qty. (Ltr.) | D2: Avg. Rate (OMR/Ltr.) | E2: Amount (OMR) | F2: paid | G2: balance | H2: ID No. | I2: Bank Account No. | J2: Bank Name | K2: IFSC Code | L2: Phone No. | M2: Remarks
A4: 1007 | B4: AHMED ABDULLAH SAID AL RAWAS | C4: 6339.5 | D4: 0.250 | E4: =C4*D4 -> 1584.875 | G4: =E4-F4 -> 1584.875 | H4: 1515504 | I4: 0615500670380001 | J4: Bank Meethaq | K4: BMUSOMRXISL | L4: 91748840
A5: 1041 | B5: AHMED SALIM ALI BAITSAID | C5: 2628 | D5: 0.250 | E5: =C5*D5 -> 657 | G5: =E5-F5 -> 657 | H5: 6827729 | I5: 0406003463970017 | J5: BANK MUSCAT | K5: BMUSOMRX | L5: 92272935
A6: 1125 | B6: MUSALLAM SAID ALI BAITSAID | C6: 5184.2 | D6: 0.250 | E6: =C6*D6 -> 1296.05 | F6: =2.82499999999993+1293.225 -> 1296.05 | G6: =E6-F6 -> 0 | H6: 6828774 | I6: 01011456108001 | J6: BANK DHOFAR | K6: BDOFOMRU | L6: 91267555 | M6: 20-10-2025 | N6: 27-10-2025
A7: 1222 | B7: Mahad Salim Abdulaziz Alkathiri | D7: 0.250 | E7: =C7*D7 -> 0 | G7: =E7-F7 -> 0 | H7: 31221 | I7: 1006623107017 | J7: NBO | K7: NBOMOMRX
A8: 1286 | B8: SALIM AMER AHMED AL YAFAEI | C8: 2947.9 | D8: 0.250 | E8: =C8*D8 -> 736.975 | G8: =E8-F8 -> 736.975 | H8: 368056 | I8: 0406003218280013 | J8: BANK MUSCAT | K8: BMUSOMRX | L8: 99494264
A9: 1344 | B9: SAID AMERAHMED BAITSAID | C9: 3115.4 | D9: 0.250 | E9: =C9*D9 -> 778.85 | F9: =777.825+1.025 -> 778.85 | G9: =E9-F9 -> 0 | H9: 4014519 | I9: 3109370559500 | J9: OAB | K9: OMABOMRU | M9: 15-10-25 | N9: 45727
A10: 1352 | B10: MOHAMMED MASOUD AJHAM ALSH AL KATHIRI | C10: 1131.7 | D10: 0.250 | E10: =C10*D10 -> 282.925 | F10: =276.975+5.95 -> 282.925 | G10: =E10-F10 -> 0 | H10: 1627344 | I10: 0397046773470015 | J10: BANK MUSCAT | K10: BMUSOMRX | M10: 15-10-25 | N10: 45788
A11: 1354 | B11: AHMED SAID HASSAN BAITSAID | C11: 2065 | D11: 0.250 | E11: =C11*D11 -> 516.25 | G11: =E11-F11 -> 516.25 | H11: 925709 | I11: 0406018690130014 | J11: BANK MUSCAT | K11: BMUSOMRX | L11: 95187860
A12: 1357 | B12: MUSALLAM SAID ALI BAIT SAID | C12: 4830.8 | D12: 0.250 | E12: =C12*D12 -> 1207.7 | G12: =E12-F12 -> 1207.7 | H12: 1052276 | I12: 01040280323001 | J12: BANK DHOFAR | K12: BDOFOMRU | L12: 95301260
A13: 1359 | B13: MUSALLAM MUSTAHIL SAID BAIT SAID | C13: 3200 | D13: 0.250 | E13: =C13*D13 -> 800 | F13: =796.8+3.2 -> 800 | G13: =E13-F13 -> 0 | H13: 4812026 | I13: 1083517184017 | J13: NBO | K13: NBOMOMRX | L13: 96616558 | M13: 15-10-25 | N13: 45728
A14: 1367 | B14: ALI MUSALLAM AHMED BAIT SAID | C14: 1286 | D14: 0.250 | E14: =C14*D14 -> 321.5 | F14: 319.875 | G14: =E14-F14 -> 1.625 | H14: 6663593 | I14: 0406003006560016 | J14: BANK MUSCAT | K14: BMUSOMRX | L14: 92817702 | M14: 14-10-2025
A15: 1368 | B15: MOHAMMD SAID AHMED AL KATHIRI | C15: 2402.6 | D15: 0.250 | E15: =C15*D15 -> 600.65 | G15: =E15-F15 -> 600.65 | H15: 561902 | I15: 01040854387001 | J15: BANK DHOFAR | K15: BDOFOMRU | L15: 99499622
A16: 2098 | B16: Bakhit Musallam Ali Kashoob | C16: 674.6 | D16: 0.250 | E16: =C16*D16 -> 168.65 | F16: =166.075+2.575 -> 168.65 | G16: =E16-F16 -> 0 | H16: 1065899 | I16: 132857700081018 | J16: BANK MUSCAT | K16: BMUSOMRX | M16: 15-10-25 | N16: 31-12-25
A17: 3002 | B17: KHALID MUBARAK ALI ATQOON AL SHAHRI | C17: 1045.1 | D17: 0.250 | E17: =C17*D17 -> 261.275 | F17: =259.375+1.9 -> 261.275 | G17: =E17-F17 -> 0 | H17: 21220177 | I17: 0401016727580038 | J17: BANK MUSCAT | K17: BMUSOMRX | L17: 99280644 | M17: 15-10-25 | N17: 29-10-2025
A18: 3035 | B18: TARIQ SALIM SUHAIL AL BARAMI | D18: 0.250 | E18: =C18*D18 -> 0 | G18: =E18-F18 -> 0 | H18: 6725058 | I18: 01011059048001 | J18: BANK DHOFAR | K18: BDOFOMRU | L18: 99198121
A19: 3057 | B19: ALI AHMED MOHAMMED AL KATHIRI | C19: 3132.7 | D19: 0.250 | E19: =C19*D19 -> 783.175 | F19: =E19 -> 783.175 | G19: =E19-F19 -> 0 | H19: 626819 | I19: 0397003510460014 | J19: BANK MUSCAT | K19: BMUSOMRX | L19: 99298522 | M19: BT 04-12-2025
A20: 3062 | B20: ALI MAHAD SILMOUN QATAN | C20: 1887.4 | D20: 0.250 | E20: =C20*D20 -> 471.85 | G20: =E20-F20 -> 471.85 | H20: 300741 | I20: 0397004203200017 | J20: BANK MUSCAT | K20: BMUSOMRX | L20: 99008320
A21: 3080 | B21: MUSALLAM BAKHIT AWADH L BARAAMI | C21: 1286 | D21: 0.250 | E21: =C21*D21 -> 321.5 | F21: =E21 -> 321.5 | G21: =E21-F21 -> 0 | H21: 14301608 | I21: 0397003041020024 | J21: BANK MUSCAT | K21: BMUSOMRX | L21: 98122611 | M21: BT 04-12-2025
A22: 3086 | B22: MUSALLAM ALI MATOOQ TABOOK | D22: 0.250 | E22: =C22*D22 -> 0 | G22: =E22-F22 -> 0 | H22: 300033 | I22: 0397003905720015 | J22: BANK MUSCAT | K22: BMUSOMRX
A23: 3132 | B23: HASHIM SALIM ALI ATIF AL YAFAI | C23: 1286.1 | D23: 0.250 | E23: =C23*D23 -> 321.525 | G23: =E23-F23 -> 321.525 | H23: 14606296 | I23: 01013095125001 | J23: BANK DHOFAR | K23: BDOFOMRU | L23: 91493522 | M23: Update Bank account on 23-9-2025
A24: 3134 | B24: HASSAN SUHAIL MAHAD QATAN | C24: 1746.4 | D24: 0.250 | E24: =C24*D24 -> 436.6 | F24: =E24 -> 436.6 | G24: =E24-F24 -> 0 | H24: 2154413 | I24: 01010850952003 | J24: BANK DHOFAR | K24: BDOFOMRU | L24: 99493731 | M24: BT 24 - 9 -2025
A25: 3142 | B25: MOHAMMED AHMED SAAD MASHRAH AL SHAHRI | C25: 4635.4 | D25: 0.250 | E25: =C25*D25 -> 1158.85 | F25: =1154.675+4.175 -> 1158.85 | G25: =E25-F25 -> 0 | H25: 165497 | I25: 3129019324700 | J25: OAB | K25: OMABOMRU | L25: 99499872 | M25: 15-10-25 | N25: 19-11-25
A26: 3145 | B26: MOHAMMED BAKHIT MASOUD QATAN | C26: 3240.5 | D26: 0.250 | E26: =C26*D26 -> 810.125 | F26: =E26 -> 810.125 | G26: =E26-F26 -> 0 | H26: 1915745 | I26: 0404002595460014 | J26: BANK MUSCAT | K26: BMUSOMRX | L26: 99489050 | M26: 20-10-2025
A27: 3147 | B27: KHALID SAID MAHAD KASHOUB | C27: 1026.9 | D27: 0.250 | E27: =C27*D27 -> 256.725 | F27: =256.15+0.575 -> 256.725 | G27: =E27-F27 -> 0 | H27: 1662414 | I27: 3129770819700 | J27: OAB | K27: OMABOMRU | L27: 99282006 | M27: 27-10-2025 | N27: 45941
A28: 3148 | B28: MUSALLAM AHMED MAHTOUQ AL ZAWAMRI | C28: 1253.1 | D28: 0.250 | E28: =C28*D28 -> 313.275 | F28: =E28 -> 313.275 | G28: =E28-F28 -> 0 | H28: 19545736 | I28: 01011208343002 | J28: BANK DHOFAR | K28: BDOFOMRU | M28: 22-10-2025
A29: 3149 | B29: ALI SAID ALI AL ZAWAMRI | C29: 1819 | D29: 0.250 | E29: =C29*D29 -> 454.75 | F29: =E29 -> 454.75 | G29: =E29-F29 -> 0 | H29: 4941095 | I29: 1104036354300 | J29: Ahli Bank | K29: AUBOOMRU | L29: 93500864 | M29: 20-10-2025
A30: 3152 | B30: BAKHIT SALIM MAHAD QATAN | C30: 3040.4 | D30: 0.250 | E30: =C30*D30 -> 760.1 | F30: =759.55+0.55 -> 760.1 | G30: =E30-F30 -> 0 | H30: 941993 | I30: 01042574515001 | J30: BANK DHOFAR | K30: BDOFOMRU | L30: 99086500 | M30: 24.9.2025 | N30: 15-10-25
A31: 3153 | B31: ALI MAHAD SAID QATAN | C31: 2825.2 | D31: 0.250 | E31: =C31*D31 -> 706.3 | G31: =E31-F31 -> 706.3 | H31: 6989479 | I31: 0397003672070015 | J31: BANK MUSCAT | K31: BMUSOMRX | L31: 99699500
A32: 3155 | B32: SAID BAKHIT MAHAD QATAN | C32: 636 | D32: 0.250 | E32: =C32*D32 -> 159 | G32: =E32-F32 -> 159 | H32: 19188794 | I32: 0402003042750013 | J32: BANK MUSCAT | K32: BMUSOMRX | L32: 93215515
A33: 3158 | B33: AHMED OBAIDAN AHMED AL KATHIRI | C33: 3163.1 | D33: 0.250 | E33: =C33*D33 -> 790.775 | G33: =E33-F33 -> 790.775 | H33: 596869 | I33: 0401049081340015 | J33: BANK MUSCAT | K33: BMUSOMRX | L33: 99694218
A34: 3159 | B34: AHMED BAKHIT SALEM AL BARAMI | C34: 863.7 | D34: 0.250 | E34: =C34*D34 -> 215.925 | G34: =E34-F34 -> 215.925 | H34: 1297478 | I34: 0397003703480012 | J34: BANK MUSCAT | K34: BMUSOMRX | L34: 99497177
A35: 3160 | B35: NAIF MUBARAK BAKHIT AL BARAAMI | C35: 1850.3 | D35: 0.250 | E35: =C35*D35 -> 462.575 | G35: =E35-F35 -> 462.575 | H35: 2837163 | I35: 00510031862001 | J35: Bank Nizwa | K35: BNZWOMRX | L35: 99497455
A36: 3162 | B36: MOHAMMED SAID FARAJ AL KATHIRI | C36: 5826.9 | D36: 0.250 | E36: =C36*D36 -> 1456.725 | F36: =E36 -> 1456.725 | G36: =E36-F36 -> 0 | H36: 7017227 | I36: 01010940071001 | J36: BANK DHOFAR | K36: BDOFOMRU | L36: 99523400 | M36: 46002
A37: 3164 | B37: ALI MUSALLLAM HASSAN BAITSAID | C37: 2415.9 | D37: 0.250 | E37: =C37*D37 -> 603.975 | F37: =E37 -> 603.975 | G37: =E37-F37 -> 0 | H37: 7466062 | I37: 01646038607001 | J37: Maisarah | K37: BDOFOMRUMIB | L37: 91135005 | M37: 29-10-2025 | N37: 29-10-2025
A38: 3165 | B38: KHALID MOHAMMED MASAAOD AGGHRIB AL SHAHRI | C38: 367.7 | D38: 0.250 | E38: =C38*D38 -> 91.925 | G38: =E38-F38 -> 91.925 | H38: 19029628 | I38: 01011251497002 | J38: BANK DHOFAR | K38: BDOFOMRU | L38: 96055446
A39: 3169 | B39: MOHAMMED ALI SAID AL ZAWAMRY | C39: 1910.5 | D39: 0.250 | E39: =C39*D39 -> 477.625 | F39: 4.675 | G39: =E39-F39 -> 472.95 | H39: 3068756 | I39: 01012573317001 | J39: BANK DHOFAR | K39: BDOFOMRU | L39: 99691806 | M39: 45727
A40: 3171 | B40: HATAM AWADH SAID QATAN | C40: 1055.2 | D40: 0.250 | E40: =C40*D40 -> 263.8 | F40: =259.375+4.425 -> 263.8 | G40: =E40-F40 -> 0 | H40: 7239057 | I40: 3109607126500 | J40: OAB | K40: OMABOMRU | L40: 95880860 | M40: 15-10-25 | N40: 17-11-25
A41: 3172 | B41: Fatima Suleimon Salim ALBaramiyah | C41: 1062.4 | D41: 0.250 | E41: =C41*D41 -> 265.6 | G41: =E41-F41 -> 265.6 | H41: 5276984 | I41: 0439046831000027 | J41: BANK MUSCAT | K41: BMUSOMRX | L41: 99188860
A42: 3173 | B42: MUSALLAM AHMED SAAD AL BARAAMI | C42: 842 | D42: 0.250 | E42: =C42*D42 -> 210.5 | F42: =209.95+0.55 -> 210.5 | G42: =E42-F42 -> 0 | H42: 6825655 | I42: 0397004380200011 | J42: BANK MUSCAT | K42: BMUSOMRX | L42: 98957747 | M42: 15-10-25 | N42: BT-11-11-25
A43: 3174 | B43: AHMED MUSALLAM SAID QATAN | C43: 624.6 | D43: 0.250 | E43: =C43*D43 -> 156.15 | F43: =E43 -> 156.15 | G43: =E43-F43 -> 0 | H43: 7547492 | I43: 0401002379960017 | J43: BANK MUSCAT | K43: BMUSOMRX | L43: 91790502 | M43: 45728
A44: 3175 | B44: SAID AHMED NASIB AL BARAAMI | C44: 626.2 | D44: 0.250 | E44: =C44*D44 -> 156.55 | F44: =E44 -> 156.55 | G44: =E44-F44 -> 0 | H44: 7325076 | I44: 1006794849001 | J44: NBO | K44: NBOMOMRX | L44: 92890700 | M44: 27-10-2025
A45: 3176 | B45: KHAYAR ALI SAID AL BARAAMI | C45: 437.3 | D45: 0.250 | E45: =C45*D45 -> 109.325 | F45: =109.25 -> 109.25 | G45: =E45-F45 -> 0.075 | H45: 12178145 | I45: 0406015163810016 | J45: BANK MUSCAT | K45: BMUSOMRX | L45: 93348565 | M45: 46008
A46: 3179 | B46: SUHAIL MOHAMMED SUHAIL TABUK | C46: 3734 | D46: 0.250 | E46: =C46*D46 -> 933.5 | G46: =E46-F46 -> 933.5 | H46: 1870852 | I46: 3129685484720 | J46: OAB | K46: OMABOMRU | L46: 99050691
A47: 3181 | B47: TARIK MASOUD MAJADAH AL KATHIRI | C47: 1772.7 | D47: 0.250 | E47: =C47*D47 -> 443.175 | G47: =E47-F47 -> 443.175 | H47: 6116067 | I47: 3109710314700 | J47: OAB | K47: OMABOMRU | L47: 99191102
A48: 3183 | B48: Salim Musallam Ali Qatan | C48: 1121.3 | D48: 0.250 | E48: =C48*D48 -> 280.325 | F48: =277.2+3.125 -> 280.325 | G48: =E48-F48 -> 0 | H48: 4955092 | I48: 0401002697260019 | J48: BANK MUSCAT | K48: BMUSOMRX | L48: 98152775 | M48: 15-10-25 | N48: 45727
A49: 3184 | B49: ALI MOHAMMED MUSALLAM AL BARAAMI | C49: 2566.8 | D49: 0.250 | E49: =C49*D49 -> 641.7 | G49: =E49-F49 -> 641.7 | H49: 6701602 | I49: 01011004872002 | J49: BANK DHOFAR | K49: BDOFOMRU | L49: 99496161
A50: 3185 | B50: MOHAMMED ALI AHMED AMOOSH THOAR | C50: 959.1 | D50: 0.250 | E50: =C50*D50 -> 239.775 | F50: =237.95+1.825 -> 239.775 | G50: =E50-F50 -> 0 | H50: 15179209 | I50: 0405020308900019 | J50: BANK MUSCAT | K50: BMUSOMRX | L50: 94919974 | M50: 14-10-2025 | N50: 45941
A51: 3188 | B51: HASSAN BAKHIT AHMED QATAN | C51: 701.9 | D51: 0.250 | E51: =C51*D51 -> 175.475 | F51: =E51 -> 175.475 | G51: =E51-F51 -> 0 | H51: 19290729 | I51: 01041574026001 | J51: BANK DHOFAR | K51: BDOFOMRU | L51: 95606029 | M51: 27-10-2025
A52: 3189 | B52: SAID AHMED SAID AL ZAWAMRI | C52: 1143.3 | D52: 0.250 | E52: =C52*D52 -> 285.825 | F52: =E52 -> 285.825 | G52: =E52-F52 -> 0 | H52: 2802613 | I52: 0405002746200013 | J52: BANK MUSCAT | K52: BMUSOMRX | L52: 99480848 | M52: 45960
A53: 3190 | B53: TAFOOL SILMOUN SALIM AL BARAMI | C53: 478.9 | D53: 0.250 | E53: =C53*D53 -> 119.725 | G53: =E53-F53 -> 119.725 | H53: 3555896 | I53: 0402014490950017 | J53: BANK MUSCAT | K53: BMUSOMRX | L53: 92881155
A54: 3192 | B54: GHAZI SALIM MASOUD TABOOK | C54: 994.6 | D54: 0.250 | E54: =C54*D54 -> 248.65 | F54: =E54 -> 248.65 | G54: =E54-F54 -> 0 | H54: 5271448 | I54: 0401002602010018 | J54: BANK MUSCAT | K54: BMUSOMRX | L54: 99489918 | M54: 27-10-2025
A55: 3195 | B55: MUSTAHIL SAID MUSTAHIL AL BARAAMI | C55: 646.1 | D55: 0.250 | E55: =C55*D55 -> 161.525 | G55: =E55-F55 -> 161.525 | H55: 675849 | I55: 01011097969001 | J55: BANK DHOFAR | K55: BDOFOMRU | L55: 99483811
A56: 3196 | B56: JASIM MOHAMMED SAID ALI AFIR AL ZAWAMARI | C56: 620.5 | D56: 0.250 | E56: =C56*D56 -> 155.125 | G56: =E56-F56 -> 155.125 | H56: 21080217 | I56: 0401007927380037 | J56: BANK MUSCAT | K56: BMUSOMRX | L56: 95490778
A57: 3197 | B57: MOHSIN SAID MOHAMED BA AWAIN | C57: 1859.1 | D57: 0.250 | E57: =C57*D57 -> 464.775 | G57: =E57-F57 -> 464.775 | H57: 6479515 | I57: 0406003220920038 | J57: BANK MUSCAT | K57: BMUSOMRX | L57: 92349032
A58: 3198 | B58: ADIL SAID AHMED AL ZAWAMRI | C58: 621.1 | D58: 0.250 | E58: =C58*D58 -> 155.275 | G58: =E58-F58 -> 155.275 | H58: 6360793 | I58: 00510047506001 | J58: Bank Nizwa | K58: BNZWOMRX | L58: 99336200
A59: 3310 | B59: AHMED SUHAIL SAID AL BARAMI | C59: 1286.5 | D59: 0.250 | E59: =C59*D59 -> 321.625 | F59: =E59 -> 321.625 | G59: =E59-F59 -> 0 | H59: 1007615 | I59: 0397003855850017 | J59: BANK MUSCAT | K59: BMUSOMRX | L59: 99056614 | M59: BT-11-12-2025
A60: 3324 | B60: BAKHIT AWADH BAKHIT AL BARAAMI | C60: 1279.3 | D60: 0.250 | E60: =C60*D60 -> 319.825 | F60: =E60 -> 319.825 | G60: =E60-F60 -> 0 | H60: 207402 | I60: 0401057742590016 | J60: BANK MUSCAT | K60: BMUSOMRX | L60: 99487533 | M60: BT 04-12-2025
A61: 3330 | B61: Salim Ahmed Aubad Al kathiri | C61: 1978.3 | D61: 0.250 | E61: =C61*D61 -> 494.575 | G61: =E61-F61 -> 494.575 | H61: 6375079 | I61: 0397062111930011 | J61: Bank Muscat | K61: BMUSOMRX
A62: 3333 | B62: Mahad Salim Zaed Bait Said | C62: 1198.5 | D62: 0.250 | E62: =C62*D62 -> 299.625 | G62: =E62-F62 -> 299.625 | H62: 757601 | I62: 1023113274001 | J62: NBO | K62: NBOMOMRX
A63: 3339 | B63: Khalid Ahmed Salim Amer Jid Almahri | C63: 474.1 | D63: 0.250 | E63: =C63*D63 -> 118.525 | F63: =116.4+2.125 -> 118.525 | G63: =E63-F63 -> 0 | H63: 12415718 | I63: 0401050718800013 | J63: BANK MUSCAT | K63: BMUSOMRX | M63: 15-10-25 | N63: 29-10-2025
A64: 3341 | B64: Mahad Ahmed Alkathiri | C64: 560.5 | D64: 0.250 | E64: =C64*D64 -> 140.125 | F64: =E64 -> 140.125 | G64: =E64-F64 -> 0 | H64: 702161 | I64: 3109593036500 | J64: OAB | K64: OMABOMRU | L64: 99290644 | M64: BT-27-10-2025
A65: 3500 | B65: Salim Mohammed Ahmed Al Kathiri | D65: 0.250 | E65: =C65*D65 -> 0 | G65: =E65-F65 -> 0 | H65: 13525845 | I65: 10600259604017 | J65: NBO | K65: NBOMOMRX | L65: 93985671
A66: 3501 | B66: Said Masoud Ahmed Al kathiri | C66: 1935.2 | D66: 0.250 | E66: =C66*D66 -> 483.8 | G66: =E66-F66 -> 483.8 | H66: 13525794 | I66: 0402003356710024 | J66: BANK MUSCAT | K66: BMUSOMRX | L66: 92868004
A67: 3502 | B67: Ahmed Bakhit Ahmed Al Kathiri | C67: 1329.6 | D67: 0.250 | E67: =C67*D67 -> 332.4 | G67: =E67-F67 -> 332.4 | H67: 22522336 | I67: 01011021065002 | J67: BANK DHOFAR | K67: BDOFOMRU
A68: 3503 | B68: Imad Bakhit Salim Bakhit Qatan | C68: 647.1 | D68: 0.250 | E68: =C68*D68 -> 161.775 | G68: =E68-F68 -> 161.775 | H68: 9212492 | I68: 0401028325700011 | J68: BANK MUSCAT | K68: BMUSOMRX | L68: 98080144
A69: 3504 | B69: Ali Salem Amer Al Kathiri | D69: 0.250 | E69: =C69*D69 -> 0 | G69: =E69-F69 -> 0 | H69: 939641 | I69: 0406003375130017 | J69: BANK MUSCAT | K69: BMUSOMRX | L69: 99588609
A70: 3506 | B70: Ahmed Masoud Salim Al Kathiri | C70: 474.6 | D70: 0.250 | E70: =C70*D70 -> 118.65 | F70: =E70 -> 118.65 | G70: =E70-F70 -> 0 | H70: 13307752 | I70: 0397048001530015 | J70: BANK MUSCAT | K70: BMUSOMRX | L70: 99294425 | M70: 45941
A71: 3507 | B71: Bakhit Suhail Ahmed Qatan | C71: 1286.9 | D71: 0.250 | E71: =C71*D71 -> 321.725 | G71: =E71-F71 -> 321.725 | H71: 1184669 | I71: 01040281423001 | J71: BANK DHOFAR | K71: BDOFOMRU | L71: 99291928
A72: 3508 | B72: Said Ali Said Al Zawamri | C72: 646.7 | D72: 0.250 | E72: =C72*D72 -> 161.675 | G72: =E72-F72 -> 161.675 | H72: 2567166 | I72: 0439004225500028 | J72: BANK MUSCAT | K72: BMUSOMRX | L72: 92570156
A73: 3509 | B73: Asama Mohammed Ahmed Masharah Al Shahri | C73: 569.8 | D73: 0.250 | E73: =C73*D73 -> 142.45 | G73: =E73-F73 -> 142.45 | H73: 22760088 | I73: 3129152535700 | J73: OAB | K73: OMABOMRU | L73: 91476443
A74: 3510 | B74: Amer Ali Ahmed Al kathiri | C74: 1253.7 | D74: 0.250 | E74: =C74*D74 -> 313.425 | G74: =E74-F74 -> 313.425 | H74: 6920351 | I74: 0397003252950036 | J74: BANK MUSCAT | K74: BMUSOMRX | L74: 98933077
A75: 3511 | B75: Said Ali Said Qatan | C75: 679.3 | D75: 0.250 | E75: =C75*D75 -> 169.825 | F75: =167.05+2.775 -> 169.825 | G75: =E75-F75 -> 0 | H75: 2640016 | I75: 0501036199001 | J75: Ahli Islamic | K75: AUBOOMRUALH | L75: 92953388 | M75: 15-10-25 | N75: 45727
A76: 3512 | B76: Ahmed Abdul Rahim Ali Al Kathiri | D76: 0.250 | E76: =C76*D76 -> 0 | G76: =E76-F76 -> 0 | H76: 5514631 | I76: 01041149485001 | J76: BANK DHOFAR | K76: BDOFOMRU
A77: 3513 | B77: Khair Salim Faraj Al Kathiri | C77: 2575 | D77: 0.250 | E77: =C77*D77 -> 643.75 | F77: =E77 -> 643.75 | G77: =E77-F77 -> 0 | H77: 7047376 | I77: 01013042263001 | J77: BANK DHOFAR | K77: BDOFOMRU | L77: 90106022 | M77: 46002
A78: 3514 | B78: Said Salim Faraj Al Kathiri | C78: 1255.9 | D78: 0.250 | E78: =C78*D78 -> 313.975 | F78: =2.64999999999998+311.325 -> 313.975 | G78: =E78-F78 -> 0 | H78: 440083 | I78: 0397003539170015 | J78: Bank Muscat | K78: BMUSOMRX | L78: 92363355 | M78: 19-11-25 | N78: 45700
A79: 3515 | B79: Ali Ajaham Ali Bait said | C79: 1749.3 | D79: 0.250 | E79: =C79*D79 -> 437.325 | F79: 433.45 | G79: =E79-F79 -> 3.875 | H79: 6645198 | I79: 01011180247001 | J79: BANK DHOFAR | K79: BDOFOMRU | L79: 94411217 | M79: 15-10-25
A80: 3516 | B80: Musallam Hassan Ali Bait Muhammed Bin Ahmed | C80: 1842.2 | D80: 0.250 | E80: =C80*D80 -> 460.55 | F80: =E80 -> 460.55 | G80: =E80-F80 -> 0 | H80: 1165877 | I80: 01010127958001 | J80: BANK DHOFAR | K80: BDOFOMRU | M80: BT-16-11-25
A81: 3517 | B81: Mohammed Salim Faraj Al Kathiri | C81: 1280.3 | D81: 0.250 | E81: =C81*D81 -> 320.075 | F81: =2.12499999999999+317.95 -> 320.075 | G81: =E81-F81 -> 0 | H81: 7047081 | I81: 01010401370002 | J81: BANK DHOFAR | K81: BDOFOMRU | M81: 14-10-2025 | N81: 45727
A82: 3518 | B82: Ali Ahmed Ali Bait Said | C82: 1069.1 | D82: 0.250 | E82: =C82*D82 -> 267.275 | F82: =E82 -> 267.275 | G82: =E82-F82 -> 0 | H82: 20386956 | I82: 0396064567750014 | J82: BANK MUSCAT | K82: BMUSOMRX | M82: 20-10-2025
A83: 3519 | B83: Masoud Salim Faraj Al Kathiri | C83: 637.5 | D83: 0.250 | E83: =C83*D83 -> 159.375 | F83: =1.05+158.325 -> 159.375 | G83: =E83-F83 -> 0 | H83: 7047221 | I83: 01011028414003 | J83: BANK DHOFAR | K83: BDOFOMRU | M83: 14-10-2025 | N83: 45727
A84: 3520 | B84: Musallam Mahad Suhail Al Barami | C84: 930.8 | D84: 0.250 | E84: =C84*D84 -> 232.7 | G84: =E84-F84 -> 232.7 | H84: 5665362 | I84: 01011072899001 | J84: BANK DHOFAR | K84: BDOFOMRU
A85: 3521 | B85: Omar Said Awadh Bait Said | C85: 3669.6 | D85: 0.250 | E85: =C85*D85 -> 917.4 | G85: =E85-F85 -> 917.4 | H85: 7064553 | I85: 0396019442490023 | J85: BANK MUSCAT | K85: BMUSOMRX
A86: 3522 | B86: Said Ahmed Ali Qatan | C86: 364.2 | D86: 0.250 | E86: =C86*D86 -> 91.05 | G86: =E86-F86 -> 91.05 | H86: 11365191 | I86: 01010121273002 | J86: BANK DHOFAR | K86: BDOFOMRU
G87: =E87-F87 -> 0
C88: =SUM(C4:C87) -> 133905.1 | E88: =SUM(E4:E87) -> 33476.275 | F88: =SUM(F4:F87) -> 17181.425 | G88: =SUM(G4:G87) -> 16294.85

Sheet SEP-25
A1: HAJEEF COW MILK PROCUREMENT FROM 01-Sep-2025 to 30-Sep-2025
A2: Farmer Code | B2: Farmer Name | C2: Milk Qty. (Ltr.) | D2: Avg. Rate (OMR/Ltr.) | E2: Amount (OMR) | F2: Paid | G2: Balance | H2: ID No. | I2: Bank Account No. | J2: Bank Name | K2: IFSC Code | L2: Phone No. | M2: Remarks
A4: 1007 | B4: AHMED ABDULLAH SAID AL RAWAS | C4: 6256 | D4: 0.250 | E4: =C4*D4 -> 1564 | G4: =E4-F4 -> 1564 | H4: 1515504 | I4: 0615500670380001 | J4: Bank Meethaq | K4: BMUSOMRXISL | L4: 91748840
A5: 1041 | B5: AHMED SALIM ALI BAITSAID | C5: 1848 | D5: 0.250 | E5: =C5*D5 -> 462 | G5: =E5-F5 -> 462 | H5: 6827729 | I5: 0406003463970017 | J5: BANK MUSCAT | K5: BMUSOMRX | L5: 92272935
A6: 1125 | B6: MUSALLAM SAID ALI BAITSAID | C6: 4605.9 | D6: 0.250 | E6: =C6*D6 -> 1151.475 | F6: =3.52500000000001+1147.95 -> 1151.475 | G6: =E6-F6 -> 0 | H6: 6828774 | I6: 01011456108001 | J6: BANK DHOFAR | K6: BDOFOMRU | L6: 91267555 | M6: 27-10-2025 | N6: 45941
A7: 1222 | B7: Mahad Salim Abdulaziz Alkathiri | D7: 0.250 | E7: =C7*D7 -> 0 | G7: =E7-F7 -> 0 | H7: 31221 | I7: 1006623107017 | J7: NBO | K7: NBOMOMRX
A8: 1286 | B8: SALIM AMER AHMED AL YAFAEI | C8: 2947.9 | D8: 0.250 | E8: =C8*D8 -> 736.975 | G8: =E8-F8 -> 736.975 | H8: 368056 | I8: 0406003218280013 | J8: BANK MUSCAT | K8: BMUSOMRX | L8: 99494264
A9: 1344 | B9: SAID AMERAHMED BAITSAID | C9: 3192.1 | D9: 0.250 | E9: =C9*D9 -> 798.025 | F9: =796.975+1.05 -> 798.025 | G9: =E9-F9 -> 0 | H9: 4014519 | I9: 3109370559500 | J9: OAB | K9: OMABOMRU | M9: 45727 | N9: 17-12-25
A10: 1352 | B10: MOHAMMED MASOUD AJHAM ALSH AL KATHIRI | C10: 1217.7 | D10: 0.250 | E10: =C10*D10 -> 304.425 | F10: =302.8+1.625 -> 304.425 | G10: =E10-F10 -> 0 | H10: 1627344 | I10: 0397046773470015 | J10: BANK MUSCAT | K10: BMUSOMRX | M10: 45788 | N10: 46002
A11: 1354 | B11: AHMED SAID HASSAN BAITSAID | C11: 1705.2 | D11: 0.250 | E11: =C11*D11 -> 426.3 | G11: =E11-F11 -> 426.3 | H11: 925709 | I11: 0406018690130014 | J11: BANK MUSCAT | K11: BMUSOMRX | L11: 95187860
A12: 1357 | B12: MUSALLAM SAID ALI BAIT SAID | C12: 3989.3 | D12: 0.250 | E12: =C12*D12 -> 997.325 | G12: =E12-F12 -> 997.325 | H12: 1052276 | I12: 01040280323001 | J12: BANK DHOFAR | K12: BDOFOMRU | L12: 95301260
A13: 1359 | B13: MUSALLAM MUSTAHIL SAID BAIT SAID | C13: 2256 | D13: 0.250 | E13: =C13*D13 -> 564 | F13: =E13 -> 564 | G13: =E13-F13 -> 0 | H13: 4812026 | I13: 1083517184017 | J13: NBO | K13: NBOMOMRX | L13: 96616558 | M13: 45728
A14: 1367 | B14: ALI MUSALLAM AHMED BAIT SAID | C14: 1601.9 | D14: 0.250 | E14: =C14*D14 -> 400.475 | G14: =E14-F14 -> 400.475 | H14: 6663593 | I14: 0406003006560016 | J14: BANK MUSCAT | K14: BMUSOMRX | L14: 92817702
A15: 1368 | B15: MOHAMMD SAID AHMED AL KATHIRI | C15: 3056 | D15: 0.250 | E15: =C15*D15 -> 764 | G15: =E15-F15 -> 764 | H15: 561902 | I15: 01040854387001 | J15: BANK DHOFAR | K15: BDOFOMRU | L15: 99499622
A16: 2098 | B16: Bakhit Musallam Ali Kashoob | C16: 603.1 | D16: 0.250 | E16: =C16*D16 -> 150.775 | F16: =E16 -> 150.775 | G16: =E16-F16 -> 0 | H16: 1065899 | I16: 132857700081018 | J16: BANK MUSCAT | K16: BMUSOMRX | M16: 31-12-25
A17: 3002 | B17: KHALID MUBARAK ALI ATQOON AL SHAHRI | C17: 1073.9 | D17: 0.250 | E17: =C17*D17 -> 268.475 | F17: =265.4+3.075 -> 268.475 | G17: =E17-F17 -> 0 | H17: 21220177 | I17: 0401016727580038 | J17: BANK MUSCAT | K17: BMUSOMRX | L17: 99280644 | M17: 29-10-2025 | N17: 14-12-25
A18: 3035 | B18: TARIQ SALIM SUHAIL AL BARAMI | D18: 0.250 | E18: =C18*D18 -> 0 | G18: =E18-F18 -> 0 | H18: 6725058 | I18: 01011059048001 | J18: BANK DHOFAR | K18: BDOFOMRU | L18: 99198121
A19: 3057 | B19: ALI AHMED MOHAMMED AL KATHIRI | C19: 2721.8 | D19: 0.250 | E19: =C19*D19 -> 680.45 | F19: =0.275 -> 0.275 | G19: =E19-F19 -> 680.175 | H19: 626819 | I19: 0397003510460014 | J19: BANK MUSCAT | K19: BMUSOMRX | L19: 99298522 | M19: BT
A20: 3062 | B20: ALI MAHAD SILMOUN QATAN | C20: 2117.6 | D20: 0.250 | E20: =C20*D20 -> 529.4 | G20: =E20-F20 -> 529.4 | H20: 300741 | I20: 0397004203200017 | J20: BANK MUSCAT | K20: BMUSOMRX | L20: 99008320
A21: 3080 | B21: MUSALLAM BAKHIT AWADH L BARAAMI | C21: 1554.7 | D21: 0.250 | E21: =C21*D21 -> 388.675 | G21: =E21-F21 -> 388.675 | H21: 14301608 | I21: 0397003041020024 | J21: BANK MUSCAT | K21: BMUSOMRX | L21: 98122611
A22: 3086 | B22: MUSALLAM ALI MATOOQ TABOOK | C22: 245.8 | D22: 0.250 | E22: =C22*D22 -> 61.45 | F22: =58.175+3.275 -> 61.45 | G22: =E22-F22 -> 0 | H22: 300033 | I22: 0397003905720015 | J22: BANK MUSCAT | K22: BMUSOMRX | M22: 27-10-2025 | N22: 45759
A23: 3132 | B23: HASHIM SALIM ALI ATIF AL YAFAI | C23: 1608.5 | D23: 0.250 | E23: =C23*D23 -> 402.125 | G23: =E23-F23 -> 402.125 | H23: 14606296 | I23: 0401024314310011 | J23: BANK MUSCAT | K23: BMUSOMRX | L23: 91493522
A24: 3134 | B24: HASSAN SUHAIL MAHAD QATAN | C24: 1812.8 | D24: 0.250 | E24: =C24*D24 -> 453.2 | G24: =E24-F24 -> 453.2 | H24: 2154413 | I24: 01010850952003 | J24: BANK DHOFAR | K24: BDOFOMRU | L24: 99493731
A25: 3142 | B25: MOHAMMED AHMED SAAD MASHRAH AL SHAHRI | C25: 4297.7 | D25: 0.250 | E25: =C25*D25 -> 1074.425 | F25: =537.325+537.1 -> 1074.425 | G25: =E25-F25 -> 0 | H25: 165497 | I25: 3129019324700 | J25: OAB | K25: OMABOMRU | L25: 99499872 | M25: 19-11-25
A26: 3145 | B26: MOHAMMED BAKHIT MASOUD QATAN | C26: 2999.7 | D26: 0.250 | E26: =C26*D26 -> 749.925 | F26: =1.7749999999999+747.6+0.55 -> 749.925 | G26: =E26-F26 -> 0 | H26: 1915745 | I26: 0404002595460014 | J26: BANK MUSCAT | K26: BMUSOMRX | L26: 99489050 | M26: 20-10-2025 | N26: 45758 | P26: 14-12-25
A27: 3147 | B27: KHALID SAID MAHAD KASHOUB | C27: 948 | D27: 0.250 | E27: =C27*D27 -> 237 | F27: =236.925+0.075 -> 237 | G27: =E27-F27 -> 0 | H27: 1662414 | I27: 3129770819700 | J27: OAB | K27: OMABOMRU | L27: 99282006 | M27: 45941 | N27: 14-12-25
A28: 3148 | B28: MUSALLAM AHMED MAHTOUQ AL ZAWAMRI | C28: 1198.3 | D28: 0.250 | E28: =C28*D28 -> 299.575 | F28: =299.375+0.2 -> 299.575 | G28: =E28-F28 -> 0 | H28: 19545736 | I28: 01011208343002 | J28: BANK DHOFAR | K28: BDOFOMRU | M28: 22-10-2025 | N28: 45973
A29: 3149 | B29: ALI SAID ALI AL ZAWAMRI | C29: 1878.7 | D29: 0.250 | E29: =C29*D29 -> 469.675 | F29: =3.44999999999995+465.5+0.725 -> 469.675 | G29: =E29-F29 -> 0 | H29: 4941095 | I29: 1104036354300 | J29: Ahli Bank | K29: AUBOOMRU | L29: 93500864 | M29: 20-10-2025 | N29: 45788 | O29: 19-11-25
A30: 3150 | B30: Awad Ahmed Said Alzwamri | C30: 154.2 | D30: 0.250 | E30: =C30*D30 -> 38.55 | F30: =34.65+3.9 -> 38.55 | G30: =E30-F30 -> 0 | H30: 18940347 | I30: 0401017288790038 | J30: BANK MUSCAT | K30: BMUSOMRX | L30: 98905289 | M30: 22-10-2025 | N30: 17-11-25
A31: 3152 | B31: BAKHIT SALIM MAHAD QATAN | C31: 3162.4 | D31: 0.250 | E31: =C31*D31 -> 790.6 | F31: =786.5+4.1 -> 790.6 | G31: =E31-F31 -> 0 | H31: 941993 | I31: 01042574515001 | J31: BANK DHOFAR | K31: BDOFOMRU | L31: 99086500 | M31: 15-10-25 | N31: 45727
A32: 3153 | B32: ALI MAHAD SAID QATAN | C32: 2918.5 | D32: 0.250 | E32: =C32*D32 -> 729.625 | G32: =E32-F32 -> 729.625 | H32: 6989479 | I32: 0397003672070015 | J32: BANK MUSCAT | K32: BMUSOMRX | L32: 99699500
A33: 3155 | B33: SAID BAKHIT MAHAD QATAN | C33: 596 | D33: 0.250 | E33: =C33*D33 -> 149 | G33: =E33-F33 -> 149 | H33: 19188794 | I33: 0402003042750013 | J33: BANK MUSCAT | K33: BMUSOMRX | L33: 93215515
A34: 3158 | B34: AHMED OBAIDAN AHMED AL KATHIRI | C34: 3136.2 | D34: 0.250 | E34: =C34*D34 -> 784.05 | G34: =E34-F34 -> 784.05 | H34: 596869 | I34: 0401049081340015 | J34: BANK MUSCAT | K34: BMUSOMRX | L34: 99694218
A35: 3159 | B35: AHMED BAKHIT SALEM AL BARAMI | C35: 653.6 | D35: 0.250 | E35: =C35*D35 -> 163.4 | G35: =E35-F35 -> 163.4 | H35: 1297478 | I35: 0397003703480012 | J35: BANK MUSCAT | K35: BMUSOMRX | L35: 99497177
A36: 3160 | B36: NAIF MUBARAK BAKHIT AL BARAAMI | C36: 2141.6 | D36: 0.250 | E36: =C36*D36 -> 535.4 | G36: =E36-F36 -> 535.4 | H36: 2837163 | I36: 00510031862001 | J36: Bank Nizwa | K36: BNZWOMRX | L36: 99497455
A37: 3162 | B37: MOHAMMED SAID FARAJ AL KATHIRI | C37: 5494.7 | D37: 0.250 | E37: =C37*D37 -> 1373.675 | G37: =E37-F37 -> 1373.675 | H37: 7017227 | I37: 01010940071001 | J37: BANK DHOFAR | K37: BDOFOMRU | L37: 99523400
A38: 3164 | B38: ALI MUSALLLAM HASSAN BAITSAID | C38: 2256.4 | D38: 0.250 | E38: =C38*D38 -> 564.1 | F38: =2.84999999999994+561.25 -> 564.1 | G38: =E38-F38 -> 0 | H38: 7466062 | I38: 01646038607001 | J38: Maisarah | K38: BDOFOMRUMIB | L38: 91135005 | M38: 29-10-2025 | N38: 46002
A39: 3165 | B39: KHALID MOHAMMED MASAAOD AGGHRIB AL SHAHRI | C39: 332.1 | D39: 0.250 | E39: =C39*D39 -> 83.025 | G39: =E39-F39 -> 83.025 | H39: 19029628 | I39: 01011251497002 | J39: BANK DHOFAR | K39: BDOFOMRU | L39: 96055446
A40: 3169 | B40: MOHAMMED ALI SAID AL ZAWAMRY | C40: 2014.7 | D40: 0.250 | E40: =C40*D40 -> 503.675 | G40: =E40-F40 -> 503.675 | H40: 3068756 | I40: 01012573317001 | J40: BANK DHOFAR | K40: BDOFOMRU | L40: 99691806
A41: 3171 | B41: HATAM AWADH SAID QATAN | C41: 1021.3 | D41: 0.250 | E41: =C41*D41 -> 255.325 | F41: =E41 -> 255.325 | G41: =E41-F41 -> 0 | H41: 7239057 | I41: 3109607126500 | J41: OAB | K41: OMABOMRU | L41: 95880860 | M41: 17-11-25
A42: 3172 | B42: Fatima Suleimon Salim ALBaramiyah | C42: 1066.7 | D42: 0.250 | E42: =C42*D42 -> 266.675 | G42: =E42-F42 -> 266.675 | H42: 5276984 | I42: 0439046831000027 | J42: BANK MUSCAT | K42: BMUSOMRX | L42: 99188860
A43: 3173 | B43: MUSALLAM AHMED SAAD AL BARAAMI | C43: 801.6 | D43: 0.250 | E43: =C43*D43 -> 200.4 | F43: =E43 -> 200.4 | G43: =E43-F43 -> 0 | H43: 6825655 | I43: 0397004380200011 | J43: BANK MUSCAT | K43: BMUSOMRX | L43: 98957747 | M43: BT-11-11-25
A44: 3174 | B44: AHMED MUSALLAM SAID QATAN | C44: 781.8 | D44: 0.250 | E44: =C44*D44 -> 195.45 | F44: =193.05+1.925 -> 194.975 | G44: =E44-F44 -> 0.475 | H44: 7547492 | I44: 0401002379960017 | J44: BANK MUSCAT | K44: BMUSOMRX | L44: 91790502 | M44: 45700 | N44: 45728
A45: 3175 | B45: SAID AHMED NASIB AL BARAAMI | C45: 837.6 | D45: 0.250 | E45: =C45*D45 -> 209.4 | F45: =207.75+1.65 -> 209.4 | G45: =E45-F45 -> 0 | H45: 7325076 | I45: 1006794849001 | J45: NBO | K45: NBOMOMRX | L45: 92890700 | M45: 27-10-2025 | N45: 15-12-25
A46: 3176 | B46: KHAYAR ALI SAID AL BARAAMI | C46: 501.9 | D46: 0.250 | E46: =C46*D46 -> 125.475 | G46: =E46-F46 -> 125.475 | H46: 12178145 | I46: 0406015163810016 | J46: BANK MUSCAT | K46: BMUSOMRX | L46: 93348565
A47: 3179 | B47: SUHAIL MOHAMMED SUHAIL TABUK | C47: 3028.2 | D47: 0.250 | E47: =C47*D47 -> 757.05 | G47: =E47-F47 -> 757.05 | H47: 1870852 | I47: 3129685484720 | J47: OAB | K47: OMABOMRU | L47: 99050691
A48: 3181 | B48: TARIK MASOUD MAJADAH AL KATHIRI | C48: 2209.7 | D48: 0.250 | E48: =C48*D48 -> 552.425 | G48: =E48-F48 -> 552.425 | H48: 6116067 | I48: 3109710314700 | J48: OAB | K48: OMABOMRU | L48: 99191102
A49: 3183 | B49: Salim Musallam Ali Qatan | C49: 1027.8 | D49: 0.250 | E49: =C49*D49 -> 256.95 | F49: =253.375+3.575 -> 256.95 | G49: =E49-F49 -> 0 | H49: 4955092 | I49: 0401002697260019 | J49: BANK MUSCAT | K49: BMUSOMRX | L49: 98152775 | M49: 45727 | N49: 14-12-25
A50: 3184 | B50: ALI MOHAMMED MUSALLAM AL BARAAMI | C50: 2404.3 | D50: 0.250 | E50: =C50*D50 -> 601.075 | G50: =E50-F50 -> 601.075 | H50: 6701602 | I50: 01011004872002 | J50: BANK DHOFAR | K50: BDOFOMRU | L50: 99496161
A51: 3185 | B51: MOHAMMED ALI AHMED AMOOSH THOAR | C51: 944 | D51: 0.250 | E51: =C51*D51 -> 236 | F51: =235.675+0.325 -> 236 | G51: =E51-F51 -> 0 | H51: 15179209 | I51: 0405020308900019 | J51: BANK MUSCAT | K51: BMUSOMRX | L51: 94919974 | M51: 45941 | N51: 14-12-25
A52: 3188 | B52: HASSAN BAKHIT AHMED QATAN | C52: 1431.8 | D52: 0.250 | E52: =C52*D52 -> 357.95 | F52: =356.75+1.2 -> 357.95 | G52: =E52-F52 -> 0 | H52: 19290729 | I52: 01041574026001 | J52: BANK DHOFAR | K52: BDOFOMRU | L52: 95606029 | M52: 27-10-2025 | N52: 24-12-25
A53: 3189 | B53: SAID AHMED SAID AL ZAWAMRI | C53: 921.8 | D53: 0.250 | E53: =C53*D53 -> 230.45 | F53: =E53 -> 230.45 | G53: =E53-F53 -> 0 | H53: 2802613 | I53: 0405002746200013 | J53: BANK MUSCAT | K53: BMUSOMRX | L53: 99480848 | M53: BT 30-10-2025
A54: 3190 | B54: TAFOOL SILMOUN SALIM AL BARAMI | C54: 528.5 | D54: 0.250 | E54: =C54*D54 -> 132.125 | G54: =E54-F54 -> 132.125 | H54: 3555896 | I54: 0402014490950017 | J54: BANK MUSCAT | K54: BMUSOMRX | L54: 92881155
A55: 3192 | B55: GHAZI SALIM MASOUD TABOOK | C55: 535 | D55: 0.250 | E55: =C55*D55 -> 133.75 | F55: =131.05+2.7 -> 133.75 | G55: =E55-F55 -> 0 | H55: 5271448 | I55: 0401002602010018 | J55: BANK MUSCAT | K55: BMUSOMRX | L55: 99489918 | M55: 27-10-2025 | N55: 15-12-25
A56: 3195 | B56: MUSTAHIL SAID MUSTAHIL AL BARAAMI | C56: 590.8 | D56: 0.250 | E56: =C56*D56 -> 147.7 | G56: =E56-F56 -> 147.7 | H56: 675849 | I56: 01011097969001 | J56: BANK DHOFAR | K56: BDOFOMRU | L56: 99483811
A57: 3196 | B57: JASIM MOHAMMED SAID ALI AFIR AL ZAWAMARI | C57: 588.2 | D57: 0.250 | E57: =C57*D57 -> 147.05 | G57: =E57-F57 -> 147.05 | H57: 21080217 | I57: 0401007927380037 | J57: BANK MUSCAT | K57: BMUSOMRX | L57: 95490778
A58: 3197 | B58: MOHSIN SAID MOHAMED BA AWAIN | C58: 1759.7 | D58: 0.250 | E58: =C58*D58 -> 439.925 | G58: =E58-F58 -> 439.925 | H58: 6479515 | I58: 0406003220920038 | J58: BANK MUSCAT | K58: BMUSOMRX | L58: 92349032
A59: 3198 | B59: ADIL SAID AHMED AL ZAWAMRI | C59: 570.9 | D59: 0.250 | E59: =C59*D59 -> 142.725 | G59: =E59-F59 -> 142.725 | H59: 6360793 | I59: 00510047506001 | J59: Bank Nizwa | K59: BNZWOMRX | L59: 99336200
A60: 3310 | B60: AHMED SUHAIL SAID AL BARAMI | C60: 1213.6 | D60: 0.250 | E60: =C60*D60 -> 303.4 | G60: =E60-F60 -> 303.4 | H60: 1007615 | I60: 0397003855850017 | J60: BANK MUSCAT | K60: BMUSOMRX | L60: 99056614
A61: 3324 | B61: BAKHIT AWADH BAKHIT AL BARAAMI | C61: 1627 | D61: 0.250 | E61: =C61*D61 -> 406.75 | G61: =E61-F61 -> 406.75 | H61: 207402 | I61: 0401057742590016 | J61: BANK MUSCAT | K61: BMUSOMRX | L61: 99487533
A62: 3330 | B62: Salim Ahmed Aubad Al kathiri | C62: 2128 | D62: 0.250 | E62: =C62*D62 -> 532 | G62: =E62-F62 -> 532 | H62: 6375079 | I62: 0397062111930011 | J62: Bank Muscat | K62: BMUSOMRX
A63: 3333 | B63: Mahad Salim Zaed Bait Said | C63: 1161.3 | D63: 0.250 | E63: =C63*D63 -> 290.325 | G63: =E63-F63 -> 290.325 | H63: 757601 | I63: 1023113274001 | J63: NBO | K63: NBOMOMRX
A64: 3339 | B64: Khalid Ahmed Salim Amer Jid Almahri | C64: 730.6 | D64: 0.250 | E64: =C64*D64 -> 182.65 | F64: =180.375+2.275 -> 182.65 | G64: =E64-F64 -> 0 | H64: 12415718 | I64: 0401050718800013 | J64: BANK MUSCAT | K64: BMUSOMRX | M64: 29-10-2025 | N64: 14-12-25
A65: 3341 | B65: Mahad Ahmed Alkathiri | C65: 441.4 | D65: 0.250 | E65: =C65*D65 -> 110.35 | F65: =E65 -> 110.35 | G65: =E65-F65 -> 0 | H65: 702161 | I65: 3109593036500 | J65: OAB | K65: OMABOMRU | L65: 99290644 | M65: BT-27-10-2025
A66: 3500 | B66: Salim Mohammed Ahmed Al Kathiri | D66: 0.250 | E66: =C66*D66 -> 0 | G66: =E66-F66 -> 0 | H66: 13525845 | I66: 10600259604017 | J66: NBO | K66: NBOMOMRX | L66: 93985671
A67: 3501 | B67: Said Masoud Ahmed Al kathiri | C67: 1352.2 | D67: 0.250 | E67: =C67*D67 -> 338.05 | G67: =E67-F67 -> 338.05 | H67: 13525794 | I67: 0402003356710024 | J67: BANK MUSCAT | K67: BMUSOMRX | L67: 92868004
A68: 3502 | B68: Ahmed Bakhit Ahmed Al Kathiri | C68: 1616.7 | D68: 0.250 | E68: =C68*D68 -> 404.175 | G68: =E68-F68 -> 404.175 | H68: 22522336 | I68: 01011021065002 | J68: BANK DHOFAR | K68: BDOFOMRU
A69: 3503 | B69: Imad Bakhit Salim Bakhit Qatan | C69: 601.7 | D69: 0.250 | E69: =C69*D69 -> 150.425 | G69: =E69-F69 -> 150.425 | H69: 9212492 | I69: 0401028325700011 | J69: BANK MUSCAT | K69: BMUSOMRX | L69: 98080144
A70: 3504 | B70: Ali Salem Amer Al Kathiri | D70: 0.250 | E70: =C70*D70 -> 0 | G70: =E70-F70 -> 0 | H70: 939641 | I70: 0406003375130017 | J70: BANK MUSCAT | K70: BMUSOMRX | L70: 99588609
A71: 3506 | B71: Ahmed Masoud Salim Al Kathiri | C71: 531.1 | D71: 0.250 | E71: =C71*D71 -> 132.775 | F71: =E71 -> 132.775 | G71: =E71-F71 -> 0 | H71: 13307752 | I71: 0397048001530015 | J71: BANK MUSCAT | K71: BMUSOMRX | L71: 99294425 | M71: 45941
A72: 3507 | B72: Bakhit Suhail Ahmed Qatan | C72: 1383.9 | D72: 0.250 | E72: =C72*D72 -> 345.975 | G72: =E72-F72 -> 345.975 | H72: 1184669 | I72: 01040281423001 | J72: BANK DHOFAR | K72: BDOFOMRU | L72: 99291928
A73: 3508 | B73: Said Ali Said Al Zawamri | C73: 1005.2 | D73: 0.250 | E73: =C73*D73 -> 251.3 | G73: =E73-F73 -> 251.3 | H73: 2567166 | I73: 0439004225500028 | J73: BANK MUSCAT | K73: BMUSOMRX | L73: 92570156
A74: 3509 | B74: Asama Mohammed Ahmed Masharah Al Shahri | C74: 542.3 | D74: 0.250 | E74: =C74*D74 -> 135.575 | G74: =E74-F74 -> 135.575 | H74: 22760088 | I74: 3129152535700 | J74: OAB | K74: OMABOMRU | L74: 91476443
A75: 3510 | B75: Amer Ali Ahmed Al kathiri | C75: 1188 | D75: 0.250 | E75: =C75*D75 -> 297 | G75: =E75-F75 -> 297 | H75: 6920351 | I75: 0397003252950036 | J75: BANK MUSCAT | K75: BMUSOMRX | L75: 98933077
A76: 3511 | B76: Said Ali Said Qatan | C76: 915.4 | D76: 0.250 | E76: =C76*D76 -> 228.85 | F76: =225.225+3.625 -> 228.85 | G76: =E76-F76 -> 0 | H76: 2640016 | I76: 0501036199001 | J76: Ahli Islamic | K76: AUBOOMRUALH | L76: 92953388 | M76: 45727 | N76: 29-12-25
A77: 3512 | B77: Ahmed Abdul Rahim Ali Al Kathiri | D77: 0.250 | E77: =C77*D77 -> 0 | G77: =E77-F77 -> 0 | H77: 5514631 | I77: 01041149485001 | J77: BANK DHOFAR | K77: BDOFOMRU
A78: 3513 | B78: Khair Salim Faraj Al Kathiri | C78: 2802.1 | D78: 0.250 | E78: =C78*D78 -> 700.525 | G78: =E78-F78 -> 700.525 | H78: 7047376 | I78: 01013042263001 | J78: BANK DHOFAR | K78: BDOFOMRU | L78: 90106022
A79: 3514 | B79: Said Salim Faraj Al Kathiri | C79: 1584.8 | D79: 0.250 | E79: =C79*D79 -> 396.2 | F79: =2.17500000000001+391.05 -> 393.225 | G79: =E79-F79 -> 2.975 | H79: 440083 | I79: 0397003539170015 | J79: Bank Muscat | K79: BMUSOMRX | L79: 92363355 | M79: 45700 | N79: 29-12-25
A80: 3515 | B80: Ali Ajaham Ali Bait said | C80: 1195 | D80: 0.250 | E80: =C80*D80 -> 298.75 | G80: =E80-F80 -> 298.75 | H80: 6645198 | I80: 01011180247001 | J80: BANK DHOFAR | K80: BDOFOMRU | L80: 94411217
A81: 3516 | B81: Musallam Hassan Ali Bait Muhammed Bin Ahmed | C81: 1775.7 | D81: 0.250 | E81: =C81*D81 -> 443.925 | G81: =E81-F81 -> 443.925 | H81: 1165877 | I81: 01010127958001 | J81: BANK DHOFAR | K81: BDOFOMRU
A82: 3517 | B82: Mohammed Salim Faraj Al Kathiri | C82: 1519.4 | D82: 0.250 | E82: =C82*D82 -> 379.85 | F82: =3.25000000000001+375.95+0.65 -> 379.85 | G82: =E82-F82 -> 0 | H82: 7047081 | I82: 01010401370002 | J82: BANK DHOFAR | K82: BDOFOMRU | M82: 45727 | N82: 17-11-25 | O82: 46008
A83: 3518 | B83: Ali Ahmed Ali Bait Said | C83: 714.1 | D83: 0.250 | E83: =C83*D83 -> 178.525 | F83: =0.825000000000023+177.7 -> 178.525 | G83: =E83-F83 -> 0 | H83: 20386956 | I83: 0396064567750014 | J83: BANK MUSCAT | K83: BMUSOMRX | M83: 20-10-2025 | N83: 45941
A84: 3519 | B84: Masoud Salim Faraj Al Kathiri | C84: 1005.9 | D84: 0.250 | E84: =C84*D84 -> 251.475 | F84: =2.27500000000001+248.2+1 -> 251.475 | G84: =E84-F84 -> 0 | H84: 7047221 | I84: 01011028414003 | J84: BANK DHOFAR | K84: BDOFOMRU | M84: 45727 | N84: 17-11-25 | O84: 46008
A85: 3520 | B85: Musallam Mahad Suhail Al Barami | C85: 1011.4 | D85: 0.250 | E85: =C85*D85 -> 252.85 | G85: =E85-F85 -> 252.85 | H85: 5665362 | I85: 01011072899001 | J85: BANK DHOFAR | K85: BDOFOMRU
A86: 3521 | B86: Omar Said Awadh Bait Said | C86: 3661.1 | D86: 0.250 | E86: =C86*D86 -> 915.275 | G86: =E86-F86 -> 915.275 | H86: 7064553 | I86: 0396019442490023 | J86: BANK MUSCAT | K86: BMUSOMRX
A87: 3522 | B87: Said Ahmed Ali Qatan | C87: 436.9 | D87: 0.250 | E87: =C87*D87 -> 109.225 | G87: =E87-F87 -> 109.225 | H87: 11365191 | I87: 01010121273002 | J87: BANK DHOFAR | K87: BDOFOMRU
A88: 3523 | B88: Said Salim | C88: 438 | D88: 0.250 | E88: =C88*D88 -> 109.5 | G88: =E88-F88 -> 109.5 | H88: 9399193 | I88: 010010137751 | J88: SOHAR | L88: 0099298810
A89: 3524 | B89: Bakhit Ali Ahmed Amer Jeed | C89: 416.7 | D89: 0.250 | E89: =C89*D89 -> 104.175 | G89: =E89-F89 -> 104.175 | H89: 1876659 | I89: 0397012592830018 | J89: BANK MUSCAT | L89: 0094800053
A90: 3525 | B90: salim Masoud Said AL-Kathiri | C90: 426.1 | D90: 0.250 | E90: =C90*D90 -> 106.525 | G90: =E90-F90 -> 106.525 | H90: 1862864 | I90: 0396057144960032 | J90: BANK MUSCAT | L90: 0091418828
A91: 3526 | B91: Masoud Ali Daid Qatan | C91: 166 | D91: 0.250 | E91: =C91*D91 -> 41.5 | G91: =E91-F91 -> 41.5 | H91: 5349102 | I91: 1502132783300 | J91: AHLI BANK | L91: 0093636606
A92: 3527 | B92: Bakhit Suhail Salim Al Barami | C92: 363.7 | D92: 0.250 | E92: =C92*D92 -> 90.925 | G92: =E92-F92 -> 90.925 | H92: 6372265 | I92: 039700370833019 | J92: BANK MUSCAT | L92: 0092488144
A93: 3528 | B93: Abdullah Salim Suhail Ahmed Al Kathiri | C93: 418.3 | D93: 0.250 | E93: =C93*D93 -> 104.575 | F93: =104.5+0.075 -> 104.575 | G93: =E93-F93 -> 0 | H93: 28605923 | I93: 0439079294590015 | J93: BANK MUSCAT | L93: 0093233289 | M93: 27-10-2025 | N93: 46008
A94: 3529 | B94: Mohammed Suhail Said Qatan | C94: 420.3 | D94: 0.250 | E94: =C94*D94 -> 105.075 | G94: =E94-F94 -> 105.075 | H94: 4702777 | I94: 0319005149020017 | J94: BANK MUSCAT | L94: 0092444040
A95: 3530 | B95: Mohammed Aslm Mohammed al Zawamri | C95: 290.2 | D95: 0.250 | E95: =C95*D95 -> 72.55 | G95: =E95-F95 -> 72.55 | H95: 1163821 | I95: 01010850775001 | J95: BANK DHOFAR | L95: 0099496955
A96: 3531 | B96: Mohammed Masoud Said khdhran Alkathiri | C96: 397 | D96: 0.250 | E96: =C96*D96 -> 99.25 | F96: =98.55+0.7 -> 99.25 | G96: =E96-F96 -> 0 | H96: 23661829 | I96: 0397059602380012 | J96: BANK MUSCAT | L96: 0092379624 | M96: 45941 | N96: 15-12-25
A97: 3532 | B97: Amer Salim Mohsin Ajham AlKathiri | C97: 404.9 | D97: 0.250 | E97: =C97*D97 -> 101.225 | F97: =E97 -> 101.225 | G97: =E97-F97 -> 0 | H97: 26301042 | I97: 01011346179002 | J97: BANK DHOFAR | L97: 0093968161 | M97: 24-12-25
A98: 3533 | B98: Ali Musallam Issa Al-Baraami | C98: 420.9 | D98: 0.250 | E98: =C98*D98 -> 105.225 | G98: =E98-F98 -> 105.225 | H98: 22979942 | I98: 0426048893580018 | J98: BANK MUSCAT | L98: 0099837335
A99: 3534 | B99: Musallam Hassan Abdullah Khdhran AlKathiri | C99: 421 | D99: 0.250 | E99: =C99*D99 -> 105.25 | F99: =102.2+3.05 -> 105.25 | G99: =E99-F99 -> 0 | H99: 14897254 | I99: 0397003341450012 | J99: BANK MUSCAT | L99: 0092226297 | M99: 45941 | N99: 15-12-25
A100: 3536 | B100: Fisal Ahmed Mahtouq Al-Zouamari | C100: 406.7 | D100: 0.250 | E100: =C100*D100 -> 101.675 | F100: =99.75+1.925 -> 101.675 | G100: =E100-F100 -> 0 | H100: 19548147 | I100: 01012588123001 | J100: BANK DHOFAR | L100: 0097176909 | M100: 22-10-25 | N100: 45973
A101: 3537 | B101: Hamid Said Al Shaiyaa Amur AlKathiri | C101: 299.2 | D101: 0.250 | E101: =C101*D101 -> 74.8 | F101: =71.25+3.55 -> 74.8 | G101: =E101-F101 -> 0 | H101: 6104979 | I101: 0396019134370025 | J101: BANK MUSCAT | L101: 0098821279 | M101: 27-10-2025 | N101: 31-12-25
...

Sheet oct25
A1: HAJEEF COW MILK PROCUREMENT FROM 01-Oct-2025 to 31-Oct-2025
A2: Farmer Code | B2: Farmer Name | C2: Milk Qty. (Ltr.) | D2: Avg. Rate (OMR/Ltr.) | E2: Amount (OMR) | F2: Amount (OMR) | G2: Balance | H2: ID No. | I2: Bank Account No. | J2: Bank Name | K2: IFSC Code | L2: Phone No. | M2: Remarks
A4: 1007 | B4: AHMED ABDULLAH SAID AL RAWAS | C4: 6878.2 | D4: 0.25 | E4: =C4*D4 -> 1719.55 | G4: =E4-F4 -> 1719.55 | H4: 1515504 | I4: 0615500670380001 | J4: Bank Meethaq | K4: BMUSOMRXISL | L4: 91748840
A5: 1041 | B5: AHMED SALIM ALI BAITSAID | C5: 2549.8 | D5: 0.25 | E5: =C5*D5 -> 637.45 | G5: =E5-F5 -> 637.45 | H5: 6827729 | I5: 0406003463970017 | J5: BANK MUSCAT | K5: BMUSOMRX | L5: 92272935
A6: 1125 | B6: MUSALLAM SAID ALI BAITSAID | C6: 5022.7 | D6: 0.25 | E6: =C6*D6 -> 1255.675 | F6: =1251.05 -> 1251.05 | G6: =E6-F6 -> 4.625 | H6: 6828774 | I6: 01011456108001 | J6: BANK DHOFAR | K6: BDOFOMRU | L6: 91267555 | M6: 45941 | N6: 15-12-25
A7: 1222 | B7: Mahad Salim Abdulaziz Alkathiri | D7: 0.25 | E7: =C7*D7 -> 0 | G7: =E7-F7 -> 0 | H7: 31221 | I7: 1006623107017 | J7: NBO | K7: NBOMOMRX
A8: 1286 | B8: SALIM AMER AHMED AL YAFAEI | C8: 3798.9 | D8: 0.25 | E8: =C8*D8 -> 949.725 | G8: =E8-F8 -> 949.725 | H8: 368056 | I8: 0406003218280013 | J8: BANK MUSCAT | K8: BMUSOMRX | L8: 99494264
A9: 1344 | B9: SAID AMERAHMED BAITSAID | C9: 3437.4 | D9: 0.25 | E9: =C9*D9 -> 859.35 | F9: 858.7 | G9: =E9-F9 -> 0.65 | H9: 4014519 | I9: 3109370559500 | J9: OAB | K9: OMABOMRU | M9: 17-12-25
A10: 1352 | B10: MOHAMMED MASOUD AJHAM ALSH AL KATHIRI | C10: 1281.6 | D10: 0.25 | E10: =C10*D10 -> 320.4 | F10: 316.625 | G10: =E10-F10 -> 3.775 | H10: 1627344 | I10: 0397046773470015 | J10: BANK MUSCAT | K10: BMUSOMRX | M10: 46002
A11: 1354 | B11: AHMED SAID HASSAN BAITSAID | C11: 2232.7 | D11: 0.25 | E11: =C11*D11 -> 558.175 | G11: =E11-F11 -> 558.175 | H11: 925709 | I11: 0406018690130014 | J11: BANK MUSCAT | K11: BMUSOMRX | L11: 95187860
A12: 1357 | B12: MUSALLAM SAID ALI BAIT SAID | C12: 4873.1 | D12: 0.25 | E12: =C12*D12 -> 1218.275 | G12: =E12-F12 -> 1218.275 | H12: 1052276 | I12: 01040280323001 | J12: BANK DHOFAR | K12: BDOFOMRU | L12: 95301260
A13: 1359 | B13: MUSALLAM MUSTAHIL SAID BAIT SAID | C13: 3273.3 | D13: 0.25 | E13: =C13*D13 -> 818.325 | F13: =2.80000000000003+812.25 -> 815.05 | G13: =E13-F13 -> 3.275 | H13: 4812026 | I13: 1083517184017 | J13: NBO | K13: NBOMOMRX | L13: 96616558 | M13: 45728 | N13: 22-12-25
A14: 1367 | B14: ALI MUSALLAM AHMED BAIT SAID | C14: 1867.7 | D14: 0.25 | E14: =C14*D14 -> 466.925 | G14: =E14-F14 -> 466.925 | H14: 6663593 | I14: 0406003006560016 | J14: BANK MUSCAT | K14: BMUSOMRX | L14: 92817702
A15: 1368 | B15: MOHAMMD SAID AHMED AL KATHIRI | C15: 1980.1 | D15: 0.25 | E15: =C15*D15 -> 495.025 | G15: =E15-F15 -> 495.025 | H15: 561902 | I15: 01040854387001 | J15: BANK DHOFAR | K15: BDOFOMRU | L15: 99499622
A16: 2098 | B16: Bakhit Musallam Ali Kashoob | C16: 647.1 | D16: 0.25 | E16: =C16*D16 -> 161.775 | F16: =160.15 -> 160.15 | G16: =E16-F16 -> 1.625 | H16: 1065899 | I16: 132857700081018 | J16: BANK MUSCAT | K16: BMUSOMRX | M16: 31-12-25
A17: 2529 | B17: Masoud Salim Masoud Tabook | C17: 1029 | D17: 0.25 | E17: =C17*D17 -> 257.25 | F17: =256.5 -> 256.5 | G17: =E17-F17 -> 0.75 | H17: 6375262 | I17: 0401025220480017 | J17: BANK MUSCAT | K17: BMUSOMRX | L17: 95144359 | M17: 46008
A18: 3002 | B18: KHALID MUBARAK ALI ATQOON AL SHAHRI | C18: 1358 | D18: 0.25 | E18: =C18*D18 -> 339.5 | F18: 338.475 | G18: =E18-F18 -> 1.025 | H18: 21220177 | I18: 0401016727580038 | J18: BANK MUSCAT | K18: BMUSOMRX | L18: 99280644 | M18: 14-12-25
A19: 3035 | B19: TARIQ SALIM SUHAIL AL BARAMI | C19: 512.5 | D19: 0.25 | E19: =C19*D19 -> 128.125 | G19: =E19-F19 -> 128.125 | H19: 6725058 | I19: 01011059048001 | J19: BANK DHOFAR | K19: BDOFOMRU | L19: 99198121
A20: 3057 | B20: ALI AHMED MOHAMMED AL KATHIRI | C20: 2683.7 | D20: 0.25 | E20: =C20*D20 -> 670.925 | G20: =E20-F20 -> 670.925 | H20: 626819 | I20: 0397003510460014 | J20: BANK MUSCAT | K20: BMUSOMRX | L20: 99298522
A21: 3062 | B21: ALI MAHAD SILMOUN QATAN | C21: 2716.6 | D21: 0.25 | E21: =C21*D21 -> 679.15 | G21: =E21-F21 -> 679.15 | H21: 300741 | I21: 0397004203200017 | J21: BANK MUSCAT | K21: BMUSOMRX | L21: 99008320
A22: 3080 | B22: MUSALLAM BAKHIT AWADH L BARAAMI | C22: 1906.6 | D22: 0.25 | E22: =C22*D22 -> 476.65 | G22: =E22-F22 -> 476.65 | H22: 14301608 | I22: 0397003041020024 | J22: BANK MUSCAT | K22: BMUSOMRX | L22: 98122611
A23: 3086 | B23: MUSALLAM ALI MATOOQ TABOOK | C23: 751.8 | D23: 0.25 | E23: =C23*D23 -> 187.95 | F23: =184.825 -> 184.825 | G23: =E23-F23 -> 3.125 | H23: 300033 | I23: 0397003905720015 | J23: BANK MUSCAT | K23: BMUSOMRX | M23: 45759
A24: 3132 | B24: HASHIM SALIM ALI ATIF AL YAFAI | C24: 1894.1 | D24: 0.25 | E24: =C24*D24 -> 473.525 | G24: =E24-F24 -> 473.525 | H24: 14606296 | I24: 0401024314310011 | J24: BANK MUSCAT | K24: BMUSOMRX | L24: 91493522
A25: 3134 | B25: HASSAN SUHAIL MAHAD QATAN | C25: 1971.7 | D25: 0.25 | E25: =C25*D25 -> 492.925 | G25: =E25-F25 -> 492.925 | H25: 2154413 | I25: 01010850952003 | J25: BANK DHOFAR | K25: BDOFOMRU | L25: 99493731
A26: 3142 | B26: MOHAMMED AHMED SAAD MASHRAH AL SHAHRI | C26: 4731.6 | D26: 0.25 | E26: =C26*D26 -> 1182.9 | F26: =4.4+589+589 -> 1182.4 | G26: =E26-F26 -> 0.5 | H26: 165497 | I26: 3129019324700 | J26: OAB | K26: OMABOMRU | L26: 99499872 | M26: 19-11-25 | N26: 17-12-25
A27: 3145 | B27: MOHAMMED BAKHIT MASOUD QATAN | C27: 2832.9 | D27: 0.25 | E27: =C27*D27 -> 708.225 | F27: =704.95 -> 704.95 | G27: =E27-F27 -> 3.275 | H27: 1915745 | I27: 0404002595460014 | J27: BANK MUSCAT | K27: BMUSOMRX | L27: 99489050 | M27: 14-12-25
A28: 3147 | B28: KHALID SAID MAHAD KASHOUB | C28: 1970.1 | D28: 0.25 | E28: =C28*D28 -> 492.525 | F28: 489.175 | G28: =E28-F28 -> 3.35 | H28: 1662414 | I28: 3129770819700 | J28: OAB | K28: OMABOMRU | L28: 99282006 | M28: 14-12-25
A29: 3148 | B29: MUSALLAM AHMED MAHTOUQ AL ZAWAMRI | C29: 1387.6 | D29: 0.25 | E29: =C29*D29 -> 346.9 | F29: =346.55 -> 346.55 | G29: =E29-F29 -> 0.35 | H29: 19545736 | I29: 01011208343002 | J29: BANK DHOFAR | K29: BDOFOMRU | M29: 45973
A30: 3149 | B30: ALI SAID ALI AL ZAWAMRI | C30: 1871.7 | D30: 0.25 | E30: =C30*D30 -> 467.925 | F30: 464.775 | G30: =E30-F30 -> 3.15 | H30: 4941095 | I30: 1104036354300 | J30: Ahli Bank | K30: AUBOOMRU | L30: 93500864 | M30: 19-11-25
A31: 3150 | B31: Awad Ahmed Said Alzwamri | C31: 483.1 | D31: 0.25 | E31: =C31*D31 -> 120.775 | F31: 119.85 | G31: =E31-F31 -> 0.925 | H31: 18940347 | I31: 0401017288790038 | J31: BANK MUSCAT | K31: BMUSOMRX | L31: 98905289 | M31: 17-11-25
A32: 3152 | B32: BAKHIT SALIM MAHAD QATAN | C32: 3209.7 | D32: 0.25 | E32: =C32*D32 -> 802.425 | F32: =E32 -> 802.425 | G32: =E32-F32 -> 0 | H32: 941993 | I32: 01042574515001 | J32: BANK DHOFAR | K32: BDOFOMRU | L32: 99086500 | M32: 45727 | N32: .975-11-2025
A33: 3153 | B33: ALI MAHAD SAID QATAN | C33: 2897.3 | D33: 0.25 | E33: =C33*D33 -> 724.325 | G33: =E33-F33 -> 724.325 | H33: 6989479 | I33: 0397003672070015 | J33: BANK MUSCAT | K33: BMUSOMRX | L33: 99699500
A34: 3155 | B34: SAID BAKHIT MAHAD QATAN | C34: 627.2 | D34: 0.25 | E34: =C34*D34 -> 156.8 | G34: =E34-F34 -> 156.8 | H34: 19188794 | I34: 0402003042750013 | J34: BANK MUSCAT | K34: BMUSOMRX | L34: 93215515
A35: 3158 | B35: AHMED OBAIDAN AHMED AL KATHIRI | C35: 3556.4 | D35: 0.25 | E35: =C35*D35 -> 889.1 | G35: =E35-F35 -> 889.1 | H35: 596869 | I35: 0401049081340015 | J35: BANK MUSCAT | K35: BMUSOMRX | L35: 99694218
A36: 3159 | B36: AHMED BAKHIT SALEM AL BARAMI | C36: 619.3 | D36: 0.25 | E36: =C36*D36 -> 154.825 | G36: =E36-F36 -> 154.825 | H36: 1297478 | I36: 0397003703480012 | J36: BANK MUSCAT | K36: BMUSOMRX | L36: 99497177
A37: 3160 | B37: NAIF MUBARAK BAKHIT AL BARAAMI | C37: 2400 | D37: 0.25 | E37: =C37*D37 -> 600 | G37: =E37-F37 -> 600 | H37: 2837163 | I37: 00510031862001 | J37: Bank Nizwa | K37: BNZWOMRX | L37: 99497455
A38: 3162 | B38: MOHAMMED SAID FARAJ AL KATHIRI | C38: 5734.4 | D38: 0.25 | E38: =C38*D38 -> 1433.6 | G38: =E38-F38 -> 1433.6 | H38: 7017227 | I38: 01010940071001 | J38: BANK DHOFAR | K38: BDOFOMRU | L38: 99523400
A39: 3164 | B39: ALI MUSALLLAM HASSAN BAITSAID | C39: 2426.6 | D39: 0.25 | E39: =C39*D39 -> 606.65 | F39: =3.25+602.25 -> 605.5 | G39: =E39-F39 -> 1.15 | H39: 7466062 | I39: 01646038607001 | J39: Maisarah | K39: BDOFOMRUMIB | L39: 91135005 | M39: 46002 | N39: 14-12-25
A40: 3165 | B40: KHALID MOHAMMED MASAAOD AGGHRIB AL SHAHRI | C40: 460.7 | D40: 0.25 | E40: =C40*D40 -> 115.175 | G40: =E40-F40 -> 115.175 | H40: 19029628 | I40: 01011251497002 | J40: BANK DHOFAR | K40: BDOFOMRU | L40: 96055446
A41: 3169 | B41: MOHAMMED ALI SAID AL ZAWAMRY | C41: 2509.2 | D41: 0.25 | E41: =C41*D41 -> 627.3 | G41: =E41-F41 -> 627.3 | H41: 3068756 | I41: 01012573317001 | J41: BANK DHOFAR | K41: BDOFOMRU | L41: 99691806
A42: 3171 | B42: HATAM AWADH SAID QATAN | C42: 1120.2 | D42: 0.25 | E42: =C42*D42 -> 280.05 | F42: 277 | G42: =E42-F42 -> 3.05 | H42: 7239057 | I42: 3109607126500 | J42: OAB | K42: OMABOMRU | L42: 95880860 | M42: 17-11-25
A43: 3172 | B43: Fatima Suleimon Salim ALBaramiyah | C43: 1316.4 | D43: 0.25 | E43: =C43*D43 -> 329.1 | G43: =E43-F43 -> 329.1 | H43: 5276984 | I43: 0439046831000027 | J43: BANK MUSCAT | K43: BMUSOMRX | L43: 99188860
A44: 3173 | B44: MUSALLAM AHMED SAAD AL BARAAMI | C44: 725.1 | D44: 0.25 | E44: =C44*D44 -> 181.275 | F44: =178.2 -> 178.2 | G44: =E44-F44 -> 3.075 | H44: 6825655 | I44: 0397004380200011 | J44: BANK MUSCAT | K44: BMUSOMRX | L44: 98957747 | M44: 17-12-25
A45: 3174 | B45: AHMED MUSALLAM SAID QATAN | C45: 1013.5 | D45: 0.25 | E45: =C45*D45 -> 253.375 | G45: =E45-F45 -> 253.375 | H45: 7547492 | I45: 0401002379960017 | J45: BANK MUSCAT | K45: BMUSOMRX | L45: 91790502
A46: 3175 | B46: SAID AHMED NASIB AL BARAAMI | C46: 776.3 | D46: 0.25 | E46: =C46*D46 -> 194.075 | F46: 193.1 | G46: =E46-F46 -> 0.975 | H46: 7325076 | I46: 1006794849001 | J46: NBO | K46: NBOMOMRX | L46: 92890700 | M46: 15-12-25
A47: 3176 | B47: KHAYAR ALI SAID AL BARAAMI | C47: 507.3 | D47: 0.25 | E47: =C47*D47 -> 126.825 | G47: =E47-F47 -> 126.825 | H47: 12178145 | I47: 0406015163810016 | J47: BANK MUSCAT | K47: BMUSOMRX | L47: 93348565
A48: 3179 | B48: SUHAIL MOHAMMED SUHAIL TABUK | C48: 2651.7 | D48: 0.25 | E48: =C48*D48 -> 662.925 | G48: =E48-F48 -> 662.925 | H48: 1870852 | I48: 3129685484720 | J48: OAB | K48: OMABOMRU | L48: 99050691
A49: 3181 | B49: TARIK MASOUD MAJADAH AL KATHIRI | C49: 2547.4 | D49: 0.25 | E49: =C49*D49 -> 636.85 | G49: =E49-F49 -> 636.85 | H49: 6116067 | I49: 3109710314700 | J49: OAB | K49: OMABOMRU | L49: 99191102
A50: 3183 | B50: Salim Musallam Ali Qatan | C50: 1284.4 | D50: 0.25 | E50: =C50*D50 -> 321.1 | F50: 319.425 | G50: =E50-F50 -> 1.675 | H50: 4955092 | I50: 0401002697260019 | J50: BANK MUSCAT | K50: BMUSOMRX | L50: 98152775 | M50: 14-12-25
A51: 3184 | B51: ALI MOHAMMED MUSALLAM AL BARAAMI | C51: 2570.1 | D51: 0.25 | E51: =C51*D51 -> 642.525 | G51: =E51-F51 -> 642.525 | H51: 6701602 | I51: 01011004872002 | J51: BANK DHOFAR | K51: BDOFOMRU | L51: 99496161
A52: 3185 | B52: MOHAMMED ALI AHMED AMOOSH THOAR | C52: 1240.4 | D52: 0.25 | E52: =C52*D52 -> 310.1 | F52: 308.425 | G52: =E52-F52 -> 1.675 | H52: 15179209 | I52: 0405020308900019 | J52: BANK MUSCAT | K52: BMUSOMRX | L52: 94919974 | M52: 14-12-25
A53: 3188 | B53: HASSAN BAKHIT AHMED QATAN | C53: 1584.7 | D53: 0.25 | E53: =C53*D53 -> 396.175 | F53: 394.8 | G53: =E53-F53 -> 1.375 | H53: 19290729 | I53: 01041574026001 | J53: BANK DHOFAR | K53: BDOFOMRU | L53: 95606029 | M53: 24-12-25
A54: 3189 | B54: SAID AHMED SAID AL ZAWAMRI | C54: 917.1 | D54: 0.25 | E54: =C54*D54 -> 229.275 | G54: =E54-F54 -> 229.275 | H54: 2802613 | I54: 0405002746200013 | J54: BANK MUSCAT | K54: BMUSOMRX | L54: 99480848
A55: 3190 | B55: TAFOOL SILMOUN SALIM AL BARAMI | C55: 596.5 | D55: 0.25 | E55: =C55*D55 -> 149.125 | G55: =E55-F55 -> 149.125 | H55: 3555896 | I55: 0402014490950017 | J55: BANK MUSCAT | K55: BMUSOMRX | L55: 92881155
A56: 3192 | B56: GHAZI SALIM MASOUD TABOOK | C56: 982 | D56: 0.25 | E56: =C56*D56 -> 245.5 | F56: 244.8 | G56: =E56-F56 -> 0.7 | H56: 5271448 | I56: 0401002602010018 | J56: BANK MUSCAT | K56: BMUSOMRX | L56: 99489918 | M56: 15-12-25
A57: 3195 | B57: MUSTAHIL SAID MUSTAHIL AL BARAAMI | C57: 628.5 | D57: 0.25 | E57: =C57*D57 -> 157.125 | G57: =E57-F57 -> 157.125 | H57: 675849 | I57: 01011097969001 | J57: BANK DHOFAR | K57: BDOFOMRU | L57: 99483811
A58: 3196 | B58: JASIM MOHAMMED SAID ALI AFIR AL ZAWAMARI | C58: 627 | D58: 0.25 | E58: =C58*D58 -> 156.75 | G58: =E58-F58 -> 156.75 | H58: 21080217 | I58: 0401007927380037 | J58: BANK MUSCAT | K58: BMUSOMRX | L58: 95490778
A59: 3197 | B59: MOHSIN SAID MOHAMED BA AWAIN | C59: 1860.4 | D59: 0.25 | E59: =C59*D59 -> 465.1 | G59: =E59-F59 -> 465.1 | H59: 6479515 | I59: 0406003220920038 | J59: BANK MUSCAT | K59: BMUSOMRX | L59: 92349032
A60: 3198 | B60: ADIL SAID AHMED AL ZAWAMRI | C60: 507.8 | D60: 0.25 | E60: =C60*D60 -> 126.95 | G60: =E60-F60 -> 126.95 | H60: 6360793 | I60: 00510047506001 | J60: Bank Nizwa | K60: BNZWOMRX | L60: 99336200
A61: 3310 | B61: AHMED SUHAIL SAID AL BARAMI | C61: 1281.3 | D61: 0.25 | E61: =C61*D61 -> 320.325 | G61: =E61-F61 -> 320.325 | H61: 1007615 | I61: 0397003855850017 | J61: BANK MUSCAT | K61: BMUSOMRX | L61: 99056614
A62: 3324 | B62: BAKHIT AWADH BAKHIT AL BARAAMI | C62: 1902.7 | D62: 0.25 | E62: =C62*D62 -> 475.675 | G62: =E62-F62 -> 475.675 | H62: 207402 | I62: 0401057742590016 | J62: BANK MUSCAT | K62: BMUSOMRX | L62: 99487533
A63: 3330 | B63: Salim Ahmed Aubad Al kathiri | C63: 2337.4 | D63: 0.25 | E63: =C63*D63 -> 584.35 | G63: =E63-F63 -> 584.35 | H63: 6375079 | I63: 0397062111930011 | J63: Bank Muscat | K63: BMUSOMRX
A64: 3333 | B64: Mahad Salim Zaed Bait Said | C64: 1786 | D64: 0.25 | E64: =C64*D64 -> 446.5 | G64: =E64-F64 -> 446.5 | H64: 757601 | I64: 1023113274001 | J64: NBO | K64: NBOMOMRX
A65: 3339 | B65: Khalid Ahmed Salim Amer Jid Almahri | C65: 689.8 | D65: 0.25 | E65: =C65*D65 -> 172.45 | F65: 169.275 | G65: =E65-F65 -> 3.175 | H65: 12415718 | I65: 0401050718800013 | J65: BANK MUSCAT | K65: BMUSOMRX | M65: 14-12-25
A66: 3341 | B66: Mahad Ahmed Alkathiri | C66: 373.4 | D66: 0.25 | E66: =C66*D66 -> 93.35 | G66: =E66-F66 -> 93.35 | H66: 702161 | I66: 3109593036500 | J66: OAB | K66: OMABOMRU | L66: 99290644
A67: 3500 | B67: Salim Mohammed Ahmed Al Kathiri | D67: 0.25 | E67: =C67*D67 -> 0 | G67: =E67-F67 -> 0 | H67: 13525845 | I67: 10600259604017 | J67: NBO | K67: NBOMOMRX | L67: 93985671
A68: 3501 | B68: Said Masoud Ahmed Al kathiri | C68: 1676.7 | D68: 0.25 | E68: =C68*D68 -> 419.175 | G68: =E68-F68 -> 419.175 | H68: 13525794 | I68: 0402003356710024 | J68: BANK MUSCAT | K68: BMUSOMRX | L68: 92868004
A69: 3502 | B69: Ahmed Bakhit Ahmed Al Kathiri | C69: 1906.1 | D69: 0.25 | E69: =C69*D69 -> 476.525 | G69: =E69-F69 -> 476.525 | H69: 22522336 | I69: 01011021065002 | J69: BANK DHOFAR | K69: BDOFOMRU
A70: 3503 | B70: Imad Bakhit Salim Bakhit Qatan | C70: 622.1 | D70: 0.25 | E70: =C70*D70 -> 155.525 | G70: =E70-F70 -> 155.525 | H70: 9212492 | I70: 0401028325700011 | J70: BANK MUSCAT | K70: BMUSOMRX | L70: 98080144
A71: 3504 | B71: Ali Salem Amer Al Kathiri | D71: 0.25 | E71: =C71*D71 -> 0 | G71: =E71-F71 -> 0 | H71: 939641 | I71: 0406003375130017 | J71: BANK MUSCAT | K71: BMUSOMRX | L71: 99588609
A72: 3506 | B72: Ahmed Masoud Salim Al Kathiri | C72: 526.2 | D72: 0.25 | E72: =C72*D72 -> 131.55 | F72: 114.425 | G72: =E72-F72 -> 17.125 | H72: 13307752 | I72: 0397048001530015 | J72: BANK MUSCAT | K72: BMUSOMRX | L72: 99294425 | M72: 45941
A73: 3507 | B73: Bakhit Suhail Ahmed Qatan | C73: 1049 | D73: 0.25 | E73: =C73*D73 -> 262.25 | G73: =E73-F73 -> 262.25 | H73: 1184669 | I73: 01040281423001 | J73: BANK DHOFAR | K73: BDOFOMRU | L73: 99291928
A74: 3508 | B74: Said Ali Said Al Zawamri | C74: 1189.5 | D74: 0.25 | E74: =C74*D74 -> 297.375 | G74: =E74-F74 -> 297.375 | H74: 2567166 | I74: 0439004225500028 | J74: BANK MUSCAT | K74: BMUSOMRX | L74: 92570156
A75: 3509 | B75: Asama Mohammed Ahmed Masharah Al Shahri | C75: 600.9 | D75: 0.25 | E75: =C75*D75 -> 150.225 | G75: =E75-F75 -> 150.225 | H75: 22760088 | I75: 3129152535700 | J75: OAB | K75: OMABOMRU | L75: 91476443
A76: 3510 | B76: Amer Ali Ahmed Al kathiri | C76: 1145.6 | D76: 0.25 | E76: =C76*D76 -> 286.4 | G76: =E76-F76 -> 286.4 | H76: 6920351 | I76: 0397003252950036 | J76: BANK MUSCAT | K76: BMUSOMRX | L76: 98933077
A77: 3511 | B77: Said Ali Said Qatan | C77: 1803.4 | D77: 0.25 | E77: =C77*D77 -> 450.85 | F77: 447.625 | G77: =E77-F77 -> 3.225 | H77: 2640016 | I77: 0501036199001 | J77: Ahli Islamic | K77: AUBOOMRUALH | L77: 92953388 | M77: 29-12-25
A78: 3512 | B78: Ahmed Abdul Rahim Ali Al Kathiri | D78: 0.25 | E78: =C78*D78 -> 0 | G78: =E78-F78 -> 0 | H78: 5514631 | I78: 01041149485001 | J78: BANK DHOFAR | K78: BDOFOMRU
A79: 3513 | B79: Khair Salim Faraj Al Kathiri | C79: 3147 | D79: 0.25 | E79: =C79*D79 -> 786.75 | G79: =E79-F79 -> 786.75 | H79: 7047376 | I79: 01013042263001 | J79: BANK DHOFAR | K79: BDOFOMRU | L79: 90106022
A80: 3514 | B80: Said Salim Faraj Al Kathiri | C80: 1798.2 | D80: 0.25 | E80: =C80*D80 -> 449.55 | G80: =E80-F80 -> 449.55 | H80: 440083 | I80: 0397003539170015 | J80: Bank Muscat | K80: BMUSOMRX | L80: 92363355
A81: 3515 | B81: Ali Ajaham Ali Bait said | C81: 792.4 | D81: 0.25 | E81: =C81*D81 -> 198.1 | G81: =E81-F81 -> 198.1 | H81: 6645198 | I81: 01011180247001 | J81: BANK DHOFAR | K81: BDOFOMRU | L81: 94411217
A82: 3516 | B82: Musallam Hassan Ali Bait Muhammed Bin Ahmed | C82: 1920.2 | D82: 0.25 | E82: =C82*D82 -> 480.05 | G82: =E82-F82 -> 480.05 | H82: 1165877 | I82: 01010127958001 | J82: BANK DHOFAR | K82: BDOFOMRU
A83: 3517 | B83: Mohammed Salim Faraj Al Kathiri | C83: 1809.4 | D83: 0.25 | E83: =C83*D83 -> 452.35 | F83: 451.95 | G83: =E83-F83 -> 0.4 | H83: 7047081 | I83: 01010401370002 | J83: BANK DHOFAR | K83: BDOFOMRU | M83: 46008
A84: 3518 | B84: Ali Ahmed Ali Bait Said | C84: 1128.5 | D84: 0.25 | E84: =C84*D84 -> 282.125 | F84: =0.5+277.2 -> 277.7 | G84: =E84-F84 -> 4.425 | H84: 20386956 | I84: 0396064567750014 | J84: BANK MUSCAT | K84: BMUSOMRX | M84: 45941 | N84: 29-12-25
A85: 3519 | B85: Masoud Salim Faraj Al Kathiri | C85: 1161.5 | D85: 0.25 | E85: =C85*D85 -> 290.375 | F85: 287.35 | G85: =E85-F85 -> 3.025 | H85: 7047221 | I85: 01011028414003 | J85: BANK DHOFAR | K85: BDOFOMRU | M85: 46008
A86: 3520 | B86: Musallam Mahad Suhail Al Barami | C86: 956.7 | D86: 0.25 | E86: =C86*D86 -> 239.175 | G86: =E86-F86 -> 239.175 | H86: 5665362 | I86: 01011072899001 | J86: BANK DHOFAR | K86: BDOFOMRU
A87: 3521 | B87: Omar Said Awadh Bait Said | C87: 4228.7 | D87: 0.25 | E87: =C87*D87 -> 1057.175 | G87: =E87-F87 -> 1057.175 | H87: 7064553 | I87: 0396019442490023 | J87: BANK MUSCAT | K87: BMUSOMRX
A88: 3522 | B88: Said Ahmed Ali Qatan | C88: 396.6 | D88: 0.25 | E88: =C88*D88 -> 99.15 | G88: =E88-F88 -> 99.15 | H88: 11365191 | I88: 01010121273002 | J88: BANK DHOFAR | K88: BDOFOMRU
A89: 3523 | B89: Said Salim | C89: 635.4 | D89: 0.25 | E89: =C89*D89 -> 158.85 | G89: =E89-F89 -> 158.85 | H89: 9399193 | I89: 010010137751 | J89: SOHAR | L89: 0099298810
A90: 3524 | B90: Bakhit Ali Ahmed Amer Jeed | C90: 618.3 | D90: 0.25 | E90: =C90*D90 -> 154.575 | G90: =E90-F90 -> 154.575 | H90: 1876659 | I90: 0397012592830018 | J90: BANK MUSCAT | L90: 0094800053
A91: 3525 | B91: salim Masoud Said AL-Kathiri | C91: 478.7 | D91: 0.25 | E91: =C91*D91 -> 119.675 | G91: =E91-F91 -> 119.675 | H91: 1862864 | I91: 0396057144960032 | J91: BANK MUSCAT | L91: 0091418828
A92: 3526 | B92: Masoud Ali Daid Qatan | C92: 191.4 | D92: 0.25 | E92: =C92*D92 -> 47.85 | G92: =E92-F92 -> 47.85 | H92: 5349102 | I92: 1502132783300 | J92: AHLI BANK | L92: 0093636606
A93: 3527 | B93: Bakhit Suhail Salim Al Barami | C93: 569.5 | D93: 0.25 | E93: =C93*D93 -> 142.375 | G93: =E93-F93 -> 142.375 | H93: 6372265 | I93: 039700370833019 | J93: BANK MUSCAT | L93: 0092488144
A94: 3528 | B94: Abdullah Salim Suhail Ahmed Al Kathiri | C94: 618.3 | D94: 0.25 | E94: =C94*D94 -> 154.575 | F94: 153.375 | G94: =E94-F94 -> 1.2 | H94: 28605923 | I94: 0439079294590015 | J94: BANK MUSCAT | L94: 0093233289 | M94: 46008
A95: 3529 | B95: Mohammed Suhail Said Qatan | C95: 599.3 | D95: 0.25 | E95: =C95*D95 -> 149.825 | G95: =E95-F95 -> 149.825 | H95: 4702777 | I95: 0319005149020017 | J95: BANK MUSCAT | L95: 0092444040
A96: 3530 | B96: Mohammed Aslm Mohammed al Zawamri | C96: 580.6 | D96: 0.25 | E96: =C96*D96 -> 145.15 | G96: =E96-F96 -> 145.15 | H96: 1163821 | I96: 01010850775001 | J96: BANK DHOFAR | L96: 0099496955
A97: 3531 | B97: Mohammed Masoud Said khdhran Alkathiri | C97: 615.6 | D97: 0.25 | E97: =C97*D97 -> 153.9 | F97: 152.6 | G97: =E97-F97 -> 1.3 | H97: 23661829 | I97: 0397059602380012 | J97: BANK MUSCAT | L97: 0092379624 | M97: 15-12-25
A98: 3532 | B98: Amer Salim Mohsin Ajham AlKathiri | C98: 623.4 | D98: 0.25 | E98: =C98*D98 -> 155.85 | F98: 155.275 | G98: =E98-F98 -> 0.575 | H98: 26301042 | I98: 01011346179002 | J98: BANK DHOFAR | L98: 0093968161 | M98: 24-12-25
A99: 3533 | B99: Ali Musallam Issa Al-Baraami | C99: 608 | D99: 0.25 | E99: =C99*D99 -> 152 | G99: =E99-F99 -> 152 | H99: 22979942 | I99: 0426048893580018 | J99: BANK MUSCAT | L99: 0099837335
A100: 3534 | B100: Musallam Hassan Abdullah Khdhran AlKathiri | C100: 622.9 | D100: 0.25 | E100: =C100*D100 -> 155.725 | F100: 153.9 | G100: =E100-F100 -> 1.825 | H100: 14897254 | I100: 0397003341450012 | J100: BANK MUSCAT | L100: 0092226297 | M100: 15-12-25
A101: 3535 | B101: Omar Masoud Ali Albarami | C101: 476.4 | D101: 0.25 | E101: =C101*D101 -> 119.1 | G101: =E101-F101 -> 119.1 | H101: 1694834 | I101: 0403053364170013 | J101: BANK MUSCAT | L101: 98444454
...

Sheet nov-25
A1: HAJEEF COW MILK PROCUREMENT FROM 01-Nov-2025 to 30-Nov-2025
A2: Farmer Code | B2: Farmer Name | C2: Milk Qty. (Ltr.) | D2: Avg. Rate (OMR/Ltr.) | E2: Amount (OMR) | G2: Balance | H2: ID No. | I2: Bank Account No. | J2: Bank Name | K2: IFSC Code | L2: Phone No.
A4: 1007 | B4: AHMED ABDULLAH SAID AL RAWAS | C4: 6003.5 | D4: 0.25 | E4: =C4*D4 -> 1500.875 | G4: =E4-F4 -> 1500.875 | H4: 1515504 | I4: 0615500670380001 | J4: Bank Meethaq | K4: BMUSOMRXISL | L4: 91748840
A5: 1041 | B5: AHMED SALIM ALI BAITSAID | C5: 2701.1 | D5: 0.25 | E5: =C5*D5 -> 675.275 | G5: =E5-F5 -> 675.275 | H5: 6827729 | I5: 0406003463970017 | J5: BANK MUSCAT | K5: BMUSOMRX | L5: 92272935
A6: 1125 | B6: MUSALLAM SAID ALI BAITSAID | C6: 4391 | D6: 0.25 | E6: =C6*D6 -> 1097.75 | G6: =E6-F6 -> 1097.75 | H6: 6828774 | I6: 01011456108001 | J6: BANK DHOFAR | K6: BDOFOMRU | L6: 91267555
A7: 1222 | B7: Mahad Salim Abdulaziz Alkathiri | D7: 0.25 | E7: =C7*D7 -> 0 | G7: =E7-F7 -> 0 | H7: 31221 | I7: 1006623107017 | J7: NBO | K7: NBOMOMRX
A8: 1286 | B8: SALIM AMER AHMED AL YAFAEI | C8: 3784.4 | D8: 0.25 | E8: =C8*D8 -> 946.1 | G8: =E8-F8 -> 946.1 | H8: 368056 | I8: 0406003218280013 | J8: BANK MUSCAT | K8: BMUSOMRX | L8: 99494264
A9: 1344 | B9: SAID AMERAHMED BAITSAID | C9: 3104.4 | D9: 0.25 | E9: =C9*D9 -> 776.1 | G9: =E9-F9 -> 776.1 | H9: 4014519 | I9: 3109370559500 | J9: OAB | K9: OMABOMRU
A10: 1352 | B10: MOHAMMED MASOUD AJHAM ALSH AL KATHIRI | C10: 1103.1 | D10: 0.25 | E10: =C10*D10 -> 275.775 | G10: =E10-F10 -> 275.775 | H10: 1627344 | I10: 0397046773470015 | J10: BANK MUSCAT | K10: BMUSOMRX
A11: 1354 | B11: AHMED SAID HASSAN BAITSAID | C11: 2086.1 | D11: 0.25 | E11: =C11*D11 -> 521.525 | G11: =E11-F11 -> 521.525 | H11: 925709 | I11: 0406018690130014 | J11: BANK MUSCAT | K11: BMUSOMRX | L11: 95187860
A12: 1357 | B12: MUSALLAM SAID ALI BAIT SAID | C12: 4488.5 | D12: 0.25 | E12: =C12*D12 -> 1122.125 | G12: =E12-F12 -> 1122.125 | H12: 1052276 | I12: 01040280323001 | J12: BANK DHOFAR | K12: BDOFOMRU | L12: 95301260
A13: 1359 | B13: MUSALLAM MUSTAHIL SAID BAIT SAID | C13: 3693.3 | D13: 0.25 | E13: =C13*D13 -> 923.325 | G13: =E13-F13 -> 923.325 | H13: 4812026 | I13: 1083517184017 | J13: NBO | K13: NBOMOMRX | L13: 96616558
A14: 1367 | B14: ALI MUSALLAM AHMED BAIT SAID | C14: 1559.1 | D14: 0.25 | E14: =C14*D14 -> 389.775 | G14: =E14-F14 -> 389.775 | H14: 6663593 | I14: 0406003006560016 | J14: BANK MUSCAT | K14: BMUSOMRX | L14: 92817702
A15: 1368 | B15: MOHAMMD SAID AHMED AL KATHIRI | C15: 1676.6 | D15: 0.25 | E15: =C15*D15 -> 419.15 | G15: =E15-F15 -> 419.15 | H15: 561902 | I15: 01040854387001 | J15: BANK DHOFAR | K15: BDOFOMRU | L15: 99499622
A16: 2098 | B16: Bakhit Musallam Ali Kashoob | C16: 556.7 | D16: 0.25 | E16: =C16*D16 -> 139.175 | G16: =E16-F16 -> 139.175 | H16: 1065899 | I16: 132857700081018 | J16: BANK MUSCAT | K16: BMUSOMRX
A17: 2529 | B17: Masoud Salim Masoud Tabook | C17: 831.1 | D17: 0.25 | E17: =C17*D17 -> 207.775 | G17: =E17-F17 -> 207.775 | H17: 6375262 | I17: 0401025220480017 | J17: BANK MUSCAT | K17: BMUSOMRX | L17: 95144359
A18: 3002 | B18: KHALID MUBARAK ALI ATQOON AL SHAHRI | C18: 1398.8 | D18: 0.25 | E18: =C18*D18 -> 349.7 | G18: =E18-F18 -> 349.7 | H18: 21220177 | I18: 0401016727580038 | J18: BANK MUSCAT | K18: BMUSOMRX | L18: 99280644
A19: 3035 | B19: TARIQ SALIM SUHAIL AL BARAMI | C19: 539.5 | D19: 0.25 | E19: =C19*D19 -> 134.875 | G19: =E19-F19 -> 134.875 | H19: 6725058 | I19: 01011059048001 | J19: BANK DHOFAR | K19: BDOFOMRU | L19: 99198121
A20: 3057 | B20: ALI AHMED MOHAMMED AL KATHIRI | C20: 2283.9 | D20: 0.25 | E20: =C20*D20 -> 570.975 | G20: =E20-F20 -> 570.975 | H20: 626819 | I20: 0397003510460014 | J20: BANK MUSCAT | K20: BMUSOMRX | L20: 99298522
A21: 3062 | B21: ALI MAHAD SILMOUN QATAN | C21: 2474.6 | D21: 0.25 | E21: =C21*D21 -> 618.65 | G21: =E21-F21 -> 618.65 | H21: 300741 | I21: 0397004203200017 | J21: BANK MUSCAT | K21: BMUSOMRX | L21: 99008320
A22: 3080 | B22: MUSALLAM BAKHIT AWADH L BARAAMI | C22: 1621.2 | D22: 0.25 | E22: =C22*D22 -> 405.3 | G22: =E22-F22 -> 405.3 | H22: 14301608 | I22: 0397003041020024 | J22: BANK MUSCAT | K22: BMUSOMRX | L22: 98122611
A23: 3086 | B23: MUSALLAM ALI MATOOQ TABOOK | C23: 836.3 | D23: 0.25 | E23: =C23*D23 -> 209.075 | G23: =E23-F23 -> 209.075 | H23: 300033 | I23: 0397003905720015 | J23: BANK MUSCAT | K23: BMUSOMRX
A24: 3132 | B24: HASHIM SALIM ALI ATIF AL YAFAI | C24: 1634 | D24: 0.25 | E24: =C24*D24 -> 408.5 | G24: =E24-F24 -> 408.5 | H24: 14606296 | I24: 0401024314310011 | J24: BANK MUSCAT | K24: BMUSOMRX | L24: 91493522
A25: 3134 | B25: HASSAN SUHAIL MAHAD QATAN | C25: 1488.5 | D25: 0.25 | E25: =C25*D25 -> 372.125 | G25: =E25-F25 -> 372.125 | H25: 2154413 | I25: 01010850952003 | J25: BANK DHOFAR | K25: BDOFOMRU | L25: 99493731
A26: 3142 | B26: MOHAMMED AHMED SAAD MASHRAH AL SHAHRI | C26: 4173.7 | D26: 0.25 | E26: =C26*D26 -> 1043.425 | G26: =E26-F26 -> 1043.425 | H26: 165497 | I26: 3129019324700 | J26: OAB | K26: OMABOMRU | L26: 99499872
A27: 3145 | B27: MOHAMMED BAKHIT MASOUD QATAN | C27: 2239.2 | D27: 0.25 | E27: =C27*D27 -> 559.8 | G27: =E27-F27 -> 559.8 | H27: 1915745 | I27: 0404002595460014 | J27: BANK MUSCAT | K27: BMUSOMRX | L27: 99489050
A28: 3147 | B28: KHALID SAID MAHAD KASHOUB | C28: 1598 | D28: 0.25 | E28: =C28*D28 -> 399.5 | G28: =E28-F28 -> 399.5 | H28: 1662414 | I28: 3129770819700 | J28: OAB | K28: OMABOMRU | L28: 99282006
A29: 3148 | B29: MUSALLAM AHMED MAHTOUQ AL ZAWAMRI | C29: 1642.3 | D29: 0.25 | E29: =C29*D29 -> 410.575 | G29: =E29-F29 -> 410.575 | H29: 19545736 | I29: 01011208343002 | J29: BANK DHOFAR | K29: BDOFOMRU
A30: 3149 | B30: ALI SAID ALI AL ZAWAMRI | C30: 1410.6 | D30: 0.25 | E30: =C30*D30 -> 352.65 | G30: =E30-F30 -> 352.65 | H30: 4941095 | I30: 1104036354300 | J30: Ahli Bank | K30: AUBOOMRU | L30: 93500864
A31: 3150 | B31: Awad Ahmed Said Alzwamri | C31: 488.3 | D31: 0.25 | E31: =C31*D31 -> 122.075 | G31: =E31-F31 -> 122.075 | H31: 18940347 | I31: 0401017288790038 | J31: BANK MUSCAT | K31: BMUSOMRX | L31: 98905289
A32: 3152 | B32: BAKHIT SALIM MAHAD QATAN | C32: 3040.6 | D32: 0.25 | E32: =C32*D32 -> 760.15 | F32: =0.975+350.4 -> 351.375 | G32: =E32-F32 -> 408.775 | H32: 941993 | I32: 01042574515001 | J32: BANK DHOFAR | K32: BDOFOMRU | L32: 99086500 | M32: 45727 | N32: .975-11-2025
A33: 3153 | B33: ALI MAHAD SAID QATAN | C33: 2433.6 | D33: 0.25 | E33: =C33*D33 -> 608.4 | G33: =E33-F33 -> 608.4 | H33: 6989479 | I33: 0397003672070015 | J33: BANK MUSCAT | K33: BMUSOMRX | L33: 99699500
A34: 3155 | B34: SAID BAKHIT MAHAD QATAN | C34: 540.8 | D34: 0.25 | E34: =C34*D34 -> 135.2 | G34: =E34-F34 -> 135.2 | H34: 19188794 | I34: 0402003042750013 | J34: BANK MUSCAT | K34: BMUSOMRX | L34: 93215515
A35: 3158 | B35: AHMED OBAIDAN AHMED AL KATHIRI | C35: 3186.1 | D35: 0.25 | E35: =C35*D35 -> 796.525 | G35: =E35-F35 -> 796.525 | H35: 596869 | I35: 0401049081340015 | J35: BANK MUSCAT | K35: BMUSOMRX | L35: 99694218
A36: 3159 | B36: AHMED BAKHIT SALEM AL BARAMI | C36: 548.8 | D36: 0.25 | E36: =C36*D36 -> 137.2 | G36: =E36-F36 -> 137.2 | H36: 1297478 | I36: 0397003703480012 | J36: BANK MUSCAT | K36: BMUSOMRX | L36: 99497177
A37: 3160 | B37: NAIF MUBARAK BAKHIT AL BARAAMI | C37: 1680.7 | D37: 0.25 | E37: =C37*D37 -> 420.175 | G37: =E37-F37 -> 420.175 | H37: 2837163 | I37: 00510031862001 | J37: Bank Nizwa | K37: BNZWOMRX | L37: 99497455
A38: 3162 | B38: MOHAMMED SAID FARAJ AL KATHIRI | C38: 4995 | D38: 0.25 | E38: =C38*D38 -> 1248.75 | G38: =E38-F38 -> 1248.75 | H38: 7017227 | I38: 01010940071001 | J38: BANK DHOFAR | K38: BDOFOMRU | L38: 99523400
A39: 3164 | B39: ALI MUSALLLAM HASSAN BAITSAID | C39: 2057.1 | D39: 0.25 | E39: =C39*D39 -> 514.275 | G39: =E39-F39 -> 514.275 | H39: 7466062 | I39: 01646038607001 | J39: Maisarah | K39: BDOFOMRUMIB | L39: 91135005
A40: 3165 | B40: KHALID MOHAMMED MASAAOD AGGHRIB AL SHAHRI | C40: 497.9 | D40: 0.25 | E40: =C40*D40 -> 124.475 | G40: =E40-F40 -> 124.475 | H40: 19029628 | I40: 01011251497002 | J40: BANK DHOFAR | K40: BDOFOMRU | L40: 96055446
A41: 3169 | B41: MOHAMMED ALI SAID AL ZAWAMRY | C41: 1983.2 | D41: 0.25 | E41: =C41*D41 -> 495.8 | G41: =E41-F41 -> 495.8 | H41: 3068756 | I41: 01012573317001 | J41: BANK DHOFAR | K41: BDOFOMRU | L41: 99691806
A42: 3171 | B42: HATAM AWADH SAID QATAN | C42: 915.4 | D42: 0.25 | E42: =C42*D42 -> 228.85 | G42: =E42-F42 -> 228.85 | H42: 7239057 | I42: 3109607126500 | J42: OAB | K42: OMABOMRU | L42: 95880860
A43: 3172 | B43: Fatima Suleimon Salim ALBaramiyah | C43: 1587.6 | D43: 0.25 | E43: =C43*D43 -> 396.9 | G43: =E43-F43 -> 396.9 | H43: 5276984 | I43: 0439046831000027 | J43: BANK MUSCAT | K43: BMUSOMRX | L43: 99188860
A44: 3173 | B44: MUSALLAM AHMED SAAD AL BARAAMI | C44: 658.1 | D44: 0.25 | E44: =C44*D44 -> 164.525 | G44: =E44-F44 -> 164.525 | H44: 6825655 | I44: 0397004380200011 | J44: BANK MUSCAT | K44: BMUSOMRX | L44: 98957747
A45: 3174 | B45: AHMED MUSALLAM SAID QATAN | C45: 1180 | D45: 0.25 | E45: =C45*D45 -> 295 | G45: =E45-F45 -> 295 | H45: 7547492 | I45: 0401002379960017 | J45: BANK MUSCAT | K45: BMUSOMRX | L45: 91790502
A46: 3175 | B46: SAID AHMED NASIB AL BARAAMI | C46: 586.2 | D46: 0.25 | E46: =C46*D46 -> 146.55 | G46: =E46-F46 -> 146.55 | H46: 7325076 | I46: 1006794849001 | J46: NBO | K46: NBOMOMRX | L46: 92890700
A47: 3176 | B47: KHAYAR ALI SAID AL BARAAMI | C47: 355.7 | D47: 0.25 | E47: =C47*D47 -> 88.925 | G47: =E47-F47 -> 88.925 | H47: 12178145 | I47: 0406015163810016 | J47: BANK MUSCAT | K47: BMUSOMRX | L47: 93348565
... A62: 3324 | B62: BAKHIT AWADH BAKHIT AL BARAAMI | C62: 1640.4 | D62: 0.25 | E62: =C62*D62 -> 410.1 | G62: =E62-F62 -> 410.1 | H62: 207402 | I62: 0401057742590016 | J62: BANK MUSCAT | K62: BMUSOMRX | L62: 99487533
A63: 3330 | B63: Salim Ahmed Aubad Al kathiri | C63: 1949.1 | D63: 0.25 | E63: =C63*D63 -> 487.275 | G63: =E63-F63 -> 487.275 | H63: 6375079 | I63: 0397062111930011 | J63: Bank Muscat | K63: BMUSOMRX
A64: 3333 | B64: Mahad Salim Zaed Bait Said | C64: 1685.6 | D64: 0.25 | E64: =C64*D64 -> 421.4 | G64: =E64-F64 -> 421.4 | H64: 757601 | I64: 1023113274001 | J64: NBO | K64: NBOMOMRX
A65: 3339 | B65: Khalid Ahmed Salim Amer Jid Almahri | C65: 515.8 | D65: 0.25 | E65: =C65*D65 -> 128.95 | G65: =E65-F65 -> 128.95 | H65: 12415718 | I65: 0401050718800013 | J65: BANK MUSCAT | K65: BMUSOMRX
A66: 3341 | B66: Mahad Ahmed Alkathiri | C66: 581.1 | D66: 0.25 | E66: =C66*D66 -> 145.275 | G66: =E66-F66 -> 145.275 | H66: 702161 | I66: 3109593036500 | J66: OAB | K66: OMABOMRU | L66: 99290644
A67: 3500 | B67: Salim Mohammed Ahmed Al Kathiri | D67: 0.25 | E67: =C67*D67 -> 0 | G67: =E67-F67 -> 0 | H67: 13525845 | I67: 10600259604017 | J67: NBO | K67: NBOMOMRX | L67: 93985671
A68: 3501 | B68: Said Masoud Ahmed Al kathiri | C68: 1531.9 | D68: 0.25 | E68: =C68*D68 -> 382.975 | G68: =E68-F68 -> 382.975 | H68: 13525794 | I68: 0402003356710024 | J68: BANK MUSCAT | K68: BMUSOMRX | L68: 92868004
A69: 3502 | B69: Ahmed Bakhit Ahmed Al Kathiri | C69: 1652.8 | D69: 0.25 | E69: =C69*D69 -> 413.2 | G69: =E69-F69 -> 413.2 | H69: 22522336 | I69: 01011021065002 | J69: BANK DHOFAR | K69: BDOFOMRU
A70: 3503 | B70: Imad Bakhit Salim Bakhit Qatan | C70: 545.4 | D70: 0.25 | E70: =C70*D70 -> 136.35 | G70: =E70-F70 -> 136.35 | H70: 9212492 | I70: 0401028325700011 | J70: BANK MUSCAT | K70: BMUSOMRX | L70: 98080144
A71: 3504 | B71: Ali Salem Amer Al Kathiri | C71: 368.5 | D71: 0.25 | E71: =C71*D71 -> 92.125 | G71: =E71-F71 -> 92.125 | H71: 939641 | I71: 0406003375130017 | J71: BANK MUSCAT | K71: BMUSOMRX | L71: 99588609
A72: 3506 | B72: Ahmed Masoud Salim Al Kathiri | C72: 490.6 | D72: 0.25 | E72: =C72*D72 -> 122.65 | G72: =E72-F72 -> 122.65 | H72: 13307752 | I72: 0397048001530015 | J72: BANK MUSCAT | K72: BMUSOMRX | L72: 99294425
A73: 3507 | B73: Bakhit Suhail Ahmed Qatan | C73: 958.8 | D73: 0.25 | E73: =C73*D73 -> 239.7 | G73: =E73-F73 -> 239.7 | H73: 1184669 | I73: 01040281423001 | J73: BANK DHOFAR | K73: BDOFOMRU | L73: 99291928
A74: 3508 | B74: Said Ali Said Al Zawamri | C74: 1045.1 | D74: 0.25 | E74: =C74*D74 -> 261.275 | G74: =E74-F74 -> 261.275 | H74: 2567166 | I74: 0439004225500028 | J74: BANK MUSCAT | K74: BMUSOMRX | L74: 92570156
A75: 3509 | B75: Asama Mohammed Ahmed Masharah Al Shahri | C75: 522.6 | D75: 0.25 | E75: =C75*D75 -> 130.65 | G75: =E75-F75 -> 130.65 | H75: 22760088 | I75: 3129152535700 | J75: OAB | K75: OMABOMRU | L75: 91476443
A76: 3510 | B76: Amer Ali Ahmed Al kathiri | C76: 1099.3 | D76: 0.25 | E76: =C76*D76 -> 274.825 | G76: =E76-F76 -> 274.825 | H76: 6920351 | I76: 0397003252950036 | J76: BANK MUSCAT | K76: BMUSOMRX | L76: 98933077
A77: 3511 | B77: Said Ali Said Qatan | C77: 1661.3 | D77: 0.25 | E77: =C77*D77 -> 415.325 | G77: =E77-F77 -> 415.325 | H77: 2640016 | I77: 0501036199001 | J77: Ahli Islamic | K77: AUBOOMRUALH | L77: 92953388
A78: 3512 | B78: Ahmed Abdul Rahim Ali Al Kathiri | C78: 659.8 | D78: 0.25 | E78: =C78*D78 -> 164.95 | G78: =E78-F78 -> 164.95 | H78: 5514631 | I78: 01041149485001 | J78: BANK DHOFAR | K78: BDOFOMRU
A79: 3513 | B79: Khair Salim Faraj Al Kathiri | C79: 2726 | D79: 0.25 | E79: =C79*D79 -> 681.5 | G79: =E79-F79 -> 681.5 | H79: 7047376 | I79: 01013042263001 | J79: BANK DHOFAR | K79: BDOFOMRU | L79: 90106022
A80: 3514 | B80: Said Salim Faraj Al Kathiri | C80: 1575.7 | D80: 0.25 | E80: =C80*D80 -> 393.925 | G80: =E80-F80 -> 393.925 | H80: 440083 | I80: 0397003539170015 | J80: Bank Muscat | K80: BMUSOMRX | L80: 92363355
A81: 3515 | B81: Ali Ajaham Ali Bait said | C81: 596.5 | D81: 0.25 | E81: =C81*D81 -> 149.125 | G81: =E81-F81 -> 149.125 | H81: 6645198 | I81: 01011180247001 | J81: BANK DHOFAR | K81: BDOFOMRU | L81: 94411217
A82: 3516 | B82: Musallam Hassan Ali Bait Muhammed Bin Ahmed | C82: 1594.3 | D82: 0.25 | E82: =C82*D82 -> 398.575 | G82: =E82-F82 -> 398.575 | H82: 1165877 | I82: 01010127958001 | J82: BANK DHOFAR | K82: BDOFOMRU
A83: 3517 | B83: Mohammed Salim Faraj Al Kathiri | C83: 1377.2 | D83: 0.25 | E83: =C83*D83 -> 344.3 | G83: =E83-F83 -> 344.3 | H83: 7047081 | I83: 01010401370002 | J83: BANK DHOFAR | K83: BDOFOMRU
A84: 3518 | B84: Ali Ahmed Ali Bait Said | C84: 607.8 | D84: 0.25 | E84: =C84*D84 -> 151.95 | G84: =E84-F84 -> 151.95 | H84: 20386956 | I84: 0396064567750014 | J84: BANK MUSCAT | K84: BMUSOMRX
A85: 3519 | B85: Masoud Salim Faraj Al Kathiri | C85: 1017.5 | D85: 0.25 | E85: =C85*D85 -> 254.375 | G85: =E85-F85 -> 254.375 | H85: 7047221 | I85: 01011028414003 | J85: BANK DHOFAR | K85: BDOFOMRU
A86: 3520 | B86: Musallam Mahad Suhail Al Barami | C86: 781.1 | D86: 0.25 | E86: =C86*D86 -> 195.275 | G86: =E86-F86 -> 195.275 | H86: 5665362 | I86: 01011072899001 | J86: BANK DHOFAR | K86: BDOFOMRU
A87: 3521 | B87: Omar Said Awadh Bait Said | C87: 3750.3 | D87: 0.25 | E87: =C87*D87 -> 937.575 | G87: =E87-F87 -> 937.575 | H87: 7064553 | I87: 0396019442490023 | J87: BANK MUSCAT | K87: BMUSOMRX
A88: 3522 | B88: Said Ahmed Ali Qatan | C88: 351.6 | D88: 0.25 | E88: =C88*D88 -> 87.9 | G88: =E88-F88 -> 87.9 | H88: 11365191 | I88: 01010121273002 | J88: BANK DHOFAR | K88: BDOFOMRU
A89: 3523 | B89: Said Salim Amer Qatan | C89: 541.3 | D89: 0.25 | E89: =C89*D89 -> 135.325 | G89: =E89-F89 -> 135.325 | H89: 9399193 | I89: 010010137751 | J89: SOHAR | L89: 99298810
A90: 3524 | B90: Bakhit Ali Ahmed Amer Jeed | C90: 527.9 | D90: 0.25 | E90: =C90*D90 -> 131.975 | G90: =E90-F90 -> 131.975 | H90: 1876659 | I90: 0397012592830018 | J90: BANK MUSCAT | L90: 94800053
A91: 3525 | B91: salim Masoud Said AL-Kathiri | C91: 394.3 | D91: 0.25 | E91: =C91*D91 -> 98.575 | G91: =E91-F91 -> 98.575 | H91: 1862864 | I91: 0396057144960032 | J91: BANK MUSCAT | L91: 91418828
A92: 3526 | B92: Masoud Ali Daid Qatan | C92: 445.2 | D92: 0.25 | E92: =C92*D92 -> 111.3 | G92: =E92-F92 -> 111.3 | H92: 5349102 | I92: 1502132783300 | J92: AHLI BANK | L92: 93636606
A93: 3527 | B93: Bakhit Suhail Salim Al Barami | C93: 531.4 | D93: 0.25 | E93: =C93*D93 -> 132.85 | G93: =E93-F93 -> 132.85 | H93: 6372265 | I93: 039700370833019 | J93: BANK MUSCAT | L93: 92488144
A94: 3528 | B94: Abdullah Salim Suhail Ahmed Al Kathiri | C94: 519.4 | D94: 0.25 | E94: =C94*D94 -> 129.85 | G94: =E94-F94 -> 129.85 | H94: 28605923 | I94: 0439079294590015 | J94: BANK MUSCAT | L94: 93233289
A95: 3529 | B95: Mohammed Suhail Said Qatan | C95: 539.4 | D95: 0.25 | E95: =C95*D95 -> 134.85 | G95: =E95-F95 -> 134.85 | H95: 4702777 | I95: 0319005149020017 | J95: BANK MUSCAT | L95: 92444040
A96: 3530 | B96: Mohammed Aslm Mohammed al Zawamri | C96: 480.4 | D96: 0.25 | E96: =C96*D96 -> 120.1 | G96: =E96-F96 -> 120.1 | H96: 1163821 | I96: 01010850775001 | J96: BANK DHOFAR | L96: 99496955
A97: 3531 | B97: Mohammed Masoud Said khdhran Alkathiri | C97: 540 | D97: 0.25 | E97: =C97*D97 -> 135 | G97: =E97-F97 -> 135 | H97: 23661829 | I97: 0397059602380012 | J97: BANK MUSCAT | L97: 92379624
A98: 3532 | B98: Amer Salim Mohsin Ajham AlKathiri | C98: 533.9 | D98: 0.25 | E98: =C98*D98 -> 133.475 | G98: =E98-F98 -> 133.475 | H98: 26301042 | I98: 01011346179002 | J98: BANK DHOFAR | L98: 93968161
A99: 3533 | B99: Ali Musallam Issa Al-Baraami | C99: 530.4 | D99: 0.25 | E99: =C99*D99 -> 132.6 | G99: =E99-F99 -> 132.6 | H99: 22979942 | I99: 0426048893580018 | J99: BANK MUSCAT | L99: 99837335
A100: 3534 | B100: Musallam Hassan Abdullah Khdhran AlKathiri | C100: 536.5 | D100: 0.25 | E100: =C100*D100 -> 134.125 | G100: =E100-F100 -> 134.125 | H100: 14897254 | I100: 0397003341450012 | J100: BANK MUSCAT | L100: 92226297
... A124: 3558 | B124: Said Abdullah Said Al Kathiri | C124: 36.8 | D124: 0.25 | E124: =C124*D124 -> 9.2 | G124: =E124-F124 -> 9.2 | H124: 790841 | I124: 01041462519001 | J124: BANK DHOFAR | L124: 99679031
A125: 3559 | B125: Ahmed Mohammed Abdullah AlKathiri | D125: 0.25 | E125: =C125*D125 -> 0 | G125: =E125-F125 -> 0 | H125: 14330314 | I125: 10060245826001 | J125: NBO | L125: 98044999
